Workbook

Sheet How To Use
A1: Claims Template - ADMINISTRATIVE CONTROL AUTHORITY (ACA) (Walk In)
A3: Monthly steps
A4: 1. Open the 'Per Line' tab. Delete the old data in the BLUE columns only (row 2 down). Never delete the green or grey columns.
A5: 2. Paste the new month's data as VALUES starting at A2, into the blue columns: A-E, G-T, Y (same order as the system export).
A6: 3. Green columns (F, U, V, W, X) and the grey helper columns (Z-AD) calculate automatically - do not paste over them.
A7: 4. 'Per Invoice' fills itself from 'Per Line' (one row per POS Reference, split into IMP / Local). No pivot table, no refresh.
A8: 5. The ONLY manual column in 'Per Invoice' is column A 'Invoice' (blue): type it yourself. Everything else is formula.
A9: 6. Open 'Settings' and check STATUS says OK (Per Line totals = Per Invoice totals).
A11: Colour legend
A12: Blue header = typed/pasted by you (raw data, and 'Invoice' in Per Invoice). Green header = formula (do not paste over). Grey header = helper formula (do not touch). Yellow cell (Settings) = editable rate.
A14: Calculation rules (taken from the September 2026 sheet)
A15: Co val = Co Payment % x Subtotal / 100. Discount = Total x Rebates (Rebates is a fraction here, e.g. 0.14). Subtotal = Total - Discount. Net = Subtotal - Co val. (Total = 'Total Delivered')
... A20: Capacity: up to 500 lines and 200 invoices per month. A line with an empty POS Reference is ignored.

Sheet Settings
B1: Company settings & checks
B3: Insurance Company | C3: ADMINISTRATIVE CONTROL AUTHORITY (ACA) | D3: Informational only
B4: Corporate | C4: - | D4: Informational only
B5: Sheet type | C5: Walk In | D5: Informational only
B6: Local products rebate % | C6: 0.12 | D6: Source: Sep sheet (Rebates = 0.12 on Local lines).
B7: Imported (IMP) products rebate % | C7: 0.05 | D7: Source: Sep sheet (Rebates = 0.05 on non-local lines; 0 on special lines).
B9: Month totals / reconciliation
B10: Lines loaded | C10: =COUNTA('Per Line'!$A$2:$A$501)
B11: Invoices (unique Order #) | C11: =MAX('Per Line'!$AA$2:$AA$501)
B12: Invoices shown in Per Invoice | C12: =SUMPRODUCT(--('Per Invoice'!$B$2:$B$201<>""))
B13: Grand Total - Per Line (Product Total) | C13: =SUM('Per Line'!$M$2:$M$501)
B14: Grand Total - Per Invoice | C14: =SUM('Per Invoice'!$S$2:$S$201)
B15: Discount - Per Line | C15: =SUM('Per Line'!$V$2:$V$501)
B16: Discount - Per Invoice | C16: =SUM('Per Invoice'!$Q$2:$Q$201)
B17: Co val - Per Line | C17: =SUM('Per Line'!$F$2:$F$501)
B18: Co val - Per Invoice | C18: =SUM('Per Invoice'!$G$2:$G$201)
B19: Net - Per Line | C19: =SUM('Per Line'!$X$2:$X$501)
B20: Net - Per Invoice | C20: =SUM('Per Invoice'!$T$2:$T$201)
B21: Max Limit adjustment (Co val, Per Invoice only) | C21: 0 | D21: This company's Per Invoice has no Max Limit rule.
B23: STATUS | C23: =IF(C10=0,"No data loaded",IF(COUNTA('Per Line'!$A:$A)-1>500,"TOO MANY LINES - extend template",IF(C11>200,"TOO MANY INVOICES - extend template",IF(AND(ROUND(C13-C14,2)=0,ROUND(C15-C16,2)=0,ROUND(C17+C21-C18,2)=0,ROUND(C19-C21-C20,2)=0,C11=C12),"OK","CHECK - Per Line and Per Invoice do not match")))) | D23: Must say OK after you paste the month data.

Sheet Per Line
A1: Pos Reference | B1: Insurance Company | C1: Name | D1: Card Number | E1: Co Payment % | F1: Co val | G1: Heisenberg id | H1: Product | I1: Original Quantity | J1: Original Price | K1: Delivered Qty | L1: Delivered Price | M1: Total Delivered | N1: Order Amount Total | O1: Payment Amount | P1: Payment Type | Q1: Session | R1: Create Date | S1: Order Reference | T1: Product Template - Product Tmpl → Is Local | U1: Rebates | V1: Discount | W1: Subtotal | X1: Net | Y1: Special Rebates? | Z1: Order 1st Row (helper) | AA1: Invoice # (helper) | AB1: Is Local (helper) | AC1: Is Special (helper) | AD1: Sort Key (helper)
F2: =IF($A2="","",E2*W2/100) | U2: =IF($A2="","",IF($AC2=1,0,IF($AB2=1,Settings!$C$6,Settings!$C$7))*1) | V2: =IF($A2="","",U2*M2) | W2: =IF($A2="","",M2-V2) | X2: =IF($A2="","",W2-F2) | Z2: =IF($A2="","",IF(COUNTIF($A$2:$A2,$A2)=1,1,0)) | AA2: =IF($Z2=1,SUMPRODUCT(--($AD$2:$AD$501<$AD2))+1,"") | AB2: =IF($A2="","",IF(OR($T2=TRUE(),$T2="TRUE"),1,0)) | AC2: =IF($A2="","",IF($Y2="Yes",1,0)) | AD2: =IF($Z2=1,IFERROR(IF(VALUE($A2)<100000000,VALUE($A2),1000000000),IFERROR(IF(VALUE(MID($A2,2,20))<100000000,VALUE(MID($A2,2,20)),1000000000),1000000000))+ROW()/100000,"")
F3: =IF($A3="","",E3*W3/100) | U3: =IF($A3="","",IF($AC3=1,0,IF($AB3=1,Settings!$C$6,Settings!$C$7))*1) | V3: =IF($A3="","",U3*M3) | W3: =IF($A3="","",M3-V3) | X3: =IF($A3="","",W3-F3) | Z3: =IF($A3="","",IF(COUNTIF($A$2:$A3,$A3)=1,1,0)) | AA3: =IF($Z3=1,SUMPRODUCT(--($AD$2:$AD$501<$AD3))+1,"") | AB3: =IF($A3="","",IF(OR($T3=TRUE(),$T3="TRUE"),1,0)) | AC3: =IF($A3="","",IF($Y3="Yes",1,0)) | AD3: =IF($Z3=1,IFERROR(IF(VALUE($A3)<100000000,VALUE($A3),1000000000),IFERROR(IF(VALUE(MID($A3,2,20))<100000000,VALUE(MID($A3,2,20)),1000000000),1000000000))+ROW()/100000,"")
F4: =IF($A4="","",E4*W4/100) | U4: =IF($A4="","",IF($AC4=1,0,IF($AB4=1,Settings!$C$6,Settings!$C$7))*1) | V4: =IF($A4="","",U4*M4) | W4: =IF($A4="","",M4-V4) | X4: =IF($A4="","",W4-F4) | Z4: =IF($A4="","",IF(COUNTIF($A$2:$A4,$A4)=1,1,0)) | AA4: =IF($Z4=1,SUMPRODUCT(--($AD$2:$AD$501<$AD4))+1,"") | AB4: =IF($A4="","",IF(OR($T4=TRUE(),$T4="TRUE"),1,0)) | AC4: =IF($A4="","",IF($Y4="Yes",1,0)) | AD4: =IF($Z4=1,IFERROR(IF(VALUE($A4)<100000000,VALUE($A4),1000000000),IFERROR(IF(VALUE(MID($A4,2,20))<100000000,VALUE(MID($A4,2,20)),1000000000),1000000000))+ROW()/100000,"")
F5: =IF($A5="","",E5*W5/100) | U5: =IF($A5="","",IF($AC5=1,0,IF($AB5=1,Settings!$C$6,Settings!$C$7))*1) | V5: =IF($A5="","",U5*M5) | W5: =IF($A5="","",M5-V5) | X5: =IF($A5="","",W5-F5) | Z5: =IF($A5="","",IF(COUNTIF($A$2:$A5,$A5)=1,1,0)) | AA5: =IF($Z5=1,SUMPRODUCT(--($AD$2:$AD$501<$AD5))+1,"") | AB5: =IF($A5="","",IF(OR($T5=TRUE(),$T5="TRUE"),1,0)) | AC5: =IF($A5="","",IF($Y5="Yes",1,0)) | AD5: =IF($Z5=1,IFERROR(IF(VALUE($A5)<100000000,VALUE($A5),1000000000),IFERROR(IF(VALUE(MID($A5,2,20))<100000000,VALUE(MID($A5,2,20)),1000000000),1000000000))+ROW()/100000,"")
F6: =IF($A6="","",E6*W6/100) | U6: =IF($A6="","",IF($AC6=1,0,IF($AB6=1,Settings!$C$6,Settings!$C$7))*1) | V6: =IF($A6="","",U6*M6) | W6: =IF($A6="","",M6-V6) | X6: =IF($A6="","",W6-F6) | Z6: =IF($A6="","",IF(COUNTIF($A$2:$A6,$A6)=1,1,0)) | AA6: =IF($Z6=1,SUMPRODUCT(--($AD$2:$AD$501<$AD6))+1,"") | AB6: =IF($A6="","",IF(OR($T6=TRUE(),$T6="TRUE"),1,0)) | AC6: =IF($A6="","",IF($Y6="Yes",1,0)) | AD6: =IF($Z6=1,IFERROR(IF(VALUE($A6)<100000000,VALUE($A6),1000000000),IFERROR(IF(VALUE(MID($A6,2,20))<100000000,VALUE(MID($A6,2,20)),1000000000),1000000000))+ROW()/100000,"")
F7: =IF($A7="","",E7*W7/100) | U7: =IF($A7="","",IF($AC7=1,0,IF($AB7=1,Settings!$C$6,Settings!$C$7))*1) | V7: =IF($A7="","",U7*M7) | W7: =IF($A7="","",M7-V7) | X7: =IF($A7="","",W7-F7) | Z7: =IF($A7="","",IF(COUNTIF($A$2:$A7,$A7)=1,1,0)) | AA7: =IF($Z7=1,SUMPRODUCT(--($AD$2:$AD$501<$AD7))+1,"") | AB7: =IF($A7="","",IF(OR($T7=TRUE(),$T7="TRUE"),1,0)) | AC7: =IF($A7="","",IF($Y7="Yes",1,0)) | AD7: =IF($Z7=1,IFERROR(IF(VALUE($A7)<100000000,VALUE($A7),1000000000),IFERROR(IF(VALUE(MID($A7,2,20))<100000000,VALUE(MID($A7,2,20)),1000000000),1000000000))+ROW()/100000,"")
F8: =IF($A8="","",E8*W8/100) | U8: =IF($A8="","",IF($AC8=1,0,IF($AB8=1,Settings!$C$6,Settings!$C$7))*1) | V8: =IF($A8="","",U8*M8) | W8: =IF($A8="","",M8-V8) | X8: =IF($A8="","",W8-F8) | Z8: =IF($A8="","",IF(COUNTIF($A$2:$A8,$A8)=1,1,0)) | AA8: =IF($Z8=1,SUMPRODUCT(--($AD$2:$AD$501<$AD8))+1,"") | AB8: =IF($A8="","",IF(OR($T8=TRUE(),$T8="TRUE"),1,0)) | AC8: =IF($A8="","",IF($Y8="Yes",1,0)) | AD8: =IF($Z8=1,IFERROR(IF(VALUE($A8)<100000000,VALUE($A8),1000000000),IFERROR(IF(VALUE(MID($A8,2,20))<100000000,VALUE(MID($A8,2,20)),1000000000),1000000000))+ROW()/100000,"")
F9: =IF($A9="","",E9*W9/100) | U9: =IF($A9="","",IF($AC9=1,0,IF($AB9=1,Settings!$C$6,Settings!$C$7))*1) | V9: =IF($A9="","",U9*M9) | W9: =IF($A9="","",M9-V9) | X9: =IF($A9="","",W9-F9) | Z9: =IF($A9="","",IF(COUNTIF($A$2:$A9,$A9)=1,1,0)) | AA9: =IF($Z9=1,SUMPRODUCT(--($AD$2:$AD$501<$AD9))+1,"") | AB9: =IF($A9="","",IF(OR($T9=TRUE(),$T9="TRUE"),1,0)) | AC9: =IF($A9="","",IF($Y9="Yes",1,0)) | AD9: =IF($Z9=1,IFERROR(IF(VALUE($A9)<100000000,VALUE($A9),1000000000),IFERROR(IF(VALUE(MID($A9,2,20))<100000000,VALUE(MID($A9,2,20)),1000000000),1000000000))+ROW()/100000,"")
F10: =IF($A10="","",E10*W10/100) | U10: =IF($A10="","",IF($AC10=1,0,IF($AB10=1,Settings!$C$6,Settings!$C$7))*1) | V10: =IF($A10="","",U10*M10) | W10: =IF($A10="","",M10-V10) | X10: =IF($A10="","",W10-F10) | Z10: =IF($A10="","",IF(COUNTIF($A$2:$A10,$A10)=1,1,0)) | AA10: =IF($Z10=1,SUMPRODUCT(--($AD$2:$AD$501<$AD10))+1,"") | AB10: =IF($A10="","",IF(OR($T10=TRUE(),$T10="TRUE"),1,0)) | AC10: =IF($A10="","",IF($Y10="Yes",1,0)) | AD10: =IF($Z10=1,IFERROR(IF(VALUE($A10)<100000000,VALUE($A10),1000000000),IFERROR(IF(VALUE(MID($A10,2,20))<100000000,VALUE(MID($A10,2,20)),1000000000),1000000000))+ROW()/100000,"")
F11: =IF($A11="","",E11*W11/100) | U11: =IF($A11="","",IF($AC11=1,0,IF($AB11=1,Settings!$C$6,Settings!$C$7))*1) | V11: =IF($A11="","",U11*M11) | W11: =IF($A11="","",M11-V11) | X11: =IF($A11="","",W11-F11) | Z11: =IF($A11="","",IF(COUNTIF($A$2:$A11,$A11)=1,1,0)) | AA11: =IF($Z11=1,SUMPRODUCT(--($AD$2:$AD$501<$AD11))+1,"") | AB11: =IF($A11="","",IF(OR($T11=TRUE(),$T11="TRUE"),1,0)) | AC11: =IF($A11="","",IF($Y11="Yes",1,0)) | AD11: =IF($Z11=1,IFERROR(IF(VALUE($A11)<100000000,VALUE($A11),1000000000),IFERROR(IF(VALUE(MID($A11,2,20))<100000000,VALUE(MID($A11,2,20)),1000000000),1000000000))+ROW()/100000,"")
F12: =IF($A12="","",E12*W12/100) | U12: =IF($A12="","",IF($AC12=1,0,IF($AB12=1,Settings!$C$6,Settings!$C$7))*1) | V12: =IF($A12="","",U12*M12) | W12: =IF($A12="","",M12-V12) | X12: =IF($A12="","",W12-F12) | Z12: =IF($A12="","",IF(COUNTIF($A$2:$A12,$A12)=1,1,0)) | AA12: =IF($Z12=1,SUMPRODUCT(--($AD$2:$AD$501<$AD12))+1,"") | AB12: =IF($A12="","",IF(OR($T12=TRUE(),$T12="TRUE"),1,0)) | AC12: =IF($A12="","",IF($Y12="Yes",1,0)) | AD12: =IF($Z12=1,IFERROR(IF(VALUE($A12)<100000000,VALUE($A12),1000000000),IFERROR(IF(VALUE(MID($A12,2,20))<100000000,VALUE(MID($A12,2,20)),1000000000),1000000000))+ROW()/100000,"")
F13: =IF($A13="","",E13*W13/100) | U13: =IF($A13="","",IF($AC13=1,0,IF($AB13=1,Settings!$C$6,Settings!$C$7))*1) | V13: =IF($A13="","",U13*M13) | W13: =IF($A13="","",M13-V13) | X13: =IF($A13="","",W13-F13) | Z13: =IF($A13="","",IF(COUNTIF($A$2:$A13,$A13)=1,1,0)) | AA13: =IF($Z13=1,SUMPRODUCT(--($AD$2:$AD$501<$AD13))+1,"") | AB13: =IF($A13="","",IF(OR($T13=TRUE(),$T13="TRUE"),1,0)) | AC13: =IF($A13="","",IF($Y13="Yes",1,0)) | AD13: =IF($Z13=1,IFERROR(IF(VALUE($A13)<100000000,VALUE($A13),1000000000),IFERROR(IF(VALUE(MID($A13,2,20))<100000000,VALUE(MID($A13,2,20)),1000000000),1000000000))+ROW()/100000,"")
... F501: =IF($A501="","",E501*W501/100) | U501: =IF($A501="","",IF($AC501=1,0,IF($AB501=1,Settings!$C$6,Settings!$C$7))*1) | V501: =IF($A501="","",U501*M501) | W501: =IF($A501="","",M501-V501) | X501: =IF($A501="","",W501-F501) | Z501: =IF($A501="","",IF(COUNTIF($A$2:$A501,$A501)=1,1,0)) | AA501: =IF($Z501=1,SUMPRODUCT(--($AD$2:$AD$501<$AD501))+1,"") | AB501: =IF($A501="","",IF(OR($T501=TRUE(),$T501="TRUE"),1,0)) | AC501: =IF($A501="","",IF($Y501="Yes",1,0)) | AD501: =IF($Z501=1,IFERROR(IF(VALUE($A501)<100000000,VALUE($A501),1000000000),IFERROR(IF(VALUE(MID($A501,2,20))<100000000,VALUE(MID($A501,2,20)),1000000000),1000000000))+ROW()/100000,"")

Sheet Per Invoice
A1: Invoice | B1: Pos Reference | C1: Insurance Company | D1: Name | E1: Card Number | F1: Co Payment % | G1: Co val | H1: Session | I1: Create Date | J1: Special Rebate | K1: IMP % | L1: IMP | M1: IMP VAL | N1: LOCAL % | O1: LOCAL | P1: LOCAL VAL | Q1: TOTAL VAL | R1: SUBTOTAL | S1: Grand Total | T1: NET | U1: Src Row (helper)
B2: =IF($U2="","",INDEX('Per Line'!$A$2:$A$501,$U2)&"") | C2: =IF($U2="","",INDEX('Per Line'!$B$2:$B$501,$U2)&"") | D2: =IF($U2="","",INDEX('Per Line'!$C$2:$C$501,$U2)&"") | E2: =IF($U2="","",INDEX('Per Line'!$D$2:$D$501,$U2)&"") | F2: =IF($U2="","",INDEX('Per Line'!$E$2:$E$501,$U2)) | G2: =IF($U2="","",F2*R2/100) | H2: =IF($U2="","",INDEX('Per Line'!$Q$2:$Q$501,$U2)&"") | I2: =IF($U2="","",INDEX('Per Line'!$R$2:$R$501,$U2)) | J2: =IF($U2="","",SUMIFS('Per Line'!$M$2:$M$501,'Per Line'!$A$2:$A$501,$B2,'Per Line'!$AC$2:$AC$501,1)) | K2: =IF($U2="","",Settings!$C$7) | L2: =IF($U2="","",SUMIFS('Per Line'!$M$2:$M$501,'Per Line'!$A$2:$A$501,$B2,'Per Line'!$AB$2:$AB$501,0,'Per Line'!$AC$2:$AC$501,0)) | M2: =IF($U2="","",L2*K2) | N2: =IF($U2="","",Settings!$C$6) | O2: =IF($U2="","",SUMIFS('Per Line'!$M$2:$M$501,'Per Line'!$A$2:$A$501,$B2,'Per Line'!$AB$2:$AB$501,1,'Per Line'!$AC$2:$AC$501,0)) | P2: =IF($U2="","",O2*N2) | Q2: =IF($U2="","",P2+M2) | R2: =IF($U2="","",S2-Q2) | S2: =IF($U2="","",L2+O2+J2) | T2: =IF($U2="","",S2-Q2-G2) | U2: =IF(ROWS($U$2:$U2)<=MAX('Per Line'!$AA$2:$AA$501),MATCH(ROWS($U$2:$U2),'Per Line'!$AA$2:$AA$501,0),"")
B3: =IF($U3="","",INDEX('Per Line'!$A$2:$A$501,$U3)&"") | C3: =IF($U3="","",INDEX('Per Line'!$B$2:$B$501,$U3)&"") | D3: =IF($U3="","",INDEX('Per Line'!$C$2:$C$501,$U3)&"") | E3: =IF($U3="","",INDEX('Per Line'!$D$2:$D$501,$U3)&"") | F3: =IF($U3="","",INDEX('Per Line'!$E$2:$E$501,$U3)) | G3: =IF($U3="","",F3*R3/100) | H3: =IF($U3="","",INDEX('Per Line'!$Q$2:$Q$501,$U3)&"") | I3: =IF($U3="","",INDEX('Per Line'!$R$2:$R$501,$U3)) | J3: =IF($U3="","",SUMIFS('Per Line'!$M$2:$M$501,'Per Line'!$A$2:$A$501,$B3,'Per Line'!$AC$2:$AC$501,1)) | K3: =IF($U3="","",Settings!$C$7) | L3: =IF($U3="","",SUMIFS('Per Line'!$M$2:$M$501,'Per Line'!$A$2:$A$501,$B3,'Per Line'!$AB$2:$AB$501,0,'Per Line'!$AC$2:$AC$501,0)) | M3: =IF($U3="","",L3*K3) | N3: =IF($U3="","",Settings!$C$6) | O3: =IF($U3="","",SUMIFS('Per Line'!$M$2:$M$501,'Per Line'!$A$2:$A$501,$B3,'Per Line'!$AB$2:$AB$501,1,'Per Line'!$AC$2:$AC$501,0)) | P3: =IF($U3="","",O3*N3) | Q3: =IF($U3="","",P3+M3) | R3: =IF($U3="","",S3-Q3) | S3: =IF($U3="","",L3+O3+J3) | T3: =IF($U3="","",S3-Q3-G3) | U3: =IF(ROWS($U$2:$U3)<=MAX('Per Line'!$AA$2:$AA$501),MATCH(ROWS($U$2:$U3),'Per Line'!$AA$2:$AA$501,0),"")
B4: =IF($U4="","",INDEX('Per Line'!$A$2:$A$501,$U4)&"") | C4: =IF($U4="","",INDEX('Per Line'!$B$2:$B$501,$U4)&"") | D4: =IF($U4="","",INDEX('Per Line'!$C$2:$C$501,$U4)&"") | E4: =IF($U4="","",INDEX('Per Line'!$D$2:$D$501,$U4)&"") | F4: =IF($U4="","",INDEX('Per Line'!$E$2:$E$501,$U4)) | G4: =IF($U4="","",F4*R4/100) | H4: =IF($U4="","",INDEX('Per Line'!$Q$2:$Q$501,$U4)&"") | I4: =IF($U4="","",INDEX('Per Line'!$R$2:$R$501,$U4)) | J4: =IF($U4="","",SUMIFS('Per Line'!$M$2:$M$501,'Per Line'!$A$2:$A$501,$B4,'Per Line'!$AC$2:$AC$501,1)) | K4: =IF($U4="","",Settings!$C$7) | L4: =IF($U4="","",SUMIFS('Per Line'!$M$2:$M$501,'Per Line'!$A$2:$A$501,$B4,'Per Line'!$AB$2:$AB$501,0,'Per Line'!$AC$2:$AC$501,0)) | M4: =IF($U4="","",L4*K4) | N4: =IF($U4="","",Settings!$C$6) | O4: =IF($U4="","",SUMIFS('Per Line'!$M$2:$M$501,'Per Line'!$A$2:$A$501,$B4,'Per Line'!$AB$2:$AB$501,1,'Per Line'!$AC$2:$AC$501,0)) | P4: =IF($U4="","",O4*N4) | Q4: =IF($U4="","",P4+M4) | R4: =IF($U4="","",S4-Q4) | S4: =IF($U4="","",L4+O4+J4) | T4: =IF($U4="","",S4-Q4-G4) | U4: =IF(ROWS($U$2:$U4)<=MAX('Per Line'!$AA$2:$AA$501),MATCH(ROWS($U$2:$U4),'Per Line'!$AA$2:$AA$501,0),"")
B5: =IF($U5="","",INDEX('Per Line'!$A$2:$A$501,$U5)&"") | C5: =IF($U5="","",INDEX('Per Line'!$B$2:$B$501,$U5)&"") | D5: =IF($U5="","",INDEX('Per Line'!$C$2:$C$501,$U5)&"") | E5: =IF($U5="","",INDEX('Per Line'!$D$2:$D$501,$U5)&"") | F5: =IF($U5="","",INDEX('Per Line'!$E$2:$E$501,$U5)) | G5: =IF($U5="","",F5*R5/100) | H5: =IF($U5="","",INDEX('Per Line'!$Q$2:$Q$501,$U5)&"") | I5: =IF($U5="","",INDEX('Per Line'!$R$2:$R$501,$U5)) | J5: =IF($U5="","",SUMIFS('Per Line'!$M$2:$M$501,'Per Line'!$A$2:$A$501,$B5,'Per Line'!$AC$2:$AC$501,1)) | K5: =IF($U5="","",Settings!$C$7) | L5: =IF($U5="","",SUMIFS('Per Line'!$M$2:$M$501,'Per Line'!$A$2:$A$501,$B5,'Per Line'!$AB$2:$AB$501,0,'Per Line'!$AC$2:$AC$501,0)) | M5: =IF($U5="","",L5*K5) | N5: =IF($U5="","",Settings!$C$6) | O5: =IF($U5="","",SUMIFS('Per Line'!$M$2:$M$501,'Per Line'!$A$2:$A$501,$B5,'Per Line'!$AB$2:$AB$501,1,'Per Line'!$AC$2:$AC$501,0)) | P5: =IF($U5="","",O5*N5) | Q5: =IF($U5="","",P5+M5) | R5: =IF($U5="","",S5-Q5) | S5: =IF($U5="","",L5+O5+J5) | T5: =IF($U5="","",S5-Q5-G5) | U5: =IF(ROWS($U$2:$U5)<=MAX('Per Line'!$AA$2:$AA$501),MATCH(ROWS($U$2:$U5),'Per Line'!$AA$2:$AA$501,0),"")
B6: =IF($U6="","",INDEX('Per Line'!$A$2:$A$501,$U6)&"") | C6: =IF($U6="","",INDEX('Per Line'!$B$2:$B$501,$U6)&"") | D6: =IF($U6="","",INDEX('Per Line'!$C$2:$C$501,$U6)&"") | E6: =IF($U6="","",INDEX('Per Line'!$D$2:$D$501,$U6)&"") | F6: =IF($U6="","",INDEX('Per Line'!$E$2:$E$501,$U6)) | G6: =IF($U6="","",F6*R6/100) | H6: =IF($U6="","",INDEX('Per Line'!$Q$2:$Q$501,$U6)&"") | I6: =IF($U6="","",INDEX('Per Line'!$R$2:$R$501,$U6)) | J6: =IF($U6="","",SUMIFS('Per Line'!$M$2:$M$501,'Per Line'!$A$2:$A$501,$B6,'Per Line'!$AC$2:$AC$501,1)) | K6: =IF($U6="","",Settings!$C$7) | L6: =IF($U6="","",SUMIFS('Per Line'!$M$2:$M$501,'Per Line'!$A$2:$A$501,$B6,'Per Line'!$AB$2:$AB$501,0,'Per Line'!$AC$2:$AC$501,0)) | M6: =IF($U6="","",L6*K6) | N6: =IF($U6="","",Settings!$C$6) | O6: =IF($U6="","",SUMIFS('Per Line'!$M$2:$M$501,'Per Line'!$A$2:$A$501,$B6,'Per Line'!$AB$2:$AB$501,1,'Per Line'!$AC$2:$AC$501,0)) | P6: =IF($U6="","",O6*N6) | Q6: =IF($U6="","",P6+M6) | R6: =IF($U6="","",S6-Q6) | S6: =IF($U6="","",L6+O6+J6) | T6: =IF($U6="","",S6-Q6-G6) | U6: =IF(ROWS($U$2:$U6)<=MAX('Per Line'!$AA$2:$AA$501),MATCH(ROWS($U$2:$U6),'Per Line'!$AA$2:$AA$501,0),"")
B7: =IF($U7="","",INDEX('Per Line'!$A$2:$A$501,$U7)&"") | C7: =IF($U7="","",INDEX('Per Line'!$B$2:$B$501,$U7)&"") | D7: =IF($U7="","",INDEX('Per Line'!$C$2:$C$501,$U7)&"") | E7: =IF($U7="","",INDEX('Per Line'!$D$2:$D$501,$U7)&"") | F7: =IF($U7="","",INDEX('Per Line'!$E$2:$E$501,$U7)) | G7: =IF($U7="","",F7*R7/100) | H7: =IF($U7="","",INDEX('Per Line'!$Q$2:$Q$501,$U7)&"") | I7: =IF($U7="","",INDEX('Per Line'!$R$2:$R$501,$U7)) | J7: =IF($U7="","",SUMIFS('Per Line'!$M$2:$M$501,'Per Line'!$A$2:$A$501,$B7,'Per Line'!$AC$2:$AC$501,1)) | K7: =IF($U7="","",Settings!$C$7) | L7: =IF($U7="","",SUMIFS('Per Line'!$M$2:$M$501,'Per Line'!$A$2:$A$501,$B7,'Per Line'!$AB$2:$AB$501,0,'Per Line'!$AC$2:$AC$501,0)) | M7: =IF($U7="","",L7*K7) | N7: =IF($U7="","",Settings!$C$6) | O7: =IF($U7="","",SUMIFS('Per Line'!$M$2:$M$501,'Per Line'!$A$2:$A$501,$B7,'Per Line'!$AB$2:$AB$501,1,'Per Line'!$AC$2:$AC$501,0)) | P7: =IF($U7="","",O7*N7) | Q7: =IF($U7="","",P7+M7) | R7: =IF($U7="","",S7-Q7) | S7: =IF($U7="","",L7+O7+J7) | T7: =IF($U7="","",S7-Q7-G7) | U7: =IF(ROWS($U$2:$U7)<=MAX('Per Line'!$AA$2:$AA$501),MATCH(ROWS($U$2:$U7),'Per Line'!$AA$2:$AA$501,0),"")
B8: =IF($U8="","",INDEX('Per Line'!$A$2:$A$501,$U8)&"") | C8: =IF($U8="","",INDEX('Per Line'!$B$2:$B$501,$U8)&"") | D8: =IF($U8="","",INDEX('Per Line'!$C$2:$C$501,$U8)&"") | E8: =IF($U8="","",INDEX('Per Line'!$D$2:$D$501,$U8)&"") | F8: =IF($U8="","",INDEX('Per Line'!$E$2:$E$501,$U8)) | G8: =IF($U8="","",F8*R8/100) | H8: =IF($U8="","",INDEX('Per Line'!$Q$2:$Q$501,$U8)&"") | I8: =IF($U8="","",INDEX('Per Line'!$R$2:$R$501,$U8)) | J8: =IF($U8="","",SUMIFS('Per Line'!$M$2:$M$501,'Per Line'!$A$2:$A$501,$B8,'Per Line'!$AC$2:$AC$501,1)) | K8: =IF($U8="","",Settings!$C$7) | L8: =IF($U8="","",SUMIFS('Per Line'!$M$2:$M$501,'Per Line'!$A$2:$A$501,$B8,'Per Line'!$AB$2:$AB$501,0,'Per Line'!$AC$2:$AC$501,0)) | M8: =IF($U8="","",L8*K8) | N8: =IF($U8="","",Settings!$C$6) | O8: =IF($U8="","",SUMIFS('Per Line'!$M$2:$M$501,'Per Line'!$A$2:$A$501,$B8,'Per Line'!$AB$2:$AB$501,1,'Per Line'!$AC$2:$AC$501,0)) | P8: =IF($U8="","",O8*N8) | Q8: =IF($U8="","",P8+M8) | R8: =IF($U8="","",S8-Q8) | S8: =IF($U8="","",L8+O8+J8) | T8: =IF($U8="","",S8-Q8-G8) | U8: =IF(ROWS($U$2:$U8)<=MAX('Per Line'!$AA$2:$AA$501),MATCH(ROWS($U$2:$U8),'Per Line'!$AA$2:$AA$501,0),"")
B9: =IF($U9="","",INDEX('Per Line'!$A$2:$A$501,$U9)&"") | C9: =IF($U9="","",INDEX('Per Line'!$B$2:$B$501,$U9)&"") | D9: =IF($U9="","",INDEX('Per Line'!$C$2:$C$501,$U9)&"") | E9: =IF($U9="","",INDEX('Per Line'!$D$2:$D$501,$U9)&"") | F9: =IF($U9="","",INDEX('Per Line'!$E$2:$E$501,$U9)) | G9: =IF($U9="","",F9*R9/100) | H9: =IF($U9="","",INDEX('Per Line'!$Q$2:$Q$501,$U9)&"") | I9: =IF($U9="","",INDEX('Per Line'!$R$2:$R$501,$U9)) | J9: =IF($U9="","",SUMIFS('Per Line'!$M$2:$M$501,'Per Line'!$A$2:$A$501,$B9,'Per Line'!$AC$2:$AC$501,1)) | K9: =IF($U9="","",Settings!$C$7) | L9: =IF($U9="","",SUMIFS('Per Line'!$M$2:$M$501,'Per Line'!$A$2:$A$501,$B9,'Per Line'!$AB$2:$AB$501,0,'Per Line'!$AC$2:$AC$501,0)) | M9: =IF($U9="","",L9*K9) | N9: =IF($U9="","",Settings!$C$6) | O9: =IF($U9="","",SUMIFS('Per Line'!$M$2:$M$501,'Per Line'!$A$2:$A$501,$B9,'Per Line'!$AB$2:$AB$501,1,'Per Line'!$AC$2:$AC$501,0)) | P9: =IF($U9="","",O9*N9) | Q9: =IF($U9="","",P9+M9) | R9: =IF($U9="","",S9-Q9) | S9: =IF($U9="","",L9+O9+J9) | T9: =IF($U9="","",S9-Q9-G9) | U9: =IF(ROWS($U$2:$U9)<=MAX('Per Line'!$AA$2:$AA$501),MATCH(ROWS($U$2:$U9),'Per Line'!$AA$2:$AA$501,0),"")
B10: =IF($U10="","",INDEX('Per Line'!$A$2:$A$501,$U10)&"") | C10: =IF($U10="","",INDEX('Per Line'!$B$2:$B$501,$U10)&"") | D10: =IF($U10="","",INDEX('Per Line'!$C$2:$C$501,$U10)&"") | E10: =IF($U10="","",INDEX('Per Line'!$D$2:$D$501,$U10)&"") | F10: =IF($U10="","",INDEX('Per Line'!$E$2:$E$501,$U10)) | G10: =IF($U10="","",F10*R10/100) | H10: =IF($U10="","",INDEX('Per Line'!$Q$2:$Q$501,$U10)&"") | I10: =IF($U10="","",INDEX('Per Line'!$R$2:$R$501,$U10)) | J10: =IF($U10="","",SUMIFS('Per Line'!$M$2:$M$501,'Per Line'!$A$2:$A$501,$B10,'Per Line'!$AC$2:$AC$501,1)) | K10: =IF($U10="","",Settings!$C$7) | L10: =IF($U10="","",SUMIFS('Per Line'!$M$2:$M$501,'Per Line'!$A$2:$A$501,$B10,'Per Line'!$AB$2:$AB$501,0,'Per Line'!$AC$2:$AC$501,0)) | M10: =IF($U10="","",L10*K10) | N10: =IF($U10="","",Settings!$C$6) | O10: =IF($U10="","",SUMIFS('Per Line'!$M$2:$M$501,'Per Line'!$A$2:$A$501,$B10,'Per Line'!$AB$2:$AB$501,1,'Per Line'!$AC$2:$AC$501,0)) | P10: =IF($U10="","",O10*N10) | Q10: =IF($U10="","",P10+M10) | R10: =IF($U10="","",S10-Q10) | S10: =IF($U10="","",L10+O10+J10) | T10: =IF($U10="","",S10-Q10-G10) | U10: =IF(ROWS($U$2:$U10)<=MAX('Per Line'!$AA$2:$AA$501),MATCH(ROWS($U$2:$U10),'Per Line'!$AA$2:$AA$501,0),"")
B11: =IF($U11="","",INDEX('Per Line'!$A$2:$A$501,$U11)&"") | C11: =IF($U11="","",INDEX('Per Line'!$B$2:$B$501,$U11)&"") | D11: =IF($U11="","",INDEX('Per Line'!$C$2:$C$501,$U11)&"") | E11: =IF($U11="","",INDEX('Per Line'!$D$2:$D$501,$U11)&"") | F11: =IF($U11="","",INDEX('Per Line'!$E$2:$E$501,$U11)) | G11: =IF($U11="","",F11*R11/100) | H11: =IF($U11="","",INDEX('Per Line'!$Q$2:$Q$501,$U11)&"") | I11: =IF($U11="","",INDEX('Per Line'!$R$2:$R$501,$U11)) | J11: =IF($U11="","",SUMIFS('Per Line'!$M$2:$M$501,'Per Line'!$A$2:$A$501,$B11,'Per Line'!$AC$2:$AC$501,1)) | K11: =IF($U11="","",Settings!$C$7) | L11: =IF($U11="","",SUMIFS('Per Line'!$M$2:$M$501,'Per Line'!$A$2:$A$501,$B11,'Per Line'!$AB$2:$AB$501,0,'Per Line'!$AC$2:$AC$501,0)) | M11: =IF($U11="","",L11*K11) | N11: =IF($U11="","",Settings!$C$6) | O11: =IF($U11="","",SUMIFS('Per Line'!$M$2:$M$501,'Per Line'!$A$2:$A$501,$B11,'Per Line'!$AB$2:$AB$501,1,'Per Line'!$AC$2:$AC$501,0)) | P11: =IF($U11="","",O11*N11) | Q11: =IF($U11="","",P11+M11) | R11: =IF($U11="","",S11-Q11) | S11: =IF($U11="","",L11+O11+J11) | T11: =IF($U11="","",S11-Q11-G11) | U11: =IF(ROWS($U$2:$U11)<=MAX('Per Line'!$AA$2:$AA$501),MATCH(ROWS($U$2:$U11),'Per Line'!$AA$2:$AA$501,0),"")
B12: =IF($U12="","",INDEX('Per Line'!$A$2:$A$501,$U12)&"") | C12: =IF($U12="","",INDEX('Per Line'!$B$2:$B$501,$U12)&"") | D12: =IF($U12="","",INDEX('Per Line'!$C$2:$C$501,$U12)&"") | E12: =IF($U12="","",INDEX('Per Line'!$D$2:$D$501,$U12)&"") | F12: =IF($U12="","",INDEX('Per Line'!$E$2:$E$501,$U12)) | G12: =IF($U12="","",F12*R12/100) | H12: =IF($U12="","",INDEX('Per Line'!$Q$2:$Q$501,$U12)&"") | I12: =IF($U12="","",INDEX('Per Line'!$R$2:$R$501,$U12)) | J12: =IF($U12="","",SUMIFS('Per Line'!$M$2:$M$501,'Per Line'!$A$2:$A$501,$B12,'Per Line'!$AC$2:$AC$501,1)) | K12: =IF($U12="","",Settings!$C$7) | L12: =IF($U12="","",SUMIFS('Per Line'!$M$2:$M$501,'Per Line'!$A$2:$A$501,$B12,'Per Line'!$AB$2:$AB$501,0,'Per Line'!$AC$2:$AC$501,0)) | M12: =IF($U12="","",L12*K12) | N12: =IF($U12="","",Settings!$C$6) | O12: =IF($U12="","",SUMIFS('Per Line'!$M$2:$M$501,'Per Line'!$A$2:$A$501,$B12,'Per Line'!$AB$2:$AB$501,1,'Per Line'!$AC$2:$AC$501,0)) | P12: =IF($U12="","",O12*N12) | Q12: =IF($U12="","",P12+M12) | R12: =IF($U12="","",S12-Q12) | S12: =IF($U12="","",L12+O12+J12) | T12: =IF($U12="","",S12-Q12-G12) | U12: =IF(ROWS($U$2:$U12)<=MAX('Per Line'!$AA$2:$AA$501),MATCH(ROWS($U$2:$U12),'Per Line'!$AA$2:$AA$501,0),"")
B13: =IF($U13="","",INDEX('Per Line'!$A$2:$A$501,$U13)&"") | C13: =IF($U13="","",INDEX('Per Line'!$B$2:$B$501,$U13)&"") | D13: =IF($U13="","",INDEX('Per Line'!$C$2:$C$501,$U13)&"") | E13: =IF($U13="","",INDEX('Per Line'!$D$2:$D$501,$U13)&"") | F13: =IF($U13="","",INDEX('Per Line'!$E$2:$E$501,$U13)) | G13: =IF($U13="","",F13*R13/100) | H13: =IF($U13="","",INDEX('Per Line'!$Q$2:$Q$501,$U13)&"") | I13: =IF($U13="","",INDEX('Per Line'!$R$2:$R$501,$U13)) | J13: =IF($U13="","",SUMIFS('Per Line'!$M$2:$M$501,'Per Line'!$A$2:$A$501,$B13,'Per Line'!$AC$2:$AC$501,1)) | K13: =IF($U13="","",Settings!$C$7) | L13: =IF($U13="","",SUMIFS('Per Line'!$M$2:$M$501,'Per Line'!$A$2:$A$501,$B13,'Per Line'!$AB$2:$AB$501,0,'Per Line'!$AC$2:$AC$501,0)) | M13: =IF($U13="","",L13*K13) | N13: =IF($U13="","",Settings!$C$6) | O13: =IF($U13="","",SUMIFS('Per Line'!$M$2:$M$501,'Per Line'!$A$2:$A$501,$B13,'Per Line'!$AB$2:$AB$501,1,'Per Line'!$AC$2:$AC$501,0)) | P13: =IF($U13="","",O13*N13) | Q13: =IF($U13="","",P13+M13) | R13: =IF($U13="","",S13-Q13) | S13: =IF($U13="","",L13+O13+J13) | T13: =IF($U13="","",S13-Q13-G13) | U13: =IF(ROWS($U$2:$U13)<=MAX('Per Line'!$AA$2:$AA$501),MATCH(ROWS($U$2:$U13),'Per Line'!$AA$2:$AA$501,0),"")
... B201: =IF($U201="","",INDEX('Per Line'!$A$2:$A$501,$U201)&"") | C201: =IF($U201="","",INDEX('Per Line'!$B$2:$B$501,$U201)&"") | D201: =IF($U201="","",INDEX('Per Line'!$C$2:$C$501,$U201)&"") | E201: =IF($U201="","",INDEX('Per Line'!$D$2:$D$501,$U201)&"") | F201: =IF($U201="","",INDEX('Per Line'!$E$2:$E$501,$U201)) | G201: =IF($U201="","",F201*R201/100) | H201: =IF($U201="","",INDEX('Per Line'!$Q$2:$Q$501,$U201)&"") | I201: =IF($U201="","",INDEX('Per Line'!$R$2:$R$501,$U201)) | J201: =IF($U201="","",SUMIFS('Per Line'!$M$2:$M$501,'Per Line'!$A$2:$A$501,$B201,'Per Line'!$AC$2:$AC$501,1)) | K201: =IF($U201="","",Settings!$C$7) | L201: =IF($U201="","",SUMIFS('Per Line'!$M$2:$M$501,'Per Line'!$A$2:$A$501,$B201,'Per Line'!$AB$2:$AB$501,0,'Per Line'!$AC$2:$AC$501,0)) | M201: =IF($U201="","",L201*K201) | N201: =IF($U201="","",Settings!$C$6) | O201: =IF($U201="","",SUMIFS('Per Line'!$M$2:$M$501,'Per Line'!$A$2:$A$501,$B201,'Per Line'!$AB$2:$AB$501,1,'Per Line'!$AC$2:$AC$501,0)) | P201: =IF($U201="","",O201*N201) | Q201: =IF($U201="","",P201+M201) | R201: =IF($U201="","",S201-Q201) | S201: =IF($U201="","",L201+O201+J201) | T201: =IF($U201="","",S201-Q201-G201) | U201: =IF(ROWS($U$2:$U201)<=MAX('Per Line'!$AA$2:$AA$501),MATCH(ROWS($U$2:$U201),'Per Line'!$AA$2:$AA$501,0),"")
