Workbook

Sheet How To Use
A1: Claims Template - ADMINISTRATIVE CONTROL AUTHORITY (ACA) (Chronic)
A3: Monthly steps
A4: 1. Open the 'Per Line' tab. Delete the old data in the BLUE columns only (row 2 down). Never delete the green or grey columns.
A5: 2. Paste the new month's data as VALUES starting at A2, into the blue columns: A-J, L-T, Y-AF (same order as the system export).
A6: 3. Green columns (K, U, V, W, X) and the grey helper columns (AG-AK) calculate automatically - do not paste over them.
A7: 4. 'Per Invoice' fills itself from 'Per Line' (one row per Order #, split into IMP / Local). No pivot table, no refresh.
A8: 5. The ONLY manual column in 'Per Invoice' is column A 'Invoice' (blue): type it yourself. Everything else is formula.
A9: 6. Open 'Settings' and check STATUS says OK (Per Line totals = Per Invoice totals).
A11: Colour legend
A12: Blue header = typed/pasted by you (raw data, and 'Invoice' in Per Invoice). Green header = formula (do not paste over). Grey header = helper formula (do not touch). Yellow cell (Settings) = editable rate.
A14: Calculation rules (taken from the September 2026 sheet)
A15: Co val = Order Co Payment x Subtotal / 100. Discount = Total x Rebates / 100. Subtotal = Total - Discount. Net = Subtotal - Co val. (Total = 'Product Total')
... A20: Capacity: up to 6,000 lines and 1,200 invoices per month. A line with an empty Order # is ignored.

Sheet Settings
B1: Company settings & checks
B3: Insurance Company | C3: ADMINISTRATIVE CONTROL AUTHORITY (ACA) | D3: Informational only
B4: Corporate | C4: ACA Pensioners | D4: Informational only
B5: Sheet type | C5: Chronic | D5: Informational only
B6: Local products rebate % | C6: 0.12 | D6: Source: Sep sheet (Rebates = 12 on Local lines, 0 on Special Rebates = Yes).
B7: Imported (IMP) products rebate % | C7: 0.05 | D7: Source: Sep sheet (Rebates = 5 on non-local lines).
B9: Month totals / reconciliation
B10: Lines loaded | C10: =COUNTA('Per Line'!$C$2:$C$6001)
B11: Invoices (unique Order #) | C11: =MAX('Per Line'!$AH$2:$AH$6001)
B12: Invoices shown in Per Invoice | C12: =SUMPRODUCT(--('Per Invoice'!$B$2:$B$1201<>""))
B13: Grand Total - Per Line (Product Total) | C13: =SUM('Per Line'!$R$2:$R$6001)
B14: Grand Total - Per Invoice | C14: =SUM('Per Invoice'!$T$2:$T$1201)
B15: Discount - Per Line | C15: =SUM('Per Line'!$V$2:$V$6001)
B16: Discount - Per Invoice | C16: =SUM('Per Invoice'!$R$2:$R$1201)
B17: Co val - Per Line | C17: =SUM('Per Line'!$K$2:$K$6001)
B18: Co val - Per Invoice | C18: =SUM('Per Invoice'!$I$2:$I$1201)
B19: Net - Per Line | C19: =SUM('Per Line'!$X$2:$X$6001)
B20: Net - Per Invoice | C20: =SUM('Per Invoice'!$U$2:$U$1201)
B21: Max Limit adjustment (Co val, Per Invoice only) | C21: 0 | D21: This company's Per Invoice has no Max Limit rule.
B23: STATUS | C23: =IF(C10=0,"No data loaded",IF(COUNTA('Per Line'!$C:$C)-1>6000,"TOO MANY LINES - extend template",IF(C11>1200,"TOO MANY INVOICES - extend template",IF(AND(ROUND(C13-C14,2)=0,ROUND(C15-C16,2)=0,ROUND(C17+C21-C18,2)=0,ROUND(C19-C21-C20,2)=0,C11=C12),"OK","CHECK - Per Line and Per Invoice do not match")))) | D23: Must say OK after you paste the month data.

Sheet Per Line
A1: Cycle | B1: Approval Ref | C1: Order # | D1: Create At | E1: Insurance Company | F1: Country Portal ID | G1: Corporate | H1: Card | I1: Name | J1: Order Co Payment | K1: Co val | L1: heisenberg id | M1: Product Name | N1: Local | O1: Unit | P1: Quantity | Q1: Unit Price | R1: Product Total | S1: ERX ID | T1: Special Rebates? | U1: Rebates | V1: Discount | W1: Subtotal | X1: Net | Y1: Approval Type | Z1: Max Limit | AA1: Exceeding Limit | AB1: Amount collected from customer | AC1: By Patient (Delivered) | AD1: Dispense Number | AE1: Dispense Date | AF1: Has OTP? | AG1: Order 1st Row (helper) | AH1: Invoice # (helper) | AI1: Is Local (helper) | AJ1: Is Special (helper) | AK1: Sort Key (helper)
K2: =IF($C2="","",J2*W2/100) | U2: =IF($C2="","",IF($AJ2=1,0,IF($AI2=1,Settings!$C$6,Settings!$C$7))*100) | V2: =IF($C2="","",R2*U2/100) | W2: =IF($C2="","",R2-V2) | X2: =IF($C2="","",W2-K2) | AG2: =IF($C2="","",IF(COUNTIF($C$2:$C2,$C2)=1,1,0)) | AH2: =IF($AG2=1,SUMPRODUCT(--($AK$2:$AK$6001<$AK2))+1,"") | AI2: =IF($C2="","",IF(OR($N2=TRUE(),$N2="TRUE"),1,0)) | AJ2: =IF($C2="","",IF($T2="Yes",1,0)) | AK2: =IF($AG2=1,IFERROR(IF(VALUE($C2)<100000000,VALUE($C2),1000000000),IFERROR(IF(VALUE(MID($C2,2,20))<100000000,VALUE(MID($C2,2,20)),1000000000),1000000000))+ROW()/100000,"")
K3: =IF($C3="","",J3*W3/100) | U3: =IF($C3="","",IF($AJ3=1,0,IF($AI3=1,Settings!$C$6,Settings!$C$7))*100) | V3: =IF($C3="","",R3*U3/100) | W3: =IF($C3="","",R3-V3) | X3: =IF($C3="","",W3-K3) | AG3: =IF($C3="","",IF(COUNTIF($C$2:$C3,$C3)=1,1,0)) | AH3: =IF($AG3=1,SUMPRODUCT(--($AK$2:$AK$6001<$AK3))+1,"") | AI3: =IF($C3="","",IF(OR($N3=TRUE(),$N3="TRUE"),1,0)) | AJ3: =IF($C3="","",IF($T3="Yes",1,0)) | AK3: =IF($AG3=1,IFERROR(IF(VALUE($C3)<100000000,VALUE($C3),1000000000),IFERROR(IF(VALUE(MID($C3,2,20))<100000000,VALUE(MID($C3,2,20)),1000000000),1000000000))+ROW()/100000,"")
K4: =IF($C4="","",J4*W4/100) | U4: =IF($C4="","",IF($AJ4=1,0,IF($AI4=1,Settings!$C$6,Settings!$C$7))*100) | V4: =IF($C4="","",R4*U4/100) | W4: =IF($C4="","",R4-V4) | X4: =IF($C4="","",W4-K4) | AG4: =IF($C4="","",IF(COUNTIF($C$2:$C4,$C4)=1,1,0)) | AH4: =IF($AG4=1,SUMPRODUCT(--($AK$2:$AK$6001<$AK4))+1,"") | AI4: =IF($C4="","",IF(OR($N4=TRUE(),$N4="TRUE"),1,0)) | AJ4: =IF($C4="","",IF($T4="Yes",1,0)) | AK4: =IF($AG4=1,IFERROR(IF(VALUE($C4)<100000000,VALUE($C4),1000000000),IFERROR(IF(VALUE(MID($C4,2,20))<100000000,VALUE(MID($C4,2,20)),1000000000),1000000000))+ROW()/100000,"")
K5: =IF($C5="","",J5*W5/100) | U5: =IF($C5="","",IF($AJ5=1,0,IF($AI5=1,Settings!$C$6,Settings!$C$7))*100) | V5: =IF($C5="","",R5*U5/100) | W5: =IF($C5="","",R5-V5) | X5: =IF($C5="","",W5-K5) | AG5: =IF($C5="","",IF(COUNTIF($C$2:$C5,$C5)=1,1,0)) | AH5: =IF($AG5=1,SUMPRODUCT(--($AK$2:$AK$6001<$AK5))+1,"") | AI5: =IF($C5="","",IF(OR($N5=TRUE(),$N5="TRUE"),1,0)) | AJ5: =IF($C5="","",IF($T5="Yes",1,0)) | AK5: =IF($AG5=1,IFERROR(IF(VALUE($C5)<100000000,VALUE($C5),1000000000),IFERROR(IF(VALUE(MID($C5,2,20))<100000000,VALUE(MID($C5,2,20)),1000000000),1000000000))+ROW()/100000,"")
K6: =IF($C6="","",J6*W6/100) | U6: =IF($C6="","",IF($AJ6=1,0,IF($AI6=1,Settings!$C$6,Settings!$C$7))*100) | V6: =IF($C6="","",R6*U6/100) | W6: =IF($C6="","",R6-V6) | X6: =IF($C6="","",W6-K6) | AG6: =IF($C6="","",IF(COUNTIF($C$2:$C6,$C6)=1,1,0)) | AH6: =IF($AG6=1,SUMPRODUCT(--($AK$2:$AK$6001<$AK6))+1,"") | AI6: =IF($C6="","",IF(OR($N6=TRUE(),$N6="TRUE"),1,0)) | AJ6: =IF($C6="","",IF($T6="Yes",1,0)) | AK6: =IF($AG6=1,IFERROR(IF(VALUE($C6)<100000000,VALUE($C6),1000000000),IFERROR(IF(VALUE(MID($C6,2,20))<100000000,VALUE(MID($C6,2,20)),1000000000),1000000000))+ROW()/100000,"")
K7: =IF($C7="","",J7*W7/100) | U7: =IF($C7="","",IF($AJ7=1,0,IF($AI7=1,Settings!$C$6,Settings!$C$7))*100) | V7: =IF($C7="","",R7*U7/100) | W7: =IF($C7="","",R7-V7) | X7: =IF($C7="","",W7-K7) | AG7: =IF($C7="","",IF(COUNTIF($C$2:$C7,$C7)=1,1,0)) | AH7: =IF($AG7=1,SUMPRODUCT(--($AK$2:$AK$6001<$AK7))+1,"") | AI7: =IF($C7="","",IF(OR($N7=TRUE(),$N7="TRUE"),1,0)) | AJ7: =IF($C7="","",IF($T7="Yes",1,0)) | AK7: =IF($AG7=1,IFERROR(IF(VALUE($C7)<100000000,VALUE($C7),1000000000),IFERROR(IF(VALUE(MID($C7,2,20))<100000000,VALUE(MID($C7,2,20)),1000000000),1000000000))+ROW()/100000,"")
K8: =IF($C8="","",J8*W8/100) | U8: =IF($C8="","",IF($AJ8=1,0,IF($AI8=1,Settings!$C$6,Settings!$C$7))*100) | V8: =IF($C8="","",R8*U8/100) | W8: =IF($C8="","",R8-V8) | X8: =IF($C8="","",W8-K8) | AG8: =IF($C8="","",IF(COUNTIF($C$2:$C8,$C8)=1,1,0)) | AH8: =IF($AG8=1,SUMPRODUCT(--($AK$2:$AK$6001<$AK8))+1,"") | AI8: =IF($C8="","",IF(OR($N8=TRUE(),$N8="TRUE"),1,0)) | AJ8: =IF($C8="","",IF($T8="Yes",1,0)) | AK8: =IF($AG8=1,IFERROR(IF(VALUE($C8)<100000000,VALUE($C8),1000000000),IFERROR(IF(VALUE(MID($C8,2,20))<100000000,VALUE(MID($C8,2,20)),1000000000),1000000000))+ROW()/100000,"")
K9: =IF($C9="","",J9*W9/100) | U9: =IF($C9="","",IF($AJ9=1,0,IF($AI9=1,Settings!$C$6,Settings!$C$7))*100) | V9: =IF($C9="","",R9*U9/100) | W9: =IF($C9="","",R9-V9) | X9: =IF($C9="","",W9-K9) | AG9: =IF($C9="","",IF(COUNTIF($C$2:$C9,$C9)=1,1,0)) | AH9: =IF($AG9=1,SUMPRODUCT(--($AK$2:$AK$6001<$AK9))+1,"") | AI9: =IF($C9="","",IF(OR($N9=TRUE(),$N9="TRUE"),1,0)) | AJ9: =IF($C9="","",IF($T9="Yes",1,0)) | AK9: =IF($AG9=1,IFERROR(IF(VALUE($C9)<100000000,VALUE($C9),1000000000),IFERROR(IF(VALUE(MID($C9,2,20))<100000000,VALUE(MID($C9,2,20)),1000000000),1000000000))+ROW()/100000,"")
K10: =IF($C10="","",J10*W10/100) | U10: =IF($C10="","",IF($AJ10=1,0,IF($AI10=1,Settings!$C$6,Settings!$C$7))*100) | V10: =IF($C10="","",R10*U10/100) | W10: =IF($C10="","",R10-V10) | X10: =IF($C10="","",W10-K10) | AG10: =IF($C10="","",IF(COUNTIF($C$2:$C10,$C10)=1,1,0)) | AH10: =IF($AG10=1,SUMPRODUCT(--($AK$2:$AK$6001<$AK10))+1,"") | AI10: =IF($C10="","",IF(OR($N10=TRUE(),$N10="TRUE"),1,0)) | AJ10: =IF($C10="","",IF($T10="Yes",1,0)) | AK10: =IF($AG10=1,IFERROR(IF(VALUE($C10)<100000000,VALUE($C10),1000000000),IFERROR(IF(VALUE(MID($C10,2,20))<100000000,VALUE(MID($C10,2,20)),1000000000),1000000000))+ROW()/100000,"")
K11: =IF($C11="","",J11*W11/100) | U11: =IF($C11="","",IF($AJ11=1,0,IF($AI11=1,Settings!$C$6,Settings!$C$7))*100) | V11: =IF($C11="","",R11*U11/100) | W11: =IF($C11="","",R11-V11) | X11: =IF($C11="","",W11-K11) | AG11: =IF($C11="","",IF(COUNTIF($C$2:$C11,$C11)=1,1,0)) | AH11: =IF($AG11=1,SUMPRODUCT(--($AK$2:$AK$6001<$AK11))+1,"") | AI11: =IF($C11="","",IF(OR($N11=TRUE(),$N11="TRUE"),1,0)) | AJ11: =IF($C11="","",IF($T11="Yes",1,0)) | AK11: =IF($AG11=1,IFERROR(IF(VALUE($C11)<100000000,VALUE($C11),1000000000),IFERROR(IF(VALUE(MID($C11,2,20))<100000000,VALUE(MID($C11,2,20)),1000000000),1000000000))+ROW()/100000,"")
K12: =IF($C12="","",J12*W12/100) | U12: =IF($C12="","",IF($AJ12=1,0,IF($AI12=1,Settings!$C$6,Settings!$C$7))*100) | V12: =IF($C12="","",R12*U12/100) | W12: =IF($C12="","",R12-V12) | X12: =IF($C12="","",W12-K12) | AG12: =IF($C12="","",IF(COUNTIF($C$2:$C12,$C12)=1,1,0)) | AH12: =IF($AG12=1,SUMPRODUCT(--($AK$2:$AK$6001<$AK12))+1,"") | AI12: =IF($C12="","",IF(OR($N12=TRUE(),$N12="TRUE"),1,0)) | AJ12: =IF($C12="","",IF($T12="Yes",1,0)) | AK12: =IF($AG12=1,IFERROR(IF(VALUE($C12)<100000000,VALUE($C12),1000000000),IFERROR(IF(VALUE(MID($C12,2,20))<100000000,VALUE(MID($C12,2,20)),1000000000),1000000000))+ROW()/100000,"")
K13: =IF($C13="","",J13*W13/100) | U13: =IF($C13="","",IF($AJ13=1,0,IF($AI13=1,Settings!$C$6,Settings!$C$7))*100) | V13: =IF($C13="","",R13*U13/100) | W13: =IF($C13="","",R13-V13) | X13: =IF($C13="","",W13-K13) | AG13: =IF($C13="","",IF(COUNTIF($C$2:$C13,$C13)=1,1,0)) | AH13: =IF($AG13=1,SUMPRODUCT(--($AK$2:$AK$6001<$AK13))+1,"") | AI13: =IF($C13="","",IF(OR($N13=TRUE(),$N13="TRUE"),1,0)) | AJ13: =IF($C13="","",IF($T13="Yes",1,0)) | AK13: =IF($AG13=1,IFERROR(IF(VALUE($C13)<100000000,VALUE($C13),1000000000),IFERROR(IF(VALUE(MID($C13,2,20))<100000000,VALUE(MID($C13,2,20)),1000000000),1000000000))+ROW()/100000,"")
... K6001: =IF($C6001="","",J6001*W6001/100) | U6001: =IF($C6001="","",IF($AJ6001=1,0,IF($AI6001=1,Settings!$C$6,Settings!$C$7))*100) | V6001: =IF($C6001="","",R6001*U6001/100) | W6001: =IF($C6001="","",R6001-V6001) | X6001: =IF($C6001="","",W6001-K6001) | AG6001: =IF($C6001="","",IF(COUNTIF($C$2:$C6001,$C6001)=1,1,0)) | AH6001: =IF($AG6001=1,SUMPRODUCT(--($AK$2:$AK$6001<$AK6001))+1,"") | AI6001: =IF($C6001="","",IF(OR($N6001=TRUE(),$N6001="TRUE"),1,0)) | AJ6001: =IF($C6001="","",IF($T6001="Yes",1,0)) | AK6001: =IF($AG6001=1,IFERROR(IF(VALUE($C6001)<100000000,VALUE($C6001),1000000000),IFERROR(IF(VALUE(MID($C6001,2,20))<100000000,VALUE(MID($C6001,2,20)),1000000000),1000000000))+ROW()/100000,"")

Sheet Per Invoice
A1: Invoice | B1: Order # | C1: Create At | D1: Insurance Company | E1: Corporate | F1: Card | G1: Name | H1: Order Co Payment | I1: Co val | J1: ERX ID | K1: Special Rebates | L1: IMP % | M1: IMP | N1: IMP VAL | O1: LOCAL % | P1: LOCAL | Q1: LOCAL VAL | R1: TOTAL VAL | S1: SUBTOTAL | T1: Grand Total | U1: NET | V1: Src Row (helper)
B2: =IF($V2="","",INDEX('Per Line'!$C$2:$C$6001,$V2)&"") | C2: =IF($V2="","",INDEX('Per Line'!$D$2:$D$6001,$V2)) | D2: =IF($V2="","",INDEX('Per Line'!$E$2:$E$6001,$V2)&"") | E2: =IF($V2="","",INDEX('Per Line'!$G$2:$G$6001,$V2)&"") | F2: =IF($V2="","",INDEX('Per Line'!$H$2:$H$6001,$V2)&"") | G2: =IF($V2="","",INDEX('Per Line'!$I$2:$I$6001,$V2)&"") | H2: =IF($V2="","",INDEX('Per Line'!$J$2:$J$6001,$V2)) | I2: =IF($V2="","",H2*S2/100) | J2: =IF($V2="","",INDEX('Per Line'!$S$2:$S$6001,$V2)&"") | K2: =IF($V2="","",SUMIFS('Per Line'!$R$2:$R$6001,'Per Line'!$C$2:$C$6001,$B2,'Per Line'!$AJ$2:$AJ$6001,1)) | L2: =IF($V2="","",Settings!$C$7) | M2: =IF($V2="","",SUMIFS('Per Line'!$R$2:$R$6001,'Per Line'!$C$2:$C$6001,$B2,'Per Line'!$AI$2:$AI$6001,0,'Per Line'!$AJ$2:$AJ$6001,0)) | N2: =IF($V2="","",M2*L2) | O2: =IF($V2="","",Settings!$C$6) | P2: =IF($V2="","",SUMIFS('Per Line'!$R$2:$R$6001,'Per Line'!$C$2:$C$6001,$B2,'Per Line'!$AI$2:$AI$6001,1,'Per Line'!$AJ$2:$AJ$6001,0)) | Q2: =IF($V2="","",P2*O2) | R2: =IF($V2="","",Q2+N2) | S2: =IF($V2="","",T2-R2) | T2: =IF($V2="","",M2+P2+K2) | U2: =IF($V2="","",T2-R2-I2) | V2: =IF(ROWS($V$2:$V2)<=MAX('Per Line'!$AH$2:$AH$6001),MATCH(ROWS($V$2:$V2),'Per Line'!$AH$2:$AH$6001,0),"")
B3: =IF($V3="","",INDEX('Per Line'!$C$2:$C$6001,$V3)&"") | C3: =IF($V3="","",INDEX('Per Line'!$D$2:$D$6001,$V3)) | D3: =IF($V3="","",INDEX('Per Line'!$E$2:$E$6001,$V3)&"") | E3: =IF($V3="","",INDEX('Per Line'!$G$2:$G$6001,$V3)&"") | F3: =IF($V3="","",INDEX('Per Line'!$H$2:$H$6001,$V3)&"") | G3: =IF($V3="","",INDEX('Per Line'!$I$2:$I$6001,$V3)&"") | H3: =IF($V3="","",INDEX('Per Line'!$J$2:$J$6001,$V3)) | I3: =IF($V3="","",H3*S3/100) | J3: =IF($V3="","",INDEX('Per Line'!$S$2:$S$6001,$V3)&"") | K3: =IF($V3="","",SUMIFS('Per Line'!$R$2:$R$6001,'Per Line'!$C$2:$C$6001,$B3,'Per Line'!$AJ$2:$AJ$6001,1)) | L3: =IF($V3="","",Settings!$C$7) | M3: =IF($V3="","",SUMIFS('Per Line'!$R$2:$R$6001,'Per Line'!$C$2:$C$6001,$B3,'Per Line'!$AI$2:$AI$6001,0,'Per Line'!$AJ$2:$AJ$6001,0)) | N3: =IF($V3="","",M3*L3) | O3: =IF($V3="","",Settings!$C$6) | P3: =IF($V3="","",SUMIFS('Per Line'!$R$2:$R$6001,'Per Line'!$C$2:$C$6001,$B3,'Per Line'!$AI$2:$AI$6001,1,'Per Line'!$AJ$2:$AJ$6001,0)) | Q3: =IF($V3="","",P3*O3) | R3: =IF($V3="","",Q3+N3) | S3: =IF($V3="","",T3-R3) | T3: =IF($V3="","",M3+P3+K3) | U3: =IF($V3="","",T3-R3-I3) | V3: =IF(ROWS($V$2:$V3)<=MAX('Per Line'!$AH$2:$AH$6001),MATCH(ROWS($V$2:$V3),'Per Line'!$AH$2:$AH$6001,0),"")
B4: =IF($V4="","",INDEX('Per Line'!$C$2:$C$6001,$V4)&"") | C4: =IF($V4="","",INDEX('Per Line'!$D$2:$D$6001,$V4)) | D4: =IF($V4="","",INDEX('Per Line'!$E$2:$E$6001,$V4)&"") | E4: =IF($V4="","",INDEX('Per Line'!$G$2:$G$6001,$V4)&"") | F4: =IF($V4="","",INDEX('Per Line'!$H$2:$H$6001,$V4)&"") | G4: =IF($V4="","",INDEX('Per Line'!$I$2:$I$6001,$V4)&"") | H4: =IF($V4="","",INDEX('Per Line'!$J$2:$J$6001,$V4)) | I4: =IF($V4="","",H4*S4/100) | J4: =IF($V4="","",INDEX('Per Line'!$S$2:$S$6001,$V4)&"") | K4: =IF($V4="","",SUMIFS('Per Line'!$R$2:$R$6001,'Per Line'!$C$2:$C$6001,$B4,'Per Line'!$AJ$2:$AJ$6001,1)) | L4: =IF($V4="","",Settings!$C$7) | M4: =IF($V4="","",SUMIFS('Per Line'!$R$2:$R$6001,'Per Line'!$C$2:$C$6001,$B4,'Per Line'!$AI$2:$AI$6001,0,'Per Line'!$AJ$2:$AJ$6001,0)) | N4: =IF($V4="","",M4*L4) | O4: =IF($V4="","",Settings!$C$6) | P4: =IF($V4="","",SUMIFS('Per Line'!$R$2:$R$6001,'Per Line'!$C$2:$C$6001,$B4,'Per Line'!$AI$2:$AI$6001,1,'Per Line'!$AJ$2:$AJ$6001,0)) | Q4: =IF($V4="","",P4*O4) | R4: =IF($V4="","",Q4+N4) | S4: =IF($V4="","",T4-R4) | T4: =IF($V4="","",M4+P4+K4) | U4: =IF($V4="","",T4-R4-I4) | V4: =IF(ROWS($V$2:$V4)<=MAX('Per Line'!$AH$2:$AH$6001),MATCH(ROWS($V$2:$V4),'Per Line'!$AH$2:$AH$6001,0),"")
B5: =IF($V5="","",INDEX('Per Line'!$C$2:$C$6001,$V5)&"") | C5: =IF($V5="","",INDEX('Per Line'!$D$2:$D$6001,$V5)) | D5: =IF($V5="","",INDEX('Per Line'!$E$2:$E$6001,$V5)&"") | E5: =IF($V5="","",INDEX('Per Line'!$G$2:$G$6001,$V5)&"") | F5: =IF($V5="","",INDEX('Per Line'!$H$2:$H$6001,$V5)&"") | G5: =IF($V5="","",INDEX('Per Line'!$I$2:$I$6001,$V5)&"") | H5: =IF($V5="","",INDEX('Per Line'!$J$2:$J$6001,$V5)) | I5: =IF($V5="","",H5*S5/100) | J5: =IF($V5="","",INDEX('Per Line'!$S$2:$S$6001,$V5)&"") | K5: =IF($V5="","",SUMIFS('Per Line'!$R$2:$R$6001,'Per Line'!$C$2:$C$6001,$B5,'Per Line'!$AJ$2:$AJ$6001,1)) | L5: =IF($V5="","",Settings!$C$7) | M5: =IF($V5="","",SUMIFS('Per Line'!$R$2:$R$6001,'Per Line'!$C$2:$C$6001,$B5,'Per Line'!$AI$2:$AI$6001,0,'Per Line'!$AJ$2:$AJ$6001,0)) | N5: =IF($V5="","",M5*L5) | O5: =IF($V5="","",Settings!$C$6) | P5: =IF($V5="","",SUMIFS('Per Line'!$R$2:$R$6001,'Per Line'!$C$2:$C$6001,$B5,'Per Line'!$AI$2:$AI$6001,1,'Per Line'!$AJ$2:$AJ$6001,0)) | Q5: =IF($V5="","",P5*O5) | R5: =IF($V5="","",Q5+N5) | S5: =IF($V5="","",T5-R5) | T5: =IF($V5="","",M5+P5+K5) | U5: =IF($V5="","",T5-R5-I5) | V5: =IF(ROWS($V$2:$V5)<=MAX('Per Line'!$AH$2:$AH$6001),MATCH(ROWS($V$2:$V5),'Per Line'!$AH$2:$AH$6001,0),"")
B6: =IF($V6="","",INDEX('Per Line'!$C$2:$C$6001,$V6)&"") | C6: =IF($V6="","",INDEX('Per Line'!$D$2:$D$6001,$V6)) | D6: =IF($V6="","",INDEX('Per Line'!$E$2:$E$6001,$V6)&"") | E6: =IF($V6="","",INDEX('Per Line'!$G$2:$G$6001,$V6)&"") | F6: =IF($V6="","",INDEX('Per Line'!$H$2:$H$6001,$V6)&"") | G6: =IF($V6="","",INDEX('Per Line'!$I$2:$I$6001,$V6)&"") | H6: =IF($V6="","",INDEX('Per Line'!$J$2:$J$6001,$V6)) | I6: =IF($V6="","",H6*S6/100) | J6: =IF($V6="","",INDEX('Per Line'!$S$2:$S$6001,$V6)&"") | K6: =IF($V6="","",SUMIFS('Per Line'!$R$2:$R$6001,'Per Line'!$C$2:$C$6001,$B6,'Per Line'!$AJ$2:$AJ$6001,1)) | L6: =IF($V6="","",Settings!$C$7) | M6: =IF($V6="","",SUMIFS('Per Line'!$R$2:$R$6001,'Per Line'!$C$2:$C$6001,$B6,'Per Line'!$AI$2:$AI$6001,0,'Per Line'!$AJ$2:$AJ$6001,0)) | N6: =IF($V6="","",M6*L6) | O6: =IF($V6="","",Settings!$C$6) | P6: =IF($V6="","",SUMIFS('Per Line'!$R$2:$R$6001,'Per Line'!$C$2:$C$6001,$B6,'Per Line'!$AI$2:$AI$6001,1,'Per Line'!$AJ$2:$AJ$6001,0)) | Q6: =IF($V6="","",P6*O6) | R6: =IF($V6="","",Q6+N6) | S6: =IF($V6="","",T6-R6) | T6: =IF($V6="","",M6+P6+K6) | U6: =IF($V6="","",T6-R6-I6) | V6: =IF(ROWS($V$2:$V6)<=MAX('Per Line'!$AH$2:$AH$6001),MATCH(ROWS($V$2:$V6),'Per Line'!$AH$2:$AH$6001,0),"")
B7: =IF($V7="","",INDEX('Per Line'!$C$2:$C$6001,$V7)&"") | C7: =IF($V7="","",INDEX('Per Line'!$D$2:$D$6001,$V7)) | D7: =IF($V7="","",INDEX('Per Line'!$E$2:$E$6001,$V7)&"") | E7: =IF($V7="","",INDEX('Per Line'!$G$2:$G$6001,$V7)&"") | F7: =IF($V7="","",INDEX('Per Line'!$H$2:$H$6001,$V7)&"") | G7: =IF($V7="","",INDEX('Per Line'!$I$2:$I$6001,$V7)&"") | H7: =IF($V7="","",INDEX('Per Line'!$J$2:$J$6001,$V7)) | I7: =IF($V7="","",H7*S7/100) | J7: =IF($V7="","",INDEX('Per Line'!$S$2:$S$6001,$V7)&"") | K7: =IF($V7="","",SUMIFS('Per Line'!$R$2:$R$6001,'Per Line'!$C$2:$C$6001,$B7,'Per Line'!$AJ$2:$AJ$6001,1)) | L7: =IF($V7="","",Settings!$C$7) | M7: =IF($V7="","",SUMIFS('Per Line'!$R$2:$R$6001,'Per Line'!$C$2:$C$6001,$B7,'Per Line'!$AI$2:$AI$6001,0,'Per Line'!$AJ$2:$AJ$6001,0)) | N7: =IF($V7="","",M7*L7) | O7: =IF($V7="","",Settings!$C$6) | P7: =IF($V7="","",SUMIFS('Per Line'!$R$2:$R$6001,'Per Line'!$C$2:$C$6001,$B7,'Per Line'!$AI$2:$AI$6001,1,'Per Line'!$AJ$2:$AJ$6001,0)) | Q7: =IF($V7="","",P7*O7) | R7: =IF($V7="","",Q7+N7) | S7: =IF($V7="","",T7-R7) | T7: =IF($V7="","",M7+P7+K7) | U7: =IF($V7="","",T7-R7-I7) | V7: =IF(ROWS($V$2:$V7)<=MAX('Per Line'!$AH$2:$AH$6001),MATCH(ROWS($V$2:$V7),'Per Line'!$AH$2:$AH$6001,0),"")
B8: =IF($V8="","",INDEX('Per Line'!$C$2:$C$6001,$V8)&"") | C8: =IF($V8="","",INDEX('Per Line'!$D$2:$D$6001,$V8)) | D8: =IF($V8="","",INDEX('Per Line'!$E$2:$E$6001,$V8)&"") | E8: =IF($V8="","",INDEX('Per Line'!$G$2:$G$6001,$V8)&"") | F8: =IF($V8="","",INDEX('Per Line'!$H$2:$H$6001,$V8)&"") | G8: =IF($V8="","",INDEX('Per Line'!$I$2:$I$6001,$V8)&"") | H8: =IF($V8="","",INDEX('Per Line'!$J$2:$J$6001,$V8)) | I8: =IF($V8="","",H8*S8/100) | J8: =IF($V8="","",INDEX('Per Line'!$S$2:$S$6001,$V8)&"") | K8: =IF($V8="","",SUMIFS('Per Line'!$R$2:$R$6001,'Per Line'!$C$2:$C$6001,$B8,'Per Line'!$AJ$2:$AJ$6001,1)) | L8: =IF($V8="","",Settings!$C$7) | M8: =IF($V8="","",SUMIFS('Per Line'!$R$2:$R$6001,'Per Line'!$C$2:$C$6001,$B8,'Per Line'!$AI$2:$AI$6001,0,'Per Line'!$AJ$2:$AJ$6001,0)) | N8: =IF($V8="","",M8*L8) | O8: =IF($V8="","",Settings!$C$6) | P8: =IF($V8="","",SUMIFS('Per Line'!$R$2:$R$6001,'Per Line'!$C$2:$C$6001,$B8,'Per Line'!$AI$2:$AI$6001,1,'Per Line'!$AJ$2:$AJ$6001,0)) | Q8: =IF($V8="","",P8*O8) | R8: =IF($V8="","",Q8+N8) | S8: =IF($V8="","",T8-R8) | T8: =IF($V8="","",M8+P8+K8) | U8: =IF($V8="","",T8-R8-I8) | V8: =IF(ROWS($V$2:$V8)<=MAX('Per Line'!$AH$2:$AH$6001),MATCH(ROWS($V$2:$V8),'Per Line'!$AH$2:$AH$6001,0),"")
B9: =IF($V9="","",INDEX('Per Line'!$C$2:$C$6001,$V9)&"") | C9: =IF($V9="","",INDEX('Per Line'!$D$2:$D$6001,$V9)) | D9: =IF($V9="","",INDEX('Per Line'!$E$2:$E$6001,$V9)&"") | E9: =IF($V9="","",INDEX('Per Line'!$G$2:$G$6001,$V9)&"") | F9: =IF($V9="","",INDEX('Per Line'!$H$2:$H$6001,$V9)&"") | G9: =IF($V9="","",INDEX('Per Line'!$I$2:$I$6001,$V9)&"") | H9: =IF($V9="","",INDEX('Per Line'!$J$2:$J$6001,$V9)) | I9: =IF($V9="","",H9*S9/100) | J9: =IF($V9="","",INDEX('Per Line'!$S$2:$S$6001,$V9)&"") | K9: =IF($V9="","",SUMIFS('Per Line'!$R$2:$R$6001,'Per Line'!$C$2:$C$6001,$B9,'Per Line'!$AJ$2:$AJ$6001,1)) | L9: =IF($V9="","",Settings!$C$7) | M9: =IF($V9="","",SUMIFS('Per Line'!$R$2:$R$6001,'Per Line'!$C$2:$C$6001,$B9,'Per Line'!$AI$2:$AI$6001,0,'Per Line'!$AJ$2:$AJ$6001,0)) | N9: =IF($V9="","",M9*L9) | O9: =IF($V9="","",Settings!$C$6) | P9: =IF($V9="","",SUMIFS('Per Line'!$R$2:$R$6001,'Per Line'!$C$2:$C$6001,$B9,'Per Line'!$AI$2:$AI$6001,1,'Per Line'!$AJ$2:$AJ$6001,0)) | Q9: =IF($V9="","",P9*O9) | R9: =IF($V9="","",Q9+N9) | S9: =IF($V9="","",T9-R9) | T9: =IF($V9="","",M9+P9+K9) | U9: =IF($V9="","",T9-R9-I9) | V9: =IF(ROWS($V$2:$V9)<=MAX('Per Line'!$AH$2:$AH$6001),MATCH(ROWS($V$2:$V9),'Per Line'!$AH$2:$AH$6001,0),"")
B10: =IF($V10="","",INDEX('Per Line'!$C$2:$C$6001,$V10)&"") | C10: =IF($V10="","",INDEX('Per Line'!$D$2:$D$6001,$V10)) | D10: =IF($V10="","",INDEX('Per Line'!$E$2:$E$6001,$V10)&"") | E10: =IF($V10="","",INDEX('Per Line'!$G$2:$G$6001,$V10)&"") | F10: =IF($V10="","",INDEX('Per Line'!$H$2:$H$6001,$V10)&"") | G10: =IF($V10="","",INDEX('Per Line'!$I$2:$I$6001,$V10)&"") | H10: =IF($V10="","",INDEX('Per Line'!$J$2:$J$6001,$V10)) | I10: =IF($V10="","",H10*S10/100) | J10: =IF($V10="","",INDEX('Per Line'!$S$2:$S$6001,$V10)&"") | K10: =IF($V10="","",SUMIFS('Per Line'!$R$2:$R$6001,'Per Line'!$C$2:$C$6001,$B10,'Per Line'!$AJ$2:$AJ$6001,1)) | L10: =IF($V10="","",Settings!$C$7) | M10: =IF($V10="","",SUMIFS('Per Line'!$R$2:$R$6001,'Per Line'!$C$2:$C$6001,$B10,'Per Line'!$AI$2:$AI$6001,0,'Per Line'!$AJ$2:$AJ$6001,0)) | N10: =IF($V10="","",M10*L10) | O10: =IF($V10="","",Settings!$C$6) | P10: =IF($V10="","",SUMIFS('Per Line'!$R$2:$R$6001,'Per Line'!$C$2:$C$6001,$B10,'Per Line'!$AI$2:$AI$6001,1,'Per Line'!$AJ$2:$AJ$6001,0)) | Q10: =IF($V10="","",P10*O10) | R10: =IF($V10="","",Q10+N10) | S10: =IF($V10="","",T10-R10) | T10: =IF($V10="","",M10+P10+K10) | U10: =IF($V10="","",T10-R10-I10) | V10: =IF(ROWS($V$2:$V10)<=MAX('Per Line'!$AH$2:$AH$6001),MATCH(ROWS($V$2:$V10),'Per Line'!$AH$2:$AH$6001,0),"")
B11: =IF($V11="","",INDEX('Per Line'!$C$2:$C$6001,$V11)&"") | C11: =IF($V11="","",INDEX('Per Line'!$D$2:$D$6001,$V11)) | D11: =IF($V11="","",INDEX('Per Line'!$E$2:$E$6001,$V11)&"") | E11: =IF($V11="","",INDEX('Per Line'!$G$2:$G$6001,$V11)&"") | F11: =IF($V11="","",INDEX('Per Line'!$H$2:$H$6001,$V11)&"") | G11: =IF($V11="","",INDEX('Per Line'!$I$2:$I$6001,$V11)&"") | H11: =IF($V11="","",INDEX('Per Line'!$J$2:$J$6001,$V11)) | I11: =IF($V11="","",H11*S11/100) | J11: =IF($V11="","",INDEX('Per Line'!$S$2:$S$6001,$V11)&"") | K11: =IF($V11="","",SUMIFS('Per Line'!$R$2:$R$6001,'Per Line'!$C$2:$C$6001,$B11,'Per Line'!$AJ$2:$AJ$6001,1)) | L11: =IF($V11="","",Settings!$C$7) | M11: =IF($V11="","",SUMIFS('Per Line'!$R$2:$R$6001,'Per Line'!$C$2:$C$6001,$B11,'Per Line'!$AI$2:$AI$6001,0,'Per Line'!$AJ$2:$AJ$6001,0)) | N11: =IF($V11="","",M11*L11) | O11: =IF($V11="","",Settings!$C$6) | P11: =IF($V11="","",SUMIFS('Per Line'!$R$2:$R$6001,'Per Line'!$C$2:$C$6001,$B11,'Per Line'!$AI$2:$AI$6001,1,'Per Line'!$AJ$2:$AJ$6001,0)) | Q11: =IF($V11="","",P11*O11) | R11: =IF($V11="","",Q11+N11) | S11: =IF($V11="","",T11-R11) | T11: =IF($V11="","",M11+P11+K11) | U11: =IF($V11="","",T11-R11-I11) | V11: =IF(ROWS($V$2:$V11)<=MAX('Per Line'!$AH$2:$AH$6001),MATCH(ROWS($V$2:$V11),'Per Line'!$AH$2:$AH$6001,0),"")
B12: =IF($V12="","",INDEX('Per Line'!$C$2:$C$6001,$V12)&"") | C12: =IF($V12="","",INDEX('Per Line'!$D$2:$D$6001,$V12)) | D12: =IF($V12="","",INDEX('Per Line'!$E$2:$E$6001,$V12)&"") | E12: =IF($V12="","",INDEX('Per Line'!$G$2:$G$6001,$V12)&"") | F12: =IF($V12="","",INDEX('Per Line'!$H$2:$H$6001,$V12)&"") | G12: =IF($V12="","",INDEX('Per Line'!$I$2:$I$6001,$V12)&"") | H12: =IF($V12="","",INDEX('Per Line'!$J$2:$J$6001,$V12)) | I12: =IF($V12="","",H12*S12/100) | J12: =IF($V12="","",INDEX('Per Line'!$S$2:$S$6001,$V12)&"") | K12: =IF($V12="","",SUMIFS('Per Line'!$R$2:$R$6001,'Per Line'!$C$2:$C$6001,$B12,'Per Line'!$AJ$2:$AJ$6001,1)) | L12: =IF($V12="","",Settings!$C$7) | M12: =IF($V12="","",SUMIFS('Per Line'!$R$2:$R$6001,'Per Line'!$C$2:$C$6001,$B12,'Per Line'!$AI$2:$AI$6001,0,'Per Line'!$AJ$2:$AJ$6001,0)) | N12: =IF($V12="","",M12*L12) | O12: =IF($V12="","",Settings!$C$6) | P12: =IF($V12="","",SUMIFS('Per Line'!$R$2:$R$6001,'Per Line'!$C$2:$C$6001,$B12,'Per Line'!$AI$2:$AI$6001,1,'Per Line'!$AJ$2:$AJ$6001,0)) | Q12: =IF($V12="","",P12*O12) | R12: =IF($V12="","",Q12+N12) | S12: =IF($V12="","",T12-R12) | T12: =IF($V12="","",M12+P12+K12) | U12: =IF($V12="","",T12-R12-I12) | V12: =IF(ROWS($V$2:$V12)<=MAX('Per Line'!$AH$2:$AH$6001),MATCH(ROWS($V$2:$V12),'Per Line'!$AH$2:$AH$6001,0),"")
B13: =IF($V13="","",INDEX('Per Line'!$C$2:$C$6001,$V13)&"") | C13: =IF($V13="","",INDEX('Per Line'!$D$2:$D$6001,$V13)) | D13: =IF($V13="","",INDEX('Per Line'!$E$2:$E$6001,$V13)&"") | E13: =IF($V13="","",INDEX('Per Line'!$G$2:$G$6001,$V13)&"") | F13: =IF($V13="","",INDEX('Per Line'!$H$2:$H$6001,$V13)&"") | G13: =IF($V13="","",INDEX('Per Line'!$I$2:$I$6001,$V13)&"") | H13: =IF($V13="","",INDEX('Per Line'!$J$2:$J$6001,$V13)) | I13: =IF($V13="","",H13*S13/100) | J13: =IF($V13="","",INDEX('Per Line'!$S$2:$S$6001,$V13)&"") | K13: =IF($V13="","",SUMIFS('Per Line'!$R$2:$R$6001,'Per Line'!$C$2:$C$6001,$B13,'Per Line'!$AJ$2:$AJ$6001,1)) | L13: =IF($V13="","",Settings!$C$7) | M13: =IF($V13="","",SUMIFS('Per Line'!$R$2:$R$6001,'Per Line'!$C$2:$C$6001,$B13,'Per Line'!$AI$2:$AI$6001,0,'Per Line'!$AJ$2:$AJ$6001,0)) | N13: =IF($V13="","",M13*L13) | O13: =IF($V13="","",Settings!$C$6) | P13: =IF($V13="","",SUMIFS('Per Line'!$R$2:$R$6001,'Per Line'!$C$2:$C$6001,$B13,'Per Line'!$AI$2:$AI$6001,1,'Per Line'!$AJ$2:$AJ$6001,0)) | Q13: =IF($V13="","",P13*O13) | R13: =IF($V13="","",Q13+N13) | S13: =IF($V13="","",T13-R13) | T13: =IF($V13="","",M13+P13+K13) | U13: =IF($V13="","",T13-R13-I13) | V13: =IF(ROWS($V$2:$V13)<=MAX('Per Line'!$AH$2:$AH$6001),MATCH(ROWS($V$2:$V13),'Per Line'!$AH$2:$AH$6001,0),"")
... B1201: =IF($V1201="","",INDEX('Per Line'!$C$2:$C$6001,$V1201)&"") | C1201: =IF($V1201="","",INDEX('Per Line'!$D$2:$D$6001,$V1201)) | D1201: =IF($V1201="","",INDEX('Per Line'!$E$2:$E$6001,$V1201)&"") | E1201: =IF($V1201="","",INDEX('Per Line'!$G$2:$G$6001,$V1201)&"") | F1201: =IF($V1201="","",INDEX('Per Line'!$H$2:$H$6001,$V1201)&"") | G1201: =IF($V1201="","",INDEX('Per Line'!$I$2:$I$6001,$V1201)&"") | H1201: =IF($V1201="","",INDEX('Per Line'!$J$2:$J$6001,$V1201)) | I1201: =IF($V1201="","",H1201*S1201/100) | J1201: =IF($V1201="","",INDEX('Per Line'!$S$2:$S$6001,$V1201)&"") | K1201: =IF($V1201="","",SUMIFS('Per Line'!$R$2:$R$6001,'Per Line'!$C$2:$C$6001,$B1201,'Per Line'!$AJ$2:$AJ$6001,1)) | L1201: =IF($V1201="","",Settings!$C$7) | M1201: =IF($V1201="","",SUMIFS('Per Line'!$R$2:$R$6001,'Per Line'!$C$2:$C$6001,$B1201,'Per Line'!$AI$2:$AI$6001,0,'Per Line'!$AJ$2:$AJ$6001,0)) | N1201: =IF($V1201="","",M1201*L1201) | O1201: =IF($V1201="","",Settings!$C$6) | P1201: =IF($V1201="","",SUMIFS('Per Line'!$R$2:$R$6001,'Per Line'!$C$2:$C$6001,$B1201,'Per Line'!$AI$2:$AI$6001,1,'Per Line'!$AJ$2:$AJ$6001,0)) | Q1201: =IF($V1201="","",P1201*O1201) | R1201: =IF($V1201="","",Q1201+N1201) | S1201: =IF($V1201="","",T1201-R1201) | T1201: =IF($V1201="","",M1201+P1201+K1201) | U1201: =IF($V1201="","",T1201-R1201-I1201) | V1201: =IF(ROWS($V$2:$V1201)<=MAX('Per Line'!$AH$2:$AH$6001),MATCH(ROWS($V$2:$V1201),'Per Line'!$AH$2:$AH$6001,0),"")
