Workbook

Sheet How To Use
A1: Claims Template - AHLY MEDICAL (Chronic)
A3: Monthly steps
A4: 1. Open the 'Per Line' tab. Delete the old data in the BLUE columns only (row 2 down). Never delete the green or grey columns.
A5: 2. Paste the new month's data as VALUES starting at A2, into the blue columns: B-Q, S-Y, AC-AD, AF (same order as the system export).
A6: 3. Green columns (A, R, Z, AA, AB, AE) and the grey helper columns (AG-AL) calculate automatically - do not paste over them.
A7: 4. 'Per Invoice' fills itself from 'Per Line' (one row per Order #, split into IMP / Local). No pivot table, no refresh.
A8: 5. The columns you type yourself in 'Per Invoice' (blue headers): A 'Invoice', X 'comment'. Everything else is formula. Type them AFTER pasting the month data (they follow the row, not the order).
A9: 6. Open 'Settings' and check STATUS says OK (Per Line totals = Per Invoice totals).
A11: Colour legend
A12: Blue header = typed/pasted by you (raw data, and 'Invoice' in Per Invoice). Green header = formula (do not paste over). Grey header = helper formula (do not touch). Yellow cell (Settings) = editable rate.
A14: Calculation rules (taken from the September 2026 sheet)
A15: Co val = Order Co Payment x Total / 100. Discount = Total x Rebates / 100. Subtotal = Total - Discount. Net = Subtotal - Co val. (Total = 'Product Total')
... A20: Capacity: up to 8,000 lines and 2,000 invoices per month. A line with an empty Order # is ignored.

Sheet Settings
B1: Company settings & checks
B3: Insurance Company | C3: AHLY MEDICAL | D3: Informational only
B4: Corporate | C4: ABE - Dokki; ABE - Dokki - VIP; Egypt Air amc; ABE - Sabry Abo Alam; ABE - Tahrir; ABE - Tahrir - VIP; ABE - Sabry Abo Alam - VIP; AMC - Individual | D4: Informational only
B5: Sheet type | C5: Chronic | D5: Informational only
B6: Local products rebate % | C6: 0.14 | D6: Source: Sep sheet (Rebates = 14 on Local lines, 0 on Special Rebates = Yes).
B7: Imported (IMP) products rebate % | C7: 0.06 | D7: Source: Sep sheet (Rebates = 6 on non-local lines).
B9: Month totals / reconciliation
B10: Lines loaded | C10: =COUNTA('Per Line'!$F$2:$F$8001)
B11: Invoices (unique Order # + Approval Ref) | C11: =MAX('Per Line'!$AI$2:$AI$8001)
B12: Invoices shown in Per Invoice | C12: =SUMPRODUCT(--('Per Invoice'!$B$2:$B$2001<>""))
B13: Grand Total - Per Line (Product Total) | C13: =SUM('Per Line'!$Y$2:$Y$8001)
B14: Grand Total - Per Invoice | C14: =SUM('Per Invoice'!$V$2:$V$2001)
B15: Discount - Per Line | C15: =SUM('Per Line'!$Z$2:$Z$8001)
B16: Discount - Per Invoice | C16: =SUM('Per Invoice'!$T$2:$T$2001)
B17: Co val - Per Line | C17: =SUM('Per Line'!$R$2:$R$8001)
B18: Co val - Per Invoice | C18: =SUM('Per Invoice'!$K$2:$K$2001)
B19: Net - Per Line | C19: =SUM('Per Line'!$AB$2:$AB$8001)
B20: Net - Per Invoice | C20: =SUM('Per Invoice'!$W$2:$W$2001)
B21: Max Limit adjustment (Co val, Per Invoice only) | C21: 0 | D21: This company's Per Invoice has no Max Limit rule.
B23: STATUS | C23: =IF(C10=0,"No data loaded",IF(COUNTA('Per Line'!$F:$F)-1>8000,"TOO MANY LINES - extend template",IF(C11>2000,"TOO MANY INVOICES - extend template",IF(AND(ROUND(C13-C14,2)=0,ROUND(C15-C16,2)=0,ROUND(C17+C21-C18,2)=0,ROUND(C19-C21-C20,2)=0,C11=C12),"OK","CHECK - Per Line and Per Invoice do not match")))) | D23: Must say OK after you paste the month data.

Sheet Per Line
A1: INV | B1: Ticket # | C1: Stage | D1: Approval Ref | E1: Approval Stage | F1: Order # | G1: Channel | H1: Create At | I1: Insurance Company | J1: Country Portal ID | K1: Corporate | L1: Card | M1: Name | N1: Status | O1: Local Rebates | P1: Imported Rebates | Q1: Order Co Payment | R1: Co val | S1: heisenberg id | T1: Product Name | U1: Local | V1: Unit | W1: Quantity | X1: Unit Price | Y1: Product Total | Z1: Discount | AA1: Subtotal | AB1: Net | AC1: ERX ID | AD1: Special Rebates? | AE1: Rebates | AF1: Approval Type | AG1: Invoice Key (helper) | AH1: Order 1st Row (helper) | AI1: Invoice # (helper) | AJ1: Is Local (helper) | AK1: Is Special (helper) | AL1: Sort Key (helper)
A2: =IF($F2="","",IFERROR(IF(INDEX('Per Invoice'!$A$2:$A$2001,MATCH($F2,'Per Invoice'!$B$2:$B$2001,0))=0,"",INDEX('Per Invoice'!$A$2:$A$2001,MATCH($F2,'Per Invoice'!$B$2:$B$2001,0))),"")) | R2: =IF($F2="","",Q2*Y2/100) | Z2: =IF($F2="","",Y2*AE2/100) | AA2: =IF($F2="","",Y2-Z2) | AB2: =IF($F2="","",AA2-R2) | AE2: =IF($F2="","",IF($AK2=1,0,IF($AJ2=1,Settings!$C$6,Settings!$C$7))*100) | AG2: =IF($F2="","",$F2&"|"&$D2&"") | AH2: =IF($F2="","",IF(COUNTIF($AG$2:$AG2,$AG2)=1,1,0)) | AI2: =IF($AH2=1,SUMPRODUCT(--($AL$2:$AL$8001<$AL2))+1,"") | AJ2: =IF($F2="","",IF(OR($U2=TRUE(),$U2="TRUE"),1,0)) | AK2: =IF($F2="","",IF($AD2="Yes",1,0)) | AL2: =IF($AH2=1,IFERROR(IF(VALUE($F2)<100000000,VALUE($F2),1000000000),IFERROR(IF(VALUE(MID($F2,2,20))<100000000,VALUE(MID($F2,2,20)),1000000000),1000000000))+ROW()/100000,"")
A3: =IF($F3="","",IFERROR(IF(INDEX('Per Invoice'!$A$2:$A$2001,MATCH($F3,'Per Invoice'!$B$2:$B$2001,0))=0,"",INDEX('Per Invoice'!$A$2:$A$2001,MATCH($F3,'Per Invoice'!$B$2:$B$2001,0))),"")) | R3: =IF($F3="","",Q3*Y3/100) | Z3: =IF($F3="","",Y3*AE3/100) | AA3: =IF($F3="","",Y3-Z3) | AB3: =IF($F3="","",AA3-R3) | AE3: =IF($F3="","",IF($AK3=1,0,IF($AJ3=1,Settings!$C$6,Settings!$C$7))*100) | AG3: =IF($F3="","",$F3&"|"&$D3&"") | AH3: =IF($F3="","",IF(COUNTIF($AG$2:$AG3,$AG3)=1,1,0)) | AI3: =IF($AH3=1,SUMPRODUCT(--($AL$2:$AL$8001<$AL3))+1,"") | AJ3: =IF($F3="","",IF(OR($U3=TRUE(),$U3="TRUE"),1,0)) | AK3: =IF($F3="","",IF($AD3="Yes",1,0)) | AL3: =IF($AH3=1,IFERROR(IF(VALUE($F3)<100000000,VALUE($F3),1000000000),IFERROR(IF(VALUE(MID($F3,2,20))<100000000,VALUE(MID($F3,2,20)),1000000000),1000000000))+ROW()/100000,"")
A4: =IF($F4="","",IFERROR(IF(INDEX('Per Invoice'!$A$2:$A$2001,MATCH($F4,'Per Invoice'!$B$2:$B$2001,0))=0,"",INDEX('Per Invoice'!$A$2:$A$2001,MATCH($F4,'Per Invoice'!$B$2:$B$2001,0))),"")) | R4: =IF($F4="","",Q4*Y4/100) | Z4: =IF($F4="","",Y4*AE4/100) | AA4: =IF($F4="","",Y4-Z4) | AB4: =IF($F4="","",AA4-R4) | AE4: =IF($F4="","",IF($AK4=1,0,IF($AJ4=1,Settings!$C$6,Settings!$C$7))*100) | AG4: =IF($F4="","",$F4&"|"&$D4&"") | AH4: =IF($F4="","",IF(COUNTIF($AG$2:$AG4,$AG4)=1,1,0)) | AI4: =IF($AH4=1,SUMPRODUCT(--($AL$2:$AL$8001<$AL4))+1,"") | AJ4: =IF($F4="","",IF(OR($U4=TRUE(),$U4="TRUE"),1,0)) | AK4: =IF($F4="","",IF($AD4="Yes",1,0)) | AL4: =IF($AH4=1,IFERROR(IF(VALUE($F4)<100000000,VALUE($F4),1000000000),IFERROR(IF(VALUE(MID($F4,2,20))<100000000,VALUE(MID($F4,2,20)),1000000000),1000000000))+ROW()/100000,"")
A5: =IF($F5="","",IFERROR(IF(INDEX('Per Invoice'!$A$2:$A$2001,MATCH($F5,'Per Invoice'!$B$2:$B$2001,0))=0,"",INDEX('Per Invoice'!$A$2:$A$2001,MATCH($F5,'Per Invoice'!$B$2:$B$2001,0))),"")) | R5: =IF($F5="","",Q5*Y5/100) | Z5: =IF($F5="","",Y5*AE5/100) | AA5: =IF($F5="","",Y5-Z5) | AB5: =IF($F5="","",AA5-R5) | AE5: =IF($F5="","",IF($AK5=1,0,IF($AJ5=1,Settings!$C$6,Settings!$C$7))*100) | AG5: =IF($F5="","",$F5&"|"&$D5&"") | AH5: =IF($F5="","",IF(COUNTIF($AG$2:$AG5,$AG5)=1,1,0)) | AI5: =IF($AH5=1,SUMPRODUCT(--($AL$2:$AL$8001<$AL5))+1,"") | AJ5: =IF($F5="","",IF(OR($U5=TRUE(),$U5="TRUE"),1,0)) | AK5: =IF($F5="","",IF($AD5="Yes",1,0)) | AL5: =IF($AH5=1,IFERROR(IF(VALUE($F5)<100000000,VALUE($F5),1000000000),IFERROR(IF(VALUE(MID($F5,2,20))<100000000,VALUE(MID($F5,2,20)),1000000000),1000000000))+ROW()/100000,"")
A6: =IF($F6="","",IFERROR(IF(INDEX('Per Invoice'!$A$2:$A$2001,MATCH($F6,'Per Invoice'!$B$2:$B$2001,0))=0,"",INDEX('Per Invoice'!$A$2:$A$2001,MATCH($F6,'Per Invoice'!$B$2:$B$2001,0))),"")) | R6: =IF($F6="","",Q6*Y6/100) | Z6: =IF($F6="","",Y6*AE6/100) | AA6: =IF($F6="","",Y6-Z6) | AB6: =IF($F6="","",AA6-R6) | AE6: =IF($F6="","",IF($AK6=1,0,IF($AJ6=1,Settings!$C$6,Settings!$C$7))*100) | AG6: =IF($F6="","",$F6&"|"&$D6&"") | AH6: =IF($F6="","",IF(COUNTIF($AG$2:$AG6,$AG6)=1,1,0)) | AI6: =IF($AH6=1,SUMPRODUCT(--($AL$2:$AL$8001<$AL6))+1,"") | AJ6: =IF($F6="","",IF(OR($U6=TRUE(),$U6="TRUE"),1,0)) | AK6: =IF($F6="","",IF($AD6="Yes",1,0)) | AL6: =IF($AH6=1,IFERROR(IF(VALUE($F6)<100000000,VALUE($F6),1000000000),IFERROR(IF(VALUE(MID($F6,2,20))<100000000,VALUE(MID($F6,2,20)),1000000000),1000000000))+ROW()/100000,"")
A7: =IF($F7="","",IFERROR(IF(INDEX('Per Invoice'!$A$2:$A$2001,MATCH($F7,'Per Invoice'!$B$2:$B$2001,0))=0,"",INDEX('Per Invoice'!$A$2:$A$2001,MATCH($F7,'Per Invoice'!$B$2:$B$2001,0))),"")) | R7: =IF($F7="","",Q7*Y7/100) | Z7: =IF($F7="","",Y7*AE7/100) | AA7: =IF($F7="","",Y7-Z7) | AB7: =IF($F7="","",AA7-R7) | AE7: =IF($F7="","",IF($AK7=1,0,IF($AJ7=1,Settings!$C$6,Settings!$C$7))*100) | AG7: =IF($F7="","",$F7&"|"&$D7&"") | AH7: =IF($F7="","",IF(COUNTIF($AG$2:$AG7,$AG7)=1,1,0)) | AI7: =IF($AH7=1,SUMPRODUCT(--($AL$2:$AL$8001<$AL7))+1,"") | AJ7: =IF($F7="","",IF(OR($U7=TRUE(),$U7="TRUE"),1,0)) | AK7: =IF($F7="","",IF($AD7="Yes",1,0)) | AL7: =IF($AH7=1,IFERROR(IF(VALUE($F7)<100000000,VALUE($F7),1000000000),IFERROR(IF(VALUE(MID($F7,2,20))<100000000,VALUE(MID($F7,2,20)),1000000000),1000000000))+ROW()/100000,"")
A8: =IF($F8="","",IFERROR(IF(INDEX('Per Invoice'!$A$2:$A$2001,MATCH($F8,'Per Invoice'!$B$2:$B$2001,0))=0,"",INDEX('Per Invoice'!$A$2:$A$2001,MATCH($F8,'Per Invoice'!$B$2:$B$2001,0))),"")) | R8: =IF($F8="","",Q8*Y8/100) | Z8: =IF($F8="","",Y8*AE8/100) | AA8: =IF($F8="","",Y8-Z8) | AB8: =IF($F8="","",AA8-R8) | AE8: =IF($F8="","",IF($AK8=1,0,IF($AJ8=1,Settings!$C$6,Settings!$C$7))*100) | AG8: =IF($F8="","",$F8&"|"&$D8&"") | AH8: =IF($F8="","",IF(COUNTIF($AG$2:$AG8,$AG8)=1,1,0)) | AI8: =IF($AH8=1,SUMPRODUCT(--($AL$2:$AL$8001<$AL8))+1,"") | AJ8: =IF($F8="","",IF(OR($U8=TRUE(),$U8="TRUE"),1,0)) | AK8: =IF($F8="","",IF($AD8="Yes",1,0)) | AL8: =IF($AH8=1,IFERROR(IF(VALUE($F8)<100000000,VALUE($F8),1000000000),IFERROR(IF(VALUE(MID($F8,2,20))<100000000,VALUE(MID($F8,2,20)),1000000000),1000000000))+ROW()/100000,"")
A9: =IF($F9="","",IFERROR(IF(INDEX('Per Invoice'!$A$2:$A$2001,MATCH($F9,'Per Invoice'!$B$2:$B$2001,0))=0,"",INDEX('Per Invoice'!$A$2:$A$2001,MATCH($F9,'Per Invoice'!$B$2:$B$2001,0))),"")) | R9: =IF($F9="","",Q9*Y9/100) | Z9: =IF($F9="","",Y9*AE9/100) | AA9: =IF($F9="","",Y9-Z9) | AB9: =IF($F9="","",AA9-R9) | AE9: =IF($F9="","",IF($AK9=1,0,IF($AJ9=1,Settings!$C$6,Settings!$C$7))*100) | AG9: =IF($F9="","",$F9&"|"&$D9&"") | AH9: =IF($F9="","",IF(COUNTIF($AG$2:$AG9,$AG9)=1,1,0)) | AI9: =IF($AH9=1,SUMPRODUCT(--($AL$2:$AL$8001<$AL9))+1,"") | AJ9: =IF($F9="","",IF(OR($U9=TRUE(),$U9="TRUE"),1,0)) | AK9: =IF($F9="","",IF($AD9="Yes",1,0)) | AL9: =IF($AH9=1,IFERROR(IF(VALUE($F9)<100000000,VALUE($F9),1000000000),IFERROR(IF(VALUE(MID($F9,2,20))<100000000,VALUE(MID($F9,2,20)),1000000000),1000000000))+ROW()/100000,"")
A10: =IF($F10="","",IFERROR(IF(INDEX('Per Invoice'!$A$2:$A$2001,MATCH($F10,'Per Invoice'!$B$2:$B$2001,0))=0,"",INDEX('Per Invoice'!$A$2:$A$2001,MATCH($F10,'Per Invoice'!$B$2:$B$2001,0))),"")) | R10: =IF($F10="","",Q10*Y10/100) | Z10: =IF($F10="","",Y10*AE10/100) | AA10: =IF($F10="","",Y10-Z10) | AB10: =IF($F10="","",AA10-R10) | AE10: =IF($F10="","",IF($AK10=1,0,IF($AJ10=1,Settings!$C$6,Settings!$C$7))*100) | AG10: =IF($F10="","",$F10&"|"&$D10&"") | AH10: =IF($F10="","",IF(COUNTIF($AG$2:$AG10,$AG10)=1,1,0)) | AI10: =IF($AH10=1,SUMPRODUCT(--($AL$2:$AL$8001<$AL10))+1,"") | AJ10: =IF($F10="","",IF(OR($U10=TRUE(),$U10="TRUE"),1,0)) | AK10: =IF($F10="","",IF($AD10="Yes",1,0)) | AL10: =IF($AH10=1,IFERROR(IF(VALUE($F10)<100000000,VALUE($F10),1000000000),IFERROR(IF(VALUE(MID($F10,2,20))<100000000,VALUE(MID($F10,2,20)),1000000000),1000000000))+ROW()/100000,"")
A11: =IF($F11="","",IFERROR(IF(INDEX('Per Invoice'!$A$2:$A$2001,MATCH($F11,'Per Invoice'!$B$2:$B$2001,0))=0,"",INDEX('Per Invoice'!$A$2:$A$2001,MATCH($F11,'Per Invoice'!$B$2:$B$2001,0))),"")) | R11: =IF($F11="","",Q11*Y11/100) | Z11: =IF($F11="","",Y11*AE11/100) | AA11: =IF($F11="","",Y11-Z11) | AB11: =IF($F11="","",AA11-R11) | AE11: =IF($F11="","",IF($AK11=1,0,IF($AJ11=1,Settings!$C$6,Settings!$C$7))*100) | AG11: =IF($F11="","",$F11&"|"&$D11&"") | AH11: =IF($F11="","",IF(COUNTIF($AG$2:$AG11,$AG11)=1,1,0)) | AI11: =IF($AH11=1,SUMPRODUCT(--($AL$2:$AL$8001<$AL11))+1,"") | AJ11: =IF($F11="","",IF(OR($U11=TRUE(),$U11="TRUE"),1,0)) | AK11: =IF($F11="","",IF($AD11="Yes",1,0)) | AL11: =IF($AH11=1,IFERROR(IF(VALUE($F11)<100000000,VALUE($F11),1000000000),IFERROR(IF(VALUE(MID($F11,2,20))<100000000,VALUE(MID($F11,2,20)),1000000000),1000000000))+ROW()/100000,"")
A12: =IF($F12="","",IFERROR(IF(INDEX('Per Invoice'!$A$2:$A$2001,MATCH($F12,'Per Invoice'!$B$2:$B$2001,0))=0,"",INDEX('Per Invoice'!$A$2:$A$2001,MATCH($F12,'Per Invoice'!$B$2:$B$2001,0))),"")) | R12: =IF($F12="","",Q12*Y12/100) | Z12: =IF($F12="","",Y12*AE12/100) | AA12: =IF($F12="","",Y12-Z12) | AB12: =IF($F12="","",AA12-R12) | AE12: =IF($F12="","",IF($AK12=1,0,IF($AJ12=1,Settings!$C$6,Settings!$C$7))*100) | AG12: =IF($F12="","",$F12&"|"&$D12&"") | AH12: =IF($F12="","",IF(COUNTIF($AG$2:$AG12,$AG12)=1,1,0)) | AI12: =IF($AH12=1,SUMPRODUCT(--($AL$2:$AL$8001<$AL12))+1,"") | AJ12: =IF($F12="","",IF(OR($U12=TRUE(),$U12="TRUE"),1,0)) | AK12: =IF($F12="","",IF($AD12="Yes",1,0)) | AL12: =IF($AH12=1,IFERROR(IF(VALUE($F12)<100000000,VALUE($F12),1000000000),IFERROR(IF(VALUE(MID($F12,2,20))<100000000,VALUE(MID($F12,2,20)),1000000000),1000000000))+ROW()/100000,"")
A13: =IF($F13="","",IFERROR(IF(INDEX('Per Invoice'!$A$2:$A$2001,MATCH($F13,'Per Invoice'!$B$2:$B$2001,0))=0,"",INDEX('Per Invoice'!$A$2:$A$2001,MATCH($F13,'Per Invoice'!$B$2:$B$2001,0))),"")) | R13: =IF($F13="","",Q13*Y13/100) | Z13: =IF($F13="","",Y13*AE13/100) | AA13: =IF($F13="","",Y13-Z13) | AB13: =IF($F13="","",AA13-R13) | AE13: =IF($F13="","",IF($AK13=1,0,IF($AJ13=1,Settings!$C$6,Settings!$C$7))*100) | AG13: =IF($F13="","",$F13&"|"&$D13&"") | AH13: =IF($F13="","",IF(COUNTIF($AG$2:$AG13,$AG13)=1,1,0)) | AI13: =IF($AH13=1,SUMPRODUCT(--($AL$2:$AL$8001<$AL13))+1,"") | AJ13: =IF($F13="","",IF(OR($U13=TRUE(),$U13="TRUE"),1,0)) | AK13: =IF($F13="","",IF($AD13="Yes",1,0)) | AL13: =IF($AH13=1,IFERROR(IF(VALUE($F13)<100000000,VALUE($F13),1000000000),IFERROR(IF(VALUE(MID($F13,2,20))<100000000,VALUE(MID($F13,2,20)),1000000000),1000000000))+ROW()/100000,"")
... A8001: =IF($F8001="","",IFERROR(IF(INDEX('Per Invoice'!$A$2:$A$2001,MATCH($F8001,'Per Invoice'!$B$2:$B$2001,0))=0,"",INDEX('Per Invoice'!$A$2:$A$2001,MATCH($F8001,'Per Invoice'!$B$2:$B$2001,0))),"")) | R8001: =IF($F8001="","",Q8001*Y8001/100) | Z8001: =IF($F8001="","",Y8001*AE8001/100) | AA8001: =IF($F8001="","",Y8001-Z8001) | AB8001: =IF($F8001="","",AA8001-R8001) | AE8001: =IF($F8001="","",IF($AK8001=1,0,IF($AJ8001=1,Settings!$C$6,Settings!$C$7))*100) | AG8001: =IF($F8001="","",$F8001&"|"&$D8001&"") | AH8001: =IF($F8001="","",IF(COUNTIF($AG$2:$AG8001,$AG8001)=1,1,0)) | AI8001: =IF($AH8001=1,SUMPRODUCT(--($AL$2:$AL$8001<$AL8001))+1,"") | AJ8001: =IF($F8001="","",IF(OR($U8001=TRUE(),$U8001="TRUE"),1,0)) | AK8001: =IF($F8001="","",IF($AD8001="Yes",1,0)) | AL8001: =IF($AH8001=1,IFERROR(IF(VALUE($F8001)<100000000,VALUE($F8001),1000000000),IFERROR(IF(VALUE(MID($F8001,2,20))<100000000,VALUE(MID($F8001,2,20)),1000000000),1000000000))+ROW()/100000,"")

Sheet Per Invoice
A1: Invoice | B1: Order # | C1: Approval Ref | D1: Ticket # | E1: Stage | F1: Channel | G1: Card | H1: Name | I1: Status | J1: Order Co Payment | K1: Co val | L1: Corporate | M1: sp rebets | N1: imp% | O1: imp | P1: impo val | Q1: local% | R1: local | S1: local val | T1: disc | U1: subtotal | V1: Grand Total | W1: net | X1: comment | Y1: Src Row (helper)
B2: =IF($Y2="","",INDEX('Per Line'!$F$2:$F$8001,$Y2)&"") | C2: =IF($Y2="","",INDEX('Per Line'!$D$2:$D$8001,$Y2)&"") | D2: =IF($Y2="","",INDEX('Per Line'!$B$2:$B$8001,$Y2)) | E2: =IF($Y2="","",INDEX('Per Line'!$C$2:$C$8001,$Y2)&"") | F2: =IF($Y2="","",INDEX('Per Line'!$G$2:$G$8001,$Y2)&"") | G2: =IF($Y2="","",INDEX('Per Line'!$L$2:$L$8001,$Y2)&"") | H2: =IF($Y2="","",INDEX('Per Line'!$M$2:$M$8001,$Y2)&"") | I2: =IF($Y2="","",INDEX('Per Line'!$N$2:$N$8001,$Y2)&"") | J2: =IF($Y2="","",INDEX('Per Line'!$Q$2:$Q$8001,$Y2)) | K2: =IF($Y2="","",J2*V2/100) | L2: =IF($Y2="","",INDEX('Per Line'!$K$2:$K$8001,$Y2)&"") | M2: =IF($Y2="","",SUMIFS('Per Line'!$Y$2:$Y$8001,'Per Line'!$AG$2:$AG$8001,$B2&"|"&$C2,'Per Line'!$AK$2:$AK$8001,1)) | N2: =IF($Y2="","",Settings!$C$7) | O2: =IF($Y2="","",SUMIFS('Per Line'!$Y$2:$Y$8001,'Per Line'!$AG$2:$AG$8001,$B2&"|"&$C2,'Per Line'!$AJ$2:$AJ$8001,0,'Per Line'!$AK$2:$AK$8001,0)) | P2: =IF($Y2="","",O2*N2) | Q2: =IF($Y2="","",Settings!$C$6) | R2: =IF($Y2="","",SUMIFS('Per Line'!$Y$2:$Y$8001,'Per Line'!$AG$2:$AG$8001,$B2&"|"&$C2,'Per Line'!$AJ$2:$AJ$8001,1,'Per Line'!$AK$2:$AK$8001,0)) | S2: =IF($Y2="","",R2*Q2) | T2: =IF($Y2="","",S2+P2) | U2: =IF($Y2="","",V2-T2) | V2: =IF($Y2="","",O2+R2+M2) | W2: =IF($Y2="","",V2-T2-K2) | Y2: =IF(ROWS($Y$2:$Y2)<=MAX('Per Line'!$AI$2:$AI$8001),MATCH(ROWS($Y$2:$Y2),'Per Line'!$AI$2:$AI$8001,0),"")
B3: =IF($Y3="","",INDEX('Per Line'!$F$2:$F$8001,$Y3)&"") | C3: =IF($Y3="","",INDEX('Per Line'!$D$2:$D$8001,$Y3)&"") | D3: =IF($Y3="","",INDEX('Per Line'!$B$2:$B$8001,$Y3)) | E3: =IF($Y3="","",INDEX('Per Line'!$C$2:$C$8001,$Y3)&"") | F3: =IF($Y3="","",INDEX('Per Line'!$G$2:$G$8001,$Y3)&"") | G3: =IF($Y3="","",INDEX('Per Line'!$L$2:$L$8001,$Y3)&"") | H3: =IF($Y3="","",INDEX('Per Line'!$M$2:$M$8001,$Y3)&"") | I3: =IF($Y3="","",INDEX('Per Line'!$N$2:$N$8001,$Y3)&"") | J3: =IF($Y3="","",INDEX('Per Line'!$Q$2:$Q$8001,$Y3)) | K3: =IF($Y3="","",J3*V3/100) | L3: =IF($Y3="","",INDEX('Per Line'!$K$2:$K$8001,$Y3)&"") | M3: =IF($Y3="","",SUMIFS('Per Line'!$Y$2:$Y$8001,'Per Line'!$AG$2:$AG$8001,$B3&"|"&$C3,'Per Line'!$AK$2:$AK$8001,1)) | N3: =IF($Y3="","",Settings!$C$7) | O3: =IF($Y3="","",SUMIFS('Per Line'!$Y$2:$Y$8001,'Per Line'!$AG$2:$AG$8001,$B3&"|"&$C3,'Per Line'!$AJ$2:$AJ$8001,0,'Per Line'!$AK$2:$AK$8001,0)) | P3: =IF($Y3="","",O3*N3) | Q3: =IF($Y3="","",Settings!$C$6) | R3: =IF($Y3="","",SUMIFS('Per Line'!$Y$2:$Y$8001,'Per Line'!$AG$2:$AG$8001,$B3&"|"&$C3,'Per Line'!$AJ$2:$AJ$8001,1,'Per Line'!$AK$2:$AK$8001,0)) | S3: =IF($Y3="","",R3*Q3) | T3: =IF($Y3="","",S3+P3) | U3: =IF($Y3="","",V3-T3) | V3: =IF($Y3="","",O3+R3+M3) | W3: =IF($Y3="","",V3-T3-K3) | Y3: =IF(ROWS($Y$2:$Y3)<=MAX('Per Line'!$AI$2:$AI$8001),MATCH(ROWS($Y$2:$Y3),'Per Line'!$AI$2:$AI$8001,0),"")
B4: =IF($Y4="","",INDEX('Per Line'!$F$2:$F$8001,$Y4)&"") | C4: =IF($Y4="","",INDEX('Per Line'!$D$2:$D$8001,$Y4)&"") | D4: =IF($Y4="","",INDEX('Per Line'!$B$2:$B$8001,$Y4)) | E4: =IF($Y4="","",INDEX('Per Line'!$C$2:$C$8001,$Y4)&"") | F4: =IF($Y4="","",INDEX('Per Line'!$G$2:$G$8001,$Y4)&"") | G4: =IF($Y4="","",INDEX('Per Line'!$L$2:$L$8001,$Y4)&"") | H4: =IF($Y4="","",INDEX('Per Line'!$M$2:$M$8001,$Y4)&"") | I4: =IF($Y4="","",INDEX('Per Line'!$N$2:$N$8001,$Y4)&"") | J4: =IF($Y4="","",INDEX('Per Line'!$Q$2:$Q$8001,$Y4)) | K4: =IF($Y4="","",J4*V4/100) | L4: =IF($Y4="","",INDEX('Per Line'!$K$2:$K$8001,$Y4)&"") | M4: =IF($Y4="","",SUMIFS('Per Line'!$Y$2:$Y$8001,'Per Line'!$AG$2:$AG$8001,$B4&"|"&$C4,'Per Line'!$AK$2:$AK$8001,1)) | N4: =IF($Y4="","",Settings!$C$7) | O4: =IF($Y4="","",SUMIFS('Per Line'!$Y$2:$Y$8001,'Per Line'!$AG$2:$AG$8001,$B4&"|"&$C4,'Per Line'!$AJ$2:$AJ$8001,0,'Per Line'!$AK$2:$AK$8001,0)) | P4: =IF($Y4="","",O4*N4) | Q4: =IF($Y4="","",Settings!$C$6) | R4: =IF($Y4="","",SUMIFS('Per Line'!$Y$2:$Y$8001,'Per Line'!$AG$2:$AG$8001,$B4&"|"&$C4,'Per Line'!$AJ$2:$AJ$8001,1,'Per Line'!$AK$2:$AK$8001,0)) | S4: =IF($Y4="","",R4*Q4) | T4: =IF($Y4="","",S4+P4) | U4: =IF($Y4="","",V4-T4) | V4: =IF($Y4="","",O4+R4+M4) | W4: =IF($Y4="","",V4-T4-K4) | Y4: =IF(ROWS($Y$2:$Y4)<=MAX('Per Line'!$AI$2:$AI$8001),MATCH(ROWS($Y$2:$Y4),'Per Line'!$AI$2:$AI$8001,0),"")
B5: =IF($Y5="","",INDEX('Per Line'!$F$2:$F$8001,$Y5)&"") | C5: =IF($Y5="","",INDEX('Per Line'!$D$2:$D$8001,$Y5)&"") | D5: =IF($Y5="","",INDEX('Per Line'!$B$2:$B$8001,$Y5)) | E5: =IF($Y5="","",INDEX('Per Line'!$C$2:$C$8001,$Y5)&"") | F5: =IF($Y5="","",INDEX('Per Line'!$G$2:$G$8001,$Y5)&"") | G5: =IF($Y5="","",INDEX('Per Line'!$L$2:$L$8001,$Y5)&"") | H5: =IF($Y5="","",INDEX('Per Line'!$M$2:$M$8001,$Y5)&"") | I5: =IF($Y5="","",INDEX('Per Line'!$N$2:$N$8001,$Y5)&"") | J5: =IF($Y5="","",INDEX('Per Line'!$Q$2:$Q$8001,$Y5)) | K5: =IF($Y5="","",J5*V5/100) | L5: =IF($Y5="","",INDEX('Per Line'!$K$2:$K$8001,$Y5)&"") | M5: =IF($Y5="","",SUMIFS('Per Line'!$Y$2:$Y$8001,'Per Line'!$AG$2:$AG$8001,$B5&"|"&$C5,'Per Line'!$AK$2:$AK$8001,1)) | N5: =IF($Y5="","",Settings!$C$7) | O5: =IF($Y5="","",SUMIFS('Per Line'!$Y$2:$Y$8001,'Per Line'!$AG$2:$AG$8001,$B5&"|"&$C5,'Per Line'!$AJ$2:$AJ$8001,0,'Per Line'!$AK$2:$AK$8001,0)) | P5: =IF($Y5="","",O5*N5) | Q5: =IF($Y5="","",Settings!$C$6) | R5: =IF($Y5="","",SUMIFS('Per Line'!$Y$2:$Y$8001,'Per Line'!$AG$2:$AG$8001,$B5&"|"&$C5,'Per Line'!$AJ$2:$AJ$8001,1,'Per Line'!$AK$2:$AK$8001,0)) | S5: =IF($Y5="","",R5*Q5) | T5: =IF($Y5="","",S5+P5) | U5: =IF($Y5="","",V5-T5) | V5: =IF($Y5="","",O5+R5+M5) | W5: =IF($Y5="","",V5-T5-K5) | Y5: =IF(ROWS($Y$2:$Y5)<=MAX('Per Line'!$AI$2:$AI$8001),MATCH(ROWS($Y$2:$Y5),'Per Line'!$AI$2:$AI$8001,0),"")
B6: =IF($Y6="","",INDEX('Per Line'!$F$2:$F$8001,$Y6)&"") | C6: =IF($Y6="","",INDEX('Per Line'!$D$2:$D$8001,$Y6)&"") | D6: =IF($Y6="","",INDEX('Per Line'!$B$2:$B$8001,$Y6)) | E6: =IF($Y6="","",INDEX('Per Line'!$C$2:$C$8001,$Y6)&"") | F6: =IF($Y6="","",INDEX('Per Line'!$G$2:$G$8001,$Y6)&"") | G6: =IF($Y6="","",INDEX('Per Line'!$L$2:$L$8001,$Y6)&"") | H6: =IF($Y6="","",INDEX('Per Line'!$M$2:$M$8001,$Y6)&"") | I6: =IF($Y6="","",INDEX('Per Line'!$N$2:$N$8001,$Y6)&"") | J6: =IF($Y6="","",INDEX('Per Line'!$Q$2:$Q$8001,$Y6)) | K6: =IF($Y6="","",J6*V6/100) | L6: =IF($Y6="","",INDEX('Per Line'!$K$2:$K$8001,$Y6)&"") | M6: =IF($Y6="","",SUMIFS('Per Line'!$Y$2:$Y$8001,'Per Line'!$AG$2:$AG$8001,$B6&"|"&$C6,'Per Line'!$AK$2:$AK$8001,1)) | N6: =IF($Y6="","",Settings!$C$7) | O6: =IF($Y6="","",SUMIFS('Per Line'!$Y$2:$Y$8001,'Per Line'!$AG$2:$AG$8001,$B6&"|"&$C6,'Per Line'!$AJ$2:$AJ$8001,0,'Per Line'!$AK$2:$AK$8001,0)) | P6: =IF($Y6="","",O6*N6) | Q6: =IF($Y6="","",Settings!$C$6) | R6: =IF($Y6="","",SUMIFS('Per Line'!$Y$2:$Y$8001,'Per Line'!$AG$2:$AG$8001,$B6&"|"&$C6,'Per Line'!$AJ$2:$AJ$8001,1,'Per Line'!$AK$2:$AK$8001,0)) | S6: =IF($Y6="","",R6*Q6) | T6: =IF($Y6="","",S6+P6) | U6: =IF($Y6="","",V6-T6) | V6: =IF($Y6="","",O6+R6+M6) | W6: =IF($Y6="","",V6-T6-K6) | Y6: =IF(ROWS($Y$2:$Y6)<=MAX('Per Line'!$AI$2:$AI$8001),MATCH(ROWS($Y$2:$Y6),'Per Line'!$AI$2:$AI$8001,0),"")
B7: =IF($Y7="","",INDEX('Per Line'!$F$2:$F$8001,$Y7)&"") | C7: =IF($Y7="","",INDEX('Per Line'!$D$2:$D$8001,$Y7)&"") | D7: =IF($Y7="","",INDEX('Per Line'!$B$2:$B$8001,$Y7)) | E7: =IF($Y7="","",INDEX('Per Line'!$C$2:$C$8001,$Y7)&"") | F7: =IF($Y7="","",INDEX('Per Line'!$G$2:$G$8001,$Y7)&"") | G7: =IF($Y7="","",INDEX('Per Line'!$L$2:$L$8001,$Y7)&"") | H7: =IF($Y7="","",INDEX('Per Line'!$M$2:$M$8001,$Y7)&"") | I7: =IF($Y7="","",INDEX('Per Line'!$N$2:$N$8001,$Y7)&"") | J7: =IF($Y7="","",INDEX('Per Line'!$Q$2:$Q$8001,$Y7)) | K7: =IF($Y7="","",J7*V7/100) | L7: =IF($Y7="","",INDEX('Per Line'!$K$2:$K$8001,$Y7)&"") | M7: =IF($Y7="","",SUMIFS('Per Line'!$Y$2:$Y$8001,'Per Line'!$AG$2:$AG$8001,$B7&"|"&$C7,'Per Line'!$AK$2:$AK$8001,1)) | N7: =IF($Y7="","",Settings!$C$7) | O7: =IF($Y7="","",SUMIFS('Per Line'!$Y$2:$Y$8001,'Per Line'!$AG$2:$AG$8001,$B7&"|"&$C7,'Per Line'!$AJ$2:$AJ$8001,0,'Per Line'!$AK$2:$AK$8001,0)) | P7: =IF($Y7="","",O7*N7) | Q7: =IF($Y7="","",Settings!$C$6) | R7: =IF($Y7="","",SUMIFS('Per Line'!$Y$2:$Y$8001,'Per Line'!$AG$2:$AG$8001,$B7&"|"&$C7,'Per Line'!$AJ$2:$AJ$8001,1,'Per Line'!$AK$2:$AK$8001,0)) | S7: =IF($Y7="","",R7*Q7) | T7: =IF($Y7="","",S7+P7) | U7: =IF($Y7="","",V7-T7) | V7: =IF($Y7="","",O7+R7+M7) | W7: =IF($Y7="","",V7-T7-K7) | Y7: =IF(ROWS($Y$2:$Y7)<=MAX('Per Line'!$AI$2:$AI$8001),MATCH(ROWS($Y$2:$Y7),'Per Line'!$AI$2:$AI$8001,0),"")
B8: =IF($Y8="","",INDEX('Per Line'!$F$2:$F$8001,$Y8)&"") | C8: =IF($Y8="","",INDEX('Per Line'!$D$2:$D$8001,$Y8)&"") | D8: =IF($Y8="","",INDEX('Per Line'!$B$2:$B$8001,$Y8)) | E8: =IF($Y8="","",INDEX('Per Line'!$C$2:$C$8001,$Y8)&"") | F8: =IF($Y8="","",INDEX('Per Line'!$G$2:$G$8001,$Y8)&"") | G8: =IF($Y8="","",INDEX('Per Line'!$L$2:$L$8001,$Y8)&"") | H8: =IF($Y8="","",INDEX('Per Line'!$M$2:$M$8001,$Y8)&"") | I8: =IF($Y8="","",INDEX('Per Line'!$N$2:$N$8001,$Y8)&"") | J8: =IF($Y8="","",INDEX('Per Line'!$Q$2:$Q$8001,$Y8)) | K8: =IF($Y8="","",J8*V8/100) | L8: =IF($Y8="","",INDEX('Per Line'!$K$2:$K$8001,$Y8)&"") | M8: =IF($Y8="","",SUMIFS('Per Line'!$Y$2:$Y$8001,'Per Line'!$AG$2:$AG$8001,$B8&"|"&$C8,'Per Line'!$AK$2:$AK$8001,1)) | N8: =IF($Y8="","",Settings!$C$7) | O8: =IF($Y8="","",SUMIFS('Per Line'!$Y$2:$Y$8001,'Per Line'!$AG$2:$AG$8001,$B8&"|"&$C8,'Per Line'!$AJ$2:$AJ$8001,0,'Per Line'!$AK$2:$AK$8001,0)) | P8: =IF($Y8="","",O8*N8) | Q8: =IF($Y8="","",Settings!$C$6) | R8: =IF($Y8="","",SUMIFS('Per Line'!$Y$2:$Y$8001,'Per Line'!$AG$2:$AG$8001,$B8&"|"&$C8,'Per Line'!$AJ$2:$AJ$8001,1,'Per Line'!$AK$2:$AK$8001,0)) | S8: =IF($Y8="","",R8*Q8) | T8: =IF($Y8="","",S8+P8) | U8: =IF($Y8="","",V8-T8) | V8: =IF($Y8="","",O8+R8+M8) | W8: =IF($Y8="","",V8-T8-K8) | Y8: =IF(ROWS($Y$2:$Y8)<=MAX('Per Line'!$AI$2:$AI$8001),MATCH(ROWS($Y$2:$Y8),'Per Line'!$AI$2:$AI$8001,0),"")
B9: =IF($Y9="","",INDEX('Per Line'!$F$2:$F$8001,$Y9)&"") | C9: =IF($Y9="","",INDEX('Per Line'!$D$2:$D$8001,$Y9)&"") | D9: =IF($Y9="","",INDEX('Per Line'!$B$2:$B$8001,$Y9)) | E9: =IF($Y9="","",INDEX('Per Line'!$C$2:$C$8001,$Y9)&"") | F9: =IF($Y9="","",INDEX('Per Line'!$G$2:$G$8001,$Y9)&"") | G9: =IF($Y9="","",INDEX('Per Line'!$L$2:$L$8001,$Y9)&"") | H9: =IF($Y9="","",INDEX('Per Line'!$M$2:$M$8001,$Y9)&"") | I9: =IF($Y9="","",INDEX('Per Line'!$N$2:$N$8001,$Y9)&"") | J9: =IF($Y9="","",INDEX('Per Line'!$Q$2:$Q$8001,$Y9)) | K9: =IF($Y9="","",J9*V9/100) | L9: =IF($Y9="","",INDEX('Per Line'!$K$2:$K$8001,$Y9)&"") | M9: =IF($Y9="","",SUMIFS('Per Line'!$Y$2:$Y$8001,'Per Line'!$AG$2:$AG$8001,$B9&"|"&$C9,'Per Line'!$AK$2:$AK$8001,1)) | N9: =IF($Y9="","",Settings!$C$7) | O9: =IF($Y9="","",SUMIFS('Per Line'!$Y$2:$Y$8001,'Per Line'!$AG$2:$AG$8001,$B9&"|"&$C9,'Per Line'!$AJ$2:$AJ$8001,0,'Per Line'!$AK$2:$AK$8001,0)) | P9: =IF($Y9="","",O9*N9) | Q9: =IF($Y9="","",Settings!$C$6) | R9: =IF($Y9="","",SUMIFS('Per Line'!$Y$2:$Y$8001,'Per Line'!$AG$2:$AG$8001,$B9&"|"&$C9,'Per Line'!$AJ$2:$AJ$8001,1,'Per Line'!$AK$2:$AK$8001,0)) | S9: =IF($Y9="","",R9*Q9) | T9: =IF($Y9="","",S9+P9) | U9: =IF($Y9="","",V9-T9) | V9: =IF($Y9="","",O9+R9+M9) | W9: =IF($Y9="","",V9-T9-K9) | Y9: =IF(ROWS($Y$2:$Y9)<=MAX('Per Line'!$AI$2:$AI$8001),MATCH(ROWS($Y$2:$Y9),'Per Line'!$AI$2:$AI$8001,0),"")
B10: =IF($Y10="","",INDEX('Per Line'!$F$2:$F$8001,$Y10)&"") | C10: =IF($Y10="","",INDEX('Per Line'!$D$2:$D$8001,$Y10)&"") | D10: =IF($Y10="","",INDEX('Per Line'!$B$2:$B$8001,$Y10)) | E10: =IF($Y10="","",INDEX('Per Line'!$C$2:$C$8001,$Y10)&"") | F10: =IF($Y10="","",INDEX('Per Line'!$G$2:$G$8001,$Y10)&"") | G10: =IF($Y10="","",INDEX('Per Line'!$L$2:$L$8001,$Y10)&"") | H10: =IF($Y10="","",INDEX('Per Line'!$M$2:$M$8001,$Y10)&"") | I10: =IF($Y10="","",INDEX('Per Line'!$N$2:$N$8001,$Y10)&"") | J10: =IF($Y10="","",INDEX('Per Line'!$Q$2:$Q$8001,$Y10)) | K10: =IF($Y10="","",J10*V10/100) | L10: =IF($Y10="","",INDEX('Per Line'!$K$2:$K$8001,$Y10)&"") | M10: =IF($Y10="","",SUMIFS('Per Line'!$Y$2:$Y$8001,'Per Line'!$AG$2:$AG$8001,$B10&"|"&$C10,'Per Line'!$AK$2:$AK$8001,1)) | N10: =IF($Y10="","",Settings!$C$7) | O10: =IF($Y10="","",SUMIFS('Per Line'!$Y$2:$Y$8001,'Per Line'!$AG$2:$AG$8001,$B10&"|"&$C10,'Per Line'!$AJ$2:$AJ$8001,0,'Per Line'!$AK$2:$AK$8001,0)) | P10: =IF($Y10="","",O10*N10) | Q10: =IF($Y10="","",Settings!$C$6) | R10: =IF($Y10="","",SUMIFS('Per Line'!$Y$2:$Y$8001,'Per Line'!$AG$2:$AG$8001,$B10&"|"&$C10,'Per Line'!$AJ$2:$AJ$8001,1,'Per Line'!$AK$2:$AK$8001,0)) | S10: =IF($Y10="","",R10*Q10) | T10: =IF($Y10="","",S10+P10) | U10: =IF($Y10="","",V10-T10) | V10: =IF($Y10="","",O10+R10+M10) | W10: =IF($Y10="","",V10-T10-K10) | Y10: =IF(ROWS($Y$2:$Y10)<=MAX('Per Line'!$AI$2:$AI$8001),MATCH(ROWS($Y$2:$Y10),'Per Line'!$AI$2:$AI$8001,0),"")
B11: =IF($Y11="","",INDEX('Per Line'!$F$2:$F$8001,$Y11)&"") | C11: =IF($Y11="","",INDEX('Per Line'!$D$2:$D$8001,$Y11)&"") | D11: =IF($Y11="","",INDEX('Per Line'!$B$2:$B$8001,$Y11)) | E11: =IF($Y11="","",INDEX('Per Line'!$C$2:$C$8001,$Y11)&"") | F11: =IF($Y11="","",INDEX('Per Line'!$G$2:$G$8001,$Y11)&"") | G11: =IF($Y11="","",INDEX('Per Line'!$L$2:$L$8001,$Y11)&"") | H11: =IF($Y11="","",INDEX('Per Line'!$M$2:$M$8001,$Y11)&"") | I11: =IF($Y11="","",INDEX('Per Line'!$N$2:$N$8001,$Y11)&"") | J11: =IF($Y11="","",INDEX('Per Line'!$Q$2:$Q$8001,$Y11)) | K11: =IF($Y11="","",J11*V11/100) | L11: =IF($Y11="","",INDEX('Per Line'!$K$2:$K$8001,$Y11)&"") | M11: =IF($Y11="","",SUMIFS('Per Line'!$Y$2:$Y$8001,'Per Line'!$AG$2:$AG$8001,$B11&"|"&$C11,'Per Line'!$AK$2:$AK$8001,1)) | N11: =IF($Y11="","",Settings!$C$7) | O11: =IF($Y11="","",SUMIFS('Per Line'!$Y$2:$Y$8001,'Per Line'!$AG$2:$AG$8001,$B11&"|"&$C11,'Per Line'!$AJ$2:$AJ$8001,0,'Per Line'!$AK$2:$AK$8001,0)) | P11: =IF($Y11="","",O11*N11) | Q11: =IF($Y11="","",Settings!$C$6) | R11: =IF($Y11="","",SUMIFS('Per Line'!$Y$2:$Y$8001,'Per Line'!$AG$2:$AG$8001,$B11&"|"&$C11,'Per Line'!$AJ$2:$AJ$8001,1,'Per Line'!$AK$2:$AK$8001,0)) | S11: =IF($Y11="","",R11*Q11) | T11: =IF($Y11="","",S11+P11) | U11: =IF($Y11="","",V11-T11) | V11: =IF($Y11="","",O11+R11+M11) | W11: =IF($Y11="","",V11-T11-K11) | Y11: =IF(ROWS($Y$2:$Y11)<=MAX('Per Line'!$AI$2:$AI$8001),MATCH(ROWS($Y$2:$Y11),'Per Line'!$AI$2:$AI$8001,0),"")
B12: =IF($Y12="","",INDEX('Per Line'!$F$2:$F$8001,$Y12)&"") | C12: =IF($Y12="","",INDEX('Per Line'!$D$2:$D$8001,$Y12)&"") | D12: =IF($Y12="","",INDEX('Per Line'!$B$2:$B$8001,$Y12)) | E12: =IF($Y12="","",INDEX('Per Line'!$C$2:$C$8001,$Y12)&"") | F12: =IF($Y12="","",INDEX('Per Line'!$G$2:$G$8001,$Y12)&"") | G12: =IF($Y12="","",INDEX('Per Line'!$L$2:$L$8001,$Y12)&"") | H12: =IF($Y12="","",INDEX('Per Line'!$M$2:$M$8001,$Y12)&"") | I12: =IF($Y12="","",INDEX('Per Line'!$N$2:$N$8001,$Y12)&"") | J12: =IF($Y12="","",INDEX('Per Line'!$Q$2:$Q$8001,$Y12)) | K12: =IF($Y12="","",J12*V12/100) | L12: =IF($Y12="","",INDEX('Per Line'!$K$2:$K$8001,$Y12)&"") | M12: =IF($Y12="","",SUMIFS('Per Line'!$Y$2:$Y$8001,'Per Line'!$AG$2:$AG$8001,$B12&"|"&$C12,'Per Line'!$AK$2:$AK$8001,1)) | N12: =IF($Y12="","",Settings!$C$7) | O12: =IF($Y12="","",SUMIFS('Per Line'!$Y$2:$Y$8001,'Per Line'!$AG$2:$AG$8001,$B12&"|"&$C12,'Per Line'!$AJ$2:$AJ$8001,0,'Per Line'!$AK$2:$AK$8001,0)) | P12: =IF($Y12="","",O12*N12) | Q12: =IF($Y12="","",Settings!$C$6) | R12: =IF($Y12="","",SUMIFS('Per Line'!$Y$2:$Y$8001,'Per Line'!$AG$2:$AG$8001,$B12&"|"&$C12,'Per Line'!$AJ$2:$AJ$8001,1,'Per Line'!$AK$2:$AK$8001,0)) | S12: =IF($Y12="","",R12*Q12) | T12: =IF($Y12="","",S12+P12) | U12: =IF($Y12="","",V12-T12) | V12: =IF($Y12="","",O12+R12+M12) | W12: =IF($Y12="","",V12-T12-K12) | Y12: =IF(ROWS($Y$2:$Y12)<=MAX('Per Line'!$AI$2:$AI$8001),MATCH(ROWS($Y$2:$Y12),'Per Line'!$AI$2:$AI$8001,0),"")
B13: =IF($Y13="","",INDEX('Per Line'!$F$2:$F$8001,$Y13)&"") | C13: =IF($Y13="","",INDEX('Per Line'!$D$2:$D$8001,$Y13)&"") | D13: =IF($Y13="","",INDEX('Per Line'!$B$2:$B$8001,$Y13)) | E13: =IF($Y13="","",INDEX('Per Line'!$C$2:$C$8001,$Y13)&"") | F13: =IF($Y13="","",INDEX('Per Line'!$G$2:$G$8001,$Y13)&"") | G13: =IF($Y13="","",INDEX('Per Line'!$L$2:$L$8001,$Y13)&"") | H13: =IF($Y13="","",INDEX('Per Line'!$M$2:$M$8001,$Y13)&"") | I13: =IF($Y13="","",INDEX('Per Line'!$N$2:$N$8001,$Y13)&"") | J13: =IF($Y13="","",INDEX('Per Line'!$Q$2:$Q$8001,$Y13)) | K13: =IF($Y13="","",J13*V13/100) | L13: =IF($Y13="","",INDEX('Per Line'!$K$2:$K$8001,$Y13)&"") | M13: =IF($Y13="","",SUMIFS('Per Line'!$Y$2:$Y$8001,'Per Line'!$AG$2:$AG$8001,$B13&"|"&$C13,'Per Line'!$AK$2:$AK$8001,1)) | N13: =IF($Y13="","",Settings!$C$7) | O13: =IF($Y13="","",SUMIFS('Per Line'!$Y$2:$Y$8001,'Per Line'!$AG$2:$AG$8001,$B13&"|"&$C13,'Per Line'!$AJ$2:$AJ$8001,0,'Per Line'!$AK$2:$AK$8001,0)) | P13: =IF($Y13="","",O13*N13) | Q13: =IF($Y13="","",Settings!$C$6) | R13: =IF($Y13="","",SUMIFS('Per Line'!$Y$2:$Y$8001,'Per Line'!$AG$2:$AG$8001,$B13&"|"&$C13,'Per Line'!$AJ$2:$AJ$8001,1,'Per Line'!$AK$2:$AK$8001,0)) | S13: =IF($Y13="","",R13*Q13) | T13: =IF($Y13="","",S13+P13) | U13: =IF($Y13="","",V13-T13) | V13: =IF($Y13="","",O13+R13+M13) | W13: =IF($Y13="","",V13-T13-K13) | Y13: =IF(ROWS($Y$2:$Y13)<=MAX('Per Line'!$AI$2:$AI$8001),MATCH(ROWS($Y$2:$Y13),'Per Line'!$AI$2:$AI$8001,0),"")
... B2001: =IF($Y2001="","",INDEX('Per Line'!$F$2:$F$8001,$Y2001)&"") | C2001: =IF($Y2001="","",INDEX('Per Line'!$D$2:$D$8001,$Y2001)&"") | D2001: =IF($Y2001="","",INDEX('Per Line'!$B$2:$B$8001,$Y2001)) | E2001: =IF($Y2001="","",INDEX('Per Line'!$C$2:$C$8001,$Y2001)&"") | F2001: =IF($Y2001="","",INDEX('Per Line'!$G$2:$G$8001,$Y2001)&"") | G2001: =IF($Y2001="","",INDEX('Per Line'!$L$2:$L$8001,$Y2001)&"") | H2001: =IF($Y2001="","",INDEX('Per Line'!$M$2:$M$8001,$Y2001)&"") | I2001: =IF($Y2001="","",INDEX('Per Line'!$N$2:$N$8001,$Y2001)&"") | J2001: =IF($Y2001="","",INDEX('Per Line'!$Q$2:$Q$8001,$Y2001)) | K2001: =IF($Y2001="","",J2001*V2001/100) | L2001: =IF($Y2001="","",INDEX('Per Line'!$K$2:$K$8001,$Y2001)&"") | M2001: =IF($Y2001="","",SUMIFS('Per Line'!$Y$2:$Y$8001,'Per Line'!$AG$2:$AG$8001,$B2001&"|"&$C2001,'Per Line'!$AK$2:$AK$8001,1)) | N2001: =IF($Y2001="","",Settings!$C$7) | O2001: =IF($Y2001="","",SUMIFS('Per Line'!$Y$2:$Y$8001,'Per Line'!$AG$2:$AG$8001,$B2001&"|"&$C2001,'Per Line'!$AJ$2:$AJ$8001,0,'Per Line'!$AK$2:$AK$8001,0)) | P2001: =IF($Y2001="","",O2001*N2001) | Q2001: =IF($Y2001="","",Settings!$C$6) | R2001: =IF($Y2001="","",SUMIFS('Per Line'!$Y$2:$Y$8001,'Per Line'!$AG$2:$AG$8001,$B2001&"|"&$C2001,'Per Line'!$AJ$2:$AJ$8001,1,'Per Line'!$AK$2:$AK$8001,0)) | S2001: =IF($Y2001="","",R2001*Q2001) | T2001: =IF($Y2001="","",S2001+P2001) | U2001: =IF($Y2001="","",V2001-T2001) | V2001: =IF($Y2001="","",O2001+R2001+M2001) | W2001: =IF($Y2001="","",V2001-T2001-K2001) | Y2001: =IF(ROWS($Y$2:$Y2001)<=MAX('Per Line'!$AI$2:$AI$8001),MATCH(ROWS($Y$2:$Y2001),'Per Line'!$AI$2:$AI$8001,0),"")
