Workbook

Sheet How To Use
A1: Claims Template - APATCH PETROLEUM (Chronic)
A3: Monthly steps
A4: 1. Open the 'Per Line' tab. Delete the old data in the BLUE columns only (row 2 down). Never delete the green or grey columns.
A5: 2. Paste the new month's data as VALUES starting at A2, into the blue columns: A-I, K-S (same order as the system export).
A6: 3. Green columns (J, T, U, V, W) and the grey helper columns (X-AB) calculate automatically - do not paste over them.
A7: 4. 'Per Invoice' fills itself from 'Per Line' (one row per Order #, split into IMP / Local). No pivot table, no refresh.
A8: 5. The ONLY manual column in 'Per Invoice' is column A 'Invoice' (blue): type it yourself. Everything else is formula.
A9: 6. Open 'Settings' and check STATUS says OK (Per Line totals = Per Invoice totals).
A11: Colour legend
A12: Blue header = typed/pasted by you (raw data, and 'Invoice' in Per Invoice). Green header = formula (do not paste over). Grey header = helper formula (do not touch). Yellow cell (Settings) = editable rate.
A14: Calculation rules (taken from the July 2026 sheet)
A15: Co val = Order Co Payment x Total / 100. Discount = Total x Rebates / 100. Subtotal = Total - Discount. Net = Subtotal - Co val. (Total = 'Product Total')
... A20: Capacity: up to 300 lines and 100 invoices per month. A line with an empty Order # is ignored.

Sheet Settings
B1: Company settings & checks
B3: Insurance Company | C3: APATCH PETROLEUM | D3: Informational only
B4: Corporate | C4: Apache CFC; Apache IND; Apache Khalda | D4: Informational only
B5: Sheet type | C5: Chronic | D5: Informational only
B6: Local products rebate % | C6: 0.15 | D6: Source: July sheet (Rebates = 15 on Local lines).
B7: Imported (IMP) products rebate % | C7: 0.05 | D7: Source: July sheet (Rebates = 5 on non-local lines; 0 on Special Rebates = Yes).
B9: Month totals / reconciliation
B10: Lines loaded | C10: =COUNTA('Per Line'!$B$2:$B$301)
B11: Invoices (unique Order #) | C11: =MAX('Per Line'!$Y$2:$Y$301)
B12: Invoices shown in Per Invoice | C12: =SUMPRODUCT(--('Per Invoice'!$C$2:$C$101<>""))
B13: Grand Total - Per Line (Product Total) | C13: =SUM('Per Line'!$Q$2:$Q$301)
B14: Grand Total - Per Invoice | C14: =SUM('Per Invoice'!$U$2:$U$101)
B15: Discount - Per Line | C15: =SUM('Per Line'!$U$2:$U$301)
B16: Discount - Per Invoice | C16: =SUM('Per Invoice'!$S$2:$S$101)
B17: Co val - Per Line | C17: =SUM('Per Line'!$J$2:$J$301)
B18: Co val - Per Invoice | C18: =SUM('Per Invoice'!$J$2:$J$101)
B19: Net - Per Line | C19: =SUM('Per Line'!$W$2:$W$301)
B20: Net - Per Invoice | C20: =SUM('Per Invoice'!$V$2:$V$101)
B21: Max Limit adjustment (Co val, Per Invoice only) | C21: 0 | D21: This company's Per Invoice has no Max Limit rule.
B23: STATUS | C23: =IF(C10=0,"No data loaded",IF(COUNTA('Per Line'!$B:$B)-1>300,"TOO MANY LINES - extend template",IF(C11>100,"TOO MANY INVOICES - extend template",IF(AND(ROUND(C13-C14,2)=0,ROUND(C15-C16,2)=0,ROUND(C17+C21-C18,2)=0,ROUND(C19-C21-C20,2)=0,C11=C12),"OK","CHECK - Per Line and Per Invoice do not match")))) | D23: Must say OK after you paste the month data.

Sheet Per Line
A1: Cycle | B1: Order # | C1: Create At | D1: Insurance Company | E1: Country Portal ID | F1: Corporate | G1: Card | H1: Name | I1: Order Co Payment | J1: Co val | K1: heisenberg id | L1: Product Name | M1: Local | N1: Unit | O1: Quantity | P1: Unit Price | Q1: Product Total | R1: ERX ID | S1: Special Rebates? | T1: Rebates | U1: Discount | V1: Subtotal | W1: Net | X1: Order 1st Row (helper) | Y1: Invoice # (helper) | Z1: Is Local (helper) | AA1: Is Special (helper) | AB1: Sort Key (helper)
J2: =IF($B2="","",I2*Q2/100) | T2: =IF($B2="","",IF($AA2=1,0,IF($Z2=1,Settings!$C$6,Settings!$C$7))*100) | U2: =IF($B2="","",Q2*T2/100) | V2: =IF($B2="","",Q2-U2) | W2: =IF($B2="","",V2-J2) | X2: =IF($B2="","",IF(COUNTIF($B$2:$B2,$B2)=1,1,0)) | Y2: =IF($X2=1,SUMPRODUCT(--($AB$2:$AB$301<$AB2))+1,"") | Z2: =IF($B2="","",IF(OR($M2=TRUE(),$M2="TRUE"),1,0)) | AA2: =IF($B2="","",IF($S2="Yes",1,0)) | AB2: =IF($X2=1,IFERROR(IF(VALUE($B2)<100000000,VALUE($B2),1000000000),IFERROR(IF(VALUE(MID($B2,2,20))<100000000,VALUE(MID($B2,2,20)),1000000000),1000000000))+ROW()/100000,"")
J3: =IF($B3="","",I3*Q3/100) | T3: =IF($B3="","",IF($AA3=1,0,IF($Z3=1,Settings!$C$6,Settings!$C$7))*100) | U3: =IF($B3="","",Q3*T3/100) | V3: =IF($B3="","",Q3-U3) | W3: =IF($B3="","",V3-J3) | X3: =IF($B3="","",IF(COUNTIF($B$2:$B3,$B3)=1,1,0)) | Y3: =IF($X3=1,SUMPRODUCT(--($AB$2:$AB$301<$AB3))+1,"") | Z3: =IF($B3="","",IF(OR($M3=TRUE(),$M3="TRUE"),1,0)) | AA3: =IF($B3="","",IF($S3="Yes",1,0)) | AB3: =IF($X3=1,IFERROR(IF(VALUE($B3)<100000000,VALUE($B3),1000000000),IFERROR(IF(VALUE(MID($B3,2,20))<100000000,VALUE(MID($B3,2,20)),1000000000),1000000000))+ROW()/100000,"")
J4: =IF($B4="","",I4*Q4/100) | T4: =IF($B4="","",IF($AA4=1,0,IF($Z4=1,Settings!$C$6,Settings!$C$7))*100) | U4: =IF($B4="","",Q4*T4/100) | V4: =IF($B4="","",Q4-U4) | W4: =IF($B4="","",V4-J4) | X4: =IF($B4="","",IF(COUNTIF($B$2:$B4,$B4)=1,1,0)) | Y4: =IF($X4=1,SUMPRODUCT(--($AB$2:$AB$301<$AB4))+1,"") | Z4: =IF($B4="","",IF(OR($M4=TRUE(),$M4="TRUE"),1,0)) | AA4: =IF($B4="","",IF($S4="Yes",1,0)) | AB4: =IF($X4=1,IFERROR(IF(VALUE($B4)<100000000,VALUE($B4),1000000000),IFERROR(IF(VALUE(MID($B4,2,20))<100000000,VALUE(MID($B4,2,20)),1000000000),1000000000))+ROW()/100000,"")
J5: =IF($B5="","",I5*Q5/100) | T5: =IF($B5="","",IF($AA5=1,0,IF($Z5=1,Settings!$C$6,Settings!$C$7))*100) | U5: =IF($B5="","",Q5*T5/100) | V5: =IF($B5="","",Q5-U5) | W5: =IF($B5="","",V5-J5) | X5: =IF($B5="","",IF(COUNTIF($B$2:$B5,$B5)=1,1,0)) | Y5: =IF($X5=1,SUMPRODUCT(--($AB$2:$AB$301<$AB5))+1,"") | Z5: =IF($B5="","",IF(OR($M5=TRUE(),$M5="TRUE"),1,0)) | AA5: =IF($B5="","",IF($S5="Yes",1,0)) | AB5: =IF($X5=1,IFERROR(IF(VALUE($B5)<100000000,VALUE($B5),1000000000),IFERROR(IF(VALUE(MID($B5,2,20))<100000000,VALUE(MID($B5,2,20)),1000000000),1000000000))+ROW()/100000,"")
J6: =IF($B6="","",I6*Q6/100) | T6: =IF($B6="","",IF($AA6=1,0,IF($Z6=1,Settings!$C$6,Settings!$C$7))*100) | U6: =IF($B6="","",Q6*T6/100) | V6: =IF($B6="","",Q6-U6) | W6: =IF($B6="","",V6-J6) | X6: =IF($B6="","",IF(COUNTIF($B$2:$B6,$B6)=1,1,0)) | Y6: =IF($X6=1,SUMPRODUCT(--($AB$2:$AB$301<$AB6))+1,"") | Z6: =IF($B6="","",IF(OR($M6=TRUE(),$M6="TRUE"),1,0)) | AA6: =IF($B6="","",IF($S6="Yes",1,0)) | AB6: =IF($X6=1,IFERROR(IF(VALUE($B6)<100000000,VALUE($B6),1000000000),IFERROR(IF(VALUE(MID($B6,2,20))<100000000,VALUE(MID($B6,2,20)),1000000000),1000000000))+ROW()/100000,"")
J7: =IF($B7="","",I7*Q7/100) | T7: =IF($B7="","",IF($AA7=1,0,IF($Z7=1,Settings!$C$6,Settings!$C$7))*100) | U7: =IF($B7="","",Q7*T7/100) | V7: =IF($B7="","",Q7-U7) | W7: =IF($B7="","",V7-J7) | X7: =IF($B7="","",IF(COUNTIF($B$2:$B7,$B7)=1,1,0)) | Y7: =IF($X7=1,SUMPRODUCT(--($AB$2:$AB$301<$AB7))+1,"") | Z7: =IF($B7="","",IF(OR($M7=TRUE(),$M7="TRUE"),1,0)) | AA7: =IF($B7="","",IF($S7="Yes",1,0)) | AB7: =IF($X7=1,IFERROR(IF(VALUE($B7)<100000000,VALUE($B7),1000000000),IFERROR(IF(VALUE(MID($B7,2,20))<100000000,VALUE(MID($B7,2,20)),1000000000),1000000000))+ROW()/100000,"")
J8: =IF($B8="","",I8*Q8/100) | T8: =IF($B8="","",IF($AA8=1,0,IF($Z8=1,Settings!$C$6,Settings!$C$7))*100) | U8: =IF($B8="","",Q8*T8/100) | V8: =IF($B8="","",Q8-U8) | W8: =IF($B8="","",V8-J8) | X8: =IF($B8="","",IF(COUNTIF($B$2:$B8,$B8)=1,1,0)) | Y8: =IF($X8=1,SUMPRODUCT(--($AB$2:$AB$301<$AB8))+1,"") | Z8: =IF($B8="","",IF(OR($M8=TRUE(),$M8="TRUE"),1,0)) | AA8: =IF($B8="","",IF($S8="Yes",1,0)) | AB8: =IF($X8=1,IFERROR(IF(VALUE($B8)<100000000,VALUE($B8),1000000000),IFERROR(IF(VALUE(MID($B8,2,20))<100000000,VALUE(MID($B8,2,20)),1000000000),1000000000))+ROW()/100000,"")
J9: =IF($B9="","",I9*Q9/100) | T9: =IF($B9="","",IF($AA9=1,0,IF($Z9=1,Settings!$C$6,Settings!$C$7))*100) | U9: =IF($B9="","",Q9*T9/100) | V9: =IF($B9="","",Q9-U9) | W9: =IF($B9="","",V9-J9) | X9: =IF($B9="","",IF(COUNTIF($B$2:$B9,$B9)=1,1,0)) | Y9: =IF($X9=1,SUMPRODUCT(--($AB$2:$AB$301<$AB9))+1,"") | Z9: =IF($B9="","",IF(OR($M9=TRUE(),$M9="TRUE"),1,0)) | AA9: =IF($B9="","",IF($S9="Yes",1,0)) | AB9: =IF($X9=1,IFERROR(IF(VALUE($B9)<100000000,VALUE($B9),1000000000),IFERROR(IF(VALUE(MID($B9,2,20))<100000000,VALUE(MID($B9,2,20)),1000000000),1000000000))+ROW()/100000,"")
J10: =IF($B10="","",I10*Q10/100) | T10: =IF($B10="","",IF($AA10=1,0,IF($Z10=1,Settings!$C$6,Settings!$C$7))*100) | U10: =IF($B10="","",Q10*T10/100) | V10: =IF($B10="","",Q10-U10) | W10: =IF($B10="","",V10-J10) | X10: =IF($B10="","",IF(COUNTIF($B$2:$B10,$B10)=1,1,0)) | Y10: =IF($X10=1,SUMPRODUCT(--($AB$2:$AB$301<$AB10))+1,"") | Z10: =IF($B10="","",IF(OR($M10=TRUE(),$M10="TRUE"),1,0)) | AA10: =IF($B10="","",IF($S10="Yes",1,0)) | AB10: =IF($X10=1,IFERROR(IF(VALUE($B10)<100000000,VALUE($B10),1000000000),IFERROR(IF(VALUE(MID($B10,2,20))<100000000,VALUE(MID($B10,2,20)),1000000000),1000000000))+ROW()/100000,"")
J11: =IF($B11="","",I11*Q11/100) | T11: =IF($B11="","",IF($AA11=1,0,IF($Z11=1,Settings!$C$6,Settings!$C$7))*100) | U11: =IF($B11="","",Q11*T11/100) | V11: =IF($B11="","",Q11-U11) | W11: =IF($B11="","",V11-J11) | X11: =IF($B11="","",IF(COUNTIF($B$2:$B11,$B11)=1,1,0)) | Y11: =IF($X11=1,SUMPRODUCT(--($AB$2:$AB$301<$AB11))+1,"") | Z11: =IF($B11="","",IF(OR($M11=TRUE(),$M11="TRUE"),1,0)) | AA11: =IF($B11="","",IF($S11="Yes",1,0)) | AB11: =IF($X11=1,IFERROR(IF(VALUE($B11)<100000000,VALUE($B11),1000000000),IFERROR(IF(VALUE(MID($B11,2,20))<100000000,VALUE(MID($B11,2,20)),1000000000),1000000000))+ROW()/100000,"")
J12: =IF($B12="","",I12*Q12/100) | T12: =IF($B12="","",IF($AA12=1,0,IF($Z12=1,Settings!$C$6,Settings!$C$7))*100) | U12: =IF($B12="","",Q12*T12/100) | V12: =IF($B12="","",Q12-U12) | W12: =IF($B12="","",V12-J12) | X12: =IF($B12="","",IF(COUNTIF($B$2:$B12,$B12)=1,1,0)) | Y12: =IF($X12=1,SUMPRODUCT(--($AB$2:$AB$301<$AB12))+1,"") | Z12: =IF($B12="","",IF(OR($M12=TRUE(),$M12="TRUE"),1,0)) | AA12: =IF($B12="","",IF($S12="Yes",1,0)) | AB12: =IF($X12=1,IFERROR(IF(VALUE($B12)<100000000,VALUE($B12),1000000000),IFERROR(IF(VALUE(MID($B12,2,20))<100000000,VALUE(MID($B12,2,20)),1000000000),1000000000))+ROW()/100000,"")
J13: =IF($B13="","",I13*Q13/100) | T13: =IF($B13="","",IF($AA13=1,0,IF($Z13=1,Settings!$C$6,Settings!$C$7))*100) | U13: =IF($B13="","",Q13*T13/100) | V13: =IF($B13="","",Q13-U13) | W13: =IF($B13="","",V13-J13) | X13: =IF($B13="","",IF(COUNTIF($B$2:$B13,$B13)=1,1,0)) | Y13: =IF($X13=1,SUMPRODUCT(--($AB$2:$AB$301<$AB13))+1,"") | Z13: =IF($B13="","",IF(OR($M13=TRUE(),$M13="TRUE"),1,0)) | AA13: =IF($B13="","",IF($S13="Yes",1,0)) | AB13: =IF($X13=1,IFERROR(IF(VALUE($B13)<100000000,VALUE($B13),1000000000),IFERROR(IF(VALUE(MID($B13,2,20))<100000000,VALUE(MID($B13,2,20)),1000000000),1000000000))+ROW()/100000,"")
... J301: =IF($B301="","",I301*Q301/100) | T301: =IF($B301="","",IF($AA301=1,0,IF($Z301=1,Settings!$C$6,Settings!$C$7))*100) | U301: =IF($B301="","",Q301*T301/100) | V301: =IF($B301="","",Q301-U301) | W301: =IF($B301="","",V301-J301) | X301: =IF($B301="","",IF(COUNTIF($B$2:$B301,$B301)=1,1,0)) | Y301: =IF($X301=1,SUMPRODUCT(--($AB$2:$AB$301<$AB301))+1,"") | Z301: =IF($B301="","",IF(OR($M301=TRUE(),$M301="TRUE"),1,0)) | AA301: =IF($B301="","",IF($S301="Yes",1,0)) | AB301: =IF($X301=1,IFERROR(IF(VALUE($B301)<100000000,VALUE($B301),1000000000),IFERROR(IF(VALUE(MID($B301,2,20))<100000000,VALUE(MID($B301,2,20)),1000000000),1000000000))+ROW()/100000,"")

Sheet Per Invoice
A1: Invoice | B1: Cycle | C1: Order # | D1: Create At | E1: Country Portal ID | F1: Corporate | G1: Card | H1: Name | I1: Order Co Payment | J1: Co val | K1: ERX ID | L1: Special Rebates | M1: IMP % | N1: IMP | O1: IMP VAL | P1: LOCAL % | Q1: LOCAL | R1: LOCAL VAL | S1: TOTAL VAL | T1: SUBTOTAL | U1: Grand Total | V1: NET | W1: Src Row (helper)
B2: =IF($W2="","",INDEX('Per Line'!$A$2:$A$301,$W2)&"") | C2: =IF($W2="","",INDEX('Per Line'!$B$2:$B$301,$W2)&"") | D2: =IF($W2="","",INDEX('Per Line'!$C$2:$C$301,$W2)) | E2: =IF($W2="","",INDEX('Per Line'!$E$2:$E$301,$W2)&"") | F2: =IF($W2="","",INDEX('Per Line'!$F$2:$F$301,$W2)&"") | G2: =IF($W2="","",INDEX('Per Line'!$G$2:$G$301,$W2)&"") | H2: =IF($W2="","",INDEX('Per Line'!$H$2:$H$301,$W2)&"") | I2: =IF($W2="","",INDEX('Per Line'!$I$2:$I$301,$W2)) | J2: =IF($W2="","",I2*U2/100) | K2: =IF($W2="","",INDEX('Per Line'!$R$2:$R$301,$W2)&"") | L2: =IF($W2="","",SUMIFS('Per Line'!$Q$2:$Q$301,'Per Line'!$B$2:$B$301,$C2,'Per Line'!$AA$2:$AA$301,1)) | M2: =IF($W2="","",Settings!$C$7) | N2: =IF($W2="","",SUMIFS('Per Line'!$Q$2:$Q$301,'Per Line'!$B$2:$B$301,$C2,'Per Line'!$Z$2:$Z$301,0,'Per Line'!$AA$2:$AA$301,0)) | O2: =IF($W2="","",N2*M2) | P2: =IF($W2="","",Settings!$C$6) | Q2: =IF($W2="","",SUMIFS('Per Line'!$Q$2:$Q$301,'Per Line'!$B$2:$B$301,$C2,'Per Line'!$Z$2:$Z$301,1,'Per Line'!$AA$2:$AA$301,0)) | R2: =IF($W2="","",Q2*P2) | S2: =IF($W2="","",R2+O2) | T2: =IF($W2="","",U2-S2) | U2: =IF($W2="","",N2+Q2+L2) | V2: =IF($W2="","",U2-S2-J2) | W2: =IF(ROWS($W$2:$W2)<=MAX('Per Line'!$Y$2:$Y$301),MATCH(ROWS($W$2:$W2),'Per Line'!$Y$2:$Y$301,0),"")
B3: =IF($W3="","",INDEX('Per Line'!$A$2:$A$301,$W3)&"") | C3: =IF($W3="","",INDEX('Per Line'!$B$2:$B$301,$W3)&"") | D3: =IF($W3="","",INDEX('Per Line'!$C$2:$C$301,$W3)) | E3: =IF($W3="","",INDEX('Per Line'!$E$2:$E$301,$W3)&"") | F3: =IF($W3="","",INDEX('Per Line'!$F$2:$F$301,$W3)&"") | G3: =IF($W3="","",INDEX('Per Line'!$G$2:$G$301,$W3)&"") | H3: =IF($W3="","",INDEX('Per Line'!$H$2:$H$301,$W3)&"") | I3: =IF($W3="","",INDEX('Per Line'!$I$2:$I$301,$W3)) | J3: =IF($W3="","",I3*U3/100) | K3: =IF($W3="","",INDEX('Per Line'!$R$2:$R$301,$W3)&"") | L3: =IF($W3="","",SUMIFS('Per Line'!$Q$2:$Q$301,'Per Line'!$B$2:$B$301,$C3,'Per Line'!$AA$2:$AA$301,1)) | M3: =IF($W3="","",Settings!$C$7) | N3: =IF($W3="","",SUMIFS('Per Line'!$Q$2:$Q$301,'Per Line'!$B$2:$B$301,$C3,'Per Line'!$Z$2:$Z$301,0,'Per Line'!$AA$2:$AA$301,0)) | O3: =IF($W3="","",N3*M3) | P3: =IF($W3="","",Settings!$C$6) | Q3: =IF($W3="","",SUMIFS('Per Line'!$Q$2:$Q$301,'Per Line'!$B$2:$B$301,$C3,'Per Line'!$Z$2:$Z$301,1,'Per Line'!$AA$2:$AA$301,0)) | R3: =IF($W3="","",Q3*P3) | S3: =IF($W3="","",R3+O3) | T3: =IF($W3="","",U3-S3) | U3: =IF($W3="","",N3+Q3+L3) | V3: =IF($W3="","",U3-S3-J3) | W3: =IF(ROWS($W$2:$W3)<=MAX('Per Line'!$Y$2:$Y$301),MATCH(ROWS($W$2:$W3),'Per Line'!$Y$2:$Y$301,0),"")
B4: =IF($W4="","",INDEX('Per Line'!$A$2:$A$301,$W4)&"") | C4: =IF($W4="","",INDEX('Per Line'!$B$2:$B$301,$W4)&"") | D4: =IF($W4="","",INDEX('Per Line'!$C$2:$C$301,$W4)) | E4: =IF($W4="","",INDEX('Per Line'!$E$2:$E$301,$W4)&"") | F4: =IF($W4="","",INDEX('Per Line'!$F$2:$F$301,$W4)&"") | G4: =IF($W4="","",INDEX('Per Line'!$G$2:$G$301,$W4)&"") | H4: =IF($W4="","",INDEX('Per Line'!$H$2:$H$301,$W4)&"") | I4: =IF($W4="","",INDEX('Per Line'!$I$2:$I$301,$W4)) | J4: =IF($W4="","",I4*U4/100) | K4: =IF($W4="","",INDEX('Per Line'!$R$2:$R$301,$W4)&"") | L4: =IF($W4="","",SUMIFS('Per Line'!$Q$2:$Q$301,'Per Line'!$B$2:$B$301,$C4,'Per Line'!$AA$2:$AA$301,1)) | M4: =IF($W4="","",Settings!$C$7) | N4: =IF($W4="","",SUMIFS('Per Line'!$Q$2:$Q$301,'Per Line'!$B$2:$B$301,$C4,'Per Line'!$Z$2:$Z$301,0,'Per Line'!$AA$2:$AA$301,0)) | O4: =IF($W4="","",N4*M4) | P4: =IF($W4="","",Settings!$C$6) | Q4: =IF($W4="","",SUMIFS('Per Line'!$Q$2:$Q$301,'Per Line'!$B$2:$B$301,$C4,'Per Line'!$Z$2:$Z$301,1,'Per Line'!$AA$2:$AA$301,0)) | R4: =IF($W4="","",Q4*P4) | S4: =IF($W4="","",R4+O4) | T4: =IF($W4="","",U4-S4) | U4: =IF($W4="","",N4+Q4+L4) | V4: =IF($W4="","",U4-S4-J4) | W4: =IF(ROWS($W$2:$W4)<=MAX('Per Line'!$Y$2:$Y$301),MATCH(ROWS($W$2:$W4),'Per Line'!$Y$2:$Y$301,0),"")
B5: =IF($W5="","",INDEX('Per Line'!$A$2:$A$301,$W5)&"") | C5: =IF($W5="","",INDEX('Per Line'!$B$2:$B$301,$W5)&"") | D5: =IF($W5="","",INDEX('Per Line'!$C$2:$C$301,$W5)) | E5: =IF($W5="","",INDEX('Per Line'!$E$2:$E$301,$W5)&"") | F5: =IF($W5="","",INDEX('Per Line'!$F$2:$F$301,$W5)&"") | G5: =IF($W5="","",INDEX('Per Line'!$G$2:$G$301,$W5)&"") | H5: =IF($W5="","",INDEX('Per Line'!$H$2:$H$301,$W5)&"") | I5: =IF($W5="","",INDEX('Per Line'!$I$2:$I$301,$W5)) | J5: =IF($W5="","",I5*U5/100) | K5: =IF($W5="","",INDEX('Per Line'!$R$2:$R$301,$W5)&"") | L5: =IF($W5="","",SUMIFS('Per Line'!$Q$2:$Q$301,'Per Line'!$B$2:$B$301,$C5,'Per Line'!$AA$2:$AA$301,1)) | M5: =IF($W5="","",Settings!$C$7) | N5: =IF($W5="","",SUMIFS('Per Line'!$Q$2:$Q$301,'Per Line'!$B$2:$B$301,$C5,'Per Line'!$Z$2:$Z$301,0,'Per Line'!$AA$2:$AA$301,0)) | O5: =IF($W5="","",N5*M5) | P5: =IF($W5="","",Settings!$C$6) | Q5: =IF($W5="","",SUMIFS('Per Line'!$Q$2:$Q$301,'Per Line'!$B$2:$B$301,$C5,'Per Line'!$Z$2:$Z$301,1,'Per Line'!$AA$2:$AA$301,0)) | R5: =IF($W5="","",Q5*P5) | S5: =IF($W5="","",R5+O5) | T5: =IF($W5="","",U5-S5) | U5: =IF($W5="","",N5+Q5+L5) | V5: =IF($W5="","",U5-S5-J5) | W5: =IF(ROWS($W$2:$W5)<=MAX('Per Line'!$Y$2:$Y$301),MATCH(ROWS($W$2:$W5),'Per Line'!$Y$2:$Y$301,0),"")
B6: =IF($W6="","",INDEX('Per Line'!$A$2:$A$301,$W6)&"") | C6: =IF($W6="","",INDEX('Per Line'!$B$2:$B$301,$W6)&"") | D6: =IF($W6="","",INDEX('Per Line'!$C$2:$C$301,$W6)) | E6: =IF($W6="","",INDEX('Per Line'!$E$2:$E$301,$W6)&"") | F6: =IF($W6="","",INDEX('Per Line'!$F$2:$F$301,$W6)&"") | G6: =IF($W6="","",INDEX('Per Line'!$G$2:$G$301,$W6)&"") | H6: =IF($W6="","",INDEX('Per Line'!$H$2:$H$301,$W6)&"") | I6: =IF($W6="","",INDEX('Per Line'!$I$2:$I$301,$W6)) | J6: =IF($W6="","",I6*U6/100) | K6: =IF($W6="","",INDEX('Per Line'!$R$2:$R$301,$W6)&"") | L6: =IF($W6="","",SUMIFS('Per Line'!$Q$2:$Q$301,'Per Line'!$B$2:$B$301,$C6,'Per Line'!$AA$2:$AA$301,1)) | M6: =IF($W6="","",Settings!$C$7) | N6: =IF($W6="","",SUMIFS('Per Line'!$Q$2:$Q$301,'Per Line'!$B$2:$B$301,$C6,'Per Line'!$Z$2:$Z$301,0,'Per Line'!$AA$2:$AA$301,0)) | O6: =IF($W6="","",N6*M6) | P6: =IF($W6="","",Settings!$C$6) | Q6: =IF($W6="","",SUMIFS('Per Line'!$Q$2:$Q$301,'Per Line'!$B$2:$B$301,$C6,'Per Line'!$Z$2:$Z$301,1,'Per Line'!$AA$2:$AA$301,0)) | R6: =IF($W6="","",Q6*P6) | S6: =IF($W6="","",R6+O6) | T6: =IF($W6="","",U6-S6) | U6: =IF($W6="","",N6+Q6+L6) | V6: =IF($W6="","",U6-S6-J6) | W6: =IF(ROWS($W$2:$W6)<=MAX('Per Line'!$Y$2:$Y$301),MATCH(ROWS($W$2:$W6),'Per Line'!$Y$2:$Y$301,0),"")
B7: =IF($W7="","",INDEX('Per Line'!$A$2:$A$301,$W7)&"") | C7: =IF($W7="","",INDEX('Per Line'!$B$2:$B$301,$W7)&"") | D7: =IF($W7="","",INDEX('Per Line'!$C$2:$C$301,$W7)) | E7: =IF($W7="","",INDEX('Per Line'!$E$2:$E$301,$W7)&"") | F7: =IF($W7="","",INDEX('Per Line'!$F$2:$F$301,$W7)&"") | G7: =IF($W7="","",INDEX('Per Line'!$G$2:$G$301,$W7)&"") | H7: =IF($W7="","",INDEX('Per Line'!$H$2:$H$301,$W7)&"") | I7: =IF($W7="","",INDEX('Per Line'!$I$2:$I$301,$W7)) | J7: =IF($W7="","",I7*U7/100) | K7: =IF($W7="","",INDEX('Per Line'!$R$2:$R$301,$W7)&"") | L7: =IF($W7="","",SUMIFS('Per Line'!$Q$2:$Q$301,'Per Line'!$B$2:$B$301,$C7,'Per Line'!$AA$2:$AA$301,1)) | M7: =IF($W7="","",Settings!$C$7) | N7: =IF($W7="","",SUMIFS('Per Line'!$Q$2:$Q$301,'Per Line'!$B$2:$B$301,$C7,'Per Line'!$Z$2:$Z$301,0,'Per Line'!$AA$2:$AA$301,0)) | O7: =IF($W7="","",N7*M7) | P7: =IF($W7="","",Settings!$C$6) | Q7: =IF($W7="","",SUMIFS('Per Line'!$Q$2:$Q$301,'Per Line'!$B$2:$B$301,$C7,'Per Line'!$Z$2:$Z$301,1,'Per Line'!$AA$2:$AA$301,0)) | R7: =IF($W7="","",Q7*P7) | S7: =IF($W7="","",R7+O7) | T7: =IF($W7="","",U7-S7) | U7: =IF($W7="","",N7+Q7+L7) | V7: =IF($W7="","",U7-S7-J7) | W7: =IF(ROWS($W$2:$W7)<=MAX('Per Line'!$Y$2:$Y$301),MATCH(ROWS($W$2:$W7),'Per Line'!$Y$2:$Y$301,0),"")
B8: =IF($W8="","",INDEX('Per Line'!$A$2:$A$301,$W8)&"") | C8: =IF($W8="","",INDEX('Per Line'!$B$2:$B$301,$W8)&"") | D8: =IF($W8="","",INDEX('Per Line'!$C$2:$C$301,$W8)) | E8: =IF($W8="","",INDEX('Per Line'!$E$2:$E$301,$W8)&"") | F8: =IF($W8="","",INDEX('Per Line'!$F$2:$F$301,$W8)&"") | G8: =IF($W8="","",INDEX('Per Line'!$G$2:$G$301,$W8)&"") | H8: =IF($W8="","",INDEX('Per Line'!$H$2:$H$301,$W8)&"") | I8: =IF($W8="","",INDEX('Per Line'!$I$2:$I$301,$W8)) | J8: =IF($W8="","",I8*U8/100) | K8: =IF($W8="","",INDEX('Per Line'!$R$2:$R$301,$W8)&"") | L8: =IF($W8="","",SUMIFS('Per Line'!$Q$2:$Q$301,'Per Line'!$B$2:$B$301,$C8,'Per Line'!$AA$2:$AA$301,1)) | M8: =IF($W8="","",Settings!$C$7) | N8: =IF($W8="","",SUMIFS('Per Line'!$Q$2:$Q$301,'Per Line'!$B$2:$B$301,$C8,'Per Line'!$Z$2:$Z$301,0,'Per Line'!$AA$2:$AA$301,0)) | O8: =IF($W8="","",N8*M8) | P8: =IF($W8="","",Settings!$C$6) | Q8: =IF($W8="","",SUMIFS('Per Line'!$Q$2:$Q$301,'Per Line'!$B$2:$B$301,$C8,'Per Line'!$Z$2:$Z$301,1,'Per Line'!$AA$2:$AA$301,0)) | R8: =IF($W8="","",Q8*P8) | S8: =IF($W8="","",R8+O8) | T8: =IF($W8="","",U8-S8) | U8: =IF($W8="","",N8+Q8+L8) | V8: =IF($W8="","",U8-S8-J8) | W8: =IF(ROWS($W$2:$W8)<=MAX('Per Line'!$Y$2:$Y$301),MATCH(ROWS($W$2:$W8),'Per Line'!$Y$2:$Y$301,0),"")
B9: =IF($W9="","",INDEX('Per Line'!$A$2:$A$301,$W9)&"") | C9: =IF($W9="","",INDEX('Per Line'!$B$2:$B$301,$W9)&"") | D9: =IF($W9="","",INDEX('Per Line'!$C$2:$C$301,$W9)) | E9: =IF($W9="","",INDEX('Per Line'!$E$2:$E$301,$W9)&"") | F9: =IF($W9="","",INDEX('Per Line'!$F$2:$F$301,$W9)&"") | G9: =IF($W9="","",INDEX('Per Line'!$G$2:$G$301,$W9)&"") | H9: =IF($W9="","",INDEX('Per Line'!$H$2:$H$301,$W9)&"") | I9: =IF($W9="","",INDEX('Per Line'!$I$2:$I$301,$W9)) | J9: =IF($W9="","",I9*U9/100) | K9: =IF($W9="","",INDEX('Per Line'!$R$2:$R$301,$W9)&"") | L9: =IF($W9="","",SUMIFS('Per Line'!$Q$2:$Q$301,'Per Line'!$B$2:$B$301,$C9,'Per Line'!$AA$2:$AA$301,1)) | M9: =IF($W9="","",Settings!$C$7) | N9: =IF($W9="","",SUMIFS('Per Line'!$Q$2:$Q$301,'Per Line'!$B$2:$B$301,$C9,'Per Line'!$Z$2:$Z$301,0,'Per Line'!$AA$2:$AA$301,0)) | O9: =IF($W9="","",N9*M9) | P9: =IF($W9="","",Settings!$C$6) | Q9: =IF($W9="","",SUMIFS('Per Line'!$Q$2:$Q$301,'Per Line'!$B$2:$B$301,$C9,'Per Line'!$Z$2:$Z$301,1,'Per Line'!$AA$2:$AA$301,0)) | R9: =IF($W9="","",Q9*P9) | S9: =IF($W9="","",R9+O9) | T9: =IF($W9="","",U9-S9) | U9: =IF($W9="","",N9+Q9+L9) | V9: =IF($W9="","",U9-S9-J9) | W9: =IF(ROWS($W$2:$W9)<=MAX('Per Line'!$Y$2:$Y$301),MATCH(ROWS($W$2:$W9),'Per Line'!$Y$2:$Y$301,0),"")
B10: =IF($W10="","",INDEX('Per Line'!$A$2:$A$301,$W10)&"") | C10: =IF($W10="","",INDEX('Per Line'!$B$2:$B$301,$W10)&"") | D10: =IF($W10="","",INDEX('Per Line'!$C$2:$C$301,$W10)) | E10: =IF($W10="","",INDEX('Per Line'!$E$2:$E$301,$W10)&"") | F10: =IF($W10="","",INDEX('Per Line'!$F$2:$F$301,$W10)&"") | G10: =IF($W10="","",INDEX('Per Line'!$G$2:$G$301,$W10)&"") | H10: =IF($W10="","",INDEX('Per Line'!$H$2:$H$301,$W10)&"") | I10: =IF($W10="","",INDEX('Per Line'!$I$2:$I$301,$W10)) | J10: =IF($W10="","",I10*U10/100) | K10: =IF($W10="","",INDEX('Per Line'!$R$2:$R$301,$W10)&"") | L10: =IF($W10="","",SUMIFS('Per Line'!$Q$2:$Q$301,'Per Line'!$B$2:$B$301,$C10,'Per Line'!$AA$2:$AA$301,1)) | M10: =IF($W10="","",Settings!$C$7) | N10: =IF($W10="","",SUMIFS('Per Line'!$Q$2:$Q$301,'Per Line'!$B$2:$B$301,$C10,'Per Line'!$Z$2:$Z$301,0,'Per Line'!$AA$2:$AA$301,0)) | O10: =IF($W10="","",N10*M10) | P10: =IF($W10="","",Settings!$C$6) | Q10: =IF($W10="","",SUMIFS('Per Line'!$Q$2:$Q$301,'Per Line'!$B$2:$B$301,$C10,'Per Line'!$Z$2:$Z$301,1,'Per Line'!$AA$2:$AA$301,0)) | R10: =IF($W10="","",Q10*P10) | S10: =IF($W10="","",R10+O10) | T10: =IF($W10="","",U10-S10) | U10: =IF($W10="","",N10+Q10+L10) | V10: =IF($W10="","",U10-S10-J10) | W10: =IF(ROWS($W$2:$W10)<=MAX('Per Line'!$Y$2:$Y$301),MATCH(ROWS($W$2:$W10),'Per Line'!$Y$2:$Y$301,0),"")
B11: =IF($W11="","",INDEX('Per Line'!$A$2:$A$301,$W11)&"") | C11: =IF($W11="","",INDEX('Per Line'!$B$2:$B$301,$W11)&"") | D11: =IF($W11="","",INDEX('Per Line'!$C$2:$C$301,$W11)) | E11: =IF($W11="","",INDEX('Per Line'!$E$2:$E$301,$W11)&"") | F11: =IF($W11="","",INDEX('Per Line'!$F$2:$F$301,$W11)&"") | G11: =IF($W11="","",INDEX('Per Line'!$G$2:$G$301,$W11)&"") | H11: =IF($W11="","",INDEX('Per Line'!$H$2:$H$301,$W11)&"") | I11: =IF($W11="","",INDEX('Per Line'!$I$2:$I$301,$W11)) | J11: =IF($W11="","",I11*U11/100) | K11: =IF($W11="","",INDEX('Per Line'!$R$2:$R$301,$W11)&"") | L11: =IF($W11="","",SUMIFS('Per Line'!$Q$2:$Q$301,'Per Line'!$B$2:$B$301,$C11,'Per Line'!$AA$2:$AA$301,1)) | M11: =IF($W11="","",Settings!$C$7) | N11: =IF($W11="","",SUMIFS('Per Line'!$Q$2:$Q$301,'Per Line'!$B$2:$B$301,$C11,'Per Line'!$Z$2:$Z$301,0,'Per Line'!$AA$2:$AA$301,0)) | O11: =IF($W11="","",N11*M11) | P11: =IF($W11="","",Settings!$C$6) | Q11: =IF($W11="","",SUMIFS('Per Line'!$Q$2:$Q$301,'Per Line'!$B$2:$B$301,$C11,'Per Line'!$Z$2:$Z$301,1,'Per Line'!$AA$2:$AA$301,0)) | R11: =IF($W11="","",Q11*P11) | S11: =IF($W11="","",R11+O11) | T11: =IF($W11="","",U11-S11) | U11: =IF($W11="","",N11+Q11+L11) | V11: =IF($W11="","",U11-S11-J11) | W11: =IF(ROWS($W$2:$W11)<=MAX('Per Line'!$Y$2:$Y$301),MATCH(ROWS($W$2:$W11),'Per Line'!$Y$2:$Y$301,0),"")
B12: =IF($W12="","",INDEX('Per Line'!$A$2:$A$301,$W12)&"") | C12: =IF($W12="","",INDEX('Per Line'!$B$2:$B$301,$W12)&"") | D12: =IF($W12="","",INDEX('Per Line'!$C$2:$C$301,$W12)) | E12: =IF($W12="","",INDEX('Per Line'!$E$2:$E$301,$W12)&"") | F12: =IF($W12="","",INDEX('Per Line'!$F$2:$F$301,$W12)&"") | G12: =IF($W12="","",INDEX('Per Line'!$G$2:$G$301,$W12)&"") | H12: =IF($W12="","",INDEX('Per Line'!$H$2:$H$301,$W12)&"") | I12: =IF($W12="","",INDEX('Per Line'!$I$2:$I$301,$W12)) | J12: =IF($W12="","",I12*U12/100) | K12: =IF($W12="","",INDEX('Per Line'!$R$2:$R$301,$W12)&"") | L12: =IF($W12="","",SUMIFS('Per Line'!$Q$2:$Q$301,'Per Line'!$B$2:$B$301,$C12,'Per Line'!$AA$2:$AA$301,1)) | M12: =IF($W12="","",Settings!$C$7) | N12: =IF($W12="","",SUMIFS('Per Line'!$Q$2:$Q$301,'Per Line'!$B$2:$B$301,$C12,'Per Line'!$Z$2:$Z$301,0,'Per Line'!$AA$2:$AA$301,0)) | O12: =IF($W12="","",N12*M12) | P12: =IF($W12="","",Settings!$C$6) | Q12: =IF($W12="","",SUMIFS('Per Line'!$Q$2:$Q$301,'Per Line'!$B$2:$B$301,$C12,'Per Line'!$Z$2:$Z$301,1,'Per Line'!$AA$2:$AA$301,0)) | R12: =IF($W12="","",Q12*P12) | S12: =IF($W12="","",R12+O12) | T12: =IF($W12="","",U12-S12) | U12: =IF($W12="","",N12+Q12+L12) | V12: =IF($W12="","",U12-S12-J12) | W12: =IF(ROWS($W$2:$W12)<=MAX('Per Line'!$Y$2:$Y$301),MATCH(ROWS($W$2:$W12),'Per Line'!$Y$2:$Y$301,0),"")
B13: =IF($W13="","",INDEX('Per Line'!$A$2:$A$301,$W13)&"") | C13: =IF($W13="","",INDEX('Per Line'!$B$2:$B$301,$W13)&"") | D13: =IF($W13="","",INDEX('Per Line'!$C$2:$C$301,$W13)) | E13: =IF($W13="","",INDEX('Per Line'!$E$2:$E$301,$W13)&"") | F13: =IF($W13="","",INDEX('Per Line'!$F$2:$F$301,$W13)&"") | G13: =IF($W13="","",INDEX('Per Line'!$G$2:$G$301,$W13)&"") | H13: =IF($W13="","",INDEX('Per Line'!$H$2:$H$301,$W13)&"") | I13: =IF($W13="","",INDEX('Per Line'!$I$2:$I$301,$W13)) | J13: =IF($W13="","",I13*U13/100) | K13: =IF($W13="","",INDEX('Per Line'!$R$2:$R$301,$W13)&"") | L13: =IF($W13="","",SUMIFS('Per Line'!$Q$2:$Q$301,'Per Line'!$B$2:$B$301,$C13,'Per Line'!$AA$2:$AA$301,1)) | M13: =IF($W13="","",Settings!$C$7) | N13: =IF($W13="","",SUMIFS('Per Line'!$Q$2:$Q$301,'Per Line'!$B$2:$B$301,$C13,'Per Line'!$Z$2:$Z$301,0,'Per Line'!$AA$2:$AA$301,0)) | O13: =IF($W13="","",N13*M13) | P13: =IF($W13="","",Settings!$C$6) | Q13: =IF($W13="","",SUMIFS('Per Line'!$Q$2:$Q$301,'Per Line'!$B$2:$B$301,$C13,'Per Line'!$Z$2:$Z$301,1,'Per Line'!$AA$2:$AA$301,0)) | R13: =IF($W13="","",Q13*P13) | S13: =IF($W13="","",R13+O13) | T13: =IF($W13="","",U13-S13) | U13: =IF($W13="","",N13+Q13+L13) | V13: =IF($W13="","",U13-S13-J13) | W13: =IF(ROWS($W$2:$W13)<=MAX('Per Line'!$Y$2:$Y$301),MATCH(ROWS($W$2:$W13),'Per Line'!$Y$2:$Y$301,0),"")
... B101: =IF($W101="","",INDEX('Per Line'!$A$2:$A$301,$W101)&"") | C101: =IF($W101="","",INDEX('Per Line'!$B$2:$B$301,$W101)&"") | D101: =IF($W101="","",INDEX('Per Line'!$C$2:$C$301,$W101)) | E101: =IF($W101="","",INDEX('Per Line'!$E$2:$E$301,$W101)&"") | F101: =IF($W101="","",INDEX('Per Line'!$F$2:$F$301,$W101)&"") | G101: =IF($W101="","",INDEX('Per Line'!$G$2:$G$301,$W101)&"") | H101: =IF($W101="","",INDEX('Per Line'!$H$2:$H$301,$W101)&"") | I101: =IF($W101="","",INDEX('Per Line'!$I$2:$I$301,$W101)) | J101: =IF($W101="","",I101*U101/100) | K101: =IF($W101="","",INDEX('Per Line'!$R$2:$R$301,$W101)&"") | L101: =IF($W101="","",SUMIFS('Per Line'!$Q$2:$Q$301,'Per Line'!$B$2:$B$301,$C101,'Per Line'!$AA$2:$AA$301,1)) | M101: =IF($W101="","",Settings!$C$7) | N101: =IF($W101="","",SUMIFS('Per Line'!$Q$2:$Q$301,'Per Line'!$B$2:$B$301,$C101,'Per Line'!$Z$2:$Z$301,0,'Per Line'!$AA$2:$AA$301,0)) | O101: =IF($W101="","",N101*M101) | P101: =IF($W101="","",Settings!$C$6) | Q101: =IF($W101="","",SUMIFS('Per Line'!$Q$2:$Q$301,'Per Line'!$B$2:$B$301,$C101,'Per Line'!$Z$2:$Z$301,1,'Per Line'!$AA$2:$AA$301,0)) | R101: =IF($W101="","",Q101*P101) | S101: =IF($W101="","",R101+O101) | T101: =IF($W101="","",U101-S101) | U101: =IF($W101="","",N101+Q101+L101) | V101: =IF($W101="","",U101-S101-J101) | W101: =IF(ROWS($W$2:$W101)<=MAX('Per Line'!$Y$2:$Y$301),MATCH(ROWS($W$2:$W101),'Per Line'!$Y$2:$Y$301,0),"")
