Workbook

Sheet How To Use
A1: Claims Template - AXA SERVICES EGYPT - GHABBOUR OFFLINE (Chronic)
A3: Monthly steps
A4: 1. Open the 'Per Line' tab. Delete the old data in the BLUE columns only (row 2 down). Never delete the green or grey columns.
A5: 2. Paste the new month's data as VALUES starting at A2, into the blue columns: A-M, O-V, Z-AA, AC-AJ (same order as the system export).
A6: 3. Green columns (N, W, X, Y, AB) and the grey helper columns (AK-AO) calculate automatically - do not paste over them.
A7: 4. 'Per Invoice' fills itself from 'Per Line' (one row per Order #, split into IMP / Local). No pivot table, no refresh.
A8: 5. The ONLY manual column in 'Per Invoice' is column A 'Invoice' (blue): type it yourself. Everything else is formula.
A9: 6. Open 'Settings' and check STATUS says OK (Per Line totals = Per Invoice totals).
A11: Colour legend
A12: Blue header = typed/pasted by you (raw data, and 'Invoice' in Per Invoice). Green header = formula (do not paste over). Grey header = helper formula (do not touch). Yellow cell (Settings) = editable rate.
A14: Calculation rules (taken from the September 2026 sheet)
A15: Co val = Order Co Payment x Subtotal / 100. Discount = Total x Rebates / 100. Subtotal = Total - Discount. Net = Subtotal - Co val. (Total = 'Product Total')
... A20: Capacity: up to 200 lines and 60 invoices per month. A line with an empty Order # is ignored.

Sheet Settings
B1: Company settings & checks
B3: Insurance Company | C3: AXA SERVICES EGYPT - GHABBOUR OFFLINE | D3: Informational only
B4: Corporate | C4: Ghabbour-AXA-Offline | D4: Informational only
B5: Sheet type | C5: Chronic | D5: Informational only
B6: Local products rebate % | C6: 0.14 | D6: Source: AXA sheets (Rebates = 14 on Local lines).
B7: Imported (IMP) products rebate % | C7: 0.07 | D7: Source: AXA sheets (Rebates = 7 on non-local lines).
B8: Special rebate % (Special Rebates? = Yes) | C8: 0.05 | D8: Lines flagged Special Rebates? = Yes get this rate (local or imported).
B9: Month totals / reconciliation
B10: Lines loaded | C10: =COUNTA('Per Line'!$D$2:$D$201)
B11: Invoices (unique Order #) | C11: =MAX('Per Line'!$AL$2:$AL$201)
B12: Invoices shown in Per Invoice | C12: =SUMPRODUCT(--('Per Invoice'!$B$2:$B$61<>""))
B13: Grand Total - Per Line (Product Total) | C13: =SUM('Per Line'!$V$2:$V$201)
B14: Grand Total - Per Invoice | C14: =SUM('Per Invoice'!$AF$2:$AF$61)
B15: Discount - Per Line | C15: =SUM('Per Line'!$W$2:$W$201)
B16: Discount - Per Invoice | C16: =SUM('Per Invoice'!$AD$2:$AD$61)
B17: Co val - Per Line | C17: =SUM('Per Line'!$N$2:$N$201)
B18: Co val - Per Invoice | C18: =SUM('Per Invoice'!$N$2:$N$61)
B19: Net - Per Line | C19: =SUM('Per Line'!$Y$2:$Y$201)
B20: Net - Per Invoice | C20: =SUM('Per Invoice'!$AG$2:$AG$61)
B21: Max Limit adjustment (Co val, Per Invoice only) | C21: 0 | D21: This company's Per Invoice has no Max Limit rule.
B23: STATUS | C23: =IF(C10=0,"No data loaded",IF(COUNTA('Per Line'!$D:$D)-1>200,"TOO MANY LINES - extend template",IF(C11>60,"TOO MANY INVOICES - extend template",IF(AND(ROUND(C13-C14,2)=0,ROUND(C15-C16,2)=0,ROUND(C17+C21-C18,2)=0,ROUND(C19-C21-C20,2)=0,C11=C12),"OK","CHECK - Per Line and Per Invoice do not match")))) | D23: Must say OK after you paste the month data.

Sheet Per Line
A1: Batch ID | B1: Ticket # | C1: Stage | D1: Order # | E1: Channel | F1: Create At | G1: Insurance Company | H1: Country Portal ID | I1: Corporate | J1: Card | K1: Name | L1: Status | M1: Order Co Payment | N1: Co val | O1: By Patient | P1: heisenberg id | Q1: Product Name | R1: Local | S1: Unit | T1: Quantity | U1: Unit Price | V1: Product Total | W1: Discount | X1: Subtotal | Y1: Net | Z1: ERX ID | AA1: Special Rebates? | AB1: Rebates | AC1: Approval Type | AD1: Max Limit | AE1: Exceeding Limit | AF1: Amount collected from customer | AG1: By Patient (Delivered) | AH1: Dispense Number | AI1: Dispense Date | AJ1: Has OTP? | AK1: Order 1st Row (helper) | AL1: Invoice # (helper) | AM1: Is Local (helper) | AN1: Is Special (helper) | AO1: Sort Key (helper)
N2: =IF($D2="","",M2*X2/100) | W2: =IF($D2="","",V2*AB2/100) | X2: =IF($D2="","",V2-W2) | Y2: =IF($D2="","",X2-N2) | AB2: =IF($D2="","",IF($AN2=1,Settings!$C$8,IF($AM2=1,Settings!$C$6,Settings!$C$7))*100) | AK2: =IF($D2="","",IF(COUNTIF($D$2:$D2,$D2)=1,1,0)) | AL2: =IF($AK2=1,SUMPRODUCT(--($AO$2:$AO$201<$AO2))+1,"") | AM2: =IF($D2="","",IF(OR($R2=TRUE(),$R2="TRUE"),1,0)) | AN2: =IF($D2="","",IF($AA2="Yes",1,0)) | AO2: =IF($AK2=1,IFERROR(IF(VALUE($D2)<100000000,VALUE($D2),1000000000),IFERROR(IF(VALUE(MID($D2,2,20))<100000000,VALUE(MID($D2,2,20)),1000000000),1000000000))+ROW()/100000,"")
N3: =IF($D3="","",M3*X3/100) | W3: =IF($D3="","",V3*AB3/100) | X3: =IF($D3="","",V3-W3) | Y3: =IF($D3="","",X3-N3) | AB3: =IF($D3="","",IF($AN3=1,Settings!$C$8,IF($AM3=1,Settings!$C$6,Settings!$C$7))*100) | AK3: =IF($D3="","",IF(COUNTIF($D$2:$D3,$D3)=1,1,0)) | AL3: =IF($AK3=1,SUMPRODUCT(--($AO$2:$AO$201<$AO3))+1,"") | AM3: =IF($D3="","",IF(OR($R3=TRUE(),$R3="TRUE"),1,0)) | AN3: =IF($D3="","",IF($AA3="Yes",1,0)) | AO3: =IF($AK3=1,IFERROR(IF(VALUE($D3)<100000000,VALUE($D3),1000000000),IFERROR(IF(VALUE(MID($D3,2,20))<100000000,VALUE(MID($D3,2,20)),1000000000),1000000000))+ROW()/100000,"")
N4: =IF($D4="","",M4*X4/100) | W4: =IF($D4="","",V4*AB4/100) | X4: =IF($D4="","",V4-W4) | Y4: =IF($D4="","",X4-N4) | AB4: =IF($D4="","",IF($AN4=1,Settings!$C$8,IF($AM4=1,Settings!$C$6,Settings!$C$7))*100) | AK4: =IF($D4="","",IF(COUNTIF($D$2:$D4,$D4)=1,1,0)) | AL4: =IF($AK4=1,SUMPRODUCT(--($AO$2:$AO$201<$AO4))+1,"") | AM4: =IF($D4="","",IF(OR($R4=TRUE(),$R4="TRUE"),1,0)) | AN4: =IF($D4="","",IF($AA4="Yes",1,0)) | AO4: =IF($AK4=1,IFERROR(IF(VALUE($D4)<100000000,VALUE($D4),1000000000),IFERROR(IF(VALUE(MID($D4,2,20))<100000000,VALUE(MID($D4,2,20)),1000000000),1000000000))+ROW()/100000,"")
N5: =IF($D5="","",M5*X5/100) | W5: =IF($D5="","",V5*AB5/100) | X5: =IF($D5="","",V5-W5) | Y5: =IF($D5="","",X5-N5) | AB5: =IF($D5="","",IF($AN5=1,Settings!$C$8,IF($AM5=1,Settings!$C$6,Settings!$C$7))*100) | AK5: =IF($D5="","",IF(COUNTIF($D$2:$D5,$D5)=1,1,0)) | AL5: =IF($AK5=1,SUMPRODUCT(--($AO$2:$AO$201<$AO5))+1,"") | AM5: =IF($D5="","",IF(OR($R5=TRUE(),$R5="TRUE"),1,0)) | AN5: =IF($D5="","",IF($AA5="Yes",1,0)) | AO5: =IF($AK5=1,IFERROR(IF(VALUE($D5)<100000000,VALUE($D5),1000000000),IFERROR(IF(VALUE(MID($D5,2,20))<100000000,VALUE(MID($D5,2,20)),1000000000),1000000000))+ROW()/100000,"")
N6: =IF($D6="","",M6*X6/100) | W6: =IF($D6="","",V6*AB6/100) | X6: =IF($D6="","",V6-W6) | Y6: =IF($D6="","",X6-N6) | AB6: =IF($D6="","",IF($AN6=1,Settings!$C$8,IF($AM6=1,Settings!$C$6,Settings!$C$7))*100) | AK6: =IF($D6="","",IF(COUNTIF($D$2:$D6,$D6)=1,1,0)) | AL6: =IF($AK6=1,SUMPRODUCT(--($AO$2:$AO$201<$AO6))+1,"") | AM6: =IF($D6="","",IF(OR($R6=TRUE(),$R6="TRUE"),1,0)) | AN6: =IF($D6="","",IF($AA6="Yes",1,0)) | AO6: =IF($AK6=1,IFERROR(IF(VALUE($D6)<100000000,VALUE($D6),1000000000),IFERROR(IF(VALUE(MID($D6,2,20))<100000000,VALUE(MID($D6,2,20)),1000000000),1000000000))+ROW()/100000,"")
N7: =IF($D7="","",M7*X7/100) | W7: =IF($D7="","",V7*AB7/100) | X7: =IF($D7="","",V7-W7) | Y7: =IF($D7="","",X7-N7) | AB7: =IF($D7="","",IF($AN7=1,Settings!$C$8,IF($AM7=1,Settings!$C$6,Settings!$C$7))*100) | AK7: =IF($D7="","",IF(COUNTIF($D$2:$D7,$D7)=1,1,0)) | AL7: =IF($AK7=1,SUMPRODUCT(--($AO$2:$AO$201<$AO7))+1,"") | AM7: =IF($D7="","",IF(OR($R7=TRUE(),$R7="TRUE"),1,0)) | AN7: =IF($D7="","",IF($AA7="Yes",1,0)) | AO7: =IF($AK7=1,IFERROR(IF(VALUE($D7)<100000000,VALUE($D7),1000000000),IFERROR(IF(VALUE(MID($D7,2,20))<100000000,VALUE(MID($D7,2,20)),1000000000),1000000000))+ROW()/100000,"")
N8: =IF($D8="","",M8*X8/100) | W8: =IF($D8="","",V8*AB8/100) | X8: =IF($D8="","",V8-W8) | Y8: =IF($D8="","",X8-N8) | AB8: =IF($D8="","",IF($AN8=1,Settings!$C$8,IF($AM8=1,Settings!$C$6,Settings!$C$7))*100) | AK8: =IF($D8="","",IF(COUNTIF($D$2:$D8,$D8)=1,1,0)) | AL8: =IF($AK8=1,SUMPRODUCT(--($AO$2:$AO$201<$AO8))+1,"") | AM8: =IF($D8="","",IF(OR($R8=TRUE(),$R8="TRUE"),1,0)) | AN8: =IF($D8="","",IF($AA8="Yes",1,0)) | AO8: =IF($AK8=1,IFERROR(IF(VALUE($D8)<100000000,VALUE($D8),1000000000),IFERROR(IF(VALUE(MID($D8,2,20))<100000000,VALUE(MID($D8,2,20)),1000000000),1000000000))+ROW()/100000,"")
N9: =IF($D9="","",M9*X9/100) | W9: =IF($D9="","",V9*AB9/100) | X9: =IF($D9="","",V9-W9) | Y9: =IF($D9="","",X9-N9) | AB9: =IF($D9="","",IF($AN9=1,Settings!$C$8,IF($AM9=1,Settings!$C$6,Settings!$C$7))*100) | AK9: =IF($D9="","",IF(COUNTIF($D$2:$D9,$D9)=1,1,0)) | AL9: =IF($AK9=1,SUMPRODUCT(--($AO$2:$AO$201<$AO9))+1,"") | AM9: =IF($D9="","",IF(OR($R9=TRUE(),$R9="TRUE"),1,0)) | AN9: =IF($D9="","",IF($AA9="Yes",1,0)) | AO9: =IF($AK9=1,IFERROR(IF(VALUE($D9)<100000000,VALUE($D9),1000000000),IFERROR(IF(VALUE(MID($D9,2,20))<100000000,VALUE(MID($D9,2,20)),1000000000),1000000000))+ROW()/100000,"")
N10: =IF($D10="","",M10*X10/100) | W10: =IF($D10="","",V10*AB10/100) | X10: =IF($D10="","",V10-W10) | Y10: =IF($D10="","",X10-N10) | AB10: =IF($D10="","",IF($AN10=1,Settings!$C$8,IF($AM10=1,Settings!$C$6,Settings!$C$7))*100) | AK10: =IF($D10="","",IF(COUNTIF($D$2:$D10,$D10)=1,1,0)) | AL10: =IF($AK10=1,SUMPRODUCT(--($AO$2:$AO$201<$AO10))+1,"") | AM10: =IF($D10="","",IF(OR($R10=TRUE(),$R10="TRUE"),1,0)) | AN10: =IF($D10="","",IF($AA10="Yes",1,0)) | AO10: =IF($AK10=1,IFERROR(IF(VALUE($D10)<100000000,VALUE($D10),1000000000),IFERROR(IF(VALUE(MID($D10,2,20))<100000000,VALUE(MID($D10,2,20)),1000000000),1000000000))+ROW()/100000,"")
N11: =IF($D11="","",M11*X11/100) | W11: =IF($D11="","",V11*AB11/100) | X11: =IF($D11="","",V11-W11) | Y11: =IF($D11="","",X11-N11) | AB11: =IF($D11="","",IF($AN11=1,Settings!$C$8,IF($AM11=1,Settings!$C$6,Settings!$C$7))*100) | AK11: =IF($D11="","",IF(COUNTIF($D$2:$D11,$D11)=1,1,0)) | AL11: =IF($AK11=1,SUMPRODUCT(--($AO$2:$AO$201<$AO11))+1,"") | AM11: =IF($D11="","",IF(OR($R11=TRUE(),$R11="TRUE"),1,0)) | AN11: =IF($D11="","",IF($AA11="Yes",1,0)) | AO11: =IF($AK11=1,IFERROR(IF(VALUE($D11)<100000000,VALUE($D11),1000000000),IFERROR(IF(VALUE(MID($D11,2,20))<100000000,VALUE(MID($D11,2,20)),1000000000),1000000000))+ROW()/100000,"")
N12: =IF($D12="","",M12*X12/100) | W12: =IF($D12="","",V12*AB12/100) | X12: =IF($D12="","",V12-W12) | Y12: =IF($D12="","",X12-N12) | AB12: =IF($D12="","",IF($AN12=1,Settings!$C$8,IF($AM12=1,Settings!$C$6,Settings!$C$7))*100) | AK12: =IF($D12="","",IF(COUNTIF($D$2:$D12,$D12)=1,1,0)) | AL12: =IF($AK12=1,SUMPRODUCT(--($AO$2:$AO$201<$AO12))+1,"") | AM12: =IF($D12="","",IF(OR($R12=TRUE(),$R12="TRUE"),1,0)) | AN12: =IF($D12="","",IF($AA12="Yes",1,0)) | AO12: =IF($AK12=1,IFERROR(IF(VALUE($D12)<100000000,VALUE($D12),1000000000),IFERROR(IF(VALUE(MID($D12,2,20))<100000000,VALUE(MID($D12,2,20)),1000000000),1000000000))+ROW()/100000,"")
N13: =IF($D13="","",M13*X13/100) | W13: =IF($D13="","",V13*AB13/100) | X13: =IF($D13="","",V13-W13) | Y13: =IF($D13="","",X13-N13) | AB13: =IF($D13="","",IF($AN13=1,Settings!$C$8,IF($AM13=1,Settings!$C$6,Settings!$C$7))*100) | AK13: =IF($D13="","",IF(COUNTIF($D$2:$D13,$D13)=1,1,0)) | AL13: =IF($AK13=1,SUMPRODUCT(--($AO$2:$AO$201<$AO13))+1,"") | AM13: =IF($D13="","",IF(OR($R13=TRUE(),$R13="TRUE"),1,0)) | AN13: =IF($D13="","",IF($AA13="Yes",1,0)) | AO13: =IF($AK13=1,IFERROR(IF(VALUE($D13)<100000000,VALUE($D13),1000000000),IFERROR(IF(VALUE(MID($D13,2,20))<100000000,VALUE(MID($D13,2,20)),1000000000),1000000000))+ROW()/100000,"")
... N201: =IF($D201="","",M201*X201/100) | W201: =IF($D201="","",V201*AB201/100) | X201: =IF($D201="","",V201-W201) | Y201: =IF($D201="","",X201-N201) | AB201: =IF($D201="","",IF($AN201=1,Settings!$C$8,IF($AM201=1,Settings!$C$6,Settings!$C$7))*100) | AK201: =IF($D201="","",IF(COUNTIF($D$2:$D201,$D201)=1,1,0)) | AL201: =IF($AK201=1,SUMPRODUCT(--($AO$2:$AO$201<$AO201))+1,"") | AM201: =IF($D201="","",IF(OR($R201=TRUE(),$R201="TRUE"),1,0)) | AN201: =IF($D201="","",IF($AA201="Yes",1,0)) | AO201: =IF($AK201=1,IFERROR(IF(VALUE($D201)<100000000,VALUE($D201),1000000000),IFERROR(IF(VALUE(MID($D201,2,20))<100000000,VALUE(MID($D201,2,20)),1000000000),1000000000))+ROW()/100000,"")

Sheet Per Invoice
A1: Invoice | B1: Order # | C1: Batch ID | D1: Ticket # | E1: Stage | F1: Channel | G1: Create At | H1: Insurance Company | I1: Corporate | J1: Card | K1: Name | L1: Status | M1: Order Co Payment | N1: Co val | O1: ERX ID | P1: Approval Type | Q1: Max Limit | R1: Exceeding Limit | S1: Dispense Number | T1: Dispense Date | U1: SP% | V1: SP | W1: SP VAL | X1: IMP% | Y1: IMP | Z1: IMP VAL | AA1: LOCAL% | AB1: LOCAL | AC1: LOCAL VAL | AD1: TOTAL VAL | AE1: SUBTOTAL | AF1: Grand Total | AG1: NET | AH1: Src Row (helper)
B2: =IF($AH2="","",INDEX('Per Line'!$D$2:$D$201,$AH2)&"") | C2: =IF($AH2="","",INDEX('Per Line'!$A$2:$A$201,$AH2)&"") | D2: =IF($AH2="","",INDEX('Per Line'!$B$2:$B$201,$AH2)) | E2: =IF($AH2="","",INDEX('Per Line'!$C$2:$C$201,$AH2)&"") | F2: =IF($AH2="","",INDEX('Per Line'!$E$2:$E$201,$AH2)&"") | G2: =IF($AH2="","",INDEX('Per Line'!$F$2:$F$201,$AH2)) | H2: =IF($AH2="","",INDEX('Per Line'!$G$2:$G$201,$AH2)&"") | I2: =IF($AH2="","",INDEX('Per Line'!$I$2:$I$201,$AH2)&"") | J2: =IF($AH2="","",INDEX('Per Line'!$J$2:$J$201,$AH2)&"") | K2: =IF($AH2="","",INDEX('Per Line'!$K$2:$K$201,$AH2)&"") | L2: =IF($AH2="","",INDEX('Per Line'!$L$2:$L$201,$AH2)&"") | M2: =IF($AH2="","",INDEX('Per Line'!$M$2:$M$201,$AH2)) | N2: =IF($AH2="","",M2*AE2/100) | O2: =IF($AH2="","",INDEX('Per Line'!$Z$2:$Z$201,$AH2)&"") | P2: =IF($AH2="","",INDEX('Per Line'!$AC$2:$AC$201,$AH2)&"") | Q2: =IF($AH2="","",INDEX('Per Line'!$AD$2:$AD$201,$AH2)) | R2: =IF($AH2="","",IF(AND(ISNUMBER(Q2),Q2>0),AF2>Q2,FALSE)) | S2: =IF($AH2="","",INDEX('Per Line'!$AH$2:$AH$201,$AH2)&"") | T2: =IF($AH2="","",INDEX('Per Line'!$AI$2:$AI$201,$AH2)) | U2: =IF($AH2="","",Settings!$C$8) | V2: =IF($AH2="","",SUMIFS('Per Line'!$V$2:$V$201,'Per Line'!$D$2:$D$201,$B2,'Per Line'!$AN$2:$AN$201,1)) | W2: =IF($AH2="","",V2*U2) | X2: =IF($AH2="","",Settings!$C$7) | Y2: =IF($AH2="","",SUMIFS('Per Line'!$V$2:$V$201,'Per Line'!$D$2:$D$201,$B2,'Per Line'!$AM$2:$AM$201,0,'Per Line'!$AN$2:$AN$201,0)) | Z2: =IF($AH2="","",Y2*X2) | AA2: =IF($AH2="","",Settings!$C$6) | AB2: =IF($AH2="","",SUMIFS('Per Line'!$V$2:$V$201,'Per Line'!$D$2:$D$201,$B2,'Per Line'!$AM$2:$AM$201,1,'Per Line'!$AN$2:$AN$201,0)) | AC2: =IF($AH2="","",AB2*AA2) | AD2: =IF($AH2="","",AC2+Z2+W2) | AE2: =IF($AH2="","",AF2-AD2) | AF2: =IF($AH2="","",Y2+AB2+V2) | AG2: =IF($AH2="","",AF2-AD2-N2) | AH2: =IF(ROWS($AH$2:$AH2)<=MAX('Per Line'!$AL$2:$AL$201),MATCH(ROWS($AH$2:$AH2),'Per Line'!$AL$2:$AL$201,0),"")
B3: =IF($AH3="","",INDEX('Per Line'!$D$2:$D$201,$AH3)&"") | C3: =IF($AH3="","",INDEX('Per Line'!$A$2:$A$201,$AH3)&"") | D3: =IF($AH3="","",INDEX('Per Line'!$B$2:$B$201,$AH3)) | E3: =IF($AH3="","",INDEX('Per Line'!$C$2:$C$201,$AH3)&"") | F3: =IF($AH3="","",INDEX('Per Line'!$E$2:$E$201,$AH3)&"") | G3: =IF($AH3="","",INDEX('Per Line'!$F$2:$F$201,$AH3)) | H3: =IF($AH3="","",INDEX('Per Line'!$G$2:$G$201,$AH3)&"") | I3: =IF($AH3="","",INDEX('Per Line'!$I$2:$I$201,$AH3)&"") | J3: =IF($AH3="","",INDEX('Per Line'!$J$2:$J$201,$AH3)&"") | K3: =IF($AH3="","",INDEX('Per Line'!$K$2:$K$201,$AH3)&"") | L3: =IF($AH3="","",INDEX('Per Line'!$L$2:$L$201,$AH3)&"") | M3: =IF($AH3="","",INDEX('Per Line'!$M$2:$M$201,$AH3)) | N3: =IF($AH3="","",M3*AE3/100) | O3: =IF($AH3="","",INDEX('Per Line'!$Z$2:$Z$201,$AH3)&"") | P3: =IF($AH3="","",INDEX('Per Line'!$AC$2:$AC$201,$AH3)&"") | Q3: =IF($AH3="","",INDEX('Per Line'!$AD$2:$AD$201,$AH3)) | R3: =IF($AH3="","",IF(AND(ISNUMBER(Q3),Q3>0),AF3>Q3,FALSE)) | S3: =IF($AH3="","",INDEX('Per Line'!$AH$2:$AH$201,$AH3)&"") | T3: =IF($AH3="","",INDEX('Per Line'!$AI$2:$AI$201,$AH3)) | U3: =IF($AH3="","",Settings!$C$8) | V3: =IF($AH3="","",SUMIFS('Per Line'!$V$2:$V$201,'Per Line'!$D$2:$D$201,$B3,'Per Line'!$AN$2:$AN$201,1)) | W3: =IF($AH3="","",V3*U3) | X3: =IF($AH3="","",Settings!$C$7) | Y3: =IF($AH3="","",SUMIFS('Per Line'!$V$2:$V$201,'Per Line'!$D$2:$D$201,$B3,'Per Line'!$AM$2:$AM$201,0,'Per Line'!$AN$2:$AN$201,0)) | Z3: =IF($AH3="","",Y3*X3) | AA3: =IF($AH3="","",Settings!$C$6) | AB3: =IF($AH3="","",SUMIFS('Per Line'!$V$2:$V$201,'Per Line'!$D$2:$D$201,$B3,'Per Line'!$AM$2:$AM$201,1,'Per Line'!$AN$2:$AN$201,0)) | AC3: =IF($AH3="","",AB3*AA3) | AD3: =IF($AH3="","",AC3+Z3+W3) | AE3: =IF($AH3="","",AF3-AD3) | AF3: =IF($AH3="","",Y3+AB3+V3) | AG3: =IF($AH3="","",AF3-AD3-N3) | AH3: =IF(ROWS($AH$2:$AH3)<=MAX('Per Line'!$AL$2:$AL$201),MATCH(ROWS($AH$2:$AH3),'Per Line'!$AL$2:$AL$201,0),"")
B4: =IF($AH4="","",INDEX('Per Line'!$D$2:$D$201,$AH4)&"") | C4: =IF($AH4="","",INDEX('Per Line'!$A$2:$A$201,$AH4)&"") | D4: =IF($AH4="","",INDEX('Per Line'!$B$2:$B$201,$AH4)) | E4: =IF($AH4="","",INDEX('Per Line'!$C$2:$C$201,$AH4)&"") | F4: =IF($AH4="","",INDEX('Per Line'!$E$2:$E$201,$AH4)&"") | G4: =IF($AH4="","",INDEX('Per Line'!$F$2:$F$201,$AH4)) | H4: =IF($AH4="","",INDEX('Per Line'!$G$2:$G$201,$AH4)&"") | I4: =IF($AH4="","",INDEX('Per Line'!$I$2:$I$201,$AH4)&"") | J4: =IF($AH4="","",INDEX('Per Line'!$J$2:$J$201,$AH4)&"") | K4: =IF($AH4="","",INDEX('Per Line'!$K$2:$K$201,$AH4)&"") | L4: =IF($AH4="","",INDEX('Per Line'!$L$2:$L$201,$AH4)&"") | M4: =IF($AH4="","",INDEX('Per Line'!$M$2:$M$201,$AH4)) | N4: =IF($AH4="","",M4*AE4/100) | O4: =IF($AH4="","",INDEX('Per Line'!$Z$2:$Z$201,$AH4)&"") | P4: =IF($AH4="","",INDEX('Per Line'!$AC$2:$AC$201,$AH4)&"") | Q4: =IF($AH4="","",INDEX('Per Line'!$AD$2:$AD$201,$AH4)) | R4: =IF($AH4="","",IF(AND(ISNUMBER(Q4),Q4>0),AF4>Q4,FALSE)) | S4: =IF($AH4="","",INDEX('Per Line'!$AH$2:$AH$201,$AH4)&"") | T4: =IF($AH4="","",INDEX('Per Line'!$AI$2:$AI$201,$AH4)) | U4: =IF($AH4="","",Settings!$C$8) | V4: =IF($AH4="","",SUMIFS('Per Line'!$V$2:$V$201,'Per Line'!$D$2:$D$201,$B4,'Per Line'!$AN$2:$AN$201,1)) | W4: =IF($AH4="","",V4*U4) | X4: =IF($AH4="","",Settings!$C$7) | Y4: =IF($AH4="","",SUMIFS('Per Line'!$V$2:$V$201,'Per Line'!$D$2:$D$201,$B4,'Per Line'!$AM$2:$AM$201,0,'Per Line'!$AN$2:$AN$201,0)) | Z4: =IF($AH4="","",Y4*X4) | AA4: =IF($AH4="","",Settings!$C$6) | AB4: =IF($AH4="","",SUMIFS('Per Line'!$V$2:$V$201,'Per Line'!$D$2:$D$201,$B4,'Per Line'!$AM$2:$AM$201,1,'Per Line'!$AN$2:$AN$201,0)) | AC4: =IF($AH4="","",AB4*AA4) | AD4: =IF($AH4="","",AC4+Z4+W4) | AE4: =IF($AH4="","",AF4-AD4) | AF4: =IF($AH4="","",Y4+AB4+V4) | AG4: =IF($AH4="","",AF4-AD4-N4) | AH4: =IF(ROWS($AH$2:$AH4)<=MAX('Per Line'!$AL$2:$AL$201),MATCH(ROWS($AH$2:$AH4),'Per Line'!$AL$2:$AL$201,0),"")
B5: =IF($AH5="","",INDEX('Per Line'!$D$2:$D$201,$AH5)&"") | C5: =IF($AH5="","",INDEX('Per Line'!$A$2:$A$201,$AH5)&"") | D5: =IF($AH5="","",INDEX('Per Line'!$B$2:$B$201,$AH5)) | E5: =IF($AH5="","",INDEX('Per Line'!$C$2:$C$201,$AH5)&"") | F5: =IF($AH5="","",INDEX('Per Line'!$E$2:$E$201,$AH5)&"") | G5: =IF($AH5="","",INDEX('Per Line'!$F$2:$F$201,$AH5)) | H5: =IF($AH5="","",INDEX('Per Line'!$G$2:$G$201,$AH5)&"") | I5: =IF($AH5="","",INDEX('Per Line'!$I$2:$I$201,$AH5)&"") | J5: =IF($AH5="","",INDEX('Per Line'!$J$2:$J$201,$AH5)&"") | K5: =IF($AH5="","",INDEX('Per Line'!$K$2:$K$201,$AH5)&"") | L5: =IF($AH5="","",INDEX('Per Line'!$L$2:$L$201,$AH5)&"") | M5: =IF($AH5="","",INDEX('Per Line'!$M$2:$M$201,$AH5)) | N5: =IF($AH5="","",M5*AE5/100) | O5: =IF($AH5="","",INDEX('Per Line'!$Z$2:$Z$201,$AH5)&"") | P5: =IF($AH5="","",INDEX('Per Line'!$AC$2:$AC$201,$AH5)&"") | Q5: =IF($AH5="","",INDEX('Per Line'!$AD$2:$AD$201,$AH5)) | R5: =IF($AH5="","",IF(AND(ISNUMBER(Q5),Q5>0),AF5>Q5,FALSE)) | S5: =IF($AH5="","",INDEX('Per Line'!$AH$2:$AH$201,$AH5)&"") | T5: =IF($AH5="","",INDEX('Per Line'!$AI$2:$AI$201,$AH5)) | U5: =IF($AH5="","",Settings!$C$8) | V5: =IF($AH5="","",SUMIFS('Per Line'!$V$2:$V$201,'Per Line'!$D$2:$D$201,$B5,'Per Line'!$AN$2:$AN$201,1)) | W5: =IF($AH5="","",V5*U5) | X5: =IF($AH5="","",Settings!$C$7) | Y5: =IF($AH5="","",SUMIFS('Per Line'!$V$2:$V$201,'Per Line'!$D$2:$D$201,$B5,'Per Line'!$AM$2:$AM$201,0,'Per Line'!$AN$2:$AN$201,0)) | Z5: =IF($AH5="","",Y5*X5) | AA5: =IF($AH5="","",Settings!$C$6) | AB5: =IF($AH5="","",SUMIFS('Per Line'!$V$2:$V$201,'Per Line'!$D$2:$D$201,$B5,'Per Line'!$AM$2:$AM$201,1,'Per Line'!$AN$2:$AN$201,0)) | AC5: =IF($AH5="","",AB5*AA5) | AD5: =IF($AH5="","",AC5+Z5+W5) | AE5: =IF($AH5="","",AF5-AD5) | AF5: =IF($AH5="","",Y5+AB5+V5) | AG5: =IF($AH5="","",AF5-AD5-N5) | AH5: =IF(ROWS($AH$2:$AH5)<=MAX('Per Line'!$AL$2:$AL$201),MATCH(ROWS($AH$2:$AH5),'Per Line'!$AL$2:$AL$201,0),"")
B6: =IF($AH6="","",INDEX('Per Line'!$D$2:$D$201,$AH6)&"") | C6: =IF($AH6="","",INDEX('Per Line'!$A$2:$A$201,$AH6)&"") | D6: =IF($AH6="","",INDEX('Per Line'!$B$2:$B$201,$AH6)) | E6: =IF($AH6="","",INDEX('Per Line'!$C$2:$C$201,$AH6)&"") | F6: =IF($AH6="","",INDEX('Per Line'!$E$2:$E$201,$AH6)&"") | G6: =IF($AH6="","",INDEX('Per Line'!$F$2:$F$201,$AH6)) | H6: =IF($AH6="","",INDEX('Per Line'!$G$2:$G$201,$AH6)&"") | I6: =IF($AH6="","",INDEX('Per Line'!$I$2:$I$201,$AH6)&"") | J6: =IF($AH6="","",INDEX('Per Line'!$J$2:$J$201,$AH6)&"") | K6: =IF($AH6="","",INDEX('Per Line'!$K$2:$K$201,$AH6)&"") | L6: =IF($AH6="","",INDEX('Per Line'!$L$2:$L$201,$AH6)&"") | M6: =IF($AH6="","",INDEX('Per Line'!$M$2:$M$201,$AH6)) | N6: =IF($AH6="","",M6*AE6/100) | O6: =IF($AH6="","",INDEX('Per Line'!$Z$2:$Z$201,$AH6)&"") | P6: =IF($AH6="","",INDEX('Per Line'!$AC$2:$AC$201,$AH6)&"") | Q6: =IF($AH6="","",INDEX('Per Line'!$AD$2:$AD$201,$AH6)) | R6: =IF($AH6="","",IF(AND(ISNUMBER(Q6),Q6>0),AF6>Q6,FALSE)) | S6: =IF($AH6="","",INDEX('Per Line'!$AH$2:$AH$201,$AH6)&"") | T6: =IF($AH6="","",INDEX('Per Line'!$AI$2:$AI$201,$AH6)) | U6: =IF($AH6="","",Settings!$C$8) | V6: =IF($AH6="","",SUMIFS('Per Line'!$V$2:$V$201,'Per Line'!$D$2:$D$201,$B6,'Per Line'!$AN$2:$AN$201,1)) | W6: =IF($AH6="","",V6*U6) | X6: =IF($AH6="","",Settings!$C$7) | Y6: =IF($AH6="","",SUMIFS('Per Line'!$V$2:$V$201,'Per Line'!$D$2:$D$201,$B6,'Per Line'!$AM$2:$AM$201,0,'Per Line'!$AN$2:$AN$201,0)) | Z6: =IF($AH6="","",Y6*X6) | AA6: =IF($AH6="","",Settings!$C$6) | AB6: =IF($AH6="","",SUMIFS('Per Line'!$V$2:$V$201,'Per Line'!$D$2:$D$201,$B6,'Per Line'!$AM$2:$AM$201,1,'Per Line'!$AN$2:$AN$201,0)) | AC6: =IF($AH6="","",AB6*AA6) | AD6: =IF($AH6="","",AC6+Z6+W6) | AE6: =IF($AH6="","",AF6-AD6) | AF6: =IF($AH6="","",Y6+AB6+V6) | AG6: =IF($AH6="","",AF6-AD6-N6) | AH6: =IF(ROWS($AH$2:$AH6)<=MAX('Per Line'!$AL$2:$AL$201),MATCH(ROWS($AH$2:$AH6),'Per Line'!$AL$2:$AL$201,0),"")
B7: =IF($AH7="","",INDEX('Per Line'!$D$2:$D$201,$AH7)&"") | C7: =IF($AH7="","",INDEX('Per Line'!$A$2:$A$201,$AH7)&"") | D7: =IF($AH7="","",INDEX('Per Line'!$B$2:$B$201,$AH7)) | E7: =IF($AH7="","",INDEX('Per Line'!$C$2:$C$201,$AH7)&"") | F7: =IF($AH7="","",INDEX('Per Line'!$E$2:$E$201,$AH7)&"") | G7: =IF($AH7="","",INDEX('Per Line'!$F$2:$F$201,$AH7)) | H7: =IF($AH7="","",INDEX('Per Line'!$G$2:$G$201,$AH7)&"") | I7: =IF($AH7="","",INDEX('Per Line'!$I$2:$I$201,$AH7)&"") | J7: =IF($AH7="","",INDEX('Per Line'!$J$2:$J$201,$AH7)&"") | K7: =IF($AH7="","",INDEX('Per Line'!$K$2:$K$201,$AH7)&"") | L7: =IF($AH7="","",INDEX('Per Line'!$L$2:$L$201,$AH7)&"") | M7: =IF($AH7="","",INDEX('Per Line'!$M$2:$M$201,$AH7)) | N7: =IF($AH7="","",M7*AE7/100) | O7: =IF($AH7="","",INDEX('Per Line'!$Z$2:$Z$201,$AH7)&"") | P7: =IF($AH7="","",INDEX('Per Line'!$AC$2:$AC$201,$AH7)&"") | Q7: =IF($AH7="","",INDEX('Per Line'!$AD$2:$AD$201,$AH7)) | R7: =IF($AH7="","",IF(AND(ISNUMBER(Q7),Q7>0),AF7>Q7,FALSE)) | S7: =IF($AH7="","",INDEX('Per Line'!$AH$2:$AH$201,$AH7)&"") | T7: =IF($AH7="","",INDEX('Per Line'!$AI$2:$AI$201,$AH7)) | U7: =IF($AH7="","",Settings!$C$8) | V7: =IF($AH7="","",SUMIFS('Per Line'!$V$2:$V$201,'Per Line'!$D$2:$D$201,$B7,'Per Line'!$AN$2:$AN$201,1)) | W7: =IF($AH7="","",V7*U7) | X7: =IF($AH7="","",Settings!$C$7) | Y7: =IF($AH7="","",SUMIFS('Per Line'!$V$2:$V$201,'Per Line'!$D$2:$D$201,$B7,'Per Line'!$AM$2:$AM$201,0,'Per Line'!$AN$2:$AN$201,0)) | Z7: =IF($AH7="","",Y7*X7) | AA7: =IF($AH7="","",Settings!$C$6) | AB7: =IF($AH7="","",SUMIFS('Per Line'!$V$2:$V$201,'Per Line'!$D$2:$D$201,$B7,'Per Line'!$AM$2:$AM$201,1,'Per Line'!$AN$2:$AN$201,0)) | AC7: =IF($AH7="","",AB7*AA7) | AD7: =IF($AH7="","",AC7+Z7+W7) | AE7: =IF($AH7="","",AF7-AD7) | AF7: =IF($AH7="","",Y7+AB7+V7) | AG7: =IF($AH7="","",AF7-AD7-N7) | AH7: =IF(ROWS($AH$2:$AH7)<=MAX('Per Line'!$AL$2:$AL$201),MATCH(ROWS($AH$2:$AH7),'Per Line'!$AL$2:$AL$201,0),"")
B8: =IF($AH8="","",INDEX('Per Line'!$D$2:$D$201,$AH8)&"") | C8: =IF($AH8="","",INDEX('Per Line'!$A$2:$A$201,$AH8)&"") | D8: =IF($AH8="","",INDEX('Per Line'!$B$2:$B$201,$AH8)) | E8: =IF($AH8="","",INDEX('Per Line'!$C$2:$C$201,$AH8)&"") | F8: =IF($AH8="","",INDEX('Per Line'!$E$2:$E$201,$AH8)&"") | G8: =IF($AH8="","",INDEX('Per Line'!$F$2:$F$201,$AH8)) | H8: =IF($AH8="","",INDEX('Per Line'!$G$2:$G$201,$AH8)&"") | I8: =IF($AH8="","",INDEX('Per Line'!$I$2:$I$201,$AH8)&"") | J8: =IF($AH8="","",INDEX('Per Line'!$J$2:$J$201,$AH8)&"") | K8: =IF($AH8="","",INDEX('Per Line'!$K$2:$K$201,$AH8)&"") | L8: =IF($AH8="","",INDEX('Per Line'!$L$2:$L$201,$AH8)&"") | M8: =IF($AH8="","",INDEX('Per Line'!$M$2:$M$201,$AH8)) | N8: =IF($AH8="","",M8*AE8/100) | O8: =IF($AH8="","",INDEX('Per Line'!$Z$2:$Z$201,$AH8)&"") | P8: =IF($AH8="","",INDEX('Per Line'!$AC$2:$AC$201,$AH8)&"") | Q8: =IF($AH8="","",INDEX('Per Line'!$AD$2:$AD$201,$AH8)) | R8: =IF($AH8="","",IF(AND(ISNUMBER(Q8),Q8>0),AF8>Q8,FALSE)) | S8: =IF($AH8="","",INDEX('Per Line'!$AH$2:$AH$201,$AH8)&"") | T8: =IF($AH8="","",INDEX('Per Line'!$AI$2:$AI$201,$AH8)) | U8: =IF($AH8="","",Settings!$C$8) | V8: =IF($AH8="","",SUMIFS('Per Line'!$V$2:$V$201,'Per Line'!$D$2:$D$201,$B8,'Per Line'!$AN$2:$AN$201,1)) | W8: =IF($AH8="","",V8*U8) | X8: =IF($AH8="","",Settings!$C$7) | Y8: =IF($AH8="","",SUMIFS('Per Line'!$V$2:$V$201,'Per Line'!$D$2:$D$201,$B8,'Per Line'!$AM$2:$AM$201,0,'Per Line'!$AN$2:$AN$201,0)) | Z8: =IF($AH8="","",Y8*X8) | AA8: =IF($AH8="","",Settings!$C$6) | AB8: =IF($AH8="","",SUMIFS('Per Line'!$V$2:$V$201,'Per Line'!$D$2:$D$201,$B8,'Per Line'!$AM$2:$AM$201,1,'Per Line'!$AN$2:$AN$201,0)) | AC8: =IF($AH8="","",AB8*AA8) | AD8: =IF($AH8="","",AC8+Z8+W8) | AE8: =IF($AH8="","",AF8-AD8) | AF8: =IF($AH8="","",Y8+AB8+V8) | AG8: =IF($AH8="","",AF8-AD8-N8) | AH8: =IF(ROWS($AH$2:$AH8)<=MAX('Per Line'!$AL$2:$AL$201),MATCH(ROWS($AH$2:$AH8),'Per Line'!$AL$2:$AL$201,0),"")
B9: =IF($AH9="","",INDEX('Per Line'!$D$2:$D$201,$AH9)&"") | C9: =IF($AH9="","",INDEX('Per Line'!$A$2:$A$201,$AH9)&"") | D9: =IF($AH9="","",INDEX('Per Line'!$B$2:$B$201,$AH9)) | E9: =IF($AH9="","",INDEX('Per Line'!$C$2:$C$201,$AH9)&"") | F9: =IF($AH9="","",INDEX('Per Line'!$E$2:$E$201,$AH9)&"") | G9: =IF($AH9="","",INDEX('Per Line'!$F$2:$F$201,$AH9)) | H9: =IF($AH9="","",INDEX('Per Line'!$G$2:$G$201,$AH9)&"") | I9: =IF($AH9="","",INDEX('Per Line'!$I$2:$I$201,$AH9)&"") | J9: =IF($AH9="","",INDEX('Per Line'!$J$2:$J$201,$AH9)&"") | K9: =IF($AH9="","",INDEX('Per Line'!$K$2:$K$201,$AH9)&"") | L9: =IF($AH9="","",INDEX('Per Line'!$L$2:$L$201,$AH9)&"") | M9: =IF($AH9="","",INDEX('Per Line'!$M$2:$M$201,$AH9)) | N9: =IF($AH9="","",M9*AE9/100) | O9: =IF($AH9="","",INDEX('Per Line'!$Z$2:$Z$201,$AH9)&"") | P9: =IF($AH9="","",INDEX('Per Line'!$AC$2:$AC$201,$AH9)&"") | Q9: =IF($AH9="","",INDEX('Per Line'!$AD$2:$AD$201,$AH9)) | R9: =IF($AH9="","",IF(AND(ISNUMBER(Q9),Q9>0),AF9>Q9,FALSE)) | S9: =IF($AH9="","",INDEX('Per Line'!$AH$2:$AH$201,$AH9)&"") | T9: =IF($AH9="","",INDEX('Per Line'!$AI$2:$AI$201,$AH9)) | U9: =IF($AH9="","",Settings!$C$8) | V9: =IF($AH9="","",SUMIFS('Per Line'!$V$2:$V$201,'Per Line'!$D$2:$D$201,$B9,'Per Line'!$AN$2:$AN$201,1)) | W9: =IF($AH9="","",V9*U9) | X9: =IF($AH9="","",Settings!$C$7) | Y9: =IF($AH9="","",SUMIFS('Per Line'!$V$2:$V$201,'Per Line'!$D$2:$D$201,$B9,'Per Line'!$AM$2:$AM$201,0,'Per Line'!$AN$2:$AN$201,0)) | Z9: =IF($AH9="","",Y9*X9) | AA9: =IF($AH9="","",Settings!$C$6) | AB9: =IF($AH9="","",SUMIFS('Per Line'!$V$2:$V$201,'Per Line'!$D$2:$D$201,$B9,'Per Line'!$AM$2:$AM$201,1,'Per Line'!$AN$2:$AN$201,0)) | AC9: =IF($AH9="","",AB9*AA9) | AD9: =IF($AH9="","",AC9+Z9+W9) | AE9: =IF($AH9="","",AF9-AD9) | AF9: =IF($AH9="","",Y9+AB9+V9) | AG9: =IF($AH9="","",AF9-AD9-N9) | AH9: =IF(ROWS($AH$2:$AH9)<=MAX('Per Line'!$AL$2:$AL$201),MATCH(ROWS($AH$2:$AH9),'Per Line'!$AL$2:$AL$201,0),"")
B10: =IF($AH10="","",INDEX('Per Line'!$D$2:$D$201,$AH10)&"") | C10: =IF($AH10="","",INDEX('Per Line'!$A$2:$A$201,$AH10)&"") | D10: =IF($AH10="","",INDEX('Per Line'!$B$2:$B$201,$AH10)) | E10: =IF($AH10="","",INDEX('Per Line'!$C$2:$C$201,$AH10)&"") | F10: =IF($AH10="","",INDEX('Per Line'!$E$2:$E$201,$AH10)&"") | G10: =IF($AH10="","",INDEX('Per Line'!$F$2:$F$201,$AH10)) | H10: =IF($AH10="","",INDEX('Per Line'!$G$2:$G$201,$AH10)&"") | I10: =IF($AH10="","",INDEX('Per Line'!$I$2:$I$201,$AH10)&"") | J10: =IF($AH10="","",INDEX('Per Line'!$J$2:$J$201,$AH10)&"") | K10: =IF($AH10="","",INDEX('Per Line'!$K$2:$K$201,$AH10)&"") | L10: =IF($AH10="","",INDEX('Per Line'!$L$2:$L$201,$AH10)&"") | M10: =IF($AH10="","",INDEX('Per Line'!$M$2:$M$201,$AH10)) | N10: =IF($AH10="","",M10*AE10/100) | O10: =IF($AH10="","",INDEX('Per Line'!$Z$2:$Z$201,$AH10)&"") | P10: =IF($AH10="","",INDEX('Per Line'!$AC$2:$AC$201,$AH10)&"") | Q10: =IF($AH10="","",INDEX('Per Line'!$AD$2:$AD$201,$AH10)) | R10: =IF($AH10="","",IF(AND(ISNUMBER(Q10),Q10>0),AF10>Q10,FALSE)) | S10: =IF($AH10="","",INDEX('Per Line'!$AH$2:$AH$201,$AH10)&"") | T10: =IF($AH10="","",INDEX('Per Line'!$AI$2:$AI$201,$AH10)) | U10: =IF($AH10="","",Settings!$C$8) | V10: =IF($AH10="","",SUMIFS('Per Line'!$V$2:$V$201,'Per Line'!$D$2:$D$201,$B10,'Per Line'!$AN$2:$AN$201,1)) | W10: =IF($AH10="","",V10*U10) | X10: =IF($AH10="","",Settings!$C$7) | Y10: =IF($AH10="","",SUMIFS('Per Line'!$V$2:$V$201,'Per Line'!$D$2:$D$201,$B10,'Per Line'!$AM$2:$AM$201,0,'Per Line'!$AN$2:$AN$201,0)) | Z10: =IF($AH10="","",Y10*X10) | AA10: =IF($AH10="","",Settings!$C$6) | AB10: =IF($AH10="","",SUMIFS('Per Line'!$V$2:$V$201,'Per Line'!$D$2:$D$201,$B10,'Per Line'!$AM$2:$AM$201,1,'Per Line'!$AN$2:$AN$201,0)) | AC10: =IF($AH10="","",AB10*AA10) | AD10: =IF($AH10="","",AC10+Z10+W10) | AE10: =IF($AH10="","",AF10-AD10) | AF10: =IF($AH10="","",Y10+AB10+V10) | AG10: =IF($AH10="","",AF10-AD10-N10) | AH10: =IF(ROWS($AH$2:$AH10)<=MAX('Per Line'!$AL$2:$AL$201),MATCH(ROWS($AH$2:$AH10),'Per Line'!$AL$2:$AL$201,0),"")
B11: =IF($AH11="","",INDEX('Per Line'!$D$2:$D$201,$AH11)&"") | C11: =IF($AH11="","",INDEX('Per Line'!$A$2:$A$201,$AH11)&"") | D11: =IF($AH11="","",INDEX('Per Line'!$B$2:$B$201,$AH11)) | E11: =IF($AH11="","",INDEX('Per Line'!$C$2:$C$201,$AH11)&"") | F11: =IF($AH11="","",INDEX('Per Line'!$E$2:$E$201,$AH11)&"") | G11: =IF($AH11="","",INDEX('Per Line'!$F$2:$F$201,$AH11)) | H11: =IF($AH11="","",INDEX('Per Line'!$G$2:$G$201,$AH11)&"") | I11: =IF($AH11="","",INDEX('Per Line'!$I$2:$I$201,$AH11)&"") | J11: =IF($AH11="","",INDEX('Per Line'!$J$2:$J$201,$AH11)&"") | K11: =IF($AH11="","",INDEX('Per Line'!$K$2:$K$201,$AH11)&"") | L11: =IF($AH11="","",INDEX('Per Line'!$L$2:$L$201,$AH11)&"") | M11: =IF($AH11="","",INDEX('Per Line'!$M$2:$M$201,$AH11)) | N11: =IF($AH11="","",M11*AE11/100) | O11: =IF($AH11="","",INDEX('Per Line'!$Z$2:$Z$201,$AH11)&"") | P11: =IF($AH11="","",INDEX('Per Line'!$AC$2:$AC$201,$AH11)&"") | Q11: =IF($AH11="","",INDEX('Per Line'!$AD$2:$AD$201,$AH11)) | R11: =IF($AH11="","",IF(AND(ISNUMBER(Q11),Q11>0),AF11>Q11,FALSE)) | S11: =IF($AH11="","",INDEX('Per Line'!$AH$2:$AH$201,$AH11)&"") | T11: =IF($AH11="","",INDEX('Per Line'!$AI$2:$AI$201,$AH11)) | U11: =IF($AH11="","",Settings!$C$8) | V11: =IF($AH11="","",SUMIFS('Per Line'!$V$2:$V$201,'Per Line'!$D$2:$D$201,$B11,'Per Line'!$AN$2:$AN$201,1)) | W11: =IF($AH11="","",V11*U11) | X11: =IF($AH11="","",Settings!$C$7) | Y11: =IF($AH11="","",SUMIFS('Per Line'!$V$2:$V$201,'Per Line'!$D$2:$D$201,$B11,'Per Line'!$AM$2:$AM$201,0,'Per Line'!$AN$2:$AN$201,0)) | Z11: =IF($AH11="","",Y11*X11) | AA11: =IF($AH11="","",Settings!$C$6) | AB11: =IF($AH11="","",SUMIFS('Per Line'!$V$2:$V$201,'Per Line'!$D$2:$D$201,$B11,'Per Line'!$AM$2:$AM$201,1,'Per Line'!$AN$2:$AN$201,0)) | AC11: =IF($AH11="","",AB11*AA11) | AD11: =IF($AH11="","",AC11+Z11+W11) | AE11: =IF($AH11="","",AF11-AD11) | AF11: =IF($AH11="","",Y11+AB11+V11) | AG11: =IF($AH11="","",AF11-AD11-N11) | AH11: =IF(ROWS($AH$2:$AH11)<=MAX('Per Line'!$AL$2:$AL$201),MATCH(ROWS($AH$2:$AH11),'Per Line'!$AL$2:$AL$201,0),"")
B12: =IF($AH12="","",INDEX('Per Line'!$D$2:$D$201,$AH12)&"") | C12: =IF($AH12="","",INDEX('Per Line'!$A$2:$A$201,$AH12)&"") | D12: =IF($AH12="","",INDEX('Per Line'!$B$2:$B$201,$AH12)) | E12: =IF($AH12="","",INDEX('Per Line'!$C$2:$C$201,$AH12)&"") | F12: =IF($AH12="","",INDEX('Per Line'!$E$2:$E$201,$AH12)&"") | G12: =IF($AH12="","",INDEX('Per Line'!$F$2:$F$201,$AH12)) | H12: =IF($AH12="","",INDEX('Per Line'!$G$2:$G$201,$AH12)&"") | I12: =IF($AH12="","",INDEX('Per Line'!$I$2:$I$201,$AH12)&"") | J12: =IF($AH12="","",INDEX('Per Line'!$J$2:$J$201,$AH12)&"") | K12: =IF($AH12="","",INDEX('Per Line'!$K$2:$K$201,$AH12)&"") | L12: =IF($AH12="","",INDEX('Per Line'!$L$2:$L$201,$AH12)&"") | M12: =IF($AH12="","",INDEX('Per Line'!$M$2:$M$201,$AH12)) | N12: =IF($AH12="","",M12*AE12/100) | O12: =IF($AH12="","",INDEX('Per Line'!$Z$2:$Z$201,$AH12)&"") | P12: =IF($AH12="","",INDEX('Per Line'!$AC$2:$AC$201,$AH12)&"") | Q12: =IF($AH12="","",INDEX('Per Line'!$AD$2:$AD$201,$AH12)) | R12: =IF($AH12="","",IF(AND(ISNUMBER(Q12),Q12>0),AF12>Q12,FALSE)) | S12: =IF($AH12="","",INDEX('Per Line'!$AH$2:$AH$201,$AH12)&"") | T12: =IF($AH12="","",INDEX('Per Line'!$AI$2:$AI$201,$AH12)) | U12: =IF($AH12="","",Settings!$C$8) | V12: =IF($AH12="","",SUMIFS('Per Line'!$V$2:$V$201,'Per Line'!$D$2:$D$201,$B12,'Per Line'!$AN$2:$AN$201,1)) | W12: =IF($AH12="","",V12*U12) | X12: =IF($AH12="","",Settings!$C$7) | Y12: =IF($AH12="","",SUMIFS('Per Line'!$V$2:$V$201,'Per Line'!$D$2:$D$201,$B12,'Per Line'!$AM$2:$AM$201,0,'Per Line'!$AN$2:$AN$201,0)) | Z12: =IF($AH12="","",Y12*X12) | AA12: =IF($AH12="","",Settings!$C$6) | AB12: =IF($AH12="","",SUMIFS('Per Line'!$V$2:$V$201,'Per Line'!$D$2:$D$201,$B12,'Per Line'!$AM$2:$AM$201,1,'Per Line'!$AN$2:$AN$201,0)) | AC12: =IF($AH12="","",AB12*AA12) | AD12: =IF($AH12="","",AC12+Z12+W12) | AE12: =IF($AH12="","",AF12-AD12) | AF12: =IF($AH12="","",Y12+AB12+V12) | AG12: =IF($AH12="","",AF12-AD12-N12) | AH12: =IF(ROWS($AH$2:$AH12)<=MAX('Per Line'!$AL$2:$AL$201),MATCH(ROWS($AH$2:$AH12),'Per Line'!$AL$2:$AL$201,0),"")
B13: =IF($AH13="","",INDEX('Per Line'!$D$2:$D$201,$AH13)&"") | C13: =IF($AH13="","",INDEX('Per Line'!$A$2:$A$201,$AH13)&"") | D13: =IF($AH13="","",INDEX('Per Line'!$B$2:$B$201,$AH13)) | E13: =IF($AH13="","",INDEX('Per Line'!$C$2:$C$201,$AH13)&"") | F13: =IF($AH13="","",INDEX('Per Line'!$E$2:$E$201,$AH13)&"") | G13: =IF($AH13="","",INDEX('Per Line'!$F$2:$F$201,$AH13)) | H13: =IF($AH13="","",INDEX('Per Line'!$G$2:$G$201,$AH13)&"") | I13: =IF($AH13="","",INDEX('Per Line'!$I$2:$I$201,$AH13)&"") | J13: =IF($AH13="","",INDEX('Per Line'!$J$2:$J$201,$AH13)&"") | K13: =IF($AH13="","",INDEX('Per Line'!$K$2:$K$201,$AH13)&"") | L13: =IF($AH13="","",INDEX('Per Line'!$L$2:$L$201,$AH13)&"") | M13: =IF($AH13="","",INDEX('Per Line'!$M$2:$M$201,$AH13)) | N13: =IF($AH13="","",M13*AE13/100) | O13: =IF($AH13="","",INDEX('Per Line'!$Z$2:$Z$201,$AH13)&"") | P13: =IF($AH13="","",INDEX('Per Line'!$AC$2:$AC$201,$AH13)&"") | Q13: =IF($AH13="","",INDEX('Per Line'!$AD$2:$AD$201,$AH13)) | R13: =IF($AH13="","",IF(AND(ISNUMBER(Q13),Q13>0),AF13>Q13,FALSE)) | S13: =IF($AH13="","",INDEX('Per Line'!$AH$2:$AH$201,$AH13)&"") | T13: =IF($AH13="","",INDEX('Per Line'!$AI$2:$AI$201,$AH13)) | U13: =IF($AH13="","",Settings!$C$8) | V13: =IF($AH13="","",SUMIFS('Per Line'!$V$2:$V$201,'Per Line'!$D$2:$D$201,$B13,'Per Line'!$AN$2:$AN$201,1)) | W13: =IF($AH13="","",V13*U13) | X13: =IF($AH13="","",Settings!$C$7) | Y13: =IF($AH13="","",SUMIFS('Per Line'!$V$2:$V$201,'Per Line'!$D$2:$D$201,$B13,'Per Line'!$AM$2:$AM$201,0,'Per Line'!$AN$2:$AN$201,0)) | Z13: =IF($AH13="","",Y13*X13) | AA13: =IF($AH13="","",Settings!$C$6) | AB13: =IF($AH13="","",SUMIFS('Per Line'!$V$2:$V$201,'Per Line'!$D$2:$D$201,$B13,'Per Line'!$AM$2:$AM$201,1,'Per Line'!$AN$2:$AN$201,0)) | AC13: =IF($AH13="","",AB13*AA13) | AD13: =IF($AH13="","",AC13+Z13+W13) | AE13: =IF($AH13="","",AF13-AD13) | AF13: =IF($AH13="","",Y13+AB13+V13) | AG13: =IF($AH13="","",AF13-AD13-N13) | AH13: =IF(ROWS($AH$2:$AH13)<=MAX('Per Line'!$AL$2:$AL$201),MATCH(ROWS($AH$2:$AH13),'Per Line'!$AL$2:$AL$201,0),"")
... B61: =IF($AH61="","",INDEX('Per Line'!$D$2:$D$201,$AH61)&"") | C61: =IF($AH61="","",INDEX('Per Line'!$A$2:$A$201,$AH61)&"") | D61: =IF($AH61="","",INDEX('Per Line'!$B$2:$B$201,$AH61)) | E61: =IF($AH61="","",INDEX('Per Line'!$C$2:$C$201,$AH61)&"") | F61: =IF($AH61="","",INDEX('Per Line'!$E$2:$E$201,$AH61)&"") | G61: =IF($AH61="","",INDEX('Per Line'!$F$2:$F$201,$AH61)) | H61: =IF($AH61="","",INDEX('Per Line'!$G$2:$G$201,$AH61)&"") | I61: =IF($AH61="","",INDEX('Per Line'!$I$2:$I$201,$AH61)&"") | J61: =IF($AH61="","",INDEX('Per Line'!$J$2:$J$201,$AH61)&"") | K61: =IF($AH61="","",INDEX('Per Line'!$K$2:$K$201,$AH61)&"") | L61: =IF($AH61="","",INDEX('Per Line'!$L$2:$L$201,$AH61)&"") | M61: =IF($AH61="","",INDEX('Per Line'!$M$2:$M$201,$AH61)) | N61: =IF($AH61="","",M61*AE61/100) | O61: =IF($AH61="","",INDEX('Per Line'!$Z$2:$Z$201,$AH61)&"") | P61: =IF($AH61="","",INDEX('Per Line'!$AC$2:$AC$201,$AH61)&"") | Q61: =IF($AH61="","",INDEX('Per Line'!$AD$2:$AD$201,$AH61)) | R61: =IF($AH61="","",IF(AND(ISNUMBER(Q61),Q61>0),AF61>Q61,FALSE)) | S61: =IF($AH61="","",INDEX('Per Line'!$AH$2:$AH$201,$AH61)&"") | T61: =IF($AH61="","",INDEX('Per Line'!$AI$2:$AI$201,$AH61)) | U61: =IF($AH61="","",Settings!$C$8) | V61: =IF($AH61="","",SUMIFS('Per Line'!$V$2:$V$201,'Per Line'!$D$2:$D$201,$B61,'Per Line'!$AN$2:$AN$201,1)) | W61: =IF($AH61="","",V61*U61) | X61: =IF($AH61="","",Settings!$C$7) | Y61: =IF($AH61="","",SUMIFS('Per Line'!$V$2:$V$201,'Per Line'!$D$2:$D$201,$B61,'Per Line'!$AM$2:$AM$201,0,'Per Line'!$AN$2:$AN$201,0)) | Z61: =IF($AH61="","",Y61*X61) | AA61: =IF($AH61="","",Settings!$C$6) | AB61: =IF($AH61="","",SUMIFS('Per Line'!$V$2:$V$201,'Per Line'!$D$2:$D$201,$B61,'Per Line'!$AM$2:$AM$201,1,'Per Line'!$AN$2:$AN$201,0)) | AC61: =IF($AH61="","",AB61*AA61) | AD61: =IF($AH61="","",AC61+Z61+W61) | AE61: =IF($AH61="","",AF61-AD61) | AF61: =IF($AH61="","",Y61+AB61+V61) | AG61: =IF($AH61="","",AF61-AD61-N61) | AH61: =IF(ROWS($AH$2:$AH61)<=MAX('Per Line'!$AL$2:$AL$201),MATCH(ROWS($AH$2:$AH61),'Per Line'!$AL$2:$AL$201,0),"")
