Workbook

Sheet How To Use
A1: Claims Template - AXA SERVICES EGYPT (VPN)
A3: Monthly steps
A4: 1. Open the 'Per Line' tab. Delete the old data in the BLUE columns only (row 2 down). Never delete the green or grey columns.
A5: 2. Paste the new month's data as VALUES starting at A2, into the blue columns: A-L, N-T, W, Z (same order as the system export).
A6: 3. Green columns (M, U, V, X, Y) and the grey helper columns (AA-AE) calculate automatically - do not paste over them.
A7: 4. 'Per Invoice' fills itself from 'Per Line' (one row per Order #, split into IMP / Local). No pivot table, no refresh.
A8: 5. The columns you type yourself in 'Per Invoice' (blue headers): A 'Invoice', L 'Max Limit'. Everything else is formula. Type them AFTER pasting the month data (they follow the row, not the order).
A9: 6. Open 'Settings' and check STATUS says OK (Per Line totals = Per Invoice totals).
A11: Colour legend
A12: Blue header = typed/pasted by you (raw data, and 'Invoice' in Per Invoice). Green header = formula (do not paste over). Grey header = helper formula (do not touch). Yellow cell (Settings) = editable rate.
A14: Calculation rules (taken from the August 2026 sheet)
A15: Co val = Order Co Payment x Subtotal / 100. Discount = Total x Rebates / 100. Subtotal = Total - Discount. Net = Subtotal - Co val. (Total = 'Item Total Price (EGP)')
... A20: Capacity: up to 6,000 lines and 2,200 invoices per month. A line with an empty Order # is ignored.

Sheet Settings
B1: Company settings & checks
B3: Insurance Company | C3: AXA SERVICES EGYPT | D3: Informational only
B4: Corporate | C4: - | D4: Informational only
B5: Sheet type | C5: VPN | D5: Informational only
B6: Local products rebate % | C6: 0.14 | D6: Source: Aug sheet (Rebates = 14 when Imported = FALSE).
B7: Imported (IMP) products rebate % | C7: 0.07 | D7: Source: Aug sheet (IMP% = 7 on Per Invoice).
B8: Special rebate % (Special Rebates? = Yes) | C8: 0.05 | D8: Lines flagged Special Rebates? = Yes get this rate (local or imported).
B9: Month totals / reconciliation
B10: Lines loaded | C10: =COUNTA('Per Line'!$C$2:$C$6001)
B11: Invoices (unique Order #) | C11: =MAX('Per Line'!$AB$2:$AB$6001)
B12: Invoices shown in Per Invoice | C12: =SUMPRODUCT(--('Per Invoice'!$B$2:$B$2201<>""))
B13: Grand Total - Per Line (Product Total) | C13: =SUM('Per Line'!$T$2:$T$6001)
B14: Grand Total - Per Invoice | C14: =SUM('Per Invoice'!$Y$2:$Y$2201)
B15: Discount - Per Line | C15: =SUM('Per Line'!$U$2:$U$6001)
B16: Discount - Per Invoice | C16: =SUM('Per Invoice'!$W$2:$W$2201)
B17: Co val - Per Line | C17: =SUM('Per Line'!$M$2:$M$6001)
B18: Co val - Per Invoice | C18: =SUM('Per Invoice'!$K$2:$K$2201)
B19: Net - Per Line | C19: =SUM('Per Line'!$Y$2:$Y$6001)
B20: Net - Per Invoice | C20: =SUM('Per Invoice'!$Z$2:$Z$2201)
B21: Max Limit adjustment (Co val, Per Invoice only) | C21: 0 | D21: This company's Per Invoice has no Max Limit rule.
B23: STATUS | C23: =IF(C10=0,"No data loaded",IF(COUNTA('Per Line'!$C:$C)-1>6000,"TOO MANY LINES - extend template",IF(C11>2200,"TOO MANY INVOICES - extend template",IF(AND(ROUND(C13-C14,2)=0,ROUND(C15-C16,2)=0,ROUND(C17+C21-C18,2)=0,ROUND(C19-C21-C20,2)=0,C11=C12),"OK","CHECK - Per Line and Per Invoice do not match")))) | D23: Must say OK after you paste the month data.

Sheet Per Line
A1: Batch ID | B1: ERX ID | C1: Order Number | D1: ## | E1: Approval Number | F1: Dispense Number | G1: Order Type | H1: Original Order Type | I1: Payer | J1: Card Holder Name | K1: Card Number | L1: Co Payment (%) | M1: Co val | N1: Creation Date | O1: Heisenberg ID | P1: Item | Q1: Item Form | R1: Item Price (EGP) | S1: Item Quantity | T1: Item Total Price (EGP) | U1: Discount | V1: Subtotal | W1: Imported | X1: Rebates | Y1: Net | Z1: Special Rebates? | AA1: Order 1st Row (helper) | AB1: Invoice # (helper) | AC1: Is Local (helper) | AD1: Is Special (helper) | AE1: Sort Key (helper)
M2: =IF($C2="","",L2*V2/100) | U2: =IF($C2="","",T2*X2/100) | V2: =IF($C2="","",T2-U2) | X2: =IF($C2="","",IF($AD2=1,Settings!$C$8,IF($AC2=1,Settings!$C$6,Settings!$C$7))*100) | Y2: =IF($C2="","",V2-M2) | AA2: =IF($C2="","",IF(COUNTIF($C$2:$C2,$C2)=1,1,0)) | AB2: =IF($AA2=1,SUMPRODUCT(--($AE$2:$AE$6001<$AE2))+1,"") | AC2: =IF($C2="","",IF(OR($W2=TRUE(),$W2="TRUE"),0,1)) | AD2: =IF($C2="","",IF($Z2="Yes",1,0)) | AE2: =IF($AA2=1,IFERROR(IF(VALUE($C2)<100000000,VALUE($C2),1000000000),IFERROR(IF(VALUE(MID($C2,2,20))<100000000,VALUE(MID($C2,2,20)),1000000000),1000000000))+ROW()/100000,"")
M3: =IF($C3="","",L3*V3/100) | U3: =IF($C3="","",T3*X3/100) | V3: =IF($C3="","",T3-U3) | X3: =IF($C3="","",IF($AD3=1,Settings!$C$8,IF($AC3=1,Settings!$C$6,Settings!$C$7))*100) | Y3: =IF($C3="","",V3-M3) | AA3: =IF($C3="","",IF(COUNTIF($C$2:$C3,$C3)=1,1,0)) | AB3: =IF($AA3=1,SUMPRODUCT(--($AE$2:$AE$6001<$AE3))+1,"") | AC3: =IF($C3="","",IF(OR($W3=TRUE(),$W3="TRUE"),0,1)) | AD3: =IF($C3="","",IF($Z3="Yes",1,0)) | AE3: =IF($AA3=1,IFERROR(IF(VALUE($C3)<100000000,VALUE($C3),1000000000),IFERROR(IF(VALUE(MID($C3,2,20))<100000000,VALUE(MID($C3,2,20)),1000000000),1000000000))+ROW()/100000,"")
M4: =IF($C4="","",L4*V4/100) | U4: =IF($C4="","",T4*X4/100) | V4: =IF($C4="","",T4-U4) | X4: =IF($C4="","",IF($AD4=1,Settings!$C$8,IF($AC4=1,Settings!$C$6,Settings!$C$7))*100) | Y4: =IF($C4="","",V4-M4) | AA4: =IF($C4="","",IF(COUNTIF($C$2:$C4,$C4)=1,1,0)) | AB4: =IF($AA4=1,SUMPRODUCT(--($AE$2:$AE$6001<$AE4))+1,"") | AC4: =IF($C4="","",IF(OR($W4=TRUE(),$W4="TRUE"),0,1)) | AD4: =IF($C4="","",IF($Z4="Yes",1,0)) | AE4: =IF($AA4=1,IFERROR(IF(VALUE($C4)<100000000,VALUE($C4),1000000000),IFERROR(IF(VALUE(MID($C4,2,20))<100000000,VALUE(MID($C4,2,20)),1000000000),1000000000))+ROW()/100000,"")
M5: =IF($C5="","",L5*V5/100) | U5: =IF($C5="","",T5*X5/100) | V5: =IF($C5="","",T5-U5) | X5: =IF($C5="","",IF($AD5=1,Settings!$C$8,IF($AC5=1,Settings!$C$6,Settings!$C$7))*100) | Y5: =IF($C5="","",V5-M5) | AA5: =IF($C5="","",IF(COUNTIF($C$2:$C5,$C5)=1,1,0)) | AB5: =IF($AA5=1,SUMPRODUCT(--($AE$2:$AE$6001<$AE5))+1,"") | AC5: =IF($C5="","",IF(OR($W5=TRUE(),$W5="TRUE"),0,1)) | AD5: =IF($C5="","",IF($Z5="Yes",1,0)) | AE5: =IF($AA5=1,IFERROR(IF(VALUE($C5)<100000000,VALUE($C5),1000000000),IFERROR(IF(VALUE(MID($C5,2,20))<100000000,VALUE(MID($C5,2,20)),1000000000),1000000000))+ROW()/100000,"")
M6: =IF($C6="","",L6*V6/100) | U6: =IF($C6="","",T6*X6/100) | V6: =IF($C6="","",T6-U6) | X6: =IF($C6="","",IF($AD6=1,Settings!$C$8,IF($AC6=1,Settings!$C$6,Settings!$C$7))*100) | Y6: =IF($C6="","",V6-M6) | AA6: =IF($C6="","",IF(COUNTIF($C$2:$C6,$C6)=1,1,0)) | AB6: =IF($AA6=1,SUMPRODUCT(--($AE$2:$AE$6001<$AE6))+1,"") | AC6: =IF($C6="","",IF(OR($W6=TRUE(),$W6="TRUE"),0,1)) | AD6: =IF($C6="","",IF($Z6="Yes",1,0)) | AE6: =IF($AA6=1,IFERROR(IF(VALUE($C6)<100000000,VALUE($C6),1000000000),IFERROR(IF(VALUE(MID($C6,2,20))<100000000,VALUE(MID($C6,2,20)),1000000000),1000000000))+ROW()/100000,"")
M7: =IF($C7="","",L7*V7/100) | U7: =IF($C7="","",T7*X7/100) | V7: =IF($C7="","",T7-U7) | X7: =IF($C7="","",IF($AD7=1,Settings!$C$8,IF($AC7=1,Settings!$C$6,Settings!$C$7))*100) | Y7: =IF($C7="","",V7-M7) | AA7: =IF($C7="","",IF(COUNTIF($C$2:$C7,$C7)=1,1,0)) | AB7: =IF($AA7=1,SUMPRODUCT(--($AE$2:$AE$6001<$AE7))+1,"") | AC7: =IF($C7="","",IF(OR($W7=TRUE(),$W7="TRUE"),0,1)) | AD7: =IF($C7="","",IF($Z7="Yes",1,0)) | AE7: =IF($AA7=1,IFERROR(IF(VALUE($C7)<100000000,VALUE($C7),1000000000),IFERROR(IF(VALUE(MID($C7,2,20))<100000000,VALUE(MID($C7,2,20)),1000000000),1000000000))+ROW()/100000,"")
M8: =IF($C8="","",L8*V8/100) | U8: =IF($C8="","",T8*X8/100) | V8: =IF($C8="","",T8-U8) | X8: =IF($C8="","",IF($AD8=1,Settings!$C$8,IF($AC8=1,Settings!$C$6,Settings!$C$7))*100) | Y8: =IF($C8="","",V8-M8) | AA8: =IF($C8="","",IF(COUNTIF($C$2:$C8,$C8)=1,1,0)) | AB8: =IF($AA8=1,SUMPRODUCT(--($AE$2:$AE$6001<$AE8))+1,"") | AC8: =IF($C8="","",IF(OR($W8=TRUE(),$W8="TRUE"),0,1)) | AD8: =IF($C8="","",IF($Z8="Yes",1,0)) | AE8: =IF($AA8=1,IFERROR(IF(VALUE($C8)<100000000,VALUE($C8),1000000000),IFERROR(IF(VALUE(MID($C8,2,20))<100000000,VALUE(MID($C8,2,20)),1000000000),1000000000))+ROW()/100000,"")
M9: =IF($C9="","",L9*V9/100) | U9: =IF($C9="","",T9*X9/100) | V9: =IF($C9="","",T9-U9) | X9: =IF($C9="","",IF($AD9=1,Settings!$C$8,IF($AC9=1,Settings!$C$6,Settings!$C$7))*100) | Y9: =IF($C9="","",V9-M9) | AA9: =IF($C9="","",IF(COUNTIF($C$2:$C9,$C9)=1,1,0)) | AB9: =IF($AA9=1,SUMPRODUCT(--($AE$2:$AE$6001<$AE9))+1,"") | AC9: =IF($C9="","",IF(OR($W9=TRUE(),$W9="TRUE"),0,1)) | AD9: =IF($C9="","",IF($Z9="Yes",1,0)) | AE9: =IF($AA9=1,IFERROR(IF(VALUE($C9)<100000000,VALUE($C9),1000000000),IFERROR(IF(VALUE(MID($C9,2,20))<100000000,VALUE(MID($C9,2,20)),1000000000),1000000000))+ROW()/100000,"")
M10: =IF($C10="","",L10*V10/100) | U10: =IF($C10="","",T10*X10/100) | V10: =IF($C10="","",T10-U10) | X10: =IF($C10="","",IF($AD10=1,Settings!$C$8,IF($AC10=1,Settings!$C$6,Settings!$C$7))*100) | Y10: =IF($C10="","",V10-M10) | AA10: =IF($C10="","",IF(COUNTIF($C$2:$C10,$C10)=1,1,0)) | AB10: =IF($AA10=1,SUMPRODUCT(--($AE$2:$AE$6001<$AE10))+1,"") | AC10: =IF($C10="","",IF(OR($W10=TRUE(),$W10="TRUE"),0,1)) | AD10: =IF($C10="","",IF($Z10="Yes",1,0)) | AE10: =IF($AA10=1,IFERROR(IF(VALUE($C10)<100000000,VALUE($C10),1000000000),IFERROR(IF(VALUE(MID($C10,2,20))<100000000,VALUE(MID($C10,2,20)),1000000000),1000000000))+ROW()/100000,"")
M11: =IF($C11="","",L11*V11/100) | U11: =IF($C11="","",T11*X11/100) | V11: =IF($C11="","",T11-U11) | X11: =IF($C11="","",IF($AD11=1,Settings!$C$8,IF($AC11=1,Settings!$C$6,Settings!$C$7))*100) | Y11: =IF($C11="","",V11-M11) | AA11: =IF($C11="","",IF(COUNTIF($C$2:$C11,$C11)=1,1,0)) | AB11: =IF($AA11=1,SUMPRODUCT(--($AE$2:$AE$6001<$AE11))+1,"") | AC11: =IF($C11="","",IF(OR($W11=TRUE(),$W11="TRUE"),0,1)) | AD11: =IF($C11="","",IF($Z11="Yes",1,0)) | AE11: =IF($AA11=1,IFERROR(IF(VALUE($C11)<100000000,VALUE($C11),1000000000),IFERROR(IF(VALUE(MID($C11,2,20))<100000000,VALUE(MID($C11,2,20)),1000000000),1000000000))+ROW()/100000,"")
M12: =IF($C12="","",L12*V12/100) | U12: =IF($C12="","",T12*X12/100) | V12: =IF($C12="","",T12-U12) | X12: =IF($C12="","",IF($AD12=1,Settings!$C$8,IF($AC12=1,Settings!$C$6,Settings!$C$7))*100) | Y12: =IF($C12="","",V12-M12) | AA12: =IF($C12="","",IF(COUNTIF($C$2:$C12,$C12)=1,1,0)) | AB12: =IF($AA12=1,SUMPRODUCT(--($AE$2:$AE$6001<$AE12))+1,"") | AC12: =IF($C12="","",IF(OR($W12=TRUE(),$W12="TRUE"),0,1)) | AD12: =IF($C12="","",IF($Z12="Yes",1,0)) | AE12: =IF($AA12=1,IFERROR(IF(VALUE($C12)<100000000,VALUE($C12),1000000000),IFERROR(IF(VALUE(MID($C12,2,20))<100000000,VALUE(MID($C12,2,20)),1000000000),1000000000))+ROW()/100000,"")
M13: =IF($C13="","",L13*V13/100) | U13: =IF($C13="","",T13*X13/100) | V13: =IF($C13="","",T13-U13) | X13: =IF($C13="","",IF($AD13=1,Settings!$C$8,IF($AC13=1,Settings!$C$6,Settings!$C$7))*100) | Y13: =IF($C13="","",V13-M13) | AA13: =IF($C13="","",IF(COUNTIF($C$2:$C13,$C13)=1,1,0)) | AB13: =IF($AA13=1,SUMPRODUCT(--($AE$2:$AE$6001<$AE13))+1,"") | AC13: =IF($C13="","",IF(OR($W13=TRUE(),$W13="TRUE"),0,1)) | AD13: =IF($C13="","",IF($Z13="Yes",1,0)) | AE13: =IF($AA13=1,IFERROR(IF(VALUE($C13)<100000000,VALUE($C13),1000000000),IFERROR(IF(VALUE(MID($C13,2,20))<100000000,VALUE(MID($C13,2,20)),1000000000),1000000000))+ROW()/100000,"")
... M6001: =IF($C6001="","",L6001*V6001/100) | U6001: =IF($C6001="","",T6001*X6001/100) | V6001: =IF($C6001="","",T6001-U6001) | X6001: =IF($C6001="","",IF($AD6001=1,Settings!$C$8,IF($AC6001=1,Settings!$C$6,Settings!$C$7))*100) | Y6001: =IF($C6001="","",V6001-M6001) | AA6001: =IF($C6001="","",IF(COUNTIF($C$2:$C6001,$C6001)=1,1,0)) | AB6001: =IF($AA6001=1,SUMPRODUCT(--($AE$2:$AE$6001<$AE6001))+1,"") | AC6001: =IF($C6001="","",IF(OR($W6001=TRUE(),$W6001="TRUE"),0,1)) | AD6001: =IF($C6001="","",IF($Z6001="Yes",1,0)) | AE6001: =IF($AA6001=1,IFERROR(IF(VALUE($C6001)<100000000,VALUE($C6001),1000000000),IFERROR(IF(VALUE(MID($C6001,2,20))<100000000,VALUE(MID($C6001,2,20)),1000000000),1000000000))+ROW()/100000,"")

Sheet Per Invoice
A1: Invoice | B1: Order Number | C1: ERX ID | D1: Batch ID | E1: Dispense Number | F1: Order Type | G1: Payer | H1: Card Holder Name | I1: Card Number | J1: Co Payment (%) | K1: Co val | L1: Max Limit | M1: Creation Date | N1: SPECIAL REBATES% | O1: SPECIA REBATES | P1: SPECIA REBATES VAL | Q1: IMP% | R1: IMP | S1: IMP VAL | T1: LOCAL% | U1: LOCAL | V1: LOCAL VAL | W1: TOTAL VAL | X1: SUBTOTAL | Y1: Grand Total | Z1: NET | AA1: Src Row (helper)
B2: =IF($AA2="","",INDEX('Per Line'!$C$2:$C$6001,$AA2)&"") | C2: =IF($AA2="","",INDEX('Per Line'!$B$2:$B$6001,$AA2)&"") | D2: =IF($AA2="","",INDEX('Per Line'!$A$2:$A$6001,$AA2)&"") | E2: =IF($AA2="","",INDEX('Per Line'!$F$2:$F$6001,$AA2)&"") | F2: =IF($AA2="","",INDEX('Per Line'!$G$2:$G$6001,$AA2)&"") | G2: =IF($AA2="","",INDEX('Per Line'!$I$2:$I$6001,$AA2)&"") | H2: =IF($AA2="","",INDEX('Per Line'!$J$2:$J$6001,$AA2)&"") | I2: =IF($AA2="","",INDEX('Per Line'!$K$2:$K$6001,$AA2)&"") | J2: =IF($AA2="","",INDEX('Per Line'!$L$2:$L$6001,$AA2)) | K2: =IF($AA2="","",J2*X2/100) | M2: =IF($AA2="","",INDEX('Per Line'!$N$2:$N$6001,$AA2)) | N2: =IF($AA2="","",Settings!$C$8) | O2: =IF($AA2="","",SUMIFS('Per Line'!$T$2:$T$6001,'Per Line'!$C$2:$C$6001,$B2,'Per Line'!$AD$2:$AD$6001,1)) | P2: =IF($AA2="","",O2*N2) | Q2: =IF($AA2="","",Settings!$C$7) | R2: =IF($AA2="","",SUMIFS('Per Line'!$T$2:$T$6001,'Per Line'!$C$2:$C$6001,$B2,'Per Line'!$AC$2:$AC$6001,0,'Per Line'!$AD$2:$AD$6001,0)) | S2: =IF($AA2="","",R2*Q2) | T2: =IF($AA2="","",Settings!$C$6) | U2: =IF($AA2="","",SUMIFS('Per Line'!$T$2:$T$6001,'Per Line'!$C$2:$C$6001,$B2,'Per Line'!$AC$2:$AC$6001,1,'Per Line'!$AD$2:$AD$6001,0)) | V2: =IF($AA2="","",U2*T2) | W2: =IF($AA2="","",V2+S2+P2) | X2: =IF($AA2="","",Y2-W2) | Y2: =IF($AA2="","",R2+U2+O2) | Z2: =IF($AA2="","",Y2-W2-K2) | AA2: =IF(ROWS($AA$2:$AA2)<=MAX('Per Line'!$AB$2:$AB$6001),MATCH(ROWS($AA$2:$AA2),'Per Line'!$AB$2:$AB$6001,0),"")
B3: =IF($AA3="","",INDEX('Per Line'!$C$2:$C$6001,$AA3)&"") | C3: =IF($AA3="","",INDEX('Per Line'!$B$2:$B$6001,$AA3)&"") | D3: =IF($AA3="","",INDEX('Per Line'!$A$2:$A$6001,$AA3)&"") | E3: =IF($AA3="","",INDEX('Per Line'!$F$2:$F$6001,$AA3)&"") | F3: =IF($AA3="","",INDEX('Per Line'!$G$2:$G$6001,$AA3)&"") | G3: =IF($AA3="","",INDEX('Per Line'!$I$2:$I$6001,$AA3)&"") | H3: =IF($AA3="","",INDEX('Per Line'!$J$2:$J$6001,$AA3)&"") | I3: =IF($AA3="","",INDEX('Per Line'!$K$2:$K$6001,$AA3)&"") | J3: =IF($AA3="","",INDEX('Per Line'!$L$2:$L$6001,$AA3)) | K3: =IF($AA3="","",J3*X3/100) | M3: =IF($AA3="","",INDEX('Per Line'!$N$2:$N$6001,$AA3)) | N3: =IF($AA3="","",Settings!$C$8) | O3: =IF($AA3="","",SUMIFS('Per Line'!$T$2:$T$6001,'Per Line'!$C$2:$C$6001,$B3,'Per Line'!$AD$2:$AD$6001,1)) | P3: =IF($AA3="","",O3*N3) | Q3: =IF($AA3="","",Settings!$C$7) | R3: =IF($AA3="","",SUMIFS('Per Line'!$T$2:$T$6001,'Per Line'!$C$2:$C$6001,$B3,'Per Line'!$AC$2:$AC$6001,0,'Per Line'!$AD$2:$AD$6001,0)) | S3: =IF($AA3="","",R3*Q3) | T3: =IF($AA3="","",Settings!$C$6) | U3: =IF($AA3="","",SUMIFS('Per Line'!$T$2:$T$6001,'Per Line'!$C$2:$C$6001,$B3,'Per Line'!$AC$2:$AC$6001,1,'Per Line'!$AD$2:$AD$6001,0)) | V3: =IF($AA3="","",U3*T3) | W3: =IF($AA3="","",V3+S3+P3) | X3: =IF($AA3="","",Y3-W3) | Y3: =IF($AA3="","",R3+U3+O3) | Z3: =IF($AA3="","",Y3-W3-K3) | AA3: =IF(ROWS($AA$2:$AA3)<=MAX('Per Line'!$AB$2:$AB$6001),MATCH(ROWS($AA$2:$AA3),'Per Line'!$AB$2:$AB$6001,0),"")
B4: =IF($AA4="","",INDEX('Per Line'!$C$2:$C$6001,$AA4)&"") | C4: =IF($AA4="","",INDEX('Per Line'!$B$2:$B$6001,$AA4)&"") | D4: =IF($AA4="","",INDEX('Per Line'!$A$2:$A$6001,$AA4)&"") | E4: =IF($AA4="","",INDEX('Per Line'!$F$2:$F$6001,$AA4)&"") | F4: =IF($AA4="","",INDEX('Per Line'!$G$2:$G$6001,$AA4)&"") | G4: =IF($AA4="","",INDEX('Per Line'!$I$2:$I$6001,$AA4)&"") | H4: =IF($AA4="","",INDEX('Per Line'!$J$2:$J$6001,$AA4)&"") | I4: =IF($AA4="","",INDEX('Per Line'!$K$2:$K$6001,$AA4)&"") | J4: =IF($AA4="","",INDEX('Per Line'!$L$2:$L$6001,$AA4)) | K4: =IF($AA4="","",J4*X4/100) | M4: =IF($AA4="","",INDEX('Per Line'!$N$2:$N$6001,$AA4)) | N4: =IF($AA4="","",Settings!$C$8) | O4: =IF($AA4="","",SUMIFS('Per Line'!$T$2:$T$6001,'Per Line'!$C$2:$C$6001,$B4,'Per Line'!$AD$2:$AD$6001,1)) | P4: =IF($AA4="","",O4*N4) | Q4: =IF($AA4="","",Settings!$C$7) | R4: =IF($AA4="","",SUMIFS('Per Line'!$T$2:$T$6001,'Per Line'!$C$2:$C$6001,$B4,'Per Line'!$AC$2:$AC$6001,0,'Per Line'!$AD$2:$AD$6001,0)) | S4: =IF($AA4="","",R4*Q4) | T4: =IF($AA4="","",Settings!$C$6) | U4: =IF($AA4="","",SUMIFS('Per Line'!$T$2:$T$6001,'Per Line'!$C$2:$C$6001,$B4,'Per Line'!$AC$2:$AC$6001,1,'Per Line'!$AD$2:$AD$6001,0)) | V4: =IF($AA4="","",U4*T4) | W4: =IF($AA4="","",V4+S4+P4) | X4: =IF($AA4="","",Y4-W4) | Y4: =IF($AA4="","",R4+U4+O4) | Z4: =IF($AA4="","",Y4-W4-K4) | AA4: =IF(ROWS($AA$2:$AA4)<=MAX('Per Line'!$AB$2:$AB$6001),MATCH(ROWS($AA$2:$AA4),'Per Line'!$AB$2:$AB$6001,0),"")
B5: =IF($AA5="","",INDEX('Per Line'!$C$2:$C$6001,$AA5)&"") | C5: =IF($AA5="","",INDEX('Per Line'!$B$2:$B$6001,$AA5)&"") | D5: =IF($AA5="","",INDEX('Per Line'!$A$2:$A$6001,$AA5)&"") | E5: =IF($AA5="","",INDEX('Per Line'!$F$2:$F$6001,$AA5)&"") | F5: =IF($AA5="","",INDEX('Per Line'!$G$2:$G$6001,$AA5)&"") | G5: =IF($AA5="","",INDEX('Per Line'!$I$2:$I$6001,$AA5)&"") | H5: =IF($AA5="","",INDEX('Per Line'!$J$2:$J$6001,$AA5)&"") | I5: =IF($AA5="","",INDEX('Per Line'!$K$2:$K$6001,$AA5)&"") | J5: =IF($AA5="","",INDEX('Per Line'!$L$2:$L$6001,$AA5)) | K5: =IF($AA5="","",J5*X5/100) | M5: =IF($AA5="","",INDEX('Per Line'!$N$2:$N$6001,$AA5)) | N5: =IF($AA5="","",Settings!$C$8) | O5: =IF($AA5="","",SUMIFS('Per Line'!$T$2:$T$6001,'Per Line'!$C$2:$C$6001,$B5,'Per Line'!$AD$2:$AD$6001,1)) | P5: =IF($AA5="","",O5*N5) | Q5: =IF($AA5="","",Settings!$C$7) | R5: =IF($AA5="","",SUMIFS('Per Line'!$T$2:$T$6001,'Per Line'!$C$2:$C$6001,$B5,'Per Line'!$AC$2:$AC$6001,0,'Per Line'!$AD$2:$AD$6001,0)) | S5: =IF($AA5="","",R5*Q5) | T5: =IF($AA5="","",Settings!$C$6) | U5: =IF($AA5="","",SUMIFS('Per Line'!$T$2:$T$6001,'Per Line'!$C$2:$C$6001,$B5,'Per Line'!$AC$2:$AC$6001,1,'Per Line'!$AD$2:$AD$6001,0)) | V5: =IF($AA5="","",U5*T5) | W5: =IF($AA5="","",V5+S5+P5) | X5: =IF($AA5="","",Y5-W5) | Y5: =IF($AA5="","",R5+U5+O5) | Z5: =IF($AA5="","",Y5-W5-K5) | AA5: =IF(ROWS($AA$2:$AA5)<=MAX('Per Line'!$AB$2:$AB$6001),MATCH(ROWS($AA$2:$AA5),'Per Line'!$AB$2:$AB$6001,0),"")
B6: =IF($AA6="","",INDEX('Per Line'!$C$2:$C$6001,$AA6)&"") | C6: =IF($AA6="","",INDEX('Per Line'!$B$2:$B$6001,$AA6)&"") | D6: =IF($AA6="","",INDEX('Per Line'!$A$2:$A$6001,$AA6)&"") | E6: =IF($AA6="","",INDEX('Per Line'!$F$2:$F$6001,$AA6)&"") | F6: =IF($AA6="","",INDEX('Per Line'!$G$2:$G$6001,$AA6)&"") | G6: =IF($AA6="","",INDEX('Per Line'!$I$2:$I$6001,$AA6)&"") | H6: =IF($AA6="","",INDEX('Per Line'!$J$2:$J$6001,$AA6)&"") | I6: =IF($AA6="","",INDEX('Per Line'!$K$2:$K$6001,$AA6)&"") | J6: =IF($AA6="","",INDEX('Per Line'!$L$2:$L$6001,$AA6)) | K6: =IF($AA6="","",J6*X6/100) | M6: =IF($AA6="","",INDEX('Per Line'!$N$2:$N$6001,$AA6)) | N6: =IF($AA6="","",Settings!$C$8) | O6: =IF($AA6="","",SUMIFS('Per Line'!$T$2:$T$6001,'Per Line'!$C$2:$C$6001,$B6,'Per Line'!$AD$2:$AD$6001,1)) | P6: =IF($AA6="","",O6*N6) | Q6: =IF($AA6="","",Settings!$C$7) | R6: =IF($AA6="","",SUMIFS('Per Line'!$T$2:$T$6001,'Per Line'!$C$2:$C$6001,$B6,'Per Line'!$AC$2:$AC$6001,0,'Per Line'!$AD$2:$AD$6001,0)) | S6: =IF($AA6="","",R6*Q6) | T6: =IF($AA6="","",Settings!$C$6) | U6: =IF($AA6="","",SUMIFS('Per Line'!$T$2:$T$6001,'Per Line'!$C$2:$C$6001,$B6,'Per Line'!$AC$2:$AC$6001,1,'Per Line'!$AD$2:$AD$6001,0)) | V6: =IF($AA6="","",U6*T6) | W6: =IF($AA6="","",V6+S6+P6) | X6: =IF($AA6="","",Y6-W6) | Y6: =IF($AA6="","",R6+U6+O6) | Z6: =IF($AA6="","",Y6-W6-K6) | AA6: =IF(ROWS($AA$2:$AA6)<=MAX('Per Line'!$AB$2:$AB$6001),MATCH(ROWS($AA$2:$AA6),'Per Line'!$AB$2:$AB$6001,0),"")
B7: =IF($AA7="","",INDEX('Per Line'!$C$2:$C$6001,$AA7)&"") | C7: =IF($AA7="","",INDEX('Per Line'!$B$2:$B$6001,$AA7)&"") | D7: =IF($AA7="","",INDEX('Per Line'!$A$2:$A$6001,$AA7)&"") | E7: =IF($AA7="","",INDEX('Per Line'!$F$2:$F$6001,$AA7)&"") | F7: =IF($AA7="","",INDEX('Per Line'!$G$2:$G$6001,$AA7)&"") | G7: =IF($AA7="","",INDEX('Per Line'!$I$2:$I$6001,$AA7)&"") | H7: =IF($AA7="","",INDEX('Per Line'!$J$2:$J$6001,$AA7)&"") | I7: =IF($AA7="","",INDEX('Per Line'!$K$2:$K$6001,$AA7)&"") | J7: =IF($AA7="","",INDEX('Per Line'!$L$2:$L$6001,$AA7)) | K7: =IF($AA7="","",J7*X7/100) | M7: =IF($AA7="","",INDEX('Per Line'!$N$2:$N$6001,$AA7)) | N7: =IF($AA7="","",Settings!$C$8) | O7: =IF($AA7="","",SUMIFS('Per Line'!$T$2:$T$6001,'Per Line'!$C$2:$C$6001,$B7,'Per Line'!$AD$2:$AD$6001,1)) | P7: =IF($AA7="","",O7*N7) | Q7: =IF($AA7="","",Settings!$C$7) | R7: =IF($AA7="","",SUMIFS('Per Line'!$T$2:$T$6001,'Per Line'!$C$2:$C$6001,$B7,'Per Line'!$AC$2:$AC$6001,0,'Per Line'!$AD$2:$AD$6001,0)) | S7: =IF($AA7="","",R7*Q7) | T7: =IF($AA7="","",Settings!$C$6) | U7: =IF($AA7="","",SUMIFS('Per Line'!$T$2:$T$6001,'Per Line'!$C$2:$C$6001,$B7,'Per Line'!$AC$2:$AC$6001,1,'Per Line'!$AD$2:$AD$6001,0)) | V7: =IF($AA7="","",U7*T7) | W7: =IF($AA7="","",V7+S7+P7) | X7: =IF($AA7="","",Y7-W7) | Y7: =IF($AA7="","",R7+U7+O7) | Z7: =IF($AA7="","",Y7-W7-K7) | AA7: =IF(ROWS($AA$2:$AA7)<=MAX('Per Line'!$AB$2:$AB$6001),MATCH(ROWS($AA$2:$AA7),'Per Line'!$AB$2:$AB$6001,0),"")
B8: =IF($AA8="","",INDEX('Per Line'!$C$2:$C$6001,$AA8)&"") | C8: =IF($AA8="","",INDEX('Per Line'!$B$2:$B$6001,$AA8)&"") | D8: =IF($AA8="","",INDEX('Per Line'!$A$2:$A$6001,$AA8)&"") | E8: =IF($AA8="","",INDEX('Per Line'!$F$2:$F$6001,$AA8)&"") | F8: =IF($AA8="","",INDEX('Per Line'!$G$2:$G$6001,$AA8)&"") | G8: =IF($AA8="","",INDEX('Per Line'!$I$2:$I$6001,$AA8)&"") | H8: =IF($AA8="","",INDEX('Per Line'!$J$2:$J$6001,$AA8)&"") | I8: =IF($AA8="","",INDEX('Per Line'!$K$2:$K$6001,$AA8)&"") | J8: =IF($AA8="","",INDEX('Per Line'!$L$2:$L$6001,$AA8)) | K8: =IF($AA8="","",J8*X8/100) | M8: =IF($AA8="","",INDEX('Per Line'!$N$2:$N$6001,$AA8)) | N8: =IF($AA8="","",Settings!$C$8) | O8: =IF($AA8="","",SUMIFS('Per Line'!$T$2:$T$6001,'Per Line'!$C$2:$C$6001,$B8,'Per Line'!$AD$2:$AD$6001,1)) | P8: =IF($AA8="","",O8*N8) | Q8: =IF($AA8="","",Settings!$C$7) | R8: =IF($AA8="","",SUMIFS('Per Line'!$T$2:$T$6001,'Per Line'!$C$2:$C$6001,$B8,'Per Line'!$AC$2:$AC$6001,0,'Per Line'!$AD$2:$AD$6001,0)) | S8: =IF($AA8="","",R8*Q8) | T8: =IF($AA8="","",Settings!$C$6) | U8: =IF($AA8="","",SUMIFS('Per Line'!$T$2:$T$6001,'Per Line'!$C$2:$C$6001,$B8,'Per Line'!$AC$2:$AC$6001,1,'Per Line'!$AD$2:$AD$6001,0)) | V8: =IF($AA8="","",U8*T8) | W8: =IF($AA8="","",V8+S8+P8) | X8: =IF($AA8="","",Y8-W8) | Y8: =IF($AA8="","",R8+U8+O8) | Z8: =IF($AA8="","",Y8-W8-K8) | AA8: =IF(ROWS($AA$2:$AA8)<=MAX('Per Line'!$AB$2:$AB$6001),MATCH(ROWS($AA$2:$AA8),'Per Line'!$AB$2:$AB$6001,0),"")
B9: =IF($AA9="","",INDEX('Per Line'!$C$2:$C$6001,$AA9)&"") | C9: =IF($AA9="","",INDEX('Per Line'!$B$2:$B$6001,$AA9)&"") | D9: =IF($AA9="","",INDEX('Per Line'!$A$2:$A$6001,$AA9)&"") | E9: =IF($AA9="","",INDEX('Per Line'!$F$2:$F$6001,$AA9)&"") | F9: =IF($AA9="","",INDEX('Per Line'!$G$2:$G$6001,$AA9)&"") | G9: =IF($AA9="","",INDEX('Per Line'!$I$2:$I$6001,$AA9)&"") | H9: =IF($AA9="","",INDEX('Per Line'!$J$2:$J$6001,$AA9)&"") | I9: =IF($AA9="","",INDEX('Per Line'!$K$2:$K$6001,$AA9)&"") | J9: =IF($AA9="","",INDEX('Per Line'!$L$2:$L$6001,$AA9)) | K9: =IF($AA9="","",J9*X9/100) | M9: =IF($AA9="","",INDEX('Per Line'!$N$2:$N$6001,$AA9)) | N9: =IF($AA9="","",Settings!$C$8) | O9: =IF($AA9="","",SUMIFS('Per Line'!$T$2:$T$6001,'Per Line'!$C$2:$C$6001,$B9,'Per Line'!$AD$2:$AD$6001,1)) | P9: =IF($AA9="","",O9*N9) | Q9: =IF($AA9="","",Settings!$C$7) | R9: =IF($AA9="","",SUMIFS('Per Line'!$T$2:$T$6001,'Per Line'!$C$2:$C$6001,$B9,'Per Line'!$AC$2:$AC$6001,0,'Per Line'!$AD$2:$AD$6001,0)) | S9: =IF($AA9="","",R9*Q9) | T9: =IF($AA9="","",Settings!$C$6) | U9: =IF($AA9="","",SUMIFS('Per Line'!$T$2:$T$6001,'Per Line'!$C$2:$C$6001,$B9,'Per Line'!$AC$2:$AC$6001,1,'Per Line'!$AD$2:$AD$6001,0)) | V9: =IF($AA9="","",U9*T9) | W9: =IF($AA9="","",V9+S9+P9) | X9: =IF($AA9="","",Y9-W9) | Y9: =IF($AA9="","",R9+U9+O9) | Z9: =IF($AA9="","",Y9-W9-K9) | AA9: =IF(ROWS($AA$2:$AA9)<=MAX('Per Line'!$AB$2:$AB$6001),MATCH(ROWS($AA$2:$AA9),'Per Line'!$AB$2:$AB$6001,0),"")
B10: =IF($AA10="","",INDEX('Per Line'!$C$2:$C$6001,$AA10)&"") | C10: =IF($AA10="","",INDEX('Per Line'!$B$2:$B$6001,$AA10)&"") | D10: =IF($AA10="","",INDEX('Per Line'!$A$2:$A$6001,$AA10)&"") | E10: =IF($AA10="","",INDEX('Per Line'!$F$2:$F$6001,$AA10)&"") | F10: =IF($AA10="","",INDEX('Per Line'!$G$2:$G$6001,$AA10)&"") | G10: =IF($AA10="","",INDEX('Per Line'!$I$2:$I$6001,$AA10)&"") | H10: =IF($AA10="","",INDEX('Per Line'!$J$2:$J$6001,$AA10)&"") | I10: =IF($AA10="","",INDEX('Per Line'!$K$2:$K$6001,$AA10)&"") | J10: =IF($AA10="","",INDEX('Per Line'!$L$2:$L$6001,$AA10)) | K10: =IF($AA10="","",J10*X10/100) | M10: =IF($AA10="","",INDEX('Per Line'!$N$2:$N$6001,$AA10)) | N10: =IF($AA10="","",Settings!$C$8) | O10: =IF($AA10="","",SUMIFS('Per Line'!$T$2:$T$6001,'Per Line'!$C$2:$C$6001,$B10,'Per Line'!$AD$2:$AD$6001,1)) | P10: =IF($AA10="","",O10*N10) | Q10: =IF($AA10="","",Settings!$C$7) | R10: =IF($AA10="","",SUMIFS('Per Line'!$T$2:$T$6001,'Per Line'!$C$2:$C$6001,$B10,'Per Line'!$AC$2:$AC$6001,0,'Per Line'!$AD$2:$AD$6001,0)) | S10: =IF($AA10="","",R10*Q10) | T10: =IF($AA10="","",Settings!$C$6) | U10: =IF($AA10="","",SUMIFS('Per Line'!$T$2:$T$6001,'Per Line'!$C$2:$C$6001,$B10,'Per Line'!$AC$2:$AC$6001,1,'Per Line'!$AD$2:$AD$6001,0)) | V10: =IF($AA10="","",U10*T10) | W10: =IF($AA10="","",V10+S10+P10) | X10: =IF($AA10="","",Y10-W10) | Y10: =IF($AA10="","",R10+U10+O10) | Z10: =IF($AA10="","",Y10-W10-K10) | AA10: =IF(ROWS($AA$2:$AA10)<=MAX('Per Line'!$AB$2:$AB$6001),MATCH(ROWS($AA$2:$AA10),'Per Line'!$AB$2:$AB$6001,0),"")
B11: =IF($AA11="","",INDEX('Per Line'!$C$2:$C$6001,$AA11)&"") | C11: =IF($AA11="","",INDEX('Per Line'!$B$2:$B$6001,$AA11)&"") | D11: =IF($AA11="","",INDEX('Per Line'!$A$2:$A$6001,$AA11)&"") | E11: =IF($AA11="","",INDEX('Per Line'!$F$2:$F$6001,$AA11)&"") | F11: =IF($AA11="","",INDEX('Per Line'!$G$2:$G$6001,$AA11)&"") | G11: =IF($AA11="","",INDEX('Per Line'!$I$2:$I$6001,$AA11)&"") | H11: =IF($AA11="","",INDEX('Per Line'!$J$2:$J$6001,$AA11)&"") | I11: =IF($AA11="","",INDEX('Per Line'!$K$2:$K$6001,$AA11)&"") | J11: =IF($AA11="","",INDEX('Per Line'!$L$2:$L$6001,$AA11)) | K11: =IF($AA11="","",J11*X11/100) | M11: =IF($AA11="","",INDEX('Per Line'!$N$2:$N$6001,$AA11)) | N11: =IF($AA11="","",Settings!$C$8) | O11: =IF($AA11="","",SUMIFS('Per Line'!$T$2:$T$6001,'Per Line'!$C$2:$C$6001,$B11,'Per Line'!$AD$2:$AD$6001,1)) | P11: =IF($AA11="","",O11*N11) | Q11: =IF($AA11="","",Settings!$C$7) | R11: =IF($AA11="","",SUMIFS('Per Line'!$T$2:$T$6001,'Per Line'!$C$2:$C$6001,$B11,'Per Line'!$AC$2:$AC$6001,0,'Per Line'!$AD$2:$AD$6001,0)) | S11: =IF($AA11="","",R11*Q11) | T11: =IF($AA11="","",Settings!$C$6) | U11: =IF($AA11="","",SUMIFS('Per Line'!$T$2:$T$6001,'Per Line'!$C$2:$C$6001,$B11,'Per Line'!$AC$2:$AC$6001,1,'Per Line'!$AD$2:$AD$6001,0)) | V11: =IF($AA11="","",U11*T11) | W11: =IF($AA11="","",V11+S11+P11) | X11: =IF($AA11="","",Y11-W11) | Y11: =IF($AA11="","",R11+U11+O11) | Z11: =IF($AA11="","",Y11-W11-K11) | AA11: =IF(ROWS($AA$2:$AA11)<=MAX('Per Line'!$AB$2:$AB$6001),MATCH(ROWS($AA$2:$AA11),'Per Line'!$AB$2:$AB$6001,0),"")
B12: =IF($AA12="","",INDEX('Per Line'!$C$2:$C$6001,$AA12)&"") | C12: =IF($AA12="","",INDEX('Per Line'!$B$2:$B$6001,$AA12)&"") | D12: =IF($AA12="","",INDEX('Per Line'!$A$2:$A$6001,$AA12)&"") | E12: =IF($AA12="","",INDEX('Per Line'!$F$2:$F$6001,$AA12)&"") | F12: =IF($AA12="","",INDEX('Per Line'!$G$2:$G$6001,$AA12)&"") | G12: =IF($AA12="","",INDEX('Per Line'!$I$2:$I$6001,$AA12)&"") | H12: =IF($AA12="","",INDEX('Per Line'!$J$2:$J$6001,$AA12)&"") | I12: =IF($AA12="","",INDEX('Per Line'!$K$2:$K$6001,$AA12)&"") | J12: =IF($AA12="","",INDEX('Per Line'!$L$2:$L$6001,$AA12)) | K12: =IF($AA12="","",J12*X12/100) | M12: =IF($AA12="","",INDEX('Per Line'!$N$2:$N$6001,$AA12)) | N12: =IF($AA12="","",Settings!$C$8) | O12: =IF($AA12="","",SUMIFS('Per Line'!$T$2:$T$6001,'Per Line'!$C$2:$C$6001,$B12,'Per Line'!$AD$2:$AD$6001,1)) | P12: =IF($AA12="","",O12*N12) | Q12: =IF($AA12="","",Settings!$C$7) | R12: =IF($AA12="","",SUMIFS('Per Line'!$T$2:$T$6001,'Per Line'!$C$2:$C$6001,$B12,'Per Line'!$AC$2:$AC$6001,0,'Per Line'!$AD$2:$AD$6001,0)) | S12: =IF($AA12="","",R12*Q12) | T12: =IF($AA12="","",Settings!$C$6) | U12: =IF($AA12="","",SUMIFS('Per Line'!$T$2:$T$6001,'Per Line'!$C$2:$C$6001,$B12,'Per Line'!$AC$2:$AC$6001,1,'Per Line'!$AD$2:$AD$6001,0)) | V12: =IF($AA12="","",U12*T12) | W12: =IF($AA12="","",V12+S12+P12) | X12: =IF($AA12="","",Y12-W12) | Y12: =IF($AA12="","",R12+U12+O12) | Z12: =IF($AA12="","",Y12-W12-K12) | AA12: =IF(ROWS($AA$2:$AA12)<=MAX('Per Line'!$AB$2:$AB$6001),MATCH(ROWS($AA$2:$AA12),'Per Line'!$AB$2:$AB$6001,0),"")
B13: =IF($AA13="","",INDEX('Per Line'!$C$2:$C$6001,$AA13)&"") | C13: =IF($AA13="","",INDEX('Per Line'!$B$2:$B$6001,$AA13)&"") | D13: =IF($AA13="","",INDEX('Per Line'!$A$2:$A$6001,$AA13)&"") | E13: =IF($AA13="","",INDEX('Per Line'!$F$2:$F$6001,$AA13)&"") | F13: =IF($AA13="","",INDEX('Per Line'!$G$2:$G$6001,$AA13)&"") | G13: =IF($AA13="","",INDEX('Per Line'!$I$2:$I$6001,$AA13)&"") | H13: =IF($AA13="","",INDEX('Per Line'!$J$2:$J$6001,$AA13)&"") | I13: =IF($AA13="","",INDEX('Per Line'!$K$2:$K$6001,$AA13)&"") | J13: =IF($AA13="","",INDEX('Per Line'!$L$2:$L$6001,$AA13)) | K13: =IF($AA13="","",J13*X13/100) | M13: =IF($AA13="","",INDEX('Per Line'!$N$2:$N$6001,$AA13)) | N13: =IF($AA13="","",Settings!$C$8) | O13: =IF($AA13="","",SUMIFS('Per Line'!$T$2:$T$6001,'Per Line'!$C$2:$C$6001,$B13,'Per Line'!$AD$2:$AD$6001,1)) | P13: =IF($AA13="","",O13*N13) | Q13: =IF($AA13="","",Settings!$C$7) | R13: =IF($AA13="","",SUMIFS('Per Line'!$T$2:$T$6001,'Per Line'!$C$2:$C$6001,$B13,'Per Line'!$AC$2:$AC$6001,0,'Per Line'!$AD$2:$AD$6001,0)) | S13: =IF($AA13="","",R13*Q13) | T13: =IF($AA13="","",Settings!$C$6) | U13: =IF($AA13="","",SUMIFS('Per Line'!$T$2:$T$6001,'Per Line'!$C$2:$C$6001,$B13,'Per Line'!$AC$2:$AC$6001,1,'Per Line'!$AD$2:$AD$6001,0)) | V13: =IF($AA13="","",U13*T13) | W13: =IF($AA13="","",V13+S13+P13) | X13: =IF($AA13="","",Y13-W13) | Y13: =IF($AA13="","",R13+U13+O13) | Z13: =IF($AA13="","",Y13-W13-K13) | AA13: =IF(ROWS($AA$2:$AA13)<=MAX('Per Line'!$AB$2:$AB$6001),MATCH(ROWS($AA$2:$AA13),'Per Line'!$AB$2:$AB$6001,0),"")
... B2201: =IF($AA2201="","",INDEX('Per Line'!$C$2:$C$6001,$AA2201)&"") | C2201: =IF($AA2201="","",INDEX('Per Line'!$B$2:$B$6001,$AA2201)&"") | D2201: =IF($AA2201="","",INDEX('Per Line'!$A$2:$A$6001,$AA2201)&"") | E2201: =IF($AA2201="","",INDEX('Per Line'!$F$2:$F$6001,$AA2201)&"") | F2201: =IF($AA2201="","",INDEX('Per Line'!$G$2:$G$6001,$AA2201)&"") | G2201: =IF($AA2201="","",INDEX('Per Line'!$I$2:$I$6001,$AA2201)&"") | H2201: =IF($AA2201="","",INDEX('Per Line'!$J$2:$J$6001,$AA2201)&"") | I2201: =IF($AA2201="","",INDEX('Per Line'!$K$2:$K$6001,$AA2201)&"") | J2201: =IF($AA2201="","",INDEX('Per Line'!$L$2:$L$6001,$AA2201)) | K2201: =IF($AA2201="","",J2201*X2201/100) | M2201: =IF($AA2201="","",INDEX('Per Line'!$N$2:$N$6001,$AA2201)) | N2201: =IF($AA2201="","",Settings!$C$8) | O2201: =IF($AA2201="","",SUMIFS('Per Line'!$T$2:$T$6001,'Per Line'!$C$2:$C$6001,$B2201,'Per Line'!$AD$2:$AD$6001,1)) | P2201: =IF($AA2201="","",O2201*N2201) | Q2201: =IF($AA2201="","",Settings!$C$7) | R2201: =IF($AA2201="","",SUMIFS('Per Line'!$T$2:$T$6001,'Per Line'!$C$2:$C$6001,$B2201,'Per Line'!$AC$2:$AC$6001,0,'Per Line'!$AD$2:$AD$6001,0)) | S2201: =IF($AA2201="","",R2201*Q2201) | T2201: =IF($AA2201="","",Settings!$C$6) | U2201: =IF($AA2201="","",SUMIFS('Per Line'!$T$2:$T$6001,'Per Line'!$C$2:$C$6001,$B2201,'Per Line'!$AC$2:$AC$6001,1,'Per Line'!$AD$2:$AD$6001,0)) | V2201: =IF($AA2201="","",U2201*T2201) | W2201: =IF($AA2201="","",V2201+S2201+P2201) | X2201: =IF($AA2201="","",Y2201-W2201) | Y2201: =IF($AA2201="","",R2201+U2201+O2201) | Z2201: =IF($AA2201="","",Y2201-W2201-K2201) | AA2201: =IF(ROWS($AA$2:$AA2201)<=MAX('Per Line'!$AB$2:$AB$6001),MATCH(ROWS($AA$2:$AA2201),'Per Line'!$AB$2:$AB$6001,0),"")
