Workbook

Sheet How To Use
A1: Claims Template - CARE PLUS (Chronic)
A3: Monthly steps
A4: 1. Open the 'Per Line' tab. Delete the old data in the BLUE columns only (row 2 down). Never delete the green or grey columns.
A5: 2. Paste the new month's data as VALUES starting at A2, into the blue columns: A-M, O-X, AC-AJ (same order as the system export).
A6: 3. Green columns (N, Y, Z, AA, AB) and the grey helper columns (AK-AO) calculate automatically - do not paste over them.
A7: 4. 'Per Invoice' fills itself from 'Per Line' (one row per Order #, split into IMP / Local). No pivot table, no refresh.
A8: 5. The ONLY manual column in 'Per Invoice' is column A 'Invoice' (blue): type it yourself. Everything else is formula.
A9: 6. Open 'Settings' and check STATUS says OK (Per Line totals = Per Invoice totals).
A11: Colour legend
A12: Blue header = typed/pasted by you (raw data, and 'Invoice' in Per Invoice). Green header = formula (do not paste over). Grey header = helper formula (do not touch). Yellow cell (Settings) = editable rate.
A14: Calculation rules (taken from the September 2026 sheet)
A15: Co val = Order Co Payment x Total / 100. Discount = Total x Rebates / 100. Subtotal = Total - Discount. Net = Subtotal - Co val. (Total = 'Product Total')
... A20: Capacity: up to 3,000 lines and 800 invoices per month. A line with an empty Order # is ignored.

Sheet Settings
B1: Company settings & checks
B3: Insurance Company | C3: CARE PLUS | D3: Informational only
B4: Corporate | C4: El-Sallab HQ; EL-Sallab Tanta; El-Sallab Alex; El-Sallab Suhag; EL-Sallab Agamy; عربية للتنمية و التطوير العمراني; Magic Line; Obour land ... | D4: Informational only
B5: Sheet type | C5: Chronic | D5: Informational only
B6: Local products rebate % | C6: 0.15 | D6: Source: Sep sheet (Rebates = 15 on Local lines).
B7: Imported (IMP) products rebate % | C7: 0.06 | D7: Source: Sep sheet (Rebates = 6 on non-local lines; 0 on Special Rebates = Yes).
B9: Month totals / reconciliation
B10: Lines loaded | C10: =COUNTA('Per Line'!$D$2:$D$3001)
B11: Invoices (unique Order #) | C11: =MAX('Per Line'!$AL$2:$AL$3001)
B12: Invoices shown in Per Invoice | C12: =SUMPRODUCT(--('Per Invoice'!$B$2:$B$801<>""))
B13: Grand Total - Per Line (Product Total) | C13: =SUM('Per Line'!$V$2:$V$3001)
B14: Grand Total - Per Invoice | C14: =SUM('Per Invoice'!$V$2:$V$801)
B15: Discount - Per Line | C15: =SUM('Per Line'!$Z$2:$Z$3001)
B16: Discount - Per Invoice | C16: =SUM('Per Invoice'!$T$2:$T$801)
B17: Co val - Per Line | C17: =SUM('Per Line'!$N$2:$N$3001)
B18: Co val - Per Invoice | C18: =SUM('Per Invoice'!$I$2:$I$801)
B19: Net - Per Line | C19: =SUM('Per Line'!$AB$2:$AB$3001)
B20: Net - Per Invoice | C20: =SUM('Per Invoice'!$W$2:$W$801)
B21: Max Limit adjustment (Co val, Per Invoice only) | C21: 0 | D21: This company's Per Invoice has no Max Limit rule.
B23: STATUS | C23: =IF(C10=0,"No data loaded",IF(COUNTA('Per Line'!$D:$D)-1>3000,"TOO MANY LINES - extend template",IF(C11>800,"TOO MANY INVOICES - extend template",IF(AND(ROUND(C13-C14,2)=0,ROUND(C15-C16,2)=0,ROUND(C17+C21-C18,2)=0,ROUND(C19-C21-C20,2)=0,C11=C12),"OK","CHECK - Per Line and Per Invoice do not match")))) | D23: Must say OK after you paste the month data.

Sheet Per Line
A1: Cycle | B1: Ticket # | C1: Stage | D1: Order # | E1: Channel | F1: Create At | G1: Insurance Company | H1: Country Portal ID | I1: Corporate | J1: Card | K1: Name | L1: Status | M1: Order Co Payment | N1: Co val | O1: By Patient | P1: heisenberg id | Q1: Product Name | R1: Local | S1: Unit | T1: Quantity | U1: Unit Price | V1: Product Total | W1: ERX ID | X1: Special Rebates? | Y1: Rebates | Z1: Discount | AA1: Subtotal | AB1: Net | AC1: Approval Type | AD1: Max Limit | AE1: Exceeding Limit | AF1: Amount collected from customer | AG1: By Patient (Delivered) | AH1: Dispense Number | AI1: Dispense Date | AJ1: Has OTP? | AK1: Order 1st Row (helper) | AL1: Invoice # (helper) | AM1: Is Local (helper) | AN1: Is Special (helper) | AO1: Sort Key (helper)
N2: =IF($D2="","",M2*V2/100) | Y2: =IF($D2="","",IF($AN2=1,0,IF($AM2=1,Settings!$C$6,Settings!$C$7))*100) | Z2: =IF($D2="","",V2*Y2/100) | AA2: =IF($D2="","",V2-Z2) | AB2: =IF($D2="","",AA2-N2) | AK2: =IF($D2="","",IF(COUNTIF($D$2:$D2,$D2)=1,1,0)) | AL2: =IF($AK2=1,SUMPRODUCT(--($AO$2:$AO$3001<$AO2))+1,"") | AM2: =IF($D2="","",IF(OR($R2=TRUE(),$R2="TRUE"),1,0)) | AN2: =IF($D2="","",IF($X2="Yes",1,0)) | AO2: =IF($AK2=1,IFERROR(IF(VALUE($D2)<100000000,VALUE($D2),1000000000),IFERROR(IF(VALUE(MID($D2,2,20))<100000000,VALUE(MID($D2,2,20)),1000000000),1000000000))+ROW()/100000,"")
N3: =IF($D3="","",M3*V3/100) | Y3: =IF($D3="","",IF($AN3=1,0,IF($AM3=1,Settings!$C$6,Settings!$C$7))*100) | Z3: =IF($D3="","",V3*Y3/100) | AA3: =IF($D3="","",V3-Z3) | AB3: =IF($D3="","",AA3-N3) | AK3: =IF($D3="","",IF(COUNTIF($D$2:$D3,$D3)=1,1,0)) | AL3: =IF($AK3=1,SUMPRODUCT(--($AO$2:$AO$3001<$AO3))+1,"") | AM3: =IF($D3="","",IF(OR($R3=TRUE(),$R3="TRUE"),1,0)) | AN3: =IF($D3="","",IF($X3="Yes",1,0)) | AO3: =IF($AK3=1,IFERROR(IF(VALUE($D3)<100000000,VALUE($D3),1000000000),IFERROR(IF(VALUE(MID($D3,2,20))<100000000,VALUE(MID($D3,2,20)),1000000000),1000000000))+ROW()/100000,"")
N4: =IF($D4="","",M4*V4/100) | Y4: =IF($D4="","",IF($AN4=1,0,IF($AM4=1,Settings!$C$6,Settings!$C$7))*100) | Z4: =IF($D4="","",V4*Y4/100) | AA4: =IF($D4="","",V4-Z4) | AB4: =IF($D4="","",AA4-N4) | AK4: =IF($D4="","",IF(COUNTIF($D$2:$D4,$D4)=1,1,0)) | AL4: =IF($AK4=1,SUMPRODUCT(--($AO$2:$AO$3001<$AO4))+1,"") | AM4: =IF($D4="","",IF(OR($R4=TRUE(),$R4="TRUE"),1,0)) | AN4: =IF($D4="","",IF($X4="Yes",1,0)) | AO4: =IF($AK4=1,IFERROR(IF(VALUE($D4)<100000000,VALUE($D4),1000000000),IFERROR(IF(VALUE(MID($D4,2,20))<100000000,VALUE(MID($D4,2,20)),1000000000),1000000000))+ROW()/100000,"")
N5: =IF($D5="","",M5*V5/100) | Y5: =IF($D5="","",IF($AN5=1,0,IF($AM5=1,Settings!$C$6,Settings!$C$7))*100) | Z5: =IF($D5="","",V5*Y5/100) | AA5: =IF($D5="","",V5-Z5) | AB5: =IF($D5="","",AA5-N5) | AK5: =IF($D5="","",IF(COUNTIF($D$2:$D5,$D5)=1,1,0)) | AL5: =IF($AK5=1,SUMPRODUCT(--($AO$2:$AO$3001<$AO5))+1,"") | AM5: =IF($D5="","",IF(OR($R5=TRUE(),$R5="TRUE"),1,0)) | AN5: =IF($D5="","",IF($X5="Yes",1,0)) | AO5: =IF($AK5=1,IFERROR(IF(VALUE($D5)<100000000,VALUE($D5),1000000000),IFERROR(IF(VALUE(MID($D5,2,20))<100000000,VALUE(MID($D5,2,20)),1000000000),1000000000))+ROW()/100000,"")
N6: =IF($D6="","",M6*V6/100) | Y6: =IF($D6="","",IF($AN6=1,0,IF($AM6=1,Settings!$C$6,Settings!$C$7))*100) | Z6: =IF($D6="","",V6*Y6/100) | AA6: =IF($D6="","",V6-Z6) | AB6: =IF($D6="","",AA6-N6) | AK6: =IF($D6="","",IF(COUNTIF($D$2:$D6,$D6)=1,1,0)) | AL6: =IF($AK6=1,SUMPRODUCT(--($AO$2:$AO$3001<$AO6))+1,"") | AM6: =IF($D6="","",IF(OR($R6=TRUE(),$R6="TRUE"),1,0)) | AN6: =IF($D6="","",IF($X6="Yes",1,0)) | AO6: =IF($AK6=1,IFERROR(IF(VALUE($D6)<100000000,VALUE($D6),1000000000),IFERROR(IF(VALUE(MID($D6,2,20))<100000000,VALUE(MID($D6,2,20)),1000000000),1000000000))+ROW()/100000,"")
N7: =IF($D7="","",M7*V7/100) | Y7: =IF($D7="","",IF($AN7=1,0,IF($AM7=1,Settings!$C$6,Settings!$C$7))*100) | Z7: =IF($D7="","",V7*Y7/100) | AA7: =IF($D7="","",V7-Z7) | AB7: =IF($D7="","",AA7-N7) | AK7: =IF($D7="","",IF(COUNTIF($D$2:$D7,$D7)=1,1,0)) | AL7: =IF($AK7=1,SUMPRODUCT(--($AO$2:$AO$3001<$AO7))+1,"") | AM7: =IF($D7="","",IF(OR($R7=TRUE(),$R7="TRUE"),1,0)) | AN7: =IF($D7="","",IF($X7="Yes",1,0)) | AO7: =IF($AK7=1,IFERROR(IF(VALUE($D7)<100000000,VALUE($D7),1000000000),IFERROR(IF(VALUE(MID($D7,2,20))<100000000,VALUE(MID($D7,2,20)),1000000000),1000000000))+ROW()/100000,"")
N8: =IF($D8="","",M8*V8/100) | Y8: =IF($D8="","",IF($AN8=1,0,IF($AM8=1,Settings!$C$6,Settings!$C$7))*100) | Z8: =IF($D8="","",V8*Y8/100) | AA8: =IF($D8="","",V8-Z8) | AB8: =IF($D8="","",AA8-N8) | AK8: =IF($D8="","",IF(COUNTIF($D$2:$D8,$D8)=1,1,0)) | AL8: =IF($AK8=1,SUMPRODUCT(--($AO$2:$AO$3001<$AO8))+1,"") | AM8: =IF($D8="","",IF(OR($R8=TRUE(),$R8="TRUE"),1,0)) | AN8: =IF($D8="","",IF($X8="Yes",1,0)) | AO8: =IF($AK8=1,IFERROR(IF(VALUE($D8)<100000000,VALUE($D8),1000000000),IFERROR(IF(VALUE(MID($D8,2,20))<100000000,VALUE(MID($D8,2,20)),1000000000),1000000000))+ROW()/100000,"")
N9: =IF($D9="","",M9*V9/100) | Y9: =IF($D9="","",IF($AN9=1,0,IF($AM9=1,Settings!$C$6,Settings!$C$7))*100) | Z9: =IF($D9="","",V9*Y9/100) | AA9: =IF($D9="","",V9-Z9) | AB9: =IF($D9="","",AA9-N9) | AK9: =IF($D9="","",IF(COUNTIF($D$2:$D9,$D9)=1,1,0)) | AL9: =IF($AK9=1,SUMPRODUCT(--($AO$2:$AO$3001<$AO9))+1,"") | AM9: =IF($D9="","",IF(OR($R9=TRUE(),$R9="TRUE"),1,0)) | AN9: =IF($D9="","",IF($X9="Yes",1,0)) | AO9: =IF($AK9=1,IFERROR(IF(VALUE($D9)<100000000,VALUE($D9),1000000000),IFERROR(IF(VALUE(MID($D9,2,20))<100000000,VALUE(MID($D9,2,20)),1000000000),1000000000))+ROW()/100000,"")
N10: =IF($D10="","",M10*V10/100) | Y10: =IF($D10="","",IF($AN10=1,0,IF($AM10=1,Settings!$C$6,Settings!$C$7))*100) | Z10: =IF($D10="","",V10*Y10/100) | AA10: =IF($D10="","",V10-Z10) | AB10: =IF($D10="","",AA10-N10) | AK10: =IF($D10="","",IF(COUNTIF($D$2:$D10,$D10)=1,1,0)) | AL10: =IF($AK10=1,SUMPRODUCT(--($AO$2:$AO$3001<$AO10))+1,"") | AM10: =IF($D10="","",IF(OR($R10=TRUE(),$R10="TRUE"),1,0)) | AN10: =IF($D10="","",IF($X10="Yes",1,0)) | AO10: =IF($AK10=1,IFERROR(IF(VALUE($D10)<100000000,VALUE($D10),1000000000),IFERROR(IF(VALUE(MID($D10,2,20))<100000000,VALUE(MID($D10,2,20)),1000000000),1000000000))+ROW()/100000,"")
N11: =IF($D11="","",M11*V11/100) | Y11: =IF($D11="","",IF($AN11=1,0,IF($AM11=1,Settings!$C$6,Settings!$C$7))*100) | Z11: =IF($D11="","",V11*Y11/100) | AA11: =IF($D11="","",V11-Z11) | AB11: =IF($D11="","",AA11-N11) | AK11: =IF($D11="","",IF(COUNTIF($D$2:$D11,$D11)=1,1,0)) | AL11: =IF($AK11=1,SUMPRODUCT(--($AO$2:$AO$3001<$AO11))+1,"") | AM11: =IF($D11="","",IF(OR($R11=TRUE(),$R11="TRUE"),1,0)) | AN11: =IF($D11="","",IF($X11="Yes",1,0)) | AO11: =IF($AK11=1,IFERROR(IF(VALUE($D11)<100000000,VALUE($D11),1000000000),IFERROR(IF(VALUE(MID($D11,2,20))<100000000,VALUE(MID($D11,2,20)),1000000000),1000000000))+ROW()/100000,"")
N12: =IF($D12="","",M12*V12/100) | Y12: =IF($D12="","",IF($AN12=1,0,IF($AM12=1,Settings!$C$6,Settings!$C$7))*100) | Z12: =IF($D12="","",V12*Y12/100) | AA12: =IF($D12="","",V12-Z12) | AB12: =IF($D12="","",AA12-N12) | AK12: =IF($D12="","",IF(COUNTIF($D$2:$D12,$D12)=1,1,0)) | AL12: =IF($AK12=1,SUMPRODUCT(--($AO$2:$AO$3001<$AO12))+1,"") | AM12: =IF($D12="","",IF(OR($R12=TRUE(),$R12="TRUE"),1,0)) | AN12: =IF($D12="","",IF($X12="Yes",1,0)) | AO12: =IF($AK12=1,IFERROR(IF(VALUE($D12)<100000000,VALUE($D12),1000000000),IFERROR(IF(VALUE(MID($D12,2,20))<100000000,VALUE(MID($D12,2,20)),1000000000),1000000000))+ROW()/100000,"")
N13: =IF($D13="","",M13*V13/100) | Y13: =IF($D13="","",IF($AN13=1,0,IF($AM13=1,Settings!$C$6,Settings!$C$7))*100) | Z13: =IF($D13="","",V13*Y13/100) | AA13: =IF($D13="","",V13-Z13) | AB13: =IF($D13="","",AA13-N13) | AK13: =IF($D13="","",IF(COUNTIF($D$2:$D13,$D13)=1,1,0)) | AL13: =IF($AK13=1,SUMPRODUCT(--($AO$2:$AO$3001<$AO13))+1,"") | AM13: =IF($D13="","",IF(OR($R13=TRUE(),$R13="TRUE"),1,0)) | AN13: =IF($D13="","",IF($X13="Yes",1,0)) | AO13: =IF($AK13=1,IFERROR(IF(VALUE($D13)<100000000,VALUE($D13),1000000000),IFERROR(IF(VALUE(MID($D13,2,20))<100000000,VALUE(MID($D13,2,20)),1000000000),1000000000))+ROW()/100000,"")
... N3001: =IF($D3001="","",M3001*V3001/100) | Y3001: =IF($D3001="","",IF($AN3001=1,0,IF($AM3001=1,Settings!$C$6,Settings!$C$7))*100) | Z3001: =IF($D3001="","",V3001*Y3001/100) | AA3001: =IF($D3001="","",V3001-Z3001) | AB3001: =IF($D3001="","",AA3001-N3001) | AK3001: =IF($D3001="","",IF(COUNTIF($D$2:$D3001,$D3001)=1,1,0)) | AL3001: =IF($AK3001=1,SUMPRODUCT(--($AO$2:$AO$3001<$AO3001))+1,"") | AM3001: =IF($D3001="","",IF(OR($R3001=TRUE(),$R3001="TRUE"),1,0)) | AN3001: =IF($D3001="","",IF($X3001="Yes",1,0)) | AO3001: =IF($AK3001=1,IFERROR(IF(VALUE($D3001)<100000000,VALUE($D3001),1000000000),IFERROR(IF(VALUE(MID($D3001,2,20))<100000000,VALUE(MID($D3001,2,20)),1000000000),1000000000))+ROW()/100000,"")

Sheet Per Invoice
A1: Invoice | B1: Order # | C1: Create At | D1: Insurance Company | E1: Corporate | F1: Card | G1: Name | H1: Order Co Payment | I1: Co val | J1: ERX ID | K1: Max Limit | L1: Exceeding Limit | M1: Special rebates | N1: IMP % | O1: IMP | P1: IMP VAL | Q1: LOCAL % | R1: LOCAL | S1: LOCAL VAL | T1: TOTAL VAL | U1: SUBTOTAL | V1: Grand Total | W1: NET | X1: Src Row (helper)
B2: =IF($X2="","",INDEX('Per Line'!$D$2:$D$3001,$X2)&"") | C2: =IF($X2="","",INDEX('Per Line'!$F$2:$F$3001,$X2)) | D2: =IF($X2="","",INDEX('Per Line'!$G$2:$G$3001,$X2)&"") | E2: =IF($X2="","",INDEX('Per Line'!$I$2:$I$3001,$X2)&"") | F2: =IF($X2="","",INDEX('Per Line'!$J$2:$J$3001,$X2)&"") | G2: =IF($X2="","",INDEX('Per Line'!$K$2:$K$3001,$X2)&"") | H2: =IF($X2="","",INDEX('Per Line'!$M$2:$M$3001,$X2)) | I2: =IF($X2="","",H2*V2/100) | J2: =IF($X2="","",INDEX('Per Line'!$W$2:$W$3001,$X2)&"") | K2: =IF($X2="","",INDEX('Per Line'!$AD$2:$AD$3001,$X2)) | L2: =IF($X2="","",IF(AND(ISNUMBER(K2),K2>0),V2>K2,FALSE)) | M2: =IF($X2="","",SUMIFS('Per Line'!$V$2:$V$3001,'Per Line'!$D$2:$D$3001,$B2,'Per Line'!$AN$2:$AN$3001,1)) | N2: =IF($X2="","",Settings!$C$7) | O2: =IF($X2="","",SUMIFS('Per Line'!$V$2:$V$3001,'Per Line'!$D$2:$D$3001,$B2,'Per Line'!$AM$2:$AM$3001,0,'Per Line'!$AN$2:$AN$3001,0)) | P2: =IF($X2="","",O2*N2) | Q2: =IF($X2="","",Settings!$C$6) | R2: =IF($X2="","",SUMIFS('Per Line'!$V$2:$V$3001,'Per Line'!$D$2:$D$3001,$B2,'Per Line'!$AM$2:$AM$3001,1,'Per Line'!$AN$2:$AN$3001,0)) | S2: =IF($X2="","",R2*Q2) | T2: =IF($X2="","",S2+P2) | U2: =IF($X2="","",V2-T2) | V2: =IF($X2="","",O2+R2+M2) | W2: =IF($X2="","",V2-T2-I2) | X2: =IF(ROWS($X$2:$X2)<=MAX('Per Line'!$AL$2:$AL$3001),MATCH(ROWS($X$2:$X2),'Per Line'!$AL$2:$AL$3001,0),"")
B3: =IF($X3="","",INDEX('Per Line'!$D$2:$D$3001,$X3)&"") | C3: =IF($X3="","",INDEX('Per Line'!$F$2:$F$3001,$X3)) | D3: =IF($X3="","",INDEX('Per Line'!$G$2:$G$3001,$X3)&"") | E3: =IF($X3="","",INDEX('Per Line'!$I$2:$I$3001,$X3)&"") | F3: =IF($X3="","",INDEX('Per Line'!$J$2:$J$3001,$X3)&"") | G3: =IF($X3="","",INDEX('Per Line'!$K$2:$K$3001,$X3)&"") | H3: =IF($X3="","",INDEX('Per Line'!$M$2:$M$3001,$X3)) | I3: =IF($X3="","",H3*V3/100) | J3: =IF($X3="","",INDEX('Per Line'!$W$2:$W$3001,$X3)&"") | K3: =IF($X3="","",INDEX('Per Line'!$AD$2:$AD$3001,$X3)) | L3: =IF($X3="","",IF(AND(ISNUMBER(K3),K3>0),V3>K3,FALSE)) | M3: =IF($X3="","",SUMIFS('Per Line'!$V$2:$V$3001,'Per Line'!$D$2:$D$3001,$B3,'Per Line'!$AN$2:$AN$3001,1)) | N3: =IF($X3="","",Settings!$C$7) | O3: =IF($X3="","",SUMIFS('Per Line'!$V$2:$V$3001,'Per Line'!$D$2:$D$3001,$B3,'Per Line'!$AM$2:$AM$3001,0,'Per Line'!$AN$2:$AN$3001,0)) | P3: =IF($X3="","",O3*N3) | Q3: =IF($X3="","",Settings!$C$6) | R3: =IF($X3="","",SUMIFS('Per Line'!$V$2:$V$3001,'Per Line'!$D$2:$D$3001,$B3,'Per Line'!$AM$2:$AM$3001,1,'Per Line'!$AN$2:$AN$3001,0)) | S3: =IF($X3="","",R3*Q3) | T3: =IF($X3="","",S3+P3) | U3: =IF($X3="","",V3-T3) | V3: =IF($X3="","",O3+R3+M3) | W3: =IF($X3="","",V3-T3-I3) | X3: =IF(ROWS($X$2:$X3)<=MAX('Per Line'!$AL$2:$AL$3001),MATCH(ROWS($X$2:$X3),'Per Line'!$AL$2:$AL$3001,0),"")
B4: =IF($X4="","",INDEX('Per Line'!$D$2:$D$3001,$X4)&"") | C4: =IF($X4="","",INDEX('Per Line'!$F$2:$F$3001,$X4)) | D4: =IF($X4="","",INDEX('Per Line'!$G$2:$G$3001,$X4)&"") | E4: =IF($X4="","",INDEX('Per Line'!$I$2:$I$3001,$X4)&"") | F4: =IF($X4="","",INDEX('Per Line'!$J$2:$J$3001,$X4)&"") | G4: =IF($X4="","",INDEX('Per Line'!$K$2:$K$3001,$X4)&"") | H4: =IF($X4="","",INDEX('Per Line'!$M$2:$M$3001,$X4)) | I4: =IF($X4="","",H4*V4/100) | J4: =IF($X4="","",INDEX('Per Line'!$W$2:$W$3001,$X4)&"") | K4: =IF($X4="","",INDEX('Per Line'!$AD$2:$AD$3001,$X4)) | L4: =IF($X4="","",IF(AND(ISNUMBER(K4),K4>0),V4>K4,FALSE)) | M4: =IF($X4="","",SUMIFS('Per Line'!$V$2:$V$3001,'Per Line'!$D$2:$D$3001,$B4,'Per Line'!$AN$2:$AN$3001,1)) | N4: =IF($X4="","",Settings!$C$7) | O4: =IF($X4="","",SUMIFS('Per Line'!$V$2:$V$3001,'Per Line'!$D$2:$D$3001,$B4,'Per Line'!$AM$2:$AM$3001,0,'Per Line'!$AN$2:$AN$3001,0)) | P4: =IF($X4="","",O4*N4) | Q4: =IF($X4="","",Settings!$C$6) | R4: =IF($X4="","",SUMIFS('Per Line'!$V$2:$V$3001,'Per Line'!$D$2:$D$3001,$B4,'Per Line'!$AM$2:$AM$3001,1,'Per Line'!$AN$2:$AN$3001,0)) | S4: =IF($X4="","",R4*Q4) | T4: =IF($X4="","",S4+P4) | U4: =IF($X4="","",V4-T4) | V4: =IF($X4="","",O4+R4+M4) | W4: =IF($X4="","",V4-T4-I4) | X4: =IF(ROWS($X$2:$X4)<=MAX('Per Line'!$AL$2:$AL$3001),MATCH(ROWS($X$2:$X4),'Per Line'!$AL$2:$AL$3001,0),"")
B5: =IF($X5="","",INDEX('Per Line'!$D$2:$D$3001,$X5)&"") | C5: =IF($X5="","",INDEX('Per Line'!$F$2:$F$3001,$X5)) | D5: =IF($X5="","",INDEX('Per Line'!$G$2:$G$3001,$X5)&"") | E5: =IF($X5="","",INDEX('Per Line'!$I$2:$I$3001,$X5)&"") | F5: =IF($X5="","",INDEX('Per Line'!$J$2:$J$3001,$X5)&"") | G5: =IF($X5="","",INDEX('Per Line'!$K$2:$K$3001,$X5)&"") | H5: =IF($X5="","",INDEX('Per Line'!$M$2:$M$3001,$X5)) | I5: =IF($X5="","",H5*V5/100) | J5: =IF($X5="","",INDEX('Per Line'!$W$2:$W$3001,$X5)&"") | K5: =IF($X5="","",INDEX('Per Line'!$AD$2:$AD$3001,$X5)) | L5: =IF($X5="","",IF(AND(ISNUMBER(K5),K5>0),V5>K5,FALSE)) | M5: =IF($X5="","",SUMIFS('Per Line'!$V$2:$V$3001,'Per Line'!$D$2:$D$3001,$B5,'Per Line'!$AN$2:$AN$3001,1)) | N5: =IF($X5="","",Settings!$C$7) | O5: =IF($X5="","",SUMIFS('Per Line'!$V$2:$V$3001,'Per Line'!$D$2:$D$3001,$B5,'Per Line'!$AM$2:$AM$3001,0,'Per Line'!$AN$2:$AN$3001,0)) | P5: =IF($X5="","",O5*N5) | Q5: =IF($X5="","",Settings!$C$6) | R5: =IF($X5="","",SUMIFS('Per Line'!$V$2:$V$3001,'Per Line'!$D$2:$D$3001,$B5,'Per Line'!$AM$2:$AM$3001,1,'Per Line'!$AN$2:$AN$3001,0)) | S5: =IF($X5="","",R5*Q5) | T5: =IF($X5="","",S5+P5) | U5: =IF($X5="","",V5-T5) | V5: =IF($X5="","",O5+R5+M5) | W5: =IF($X5="","",V5-T5-I5) | X5: =IF(ROWS($X$2:$X5)<=MAX('Per Line'!$AL$2:$AL$3001),MATCH(ROWS($X$2:$X5),'Per Line'!$AL$2:$AL$3001,0),"")
B6: =IF($X6="","",INDEX('Per Line'!$D$2:$D$3001,$X6)&"") | C6: =IF($X6="","",INDEX('Per Line'!$F$2:$F$3001,$X6)) | D6: =IF($X6="","",INDEX('Per Line'!$G$2:$G$3001,$X6)&"") | E6: =IF($X6="","",INDEX('Per Line'!$I$2:$I$3001,$X6)&"") | F6: =IF($X6="","",INDEX('Per Line'!$J$2:$J$3001,$X6)&"") | G6: =IF($X6="","",INDEX('Per Line'!$K$2:$K$3001,$X6)&"") | H6: =IF($X6="","",INDEX('Per Line'!$M$2:$M$3001,$X6)) | I6: =IF($X6="","",H6*V6/100) | J6: =IF($X6="","",INDEX('Per Line'!$W$2:$W$3001,$X6)&"") | K6: =IF($X6="","",INDEX('Per Line'!$AD$2:$AD$3001,$X6)) | L6: =IF($X6="","",IF(AND(ISNUMBER(K6),K6>0),V6>K6,FALSE)) | M6: =IF($X6="","",SUMIFS('Per Line'!$V$2:$V$3001,'Per Line'!$D$2:$D$3001,$B6,'Per Line'!$AN$2:$AN$3001,1)) | N6: =IF($X6="","",Settings!$C$7) | O6: =IF($X6="","",SUMIFS('Per Line'!$V$2:$V$3001,'Per Line'!$D$2:$D$3001,$B6,'Per Line'!$AM$2:$AM$3001,0,'Per Line'!$AN$2:$AN$3001,0)) | P6: =IF($X6="","",O6*N6) | Q6: =IF($X6="","",Settings!$C$6) | R6: =IF($X6="","",SUMIFS('Per Line'!$V$2:$V$3001,'Per Line'!$D$2:$D$3001,$B6,'Per Line'!$AM$2:$AM$3001,1,'Per Line'!$AN$2:$AN$3001,0)) | S6: =IF($X6="","",R6*Q6) | T6: =IF($X6="","",S6+P6) | U6: =IF($X6="","",V6-T6) | V6: =IF($X6="","",O6+R6+M6) | W6: =IF($X6="","",V6-T6-I6) | X6: =IF(ROWS($X$2:$X6)<=MAX('Per Line'!$AL$2:$AL$3001),MATCH(ROWS($X$2:$X6),'Per Line'!$AL$2:$AL$3001,0),"")
B7: =IF($X7="","",INDEX('Per Line'!$D$2:$D$3001,$X7)&"") | C7: =IF($X7="","",INDEX('Per Line'!$F$2:$F$3001,$X7)) | D7: =IF($X7="","",INDEX('Per Line'!$G$2:$G$3001,$X7)&"") | E7: =IF($X7="","",INDEX('Per Line'!$I$2:$I$3001,$X7)&"") | F7: =IF($X7="","",INDEX('Per Line'!$J$2:$J$3001,$X7)&"") | G7: =IF($X7="","",INDEX('Per Line'!$K$2:$K$3001,$X7)&"") | H7: =IF($X7="","",INDEX('Per Line'!$M$2:$M$3001,$X7)) | I7: =IF($X7="","",H7*V7/100) | J7: =IF($X7="","",INDEX('Per Line'!$W$2:$W$3001,$X7)&"") | K7: =IF($X7="","",INDEX('Per Line'!$AD$2:$AD$3001,$X7)) | L7: =IF($X7="","",IF(AND(ISNUMBER(K7),K7>0),V7>K7,FALSE)) | M7: =IF($X7="","",SUMIFS('Per Line'!$V$2:$V$3001,'Per Line'!$D$2:$D$3001,$B7,'Per Line'!$AN$2:$AN$3001,1)) | N7: =IF($X7="","",Settings!$C$7) | O7: =IF($X7="","",SUMIFS('Per Line'!$V$2:$V$3001,'Per Line'!$D$2:$D$3001,$B7,'Per Line'!$AM$2:$AM$3001,0,'Per Line'!$AN$2:$AN$3001,0)) | P7: =IF($X7="","",O7*N7) | Q7: =IF($X7="","",Settings!$C$6) | R7: =IF($X7="","",SUMIFS('Per Line'!$V$2:$V$3001,'Per Line'!$D$2:$D$3001,$B7,'Per Line'!$AM$2:$AM$3001,1,'Per Line'!$AN$2:$AN$3001,0)) | S7: =IF($X7="","",R7*Q7) | T7: =IF($X7="","",S7+P7) | U7: =IF($X7="","",V7-T7) | V7: =IF($X7="","",O7+R7+M7) | W7: =IF($X7="","",V7-T7-I7) | X7: =IF(ROWS($X$2:$X7)<=MAX('Per Line'!$AL$2:$AL$3001),MATCH(ROWS($X$2:$X7),'Per Line'!$AL$2:$AL$3001,0),"")
B8: =IF($X8="","",INDEX('Per Line'!$D$2:$D$3001,$X8)&"") | C8: =IF($X8="","",INDEX('Per Line'!$F$2:$F$3001,$X8)) | D8: =IF($X8="","",INDEX('Per Line'!$G$2:$G$3001,$X8)&"") | E8: =IF($X8="","",INDEX('Per Line'!$I$2:$I$3001,$X8)&"") | F8: =IF($X8="","",INDEX('Per Line'!$J$2:$J$3001,$X8)&"") | G8: =IF($X8="","",INDEX('Per Line'!$K$2:$K$3001,$X8)&"") | H8: =IF($X8="","",INDEX('Per Line'!$M$2:$M$3001,$X8)) | I8: =IF($X8="","",H8*V8/100) | J8: =IF($X8="","",INDEX('Per Line'!$W$2:$W$3001,$X8)&"") | K8: =IF($X8="","",INDEX('Per Line'!$AD$2:$AD$3001,$X8)) | L8: =IF($X8="","",IF(AND(ISNUMBER(K8),K8>0),V8>K8,FALSE)) | M8: =IF($X8="","",SUMIFS('Per Line'!$V$2:$V$3001,'Per Line'!$D$2:$D$3001,$B8,'Per Line'!$AN$2:$AN$3001,1)) | N8: =IF($X8="","",Settings!$C$7) | O8: =IF($X8="","",SUMIFS('Per Line'!$V$2:$V$3001,'Per Line'!$D$2:$D$3001,$B8,'Per Line'!$AM$2:$AM$3001,0,'Per Line'!$AN$2:$AN$3001,0)) | P8: =IF($X8="","",O8*N8) | Q8: =IF($X8="","",Settings!$C$6) | R8: =IF($X8="","",SUMIFS('Per Line'!$V$2:$V$3001,'Per Line'!$D$2:$D$3001,$B8,'Per Line'!$AM$2:$AM$3001,1,'Per Line'!$AN$2:$AN$3001,0)) | S8: =IF($X8="","",R8*Q8) | T8: =IF($X8="","",S8+P8) | U8: =IF($X8="","",V8-T8) | V8: =IF($X8="","",O8+R8+M8) | W8: =IF($X8="","",V8-T8-I8) | X8: =IF(ROWS($X$2:$X8)<=MAX('Per Line'!$AL$2:$AL$3001),MATCH(ROWS($X$2:$X8),'Per Line'!$AL$2:$AL$3001,0),"")
B9: =IF($X9="","",INDEX('Per Line'!$D$2:$D$3001,$X9)&"") | C9: =IF($X9="","",INDEX('Per Line'!$F$2:$F$3001,$X9)) | D9: =IF($X9="","",INDEX('Per Line'!$G$2:$G$3001,$X9)&"") | E9: =IF($X9="","",INDEX('Per Line'!$I$2:$I$3001,$X9)&"") | F9: =IF($X9="","",INDEX('Per Line'!$J$2:$J$3001,$X9)&"") | G9: =IF($X9="","",INDEX('Per Line'!$K$2:$K$3001,$X9)&"") | H9: =IF($X9="","",INDEX('Per Line'!$M$2:$M$3001,$X9)) | I9: =IF($X9="","",H9*V9/100) | J9: =IF($X9="","",INDEX('Per Line'!$W$2:$W$3001,$X9)&"") | K9: =IF($X9="","",INDEX('Per Line'!$AD$2:$AD$3001,$X9)) | L9: =IF($X9="","",IF(AND(ISNUMBER(K9),K9>0),V9>K9,FALSE)) | M9: =IF($X9="","",SUMIFS('Per Line'!$V$2:$V$3001,'Per Line'!$D$2:$D$3001,$B9,'Per Line'!$AN$2:$AN$3001,1)) | N9: =IF($X9="","",Settings!$C$7) | O9: =IF($X9="","",SUMIFS('Per Line'!$V$2:$V$3001,'Per Line'!$D$2:$D$3001,$B9,'Per Line'!$AM$2:$AM$3001,0,'Per Line'!$AN$2:$AN$3001,0)) | P9: =IF($X9="","",O9*N9) | Q9: =IF($X9="","",Settings!$C$6) | R9: =IF($X9="","",SUMIFS('Per Line'!$V$2:$V$3001,'Per Line'!$D$2:$D$3001,$B9,'Per Line'!$AM$2:$AM$3001,1,'Per Line'!$AN$2:$AN$3001,0)) | S9: =IF($X9="","",R9*Q9) | T9: =IF($X9="","",S9+P9) | U9: =IF($X9="","",V9-T9) | V9: =IF($X9="","",O9+R9+M9) | W9: =IF($X9="","",V9-T9-I9) | X9: =IF(ROWS($X$2:$X9)<=MAX('Per Line'!$AL$2:$AL$3001),MATCH(ROWS($X$2:$X9),'Per Line'!$AL$2:$AL$3001,0),"")
B10: =IF($X10="","",INDEX('Per Line'!$D$2:$D$3001,$X10)&"") | C10: =IF($X10="","",INDEX('Per Line'!$F$2:$F$3001,$X10)) | D10: =IF($X10="","",INDEX('Per Line'!$G$2:$G$3001,$X10)&"") | E10: =IF($X10="","",INDEX('Per Line'!$I$2:$I$3001,$X10)&"") | F10: =IF($X10="","",INDEX('Per Line'!$J$2:$J$3001,$X10)&"") | G10: =IF($X10="","",INDEX('Per Line'!$K$2:$K$3001,$X10)&"") | H10: =IF($X10="","",INDEX('Per Line'!$M$2:$M$3001,$X10)) | I10: =IF($X10="","",H10*V10/100) | J10: =IF($X10="","",INDEX('Per Line'!$W$2:$W$3001,$X10)&"") | K10: =IF($X10="","",INDEX('Per Line'!$AD$2:$AD$3001,$X10)) | L10: =IF($X10="","",IF(AND(ISNUMBER(K10),K10>0),V10>K10,FALSE)) | M10: =IF($X10="","",SUMIFS('Per Line'!$V$2:$V$3001,'Per Line'!$D$2:$D$3001,$B10,'Per Line'!$AN$2:$AN$3001,1)) | N10: =IF($X10="","",Settings!$C$7) | O10: =IF($X10="","",SUMIFS('Per Line'!$V$2:$V$3001,'Per Line'!$D$2:$D$3001,$B10,'Per Line'!$AM$2:$AM$3001,0,'Per Line'!$AN$2:$AN$3001,0)) | P10: =IF($X10="","",O10*N10) | Q10: =IF($X10="","",Settings!$C$6) | R10: =IF($X10="","",SUMIFS('Per Line'!$V$2:$V$3001,'Per Line'!$D$2:$D$3001,$B10,'Per Line'!$AM$2:$AM$3001,1,'Per Line'!$AN$2:$AN$3001,0)) | S10: =IF($X10="","",R10*Q10) | T10: =IF($X10="","",S10+P10) | U10: =IF($X10="","",V10-T10) | V10: =IF($X10="","",O10+R10+M10) | W10: =IF($X10="","",V10-T10-I10) | X10: =IF(ROWS($X$2:$X10)<=MAX('Per Line'!$AL$2:$AL$3001),MATCH(ROWS($X$2:$X10),'Per Line'!$AL$2:$AL$3001,0),"")
B11: =IF($X11="","",INDEX('Per Line'!$D$2:$D$3001,$X11)&"") | C11: =IF($X11="","",INDEX('Per Line'!$F$2:$F$3001,$X11)) | D11: =IF($X11="","",INDEX('Per Line'!$G$2:$G$3001,$X11)&"") | E11: =IF($X11="","",INDEX('Per Line'!$I$2:$I$3001,$X11)&"") | F11: =IF($X11="","",INDEX('Per Line'!$J$2:$J$3001,$X11)&"") | G11: =IF($X11="","",INDEX('Per Line'!$K$2:$K$3001,$X11)&"") | H11: =IF($X11="","",INDEX('Per Line'!$M$2:$M$3001,$X11)) | I11: =IF($X11="","",H11*V11/100) | J11: =IF($X11="","",INDEX('Per Line'!$W$2:$W$3001,$X11)&"") | K11: =IF($X11="","",INDEX('Per Line'!$AD$2:$AD$3001,$X11)) | L11: =IF($X11="","",IF(AND(ISNUMBER(K11),K11>0),V11>K11,FALSE)) | M11: =IF($X11="","",SUMIFS('Per Line'!$V$2:$V$3001,'Per Line'!$D$2:$D$3001,$B11,'Per Line'!$AN$2:$AN$3001,1)) | N11: =IF($X11="","",Settings!$C$7) | O11: =IF($X11="","",SUMIFS('Per Line'!$V$2:$V$3001,'Per Line'!$D$2:$D$3001,$B11,'Per Line'!$AM$2:$AM$3001,0,'Per Line'!$AN$2:$AN$3001,0)) | P11: =IF($X11="","",O11*N11) | Q11: =IF($X11="","",Settings!$C$6) | R11: =IF($X11="","",SUMIFS('Per Line'!$V$2:$V$3001,'Per Line'!$D$2:$D$3001,$B11,'Per Line'!$AM$2:$AM$3001,1,'Per Line'!$AN$2:$AN$3001,0)) | S11: =IF($X11="","",R11*Q11) | T11: =IF($X11="","",S11+P11) | U11: =IF($X11="","",V11-T11) | V11: =IF($X11="","",O11+R11+M11) | W11: =IF($X11="","",V11-T11-I11) | X11: =IF(ROWS($X$2:$X11)<=MAX('Per Line'!$AL$2:$AL$3001),MATCH(ROWS($X$2:$X11),'Per Line'!$AL$2:$AL$3001,0),"")
B12: =IF($X12="","",INDEX('Per Line'!$D$2:$D$3001,$X12)&"") | C12: =IF($X12="","",INDEX('Per Line'!$F$2:$F$3001,$X12)) | D12: =IF($X12="","",INDEX('Per Line'!$G$2:$G$3001,$X12)&"") | E12: =IF($X12="","",INDEX('Per Line'!$I$2:$I$3001,$X12)&"") | F12: =IF($X12="","",INDEX('Per Line'!$J$2:$J$3001,$X12)&"") | G12: =IF($X12="","",INDEX('Per Line'!$K$2:$K$3001,$X12)&"") | H12: =IF($X12="","",INDEX('Per Line'!$M$2:$M$3001,$X12)) | I12: =IF($X12="","",H12*V12/100) | J12: =IF($X12="","",INDEX('Per Line'!$W$2:$W$3001,$X12)&"") | K12: =IF($X12="","",INDEX('Per Line'!$AD$2:$AD$3001,$X12)) | L12: =IF($X12="","",IF(AND(ISNUMBER(K12),K12>0),V12>K12,FALSE)) | M12: =IF($X12="","",SUMIFS('Per Line'!$V$2:$V$3001,'Per Line'!$D$2:$D$3001,$B12,'Per Line'!$AN$2:$AN$3001,1)) | N12: =IF($X12="","",Settings!$C$7) | O12: =IF($X12="","",SUMIFS('Per Line'!$V$2:$V$3001,'Per Line'!$D$2:$D$3001,$B12,'Per Line'!$AM$2:$AM$3001,0,'Per Line'!$AN$2:$AN$3001,0)) | P12: =IF($X12="","",O12*N12) | Q12: =IF($X12="","",Settings!$C$6) | R12: =IF($X12="","",SUMIFS('Per Line'!$V$2:$V$3001,'Per Line'!$D$2:$D$3001,$B12,'Per Line'!$AM$2:$AM$3001,1,'Per Line'!$AN$2:$AN$3001,0)) | S12: =IF($X12="","",R12*Q12) | T12: =IF($X12="","",S12+P12) | U12: =IF($X12="","",V12-T12) | V12: =IF($X12="","",O12+R12+M12) | W12: =IF($X12="","",V12-T12-I12) | X12: =IF(ROWS($X$2:$X12)<=MAX('Per Line'!$AL$2:$AL$3001),MATCH(ROWS($X$2:$X12),'Per Line'!$AL$2:$AL$3001,0),"")
B13: =IF($X13="","",INDEX('Per Line'!$D$2:$D$3001,$X13)&"") | C13: =IF($X13="","",INDEX('Per Line'!$F$2:$F$3001,$X13)) | D13: =IF($X13="","",INDEX('Per Line'!$G$2:$G$3001,$X13)&"") | E13: =IF($X13="","",INDEX('Per Line'!$I$2:$I$3001,$X13)&"") | F13: =IF($X13="","",INDEX('Per Line'!$J$2:$J$3001,$X13)&"") | G13: =IF($X13="","",INDEX('Per Line'!$K$2:$K$3001,$X13)&"") | H13: =IF($X13="","",INDEX('Per Line'!$M$2:$M$3001,$X13)) | I13: =IF($X13="","",H13*V13/100) | J13: =IF($X13="","",INDEX('Per Line'!$W$2:$W$3001,$X13)&"") | K13: =IF($X13="","",INDEX('Per Line'!$AD$2:$AD$3001,$X13)) | L13: =IF($X13="","",IF(AND(ISNUMBER(K13),K13>0),V13>K13,FALSE)) | M13: =IF($X13="","",SUMIFS('Per Line'!$V$2:$V$3001,'Per Line'!$D$2:$D$3001,$B13,'Per Line'!$AN$2:$AN$3001,1)) | N13: =IF($X13="","",Settings!$C$7) | O13: =IF($X13="","",SUMIFS('Per Line'!$V$2:$V$3001,'Per Line'!$D$2:$D$3001,$B13,'Per Line'!$AM$2:$AM$3001,0,'Per Line'!$AN$2:$AN$3001,0)) | P13: =IF($X13="","",O13*N13) | Q13: =IF($X13="","",Settings!$C$6) | R13: =IF($X13="","",SUMIFS('Per Line'!$V$2:$V$3001,'Per Line'!$D$2:$D$3001,$B13,'Per Line'!$AM$2:$AM$3001,1,'Per Line'!$AN$2:$AN$3001,0)) | S13: =IF($X13="","",R13*Q13) | T13: =IF($X13="","",S13+P13) | U13: =IF($X13="","",V13-T13) | V13: =IF($X13="","",O13+R13+M13) | W13: =IF($X13="","",V13-T13-I13) | X13: =IF(ROWS($X$2:$X13)<=MAX('Per Line'!$AL$2:$AL$3001),MATCH(ROWS($X$2:$X13),'Per Line'!$AL$2:$AL$3001,0),"")
... B801: =IF($X801="","",INDEX('Per Line'!$D$2:$D$3001,$X801)&"") | C801: =IF($X801="","",INDEX('Per Line'!$F$2:$F$3001,$X801)) | D801: =IF($X801="","",INDEX('Per Line'!$G$2:$G$3001,$X801)&"") | E801: =IF($X801="","",INDEX('Per Line'!$I$2:$I$3001,$X801)&"") | F801: =IF($X801="","",INDEX('Per Line'!$J$2:$J$3001,$X801)&"") | G801: =IF($X801="","",INDEX('Per Line'!$K$2:$K$3001,$X801)&"") | H801: =IF($X801="","",INDEX('Per Line'!$M$2:$M$3001,$X801)) | I801: =IF($X801="","",H801*V801/100) | J801: =IF($X801="","",INDEX('Per Line'!$W$2:$W$3001,$X801)&"") | K801: =IF($X801="","",INDEX('Per Line'!$AD$2:$AD$3001,$X801)) | L801: =IF($X801="","",IF(AND(ISNUMBER(K801),K801>0),V801>K801,FALSE)) | M801: =IF($X801="","",SUMIFS('Per Line'!$V$2:$V$3001,'Per Line'!$D$2:$D$3001,$B801,'Per Line'!$AN$2:$AN$3001,1)) | N801: =IF($X801="","",Settings!$C$7) | O801: =IF($X801="","",SUMIFS('Per Line'!$V$2:$V$3001,'Per Line'!$D$2:$D$3001,$B801,'Per Line'!$AM$2:$AM$3001,0,'Per Line'!$AN$2:$AN$3001,0)) | P801: =IF($X801="","",O801*N801) | Q801: =IF($X801="","",Settings!$C$6) | R801: =IF($X801="","",SUMIFS('Per Line'!$V$2:$V$3001,'Per Line'!$D$2:$D$3001,$B801,'Per Line'!$AM$2:$AM$3001,1,'Per Line'!$AN$2:$AN$3001,0)) | S801: =IF($X801="","",R801*Q801) | T801: =IF($X801="","",S801+P801) | U801: =IF($X801="","",V801-T801) | V801: =IF($X801="","",O801+R801+M801) | W801: =IF($X801="","",V801-T801-I801) | X801: =IF(ROWS($X$2:$X801)<=MAX('Per Line'!$AL$2:$AL$3001),MATCH(ROWS($X$2:$X801),'Per Line'!$AL$2:$AL$3001,0),"")
