Workbook

Sheet How To Use
A1: Claims Template - CINEMA SYNDICATE (Chronic)
A3: Monthly steps
A4: 1. Open the 'Per Line' tab. Delete the old data in the BLUE columns only (row 2 down). Never delete the green or grey columns.
A5: 2. Paste the new month's data as VALUES starting at A2, into the blue columns: A-O, Q-Z, AE-AL (same order as the system export).
A6: 3. Green columns (P, AA, AB, AC, AD) and the grey helper columns (AM-AQ) calculate automatically - do not paste over them.
A7: 4. 'Per Invoice' fills itself from 'Per Line' (one row per Order #, split into IMP / Local). No pivot table, no refresh.
A8: 5. The ONLY manual column in 'Per Invoice' is column A 'Invoice' (blue): type it yourself. Everything else is formula.
A9: 6. Open 'Settings' and check STATUS says OK (Per Line totals = Per Invoice totals).
A11: Colour legend
A12: Blue header = typed/pasted by you (raw data, and 'Invoice' in Per Invoice). Green header = formula (do not paste over). Grey header = helper formula (do not touch). Yellow cell (Settings) = editable rate.
A14: Calculation rules (taken from the September 2026 sheet)
A15: Co val = Order Co Payment x Total / 100. Discount = Total x Rebates / 100. Subtotal = Total - Discount. Net = Subtotal - Co val. (Total = 'Product Total')
... A21: Max Limit rule (as in the old sheet): if an invoice's Grand Total is above its Max Limit, Co val = Co Payment x Max Limit / 100 + (Grand Total - Max Limit). Per Line keeps the plain Co val, so 'Settings' shows the difference as 'Max Limit adjustment'.

Sheet Settings
B1: Company settings & checks
B3: Insurance Company | C3: CINEMA SYNDICATE | D3: Informational only
B4: Corporate | C4: Cinema professions syndicate | D4: Informational only
B5: Sheet type | C5: Chronic | D5: Informational only
B6: Local products rebate % | C6: 0.12 | D6: Source: Sep sheet (Rebates = 12 on Local lines, 0 on Special Rebates = Yes).
B7: Imported (IMP) products rebate % | C7: 0.03 | D7: Source: Sep sheet (Rebates = 3 on non-local lines).
B9: Month totals / reconciliation
B10: Lines loaded | C10: =COUNTA('Per Line'!$D$2:$D$1001)
B11: Invoices (unique Order #) | C11: =MAX('Per Line'!$AN$2:$AN$1001)
B12: Invoices shown in Per Invoice | C12: =SUMPRODUCT(--('Per Invoice'!$B$2:$B$301<>""))
B13: Grand Total - Per Line (Product Total) | C13: =SUM('Per Line'!$X$2:$X$1001)
B14: Grand Total - Per Invoice | C14: =SUM('Per Invoice'!$W$2:$W$301)
B15: Discount - Per Line | C15: =SUM('Per Line'!$AB$2:$AB$1001)
B16: Discount - Per Invoice | C16: =SUM('Per Invoice'!$U$2:$U$301)
B17: Co val - Per Line | C17: =SUM('Per Line'!$P$2:$P$1001)
B18: Co val - Per Invoice | C18: =SUM('Per Invoice'!$J$2:$J$301)
B19: Net - Per Line | C19: =SUM('Per Line'!$AD$2:$AD$1001)
B20: Net - Per Invoice | C20: =SUM('Per Invoice'!$X$2:$X$301)
B21: Max Limit adjustment (Co val, Per Invoice only) | C21: =SUM('Per Invoice'!$Z$2:$Z$301) | D21: Invoices whose Grand Total is above the Max Limit: Co val = Co% x Max Limit / 100 + (Grand Total - Max Limit). This difference exists only in Per Invoice, as in the old sheet.
B23: STATUS | C23: =IF(C10=0,"No data loaded",IF(COUNTA('Per Line'!$D:$D)-1>1000,"TOO MANY LINES - extend template",IF(C11>300,"TOO MANY INVOICES - extend template",IF(AND(ROUND(C13-C14,2)=0,ROUND(C15-C16,2)=0,ROUND(C17+C21-C18,2)=0,ROUND(C19-C21-C20,2)=0,C11=C12),"OK","CHECK - Per Line and Per Invoice do not match")))) | D23: Must say OK after you paste the month data.

Sheet Per Line
A1: Ticket # | B1: Stage | C1: Approval Ref | D1: Order # | E1: Channel | F1: Create At | G1: Insurance Company | H1: Country Portal ID | I1: Corporate | J1: Card | K1: Name | L1: Status | M1: Local Rebates | N1: Imported Rebates | O1: Order Co Payment | P1: Co val | Q1: By Patient | R1: heisenberg id | S1: Product Name | T1: Local | U1: Unit | V1: Quantity | W1: Unit Price | X1: Product Total | Y1: ERX ID | Z1: Special Rebates? | AA1: Rebates | AB1: Discount | AC1: Subtotal | AD1: Net | AE1: Approval Type | AF1: Max Limit | AG1: Exceeding Limit | AH1: Amount collected from customer | AI1: By Patient (Delivered) | AJ1: Dispense Number | AK1: Dispense Date | AL1: Has OTP? | AM1: Order 1st Row (helper) | AN1: Invoice # (helper) | AO1: Is Local (helper) | AP1: Is Special (helper) | AQ1: Sort Key (helper)
P2: =IF($D2="","",O2*X2/100) | AA2: =IF($D2="","",IF($AP2=1,0,IF($AO2=1,Settings!$C$6,Settings!$C$7))*100) | AB2: =IF($D2="","",X2*AA2/100) | AC2: =IF($D2="","",X2-AB2) | AD2: =IF($D2="","",AC2-P2) | AM2: =IF($D2="","",IF(COUNTIF($D$2:$D2,$D2)=1,1,0)) | AN2: =IF($AM2=1,SUMPRODUCT(--($AQ$2:$AQ$1001<$AQ2))+1,"") | AO2: =IF($D2="","",IF(OR($T2=TRUE(),$T2="TRUE"),1,0)) | AP2: =IF($D2="","",IF($Z2="Yes",1,0)) | AQ2: =IF($AM2=1,IFERROR(IF(VALUE($D2)<100000000,VALUE($D2),1000000000),IFERROR(IF(VALUE(MID($D2,2,20))<100000000,VALUE(MID($D2,2,20)),1000000000),1000000000))+ROW()/100000,"")
P3: =IF($D3="","",O3*X3/100) | AA3: =IF($D3="","",IF($AP3=1,0,IF($AO3=1,Settings!$C$6,Settings!$C$7))*100) | AB3: =IF($D3="","",X3*AA3/100) | AC3: =IF($D3="","",X3-AB3) | AD3: =IF($D3="","",AC3-P3) | AM3: =IF($D3="","",IF(COUNTIF($D$2:$D3,$D3)=1,1,0)) | AN3: =IF($AM3=1,SUMPRODUCT(--($AQ$2:$AQ$1001<$AQ3))+1,"") | AO3: =IF($D3="","",IF(OR($T3=TRUE(),$T3="TRUE"),1,0)) | AP3: =IF($D3="","",IF($Z3="Yes",1,0)) | AQ3: =IF($AM3=1,IFERROR(IF(VALUE($D3)<100000000,VALUE($D3),1000000000),IFERROR(IF(VALUE(MID($D3,2,20))<100000000,VALUE(MID($D3,2,20)),1000000000),1000000000))+ROW()/100000,"")
P4: =IF($D4="","",O4*X4/100) | AA4: =IF($D4="","",IF($AP4=1,0,IF($AO4=1,Settings!$C$6,Settings!$C$7))*100) | AB4: =IF($D4="","",X4*AA4/100) | AC4: =IF($D4="","",X4-AB4) | AD4: =IF($D4="","",AC4-P4) | AM4: =IF($D4="","",IF(COUNTIF($D$2:$D4,$D4)=1,1,0)) | AN4: =IF($AM4=1,SUMPRODUCT(--($AQ$2:$AQ$1001<$AQ4))+1,"") | AO4: =IF($D4="","",IF(OR($T4=TRUE(),$T4="TRUE"),1,0)) | AP4: =IF($D4="","",IF($Z4="Yes",1,0)) | AQ4: =IF($AM4=1,IFERROR(IF(VALUE($D4)<100000000,VALUE($D4),1000000000),IFERROR(IF(VALUE(MID($D4,2,20))<100000000,VALUE(MID($D4,2,20)),1000000000),1000000000))+ROW()/100000,"")
P5: =IF($D5="","",O5*X5/100) | AA5: =IF($D5="","",IF($AP5=1,0,IF($AO5=1,Settings!$C$6,Settings!$C$7))*100) | AB5: =IF($D5="","",X5*AA5/100) | AC5: =IF($D5="","",X5-AB5) | AD5: =IF($D5="","",AC5-P5) | AM5: =IF($D5="","",IF(COUNTIF($D$2:$D5,$D5)=1,1,0)) | AN5: =IF($AM5=1,SUMPRODUCT(--($AQ$2:$AQ$1001<$AQ5))+1,"") | AO5: =IF($D5="","",IF(OR($T5=TRUE(),$T5="TRUE"),1,0)) | AP5: =IF($D5="","",IF($Z5="Yes",1,0)) | AQ5: =IF($AM5=1,IFERROR(IF(VALUE($D5)<100000000,VALUE($D5),1000000000),IFERROR(IF(VALUE(MID($D5,2,20))<100000000,VALUE(MID($D5,2,20)),1000000000),1000000000))+ROW()/100000,"")
P6: =IF($D6="","",O6*X6/100) | AA6: =IF($D6="","",IF($AP6=1,0,IF($AO6=1,Settings!$C$6,Settings!$C$7))*100) | AB6: =IF($D6="","",X6*AA6/100) | AC6: =IF($D6="","",X6-AB6) | AD6: =IF($D6="","",AC6-P6) | AM6: =IF($D6="","",IF(COUNTIF($D$2:$D6,$D6)=1,1,0)) | AN6: =IF($AM6=1,SUMPRODUCT(--($AQ$2:$AQ$1001<$AQ6))+1,"") | AO6: =IF($D6="","",IF(OR($T6=TRUE(),$T6="TRUE"),1,0)) | AP6: =IF($D6="","",IF($Z6="Yes",1,0)) | AQ6: =IF($AM6=1,IFERROR(IF(VALUE($D6)<100000000,VALUE($D6),1000000000),IFERROR(IF(VALUE(MID($D6,2,20))<100000000,VALUE(MID($D6,2,20)),1000000000),1000000000))+ROW()/100000,"")
P7: =IF($D7="","",O7*X7/100) | AA7: =IF($D7="","",IF($AP7=1,0,IF($AO7=1,Settings!$C$6,Settings!$C$7))*100) | AB7: =IF($D7="","",X7*AA7/100) | AC7: =IF($D7="","",X7-AB7) | AD7: =IF($D7="","",AC7-P7) | AM7: =IF($D7="","",IF(COUNTIF($D$2:$D7,$D7)=1,1,0)) | AN7: =IF($AM7=1,SUMPRODUCT(--($AQ$2:$AQ$1001<$AQ7))+1,"") | AO7: =IF($D7="","",IF(OR($T7=TRUE(),$T7="TRUE"),1,0)) | AP7: =IF($D7="","",IF($Z7="Yes",1,0)) | AQ7: =IF($AM7=1,IFERROR(IF(VALUE($D7)<100000000,VALUE($D7),1000000000),IFERROR(IF(VALUE(MID($D7,2,20))<100000000,VALUE(MID($D7,2,20)),1000000000),1000000000))+ROW()/100000,"")
P8: =IF($D8="","",O8*X8/100) | AA8: =IF($D8="","",IF($AP8=1,0,IF($AO8=1,Settings!$C$6,Settings!$C$7))*100) | AB8: =IF($D8="","",X8*AA8/100) | AC8: =IF($D8="","",X8-AB8) | AD8: =IF($D8="","",AC8-P8) | AM8: =IF($D8="","",IF(COUNTIF($D$2:$D8,$D8)=1,1,0)) | AN8: =IF($AM8=1,SUMPRODUCT(--($AQ$2:$AQ$1001<$AQ8))+1,"") | AO8: =IF($D8="","",IF(OR($T8=TRUE(),$T8="TRUE"),1,0)) | AP8: =IF($D8="","",IF($Z8="Yes",1,0)) | AQ8: =IF($AM8=1,IFERROR(IF(VALUE($D8)<100000000,VALUE($D8),1000000000),IFERROR(IF(VALUE(MID($D8,2,20))<100000000,VALUE(MID($D8,2,20)),1000000000),1000000000))+ROW()/100000,"")
P9: =IF($D9="","",O9*X9/100) | AA9: =IF($D9="","",IF($AP9=1,0,IF($AO9=1,Settings!$C$6,Settings!$C$7))*100) | AB9: =IF($D9="","",X9*AA9/100) | AC9: =IF($D9="","",X9-AB9) | AD9: =IF($D9="","",AC9-P9) | AM9: =IF($D9="","",IF(COUNTIF($D$2:$D9,$D9)=1,1,0)) | AN9: =IF($AM9=1,SUMPRODUCT(--($AQ$2:$AQ$1001<$AQ9))+1,"") | AO9: =IF($D9="","",IF(OR($T9=TRUE(),$T9="TRUE"),1,0)) | AP9: =IF($D9="","",IF($Z9="Yes",1,0)) | AQ9: =IF($AM9=1,IFERROR(IF(VALUE($D9)<100000000,VALUE($D9),1000000000),IFERROR(IF(VALUE(MID($D9,2,20))<100000000,VALUE(MID($D9,2,20)),1000000000),1000000000))+ROW()/100000,"")
P10: =IF($D10="","",O10*X10/100) | AA10: =IF($D10="","",IF($AP10=1,0,IF($AO10=1,Settings!$C$6,Settings!$C$7))*100) | AB10: =IF($D10="","",X10*AA10/100) | AC10: =IF($D10="","",X10-AB10) | AD10: =IF($D10="","",AC10-P10) | AM10: =IF($D10="","",IF(COUNTIF($D$2:$D10,$D10)=1,1,0)) | AN10: =IF($AM10=1,SUMPRODUCT(--($AQ$2:$AQ$1001<$AQ10))+1,"") | AO10: =IF($D10="","",IF(OR($T10=TRUE(),$T10="TRUE"),1,0)) | AP10: =IF($D10="","",IF($Z10="Yes",1,0)) | AQ10: =IF($AM10=1,IFERROR(IF(VALUE($D10)<100000000,VALUE($D10),1000000000),IFERROR(IF(VALUE(MID($D10,2,20))<100000000,VALUE(MID($D10,2,20)),1000000000),1000000000))+ROW()/100000,"")
P11: =IF($D11="","",O11*X11/100) | AA11: =IF($D11="","",IF($AP11=1,0,IF($AO11=1,Settings!$C$6,Settings!$C$7))*100) | AB11: =IF($D11="","",X11*AA11/100) | AC11: =IF($D11="","",X11-AB11) | AD11: =IF($D11="","",AC11-P11) | AM11: =IF($D11="","",IF(COUNTIF($D$2:$D11,$D11)=1,1,0)) | AN11: =IF($AM11=1,SUMPRODUCT(--($AQ$2:$AQ$1001<$AQ11))+1,"") | AO11: =IF($D11="","",IF(OR($T11=TRUE(),$T11="TRUE"),1,0)) | AP11: =IF($D11="","",IF($Z11="Yes",1,0)) | AQ11: =IF($AM11=1,IFERROR(IF(VALUE($D11)<100000000,VALUE($D11),1000000000),IFERROR(IF(VALUE(MID($D11,2,20))<100000000,VALUE(MID($D11,2,20)),1000000000),1000000000))+ROW()/100000,"")
P12: =IF($D12="","",O12*X12/100) | AA12: =IF($D12="","",IF($AP12=1,0,IF($AO12=1,Settings!$C$6,Settings!$C$7))*100) | AB12: =IF($D12="","",X12*AA12/100) | AC12: =IF($D12="","",X12-AB12) | AD12: =IF($D12="","",AC12-P12) | AM12: =IF($D12="","",IF(COUNTIF($D$2:$D12,$D12)=1,1,0)) | AN12: =IF($AM12=1,SUMPRODUCT(--($AQ$2:$AQ$1001<$AQ12))+1,"") | AO12: =IF($D12="","",IF(OR($T12=TRUE(),$T12="TRUE"),1,0)) | AP12: =IF($D12="","",IF($Z12="Yes",1,0)) | AQ12: =IF($AM12=1,IFERROR(IF(VALUE($D12)<100000000,VALUE($D12),1000000000),IFERROR(IF(VALUE(MID($D12,2,20))<100000000,VALUE(MID($D12,2,20)),1000000000),1000000000))+ROW()/100000,"")
P13: =IF($D13="","",O13*X13/100) | AA13: =IF($D13="","",IF($AP13=1,0,IF($AO13=1,Settings!$C$6,Settings!$C$7))*100) | AB13: =IF($D13="","",X13*AA13/100) | AC13: =IF($D13="","",X13-AB13) | AD13: =IF($D13="","",AC13-P13) | AM13: =IF($D13="","",IF(COUNTIF($D$2:$D13,$D13)=1,1,0)) | AN13: =IF($AM13=1,SUMPRODUCT(--($AQ$2:$AQ$1001<$AQ13))+1,"") | AO13: =IF($D13="","",IF(OR($T13=TRUE(),$T13="TRUE"),1,0)) | AP13: =IF($D13="","",IF($Z13="Yes",1,0)) | AQ13: =IF($AM13=1,IFERROR(IF(VALUE($D13)<100000000,VALUE($D13),1000000000),IFERROR(IF(VALUE(MID($D13,2,20))<100000000,VALUE(MID($D13,2,20)),1000000000),1000000000))+ROW()/100000,"")
... P1001: =IF($D1001="","",O1001*X1001/100) | AA1001: =IF($D1001="","",IF($AP1001=1,0,IF($AO1001=1,Settings!$C$6,Settings!$C$7))*100) | AB1001: =IF($D1001="","",X1001*AA1001/100) | AC1001: =IF($D1001="","",X1001-AB1001) | AD1001: =IF($D1001="","",AC1001-P1001) | AM1001: =IF($D1001="","",IF(COUNTIF($D$2:$D1001,$D1001)=1,1,0)) | AN1001: =IF($AM1001=1,SUMPRODUCT(--($AQ$2:$AQ$1001<$AQ1001))+1,"") | AO1001: =IF($D1001="","",IF(OR($T1001=TRUE(),$T1001="TRUE"),1,0)) | AP1001: =IF($D1001="","",IF($Z1001="Yes",1,0)) | AQ1001: =IF($AM1001=1,IFERROR(IF(VALUE($D1001)<100000000,VALUE($D1001),1000000000),IFERROR(IF(VALUE(MID($D1001,2,20))<100000000,VALUE(MID($D1001,2,20)),1000000000),1000000000))+ROW()/100000,"")

Sheet Per Invoice
A1: Invoice | B1: Order # | C1: Approval Ref | D1: Create At | E1: Insurance Company | F1: Corporate | G1: Card | H1: Name | I1: Order Co Payment | J1: Co val | K1: ERX ID | L1: Max Limit | M1: Exceeding Limit | N1: Special Rebates | O1: IMP% | P1: IMP | Q1: IMP VAL | R1: LOCAL % | S1: LOCAL | T1: LOCAL VAL | U1: TOTAL VAL | V1: SUBTOTAL | W1: Grand Total | X1: NET | Y1: Src Row (helper) | Z1: Limit Adj (helper)
B2: =IF($Y2="","",INDEX('Per Line'!$D$2:$D$1001,$Y2)&"") | C2: =IF($Y2="","",INDEX('Per Line'!$C$2:$C$1001,$Y2)&"") | D2: =IF($Y2="","",INDEX('Per Line'!$F$2:$F$1001,$Y2)) | E2: =IF($Y2="","",INDEX('Per Line'!$G$2:$G$1001,$Y2)&"") | F2: =IF($Y2="","",INDEX('Per Line'!$I$2:$I$1001,$Y2)&"") | G2: =IF($Y2="","",INDEX('Per Line'!$J$2:$J$1001,$Y2)&"") | H2: =IF($Y2="","",INDEX('Per Line'!$K$2:$K$1001,$Y2)&"") | I2: =IF($Y2="","",INDEX('Per Line'!$O$2:$O$1001,$Y2)) | J2: =IF($Y2="","",IF(AND(ISNUMBER(L2),L2>0,W2>L2),I2*L2/100+(W2-L2),I2*W2/100)) | K2: =IF($Y2="","",INDEX('Per Line'!$Y$2:$Y$1001,$Y2)&"") | L2: =IF($Y2="","",INDEX('Per Line'!$AF$2:$AF$1001,$Y2)) | M2: =IF($Y2="","",IF(AND(ISNUMBER(L2),L2>0),W2>L2,FALSE)) | N2: =IF($Y2="","",SUMIFS('Per Line'!$X$2:$X$1001,'Per Line'!$D$2:$D$1001,$B2,'Per Line'!$AP$2:$AP$1001,1)) | O2: =IF($Y2="","",Settings!$C$7) | P2: =IF($Y2="","",SUMIFS('Per Line'!$X$2:$X$1001,'Per Line'!$D$2:$D$1001,$B2,'Per Line'!$AO$2:$AO$1001,0,'Per Line'!$AP$2:$AP$1001,0)) | Q2: =IF($Y2="","",P2*O2) | R2: =IF($Y2="","",Settings!$C$6) | S2: =IF($Y2="","",SUMIFS('Per Line'!$X$2:$X$1001,'Per Line'!$D$2:$D$1001,$B2,'Per Line'!$AO$2:$AO$1001,1,'Per Line'!$AP$2:$AP$1001,0)) | T2: =IF($Y2="","",S2*R2) | U2: =IF($Y2="","",T2+Q2) | V2: =IF($Y2="","",W2-U2) | W2: =IF($Y2="","",P2+S2+N2) | X2: =IF($Y2="","",W2-U2-J2) | Y2: =IF(ROWS($Y$2:$Y2)<=MAX('Per Line'!$AN$2:$AN$1001),MATCH(ROWS($Y$2:$Y2),'Per Line'!$AN$2:$AN$1001,0),"") | Z2: =IF($Y2="","",J2-I2*W2/100)
B3: =IF($Y3="","",INDEX('Per Line'!$D$2:$D$1001,$Y3)&"") | C3: =IF($Y3="","",INDEX('Per Line'!$C$2:$C$1001,$Y3)&"") | D3: =IF($Y3="","",INDEX('Per Line'!$F$2:$F$1001,$Y3)) | E3: =IF($Y3="","",INDEX('Per Line'!$G$2:$G$1001,$Y3)&"") | F3: =IF($Y3="","",INDEX('Per Line'!$I$2:$I$1001,$Y3)&"") | G3: =IF($Y3="","",INDEX('Per Line'!$J$2:$J$1001,$Y3)&"") | H3: =IF($Y3="","",INDEX('Per Line'!$K$2:$K$1001,$Y3)&"") | I3: =IF($Y3="","",INDEX('Per Line'!$O$2:$O$1001,$Y3)) | J3: =IF($Y3="","",IF(AND(ISNUMBER(L3),L3>0,W3>L3),I3*L3/100+(W3-L3),I3*W3/100)) | K3: =IF($Y3="","",INDEX('Per Line'!$Y$2:$Y$1001,$Y3)&"") | L3: =IF($Y3="","",INDEX('Per Line'!$AF$2:$AF$1001,$Y3)) | M3: =IF($Y3="","",IF(AND(ISNUMBER(L3),L3>0),W3>L3,FALSE)) | N3: =IF($Y3="","",SUMIFS('Per Line'!$X$2:$X$1001,'Per Line'!$D$2:$D$1001,$B3,'Per Line'!$AP$2:$AP$1001,1)) | O3: =IF($Y3="","",Settings!$C$7) | P3: =IF($Y3="","",SUMIFS('Per Line'!$X$2:$X$1001,'Per Line'!$D$2:$D$1001,$B3,'Per Line'!$AO$2:$AO$1001,0,'Per Line'!$AP$2:$AP$1001,0)) | Q3: =IF($Y3="","",P3*O3) | R3: =IF($Y3="","",Settings!$C$6) | S3: =IF($Y3="","",SUMIFS('Per Line'!$X$2:$X$1001,'Per Line'!$D$2:$D$1001,$B3,'Per Line'!$AO$2:$AO$1001,1,'Per Line'!$AP$2:$AP$1001,0)) | T3: =IF($Y3="","",S3*R3) | U3: =IF($Y3="","",T3+Q3) | V3: =IF($Y3="","",W3-U3) | W3: =IF($Y3="","",P3+S3+N3) | X3: =IF($Y3="","",W3-U3-J3) | Y3: =IF(ROWS($Y$2:$Y3)<=MAX('Per Line'!$AN$2:$AN$1001),MATCH(ROWS($Y$2:$Y3),'Per Line'!$AN$2:$AN$1001,0),"") | Z3: =IF($Y3="","",J3-I3*W3/100)
B4: =IF($Y4="","",INDEX('Per Line'!$D$2:$D$1001,$Y4)&"") | C4: =IF($Y4="","",INDEX('Per Line'!$C$2:$C$1001,$Y4)&"") | D4: =IF($Y4="","",INDEX('Per Line'!$F$2:$F$1001,$Y4)) | E4: =IF($Y4="","",INDEX('Per Line'!$G$2:$G$1001,$Y4)&"") | F4: =IF($Y4="","",INDEX('Per Line'!$I$2:$I$1001,$Y4)&"") | G4: =IF($Y4="","",INDEX('Per Line'!$J$2:$J$1001,$Y4)&"") | H4: =IF($Y4="","",INDEX('Per Line'!$K$2:$K$1001,$Y4)&"") | I4: =IF($Y4="","",INDEX('Per Line'!$O$2:$O$1001,$Y4)) | J4: =IF($Y4="","",IF(AND(ISNUMBER(L4),L4>0,W4>L4),I4*L4/100+(W4-L4),I4*W4/100)) | K4: =IF($Y4="","",INDEX('Per Line'!$Y$2:$Y$1001,$Y4)&"") | L4: =IF($Y4="","",INDEX('Per Line'!$AF$2:$AF$1001,$Y4)) | M4: =IF($Y4="","",IF(AND(ISNUMBER(L4),L4>0),W4>L4,FALSE)) | N4: =IF($Y4="","",SUMIFS('Per Line'!$X$2:$X$1001,'Per Line'!$D$2:$D$1001,$B4,'Per Line'!$AP$2:$AP$1001,1)) | O4: =IF($Y4="","",Settings!$C$7) | P4: =IF($Y4="","",SUMIFS('Per Line'!$X$2:$X$1001,'Per Line'!$D$2:$D$1001,$B4,'Per Line'!$AO$2:$AO$1001,0,'Per Line'!$AP$2:$AP$1001,0)) | Q4: =IF($Y4="","",P4*O4) | R4: =IF($Y4="","",Settings!$C$6) | S4: =IF($Y4="","",SUMIFS('Per Line'!$X$2:$X$1001,'Per Line'!$D$2:$D$1001,$B4,'Per Line'!$AO$2:$AO$1001,1,'Per Line'!$AP$2:$AP$1001,0)) | T4: =IF($Y4="","",S4*R4) | U4: =IF($Y4="","",T4+Q4) | V4: =IF($Y4="","",W4-U4) | W4: =IF($Y4="","",P4+S4+N4) | X4: =IF($Y4="","",W4-U4-J4) | Y4: =IF(ROWS($Y$2:$Y4)<=MAX('Per Line'!$AN$2:$AN$1001),MATCH(ROWS($Y$2:$Y4),'Per Line'!$AN$2:$AN$1001,0),"") | Z4: =IF($Y4="","",J4-I4*W4/100)
B5: =IF($Y5="","",INDEX('Per Line'!$D$2:$D$1001,$Y5)&"") | C5: =IF($Y5="","",INDEX('Per Line'!$C$2:$C$1001,$Y5)&"") | D5: =IF($Y5="","",INDEX('Per Line'!$F$2:$F$1001,$Y5)) | E5: =IF($Y5="","",INDEX('Per Line'!$G$2:$G$1001,$Y5)&"") | F5: =IF($Y5="","",INDEX('Per Line'!$I$2:$I$1001,$Y5)&"") | G5: =IF($Y5="","",INDEX('Per Line'!$J$2:$J$1001,$Y5)&"") | H5: =IF($Y5="","",INDEX('Per Line'!$K$2:$K$1001,$Y5)&"") | I5: =IF($Y5="","",INDEX('Per Line'!$O$2:$O$1001,$Y5)) | J5: =IF($Y5="","",IF(AND(ISNUMBER(L5),L5>0,W5>L5),I5*L5/100+(W5-L5),I5*W5/100)) | K5: =IF($Y5="","",INDEX('Per Line'!$Y$2:$Y$1001,$Y5)&"") | L5: =IF($Y5="","",INDEX('Per Line'!$AF$2:$AF$1001,$Y5)) | M5: =IF($Y5="","",IF(AND(ISNUMBER(L5),L5>0),W5>L5,FALSE)) | N5: =IF($Y5="","",SUMIFS('Per Line'!$X$2:$X$1001,'Per Line'!$D$2:$D$1001,$B5,'Per Line'!$AP$2:$AP$1001,1)) | O5: =IF($Y5="","",Settings!$C$7) | P5: =IF($Y5="","",SUMIFS('Per Line'!$X$2:$X$1001,'Per Line'!$D$2:$D$1001,$B5,'Per Line'!$AO$2:$AO$1001,0,'Per Line'!$AP$2:$AP$1001,0)) | Q5: =IF($Y5="","",P5*O5) | R5: =IF($Y5="","",Settings!$C$6) | S5: =IF($Y5="","",SUMIFS('Per Line'!$X$2:$X$1001,'Per Line'!$D$2:$D$1001,$B5,'Per Line'!$AO$2:$AO$1001,1,'Per Line'!$AP$2:$AP$1001,0)) | T5: =IF($Y5="","",S5*R5) | U5: =IF($Y5="","",T5+Q5) | V5: =IF($Y5="","",W5-U5) | W5: =IF($Y5="","",P5+S5+N5) | X5: =IF($Y5="","",W5-U5-J5) | Y5: =IF(ROWS($Y$2:$Y5)<=MAX('Per Line'!$AN$2:$AN$1001),MATCH(ROWS($Y$2:$Y5),'Per Line'!$AN$2:$AN$1001,0),"") | Z5: =IF($Y5="","",J5-I5*W5/100)
B6: =IF($Y6="","",INDEX('Per Line'!$D$2:$D$1001,$Y6)&"") | C6: =IF($Y6="","",INDEX('Per Line'!$C$2:$C$1001,$Y6)&"") | D6: =IF($Y6="","",INDEX('Per Line'!$F$2:$F$1001,$Y6)) | E6: =IF($Y6="","",INDEX('Per Line'!$G$2:$G$1001,$Y6)&"") | F6: =IF($Y6="","",INDEX('Per Line'!$I$2:$I$1001,$Y6)&"") | G6: =IF($Y6="","",INDEX('Per Line'!$J$2:$J$1001,$Y6)&"") | H6: =IF($Y6="","",INDEX('Per Line'!$K$2:$K$1001,$Y6)&"") | I6: =IF($Y6="","",INDEX('Per Line'!$O$2:$O$1001,$Y6)) | J6: =IF($Y6="","",IF(AND(ISNUMBER(L6),L6>0,W6>L6),I6*L6/100+(W6-L6),I6*W6/100)) | K6: =IF($Y6="","",INDEX('Per Line'!$Y$2:$Y$1001,$Y6)&"") | L6: =IF($Y6="","",INDEX('Per Line'!$AF$2:$AF$1001,$Y6)) | M6: =IF($Y6="","",IF(AND(ISNUMBER(L6),L6>0),W6>L6,FALSE)) | N6: =IF($Y6="","",SUMIFS('Per Line'!$X$2:$X$1001,'Per Line'!$D$2:$D$1001,$B6,'Per Line'!$AP$2:$AP$1001,1)) | O6: =IF($Y6="","",Settings!$C$7) | P6: =IF($Y6="","",SUMIFS('Per Line'!$X$2:$X$1001,'Per Line'!$D$2:$D$1001,$B6,'Per Line'!$AO$2:$AO$1001,0,'Per Line'!$AP$2:$AP$1001,0)) | Q6: =IF($Y6="","",P6*O6) | R6: =IF($Y6="","",Settings!$C$6) | S6: =IF($Y6="","",SUMIFS('Per Line'!$X$2:$X$1001,'Per Line'!$D$2:$D$1001,$B6,'Per Line'!$AO$2:$AO$1001,1,'Per Line'!$AP$2:$AP$1001,0)) | T6: =IF($Y6="","",S6*R6) | U6: =IF($Y6="","",T6+Q6) | V6: =IF($Y6="","",W6-U6) | W6: =IF($Y6="","",P6+S6+N6) | X6: =IF($Y6="","",W6-U6-J6) | Y6: =IF(ROWS($Y$2:$Y6)<=MAX('Per Line'!$AN$2:$AN$1001),MATCH(ROWS($Y$2:$Y6),'Per Line'!$AN$2:$AN$1001,0),"") | Z6: =IF($Y6="","",J6-I6*W6/100)
B7: =IF($Y7="","",INDEX('Per Line'!$D$2:$D$1001,$Y7)&"") | C7: =IF($Y7="","",INDEX('Per Line'!$C$2:$C$1001,$Y7)&"") | D7: =IF($Y7="","",INDEX('Per Line'!$F$2:$F$1001,$Y7)) | E7: =IF($Y7="","",INDEX('Per Line'!$G$2:$G$1001,$Y7)&"") | F7: =IF($Y7="","",INDEX('Per Line'!$I$2:$I$1001,$Y7)&"") | G7: =IF($Y7="","",INDEX('Per Line'!$J$2:$J$1001,$Y7)&"") | H7: =IF($Y7="","",INDEX('Per Line'!$K$2:$K$1001,$Y7)&"") | I7: =IF($Y7="","",INDEX('Per Line'!$O$2:$O$1001,$Y7)) | J7: =IF($Y7="","",IF(AND(ISNUMBER(L7),L7>0,W7>L7),I7*L7/100+(W7-L7),I7*W7/100)) | K7: =IF($Y7="","",INDEX('Per Line'!$Y$2:$Y$1001,$Y7)&"") | L7: =IF($Y7="","",INDEX('Per Line'!$AF$2:$AF$1001,$Y7)) | M7: =IF($Y7="","",IF(AND(ISNUMBER(L7),L7>0),W7>L7,FALSE)) | N7: =IF($Y7="","",SUMIFS('Per Line'!$X$2:$X$1001,'Per Line'!$D$2:$D$1001,$B7,'Per Line'!$AP$2:$AP$1001,1)) | O7: =IF($Y7="","",Settings!$C$7) | P7: =IF($Y7="","",SUMIFS('Per Line'!$X$2:$X$1001,'Per Line'!$D$2:$D$1001,$B7,'Per Line'!$AO$2:$AO$1001,0,'Per Line'!$AP$2:$AP$1001,0)) | Q7: =IF($Y7="","",P7*O7) | R7: =IF($Y7="","",Settings!$C$6) | S7: =IF($Y7="","",SUMIFS('Per Line'!$X$2:$X$1001,'Per Line'!$D$2:$D$1001,$B7,'Per Line'!$AO$2:$AO$1001,1,'Per Line'!$AP$2:$AP$1001,0)) | T7: =IF($Y7="","",S7*R7) | U7: =IF($Y7="","",T7+Q7) | V7: =IF($Y7="","",W7-U7) | W7: =IF($Y7="","",P7+S7+N7) | X7: =IF($Y7="","",W7-U7-J7) | Y7: =IF(ROWS($Y$2:$Y7)<=MAX('Per Line'!$AN$2:$AN$1001),MATCH(ROWS($Y$2:$Y7),'Per Line'!$AN$2:$AN$1001,0),"") | Z7: =IF($Y7="","",J7-I7*W7/100)
B8: =IF($Y8="","",INDEX('Per Line'!$D$2:$D$1001,$Y8)&"") | C8: =IF($Y8="","",INDEX('Per Line'!$C$2:$C$1001,$Y8)&"") | D8: =IF($Y8="","",INDEX('Per Line'!$F$2:$F$1001,$Y8)) | E8: =IF($Y8="","",INDEX('Per Line'!$G$2:$G$1001,$Y8)&"") | F8: =IF($Y8="","",INDEX('Per Line'!$I$2:$I$1001,$Y8)&"") | G8: =IF($Y8="","",INDEX('Per Line'!$J$2:$J$1001,$Y8)&"") | H8: =IF($Y8="","",INDEX('Per Line'!$K$2:$K$1001,$Y8)&"") | I8: =IF($Y8="","",INDEX('Per Line'!$O$2:$O$1001,$Y8)) | J8: =IF($Y8="","",IF(AND(ISNUMBER(L8),L8>0,W8>L8),I8*L8/100+(W8-L8),I8*W8/100)) | K8: =IF($Y8="","",INDEX('Per Line'!$Y$2:$Y$1001,$Y8)&"") | L8: =IF($Y8="","",INDEX('Per Line'!$AF$2:$AF$1001,$Y8)) | M8: =IF($Y8="","",IF(AND(ISNUMBER(L8),L8>0),W8>L8,FALSE)) | N8: =IF($Y8="","",SUMIFS('Per Line'!$X$2:$X$1001,'Per Line'!$D$2:$D$1001,$B8,'Per Line'!$AP$2:$AP$1001,1)) | O8: =IF($Y8="","",Settings!$C$7) | P8: =IF($Y8="","",SUMIFS('Per Line'!$X$2:$X$1001,'Per Line'!$D$2:$D$1001,$B8,'Per Line'!$AO$2:$AO$1001,0,'Per Line'!$AP$2:$AP$1001,0)) | Q8: =IF($Y8="","",P8*O8) | R8: =IF($Y8="","",Settings!$C$6) | S8: =IF($Y8="","",SUMIFS('Per Line'!$X$2:$X$1001,'Per Line'!$D$2:$D$1001,$B8,'Per Line'!$AO$2:$AO$1001,1,'Per Line'!$AP$2:$AP$1001,0)) | T8: =IF($Y8="","",S8*R8) | U8: =IF($Y8="","",T8+Q8) | V8: =IF($Y8="","",W8-U8) | W8: =IF($Y8="","",P8+S8+N8) | X8: =IF($Y8="","",W8-U8-J8) | Y8: =IF(ROWS($Y$2:$Y8)<=MAX('Per Line'!$AN$2:$AN$1001),MATCH(ROWS($Y$2:$Y8),'Per Line'!$AN$2:$AN$1001,0),"") | Z8: =IF($Y8="","",J8-I8*W8/100)
B9: =IF($Y9="","",INDEX('Per Line'!$D$2:$D$1001,$Y9)&"") | C9: =IF($Y9="","",INDEX('Per Line'!$C$2:$C$1001,$Y9)&"") | D9: =IF($Y9="","",INDEX('Per Line'!$F$2:$F$1001,$Y9)) | E9: =IF($Y9="","",INDEX('Per Line'!$G$2:$G$1001,$Y9)&"") | F9: =IF($Y9="","",INDEX('Per Line'!$I$2:$I$1001,$Y9)&"") | G9: =IF($Y9="","",INDEX('Per Line'!$J$2:$J$1001,$Y9)&"") | H9: =IF($Y9="","",INDEX('Per Line'!$K$2:$K$1001,$Y9)&"") | I9: =IF($Y9="","",INDEX('Per Line'!$O$2:$O$1001,$Y9)) | J9: =IF($Y9="","",IF(AND(ISNUMBER(L9),L9>0,W9>L9),I9*L9/100+(W9-L9),I9*W9/100)) | K9: =IF($Y9="","",INDEX('Per Line'!$Y$2:$Y$1001,$Y9)&"") | L9: =IF($Y9="","",INDEX('Per Line'!$AF$2:$AF$1001,$Y9)) | M9: =IF($Y9="","",IF(AND(ISNUMBER(L9),L9>0),W9>L9,FALSE)) | N9: =IF($Y9="","",SUMIFS('Per Line'!$X$2:$X$1001,'Per Line'!$D$2:$D$1001,$B9,'Per Line'!$AP$2:$AP$1001,1)) | O9: =IF($Y9="","",Settings!$C$7) | P9: =IF($Y9="","",SUMIFS('Per Line'!$X$2:$X$1001,'Per Line'!$D$2:$D$1001,$B9,'Per Line'!$AO$2:$AO$1001,0,'Per Line'!$AP$2:$AP$1001,0)) | Q9: =IF($Y9="","",P9*O9) | R9: =IF($Y9="","",Settings!$C$6) | S9: =IF($Y9="","",SUMIFS('Per Line'!$X$2:$X$1001,'Per Line'!$D$2:$D$1001,$B9,'Per Line'!$AO$2:$AO$1001,1,'Per Line'!$AP$2:$AP$1001,0)) | T9: =IF($Y9="","",S9*R9) | U9: =IF($Y9="","",T9+Q9) | V9: =IF($Y9="","",W9-U9) | W9: =IF($Y9="","",P9+S9+N9) | X9: =IF($Y9="","",W9-U9-J9) | Y9: =IF(ROWS($Y$2:$Y9)<=MAX('Per Line'!$AN$2:$AN$1001),MATCH(ROWS($Y$2:$Y9),'Per Line'!$AN$2:$AN$1001,0),"") | Z9: =IF($Y9="","",J9-I9*W9/100)
B10: =IF($Y10="","",INDEX('Per Line'!$D$2:$D$1001,$Y10)&"") | C10: =IF($Y10="","",INDEX('Per Line'!$C$2:$C$1001,$Y10)&"") | D10: =IF($Y10="","",INDEX('Per Line'!$F$2:$F$1001,$Y10)) | E10: =IF($Y10="","",INDEX('Per Line'!$G$2:$G$1001,$Y10)&"") | F10: =IF($Y10="","",INDEX('Per Line'!$I$2:$I$1001,$Y10)&"") | G10: =IF($Y10="","",INDEX('Per Line'!$J$2:$J$1001,$Y10)&"") | H10: =IF($Y10="","",INDEX('Per Line'!$K$2:$K$1001,$Y10)&"") | I10: =IF($Y10="","",INDEX('Per Line'!$O$2:$O$1001,$Y10)) | J10: =IF($Y10="","",IF(AND(ISNUMBER(L10),L10>0,W10>L10),I10*L10/100+(W10-L10),I10*W10/100)) | K10: =IF($Y10="","",INDEX('Per Line'!$Y$2:$Y$1001,$Y10)&"") | L10: =IF($Y10="","",INDEX('Per Line'!$AF$2:$AF$1001,$Y10)) | M10: =IF($Y10="","",IF(AND(ISNUMBER(L10),L10>0),W10>L10,FALSE)) | N10: =IF($Y10="","",SUMIFS('Per Line'!$X$2:$X$1001,'Per Line'!$D$2:$D$1001,$B10,'Per Line'!$AP$2:$AP$1001,1)) | O10: =IF($Y10="","",Settings!$C$7) | P10: =IF($Y10="","",SUMIFS('Per Line'!$X$2:$X$1001,'Per Line'!$D$2:$D$1001,$B10,'Per Line'!$AO$2:$AO$1001,0,'Per Line'!$AP$2:$AP$1001,0)) | Q10: =IF($Y10="","",P10*O10) | R10: =IF($Y10="","",Settings!$C$6) | S10: =IF($Y10="","",SUMIFS('Per Line'!$X$2:$X$1001,'Per Line'!$D$2:$D$1001,$B10,'Per Line'!$AO$2:$AO$1001,1,'Per Line'!$AP$2:$AP$1001,0)) | T10: =IF($Y10="","",S10*R10) | U10: =IF($Y10="","",T10+Q10) | V10: =IF($Y10="","",W10-U10) | W10: =IF($Y10="","",P10+S10+N10) | X10: =IF($Y10="","",W10-U10-J10) | Y10: =IF(ROWS($Y$2:$Y10)<=MAX('Per Line'!$AN$2:$AN$1001),MATCH(ROWS($Y$2:$Y10),'Per Line'!$AN$2:$AN$1001,0),"") | Z10: =IF($Y10="","",J10-I10*W10/100)
B11: =IF($Y11="","",INDEX('Per Line'!$D$2:$D$1001,$Y11)&"") | C11: =IF($Y11="","",INDEX('Per Line'!$C$2:$C$1001,$Y11)&"") | D11: =IF($Y11="","",INDEX('Per Line'!$F$2:$F$1001,$Y11)) | E11: =IF($Y11="","",INDEX('Per Line'!$G$2:$G$1001,$Y11)&"") | F11: =IF($Y11="","",INDEX('Per Line'!$I$2:$I$1001,$Y11)&"") | G11: =IF($Y11="","",INDEX('Per Line'!$J$2:$J$1001,$Y11)&"") | H11: =IF($Y11="","",INDEX('Per Line'!$K$2:$K$1001,$Y11)&"") | I11: =IF($Y11="","",INDEX('Per Line'!$O$2:$O$1001,$Y11)) | J11: =IF($Y11="","",IF(AND(ISNUMBER(L11),L11>0,W11>L11),I11*L11/100+(W11-L11),I11*W11/100)) | K11: =IF($Y11="","",INDEX('Per Line'!$Y$2:$Y$1001,$Y11)&"") | L11: =IF($Y11="","",INDEX('Per Line'!$AF$2:$AF$1001,$Y11)) | M11: =IF($Y11="","",IF(AND(ISNUMBER(L11),L11>0),W11>L11,FALSE)) | N11: =IF($Y11="","",SUMIFS('Per Line'!$X$2:$X$1001,'Per Line'!$D$2:$D$1001,$B11,'Per Line'!$AP$2:$AP$1001,1)) | O11: =IF($Y11="","",Settings!$C$7) | P11: =IF($Y11="","",SUMIFS('Per Line'!$X$2:$X$1001,'Per Line'!$D$2:$D$1001,$B11,'Per Line'!$AO$2:$AO$1001,0,'Per Line'!$AP$2:$AP$1001,0)) | Q11: =IF($Y11="","",P11*O11) | R11: =IF($Y11="","",Settings!$C$6) | S11: =IF($Y11="","",SUMIFS('Per Line'!$X$2:$X$1001,'Per Line'!$D$2:$D$1001,$B11,'Per Line'!$AO$2:$AO$1001,1,'Per Line'!$AP$2:$AP$1001,0)) | T11: =IF($Y11="","",S11*R11) | U11: =IF($Y11="","",T11+Q11) | V11: =IF($Y11="","",W11-U11) | W11: =IF($Y11="","",P11+S11+N11) | X11: =IF($Y11="","",W11-U11-J11) | Y11: =IF(ROWS($Y$2:$Y11)<=MAX('Per Line'!$AN$2:$AN$1001),MATCH(ROWS($Y$2:$Y11),'Per Line'!$AN$2:$AN$1001,0),"") | Z11: =IF($Y11="","",J11-I11*W11/100)
B12: =IF($Y12="","",INDEX('Per Line'!$D$2:$D$1001,$Y12)&"") | C12: =IF($Y12="","",INDEX('Per Line'!$C$2:$C$1001,$Y12)&"") | D12: =IF($Y12="","",INDEX('Per Line'!$F$2:$F$1001,$Y12)) | E12: =IF($Y12="","",INDEX('Per Line'!$G$2:$G$1001,$Y12)&"") | F12: =IF($Y12="","",INDEX('Per Line'!$I$2:$I$1001,$Y12)&"") | G12: =IF($Y12="","",INDEX('Per Line'!$J$2:$J$1001,$Y12)&"") | H12: =IF($Y12="","",INDEX('Per Line'!$K$2:$K$1001,$Y12)&"") | I12: =IF($Y12="","",INDEX('Per Line'!$O$2:$O$1001,$Y12)) | J12: =IF($Y12="","",IF(AND(ISNUMBER(L12),L12>0,W12>L12),I12*L12/100+(W12-L12),I12*W12/100)) | K12: =IF($Y12="","",INDEX('Per Line'!$Y$2:$Y$1001,$Y12)&"") | L12: =IF($Y12="","",INDEX('Per Line'!$AF$2:$AF$1001,$Y12)) | M12: =IF($Y12="","",IF(AND(ISNUMBER(L12),L12>0),W12>L12,FALSE)) | N12: =IF($Y12="","",SUMIFS('Per Line'!$X$2:$X$1001,'Per Line'!$D$2:$D$1001,$B12,'Per Line'!$AP$2:$AP$1001,1)) | O12: =IF($Y12="","",Settings!$C$7) | P12: =IF($Y12="","",SUMIFS('Per Line'!$X$2:$X$1001,'Per Line'!$D$2:$D$1001,$B12,'Per Line'!$AO$2:$AO$1001,0,'Per Line'!$AP$2:$AP$1001,0)) | Q12: =IF($Y12="","",P12*O12) | R12: =IF($Y12="","",Settings!$C$6) | S12: =IF($Y12="","",SUMIFS('Per Line'!$X$2:$X$1001,'Per Line'!$D$2:$D$1001,$B12,'Per Line'!$AO$2:$AO$1001,1,'Per Line'!$AP$2:$AP$1001,0)) | T12: =IF($Y12="","",S12*R12) | U12: =IF($Y12="","",T12+Q12) | V12: =IF($Y12="","",W12-U12) | W12: =IF($Y12="","",P12+S12+N12) | X12: =IF($Y12="","",W12-U12-J12) | Y12: =IF(ROWS($Y$2:$Y12)<=MAX('Per Line'!$AN$2:$AN$1001),MATCH(ROWS($Y$2:$Y12),'Per Line'!$AN$2:$AN$1001,0),"") | Z12: =IF($Y12="","",J12-I12*W12/100)
B13: =IF($Y13="","",INDEX('Per Line'!$D$2:$D$1001,$Y13)&"") | C13: =IF($Y13="","",INDEX('Per Line'!$C$2:$C$1001,$Y13)&"") | D13: =IF($Y13="","",INDEX('Per Line'!$F$2:$F$1001,$Y13)) | E13: =IF($Y13="","",INDEX('Per Line'!$G$2:$G$1001,$Y13)&"") | F13: =IF($Y13="","",INDEX('Per Line'!$I$2:$I$1001,$Y13)&"") | G13: =IF($Y13="","",INDEX('Per Line'!$J$2:$J$1001,$Y13)&"") | H13: =IF($Y13="","",INDEX('Per Line'!$K$2:$K$1001,$Y13)&"") | I13: =IF($Y13="","",INDEX('Per Line'!$O$2:$O$1001,$Y13)) | J13: =IF($Y13="","",IF(AND(ISNUMBER(L13),L13>0,W13>L13),I13*L13/100+(W13-L13),I13*W13/100)) | K13: =IF($Y13="","",INDEX('Per Line'!$Y$2:$Y$1001,$Y13)&"") | L13: =IF($Y13="","",INDEX('Per Line'!$AF$2:$AF$1001,$Y13)) | M13: =IF($Y13="","",IF(AND(ISNUMBER(L13),L13>0),W13>L13,FALSE)) | N13: =IF($Y13="","",SUMIFS('Per Line'!$X$2:$X$1001,'Per Line'!$D$2:$D$1001,$B13,'Per Line'!$AP$2:$AP$1001,1)) | O13: =IF($Y13="","",Settings!$C$7) | P13: =IF($Y13="","",SUMIFS('Per Line'!$X$2:$X$1001,'Per Line'!$D$2:$D$1001,$B13,'Per Line'!$AO$2:$AO$1001,0,'Per Line'!$AP$2:$AP$1001,0)) | Q13: =IF($Y13="","",P13*O13) | R13: =IF($Y13="","",Settings!$C$6) | S13: =IF($Y13="","",SUMIFS('Per Line'!$X$2:$X$1001,'Per Line'!$D$2:$D$1001,$B13,'Per Line'!$AO$2:$AO$1001,1,'Per Line'!$AP$2:$AP$1001,0)) | T13: =IF($Y13="","",S13*R13) | U13: =IF($Y13="","",T13+Q13) | V13: =IF($Y13="","",W13-U13) | W13: =IF($Y13="","",P13+S13+N13) | X13: =IF($Y13="","",W13-U13-J13) | Y13: =IF(ROWS($Y$2:$Y13)<=MAX('Per Line'!$AN$2:$AN$1001),MATCH(ROWS($Y$2:$Y13),'Per Line'!$AN$2:$AN$1001,0),"") | Z13: =IF($Y13="","",J13-I13*W13/100)
... B301: =IF($Y301="","",INDEX('Per Line'!$D$2:$D$1001,$Y301)&"") | C301: =IF($Y301="","",INDEX('Per Line'!$C$2:$C$1001,$Y301)&"") | D301: =IF($Y301="","",INDEX('Per Line'!$F$2:$F$1001,$Y301)) | E301: =IF($Y301="","",INDEX('Per Line'!$G$2:$G$1001,$Y301)&"") | F301: =IF($Y301="","",INDEX('Per Line'!$I$2:$I$1001,$Y301)&"") | G301: =IF($Y301="","",INDEX('Per Line'!$J$2:$J$1001,$Y301)&"") | H301: =IF($Y301="","",INDEX('Per Line'!$K$2:$K$1001,$Y301)&"") | I301: =IF($Y301="","",INDEX('Per Line'!$O$2:$O$1001,$Y301)) | J301: =IF($Y301="","",IF(AND(ISNUMBER(L301),L301>0,W301>L301),I301*L301/100+(W301-L301),I301*W301/100)) | K301: =IF($Y301="","",INDEX('Per Line'!$Y$2:$Y$1001,$Y301)&"") | L301: =IF($Y301="","",INDEX('Per Line'!$AF$2:$AF$1001,$Y301)) | M301: =IF($Y301="","",IF(AND(ISNUMBER(L301),L301>0),W301>L301,FALSE)) | N301: =IF($Y301="","",SUMIFS('Per Line'!$X$2:$X$1001,'Per Line'!$D$2:$D$1001,$B301,'Per Line'!$AP$2:$AP$1001,1)) | O301: =IF($Y301="","",Settings!$C$7) | P301: =IF($Y301="","",SUMIFS('Per Line'!$X$2:$X$1001,'Per Line'!$D$2:$D$1001,$B301,'Per Line'!$AO$2:$AO$1001,0,'Per Line'!$AP$2:$AP$1001,0)) | Q301: =IF($Y301="","",P301*O301) | R301: =IF($Y301="","",Settings!$C$6) | S301: =IF($Y301="","",SUMIFS('Per Line'!$X$2:$X$1001,'Per Line'!$D$2:$D$1001,$B301,'Per Line'!$AO$2:$AO$1001,1,'Per Line'!$AP$2:$AP$1001,0)) | T301: =IF($Y301="","",S301*R301) | U301: =IF($Y301="","",T301+Q301) | V301: =IF($Y301="","",W301-U301) | W301: =IF($Y301="","",P301+S301+N301) | X301: =IF($Y301="","",W301-U301-J301) | Y301: =IF(ROWS($Y$2:$Y301)<=MAX('Per Line'!$AN$2:$AN$1001),MATCH(ROWS($Y$2:$Y301),'Per Line'!$AN$2:$AN$1001,0),"") | Z301: =IF($Y301="","",J301-I301*W301/100)
