Workbook

Sheet How To Use
A1: Claims Template - CINNABON (Walk In)
A3: Monthly steps
A4: 1. Open the 'Per Line' tab. Delete the old data in the BLUE columns only (row 2 down). Never delete the green or grey columns.
A5: 2. Paste the new month's data as VALUES starting at A2, into the blue columns: A-E, G-J, N-R, T (same order as the system export).
A6: 3. Green columns (F, K, L, M, S) and the grey helper columns (U-X) calculate automatically - do not paste over them.
A7: 4. 'Per Invoice' fills itself from 'Per Line' (one row per POS Reference, split into IMP / Local). No pivot table, no refresh.
A8: 5. The ONLY manual column in 'Per Invoice' is column B 'Invoice' (blue): type it yourself. Everything else is formula.
A9: 6. Open 'Settings' and check STATUS says OK (Per Line totals = Per Invoice totals).
A11: Colour legend
A12: Blue header = typed/pasted by you (raw data, and 'Invoice' in Per Invoice). Green header = formula (do not paste over). Grey header = helper formula (do not touch). Yellow cell (Settings) = editable rate.
A14: Calculation rules (taken from the September 2026 sheet)
A15: Co val = Co Payment % x Total / 100. Discount = Total x Rebates (Rebates is a fraction here, e.g. 0.14). Subtotal = Total - Discount. Net = Subtotal - Co val. (Total = 'Total Delivered')
... A20: Capacity: up to 1,000 lines and 300 invoices per month. A line with an empty POS Reference is ignored.

Sheet Settings
B1: Company settings & checks
B3: Insurance Company | C3: CINNABON | D3: Informational only
B4: Corporate | C4: - | D4: Informational only
B5: Sheet type | C5: Walk In | D5: Informational only
B6: Local products rebate % | C6: 0.09 | D6: Source: Sep sheet (reb = 0.09 on Local lines).
B7: Imported (IMP) products rebate % | C7: 0.05 | D7: Source: Sep sheet (IMP % = 0.05 on non-local lines).
B9: Month totals / reconciliation
B10: Lines loaded | C10: =COUNTA('Per Line'!$A$2:$A$1001)
B11: Invoices (unique Order #) | C11: =MAX('Per Line'!$V$2:$V$1001)
B12: Invoices shown in Per Invoice | C12: =SUMPRODUCT(--('Per Invoice'!$A$2:$A$301<>""))
B13: Grand Total - Per Line (Product Total) | C13: =SUM('Per Line'!$N$2:$N$1001)
B14: Grand Total - Per Invoice | C14: =SUM('Per Invoice'!$S$2:$S$301)
B15: Discount - Per Line | C15: =SUM('Per Line'!$K$2:$K$1001)
B16: Discount - Per Invoice | C16: =SUM('Per Invoice'!$Q$2:$Q$301)
B17: Co val - Per Line | C17: =SUM('Per Line'!$F$2:$F$1001)
B18: Co val - Per Invoice | C18: =SUM('Per Invoice'!$G$2:$G$301)
B19: Net - Per Line | C19: =SUM('Per Line'!$M$2:$M$1001)
B20: Net - Per Invoice | C20: =SUM('Per Invoice'!$T$2:$T$301)
B21: Max Limit adjustment (Co val, Per Invoice only) | C21: 0 | D21: This company's Per Invoice has no Max Limit rule.
B23: STATUS | C23: =IF(C10=0,"No data loaded",IF(COUNTA('Per Line'!$A:$A)-1>1000,"TOO MANY LINES - extend template",IF(C11>300,"TOO MANY INVOICES - extend template",IF(AND(ROUND(C13-C14,2)=0,ROUND(C15-C16,2)=0,ROUND(C17+C21-C18,2)=0,ROUND(C19-C21-C20,2)=0,C11=C12),"OK","CHECK - Per Line and Per Invoice do not match")))) | D23: Must say OK after you paste the month data.

Sheet Per Line
A1: Pos Reference | B1: Insurance Company | C1: Name | D1: Card Number | E1: Co Payment % | F1: Co val | G1: Heisenberg id | H1: Product | I1: Delivered Qty | J1: Delivered Price | K1: Discount | L1: Subtotal | M1: Net | N1: Total Delivered | O1: Payment Type | P1: Session | Q1: Create Date | R1: Order Reference | S1: Rebates | T1: Product Template - Product Tmpl → Is Local | U1: Order 1st Row (helper) | V1: Invoice # (helper) | W1: Is Local (helper) | X1: Sort Key (helper)
F2: =IF($A2="","",E2*N2/100) | K2: =IF($A2="","",S2*N2) | L2: =IF($A2="","",N2-K2) | M2: =IF($A2="","",L2-F2) | S2: =IF($A2="","",IF($W2=1,Settings!$C$6,Settings!$C$7)*1) | U2: =IF($A2="","",IF(COUNTIF($A$2:$A2,$A2)=1,1,0)) | V2: =IF($U2=1,SUMPRODUCT(--($X$2:$X$1001<$X2))+1,"") | W2: =IF($A2="","",IF(OR($T2=TRUE(),$T2="TRUE"),1,0)) | X2: =IF($U2=1,IFERROR(IF(VALUE($A2)<100000000,VALUE($A2),1000000000),IFERROR(IF(VALUE(MID($A2,2,20))<100000000,VALUE(MID($A2,2,20)),1000000000),1000000000))+ROW()/100000,"")
F3: =IF($A3="","",E3*N3/100) | K3: =IF($A3="","",S3*N3) | L3: =IF($A3="","",N3-K3) | M3: =IF($A3="","",L3-F3) | S3: =IF($A3="","",IF($W3=1,Settings!$C$6,Settings!$C$7)*1) | U3: =IF($A3="","",IF(COUNTIF($A$2:$A3,$A3)=1,1,0)) | V3: =IF($U3=1,SUMPRODUCT(--($X$2:$X$1001<$X3))+1,"") | W3: =IF($A3="","",IF(OR($T3=TRUE(),$T3="TRUE"),1,0)) | X3: =IF($U3=1,IFERROR(IF(VALUE($A3)<100000000,VALUE($A3),1000000000),IFERROR(IF(VALUE(MID($A3,2,20))<100000000,VALUE(MID($A3,2,20)),1000000000),1000000000))+ROW()/100000,"")
F4: =IF($A4="","",E4*N4/100) | K4: =IF($A4="","",S4*N4) | L4: =IF($A4="","",N4-K4) | M4: =IF($A4="","",L4-F4) | S4: =IF($A4="","",IF($W4=1,Settings!$C$6,Settings!$C$7)*1) | U4: =IF($A4="","",IF(COUNTIF($A$2:$A4,$A4)=1,1,0)) | V4: =IF($U4=1,SUMPRODUCT(--($X$2:$X$1001<$X4))+1,"") | W4: =IF($A4="","",IF(OR($T4=TRUE(),$T4="TRUE"),1,0)) | X4: =IF($U4=1,IFERROR(IF(VALUE($A4)<100000000,VALUE($A4),1000000000),IFERROR(IF(VALUE(MID($A4,2,20))<100000000,VALUE(MID($A4,2,20)),1000000000),1000000000))+ROW()/100000,"")
F5: =IF($A5="","",E5*N5/100) | K5: =IF($A5="","",S5*N5) | L5: =IF($A5="","",N5-K5) | M5: =IF($A5="","",L5-F5) | S5: =IF($A5="","",IF($W5=1,Settings!$C$6,Settings!$C$7)*1) | U5: =IF($A5="","",IF(COUNTIF($A$2:$A5,$A5)=1,1,0)) | V5: =IF($U5=1,SUMPRODUCT(--($X$2:$X$1001<$X5))+1,"") | W5: =IF($A5="","",IF(OR($T5=TRUE(),$T5="TRUE"),1,0)) | X5: =IF($U5=1,IFERROR(IF(VALUE($A5)<100000000,VALUE($A5),1000000000),IFERROR(IF(VALUE(MID($A5,2,20))<100000000,VALUE(MID($A5,2,20)),1000000000),1000000000))+ROW()/100000,"")
F6: =IF($A6="","",E6*N6/100) | K6: =IF($A6="","",S6*N6) | L6: =IF($A6="","",N6-K6) | M6: =IF($A6="","",L6-F6) | S6: =IF($A6="","",IF($W6=1,Settings!$C$6,Settings!$C$7)*1) | U6: =IF($A6="","",IF(COUNTIF($A$2:$A6,$A6)=1,1,0)) | V6: =IF($U6=1,SUMPRODUCT(--($X$2:$X$1001<$X6))+1,"") | W6: =IF($A6="","",IF(OR($T6=TRUE(),$T6="TRUE"),1,0)) | X6: =IF($U6=1,IFERROR(IF(VALUE($A6)<100000000,VALUE($A6),1000000000),IFERROR(IF(VALUE(MID($A6,2,20))<100000000,VALUE(MID($A6,2,20)),1000000000),1000000000))+ROW()/100000,"")
F7: =IF($A7="","",E7*N7/100) | K7: =IF($A7="","",S7*N7) | L7: =IF($A7="","",N7-K7) | M7: =IF($A7="","",L7-F7) | S7: =IF($A7="","",IF($W7=1,Settings!$C$6,Settings!$C$7)*1) | U7: =IF($A7="","",IF(COUNTIF($A$2:$A7,$A7)=1,1,0)) | V7: =IF($U7=1,SUMPRODUCT(--($X$2:$X$1001<$X7))+1,"") | W7: =IF($A7="","",IF(OR($T7=TRUE(),$T7="TRUE"),1,0)) | X7: =IF($U7=1,IFERROR(IF(VALUE($A7)<100000000,VALUE($A7),1000000000),IFERROR(IF(VALUE(MID($A7,2,20))<100000000,VALUE(MID($A7,2,20)),1000000000),1000000000))+ROW()/100000,"")
F8: =IF($A8="","",E8*N8/100) | K8: =IF($A8="","",S8*N8) | L8: =IF($A8="","",N8-K8) | M8: =IF($A8="","",L8-F8) | S8: =IF($A8="","",IF($W8=1,Settings!$C$6,Settings!$C$7)*1) | U8: =IF($A8="","",IF(COUNTIF($A$2:$A8,$A8)=1,1,0)) | V8: =IF($U8=1,SUMPRODUCT(--($X$2:$X$1001<$X8))+1,"") | W8: =IF($A8="","",IF(OR($T8=TRUE(),$T8="TRUE"),1,0)) | X8: =IF($U8=1,IFERROR(IF(VALUE($A8)<100000000,VALUE($A8),1000000000),IFERROR(IF(VALUE(MID($A8,2,20))<100000000,VALUE(MID($A8,2,20)),1000000000),1000000000))+ROW()/100000,"")
F9: =IF($A9="","",E9*N9/100) | K9: =IF($A9="","",S9*N9) | L9: =IF($A9="","",N9-K9) | M9: =IF($A9="","",L9-F9) | S9: =IF($A9="","",IF($W9=1,Settings!$C$6,Settings!$C$7)*1) | U9: =IF($A9="","",IF(COUNTIF($A$2:$A9,$A9)=1,1,0)) | V9: =IF($U9=1,SUMPRODUCT(--($X$2:$X$1001<$X9))+1,"") | W9: =IF($A9="","",IF(OR($T9=TRUE(),$T9="TRUE"),1,0)) | X9: =IF($U9=1,IFERROR(IF(VALUE($A9)<100000000,VALUE($A9),1000000000),IFERROR(IF(VALUE(MID($A9,2,20))<100000000,VALUE(MID($A9,2,20)),1000000000),1000000000))+ROW()/100000,"")
F10: =IF($A10="","",E10*N10/100) | K10: =IF($A10="","",S10*N10) | L10: =IF($A10="","",N10-K10) | M10: =IF($A10="","",L10-F10) | S10: =IF($A10="","",IF($W10=1,Settings!$C$6,Settings!$C$7)*1) | U10: =IF($A10="","",IF(COUNTIF($A$2:$A10,$A10)=1,1,0)) | V10: =IF($U10=1,SUMPRODUCT(--($X$2:$X$1001<$X10))+1,"") | W10: =IF($A10="","",IF(OR($T10=TRUE(),$T10="TRUE"),1,0)) | X10: =IF($U10=1,IFERROR(IF(VALUE($A10)<100000000,VALUE($A10),1000000000),IFERROR(IF(VALUE(MID($A10,2,20))<100000000,VALUE(MID($A10,2,20)),1000000000),1000000000))+ROW()/100000,"")
F11: =IF($A11="","",E11*N11/100) | K11: =IF($A11="","",S11*N11) | L11: =IF($A11="","",N11-K11) | M11: =IF($A11="","",L11-F11) | S11: =IF($A11="","",IF($W11=1,Settings!$C$6,Settings!$C$7)*1) | U11: =IF($A11="","",IF(COUNTIF($A$2:$A11,$A11)=1,1,0)) | V11: =IF($U11=1,SUMPRODUCT(--($X$2:$X$1001<$X11))+1,"") | W11: =IF($A11="","",IF(OR($T11=TRUE(),$T11="TRUE"),1,0)) | X11: =IF($U11=1,IFERROR(IF(VALUE($A11)<100000000,VALUE($A11),1000000000),IFERROR(IF(VALUE(MID($A11,2,20))<100000000,VALUE(MID($A11,2,20)),1000000000),1000000000))+ROW()/100000,"")
F12: =IF($A12="","",E12*N12/100) | K12: =IF($A12="","",S12*N12) | L12: =IF($A12="","",N12-K12) | M12: =IF($A12="","",L12-F12) | S12: =IF($A12="","",IF($W12=1,Settings!$C$6,Settings!$C$7)*1) | U12: =IF($A12="","",IF(COUNTIF($A$2:$A12,$A12)=1,1,0)) | V12: =IF($U12=1,SUMPRODUCT(--($X$2:$X$1001<$X12))+1,"") | W12: =IF($A12="","",IF(OR($T12=TRUE(),$T12="TRUE"),1,0)) | X12: =IF($U12=1,IFERROR(IF(VALUE($A12)<100000000,VALUE($A12),1000000000),IFERROR(IF(VALUE(MID($A12,2,20))<100000000,VALUE(MID($A12,2,20)),1000000000),1000000000))+ROW()/100000,"")
F13: =IF($A13="","",E13*N13/100) | K13: =IF($A13="","",S13*N13) | L13: =IF($A13="","",N13-K13) | M13: =IF($A13="","",L13-F13) | S13: =IF($A13="","",IF($W13=1,Settings!$C$6,Settings!$C$7)*1) | U13: =IF($A13="","",IF(COUNTIF($A$2:$A13,$A13)=1,1,0)) | V13: =IF($U13=1,SUMPRODUCT(--($X$2:$X$1001<$X13))+1,"") | W13: =IF($A13="","",IF(OR($T13=TRUE(),$T13="TRUE"),1,0)) | X13: =IF($U13=1,IFERROR(IF(VALUE($A13)<100000000,VALUE($A13),1000000000),IFERROR(IF(VALUE(MID($A13,2,20))<100000000,VALUE(MID($A13,2,20)),1000000000),1000000000))+ROW()/100000,"")
... F1001: =IF($A1001="","",E1001*N1001/100) | K1001: =IF($A1001="","",S1001*N1001) | L1001: =IF($A1001="","",N1001-K1001) | M1001: =IF($A1001="","",L1001-F1001) | S1001: =IF($A1001="","",IF($W1001=1,Settings!$C$6,Settings!$C$7)*1) | U1001: =IF($A1001="","",IF(COUNTIF($A$2:$A1001,$A1001)=1,1,0)) | V1001: =IF($U1001=1,SUMPRODUCT(--($X$2:$X$1001<$X1001))+1,"") | W1001: =IF($A1001="","",IF(OR($T1001=TRUE(),$T1001="TRUE"),1,0)) | X1001: =IF($U1001=1,IFERROR(IF(VALUE($A1001)<100000000,VALUE($A1001),1000000000),IFERROR(IF(VALUE(MID($A1001,2,20))<100000000,VALUE(MID($A1001,2,20)),1000000000),1000000000))+ROW()/100000,"")

Sheet Per Invoice
A1: Pos Reference | B1: Invoice | C1: Insurance Company | D1: Name | E1: Card Number | F1: Co Payment % | G1: Co val | H1: Payment Type | I1: Create Date | J1: Order Reference | K1: IMP % | L1: IMP | M1: IMP VAL | N1: LOC % | O1: LOC | P1: LOC VAL | Q1: TOTAL VAL | R1: SUBTOTAL | S1: Grand Total | T1: NET | U1: Src Row (helper)
A2: =IF($U2="","",INDEX('Per Line'!$A$2:$A$1001,$U2)&"") | C2: =IF($U2="","",INDEX('Per Line'!$B$2:$B$1001,$U2)&"") | D2: =IF($U2="","",INDEX('Per Line'!$C$2:$C$1001,$U2)&"") | E2: =IF($U2="","",INDEX('Per Line'!$D$2:$D$1001,$U2)&"") | F2: =IF($U2="","",INDEX('Per Line'!$E$2:$E$1001,$U2)) | G2: =IF($U2="","",F2*S2/100) | H2: =IF($U2="","",INDEX('Per Line'!$O$2:$O$1001,$U2)&"") | I2: =IF($U2="","",INDEX('Per Line'!$Q$2:$Q$1001,$U2)) | J2: =IF($U2="","",INDEX('Per Line'!$R$2:$R$1001,$U2)&"") | K2: =IF($U2="","",Settings!$C$7) | L2: =IF($U2="","",SUMIFS('Per Line'!$N$2:$N$1001,'Per Line'!$A$2:$A$1001,$A2,'Per Line'!$W$2:$W$1001,0)) | M2: =IF($U2="","",L2*K2) | N2: =IF($U2="","",Settings!$C$6) | O2: =IF($U2="","",SUMIFS('Per Line'!$N$2:$N$1001,'Per Line'!$A$2:$A$1001,$A2,'Per Line'!$W$2:$W$1001,1)) | P2: =IF($U2="","",O2*N2) | Q2: =IF($U2="","",P2+M2) | R2: =IF($U2="","",S2-Q2) | S2: =IF($U2="","",L2+O2) | T2: =IF($U2="","",S2-Q2-G2) | U2: =IF(ROWS($U$2:$U2)<=MAX('Per Line'!$V$2:$V$1001),MATCH(ROWS($U$2:$U2),'Per Line'!$V$2:$V$1001,0),"")
A3: =IF($U3="","",INDEX('Per Line'!$A$2:$A$1001,$U3)&"") | C3: =IF($U3="","",INDEX('Per Line'!$B$2:$B$1001,$U3)&"") | D3: =IF($U3="","",INDEX('Per Line'!$C$2:$C$1001,$U3)&"") | E3: =IF($U3="","",INDEX('Per Line'!$D$2:$D$1001,$U3)&"") | F3: =IF($U3="","",INDEX('Per Line'!$E$2:$E$1001,$U3)) | G3: =IF($U3="","",F3*S3/100) | H3: =IF($U3="","",INDEX('Per Line'!$O$2:$O$1001,$U3)&"") | I3: =IF($U3="","",INDEX('Per Line'!$Q$2:$Q$1001,$U3)) | J3: =IF($U3="","",INDEX('Per Line'!$R$2:$R$1001,$U3)&"") | K3: =IF($U3="","",Settings!$C$7) | L3: =IF($U3="","",SUMIFS('Per Line'!$N$2:$N$1001,'Per Line'!$A$2:$A$1001,$A3,'Per Line'!$W$2:$W$1001,0)) | M3: =IF($U3="","",L3*K3) | N3: =IF($U3="","",Settings!$C$6) | O3: =IF($U3="","",SUMIFS('Per Line'!$N$2:$N$1001,'Per Line'!$A$2:$A$1001,$A3,'Per Line'!$W$2:$W$1001,1)) | P3: =IF($U3="","",O3*N3) | Q3: =IF($U3="","",P3+M3) | R3: =IF($U3="","",S3-Q3) | S3: =IF($U3="","",L3+O3) | T3: =IF($U3="","",S3-Q3-G3) | U3: =IF(ROWS($U$2:$U3)<=MAX('Per Line'!$V$2:$V$1001),MATCH(ROWS($U$2:$U3),'Per Line'!$V$2:$V$1001,0),"")
A4: =IF($U4="","",INDEX('Per Line'!$A$2:$A$1001,$U4)&"") | C4: =IF($U4="","",INDEX('Per Line'!$B$2:$B$1001,$U4)&"") | D4: =IF($U4="","",INDEX('Per Line'!$C$2:$C$1001,$U4)&"") | E4: =IF($U4="","",INDEX('Per Line'!$D$2:$D$1001,$U4)&"") | F4: =IF($U4="","",INDEX('Per Line'!$E$2:$E$1001,$U4)) | G4: =IF($U4="","",F4*S4/100) | H4: =IF($U4="","",INDEX('Per Line'!$O$2:$O$1001,$U4)&"") | I4: =IF($U4="","",INDEX('Per Line'!$Q$2:$Q$1001,$U4)) | J4: =IF($U4="","",INDEX('Per Line'!$R$2:$R$1001,$U4)&"") | K4: =IF($U4="","",Settings!$C$7) | L4: =IF($U4="","",SUMIFS('Per Line'!$N$2:$N$1001,'Per Line'!$A$2:$A$1001,$A4,'Per Line'!$W$2:$W$1001,0)) | M4: =IF($U4="","",L4*K4) | N4: =IF($U4="","",Settings!$C$6) | O4: =IF($U4="","",SUMIFS('Per Line'!$N$2:$N$1001,'Per Line'!$A$2:$A$1001,$A4,'Per Line'!$W$2:$W$1001,1)) | P4: =IF($U4="","",O4*N4) | Q4: =IF($U4="","",P4+M4) | R4: =IF($U4="","",S4-Q4) | S4: =IF($U4="","",L4+O4) | T4: =IF($U4="","",S4-Q4-G4) | U4: =IF(ROWS($U$2:$U4)<=MAX('Per Line'!$V$2:$V$1001),MATCH(ROWS($U$2:$U4),'Per Line'!$V$2:$V$1001,0),"")
A5: =IF($U5="","",INDEX('Per Line'!$A$2:$A$1001,$U5)&"") | C5: =IF($U5="","",INDEX('Per Line'!$B$2:$B$1001,$U5)&"") | D5: =IF($U5="","",INDEX('Per Line'!$C$2:$C$1001,$U5)&"") | E5: =IF($U5="","",INDEX('Per Line'!$D$2:$D$1001,$U5)&"") | F5: =IF($U5="","",INDEX('Per Line'!$E$2:$E$1001,$U5)) | G5: =IF($U5="","",F5*S5/100) | H5: =IF($U5="","",INDEX('Per Line'!$O$2:$O$1001,$U5)&"") | I5: =IF($U5="","",INDEX('Per Line'!$Q$2:$Q$1001,$U5)) | J5: =IF($U5="","",INDEX('Per Line'!$R$2:$R$1001,$U5)&"") | K5: =IF($U5="","",Settings!$C$7) | L5: =IF($U5="","",SUMIFS('Per Line'!$N$2:$N$1001,'Per Line'!$A$2:$A$1001,$A5,'Per Line'!$W$2:$W$1001,0)) | M5: =IF($U5="","",L5*K5) | N5: =IF($U5="","",Settings!$C$6) | O5: =IF($U5="","",SUMIFS('Per Line'!$N$2:$N$1001,'Per Line'!$A$2:$A$1001,$A5,'Per Line'!$W$2:$W$1001,1)) | P5: =IF($U5="","",O5*N5) | Q5: =IF($U5="","",P5+M5) | R5: =IF($U5="","",S5-Q5) | S5: =IF($U5="","",L5+O5) | T5: =IF($U5="","",S5-Q5-G5) | U5: =IF(ROWS($U$2:$U5)<=MAX('Per Line'!$V$2:$V$1001),MATCH(ROWS($U$2:$U5),'Per Line'!$V$2:$V$1001,0),"")
A6: =IF($U6="","",INDEX('Per Line'!$A$2:$A$1001,$U6)&"") | C6: =IF($U6="","",INDEX('Per Line'!$B$2:$B$1001,$U6)&"") | D6: =IF($U6="","",INDEX('Per Line'!$C$2:$C$1001,$U6)&"") | E6: =IF($U6="","",INDEX('Per Line'!$D$2:$D$1001,$U6)&"") | F6: =IF($U6="","",INDEX('Per Line'!$E$2:$E$1001,$U6)) | G6: =IF($U6="","",F6*S6/100) | H6: =IF($U6="","",INDEX('Per Line'!$O$2:$O$1001,$U6)&"") | I6: =IF($U6="","",INDEX('Per Line'!$Q$2:$Q$1001,$U6)) | J6: =IF($U6="","",INDEX('Per Line'!$R$2:$R$1001,$U6)&"") | K6: =IF($U6="","",Settings!$C$7) | L6: =IF($U6="","",SUMIFS('Per Line'!$N$2:$N$1001,'Per Line'!$A$2:$A$1001,$A6,'Per Line'!$W$2:$W$1001,0)) | M6: =IF($U6="","",L6*K6) | N6: =IF($U6="","",Settings!$C$6) | O6: =IF($U6="","",SUMIFS('Per Line'!$N$2:$N$1001,'Per Line'!$A$2:$A$1001,$A6,'Per Line'!$W$2:$W$1001,1)) | P6: =IF($U6="","",O6*N6) | Q6: =IF($U6="","",P6+M6) | R6: =IF($U6="","",S6-Q6) | S6: =IF($U6="","",L6+O6) | T6: =IF($U6="","",S6-Q6-G6) | U6: =IF(ROWS($U$2:$U6)<=MAX('Per Line'!$V$2:$V$1001),MATCH(ROWS($U$2:$U6),'Per Line'!$V$2:$V$1001,0),"")
A7: =IF($U7="","",INDEX('Per Line'!$A$2:$A$1001,$U7)&"") | C7: =IF($U7="","",INDEX('Per Line'!$B$2:$B$1001,$U7)&"") | D7: =IF($U7="","",INDEX('Per Line'!$C$2:$C$1001,$U7)&"") | E7: =IF($U7="","",INDEX('Per Line'!$D$2:$D$1001,$U7)&"") | F7: =IF($U7="","",INDEX('Per Line'!$E$2:$E$1001,$U7)) | G7: =IF($U7="","",F7*S7/100) | H7: =IF($U7="","",INDEX('Per Line'!$O$2:$O$1001,$U7)&"") | I7: =IF($U7="","",INDEX('Per Line'!$Q$2:$Q$1001,$U7)) | J7: =IF($U7="","",INDEX('Per Line'!$R$2:$R$1001,$U7)&"") | K7: =IF($U7="","",Settings!$C$7) | L7: =IF($U7="","",SUMIFS('Per Line'!$N$2:$N$1001,'Per Line'!$A$2:$A$1001,$A7,'Per Line'!$W$2:$W$1001,0)) | M7: =IF($U7="","",L7*K7) | N7: =IF($U7="","",Settings!$C$6) | O7: =IF($U7="","",SUMIFS('Per Line'!$N$2:$N$1001,'Per Line'!$A$2:$A$1001,$A7,'Per Line'!$W$2:$W$1001,1)) | P7: =IF($U7="","",O7*N7) | Q7: =IF($U7="","",P7+M7) | R7: =IF($U7="","",S7-Q7) | S7: =IF($U7="","",L7+O7) | T7: =IF($U7="","",S7-Q7-G7) | U7: =IF(ROWS($U$2:$U7)<=MAX('Per Line'!$V$2:$V$1001),MATCH(ROWS($U$2:$U7),'Per Line'!$V$2:$V$1001,0),"")
A8: =IF($U8="","",INDEX('Per Line'!$A$2:$A$1001,$U8)&"") | C8: =IF($U8="","",INDEX('Per Line'!$B$2:$B$1001,$U8)&"") | D8: =IF($U8="","",INDEX('Per Line'!$C$2:$C$1001,$U8)&"") | E8: =IF($U8="","",INDEX('Per Line'!$D$2:$D$1001,$U8)&"") | F8: =IF($U8="","",INDEX('Per Line'!$E$2:$E$1001,$U8)) | G8: =IF($U8="","",F8*S8/100) | H8: =IF($U8="","",INDEX('Per Line'!$O$2:$O$1001,$U8)&"") | I8: =IF($U8="","",INDEX('Per Line'!$Q$2:$Q$1001,$U8)) | J8: =IF($U8="","",INDEX('Per Line'!$R$2:$R$1001,$U8)&"") | K8: =IF($U8="","",Settings!$C$7) | L8: =IF($U8="","",SUMIFS('Per Line'!$N$2:$N$1001,'Per Line'!$A$2:$A$1001,$A8,'Per Line'!$W$2:$W$1001,0)) | M8: =IF($U8="","",L8*K8) | N8: =IF($U8="","",Settings!$C$6) | O8: =IF($U8="","",SUMIFS('Per Line'!$N$2:$N$1001,'Per Line'!$A$2:$A$1001,$A8,'Per Line'!$W$2:$W$1001,1)) | P8: =IF($U8="","",O8*N8) | Q8: =IF($U8="","",P8+M8) | R8: =IF($U8="","",S8-Q8) | S8: =IF($U8="","",L8+O8) | T8: =IF($U8="","",S8-Q8-G8) | U8: =IF(ROWS($U$2:$U8)<=MAX('Per Line'!$V$2:$V$1001),MATCH(ROWS($U$2:$U8),'Per Line'!$V$2:$V$1001,0),"")
A9: =IF($U9="","",INDEX('Per Line'!$A$2:$A$1001,$U9)&"") | C9: =IF($U9="","",INDEX('Per Line'!$B$2:$B$1001,$U9)&"") | D9: =IF($U9="","",INDEX('Per Line'!$C$2:$C$1001,$U9)&"") | E9: =IF($U9="","",INDEX('Per Line'!$D$2:$D$1001,$U9)&"") | F9: =IF($U9="","",INDEX('Per Line'!$E$2:$E$1001,$U9)) | G9: =IF($U9="","",F9*S9/100) | H9: =IF($U9="","",INDEX('Per Line'!$O$2:$O$1001,$U9)&"") | I9: =IF($U9="","",INDEX('Per Line'!$Q$2:$Q$1001,$U9)) | J9: =IF($U9="","",INDEX('Per Line'!$R$2:$R$1001,$U9)&"") | K9: =IF($U9="","",Settings!$C$7) | L9: =IF($U9="","",SUMIFS('Per Line'!$N$2:$N$1001,'Per Line'!$A$2:$A$1001,$A9,'Per Line'!$W$2:$W$1001,0)) | M9: =IF($U9="","",L9*K9) | N9: =IF($U9="","",Settings!$C$6) | O9: =IF($U9="","",SUMIFS('Per Line'!$N$2:$N$1001,'Per Line'!$A$2:$A$1001,$A9,'Per Line'!$W$2:$W$1001,1)) | P9: =IF($U9="","",O9*N9) | Q9: =IF($U9="","",P9+M9) | R9: =IF($U9="","",S9-Q9) | S9: =IF($U9="","",L9+O9) | T9: =IF($U9="","",S9-Q9-G9) | U9: =IF(ROWS($U$2:$U9)<=MAX('Per Line'!$V$2:$V$1001),MATCH(ROWS($U$2:$U9),'Per Line'!$V$2:$V$1001,0),"")
A10: =IF($U10="","",INDEX('Per Line'!$A$2:$A$1001,$U10)&"") | C10: =IF($U10="","",INDEX('Per Line'!$B$2:$B$1001,$U10)&"") | D10: =IF($U10="","",INDEX('Per Line'!$C$2:$C$1001,$U10)&"") | E10: =IF($U10="","",INDEX('Per Line'!$D$2:$D$1001,$U10)&"") | F10: =IF($U10="","",INDEX('Per Line'!$E$2:$E$1001,$U10)) | G10: =IF($U10="","",F10*S10/100) | H10: =IF($U10="","",INDEX('Per Line'!$O$2:$O$1001,$U10)&"") | I10: =IF($U10="","",INDEX('Per Line'!$Q$2:$Q$1001,$U10)) | J10: =IF($U10="","",INDEX('Per Line'!$R$2:$R$1001,$U10)&"") | K10: =IF($U10="","",Settings!$C$7) | L10: =IF($U10="","",SUMIFS('Per Line'!$N$2:$N$1001,'Per Line'!$A$2:$A$1001,$A10,'Per Line'!$W$2:$W$1001,0)) | M10: =IF($U10="","",L10*K10) | N10: =IF($U10="","",Settings!$C$6) | O10: =IF($U10="","",SUMIFS('Per Line'!$N$2:$N$1001,'Per Line'!$A$2:$A$1001,$A10,'Per Line'!$W$2:$W$1001,1)) | P10: =IF($U10="","",O10*N10) | Q10: =IF($U10="","",P10+M10) | R10: =IF($U10="","",S10-Q10) | S10: =IF($U10="","",L10+O10) | T10: =IF($U10="","",S10-Q10-G10) | U10: =IF(ROWS($U$2:$U10)<=MAX('Per Line'!$V$2:$V$1001),MATCH(ROWS($U$2:$U10),'Per Line'!$V$2:$V$1001,0),"")
A11: =IF($U11="","",INDEX('Per Line'!$A$2:$A$1001,$U11)&"") | C11: =IF($U11="","",INDEX('Per Line'!$B$2:$B$1001,$U11)&"") | D11: =IF($U11="","",INDEX('Per Line'!$C$2:$C$1001,$U11)&"") | E11: =IF($U11="","",INDEX('Per Line'!$D$2:$D$1001,$U11)&"") | F11: =IF($U11="","",INDEX('Per Line'!$E$2:$E$1001,$U11)) | G11: =IF($U11="","",F11*S11/100) | H11: =IF($U11="","",INDEX('Per Line'!$O$2:$O$1001,$U11)&"") | I11: =IF($U11="","",INDEX('Per Line'!$Q$2:$Q$1001,$U11)) | J11: =IF($U11="","",INDEX('Per Line'!$R$2:$R$1001,$U11)&"") | K11: =IF($U11="","",Settings!$C$7) | L11: =IF($U11="","",SUMIFS('Per Line'!$N$2:$N$1001,'Per Line'!$A$2:$A$1001,$A11,'Per Line'!$W$2:$W$1001,0)) | M11: =IF($U11="","",L11*K11) | N11: =IF($U11="","",Settings!$C$6) | O11: =IF($U11="","",SUMIFS('Per Line'!$N$2:$N$1001,'Per Line'!$A$2:$A$1001,$A11,'Per Line'!$W$2:$W$1001,1)) | P11: =IF($U11="","",O11*N11) | Q11: =IF($U11="","",P11+M11) | R11: =IF($U11="","",S11-Q11) | S11: =IF($U11="","",L11+O11) | T11: =IF($U11="","",S11-Q11-G11) | U11: =IF(ROWS($U$2:$U11)<=MAX('Per Line'!$V$2:$V$1001),MATCH(ROWS($U$2:$U11),'Per Line'!$V$2:$V$1001,0),"")
A12: =IF($U12="","",INDEX('Per Line'!$A$2:$A$1001,$U12)&"") | C12: =IF($U12="","",INDEX('Per Line'!$B$2:$B$1001,$U12)&"") | D12: =IF($U12="","",INDEX('Per Line'!$C$2:$C$1001,$U12)&"") | E12: =IF($U12="","",INDEX('Per Line'!$D$2:$D$1001,$U12)&"") | F12: =IF($U12="","",INDEX('Per Line'!$E$2:$E$1001,$U12)) | G12: =IF($U12="","",F12*S12/100) | H12: =IF($U12="","",INDEX('Per Line'!$O$2:$O$1001,$U12)&"") | I12: =IF($U12="","",INDEX('Per Line'!$Q$2:$Q$1001,$U12)) | J12: =IF($U12="","",INDEX('Per Line'!$R$2:$R$1001,$U12)&"") | K12: =IF($U12="","",Settings!$C$7) | L12: =IF($U12="","",SUMIFS('Per Line'!$N$2:$N$1001,'Per Line'!$A$2:$A$1001,$A12,'Per Line'!$W$2:$W$1001,0)) | M12: =IF($U12="","",L12*K12) | N12: =IF($U12="","",Settings!$C$6) | O12: =IF($U12="","",SUMIFS('Per Line'!$N$2:$N$1001,'Per Line'!$A$2:$A$1001,$A12,'Per Line'!$W$2:$W$1001,1)) | P12: =IF($U12="","",O12*N12) | Q12: =IF($U12="","",P12+M12) | R12: =IF($U12="","",S12-Q12) | S12: =IF($U12="","",L12+O12) | T12: =IF($U12="","",S12-Q12-G12) | U12: =IF(ROWS($U$2:$U12)<=MAX('Per Line'!$V$2:$V$1001),MATCH(ROWS($U$2:$U12),'Per Line'!$V$2:$V$1001,0),"")
A13: =IF($U13="","",INDEX('Per Line'!$A$2:$A$1001,$U13)&"") | C13: =IF($U13="","",INDEX('Per Line'!$B$2:$B$1001,$U13)&"") | D13: =IF($U13="","",INDEX('Per Line'!$C$2:$C$1001,$U13)&"") | E13: =IF($U13="","",INDEX('Per Line'!$D$2:$D$1001,$U13)&"") | F13: =IF($U13="","",INDEX('Per Line'!$E$2:$E$1001,$U13)) | G13: =IF($U13="","",F13*S13/100) | H13: =IF($U13="","",INDEX('Per Line'!$O$2:$O$1001,$U13)&"") | I13: =IF($U13="","",INDEX('Per Line'!$Q$2:$Q$1001,$U13)) | J13: =IF($U13="","",INDEX('Per Line'!$R$2:$R$1001,$U13)&"") | K13: =IF($U13="","",Settings!$C$7) | L13: =IF($U13="","",SUMIFS('Per Line'!$N$2:$N$1001,'Per Line'!$A$2:$A$1001,$A13,'Per Line'!$W$2:$W$1001,0)) | M13: =IF($U13="","",L13*K13) | N13: =IF($U13="","",Settings!$C$6) | O13: =IF($U13="","",SUMIFS('Per Line'!$N$2:$N$1001,'Per Line'!$A$2:$A$1001,$A13,'Per Line'!$W$2:$W$1001,1)) | P13: =IF($U13="","",O13*N13) | Q13: =IF($U13="","",P13+M13) | R13: =IF($U13="","",S13-Q13) | S13: =IF($U13="","",L13+O13) | T13: =IF($U13="","",S13-Q13-G13) | U13: =IF(ROWS($U$2:$U13)<=MAX('Per Line'!$V$2:$V$1001),MATCH(ROWS($U$2:$U13),'Per Line'!$V$2:$V$1001,0),"")
... A301: =IF($U301="","",INDEX('Per Line'!$A$2:$A$1001,$U301)&"") | C301: =IF($U301="","",INDEX('Per Line'!$B$2:$B$1001,$U301)&"") | D301: =IF($U301="","",INDEX('Per Line'!$C$2:$C$1001,$U301)&"") | E301: =IF($U301="","",INDEX('Per Line'!$D$2:$D$1001,$U301)&"") | F301: =IF($U301="","",INDEX('Per Line'!$E$2:$E$1001,$U301)) | G301: =IF($U301="","",F301*S301/100) | H301: =IF($U301="","",INDEX('Per Line'!$O$2:$O$1001,$U301)&"") | I301: =IF($U301="","",INDEX('Per Line'!$Q$2:$Q$1001,$U301)) | J301: =IF($U301="","",INDEX('Per Line'!$R$2:$R$1001,$U301)&"") | K301: =IF($U301="","",Settings!$C$7) | L301: =IF($U301="","",SUMIFS('Per Line'!$N$2:$N$1001,'Per Line'!$A$2:$A$1001,$A301,'Per Line'!$W$2:$W$1001,0)) | M301: =IF($U301="","",L301*K301) | N301: =IF($U301="","",Settings!$C$6) | O301: =IF($U301="","",SUMIFS('Per Line'!$N$2:$N$1001,'Per Line'!$A$2:$A$1001,$A301,'Per Line'!$W$2:$W$1001,1)) | P301: =IF($U301="","",O301*N301) | Q301: =IF($U301="","",P301+M301) | R301: =IF($U301="","",S301-Q301) | S301: =IF($U301="","",L301+O301) | T301: =IF($U301="","",S301-Q301-G301) | U301: =IF(ROWS($U$2:$U301)<=MAX('Per Line'!$V$2:$V$1001),MATCH(ROWS($U$2:$U301),'Per Line'!$V$2:$V$1001,0),"")
