Workbook

Sheet How To Use
A1: Claims Template - CINNABON (Chronic)
A3: Monthly steps
A4: 1. Open the 'Per Line' tab. Delete the old data in the BLUE columns only (row 2 down). Never delete the green or grey columns.
A5: 2. Paste the new month's data as VALUES starting at A2, into the blue columns: A-N, P-Y, AD-AK (same order as the system export).
A6: 3. Green columns (O, Z, AA, AB, AC) and the grey helper columns (AL-AP) calculate automatically - do not paste over them.
A7: 4. 'Per Invoice' fills itself from 'Per Line' (one row per Order #, split into IMP / Local). No pivot table, no refresh.
A8: 5. The ONLY manual column in 'Per Invoice' is column A 'Invoice' (blue): type it yourself. Everything else is formula.
A9: 6. Open 'Settings' and check STATUS says OK (Per Line totals = Per Invoice totals).
A11: Colour legend
A12: Blue header = typed/pasted by you (raw data, and 'Invoice' in Per Invoice). Green header = formula (do not paste over). Grey header = helper formula (do not touch). Yellow cell (Settings) = editable rate.
A14: Calculation rules (taken from the October 2026 sheet)
A15: Co val = Order Co Payment x Total / 100. Discount = Total x Rebates / 100. Subtotal = Total - Discount. Net = Subtotal - Co val. (Total = 'Product Total')
... A20: Capacity: up to 300 lines and 100 invoices per month. A line with an empty Order # is ignored.

Sheet Settings
B1: Company settings & checks
B3: Insurance Company | C3: CINNABON | D3: Informational only
B4: Corporate | C4: Cinnabon HQ | D4: Informational only
B5: Sheet type | C5: Chronic | D5: Informational only
B6: Local products rebate % | C6: 0.09 | D6: Source: Oct sheet (Rebates = 9 on Local lines).
B7: Imported (IMP) products rebate % | C7: 0.05 | D7: Source: Oct sheet (Rebates = 5 on non-local lines).
B9: Month totals / reconciliation
B10: Lines loaded | C10: =COUNTA('Per Line'!$E$2:$E$301)
B11: Invoices (unique Order #) | C11: =MAX('Per Line'!$AM$2:$AM$301)
B12: Invoices shown in Per Invoice | C12: =SUMPRODUCT(--('Per Invoice'!$B$2:$B$101<>""))
B13: Grand Total - Per Line (Product Total) | C13: =SUM('Per Line'!$W$2:$W$301)
B14: Grand Total - Per Invoice | C14: =SUM('Per Invoice'!$Z$2:$Z$101)
B15: Discount - Per Line | C15: =SUM('Per Line'!$AA$2:$AA$301)
B16: Discount - Per Invoice | C16: =SUM('Per Invoice'!$X$2:$X$101)
B17: Co val - Per Line | C17: =SUM('Per Line'!$O$2:$O$301)
B18: Co val - Per Invoice | C18: =SUM('Per Invoice'!$O$2:$O$101)
B19: Net - Per Line | C19: =SUM('Per Line'!$AC$2:$AC$301)
B20: Net - Per Invoice | C20: =SUM('Per Invoice'!$AA$2:$AA$101)
B21: Max Limit adjustment (Co val, Per Invoice only) | C21: 0 | D21: This company's Per Invoice has no Max Limit rule.
B23: STATUS | C23: =IF(C10=0,"No data loaded",IF(COUNTA('Per Line'!$E:$E)-1>300,"TOO MANY LINES - extend template",IF(C11>100,"TOO MANY INVOICES - extend template",IF(AND(ROUND(C13-C14,2)=0,ROUND(C15-C16,2)=0,ROUND(C17+C21-C18,2)=0,ROUND(C19-C21-C20,2)=0,C11=C12),"OK","CHECK - Per Line and Per Invoice do not match")))) | D23: Must say OK after you paste the month data.

Sheet Per Line
A1: Cycle | B1: Ticket # | C1: Stage | D1: Approval Ref | E1: Order # | F1: Channel | G1: Create At | H1: Insurance Company | I1: Country Portal ID | J1: Corporate | K1: Card | L1: Name | M1: Status | N1: Order Co Payment | O1: Co val | P1: By Patient | Q1: heisenberg id | R1: Product Name | S1: Local | T1: Unit | U1: Quantity | V1: Unit Price | W1: Product Total | X1: ERX ID | Y1: Special Rebates? | Z1: Rebates | AA1: Discount | AB1: Subtotal | AC1: Net | AD1: Approval Type | AE1: Max Limit | AF1: Exceeding Limit | AG1: Amount collected from customer | AH1: By Patient (Delivered) | AI1: Dispense Number | AJ1: Dispense Date | AK1: Has OTP? | AL1: Order 1st Row (helper) | AM1: Invoice # (helper) | AN1: Is Local (helper) | AO1: Is Special (helper) | AP1: Sort Key (helper)
O2: =IF($E2="","",N2*W2/100) | Z2: =IF($E2="","",IF($AO2=1,0,IF($AN2=1,Settings!$C$6,Settings!$C$7))*100) | AA2: =IF($E2="","",W2*Z2/100) | AB2: =IF($E2="","",W2-AA2) | AC2: =IF($E2="","",AB2-O2) | AL2: =IF($E2="","",IF(COUNTIF($E$2:$E2,$E2)=1,1,0)) | AM2: =IF($AL2=1,SUMPRODUCT(--($AP$2:$AP$301<$AP2))+1,"") | AN2: =IF($E2="","",IF(OR($S2=TRUE(),$S2="TRUE"),1,0)) | AO2: =IF($E2="","",IF($Y2="Yes",1,0)) | AP2: =IF($AL2=1,IFERROR(IF(VALUE($E2)<100000000,VALUE($E2),1000000000),IFERROR(IF(VALUE(MID($E2,2,20))<100000000,VALUE(MID($E2,2,20)),1000000000),1000000000))+ROW()/100000,"")
O3: =IF($E3="","",N3*W3/100) | Z3: =IF($E3="","",IF($AO3=1,0,IF($AN3=1,Settings!$C$6,Settings!$C$7))*100) | AA3: =IF($E3="","",W3*Z3/100) | AB3: =IF($E3="","",W3-AA3) | AC3: =IF($E3="","",AB3-O3) | AL3: =IF($E3="","",IF(COUNTIF($E$2:$E3,$E3)=1,1,0)) | AM3: =IF($AL3=1,SUMPRODUCT(--($AP$2:$AP$301<$AP3))+1,"") | AN3: =IF($E3="","",IF(OR($S3=TRUE(),$S3="TRUE"),1,0)) | AO3: =IF($E3="","",IF($Y3="Yes",1,0)) | AP3: =IF($AL3=1,IFERROR(IF(VALUE($E3)<100000000,VALUE($E3),1000000000),IFERROR(IF(VALUE(MID($E3,2,20))<100000000,VALUE(MID($E3,2,20)),1000000000),1000000000))+ROW()/100000,"")
O4: =IF($E4="","",N4*W4/100) | Z4: =IF($E4="","",IF($AO4=1,0,IF($AN4=1,Settings!$C$6,Settings!$C$7))*100) | AA4: =IF($E4="","",W4*Z4/100) | AB4: =IF($E4="","",W4-AA4) | AC4: =IF($E4="","",AB4-O4) | AL4: =IF($E4="","",IF(COUNTIF($E$2:$E4,$E4)=1,1,0)) | AM4: =IF($AL4=1,SUMPRODUCT(--($AP$2:$AP$301<$AP4))+1,"") | AN4: =IF($E4="","",IF(OR($S4=TRUE(),$S4="TRUE"),1,0)) | AO4: =IF($E4="","",IF($Y4="Yes",1,0)) | AP4: =IF($AL4=1,IFERROR(IF(VALUE($E4)<100000000,VALUE($E4),1000000000),IFERROR(IF(VALUE(MID($E4,2,20))<100000000,VALUE(MID($E4,2,20)),1000000000),1000000000))+ROW()/100000,"")
O5: =IF($E5="","",N5*W5/100) | Z5: =IF($E5="","",IF($AO5=1,0,IF($AN5=1,Settings!$C$6,Settings!$C$7))*100) | AA5: =IF($E5="","",W5*Z5/100) | AB5: =IF($E5="","",W5-AA5) | AC5: =IF($E5="","",AB5-O5) | AL5: =IF($E5="","",IF(COUNTIF($E$2:$E5,$E5)=1,1,0)) | AM5: =IF($AL5=1,SUMPRODUCT(--($AP$2:$AP$301<$AP5))+1,"") | AN5: =IF($E5="","",IF(OR($S5=TRUE(),$S5="TRUE"),1,0)) | AO5: =IF($E5="","",IF($Y5="Yes",1,0)) | AP5: =IF($AL5=1,IFERROR(IF(VALUE($E5)<100000000,VALUE($E5),1000000000),IFERROR(IF(VALUE(MID($E5,2,20))<100000000,VALUE(MID($E5,2,20)),1000000000),1000000000))+ROW()/100000,"")
O6: =IF($E6="","",N6*W6/100) | Z6: =IF($E6="","",IF($AO6=1,0,IF($AN6=1,Settings!$C$6,Settings!$C$7))*100) | AA6: =IF($E6="","",W6*Z6/100) | AB6: =IF($E6="","",W6-AA6) | AC6: =IF($E6="","",AB6-O6) | AL6: =IF($E6="","",IF(COUNTIF($E$2:$E6,$E6)=1,1,0)) | AM6: =IF($AL6=1,SUMPRODUCT(--($AP$2:$AP$301<$AP6))+1,"") | AN6: =IF($E6="","",IF(OR($S6=TRUE(),$S6="TRUE"),1,0)) | AO6: =IF($E6="","",IF($Y6="Yes",1,0)) | AP6: =IF($AL6=1,IFERROR(IF(VALUE($E6)<100000000,VALUE($E6),1000000000),IFERROR(IF(VALUE(MID($E6,2,20))<100000000,VALUE(MID($E6,2,20)),1000000000),1000000000))+ROW()/100000,"")
O7: =IF($E7="","",N7*W7/100) | Z7: =IF($E7="","",IF($AO7=1,0,IF($AN7=1,Settings!$C$6,Settings!$C$7))*100) | AA7: =IF($E7="","",W7*Z7/100) | AB7: =IF($E7="","",W7-AA7) | AC7: =IF($E7="","",AB7-O7) | AL7: =IF($E7="","",IF(COUNTIF($E$2:$E7,$E7)=1,1,0)) | AM7: =IF($AL7=1,SUMPRODUCT(--($AP$2:$AP$301<$AP7))+1,"") | AN7: =IF($E7="","",IF(OR($S7=TRUE(),$S7="TRUE"),1,0)) | AO7: =IF($E7="","",IF($Y7="Yes",1,0)) | AP7: =IF($AL7=1,IFERROR(IF(VALUE($E7)<100000000,VALUE($E7),1000000000),IFERROR(IF(VALUE(MID($E7,2,20))<100000000,VALUE(MID($E7,2,20)),1000000000),1000000000))+ROW()/100000,"")
O8: =IF($E8="","",N8*W8/100) | Z8: =IF($E8="","",IF($AO8=1,0,IF($AN8=1,Settings!$C$6,Settings!$C$7))*100) | AA8: =IF($E8="","",W8*Z8/100) | AB8: =IF($E8="","",W8-AA8) | AC8: =IF($E8="","",AB8-O8) | AL8: =IF($E8="","",IF(COUNTIF($E$2:$E8,$E8)=1,1,0)) | AM8: =IF($AL8=1,SUMPRODUCT(--($AP$2:$AP$301<$AP8))+1,"") | AN8: =IF($E8="","",IF(OR($S8=TRUE(),$S8="TRUE"),1,0)) | AO8: =IF($E8="","",IF($Y8="Yes",1,0)) | AP8: =IF($AL8=1,IFERROR(IF(VALUE($E8)<100000000,VALUE($E8),1000000000),IFERROR(IF(VALUE(MID($E8,2,20))<100000000,VALUE(MID($E8,2,20)),1000000000),1000000000))+ROW()/100000,"")
O9: =IF($E9="","",N9*W9/100) | Z9: =IF($E9="","",IF($AO9=1,0,IF($AN9=1,Settings!$C$6,Settings!$C$7))*100) | AA9: =IF($E9="","",W9*Z9/100) | AB9: =IF($E9="","",W9-AA9) | AC9: =IF($E9="","",AB9-O9) | AL9: =IF($E9="","",IF(COUNTIF($E$2:$E9,$E9)=1,1,0)) | AM9: =IF($AL9=1,SUMPRODUCT(--($AP$2:$AP$301<$AP9))+1,"") | AN9: =IF($E9="","",IF(OR($S9=TRUE(),$S9="TRUE"),1,0)) | AO9: =IF($E9="","",IF($Y9="Yes",1,0)) | AP9: =IF($AL9=1,IFERROR(IF(VALUE($E9)<100000000,VALUE($E9),1000000000),IFERROR(IF(VALUE(MID($E9,2,20))<100000000,VALUE(MID($E9,2,20)),1000000000),1000000000))+ROW()/100000,"")
O10: =IF($E10="","",N10*W10/100) | Z10: =IF($E10="","",IF($AO10=1,0,IF($AN10=1,Settings!$C$6,Settings!$C$7))*100) | AA10: =IF($E10="","",W10*Z10/100) | AB10: =IF($E10="","",W10-AA10) | AC10: =IF($E10="","",AB10-O10) | AL10: =IF($E10="","",IF(COUNTIF($E$2:$E10,$E10)=1,1,0)) | AM10: =IF($AL10=1,SUMPRODUCT(--($AP$2:$AP$301<$AP10))+1,"") | AN10: =IF($E10="","",IF(OR($S10=TRUE(),$S10="TRUE"),1,0)) | AO10: =IF($E10="","",IF($Y10="Yes",1,0)) | AP10: =IF($AL10=1,IFERROR(IF(VALUE($E10)<100000000,VALUE($E10),1000000000),IFERROR(IF(VALUE(MID($E10,2,20))<100000000,VALUE(MID($E10,2,20)),1000000000),1000000000))+ROW()/100000,"")
O11: =IF($E11="","",N11*W11/100) | Z11: =IF($E11="","",IF($AO11=1,0,IF($AN11=1,Settings!$C$6,Settings!$C$7))*100) | AA11: =IF($E11="","",W11*Z11/100) | AB11: =IF($E11="","",W11-AA11) | AC11: =IF($E11="","",AB11-O11) | AL11: =IF($E11="","",IF(COUNTIF($E$2:$E11,$E11)=1,1,0)) | AM11: =IF($AL11=1,SUMPRODUCT(--($AP$2:$AP$301<$AP11))+1,"") | AN11: =IF($E11="","",IF(OR($S11=TRUE(),$S11="TRUE"),1,0)) | AO11: =IF($E11="","",IF($Y11="Yes",1,0)) | AP11: =IF($AL11=1,IFERROR(IF(VALUE($E11)<100000000,VALUE($E11),1000000000),IFERROR(IF(VALUE(MID($E11,2,20))<100000000,VALUE(MID($E11,2,20)),1000000000),1000000000))+ROW()/100000,"")
O12: =IF($E12="","",N12*W12/100) | Z12: =IF($E12="","",IF($AO12=1,0,IF($AN12=1,Settings!$C$6,Settings!$C$7))*100) | AA12: =IF($E12="","",W12*Z12/100) | AB12: =IF($E12="","",W12-AA12) | AC12: =IF($E12="","",AB12-O12) | AL12: =IF($E12="","",IF(COUNTIF($E$2:$E12,$E12)=1,1,0)) | AM12: =IF($AL12=1,SUMPRODUCT(--($AP$2:$AP$301<$AP12))+1,"") | AN12: =IF($E12="","",IF(OR($S12=TRUE(),$S12="TRUE"),1,0)) | AO12: =IF($E12="","",IF($Y12="Yes",1,0)) | AP12: =IF($AL12=1,IFERROR(IF(VALUE($E12)<100000000,VALUE($E12),1000000000),IFERROR(IF(VALUE(MID($E12,2,20))<100000000,VALUE(MID($E12,2,20)),1000000000),1000000000))+ROW()/100000,"")
O13: =IF($E13="","",N13*W13/100) | Z13: =IF($E13="","",IF($AO13=1,0,IF($AN13=1,Settings!$C$6,Settings!$C$7))*100) | AA13: =IF($E13="","",W13*Z13/100) | AB13: =IF($E13="","",W13-AA13) | AC13: =IF($E13="","",AB13-O13) | AL13: =IF($E13="","",IF(COUNTIF($E$2:$E13,$E13)=1,1,0)) | AM13: =IF($AL13=1,SUMPRODUCT(--($AP$2:$AP$301<$AP13))+1,"") | AN13: =IF($E13="","",IF(OR($S13=TRUE(),$S13="TRUE"),1,0)) | AO13: =IF($E13="","",IF($Y13="Yes",1,0)) | AP13: =IF($AL13=1,IFERROR(IF(VALUE($E13)<100000000,VALUE($E13),1000000000),IFERROR(IF(VALUE(MID($E13,2,20))<100000000,VALUE(MID($E13,2,20)),1000000000),1000000000))+ROW()/100000,"")
... O301: =IF($E301="","",N301*W301/100) | Z301: =IF($E301="","",IF($AO301=1,0,IF($AN301=1,Settings!$C$6,Settings!$C$7))*100) | AA301: =IF($E301="","",W301*Z301/100) | AB301: =IF($E301="","",W301-AA301) | AC301: =IF($E301="","",AB301-O301) | AL301: =IF($E301="","",IF(COUNTIF($E$2:$E301,$E301)=1,1,0)) | AM301: =IF($AL301=1,SUMPRODUCT(--($AP$2:$AP$301<$AP301))+1,"") | AN301: =IF($E301="","",IF(OR($S301=TRUE(),$S301="TRUE"),1,0)) | AO301: =IF($E301="","",IF($Y301="Yes",1,0)) | AP301: =IF($AL301=1,IFERROR(IF(VALUE($E301)<100000000,VALUE($E301),1000000000),IFERROR(IF(VALUE(MID($E301,2,20))<100000000,VALUE(MID($E301,2,20)),1000000000),1000000000))+ROW()/100000,"")

Sheet Per Invoice
A1: Invoice | B1: Order # | C1: Cycle | D1: Ticket # | E1: Stage | F1: Approval Ref | G1: Channel | H1: Create At | I1: Insurance Company | J1: Corporate | K1: Card | L1: Name | M1: Status | N1: Order Co Payment | O1: Co val | P1: ERX ID | Q1: Special | R1: IMP % | S1: IMP | T1: IMP VAL | U1: LOCAL % | V1: LOCAL | W1: LOCAL VAL | X1: TOTAL VAL | Y1: SUBTOTAL | Z1: Grand Total | AA1: NET | AB1: Src Row (helper)
B2: =IF($AB2="","",INDEX('Per Line'!$E$2:$E$301,$AB2)&"") | C2: =IF($AB2="","",INDEX('Per Line'!$A$2:$A$301,$AB2)&"") | D2: =IF($AB2="","",INDEX('Per Line'!$B$2:$B$301,$AB2)) | E2: =IF($AB2="","",INDEX('Per Line'!$C$2:$C$301,$AB2)&"") | F2: =IF($AB2="","",INDEX('Per Line'!$D$2:$D$301,$AB2)&"") | G2: =IF($AB2="","",INDEX('Per Line'!$F$2:$F$301,$AB2)&"") | H2: =IF($AB2="","",INDEX('Per Line'!$G$2:$G$301,$AB2)) | I2: =IF($AB2="","",INDEX('Per Line'!$H$2:$H$301,$AB2)&"") | J2: =IF($AB2="","",INDEX('Per Line'!$J$2:$J$301,$AB2)&"") | K2: =IF($AB2="","",INDEX('Per Line'!$K$2:$K$301,$AB2)&"") | L2: =IF($AB2="","",INDEX('Per Line'!$L$2:$L$301,$AB2)&"") | M2: =IF($AB2="","",INDEX('Per Line'!$M$2:$M$301,$AB2)&"") | N2: =IF($AB2="","",INDEX('Per Line'!$N$2:$N$301,$AB2)) | O2: =IF($AB2="","",N2*Z2/100) | P2: =IF($AB2="","",INDEX('Per Line'!$X$2:$X$301,$AB2)&"") | Q2: =IF($AB2="","",SUMIFS('Per Line'!$W$2:$W$301,'Per Line'!$E$2:$E$301,$B2,'Per Line'!$AO$2:$AO$301,1)) | R2: =IF($AB2="","",Settings!$C$7) | S2: =IF($AB2="","",SUMIFS('Per Line'!$W$2:$W$301,'Per Line'!$E$2:$E$301,$B2,'Per Line'!$AN$2:$AN$301,0,'Per Line'!$AO$2:$AO$301,0)) | T2: =IF($AB2="","",S2*R2) | U2: =IF($AB2="","",Settings!$C$6) | V2: =IF($AB2="","",SUMIFS('Per Line'!$W$2:$W$301,'Per Line'!$E$2:$E$301,$B2,'Per Line'!$AN$2:$AN$301,1,'Per Line'!$AO$2:$AO$301,0)) | W2: =IF($AB2="","",V2*U2) | X2: =IF($AB2="","",W2+T2) | Y2: =IF($AB2="","",Z2-X2) | Z2: =IF($AB2="","",S2+V2+Q2) | AA2: =IF($AB2="","",Z2-X2-O2) | AB2: =IF(ROWS($AB$2:$AB2)<=MAX('Per Line'!$AM$2:$AM$301),MATCH(ROWS($AB$2:$AB2),'Per Line'!$AM$2:$AM$301,0),"")
B3: =IF($AB3="","",INDEX('Per Line'!$E$2:$E$301,$AB3)&"") | C3: =IF($AB3="","",INDEX('Per Line'!$A$2:$A$301,$AB3)&"") | D3: =IF($AB3="","",INDEX('Per Line'!$B$2:$B$301,$AB3)) | E3: =IF($AB3="","",INDEX('Per Line'!$C$2:$C$301,$AB3)&"") | F3: =IF($AB3="","",INDEX('Per Line'!$D$2:$D$301,$AB3)&"") | G3: =IF($AB3="","",INDEX('Per Line'!$F$2:$F$301,$AB3)&"") | H3: =IF($AB3="","",INDEX('Per Line'!$G$2:$G$301,$AB3)) | I3: =IF($AB3="","",INDEX('Per Line'!$H$2:$H$301,$AB3)&"") | J3: =IF($AB3="","",INDEX('Per Line'!$J$2:$J$301,$AB3)&"") | K3: =IF($AB3="","",INDEX('Per Line'!$K$2:$K$301,$AB3)&"") | L3: =IF($AB3="","",INDEX('Per Line'!$L$2:$L$301,$AB3)&"") | M3: =IF($AB3="","",INDEX('Per Line'!$M$2:$M$301,$AB3)&"") | N3: =IF($AB3="","",INDEX('Per Line'!$N$2:$N$301,$AB3)) | O3: =IF($AB3="","",N3*Z3/100) | P3: =IF($AB3="","",INDEX('Per Line'!$X$2:$X$301,$AB3)&"") | Q3: =IF($AB3="","",SUMIFS('Per Line'!$W$2:$W$301,'Per Line'!$E$2:$E$301,$B3,'Per Line'!$AO$2:$AO$301,1)) | R3: =IF($AB3="","",Settings!$C$7) | S3: =IF($AB3="","",SUMIFS('Per Line'!$W$2:$W$301,'Per Line'!$E$2:$E$301,$B3,'Per Line'!$AN$2:$AN$301,0,'Per Line'!$AO$2:$AO$301,0)) | T3: =IF($AB3="","",S3*R3) | U3: =IF($AB3="","",Settings!$C$6) | V3: =IF($AB3="","",SUMIFS('Per Line'!$W$2:$W$301,'Per Line'!$E$2:$E$301,$B3,'Per Line'!$AN$2:$AN$301,1,'Per Line'!$AO$2:$AO$301,0)) | W3: =IF($AB3="","",V3*U3) | X3: =IF($AB3="","",W3+T3) | Y3: =IF($AB3="","",Z3-X3) | Z3: =IF($AB3="","",S3+V3+Q3) | AA3: =IF($AB3="","",Z3-X3-O3) | AB3: =IF(ROWS($AB$2:$AB3)<=MAX('Per Line'!$AM$2:$AM$301),MATCH(ROWS($AB$2:$AB3),'Per Line'!$AM$2:$AM$301,0),"")
B4: =IF($AB4="","",INDEX('Per Line'!$E$2:$E$301,$AB4)&"") | C4: =IF($AB4="","",INDEX('Per Line'!$A$2:$A$301,$AB4)&"") | D4: =IF($AB4="","",INDEX('Per Line'!$B$2:$B$301,$AB4)) | E4: =IF($AB4="","",INDEX('Per Line'!$C$2:$C$301,$AB4)&"") | F4: =IF($AB4="","",INDEX('Per Line'!$D$2:$D$301,$AB4)&"") | G4: =IF($AB4="","",INDEX('Per Line'!$F$2:$F$301,$AB4)&"") | H4: =IF($AB4="","",INDEX('Per Line'!$G$2:$G$301,$AB4)) | I4: =IF($AB4="","",INDEX('Per Line'!$H$2:$H$301,$AB4)&"") | J4: =IF($AB4="","",INDEX('Per Line'!$J$2:$J$301,$AB4)&"") | K4: =IF($AB4="","",INDEX('Per Line'!$K$2:$K$301,$AB4)&"") | L4: =IF($AB4="","",INDEX('Per Line'!$L$2:$L$301,$AB4)&"") | M4: =IF($AB4="","",INDEX('Per Line'!$M$2:$M$301,$AB4)&"") | N4: =IF($AB4="","",INDEX('Per Line'!$N$2:$N$301,$AB4)) | O4: =IF($AB4="","",N4*Z4/100) | P4: =IF($AB4="","",INDEX('Per Line'!$X$2:$X$301,$AB4)&"") | Q4: =IF($AB4="","",SUMIFS('Per Line'!$W$2:$W$301,'Per Line'!$E$2:$E$301,$B4,'Per Line'!$AO$2:$AO$301,1)) | R4: =IF($AB4="","",Settings!$C$7) | S4: =IF($AB4="","",SUMIFS('Per Line'!$W$2:$W$301,'Per Line'!$E$2:$E$301,$B4,'Per Line'!$AN$2:$AN$301,0,'Per Line'!$AO$2:$AO$301,0)) | T4: =IF($AB4="","",S4*R4) | U4: =IF($AB4="","",Settings!$C$6) | V4: =IF($AB4="","",SUMIFS('Per Line'!$W$2:$W$301,'Per Line'!$E$2:$E$301,$B4,'Per Line'!$AN$2:$AN$301,1,'Per Line'!$AO$2:$AO$301,0)) | W4: =IF($AB4="","",V4*U4) | X4: =IF($AB4="","",W4+T4) | Y4: =IF($AB4="","",Z4-X4) | Z4: =IF($AB4="","",S4+V4+Q4) | AA4: =IF($AB4="","",Z4-X4-O4) | AB4: =IF(ROWS($AB$2:$AB4)<=MAX('Per Line'!$AM$2:$AM$301),MATCH(ROWS($AB$2:$AB4),'Per Line'!$AM$2:$AM$301,0),"")
B5: =IF($AB5="","",INDEX('Per Line'!$E$2:$E$301,$AB5)&"") | C5: =IF($AB5="","",INDEX('Per Line'!$A$2:$A$301,$AB5)&"") | D5: =IF($AB5="","",INDEX('Per Line'!$B$2:$B$301,$AB5)) | E5: =IF($AB5="","",INDEX('Per Line'!$C$2:$C$301,$AB5)&"") | F5: =IF($AB5="","",INDEX('Per Line'!$D$2:$D$301,$AB5)&"") | G5: =IF($AB5="","",INDEX('Per Line'!$F$2:$F$301,$AB5)&"") | H5: =IF($AB5="","",INDEX('Per Line'!$G$2:$G$301,$AB5)) | I5: =IF($AB5="","",INDEX('Per Line'!$H$2:$H$301,$AB5)&"") | J5: =IF($AB5="","",INDEX('Per Line'!$J$2:$J$301,$AB5)&"") | K5: =IF($AB5="","",INDEX('Per Line'!$K$2:$K$301,$AB5)&"") | L5: =IF($AB5="","",INDEX('Per Line'!$L$2:$L$301,$AB5)&"") | M5: =IF($AB5="","",INDEX('Per Line'!$M$2:$M$301,$AB5)&"") | N5: =IF($AB5="","",INDEX('Per Line'!$N$2:$N$301,$AB5)) | O5: =IF($AB5="","",N5*Z5/100) | P5: =IF($AB5="","",INDEX('Per Line'!$X$2:$X$301,$AB5)&"") | Q5: =IF($AB5="","",SUMIFS('Per Line'!$W$2:$W$301,'Per Line'!$E$2:$E$301,$B5,'Per Line'!$AO$2:$AO$301,1)) | R5: =IF($AB5="","",Settings!$C$7) | S5: =IF($AB5="","",SUMIFS('Per Line'!$W$2:$W$301,'Per Line'!$E$2:$E$301,$B5,'Per Line'!$AN$2:$AN$301,0,'Per Line'!$AO$2:$AO$301,0)) | T5: =IF($AB5="","",S5*R5) | U5: =IF($AB5="","",Settings!$C$6) | V5: =IF($AB5="","",SUMIFS('Per Line'!$W$2:$W$301,'Per Line'!$E$2:$E$301,$B5,'Per Line'!$AN$2:$AN$301,1,'Per Line'!$AO$2:$AO$301,0)) | W5: =IF($AB5="","",V5*U5) | X5: =IF($AB5="","",W5+T5) | Y5: =IF($AB5="","",Z5-X5) | Z5: =IF($AB5="","",S5+V5+Q5) | AA5: =IF($AB5="","",Z5-X5-O5) | AB5: =IF(ROWS($AB$2:$AB5)<=MAX('Per Line'!$AM$2:$AM$301),MATCH(ROWS($AB$2:$AB5),'Per Line'!$AM$2:$AM$301,0),"")
B6: =IF($AB6="","",INDEX('Per Line'!$E$2:$E$301,$AB6)&"") | C6: =IF($AB6="","",INDEX('Per Line'!$A$2:$A$301,$AB6)&"") | D6: =IF($AB6="","",INDEX('Per Line'!$B$2:$B$301,$AB6)) | E6: =IF($AB6="","",INDEX('Per Line'!$C$2:$C$301,$AB6)&"") | F6: =IF($AB6="","",INDEX('Per Line'!$D$2:$D$301,$AB6)&"") | G6: =IF($AB6="","",INDEX('Per Line'!$F$2:$F$301,$AB6)&"") | H6: =IF($AB6="","",INDEX('Per Line'!$G$2:$G$301,$AB6)) | I6: =IF($AB6="","",INDEX('Per Line'!$H$2:$H$301,$AB6)&"") | J6: =IF($AB6="","",INDEX('Per Line'!$J$2:$J$301,$AB6)&"") | K6: =IF($AB6="","",INDEX('Per Line'!$K$2:$K$301,$AB6)&"") | L6: =IF($AB6="","",INDEX('Per Line'!$L$2:$L$301,$AB6)&"") | M6: =IF($AB6="","",INDEX('Per Line'!$M$2:$M$301,$AB6)&"") | N6: =IF($AB6="","",INDEX('Per Line'!$N$2:$N$301,$AB6)) | O6: =IF($AB6="","",N6*Z6/100) | P6: =IF($AB6="","",INDEX('Per Line'!$X$2:$X$301,$AB6)&"") | Q6: =IF($AB6="","",SUMIFS('Per Line'!$W$2:$W$301,'Per Line'!$E$2:$E$301,$B6,'Per Line'!$AO$2:$AO$301,1)) | R6: =IF($AB6="","",Settings!$C$7) | S6: =IF($AB6="","",SUMIFS('Per Line'!$W$2:$W$301,'Per Line'!$E$2:$E$301,$B6,'Per Line'!$AN$2:$AN$301,0,'Per Line'!$AO$2:$AO$301,0)) | T6: =IF($AB6="","",S6*R6) | U6: =IF($AB6="","",Settings!$C$6) | V6: =IF($AB6="","",SUMIFS('Per Line'!$W$2:$W$301,'Per Line'!$E$2:$E$301,$B6,'Per Line'!$AN$2:$AN$301,1,'Per Line'!$AO$2:$AO$301,0)) | W6: =IF($AB6="","",V6*U6) | X6: =IF($AB6="","",W6+T6) | Y6: =IF($AB6="","",Z6-X6) | Z6: =IF($AB6="","",S6+V6+Q6) | AA6: =IF($AB6="","",Z6-X6-O6) | AB6: =IF(ROWS($AB$2:$AB6)<=MAX('Per Line'!$AM$2:$AM$301),MATCH(ROWS($AB$2:$AB6),'Per Line'!$AM$2:$AM$301,0),"")
B7: =IF($AB7="","",INDEX('Per Line'!$E$2:$E$301,$AB7)&"") | C7: =IF($AB7="","",INDEX('Per Line'!$A$2:$A$301,$AB7)&"") | D7: =IF($AB7="","",INDEX('Per Line'!$B$2:$B$301,$AB7)) | E7: =IF($AB7="","",INDEX('Per Line'!$C$2:$C$301,$AB7)&"") | F7: =IF($AB7="","",INDEX('Per Line'!$D$2:$D$301,$AB7)&"") | G7: =IF($AB7="","",INDEX('Per Line'!$F$2:$F$301,$AB7)&"") | H7: =IF($AB7="","",INDEX('Per Line'!$G$2:$G$301,$AB7)) | I7: =IF($AB7="","",INDEX('Per Line'!$H$2:$H$301,$AB7)&"") | J7: =IF($AB7="","",INDEX('Per Line'!$J$2:$J$301,$AB7)&"") | K7: =IF($AB7="","",INDEX('Per Line'!$K$2:$K$301,$AB7)&"") | L7: =IF($AB7="","",INDEX('Per Line'!$L$2:$L$301,$AB7)&"") | M7: =IF($AB7="","",INDEX('Per Line'!$M$2:$M$301,$AB7)&"") | N7: =IF($AB7="","",INDEX('Per Line'!$N$2:$N$301,$AB7)) | O7: =IF($AB7="","",N7*Z7/100) | P7: =IF($AB7="","",INDEX('Per Line'!$X$2:$X$301,$AB7)&"") | Q7: =IF($AB7="","",SUMIFS('Per Line'!$W$2:$W$301,'Per Line'!$E$2:$E$301,$B7,'Per Line'!$AO$2:$AO$301,1)) | R7: =IF($AB7="","",Settings!$C$7) | S7: =IF($AB7="","",SUMIFS('Per Line'!$W$2:$W$301,'Per Line'!$E$2:$E$301,$B7,'Per Line'!$AN$2:$AN$301,0,'Per Line'!$AO$2:$AO$301,0)) | T7: =IF($AB7="","",S7*R7) | U7: =IF($AB7="","",Settings!$C$6) | V7: =IF($AB7="","",SUMIFS('Per Line'!$W$2:$W$301,'Per Line'!$E$2:$E$301,$B7,'Per Line'!$AN$2:$AN$301,1,'Per Line'!$AO$2:$AO$301,0)) | W7: =IF($AB7="","",V7*U7) | X7: =IF($AB7="","",W7+T7) | Y7: =IF($AB7="","",Z7-X7) | Z7: =IF($AB7="","",S7+V7+Q7) | AA7: =IF($AB7="","",Z7-X7-O7) | AB7: =IF(ROWS($AB$2:$AB7)<=MAX('Per Line'!$AM$2:$AM$301),MATCH(ROWS($AB$2:$AB7),'Per Line'!$AM$2:$AM$301,0),"")
B8: =IF($AB8="","",INDEX('Per Line'!$E$2:$E$301,$AB8)&"") | C8: =IF($AB8="","",INDEX('Per Line'!$A$2:$A$301,$AB8)&"") | D8: =IF($AB8="","",INDEX('Per Line'!$B$2:$B$301,$AB8)) | E8: =IF($AB8="","",INDEX('Per Line'!$C$2:$C$301,$AB8)&"") | F8: =IF($AB8="","",INDEX('Per Line'!$D$2:$D$301,$AB8)&"") | G8: =IF($AB8="","",INDEX('Per Line'!$F$2:$F$301,$AB8)&"") | H8: =IF($AB8="","",INDEX('Per Line'!$G$2:$G$301,$AB8)) | I8: =IF($AB8="","",INDEX('Per Line'!$H$2:$H$301,$AB8)&"") | J8: =IF($AB8="","",INDEX('Per Line'!$J$2:$J$301,$AB8)&"") | K8: =IF($AB8="","",INDEX('Per Line'!$K$2:$K$301,$AB8)&"") | L8: =IF($AB8="","",INDEX('Per Line'!$L$2:$L$301,$AB8)&"") | M8: =IF($AB8="","",INDEX('Per Line'!$M$2:$M$301,$AB8)&"") | N8: =IF($AB8="","",INDEX('Per Line'!$N$2:$N$301,$AB8)) | O8: =IF($AB8="","",N8*Z8/100) | P8: =IF($AB8="","",INDEX('Per Line'!$X$2:$X$301,$AB8)&"") | Q8: =IF($AB8="","",SUMIFS('Per Line'!$W$2:$W$301,'Per Line'!$E$2:$E$301,$B8,'Per Line'!$AO$2:$AO$301,1)) | R8: =IF($AB8="","",Settings!$C$7) | S8: =IF($AB8="","",SUMIFS('Per Line'!$W$2:$W$301,'Per Line'!$E$2:$E$301,$B8,'Per Line'!$AN$2:$AN$301,0,'Per Line'!$AO$2:$AO$301,0)) | T8: =IF($AB8="","",S8*R8) | U8: =IF($AB8="","",Settings!$C$6) | V8: =IF($AB8="","",SUMIFS('Per Line'!$W$2:$W$301,'Per Line'!$E$2:$E$301,$B8,'Per Line'!$AN$2:$AN$301,1,'Per Line'!$AO$2:$AO$301,0)) | W8: =IF($AB8="","",V8*U8) | X8: =IF($AB8="","",W8+T8) | Y8: =IF($AB8="","",Z8-X8) | Z8: =IF($AB8="","",S8+V8+Q8) | AA8: =IF($AB8="","",Z8-X8-O8) | AB8: =IF(ROWS($AB$2:$AB8)<=MAX('Per Line'!$AM$2:$AM$301),MATCH(ROWS($AB$2:$AB8),'Per Line'!$AM$2:$AM$301,0),"")
B9: =IF($AB9="","",INDEX('Per Line'!$E$2:$E$301,$AB9)&"") | C9: =IF($AB9="","",INDEX('Per Line'!$A$2:$A$301,$AB9)&"") | D9: =IF($AB9="","",INDEX('Per Line'!$B$2:$B$301,$AB9)) | E9: =IF($AB9="","",INDEX('Per Line'!$C$2:$C$301,$AB9)&"") | F9: =IF($AB9="","",INDEX('Per Line'!$D$2:$D$301,$AB9)&"") | G9: =IF($AB9="","",INDEX('Per Line'!$F$2:$F$301,$AB9)&"") | H9: =IF($AB9="","",INDEX('Per Line'!$G$2:$G$301,$AB9)) | I9: =IF($AB9="","",INDEX('Per Line'!$H$2:$H$301,$AB9)&"") | J9: =IF($AB9="","",INDEX('Per Line'!$J$2:$J$301,$AB9)&"") | K9: =IF($AB9="","",INDEX('Per Line'!$K$2:$K$301,$AB9)&"") | L9: =IF($AB9="","",INDEX('Per Line'!$L$2:$L$301,$AB9)&"") | M9: =IF($AB9="","",INDEX('Per Line'!$M$2:$M$301,$AB9)&"") | N9: =IF($AB9="","",INDEX('Per Line'!$N$2:$N$301,$AB9)) | O9: =IF($AB9="","",N9*Z9/100) | P9: =IF($AB9="","",INDEX('Per Line'!$X$2:$X$301,$AB9)&"") | Q9: =IF($AB9="","",SUMIFS('Per Line'!$W$2:$W$301,'Per Line'!$E$2:$E$301,$B9,'Per Line'!$AO$2:$AO$301,1)) | R9: =IF($AB9="","",Settings!$C$7) | S9: =IF($AB9="","",SUMIFS('Per Line'!$W$2:$W$301,'Per Line'!$E$2:$E$301,$B9,'Per Line'!$AN$2:$AN$301,0,'Per Line'!$AO$2:$AO$301,0)) | T9: =IF($AB9="","",S9*R9) | U9: =IF($AB9="","",Settings!$C$6) | V9: =IF($AB9="","",SUMIFS('Per Line'!$W$2:$W$301,'Per Line'!$E$2:$E$301,$B9,'Per Line'!$AN$2:$AN$301,1,'Per Line'!$AO$2:$AO$301,0)) | W9: =IF($AB9="","",V9*U9) | X9: =IF($AB9="","",W9+T9) | Y9: =IF($AB9="","",Z9-X9) | Z9: =IF($AB9="","",S9+V9+Q9) | AA9: =IF($AB9="","",Z9-X9-O9) | AB9: =IF(ROWS($AB$2:$AB9)<=MAX('Per Line'!$AM$2:$AM$301),MATCH(ROWS($AB$2:$AB9),'Per Line'!$AM$2:$AM$301,0),"")
B10: =IF($AB10="","",INDEX('Per Line'!$E$2:$E$301,$AB10)&"") | C10: =IF($AB10="","",INDEX('Per Line'!$A$2:$A$301,$AB10)&"") | D10: =IF($AB10="","",INDEX('Per Line'!$B$2:$B$301,$AB10)) | E10: =IF($AB10="","",INDEX('Per Line'!$C$2:$C$301,$AB10)&"") | F10: =IF($AB10="","",INDEX('Per Line'!$D$2:$D$301,$AB10)&"") | G10: =IF($AB10="","",INDEX('Per Line'!$F$2:$F$301,$AB10)&"") | H10: =IF($AB10="","",INDEX('Per Line'!$G$2:$G$301,$AB10)) | I10: =IF($AB10="","",INDEX('Per Line'!$H$2:$H$301,$AB10)&"") | J10: =IF($AB10="","",INDEX('Per Line'!$J$2:$J$301,$AB10)&"") | K10: =IF($AB10="","",INDEX('Per Line'!$K$2:$K$301,$AB10)&"") | L10: =IF($AB10="","",INDEX('Per Line'!$L$2:$L$301,$AB10)&"") | M10: =IF($AB10="","",INDEX('Per Line'!$M$2:$M$301,$AB10)&"") | N10: =IF($AB10="","",INDEX('Per Line'!$N$2:$N$301,$AB10)) | O10: =IF($AB10="","",N10*Z10/100) | P10: =IF($AB10="","",INDEX('Per Line'!$X$2:$X$301,$AB10)&"") | Q10: =IF($AB10="","",SUMIFS('Per Line'!$W$2:$W$301,'Per Line'!$E$2:$E$301,$B10,'Per Line'!$AO$2:$AO$301,1)) | R10: =IF($AB10="","",Settings!$C$7) | S10: =IF($AB10="","",SUMIFS('Per Line'!$W$2:$W$301,'Per Line'!$E$2:$E$301,$B10,'Per Line'!$AN$2:$AN$301,0,'Per Line'!$AO$2:$AO$301,0)) | T10: =IF($AB10="","",S10*R10) | U10: =IF($AB10="","",Settings!$C$6) | V10: =IF($AB10="","",SUMIFS('Per Line'!$W$2:$W$301,'Per Line'!$E$2:$E$301,$B10,'Per Line'!$AN$2:$AN$301,1,'Per Line'!$AO$2:$AO$301,0)) | W10: =IF($AB10="","",V10*U10) | X10: =IF($AB10="","",W10+T10) | Y10: =IF($AB10="","",Z10-X10) | Z10: =IF($AB10="","",S10+V10+Q10) | AA10: =IF($AB10="","",Z10-X10-O10) | AB10: =IF(ROWS($AB$2:$AB10)<=MAX('Per Line'!$AM$2:$AM$301),MATCH(ROWS($AB$2:$AB10),'Per Line'!$AM$2:$AM$301,0),"")
B11: =IF($AB11="","",INDEX('Per Line'!$E$2:$E$301,$AB11)&"") | C11: =IF($AB11="","",INDEX('Per Line'!$A$2:$A$301,$AB11)&"") | D11: =IF($AB11="","",INDEX('Per Line'!$B$2:$B$301,$AB11)) | E11: =IF($AB11="","",INDEX('Per Line'!$C$2:$C$301,$AB11)&"") | F11: =IF($AB11="","",INDEX('Per Line'!$D$2:$D$301,$AB11)&"") | G11: =IF($AB11="","",INDEX('Per Line'!$F$2:$F$301,$AB11)&"") | H11: =IF($AB11="","",INDEX('Per Line'!$G$2:$G$301,$AB11)) | I11: =IF($AB11="","",INDEX('Per Line'!$H$2:$H$301,$AB11)&"") | J11: =IF($AB11="","",INDEX('Per Line'!$J$2:$J$301,$AB11)&"") | K11: =IF($AB11="","",INDEX('Per Line'!$K$2:$K$301,$AB11)&"") | L11: =IF($AB11="","",INDEX('Per Line'!$L$2:$L$301,$AB11)&"") | M11: =IF($AB11="","",INDEX('Per Line'!$M$2:$M$301,$AB11)&"") | N11: =IF($AB11="","",INDEX('Per Line'!$N$2:$N$301,$AB11)) | O11: =IF($AB11="","",N11*Z11/100) | P11: =IF($AB11="","",INDEX('Per Line'!$X$2:$X$301,$AB11)&"") | Q11: =IF($AB11="","",SUMIFS('Per Line'!$W$2:$W$301,'Per Line'!$E$2:$E$301,$B11,'Per Line'!$AO$2:$AO$301,1)) | R11: =IF($AB11="","",Settings!$C$7) | S11: =IF($AB11="","",SUMIFS('Per Line'!$W$2:$W$301,'Per Line'!$E$2:$E$301,$B11,'Per Line'!$AN$2:$AN$301,0,'Per Line'!$AO$2:$AO$301,0)) | T11: =IF($AB11="","",S11*R11) | U11: =IF($AB11="","",Settings!$C$6) | V11: =IF($AB11="","",SUMIFS('Per Line'!$W$2:$W$301,'Per Line'!$E$2:$E$301,$B11,'Per Line'!$AN$2:$AN$301,1,'Per Line'!$AO$2:$AO$301,0)) | W11: =IF($AB11="","",V11*U11) | X11: =IF($AB11="","",W11+T11) | Y11: =IF($AB11="","",Z11-X11) | Z11: =IF($AB11="","",S11+V11+Q11) | AA11: =IF($AB11="","",Z11-X11-O11) | AB11: =IF(ROWS($AB$2:$AB11)<=MAX('Per Line'!$AM$2:$AM$301),MATCH(ROWS($AB$2:$AB11),'Per Line'!$AM$2:$AM$301,0),"")
B12: =IF($AB12="","",INDEX('Per Line'!$E$2:$E$301,$AB12)&"") | C12: =IF($AB12="","",INDEX('Per Line'!$A$2:$A$301,$AB12)&"") | D12: =IF($AB12="","",INDEX('Per Line'!$B$2:$B$301,$AB12)) | E12: =IF($AB12="","",INDEX('Per Line'!$C$2:$C$301,$AB12)&"") | F12: =IF($AB12="","",INDEX('Per Line'!$D$2:$D$301,$AB12)&"") | G12: =IF($AB12="","",INDEX('Per Line'!$F$2:$F$301,$AB12)&"") | H12: =IF($AB12="","",INDEX('Per Line'!$G$2:$G$301,$AB12)) | I12: =IF($AB12="","",INDEX('Per Line'!$H$2:$H$301,$AB12)&"") | J12: =IF($AB12="","",INDEX('Per Line'!$J$2:$J$301,$AB12)&"") | K12: =IF($AB12="","",INDEX('Per Line'!$K$2:$K$301,$AB12)&"") | L12: =IF($AB12="","",INDEX('Per Line'!$L$2:$L$301,$AB12)&"") | M12: =IF($AB12="","",INDEX('Per Line'!$M$2:$M$301,$AB12)&"") | N12: =IF($AB12="","",INDEX('Per Line'!$N$2:$N$301,$AB12)) | O12: =IF($AB12="","",N12*Z12/100) | P12: =IF($AB12="","",INDEX('Per Line'!$X$2:$X$301,$AB12)&"") | Q12: =IF($AB12="","",SUMIFS('Per Line'!$W$2:$W$301,'Per Line'!$E$2:$E$301,$B12,'Per Line'!$AO$2:$AO$301,1)) | R12: =IF($AB12="","",Settings!$C$7) | S12: =IF($AB12="","",SUMIFS('Per Line'!$W$2:$W$301,'Per Line'!$E$2:$E$301,$B12,'Per Line'!$AN$2:$AN$301,0,'Per Line'!$AO$2:$AO$301,0)) | T12: =IF($AB12="","",S12*R12) | U12: =IF($AB12="","",Settings!$C$6) | V12: =IF($AB12="","",SUMIFS('Per Line'!$W$2:$W$301,'Per Line'!$E$2:$E$301,$B12,'Per Line'!$AN$2:$AN$301,1,'Per Line'!$AO$2:$AO$301,0)) | W12: =IF($AB12="","",V12*U12) | X12: =IF($AB12="","",W12+T12) | Y12: =IF($AB12="","",Z12-X12) | Z12: =IF($AB12="","",S12+V12+Q12) | AA12: =IF($AB12="","",Z12-X12-O12) | AB12: =IF(ROWS($AB$2:$AB12)<=MAX('Per Line'!$AM$2:$AM$301),MATCH(ROWS($AB$2:$AB12),'Per Line'!$AM$2:$AM$301,0),"")
B13: =IF($AB13="","",INDEX('Per Line'!$E$2:$E$301,$AB13)&"") | C13: =IF($AB13="","",INDEX('Per Line'!$A$2:$A$301,$AB13)&"") | D13: =IF($AB13="","",INDEX('Per Line'!$B$2:$B$301,$AB13)) | E13: =IF($AB13="","",INDEX('Per Line'!$C$2:$C$301,$AB13)&"") | F13: =IF($AB13="","",INDEX('Per Line'!$D$2:$D$301,$AB13)&"") | G13: =IF($AB13="","",INDEX('Per Line'!$F$2:$F$301,$AB13)&"") | H13: =IF($AB13="","",INDEX('Per Line'!$G$2:$G$301,$AB13)) | I13: =IF($AB13="","",INDEX('Per Line'!$H$2:$H$301,$AB13)&"") | J13: =IF($AB13="","",INDEX('Per Line'!$J$2:$J$301,$AB13)&"") | K13: =IF($AB13="","",INDEX('Per Line'!$K$2:$K$301,$AB13)&"") | L13: =IF($AB13="","",INDEX('Per Line'!$L$2:$L$301,$AB13)&"") | M13: =IF($AB13="","",INDEX('Per Line'!$M$2:$M$301,$AB13)&"") | N13: =IF($AB13="","",INDEX('Per Line'!$N$2:$N$301,$AB13)) | O13: =IF($AB13="","",N13*Z13/100) | P13: =IF($AB13="","",INDEX('Per Line'!$X$2:$X$301,$AB13)&"") | Q13: =IF($AB13="","",SUMIFS('Per Line'!$W$2:$W$301,'Per Line'!$E$2:$E$301,$B13,'Per Line'!$AO$2:$AO$301,1)) | R13: =IF($AB13="","",Settings!$C$7) | S13: =IF($AB13="","",SUMIFS('Per Line'!$W$2:$W$301,'Per Line'!$E$2:$E$301,$B13,'Per Line'!$AN$2:$AN$301,0,'Per Line'!$AO$2:$AO$301,0)) | T13: =IF($AB13="","",S13*R13) | U13: =IF($AB13="","",Settings!$C$6) | V13: =IF($AB13="","",SUMIFS('Per Line'!$W$2:$W$301,'Per Line'!$E$2:$E$301,$B13,'Per Line'!$AN$2:$AN$301,1,'Per Line'!$AO$2:$AO$301,0)) | W13: =IF($AB13="","",V13*U13) | X13: =IF($AB13="","",W13+T13) | Y13: =IF($AB13="","",Z13-X13) | Z13: =IF($AB13="","",S13+V13+Q13) | AA13: =IF($AB13="","",Z13-X13-O13) | AB13: =IF(ROWS($AB$2:$AB13)<=MAX('Per Line'!$AM$2:$AM$301),MATCH(ROWS($AB$2:$AB13),'Per Line'!$AM$2:$AM$301,0),"")
... B101: =IF($AB101="","",INDEX('Per Line'!$E$2:$E$301,$AB101)&"") | C101: =IF($AB101="","",INDEX('Per Line'!$A$2:$A$301,$AB101)&"") | D101: =IF($AB101="","",INDEX('Per Line'!$B$2:$B$301,$AB101)) | E101: =IF($AB101="","",INDEX('Per Line'!$C$2:$C$301,$AB101)&"") | F101: =IF($AB101="","",INDEX('Per Line'!$D$2:$D$301,$AB101)&"") | G101: =IF($AB101="","",INDEX('Per Line'!$F$2:$F$301,$AB101)&"") | H101: =IF($AB101="","",INDEX('Per Line'!$G$2:$G$301,$AB101)) | I101: =IF($AB101="","",INDEX('Per Line'!$H$2:$H$301,$AB101)&"") | J101: =IF($AB101="","",INDEX('Per Line'!$J$2:$J$301,$AB101)&"") | K101: =IF($AB101="","",INDEX('Per Line'!$K$2:$K$301,$AB101)&"") | L101: =IF($AB101="","",INDEX('Per Line'!$L$2:$L$301,$AB101)&"") | M101: =IF($AB101="","",INDEX('Per Line'!$M$2:$M$301,$AB101)&"") | N101: =IF($AB101="","",INDEX('Per Line'!$N$2:$N$301,$AB101)) | O101: =IF($AB101="","",N101*Z101/100) | P101: =IF($AB101="","",INDEX('Per Line'!$X$2:$X$301,$AB101)&"") | Q101: =IF($AB101="","",SUMIFS('Per Line'!$W$2:$W$301,'Per Line'!$E$2:$E$301,$B101,'Per Line'!$AO$2:$AO$301,1)) | R101: =IF($AB101="","",Settings!$C$7) | S101: =IF($AB101="","",SUMIFS('Per Line'!$W$2:$W$301,'Per Line'!$E$2:$E$301,$B101,'Per Line'!$AN$2:$AN$301,0,'Per Line'!$AO$2:$AO$301,0)) | T101: =IF($AB101="","",S101*R101) | U101: =IF($AB101="","",Settings!$C$6) | V101: =IF($AB101="","",SUMIFS('Per Line'!$W$2:$W$301,'Per Line'!$E$2:$E$301,$B101,'Per Line'!$AN$2:$AN$301,1,'Per Line'!$AO$2:$AO$301,0)) | W101: =IF($AB101="","",V101*U101) | X101: =IF($AB101="","",W101+T101) | Y101: =IF($AB101="","",Z101-X101) | Z101: =IF($AB101="","",S101+V101+Q101) | AA101: =IF($AB101="","",Z101-X101-O101) | AB101: =IF(ROWS($AB$2:$AB101)<=MAX('Per Line'!$AM$2:$AM$301),MATCH(ROWS($AB$2:$AB101),'Per Line'!$AM$2:$AM$301,0),"")
