Workbook

Sheet How To Use
A1: Claims Template - EGYCARE (Chronic)
A3: Monthly steps
A4: 1. Open the 'Per Line' tab. Delete the old data in the BLUE columns only (row 2 down). Never delete the green or grey columns.
A5: 2. Paste the new month's data as VALUES starting at A2, into the blue columns: A-M, O-U, Y-Z, AB-AI (same order as the system export).
A6: 3. Green columns (N, V, W, X, AA) and the grey helper columns (AJ-AO) calculate automatically - do not paste over them.
A7: 4. 'Per Invoice' fills itself from 'Per Line' (one row per Order #, split into IMP / Local). No pivot table, no refresh.
A8: 5. The ONLY manual column in 'Per Invoice' is column B 'Invoice' (blue): type it yourself. Everything else is formula.
A9: 6. Open 'Settings' and check STATUS says OK (Per Line totals = Per Invoice totals).
A11: Colour legend
A12: Blue header = typed/pasted by you (raw data, and 'Invoice' in Per Invoice). Green header = formula (do not paste over). Grey header = helper formula (do not touch). Yellow cell (Settings) = editable rate.
A14: Calculation rules (taken from the September 2026 sheet)
A15: Co val = Order Co Payment x Total / 100. Discount = Total x Rebates / 100. Subtotal = Total - Discount. Net = Subtotal - Co val. (Total = 'Product Total')
... A20: Capacity: up to 1,500 lines and 500 invoices per month. A line with an empty Order # is ignored.

Sheet Settings
B1: Company settings & checks
B3: Insurance Company | C3: EGYCARE | D3: Informational only
B4: Corporate | C4: Electrolux-Egycare; Xceed; El-Maghrabi group; AUBE Retirees; Amiral; EMPC; Tawakol NTT- Obour; Tawakol NTT | D4: Informational only
B5: Sheet type | C5: Chronic | D5: Informational only
B6: Local products rebate % | C6: 0.11 | D6: Source: Sep sheet (Rebates = 11 on Local lines, 0 on Special Rebates = Yes).
B7: Imported (IMP) products rebate % | C7: 0.04 | D7: Source: Sep sheet (Rebates = 4 on non-local lines).
B9: Month totals / reconciliation
B10: Lines loaded | C10: =COUNTA('Per Line'!$C$2:$C$1501)
B11: Invoices (unique Order # + Approval Ref) | C11: =MAX('Per Line'!$AL$2:$AL$1501)
B12: Invoices shown in Per Invoice | C12: =SUMPRODUCT(--('Per Invoice'!$A$2:$A$501<>""))
B13: Grand Total - Per Line (Product Total) | C13: =SUM('Per Line'!$U$2:$U$1501)
B14: Grand Total - Per Invoice | C14: =SUM('Per Invoice'!$V$2:$V$501)
B15: Discount - Per Line | C15: =SUM('Per Line'!$V$2:$V$1501)
B16: Discount - Per Invoice | C16: =SUM('Per Invoice'!$T$2:$T$501)
B17: Co val - Per Line | C17: =SUM('Per Line'!$N$2:$N$1501)
B18: Co val - Per Invoice | C18: =SUM('Per Invoice'!$K$2:$K$501)
B19: Net - Per Line | C19: =SUM('Per Line'!$X$2:$X$1501)
B20: Net - Per Invoice | C20: =SUM('Per Invoice'!$W$2:$W$501)
B21: Max Limit adjustment (Co val, Per Invoice only) | C21: 0 | D21: This company's Per Invoice has no Max Limit rule.
B23: STATUS | C23: =IF(C10=0,"No data loaded",IF(COUNTA('Per Line'!$C:$C)-1>1500,"TOO MANY LINES - extend template",IF(C11>500,"TOO MANY INVOICES - extend template",IF(AND(ROUND(C13-C14,2)=0,ROUND(C15-C16,2)=0,ROUND(C17+C21-C18,2)=0,ROUND(C19-C21-C20,2)=0,C11=C12),"OK","CHECK - Per Line and Per Invoice do not match")))) | D23: Must say OK after you paste the month data.

Sheet Per Line
A1: Ticket # | B1: Stage | C1: Order # | D1: Approval Ref | E1: Channel | F1: Create At | G1: Insurance Company | H1: Country Portal ID | I1: Corporate | J1: Card | K1: Name | L1: Status | M1: Order Co Payment | N1: Co val | O1: heisenberg id | P1: Product Name | Q1: Local | R1: Unit | S1: Quantity | T1: Unit Price | U1: Product Total | V1: Discount | W1: Subtotal | X1: Net | Y1: ERX ID | Z1: Special Rebates? | AA1: Rebates | AB1: Approval Type | AC1: Max Limit | AD1: Exceeding Limit | AE1: Amount collected from customer | AF1: By Patient (Delivered) | AG1: Dispense Number | AH1: Dispense Date | AI1: Has OTP? | AJ1: Invoice Key (helper) | AK1: Order 1st Row (helper) | AL1: Invoice # (helper) | AM1: Is Local (helper) | AN1: Is Special (helper) | AO1: Sort Key (helper)
N2: =IF($C2="","",M2*U2/100) | V2: =IF($C2="","",U2*AA2/100) | W2: =IF($C2="","",U2-V2) | X2: =IF($C2="","",W2-N2) | AA2: =IF($C2="","",IF($AN2=1,0,IF($AM2=1,Settings!$C$6,Settings!$C$7))*100) | AJ2: =IF($C2="","",$C2&"|"&$D2&"") | AK2: =IF($C2="","",IF(COUNTIF($AJ$2:$AJ2,$AJ2)=1,1,0)) | AL2: =IF($AK2=1,SUMPRODUCT(--($AO$2:$AO$1501<$AO2))+1,"") | AM2: =IF($C2="","",IF(OR($Q2=TRUE(),$Q2="TRUE"),1,0)) | AN2: =IF($C2="","",IF($Z2="Yes",1,0)) | AO2: =IF($AK2=1,IFERROR(IF(VALUE($C2)<100000000,VALUE($C2),1000000000),IFERROR(IF(VALUE(MID($C2,2,20))<100000000,VALUE(MID($C2,2,20)),1000000000),1000000000))+ROW()/100000,"")
N3: =IF($C3="","",M3*U3/100) | V3: =IF($C3="","",U3*AA3/100) | W3: =IF($C3="","",U3-V3) | X3: =IF($C3="","",W3-N3) | AA3: =IF($C3="","",IF($AN3=1,0,IF($AM3=1,Settings!$C$6,Settings!$C$7))*100) | AJ3: =IF($C3="","",$C3&"|"&$D3&"") | AK3: =IF($C3="","",IF(COUNTIF($AJ$2:$AJ3,$AJ3)=1,1,0)) | AL3: =IF($AK3=1,SUMPRODUCT(--($AO$2:$AO$1501<$AO3))+1,"") | AM3: =IF($C3="","",IF(OR($Q3=TRUE(),$Q3="TRUE"),1,0)) | AN3: =IF($C3="","",IF($Z3="Yes",1,0)) | AO3: =IF($AK3=1,IFERROR(IF(VALUE($C3)<100000000,VALUE($C3),1000000000),IFERROR(IF(VALUE(MID($C3,2,20))<100000000,VALUE(MID($C3,2,20)),1000000000),1000000000))+ROW()/100000,"")
N4: =IF($C4="","",M4*U4/100) | V4: =IF($C4="","",U4*AA4/100) | W4: =IF($C4="","",U4-V4) | X4: =IF($C4="","",W4-N4) | AA4: =IF($C4="","",IF($AN4=1,0,IF($AM4=1,Settings!$C$6,Settings!$C$7))*100) | AJ4: =IF($C4="","",$C4&"|"&$D4&"") | AK4: =IF($C4="","",IF(COUNTIF($AJ$2:$AJ4,$AJ4)=1,1,0)) | AL4: =IF($AK4=1,SUMPRODUCT(--($AO$2:$AO$1501<$AO4))+1,"") | AM4: =IF($C4="","",IF(OR($Q4=TRUE(),$Q4="TRUE"),1,0)) | AN4: =IF($C4="","",IF($Z4="Yes",1,0)) | AO4: =IF($AK4=1,IFERROR(IF(VALUE($C4)<100000000,VALUE($C4),1000000000),IFERROR(IF(VALUE(MID($C4,2,20))<100000000,VALUE(MID($C4,2,20)),1000000000),1000000000))+ROW()/100000,"")
N5: =IF($C5="","",M5*U5/100) | V5: =IF($C5="","",U5*AA5/100) | W5: =IF($C5="","",U5-V5) | X5: =IF($C5="","",W5-N5) | AA5: =IF($C5="","",IF($AN5=1,0,IF($AM5=1,Settings!$C$6,Settings!$C$7))*100) | AJ5: =IF($C5="","",$C5&"|"&$D5&"") | AK5: =IF($C5="","",IF(COUNTIF($AJ$2:$AJ5,$AJ5)=1,1,0)) | AL5: =IF($AK5=1,SUMPRODUCT(--($AO$2:$AO$1501<$AO5))+1,"") | AM5: =IF($C5="","",IF(OR($Q5=TRUE(),$Q5="TRUE"),1,0)) | AN5: =IF($C5="","",IF($Z5="Yes",1,0)) | AO5: =IF($AK5=1,IFERROR(IF(VALUE($C5)<100000000,VALUE($C5),1000000000),IFERROR(IF(VALUE(MID($C5,2,20))<100000000,VALUE(MID($C5,2,20)),1000000000),1000000000))+ROW()/100000,"")
N6: =IF($C6="","",M6*U6/100) | V6: =IF($C6="","",U6*AA6/100) | W6: =IF($C6="","",U6-V6) | X6: =IF($C6="","",W6-N6) | AA6: =IF($C6="","",IF($AN6=1,0,IF($AM6=1,Settings!$C$6,Settings!$C$7))*100) | AJ6: =IF($C6="","",$C6&"|"&$D6&"") | AK6: =IF($C6="","",IF(COUNTIF($AJ$2:$AJ6,$AJ6)=1,1,0)) | AL6: =IF($AK6=1,SUMPRODUCT(--($AO$2:$AO$1501<$AO6))+1,"") | AM6: =IF($C6="","",IF(OR($Q6=TRUE(),$Q6="TRUE"),1,0)) | AN6: =IF($C6="","",IF($Z6="Yes",1,0)) | AO6: =IF($AK6=1,IFERROR(IF(VALUE($C6)<100000000,VALUE($C6),1000000000),IFERROR(IF(VALUE(MID($C6,2,20))<100000000,VALUE(MID($C6,2,20)),1000000000),1000000000))+ROW()/100000,"")
N7: =IF($C7="","",M7*U7/100) | V7: =IF($C7="","",U7*AA7/100) | W7: =IF($C7="","",U7-V7) | X7: =IF($C7="","",W7-N7) | AA7: =IF($C7="","",IF($AN7=1,0,IF($AM7=1,Settings!$C$6,Settings!$C$7))*100) | AJ7: =IF($C7="","",$C7&"|"&$D7&"") | AK7: =IF($C7="","",IF(COUNTIF($AJ$2:$AJ7,$AJ7)=1,1,0)) | AL7: =IF($AK7=1,SUMPRODUCT(--($AO$2:$AO$1501<$AO7))+1,"") | AM7: =IF($C7="","",IF(OR($Q7=TRUE(),$Q7="TRUE"),1,0)) | AN7: =IF($C7="","",IF($Z7="Yes",1,0)) | AO7: =IF($AK7=1,IFERROR(IF(VALUE($C7)<100000000,VALUE($C7),1000000000),IFERROR(IF(VALUE(MID($C7,2,20))<100000000,VALUE(MID($C7,2,20)),1000000000),1000000000))+ROW()/100000,"")
N8: =IF($C8="","",M8*U8/100) | V8: =IF($C8="","",U8*AA8/100) | W8: =IF($C8="","",U8-V8) | X8: =IF($C8="","",W8-N8) | AA8: =IF($C8="","",IF($AN8=1,0,IF($AM8=1,Settings!$C$6,Settings!$C$7))*100) | AJ8: =IF($C8="","",$C8&"|"&$D8&"") | AK8: =IF($C8="","",IF(COUNTIF($AJ$2:$AJ8,$AJ8)=1,1,0)) | AL8: =IF($AK8=1,SUMPRODUCT(--($AO$2:$AO$1501<$AO8))+1,"") | AM8: =IF($C8="","",IF(OR($Q8=TRUE(),$Q8="TRUE"),1,0)) | AN8: =IF($C8="","",IF($Z8="Yes",1,0)) | AO8: =IF($AK8=1,IFERROR(IF(VALUE($C8)<100000000,VALUE($C8),1000000000),IFERROR(IF(VALUE(MID($C8,2,20))<100000000,VALUE(MID($C8,2,20)),1000000000),1000000000))+ROW()/100000,"")
N9: =IF($C9="","",M9*U9/100) | V9: =IF($C9="","",U9*AA9/100) | W9: =IF($C9="","",U9-V9) | X9: =IF($C9="","",W9-N9) | AA9: =IF($C9="","",IF($AN9=1,0,IF($AM9=1,Settings!$C$6,Settings!$C$7))*100) | AJ9: =IF($C9="","",$C9&"|"&$D9&"") | AK9: =IF($C9="","",IF(COUNTIF($AJ$2:$AJ9,$AJ9)=1,1,0)) | AL9: =IF($AK9=1,SUMPRODUCT(--($AO$2:$AO$1501<$AO9))+1,"") | AM9: =IF($C9="","",IF(OR($Q9=TRUE(),$Q9="TRUE"),1,0)) | AN9: =IF($C9="","",IF($Z9="Yes",1,0)) | AO9: =IF($AK9=1,IFERROR(IF(VALUE($C9)<100000000,VALUE($C9),1000000000),IFERROR(IF(VALUE(MID($C9,2,20))<100000000,VALUE(MID($C9,2,20)),1000000000),1000000000))+ROW()/100000,"")
N10: =IF($C10="","",M10*U10/100) | V10: =IF($C10="","",U10*AA10/100) | W10: =IF($C10="","",U10-V10) | X10: =IF($C10="","",W10-N10) | AA10: =IF($C10="","",IF($AN10=1,0,IF($AM10=1,Settings!$C$6,Settings!$C$7))*100) | AJ10: =IF($C10="","",$C10&"|"&$D10&"") | AK10: =IF($C10="","",IF(COUNTIF($AJ$2:$AJ10,$AJ10)=1,1,0)) | AL10: =IF($AK10=1,SUMPRODUCT(--($AO$2:$AO$1501<$AO10))+1,"") | AM10: =IF($C10="","",IF(OR($Q10=TRUE(),$Q10="TRUE"),1,0)) | AN10: =IF($C10="","",IF($Z10="Yes",1,0)) | AO10: =IF($AK10=1,IFERROR(IF(VALUE($C10)<100000000,VALUE($C10),1000000000),IFERROR(IF(VALUE(MID($C10,2,20))<100000000,VALUE(MID($C10,2,20)),1000000000),1000000000))+ROW()/100000,"")
N11: =IF($C11="","",M11*U11/100) | V11: =IF($C11="","",U11*AA11/100) | W11: =IF($C11="","",U11-V11) | X11: =IF($C11="","",W11-N11) | AA11: =IF($C11="","",IF($AN11=1,0,IF($AM11=1,Settings!$C$6,Settings!$C$7))*100) | AJ11: =IF($C11="","",$C11&"|"&$D11&"") | AK11: =IF($C11="","",IF(COUNTIF($AJ$2:$AJ11,$AJ11)=1,1,0)) | AL11: =IF($AK11=1,SUMPRODUCT(--($AO$2:$AO$1501<$AO11))+1,"") | AM11: =IF($C11="","",IF(OR($Q11=TRUE(),$Q11="TRUE"),1,0)) | AN11: =IF($C11="","",IF($Z11="Yes",1,0)) | AO11: =IF($AK11=1,IFERROR(IF(VALUE($C11)<100000000,VALUE($C11),1000000000),IFERROR(IF(VALUE(MID($C11,2,20))<100000000,VALUE(MID($C11,2,20)),1000000000),1000000000))+ROW()/100000,"")
N12: =IF($C12="","",M12*U12/100) | V12: =IF($C12="","",U12*AA12/100) | W12: =IF($C12="","",U12-V12) | X12: =IF($C12="","",W12-N12) | AA12: =IF($C12="","",IF($AN12=1,0,IF($AM12=1,Settings!$C$6,Settings!$C$7))*100) | AJ12: =IF($C12="","",$C12&"|"&$D12&"") | AK12: =IF($C12="","",IF(COUNTIF($AJ$2:$AJ12,$AJ12)=1,1,0)) | AL12: =IF($AK12=1,SUMPRODUCT(--($AO$2:$AO$1501<$AO12))+1,"") | AM12: =IF($C12="","",IF(OR($Q12=TRUE(),$Q12="TRUE"),1,0)) | AN12: =IF($C12="","",IF($Z12="Yes",1,0)) | AO12: =IF($AK12=1,IFERROR(IF(VALUE($C12)<100000000,VALUE($C12),1000000000),IFERROR(IF(VALUE(MID($C12,2,20))<100000000,VALUE(MID($C12,2,20)),1000000000),1000000000))+ROW()/100000,"")
N13: =IF($C13="","",M13*U13/100) | V13: =IF($C13="","",U13*AA13/100) | W13: =IF($C13="","",U13-V13) | X13: =IF($C13="","",W13-N13) | AA13: =IF($C13="","",IF($AN13=1,0,IF($AM13=1,Settings!$C$6,Settings!$C$7))*100) | AJ13: =IF($C13="","",$C13&"|"&$D13&"") | AK13: =IF($C13="","",IF(COUNTIF($AJ$2:$AJ13,$AJ13)=1,1,0)) | AL13: =IF($AK13=1,SUMPRODUCT(--($AO$2:$AO$1501<$AO13))+1,"") | AM13: =IF($C13="","",IF(OR($Q13=TRUE(),$Q13="TRUE"),1,0)) | AN13: =IF($C13="","",IF($Z13="Yes",1,0)) | AO13: =IF($AK13=1,IFERROR(IF(VALUE($C13)<100000000,VALUE($C13),1000000000),IFERROR(IF(VALUE(MID($C13,2,20))<100000000,VALUE(MID($C13,2,20)),1000000000),1000000000))+ROW()/100000,"")
... N1501: =IF($C1501="","",M1501*U1501/100) | V1501: =IF($C1501="","",U1501*AA1501/100) | W1501: =IF($C1501="","",U1501-V1501) | X1501: =IF($C1501="","",W1501-N1501) | AA1501: =IF($C1501="","",IF($AN1501=1,0,IF($AM1501=1,Settings!$C$6,Settings!$C$7))*100) | AJ1501: =IF($C1501="","",$C1501&"|"&$D1501&"") | AK1501: =IF($C1501="","",IF(COUNTIF($AJ$2:$AJ1501,$AJ1501)=1,1,0)) | AL1501: =IF($AK1501=1,SUMPRODUCT(--($AO$2:$AO$1501<$AO1501))+1,"") | AM1501: =IF($C1501="","",IF(OR($Q1501=TRUE(),$Q1501="TRUE"),1,0)) | AN1501: =IF($C1501="","",IF($Z1501="Yes",1,0)) | AO1501: =IF($AK1501=1,IFERROR(IF(VALUE($C1501)<100000000,VALUE($C1501),1000000000),IFERROR(IF(VALUE(MID($C1501,2,20))<100000000,VALUE(MID($C1501,2,20)),1000000000),1000000000))+ROW()/100000,"")

Sheet Per Invoice
A1: Order # | B1: Invoice | C1: Approval Ref | D1: Ticket # | E1: Insurance Company | F1: Create At | G1: Corporate | H1: Card | I1: Name | J1: Order Co Payment | K1: Co val | L1: ERX ID | M1: SP | N1: imp% | O1: IMP | P1: imp val | Q1: LOCAL% | R1: LOCAL | S1: LOCAL VAL | T1: TOTAL VAL | U1: SUBTOTAL | V1: Grand Total | W1: NET | X1: Src Row (helper)
A2: =IF($X2="","",INDEX('Per Line'!$C$2:$C$1501,$X2)&"") | C2: =IF($X2="","",INDEX('Per Line'!$D$2:$D$1501,$X2)&"") | D2: =IF($X2="","",INDEX('Per Line'!$A$2:$A$1501,$X2)) | E2: =IF($X2="","",INDEX('Per Line'!$G$2:$G$1501,$X2)&"") | F2: =IF($X2="","",INDEX('Per Line'!$F$2:$F$1501,$X2)) | G2: =IF($X2="","",INDEX('Per Line'!$I$2:$I$1501,$X2)&"") | H2: =IF($X2="","",INDEX('Per Line'!$J$2:$J$1501,$X2)&"") | I2: =IF($X2="","",INDEX('Per Line'!$K$2:$K$1501,$X2)&"") | J2: =IF($X2="","",INDEX('Per Line'!$M$2:$M$1501,$X2)) | K2: =IF($X2="","",J2*V2/100) | L2: =IF($X2="","",INDEX('Per Line'!$Y$2:$Y$1501,$X2)&"") | M2: =IF($X2="","",SUMIFS('Per Line'!$U$2:$U$1501,'Per Line'!$AJ$2:$AJ$1501,$A2&"|"&$C2,'Per Line'!$AN$2:$AN$1501,1)) | N2: =IF($X2="","",Settings!$C$7) | O2: =IF($X2="","",SUMIFS('Per Line'!$U$2:$U$1501,'Per Line'!$AJ$2:$AJ$1501,$A2&"|"&$C2,'Per Line'!$AM$2:$AM$1501,0,'Per Line'!$AN$2:$AN$1501,0)) | P2: =IF($X2="","",O2*N2) | Q2: =IF($X2="","",Settings!$C$6) | R2: =IF($X2="","",SUMIFS('Per Line'!$U$2:$U$1501,'Per Line'!$AJ$2:$AJ$1501,$A2&"|"&$C2,'Per Line'!$AM$2:$AM$1501,1,'Per Line'!$AN$2:$AN$1501,0)) | S2: =IF($X2="","",R2*Q2) | T2: =IF($X2="","",S2+P2) | U2: =IF($X2="","",V2-T2) | V2: =IF($X2="","",O2+R2+M2) | W2: =IF($X2="","",V2-T2-K2) | X2: =IF(ROWS($X$2:$X2)<=MAX('Per Line'!$AL$2:$AL$1501),MATCH(ROWS($X$2:$X2),'Per Line'!$AL$2:$AL$1501,0),"")
A3: =IF($X3="","",INDEX('Per Line'!$C$2:$C$1501,$X3)&"") | C3: =IF($X3="","",INDEX('Per Line'!$D$2:$D$1501,$X3)&"") | D3: =IF($X3="","",INDEX('Per Line'!$A$2:$A$1501,$X3)) | E3: =IF($X3="","",INDEX('Per Line'!$G$2:$G$1501,$X3)&"") | F3: =IF($X3="","",INDEX('Per Line'!$F$2:$F$1501,$X3)) | G3: =IF($X3="","",INDEX('Per Line'!$I$2:$I$1501,$X3)&"") | H3: =IF($X3="","",INDEX('Per Line'!$J$2:$J$1501,$X3)&"") | I3: =IF($X3="","",INDEX('Per Line'!$K$2:$K$1501,$X3)&"") | J3: =IF($X3="","",INDEX('Per Line'!$M$2:$M$1501,$X3)) | K3: =IF($X3="","",J3*V3/100) | L3: =IF($X3="","",INDEX('Per Line'!$Y$2:$Y$1501,$X3)&"") | M3: =IF($X3="","",SUMIFS('Per Line'!$U$2:$U$1501,'Per Line'!$AJ$2:$AJ$1501,$A3&"|"&$C3,'Per Line'!$AN$2:$AN$1501,1)) | N3: =IF($X3="","",Settings!$C$7) | O3: =IF($X3="","",SUMIFS('Per Line'!$U$2:$U$1501,'Per Line'!$AJ$2:$AJ$1501,$A3&"|"&$C3,'Per Line'!$AM$2:$AM$1501,0,'Per Line'!$AN$2:$AN$1501,0)) | P3: =IF($X3="","",O3*N3) | Q3: =IF($X3="","",Settings!$C$6) | R3: =IF($X3="","",SUMIFS('Per Line'!$U$2:$U$1501,'Per Line'!$AJ$2:$AJ$1501,$A3&"|"&$C3,'Per Line'!$AM$2:$AM$1501,1,'Per Line'!$AN$2:$AN$1501,0)) | S3: =IF($X3="","",R3*Q3) | T3: =IF($X3="","",S3+P3) | U3: =IF($X3="","",V3-T3) | V3: =IF($X3="","",O3+R3+M3) | W3: =IF($X3="","",V3-T3-K3) | X3: =IF(ROWS($X$2:$X3)<=MAX('Per Line'!$AL$2:$AL$1501),MATCH(ROWS($X$2:$X3),'Per Line'!$AL$2:$AL$1501,0),"")
A4: =IF($X4="","",INDEX('Per Line'!$C$2:$C$1501,$X4)&"") | C4: =IF($X4="","",INDEX('Per Line'!$D$2:$D$1501,$X4)&"") | D4: =IF($X4="","",INDEX('Per Line'!$A$2:$A$1501,$X4)) | E4: =IF($X4="","",INDEX('Per Line'!$G$2:$G$1501,$X4)&"") | F4: =IF($X4="","",INDEX('Per Line'!$F$2:$F$1501,$X4)) | G4: =IF($X4="","",INDEX('Per Line'!$I$2:$I$1501,$X4)&"") | H4: =IF($X4="","",INDEX('Per Line'!$J$2:$J$1501,$X4)&"") | I4: =IF($X4="","",INDEX('Per Line'!$K$2:$K$1501,$X4)&"") | J4: =IF($X4="","",INDEX('Per Line'!$M$2:$M$1501,$X4)) | K4: =IF($X4="","",J4*V4/100) | L4: =IF($X4="","",INDEX('Per Line'!$Y$2:$Y$1501,$X4)&"") | M4: =IF($X4="","",SUMIFS('Per Line'!$U$2:$U$1501,'Per Line'!$AJ$2:$AJ$1501,$A4&"|"&$C4,'Per Line'!$AN$2:$AN$1501,1)) | N4: =IF($X4="","",Settings!$C$7) | O4: =IF($X4="","",SUMIFS('Per Line'!$U$2:$U$1501,'Per Line'!$AJ$2:$AJ$1501,$A4&"|"&$C4,'Per Line'!$AM$2:$AM$1501,0,'Per Line'!$AN$2:$AN$1501,0)) | P4: =IF($X4="","",O4*N4) | Q4: =IF($X4="","",Settings!$C$6) | R4: =IF($X4="","",SUMIFS('Per Line'!$U$2:$U$1501,'Per Line'!$AJ$2:$AJ$1501,$A4&"|"&$C4,'Per Line'!$AM$2:$AM$1501,1,'Per Line'!$AN$2:$AN$1501,0)) | S4: =IF($X4="","",R4*Q4) | T4: =IF($X4="","",S4+P4) | U4: =IF($X4="","",V4-T4) | V4: =IF($X4="","",O4+R4+M4) | W4: =IF($X4="","",V4-T4-K4) | X4: =IF(ROWS($X$2:$X4)<=MAX('Per Line'!$AL$2:$AL$1501),MATCH(ROWS($X$2:$X4),'Per Line'!$AL$2:$AL$1501,0),"")
A5: =IF($X5="","",INDEX('Per Line'!$C$2:$C$1501,$X5)&"") | C5: =IF($X5="","",INDEX('Per Line'!$D$2:$D$1501,$X5)&"") | D5: =IF($X5="","",INDEX('Per Line'!$A$2:$A$1501,$X5)) | E5: =IF($X5="","",INDEX('Per Line'!$G$2:$G$1501,$X5)&"") | F5: =IF($X5="","",INDEX('Per Line'!$F$2:$F$1501,$X5)) | G5: =IF($X5="","",INDEX('Per Line'!$I$2:$I$1501,$X5)&"") | H5: =IF($X5="","",INDEX('Per Line'!$J$2:$J$1501,$X5)&"") | I5: =IF($X5="","",INDEX('Per Line'!$K$2:$K$1501,$X5)&"") | J5: =IF($X5="","",INDEX('Per Line'!$M$2:$M$1501,$X5)) | K5: =IF($X5="","",J5*V5/100) | L5: =IF($X5="","",INDEX('Per Line'!$Y$2:$Y$1501,$X5)&"") | M5: =IF($X5="","",SUMIFS('Per Line'!$U$2:$U$1501,'Per Line'!$AJ$2:$AJ$1501,$A5&"|"&$C5,'Per Line'!$AN$2:$AN$1501,1)) | N5: =IF($X5="","",Settings!$C$7) | O5: =IF($X5="","",SUMIFS('Per Line'!$U$2:$U$1501,'Per Line'!$AJ$2:$AJ$1501,$A5&"|"&$C5,'Per Line'!$AM$2:$AM$1501,0,'Per Line'!$AN$2:$AN$1501,0)) | P5: =IF($X5="","",O5*N5) | Q5: =IF($X5="","",Settings!$C$6) | R5: =IF($X5="","",SUMIFS('Per Line'!$U$2:$U$1501,'Per Line'!$AJ$2:$AJ$1501,$A5&"|"&$C5,'Per Line'!$AM$2:$AM$1501,1,'Per Line'!$AN$2:$AN$1501,0)) | S5: =IF($X5="","",R5*Q5) | T5: =IF($X5="","",S5+P5) | U5: =IF($X5="","",V5-T5) | V5: =IF($X5="","",O5+R5+M5) | W5: =IF($X5="","",V5-T5-K5) | X5: =IF(ROWS($X$2:$X5)<=MAX('Per Line'!$AL$2:$AL$1501),MATCH(ROWS($X$2:$X5),'Per Line'!$AL$2:$AL$1501,0),"")
A6: =IF($X6="","",INDEX('Per Line'!$C$2:$C$1501,$X6)&"") | C6: =IF($X6="","",INDEX('Per Line'!$D$2:$D$1501,$X6)&"") | D6: =IF($X6="","",INDEX('Per Line'!$A$2:$A$1501,$X6)) | E6: =IF($X6="","",INDEX('Per Line'!$G$2:$G$1501,$X6)&"") | F6: =IF($X6="","",INDEX('Per Line'!$F$2:$F$1501,$X6)) | G6: =IF($X6="","",INDEX('Per Line'!$I$2:$I$1501,$X6)&"") | H6: =IF($X6="","",INDEX('Per Line'!$J$2:$J$1501,$X6)&"") | I6: =IF($X6="","",INDEX('Per Line'!$K$2:$K$1501,$X6)&"") | J6: =IF($X6="","",INDEX('Per Line'!$M$2:$M$1501,$X6)) | K6: =IF($X6="","",J6*V6/100) | L6: =IF($X6="","",INDEX('Per Line'!$Y$2:$Y$1501,$X6)&"") | M6: =IF($X6="","",SUMIFS('Per Line'!$U$2:$U$1501,'Per Line'!$AJ$2:$AJ$1501,$A6&"|"&$C6,'Per Line'!$AN$2:$AN$1501,1)) | N6: =IF($X6="","",Settings!$C$7) | O6: =IF($X6="","",SUMIFS('Per Line'!$U$2:$U$1501,'Per Line'!$AJ$2:$AJ$1501,$A6&"|"&$C6,'Per Line'!$AM$2:$AM$1501,0,'Per Line'!$AN$2:$AN$1501,0)) | P6: =IF($X6="","",O6*N6) | Q6: =IF($X6="","",Settings!$C$6) | R6: =IF($X6="","",SUMIFS('Per Line'!$U$2:$U$1501,'Per Line'!$AJ$2:$AJ$1501,$A6&"|"&$C6,'Per Line'!$AM$2:$AM$1501,1,'Per Line'!$AN$2:$AN$1501,0)) | S6: =IF($X6="","",R6*Q6) | T6: =IF($X6="","",S6+P6) | U6: =IF($X6="","",V6-T6) | V6: =IF($X6="","",O6+R6+M6) | W6: =IF($X6="","",V6-T6-K6) | X6: =IF(ROWS($X$2:$X6)<=MAX('Per Line'!$AL$2:$AL$1501),MATCH(ROWS($X$2:$X6),'Per Line'!$AL$2:$AL$1501,0),"")
A7: =IF($X7="","",INDEX('Per Line'!$C$2:$C$1501,$X7)&"") | C7: =IF($X7="","",INDEX('Per Line'!$D$2:$D$1501,$X7)&"") | D7: =IF($X7="","",INDEX('Per Line'!$A$2:$A$1501,$X7)) | E7: =IF($X7="","",INDEX('Per Line'!$G$2:$G$1501,$X7)&"") | F7: =IF($X7="","",INDEX('Per Line'!$F$2:$F$1501,$X7)) | G7: =IF($X7="","",INDEX('Per Line'!$I$2:$I$1501,$X7)&"") | H7: =IF($X7="","",INDEX('Per Line'!$J$2:$J$1501,$X7)&"") | I7: =IF($X7="","",INDEX('Per Line'!$K$2:$K$1501,$X7)&"") | J7: =IF($X7="","",INDEX('Per Line'!$M$2:$M$1501,$X7)) | K7: =IF($X7="","",J7*V7/100) | L7: =IF($X7="","",INDEX('Per Line'!$Y$2:$Y$1501,$X7)&"") | M7: =IF($X7="","",SUMIFS('Per Line'!$U$2:$U$1501,'Per Line'!$AJ$2:$AJ$1501,$A7&"|"&$C7,'Per Line'!$AN$2:$AN$1501,1)) | N7: =IF($X7="","",Settings!$C$7) | O7: =IF($X7="","",SUMIFS('Per Line'!$U$2:$U$1501,'Per Line'!$AJ$2:$AJ$1501,$A7&"|"&$C7,'Per Line'!$AM$2:$AM$1501,0,'Per Line'!$AN$2:$AN$1501,0)) | P7: =IF($X7="","",O7*N7) | Q7: =IF($X7="","",Settings!$C$6) | R7: =IF($X7="","",SUMIFS('Per Line'!$U$2:$U$1501,'Per Line'!$AJ$2:$AJ$1501,$A7&"|"&$C7,'Per Line'!$AM$2:$AM$1501,1,'Per Line'!$AN$2:$AN$1501,0)) | S7: =IF($X7="","",R7*Q7) | T7: =IF($X7="","",S7+P7) | U7: =IF($X7="","",V7-T7) | V7: =IF($X7="","",O7+R7+M7) | W7: =IF($X7="","",V7-T7-K7) | X7: =IF(ROWS($X$2:$X7)<=MAX('Per Line'!$AL$2:$AL$1501),MATCH(ROWS($X$2:$X7),'Per Line'!$AL$2:$AL$1501,0),"")
A8: =IF($X8="","",INDEX('Per Line'!$C$2:$C$1501,$X8)&"") | C8: =IF($X8="","",INDEX('Per Line'!$D$2:$D$1501,$X8)&"") | D8: =IF($X8="","",INDEX('Per Line'!$A$2:$A$1501,$X8)) | E8: =IF($X8="","",INDEX('Per Line'!$G$2:$G$1501,$X8)&"") | F8: =IF($X8="","",INDEX('Per Line'!$F$2:$F$1501,$X8)) | G8: =IF($X8="","",INDEX('Per Line'!$I$2:$I$1501,$X8)&"") | H8: =IF($X8="","",INDEX('Per Line'!$J$2:$J$1501,$X8)&"") | I8: =IF($X8="","",INDEX('Per Line'!$K$2:$K$1501,$X8)&"") | J8: =IF($X8="","",INDEX('Per Line'!$M$2:$M$1501,$X8)) | K8: =IF($X8="","",J8*V8/100) | L8: =IF($X8="","",INDEX('Per Line'!$Y$2:$Y$1501,$X8)&"") | M8: =IF($X8="","",SUMIFS('Per Line'!$U$2:$U$1501,'Per Line'!$AJ$2:$AJ$1501,$A8&"|"&$C8,'Per Line'!$AN$2:$AN$1501,1)) | N8: =IF($X8="","",Settings!$C$7) | O8: =IF($X8="","",SUMIFS('Per Line'!$U$2:$U$1501,'Per Line'!$AJ$2:$AJ$1501,$A8&"|"&$C8,'Per Line'!$AM$2:$AM$1501,0,'Per Line'!$AN$2:$AN$1501,0)) | P8: =IF($X8="","",O8*N8) | Q8: =IF($X8="","",Settings!$C$6) | R8: =IF($X8="","",SUMIFS('Per Line'!$U$2:$U$1501,'Per Line'!$AJ$2:$AJ$1501,$A8&"|"&$C8,'Per Line'!$AM$2:$AM$1501,1,'Per Line'!$AN$2:$AN$1501,0)) | S8: =IF($X8="","",R8*Q8) | T8: =IF($X8="","",S8+P8) | U8: =IF($X8="","",V8-T8) | V8: =IF($X8="","",O8+R8+M8) | W8: =IF($X8="","",V8-T8-K8) | X8: =IF(ROWS($X$2:$X8)<=MAX('Per Line'!$AL$2:$AL$1501),MATCH(ROWS($X$2:$X8),'Per Line'!$AL$2:$AL$1501,0),"")
A9: =IF($X9="","",INDEX('Per Line'!$C$2:$C$1501,$X9)&"") | C9: =IF($X9="","",INDEX('Per Line'!$D$2:$D$1501,$X9)&"") | D9: =IF($X9="","",INDEX('Per Line'!$A$2:$A$1501,$X9)) | E9: =IF($X9="","",INDEX('Per Line'!$G$2:$G$1501,$X9)&"") | F9: =IF($X9="","",INDEX('Per Line'!$F$2:$F$1501,$X9)) | G9: =IF($X9="","",INDEX('Per Line'!$I$2:$I$1501,$X9)&"") | H9: =IF($X9="","",INDEX('Per Line'!$J$2:$J$1501,$X9)&"") | I9: =IF($X9="","",INDEX('Per Line'!$K$2:$K$1501,$X9)&"") | J9: =IF($X9="","",INDEX('Per Line'!$M$2:$M$1501,$X9)) | K9: =IF($X9="","",J9*V9/100) | L9: =IF($X9="","",INDEX('Per Line'!$Y$2:$Y$1501,$X9)&"") | M9: =IF($X9="","",SUMIFS('Per Line'!$U$2:$U$1501,'Per Line'!$AJ$2:$AJ$1501,$A9&"|"&$C9,'Per Line'!$AN$2:$AN$1501,1)) | N9: =IF($X9="","",Settings!$C$7) | O9: =IF($X9="","",SUMIFS('Per Line'!$U$2:$U$1501,'Per Line'!$AJ$2:$AJ$1501,$A9&"|"&$C9,'Per Line'!$AM$2:$AM$1501,0,'Per Line'!$AN$2:$AN$1501,0)) | P9: =IF($X9="","",O9*N9) | Q9: =IF($X9="","",Settings!$C$6) | R9: =IF($X9="","",SUMIFS('Per Line'!$U$2:$U$1501,'Per Line'!$AJ$2:$AJ$1501,$A9&"|"&$C9,'Per Line'!$AM$2:$AM$1501,1,'Per Line'!$AN$2:$AN$1501,0)) | S9: =IF($X9="","",R9*Q9) | T9: =IF($X9="","",S9+P9) | U9: =IF($X9="","",V9-T9) | V9: =IF($X9="","",O9+R9+M9) | W9: =IF($X9="","",V9-T9-K9) | X9: =IF(ROWS($X$2:$X9)<=MAX('Per Line'!$AL$2:$AL$1501),MATCH(ROWS($X$2:$X9),'Per Line'!$AL$2:$AL$1501,0),"")
A10: =IF($X10="","",INDEX('Per Line'!$C$2:$C$1501,$X10)&"") | C10: =IF($X10="","",INDEX('Per Line'!$D$2:$D$1501,$X10)&"") | D10: =IF($X10="","",INDEX('Per Line'!$A$2:$A$1501,$X10)) | E10: =IF($X10="","",INDEX('Per Line'!$G$2:$G$1501,$X10)&"") | F10: =IF($X10="","",INDEX('Per Line'!$F$2:$F$1501,$X10)) | G10: =IF($X10="","",INDEX('Per Line'!$I$2:$I$1501,$X10)&"") | H10: =IF($X10="","",INDEX('Per Line'!$J$2:$J$1501,$X10)&"") | I10: =IF($X10="","",INDEX('Per Line'!$K$2:$K$1501,$X10)&"") | J10: =IF($X10="","",INDEX('Per Line'!$M$2:$M$1501,$X10)) | K10: =IF($X10="","",J10*V10/100) | L10: =IF($X10="","",INDEX('Per Line'!$Y$2:$Y$1501,$X10)&"") | M10: =IF($X10="","",SUMIFS('Per Line'!$U$2:$U$1501,'Per Line'!$AJ$2:$AJ$1501,$A10&"|"&$C10,'Per Line'!$AN$2:$AN$1501,1)) | N10: =IF($X10="","",Settings!$C$7) | O10: =IF($X10="","",SUMIFS('Per Line'!$U$2:$U$1501,'Per Line'!$AJ$2:$AJ$1501,$A10&"|"&$C10,'Per Line'!$AM$2:$AM$1501,0,'Per Line'!$AN$2:$AN$1501,0)) | P10: =IF($X10="","",O10*N10) | Q10: =IF($X10="","",Settings!$C$6) | R10: =IF($X10="","",SUMIFS('Per Line'!$U$2:$U$1501,'Per Line'!$AJ$2:$AJ$1501,$A10&"|"&$C10,'Per Line'!$AM$2:$AM$1501,1,'Per Line'!$AN$2:$AN$1501,0)) | S10: =IF($X10="","",R10*Q10) | T10: =IF($X10="","",S10+P10) | U10: =IF($X10="","",V10-T10) | V10: =IF($X10="","",O10+R10+M10) | W10: =IF($X10="","",V10-T10-K10) | X10: =IF(ROWS($X$2:$X10)<=MAX('Per Line'!$AL$2:$AL$1501),MATCH(ROWS($X$2:$X10),'Per Line'!$AL$2:$AL$1501,0),"")
A11: =IF($X11="","",INDEX('Per Line'!$C$2:$C$1501,$X11)&"") | C11: =IF($X11="","",INDEX('Per Line'!$D$2:$D$1501,$X11)&"") | D11: =IF($X11="","",INDEX('Per Line'!$A$2:$A$1501,$X11)) | E11: =IF($X11="","",INDEX('Per Line'!$G$2:$G$1501,$X11)&"") | F11: =IF($X11="","",INDEX('Per Line'!$F$2:$F$1501,$X11)) | G11: =IF($X11="","",INDEX('Per Line'!$I$2:$I$1501,$X11)&"") | H11: =IF($X11="","",INDEX('Per Line'!$J$2:$J$1501,$X11)&"") | I11: =IF($X11="","",INDEX('Per Line'!$K$2:$K$1501,$X11)&"") | J11: =IF($X11="","",INDEX('Per Line'!$M$2:$M$1501,$X11)) | K11: =IF($X11="","",J11*V11/100) | L11: =IF($X11="","",INDEX('Per Line'!$Y$2:$Y$1501,$X11)&"") | M11: =IF($X11="","",SUMIFS('Per Line'!$U$2:$U$1501,'Per Line'!$AJ$2:$AJ$1501,$A11&"|"&$C11,'Per Line'!$AN$2:$AN$1501,1)) | N11: =IF($X11="","",Settings!$C$7) | O11: =IF($X11="","",SUMIFS('Per Line'!$U$2:$U$1501,'Per Line'!$AJ$2:$AJ$1501,$A11&"|"&$C11,'Per Line'!$AM$2:$AM$1501,0,'Per Line'!$AN$2:$AN$1501,0)) | P11: =IF($X11="","",O11*N11) | Q11: =IF($X11="","",Settings!$C$6) | R11: =IF($X11="","",SUMIFS('Per Line'!$U$2:$U$1501,'Per Line'!$AJ$2:$AJ$1501,$A11&"|"&$C11,'Per Line'!$AM$2:$AM$1501,1,'Per Line'!$AN$2:$AN$1501,0)) | S11: =IF($X11="","",R11*Q11) | T11: =IF($X11="","",S11+P11) | U11: =IF($X11="","",V11-T11) | V11: =IF($X11="","",O11+R11+M11) | W11: =IF($X11="","",V11-T11-K11) | X11: =IF(ROWS($X$2:$X11)<=MAX('Per Line'!$AL$2:$AL$1501),MATCH(ROWS($X$2:$X11),'Per Line'!$AL$2:$AL$1501,0),"")
A12: =IF($X12="","",INDEX('Per Line'!$C$2:$C$1501,$X12)&"") | C12: =IF($X12="","",INDEX('Per Line'!$D$2:$D$1501,$X12)&"") | D12: =IF($X12="","",INDEX('Per Line'!$A$2:$A$1501,$X12)) | E12: =IF($X12="","",INDEX('Per Line'!$G$2:$G$1501,$X12)&"") | F12: =IF($X12="","",INDEX('Per Line'!$F$2:$F$1501,$X12)) | G12: =IF($X12="","",INDEX('Per Line'!$I$2:$I$1501,$X12)&"") | H12: =IF($X12="","",INDEX('Per Line'!$J$2:$J$1501,$X12)&"") | I12: =IF($X12="","",INDEX('Per Line'!$K$2:$K$1501,$X12)&"") | J12: =IF($X12="","",INDEX('Per Line'!$M$2:$M$1501,$X12)) | K12: =IF($X12="","",J12*V12/100) | L12: =IF($X12="","",INDEX('Per Line'!$Y$2:$Y$1501,$X12)&"") | M12: =IF($X12="","",SUMIFS('Per Line'!$U$2:$U$1501,'Per Line'!$AJ$2:$AJ$1501,$A12&"|"&$C12,'Per Line'!$AN$2:$AN$1501,1)) | N12: =IF($X12="","",Settings!$C$7) | O12: =IF($X12="","",SUMIFS('Per Line'!$U$2:$U$1501,'Per Line'!$AJ$2:$AJ$1501,$A12&"|"&$C12,'Per Line'!$AM$2:$AM$1501,0,'Per Line'!$AN$2:$AN$1501,0)) | P12: =IF($X12="","",O12*N12) | Q12: =IF($X12="","",Settings!$C$6) | R12: =IF($X12="","",SUMIFS('Per Line'!$U$2:$U$1501,'Per Line'!$AJ$2:$AJ$1501,$A12&"|"&$C12,'Per Line'!$AM$2:$AM$1501,1,'Per Line'!$AN$2:$AN$1501,0)) | S12: =IF($X12="","",R12*Q12) | T12: =IF($X12="","",S12+P12) | U12: =IF($X12="","",V12-T12) | V12: =IF($X12="","",O12+R12+M12) | W12: =IF($X12="","",V12-T12-K12) | X12: =IF(ROWS($X$2:$X12)<=MAX('Per Line'!$AL$2:$AL$1501),MATCH(ROWS($X$2:$X12),'Per Line'!$AL$2:$AL$1501,0),"")
A13: =IF($X13="","",INDEX('Per Line'!$C$2:$C$1501,$X13)&"") | C13: =IF($X13="","",INDEX('Per Line'!$D$2:$D$1501,$X13)&"") | D13: =IF($X13="","",INDEX('Per Line'!$A$2:$A$1501,$X13)) | E13: =IF($X13="","",INDEX('Per Line'!$G$2:$G$1501,$X13)&"") | F13: =IF($X13="","",INDEX('Per Line'!$F$2:$F$1501,$X13)) | G13: =IF($X13="","",INDEX('Per Line'!$I$2:$I$1501,$X13)&"") | H13: =IF($X13="","",INDEX('Per Line'!$J$2:$J$1501,$X13)&"") | I13: =IF($X13="","",INDEX('Per Line'!$K$2:$K$1501,$X13)&"") | J13: =IF($X13="","",INDEX('Per Line'!$M$2:$M$1501,$X13)) | K13: =IF($X13="","",J13*V13/100) | L13: =IF($X13="","",INDEX('Per Line'!$Y$2:$Y$1501,$X13)&"") | M13: =IF($X13="","",SUMIFS('Per Line'!$U$2:$U$1501,'Per Line'!$AJ$2:$AJ$1501,$A13&"|"&$C13,'Per Line'!$AN$2:$AN$1501,1)) | N13: =IF($X13="","",Settings!$C$7) | O13: =IF($X13="","",SUMIFS('Per Line'!$U$2:$U$1501,'Per Line'!$AJ$2:$AJ$1501,$A13&"|"&$C13,'Per Line'!$AM$2:$AM$1501,0,'Per Line'!$AN$2:$AN$1501,0)) | P13: =IF($X13="","",O13*N13) | Q13: =IF($X13="","",Settings!$C$6) | R13: =IF($X13="","",SUMIFS('Per Line'!$U$2:$U$1501,'Per Line'!$AJ$2:$AJ$1501,$A13&"|"&$C13,'Per Line'!$AM$2:$AM$1501,1,'Per Line'!$AN$2:$AN$1501,0)) | S13: =IF($X13="","",R13*Q13) | T13: =IF($X13="","",S13+P13) | U13: =IF($X13="","",V13-T13) | V13: =IF($X13="","",O13+R13+M13) | W13: =IF($X13="","",V13-T13-K13) | X13: =IF(ROWS($X$2:$X13)<=MAX('Per Line'!$AL$2:$AL$1501),MATCH(ROWS($X$2:$X13),'Per Line'!$AL$2:$AL$1501,0),"")
... A501: =IF($X501="","",INDEX('Per Line'!$C$2:$C$1501,$X501)&"") | C501: =IF($X501="","",INDEX('Per Line'!$D$2:$D$1501,$X501)&"") | D501: =IF($X501="","",INDEX('Per Line'!$A$2:$A$1501,$X501)) | E501: =IF($X501="","",INDEX('Per Line'!$G$2:$G$1501,$X501)&"") | F501: =IF($X501="","",INDEX('Per Line'!$F$2:$F$1501,$X501)) | G501: =IF($X501="","",INDEX('Per Line'!$I$2:$I$1501,$X501)&"") | H501: =IF($X501="","",INDEX('Per Line'!$J$2:$J$1501,$X501)&"") | I501: =IF($X501="","",INDEX('Per Line'!$K$2:$K$1501,$X501)&"") | J501: =IF($X501="","",INDEX('Per Line'!$M$2:$M$1501,$X501)) | K501: =IF($X501="","",J501*V501/100) | L501: =IF($X501="","",INDEX('Per Line'!$Y$2:$Y$1501,$X501)&"") | M501: =IF($X501="","",SUMIFS('Per Line'!$U$2:$U$1501,'Per Line'!$AJ$2:$AJ$1501,$A501&"|"&$C501,'Per Line'!$AN$2:$AN$1501,1)) | N501: =IF($X501="","",Settings!$C$7) | O501: =IF($X501="","",SUMIFS('Per Line'!$U$2:$U$1501,'Per Line'!$AJ$2:$AJ$1501,$A501&"|"&$C501,'Per Line'!$AM$2:$AM$1501,0,'Per Line'!$AN$2:$AN$1501,0)) | P501: =IF($X501="","",O501*N501) | Q501: =IF($X501="","",Settings!$C$6) | R501: =IF($X501="","",SUMIFS('Per Line'!$U$2:$U$1501,'Per Line'!$AJ$2:$AJ$1501,$A501&"|"&$C501,'Per Line'!$AM$2:$AM$1501,1,'Per Line'!$AN$2:$AN$1501,0)) | S501: =IF($X501="","",R501*Q501) | T501: =IF($X501="","",S501+P501) | U501: =IF($X501="","",V501-T501) | V501: =IF($X501="","",O501+R501+M501) | W501: =IF($X501="","",V501-T501-K501) | X501: =IF(ROWS($X$2:$X501)<=MAX('Per Line'!$AL$2:$AL$1501),MATCH(ROWS($X$2:$X501),'Per Line'!$AL$2:$AL$1501,0),"")
