Workbook

Sheet How To Use
A1: Claims Template - EGYCARE (VPN)
A3: Monthly steps
A4: 1. Open the 'Per Line' tab. Delete the old data in the BLUE columns only (row 2 down). Never delete the green or grey columns.
A5: 2. Paste the new month's data as VALUES starting at A2, into the blue columns: A-M, O-U, Y-Z (same order as the system export).
A6: 3. Green columns (N, V, W, X, AA) and the grey helper columns (AB-AE) calculate automatically - do not paste over them.
A7: 4. 'Per Invoice' fills itself from 'Per Line' (one row per Order #, split into IMP / Local). No pivot table, no refresh.
A8: 5. The columns you type yourself in 'Per Invoice' (blue headers): A 'Invoice', H 'CARD', V 'Comment'. Everything else is formula. Type them AFTER pasting the month data (they follow the row, not the order).
A9: 6. Open 'Settings' and check STATUS says OK (Per Line totals = Per Invoice totals).
A11: Colour legend
A12: Blue header = typed/pasted by you (raw data, and 'Invoice' in Per Invoice). Green header = formula (do not paste over). Grey header = helper formula (do not touch). Yellow cell (Settings) = editable rate.
A14: Calculation rules (taken from the July 2026 sheet)
A15: Co val = Order Co Payment x Total / 100. Discount = Total x Rebates / 100. Subtotal = Total - Discount. Net = Subtotal - Co val. (Total = 'Item Total Price (EGP)')
... A20: Capacity: up to 500 lines and 200 invoices per month. A line with an empty Order # is ignored.

Sheet Settings
B1: Company settings & checks
B3: Insurance Company | C3: EGYCARE | D3: Informational only
B4: Corporate | C4: - | D4: Informational only
B5: Sheet type | C5: VPN | D5: Informational only
B6: Local products rebate % | C6: 0.11 | D6: Source: July sheet (Rebates = 11 when Imported = FALSE).
B7: Imported (IMP) products rebate % | C7: 0.04 | D7: Source: July sheet (Rebates = 4 when Imported = TRUE).
B9: Month totals / reconciliation
B10: Lines loaded | C10: =COUNTA('Per Line'!$C$2:$C$501)
B11: Invoices (unique Order #) | C11: =MAX('Per Line'!$AC$2:$AC$501)
B12: Invoices shown in Per Invoice | C12: =SUMPRODUCT(--('Per Invoice'!$B$2:$B$201<>""))
B13: Grand Total - Per Line (Product Total) | C13: =SUM('Per Line'!$Y$2:$Y$501)
B14: Grand Total - Per Invoice | C14: =SUM('Per Invoice'!$T$2:$T$201)
B15: Discount - Per Line | C15: =SUM('Per Line'!$V$2:$V$501)
B16: Discount - Per Invoice | C16: =SUM('Per Invoice'!$R$2:$R$201)
B17: Co val - Per Line | C17: =SUM('Per Line'!$N$2:$N$501)
B18: Co val - Per Invoice | C18: =SUM('Per Invoice'!$J$2:$J$201)
B19: Net - Per Line | C19: =SUM('Per Line'!$X$2:$X$501)
B20: Net - Per Invoice | C20: =SUM('Per Invoice'!$U$2:$U$201)
B21: Max Limit adjustment (Co val, Per Invoice only) | C21: 0 | D21: This company's Per Invoice has no Max Limit rule.
B23: STATUS | C23: =IF(C10=0,"No data loaded",IF(COUNTA('Per Line'!$C:$C)-1>500,"TOO MANY LINES - extend template",IF(C11>200,"TOO MANY INVOICES - extend template",IF(AND(ROUND(C13-C14,2)=0,ROUND(C15-C16,2)=0,ROUND(C17+C21-C18,2)=0,ROUND(C19-C21-C20,2)=0,C11=C12),"OK","CHECK - Per Line and Per Invoice do not match")))) | D23: Must say OK after you paste the month data.

Sheet Per Line
A1: ERX ID | B1: Mongo Order ID | C1: Order Number | D1: Approval Number | E1: Approval Reference | F1: Order Status | G1: Total (EGP) | H1: By Patient (EGP) | I1: Order Type | J1: Original Order Type | K1: Payer | L1: Card Holder Name | M1: Co Payment (%) | N1: Co val | O1: Creation Date | P1: Heisenberg ID | Q1: Item | R1: Item Unit | S1: Item Form | T1: Item Price (EGP) | U1: Item Quantity | V1: Discount | W1: Subtotal | X1: Net | Y1: Item Total Price (EGP) | Z1: Imported | AA1: Rebates | AB1: Order 1st Row (helper) | AC1: Invoice # (helper) | AD1: Is Local (helper) | AE1: Sort Key (helper)
N2: =IF($C2="","",M2*Y2/100) | V2: =IF($C2="","",Y2*AA2/100) | W2: =IF($C2="","",Y2-V2) | X2: =IF($C2="","",W2-N2) | AA2: =IF($C2="","",IF($AD2=1,Settings!$C$6,Settings!$C$7)*100) | AB2: =IF($C2="","",IF(COUNTIF($C$2:$C2,$C2)=1,1,0)) | AC2: =IF($AB2=1,SUMPRODUCT(--($AE$2:$AE$501<$AE2))+1,"") | AD2: =IF($C2="","",IF(OR($Z2=TRUE(),$Z2="TRUE"),0,1)) | AE2: =IF($AB2=1,IFERROR(IF(VALUE($C2)<100000000,VALUE($C2),1000000000),IFERROR(IF(VALUE(MID($C2,2,20))<100000000,VALUE(MID($C2,2,20)),1000000000),1000000000))+ROW()/100000,"")
N3: =IF($C3="","",M3*Y3/100) | V3: =IF($C3="","",Y3*AA3/100) | W3: =IF($C3="","",Y3-V3) | X3: =IF($C3="","",W3-N3) | AA3: =IF($C3="","",IF($AD3=1,Settings!$C$6,Settings!$C$7)*100) | AB3: =IF($C3="","",IF(COUNTIF($C$2:$C3,$C3)=1,1,0)) | AC3: =IF($AB3=1,SUMPRODUCT(--($AE$2:$AE$501<$AE3))+1,"") | AD3: =IF($C3="","",IF(OR($Z3=TRUE(),$Z3="TRUE"),0,1)) | AE3: =IF($AB3=1,IFERROR(IF(VALUE($C3)<100000000,VALUE($C3),1000000000),IFERROR(IF(VALUE(MID($C3,2,20))<100000000,VALUE(MID($C3,2,20)),1000000000),1000000000))+ROW()/100000,"")
N4: =IF($C4="","",M4*Y4/100) | V4: =IF($C4="","",Y4*AA4/100) | W4: =IF($C4="","",Y4-V4) | X4: =IF($C4="","",W4-N4) | AA4: =IF($C4="","",IF($AD4=1,Settings!$C$6,Settings!$C$7)*100) | AB4: =IF($C4="","",IF(COUNTIF($C$2:$C4,$C4)=1,1,0)) | AC4: =IF($AB4=1,SUMPRODUCT(--($AE$2:$AE$501<$AE4))+1,"") | AD4: =IF($C4="","",IF(OR($Z4=TRUE(),$Z4="TRUE"),0,1)) | AE4: =IF($AB4=1,IFERROR(IF(VALUE($C4)<100000000,VALUE($C4),1000000000),IFERROR(IF(VALUE(MID($C4,2,20))<100000000,VALUE(MID($C4,2,20)),1000000000),1000000000))+ROW()/100000,"")
N5: =IF($C5="","",M5*Y5/100) | V5: =IF($C5="","",Y5*AA5/100) | W5: =IF($C5="","",Y5-V5) | X5: =IF($C5="","",W5-N5) | AA5: =IF($C5="","",IF($AD5=1,Settings!$C$6,Settings!$C$7)*100) | AB5: =IF($C5="","",IF(COUNTIF($C$2:$C5,$C5)=1,1,0)) | AC5: =IF($AB5=1,SUMPRODUCT(--($AE$2:$AE$501<$AE5))+1,"") | AD5: =IF($C5="","",IF(OR($Z5=TRUE(),$Z5="TRUE"),0,1)) | AE5: =IF($AB5=1,IFERROR(IF(VALUE($C5)<100000000,VALUE($C5),1000000000),IFERROR(IF(VALUE(MID($C5,2,20))<100000000,VALUE(MID($C5,2,20)),1000000000),1000000000))+ROW()/100000,"")
N6: =IF($C6="","",M6*Y6/100) | V6: =IF($C6="","",Y6*AA6/100) | W6: =IF($C6="","",Y6-V6) | X6: =IF($C6="","",W6-N6) | AA6: =IF($C6="","",IF($AD6=1,Settings!$C$6,Settings!$C$7)*100) | AB6: =IF($C6="","",IF(COUNTIF($C$2:$C6,$C6)=1,1,0)) | AC6: =IF($AB6=1,SUMPRODUCT(--($AE$2:$AE$501<$AE6))+1,"") | AD6: =IF($C6="","",IF(OR($Z6=TRUE(),$Z6="TRUE"),0,1)) | AE6: =IF($AB6=1,IFERROR(IF(VALUE($C6)<100000000,VALUE($C6),1000000000),IFERROR(IF(VALUE(MID($C6,2,20))<100000000,VALUE(MID($C6,2,20)),1000000000),1000000000))+ROW()/100000,"")
N7: =IF($C7="","",M7*Y7/100) | V7: =IF($C7="","",Y7*AA7/100) | W7: =IF($C7="","",Y7-V7) | X7: =IF($C7="","",W7-N7) | AA7: =IF($C7="","",IF($AD7=1,Settings!$C$6,Settings!$C$7)*100) | AB7: =IF($C7="","",IF(COUNTIF($C$2:$C7,$C7)=1,1,0)) | AC7: =IF($AB7=1,SUMPRODUCT(--($AE$2:$AE$501<$AE7))+1,"") | AD7: =IF($C7="","",IF(OR($Z7=TRUE(),$Z7="TRUE"),0,1)) | AE7: =IF($AB7=1,IFERROR(IF(VALUE($C7)<100000000,VALUE($C7),1000000000),IFERROR(IF(VALUE(MID($C7,2,20))<100000000,VALUE(MID($C7,2,20)),1000000000),1000000000))+ROW()/100000,"")
N8: =IF($C8="","",M8*Y8/100) | V8: =IF($C8="","",Y8*AA8/100) | W8: =IF($C8="","",Y8-V8) | X8: =IF($C8="","",W8-N8) | AA8: =IF($C8="","",IF($AD8=1,Settings!$C$6,Settings!$C$7)*100) | AB8: =IF($C8="","",IF(COUNTIF($C$2:$C8,$C8)=1,1,0)) | AC8: =IF($AB8=1,SUMPRODUCT(--($AE$2:$AE$501<$AE8))+1,"") | AD8: =IF($C8="","",IF(OR($Z8=TRUE(),$Z8="TRUE"),0,1)) | AE8: =IF($AB8=1,IFERROR(IF(VALUE($C8)<100000000,VALUE($C8),1000000000),IFERROR(IF(VALUE(MID($C8,2,20))<100000000,VALUE(MID($C8,2,20)),1000000000),1000000000))+ROW()/100000,"")
N9: =IF($C9="","",M9*Y9/100) | V9: =IF($C9="","",Y9*AA9/100) | W9: =IF($C9="","",Y9-V9) | X9: =IF($C9="","",W9-N9) | AA9: =IF($C9="","",IF($AD9=1,Settings!$C$6,Settings!$C$7)*100) | AB9: =IF($C9="","",IF(COUNTIF($C$2:$C9,$C9)=1,1,0)) | AC9: =IF($AB9=1,SUMPRODUCT(--($AE$2:$AE$501<$AE9))+1,"") | AD9: =IF($C9="","",IF(OR($Z9=TRUE(),$Z9="TRUE"),0,1)) | AE9: =IF($AB9=1,IFERROR(IF(VALUE($C9)<100000000,VALUE($C9),1000000000),IFERROR(IF(VALUE(MID($C9,2,20))<100000000,VALUE(MID($C9,2,20)),1000000000),1000000000))+ROW()/100000,"")
N10: =IF($C10="","",M10*Y10/100) | V10: =IF($C10="","",Y10*AA10/100) | W10: =IF($C10="","",Y10-V10) | X10: =IF($C10="","",W10-N10) | AA10: =IF($C10="","",IF($AD10=1,Settings!$C$6,Settings!$C$7)*100) | AB10: =IF($C10="","",IF(COUNTIF($C$2:$C10,$C10)=1,1,0)) | AC10: =IF($AB10=1,SUMPRODUCT(--($AE$2:$AE$501<$AE10))+1,"") | AD10: =IF($C10="","",IF(OR($Z10=TRUE(),$Z10="TRUE"),0,1)) | AE10: =IF($AB10=1,IFERROR(IF(VALUE($C10)<100000000,VALUE($C10),1000000000),IFERROR(IF(VALUE(MID($C10,2,20))<100000000,VALUE(MID($C10,2,20)),1000000000),1000000000))+ROW()/100000,"")
N11: =IF($C11="","",M11*Y11/100) | V11: =IF($C11="","",Y11*AA11/100) | W11: =IF($C11="","",Y11-V11) | X11: =IF($C11="","",W11-N11) | AA11: =IF($C11="","",IF($AD11=1,Settings!$C$6,Settings!$C$7)*100) | AB11: =IF($C11="","",IF(COUNTIF($C$2:$C11,$C11)=1,1,0)) | AC11: =IF($AB11=1,SUMPRODUCT(--($AE$2:$AE$501<$AE11))+1,"") | AD11: =IF($C11="","",IF(OR($Z11=TRUE(),$Z11="TRUE"),0,1)) | AE11: =IF($AB11=1,IFERROR(IF(VALUE($C11)<100000000,VALUE($C11),1000000000),IFERROR(IF(VALUE(MID($C11,2,20))<100000000,VALUE(MID($C11,2,20)),1000000000),1000000000))+ROW()/100000,"")
N12: =IF($C12="","",M12*Y12/100) | V12: =IF($C12="","",Y12*AA12/100) | W12: =IF($C12="","",Y12-V12) | X12: =IF($C12="","",W12-N12) | AA12: =IF($C12="","",IF($AD12=1,Settings!$C$6,Settings!$C$7)*100) | AB12: =IF($C12="","",IF(COUNTIF($C$2:$C12,$C12)=1,1,0)) | AC12: =IF($AB12=1,SUMPRODUCT(--($AE$2:$AE$501<$AE12))+1,"") | AD12: =IF($C12="","",IF(OR($Z12=TRUE(),$Z12="TRUE"),0,1)) | AE12: =IF($AB12=1,IFERROR(IF(VALUE($C12)<100000000,VALUE($C12),1000000000),IFERROR(IF(VALUE(MID($C12,2,20))<100000000,VALUE(MID($C12,2,20)),1000000000),1000000000))+ROW()/100000,"")
N13: =IF($C13="","",M13*Y13/100) | V13: =IF($C13="","",Y13*AA13/100) | W13: =IF($C13="","",Y13-V13) | X13: =IF($C13="","",W13-N13) | AA13: =IF($C13="","",IF($AD13=1,Settings!$C$6,Settings!$C$7)*100) | AB13: =IF($C13="","",IF(COUNTIF($C$2:$C13,$C13)=1,1,0)) | AC13: =IF($AB13=1,SUMPRODUCT(--($AE$2:$AE$501<$AE13))+1,"") | AD13: =IF($C13="","",IF(OR($Z13=TRUE(),$Z13="TRUE"),0,1)) | AE13: =IF($AB13=1,IFERROR(IF(VALUE($C13)<100000000,VALUE($C13),1000000000),IFERROR(IF(VALUE(MID($C13,2,20))<100000000,VALUE(MID($C13,2,20)),1000000000),1000000000))+ROW()/100000,"")
... N501: =IF($C501="","",M501*Y501/100) | V501: =IF($C501="","",Y501*AA501/100) | W501: =IF($C501="","",Y501-V501) | X501: =IF($C501="","",W501-N501) | AA501: =IF($C501="","",IF($AD501=1,Settings!$C$6,Settings!$C$7)*100) | AB501: =IF($C501="","",IF(COUNTIF($C$2:$C501,$C501)=1,1,0)) | AC501: =IF($AB501=1,SUMPRODUCT(--($AE$2:$AE$501<$AE501))+1,"") | AD501: =IF($C501="","",IF(OR($Z501=TRUE(),$Z501="TRUE"),0,1)) | AE501: =IF($AB501=1,IFERROR(IF(VALUE($C501)<100000000,VALUE($C501),1000000000),IFERROR(IF(VALUE(MID($C501,2,20))<100000000,VALUE(MID($C501,2,20)),1000000000),1000000000))+ROW()/100000,"")

Sheet Per Invoice
A1: Invoice | B1: Order Number | C1: ERX ID | D1: Approval Reference | E1: By Patient (EGP) | F1: Payer | G1: Card Holder Name | H1: CARD | I1: Co Payment (%) | J1: Co val | K1: Creation Date | L1: % | M1: IMP | N1: IMP val | O1: % | P1: Local | Q1: Local val | R1: Discount | S1: Subtotal | T1: Grand Total | U1: Net | V1: Comment | W1: Src Row (helper)
B2: =IF($W2="","",INDEX('Per Line'!$C$2:$C$501,$W2)&"") | C2: =IF($W2="","",INDEX('Per Line'!$A$2:$A$501,$W2)&"") | D2: =IF($W2="","",INDEX('Per Line'!$E$2:$E$501,$W2)&"") | E2: =IF($W2="","",INDEX('Per Line'!$H$2:$H$501,$W2)&"") | F2: =IF($W2="","",INDEX('Per Line'!$K$2:$K$501,$W2)&"") | G2: =IF($W2="","",INDEX('Per Line'!$L$2:$L$501,$W2)&"") | I2: =IF($W2="","",INDEX('Per Line'!$M$2:$M$501,$W2)) | J2: =IF($W2="","",I2*T2/100) | K2: =IF($W2="","",INDEX('Per Line'!$O$2:$O$501,$W2)) | L2: =IF($W2="","",Settings!$C$7) | M2: =IF($W2="","",SUMIFS('Per Line'!$Y$2:$Y$501,'Per Line'!$C$2:$C$501,$B2,'Per Line'!$AD$2:$AD$501,0)) | N2: =IF($W2="","",M2*L2) | O2: =IF($W2="","",Settings!$C$6) | P2: =IF($W2="","",SUMIFS('Per Line'!$Y$2:$Y$501,'Per Line'!$C$2:$C$501,$B2,'Per Line'!$AD$2:$AD$501,1)) | Q2: =IF($W2="","",P2*O2) | R2: =IF($W2="","",Q2+N2) | S2: =IF($W2="","",T2-R2) | T2: =IF($W2="","",M2+P2) | U2: =IF($W2="","",T2-R2-J2) | W2: =IF(ROWS($W$2:$W2)<=MAX('Per Line'!$AC$2:$AC$501),MATCH(ROWS($W$2:$W2),'Per Line'!$AC$2:$AC$501,0),"")
B3: =IF($W3="","",INDEX('Per Line'!$C$2:$C$501,$W3)&"") | C3: =IF($W3="","",INDEX('Per Line'!$A$2:$A$501,$W3)&"") | D3: =IF($W3="","",INDEX('Per Line'!$E$2:$E$501,$W3)&"") | E3: =IF($W3="","",INDEX('Per Line'!$H$2:$H$501,$W3)&"") | F3: =IF($W3="","",INDEX('Per Line'!$K$2:$K$501,$W3)&"") | G3: =IF($W3="","",INDEX('Per Line'!$L$2:$L$501,$W3)&"") | I3: =IF($W3="","",INDEX('Per Line'!$M$2:$M$501,$W3)) | J3: =IF($W3="","",I3*T3/100) | K3: =IF($W3="","",INDEX('Per Line'!$O$2:$O$501,$W3)) | L3: =IF($W3="","",Settings!$C$7) | M3: =IF($W3="","",SUMIFS('Per Line'!$Y$2:$Y$501,'Per Line'!$C$2:$C$501,$B3,'Per Line'!$AD$2:$AD$501,0)) | N3: =IF($W3="","",M3*L3) | O3: =IF($W3="","",Settings!$C$6) | P3: =IF($W3="","",SUMIFS('Per Line'!$Y$2:$Y$501,'Per Line'!$C$2:$C$501,$B3,'Per Line'!$AD$2:$AD$501,1)) | Q3: =IF($W3="","",P3*O3) | R3: =IF($W3="","",Q3+N3) | S3: =IF($W3="","",T3-R3) | T3: =IF($W3="","",M3+P3) | U3: =IF($W3="","",T3-R3-J3) | W3: =IF(ROWS($W$2:$W3)<=MAX('Per Line'!$AC$2:$AC$501),MATCH(ROWS($W$2:$W3),'Per Line'!$AC$2:$AC$501,0),"")
B4: =IF($W4="","",INDEX('Per Line'!$C$2:$C$501,$W4)&"") | C4: =IF($W4="","",INDEX('Per Line'!$A$2:$A$501,$W4)&"") | D4: =IF($W4="","",INDEX('Per Line'!$E$2:$E$501,$W4)&"") | E4: =IF($W4="","",INDEX('Per Line'!$H$2:$H$501,$W4)&"") | F4: =IF($W4="","",INDEX('Per Line'!$K$2:$K$501,$W4)&"") | G4: =IF($W4="","",INDEX('Per Line'!$L$2:$L$501,$W4)&"") | I4: =IF($W4="","",INDEX('Per Line'!$M$2:$M$501,$W4)) | J4: =IF($W4="","",I4*T4/100) | K4: =IF($W4="","",INDEX('Per Line'!$O$2:$O$501,$W4)) | L4: =IF($W4="","",Settings!$C$7) | M4: =IF($W4="","",SUMIFS('Per Line'!$Y$2:$Y$501,'Per Line'!$C$2:$C$501,$B4,'Per Line'!$AD$2:$AD$501,0)) | N4: =IF($W4="","",M4*L4) | O4: =IF($W4="","",Settings!$C$6) | P4: =IF($W4="","",SUMIFS('Per Line'!$Y$2:$Y$501,'Per Line'!$C$2:$C$501,$B4,'Per Line'!$AD$2:$AD$501,1)) | Q4: =IF($W4="","",P4*O4) | R4: =IF($W4="","",Q4+N4) | S4: =IF($W4="","",T4-R4) | T4: =IF($W4="","",M4+P4) | U4: =IF($W4="","",T4-R4-J4) | W4: =IF(ROWS($W$2:$W4)<=MAX('Per Line'!$AC$2:$AC$501),MATCH(ROWS($W$2:$W4),'Per Line'!$AC$2:$AC$501,0),"")
B5: =IF($W5="","",INDEX('Per Line'!$C$2:$C$501,$W5)&"") | C5: =IF($W5="","",INDEX('Per Line'!$A$2:$A$501,$W5)&"") | D5: =IF($W5="","",INDEX('Per Line'!$E$2:$E$501,$W5)&"") | E5: =IF($W5="","",INDEX('Per Line'!$H$2:$H$501,$W5)&"") | F5: =IF($W5="","",INDEX('Per Line'!$K$2:$K$501,$W5)&"") | G5: =IF($W5="","",INDEX('Per Line'!$L$2:$L$501,$W5)&"") | I5: =IF($W5="","",INDEX('Per Line'!$M$2:$M$501,$W5)) | J5: =IF($W5="","",I5*T5/100) | K5: =IF($W5="","",INDEX('Per Line'!$O$2:$O$501,$W5)) | L5: =IF($W5="","",Settings!$C$7) | M5: =IF($W5="","",SUMIFS('Per Line'!$Y$2:$Y$501,'Per Line'!$C$2:$C$501,$B5,'Per Line'!$AD$2:$AD$501,0)) | N5: =IF($W5="","",M5*L5) | O5: =IF($W5="","",Settings!$C$6) | P5: =IF($W5="","",SUMIFS('Per Line'!$Y$2:$Y$501,'Per Line'!$C$2:$C$501,$B5,'Per Line'!$AD$2:$AD$501,1)) | Q5: =IF($W5="","",P5*O5) | R5: =IF($W5="","",Q5+N5) | S5: =IF($W5="","",T5-R5) | T5: =IF($W5="","",M5+P5) | U5: =IF($W5="","",T5-R5-J5) | W5: =IF(ROWS($W$2:$W5)<=MAX('Per Line'!$AC$2:$AC$501),MATCH(ROWS($W$2:$W5),'Per Line'!$AC$2:$AC$501,0),"")
B6: =IF($W6="","",INDEX('Per Line'!$C$2:$C$501,$W6)&"") | C6: =IF($W6="","",INDEX('Per Line'!$A$2:$A$501,$W6)&"") | D6: =IF($W6="","",INDEX('Per Line'!$E$2:$E$501,$W6)&"") | E6: =IF($W6="","",INDEX('Per Line'!$H$2:$H$501,$W6)&"") | F6: =IF($W6="","",INDEX('Per Line'!$K$2:$K$501,$W6)&"") | G6: =IF($W6="","",INDEX('Per Line'!$L$2:$L$501,$W6)&"") | I6: =IF($W6="","",INDEX('Per Line'!$M$2:$M$501,$W6)) | J6: =IF($W6="","",I6*T6/100) | K6: =IF($W6="","",INDEX('Per Line'!$O$2:$O$501,$W6)) | L6: =IF($W6="","",Settings!$C$7) | M6: =IF($W6="","",SUMIFS('Per Line'!$Y$2:$Y$501,'Per Line'!$C$2:$C$501,$B6,'Per Line'!$AD$2:$AD$501,0)) | N6: =IF($W6="","",M6*L6) | O6: =IF($W6="","",Settings!$C$6) | P6: =IF($W6="","",SUMIFS('Per Line'!$Y$2:$Y$501,'Per Line'!$C$2:$C$501,$B6,'Per Line'!$AD$2:$AD$501,1)) | Q6: =IF($W6="","",P6*O6) | R6: =IF($W6="","",Q6+N6) | S6: =IF($W6="","",T6-R6) | T6: =IF($W6="","",M6+P6) | U6: =IF($W6="","",T6-R6-J6) | W6: =IF(ROWS($W$2:$W6)<=MAX('Per Line'!$AC$2:$AC$501),MATCH(ROWS($W$2:$W6),'Per Line'!$AC$2:$AC$501,0),"")
B7: =IF($W7="","",INDEX('Per Line'!$C$2:$C$501,$W7)&"") | C7: =IF($W7="","",INDEX('Per Line'!$A$2:$A$501,$W7)&"") | D7: =IF($W7="","",INDEX('Per Line'!$E$2:$E$501,$W7)&"") | E7: =IF($W7="","",INDEX('Per Line'!$H$2:$H$501,$W7)&"") | F7: =IF($W7="","",INDEX('Per Line'!$K$2:$K$501,$W7)&"") | G7: =IF($W7="","",INDEX('Per Line'!$L$2:$L$501,$W7)&"") | I7: =IF($W7="","",INDEX('Per Line'!$M$2:$M$501,$W7)) | J7: =IF($W7="","",I7*T7/100) | K7: =IF($W7="","",INDEX('Per Line'!$O$2:$O$501,$W7)) | L7: =IF($W7="","",Settings!$C$7) | M7: =IF($W7="","",SUMIFS('Per Line'!$Y$2:$Y$501,'Per Line'!$C$2:$C$501,$B7,'Per Line'!$AD$2:$AD$501,0)) | N7: =IF($W7="","",M7*L7) | O7: =IF($W7="","",Settings!$C$6) | P7: =IF($W7="","",SUMIFS('Per Line'!$Y$2:$Y$501,'Per Line'!$C$2:$C$501,$B7,'Per Line'!$AD$2:$AD$501,1)) | Q7: =IF($W7="","",P7*O7) | R7: =IF($W7="","",Q7+N7) | S7: =IF($W7="","",T7-R7) | T7: =IF($W7="","",M7+P7) | U7: =IF($W7="","",T7-R7-J7) | W7: =IF(ROWS($W$2:$W7)<=MAX('Per Line'!$AC$2:$AC$501),MATCH(ROWS($W$2:$W7),'Per Line'!$AC$2:$AC$501,0),"")
B8: =IF($W8="","",INDEX('Per Line'!$C$2:$C$501,$W8)&"") | C8: =IF($W8="","",INDEX('Per Line'!$A$2:$A$501,$W8)&"") | D8: =IF($W8="","",INDEX('Per Line'!$E$2:$E$501,$W8)&"") | E8: =IF($W8="","",INDEX('Per Line'!$H$2:$H$501,$W8)&"") | F8: =IF($W8="","",INDEX('Per Line'!$K$2:$K$501,$W8)&"") | G8: =IF($W8="","",INDEX('Per Line'!$L$2:$L$501,$W8)&"") | I8: =IF($W8="","",INDEX('Per Line'!$M$2:$M$501,$W8)) | J8: =IF($W8="","",I8*T8/100) | K8: =IF($W8="","",INDEX('Per Line'!$O$2:$O$501,$W8)) | L8: =IF($W8="","",Settings!$C$7) | M8: =IF($W8="","",SUMIFS('Per Line'!$Y$2:$Y$501,'Per Line'!$C$2:$C$501,$B8,'Per Line'!$AD$2:$AD$501,0)) | N8: =IF($W8="","",M8*L8) | O8: =IF($W8="","",Settings!$C$6) | P8: =IF($W8="","",SUMIFS('Per Line'!$Y$2:$Y$501,'Per Line'!$C$2:$C$501,$B8,'Per Line'!$AD$2:$AD$501,1)) | Q8: =IF($W8="","",P8*O8) | R8: =IF($W8="","",Q8+N8) | S8: =IF($W8="","",T8-R8) | T8: =IF($W8="","",M8+P8) | U8: =IF($W8="","",T8-R8-J8) | W8: =IF(ROWS($W$2:$W8)<=MAX('Per Line'!$AC$2:$AC$501),MATCH(ROWS($W$2:$W8),'Per Line'!$AC$2:$AC$501,0),"")
B9: =IF($W9="","",INDEX('Per Line'!$C$2:$C$501,$W9)&"") | C9: =IF($W9="","",INDEX('Per Line'!$A$2:$A$501,$W9)&"") | D9: =IF($W9="","",INDEX('Per Line'!$E$2:$E$501,$W9)&"") | E9: =IF($W9="","",INDEX('Per Line'!$H$2:$H$501,$W9)&"") | F9: =IF($W9="","",INDEX('Per Line'!$K$2:$K$501,$W9)&"") | G9: =IF($W9="","",INDEX('Per Line'!$L$2:$L$501,$W9)&"") | I9: =IF($W9="","",INDEX('Per Line'!$M$2:$M$501,$W9)) | J9: =IF($W9="","",I9*T9/100) | K9: =IF($W9="","",INDEX('Per Line'!$O$2:$O$501,$W9)) | L9: =IF($W9="","",Settings!$C$7) | M9: =IF($W9="","",SUMIFS('Per Line'!$Y$2:$Y$501,'Per Line'!$C$2:$C$501,$B9,'Per Line'!$AD$2:$AD$501,0)) | N9: =IF($W9="","",M9*L9) | O9: =IF($W9="","",Settings!$C$6) | P9: =IF($W9="","",SUMIFS('Per Line'!$Y$2:$Y$501,'Per Line'!$C$2:$C$501,$B9,'Per Line'!$AD$2:$AD$501,1)) | Q9: =IF($W9="","",P9*O9) | R9: =IF($W9="","",Q9+N9) | S9: =IF($W9="","",T9-R9) | T9: =IF($W9="","",M9+P9) | U9: =IF($W9="","",T9-R9-J9) | W9: =IF(ROWS($W$2:$W9)<=MAX('Per Line'!$AC$2:$AC$501),MATCH(ROWS($W$2:$W9),'Per Line'!$AC$2:$AC$501,0),"")
B10: =IF($W10="","",INDEX('Per Line'!$C$2:$C$501,$W10)&"") | C10: =IF($W10="","",INDEX('Per Line'!$A$2:$A$501,$W10)&"") | D10: =IF($W10="","",INDEX('Per Line'!$E$2:$E$501,$W10)&"") | E10: =IF($W10="","",INDEX('Per Line'!$H$2:$H$501,$W10)&"") | F10: =IF($W10="","",INDEX('Per Line'!$K$2:$K$501,$W10)&"") | G10: =IF($W10="","",INDEX('Per Line'!$L$2:$L$501,$W10)&"") | I10: =IF($W10="","",INDEX('Per Line'!$M$2:$M$501,$W10)) | J10: =IF($W10="","",I10*T10/100) | K10: =IF($W10="","",INDEX('Per Line'!$O$2:$O$501,$W10)) | L10: =IF($W10="","",Settings!$C$7) | M10: =IF($W10="","",SUMIFS('Per Line'!$Y$2:$Y$501,'Per Line'!$C$2:$C$501,$B10,'Per Line'!$AD$2:$AD$501,0)) | N10: =IF($W10="","",M10*L10) | O10: =IF($W10="","",Settings!$C$6) | P10: =IF($W10="","",SUMIFS('Per Line'!$Y$2:$Y$501,'Per Line'!$C$2:$C$501,$B10,'Per Line'!$AD$2:$AD$501,1)) | Q10: =IF($W10="","",P10*O10) | R10: =IF($W10="","",Q10+N10) | S10: =IF($W10="","",T10-R10) | T10: =IF($W10="","",M10+P10) | U10: =IF($W10="","",T10-R10-J10) | W10: =IF(ROWS($W$2:$W10)<=MAX('Per Line'!$AC$2:$AC$501),MATCH(ROWS($W$2:$W10),'Per Line'!$AC$2:$AC$501,0),"")
B11: =IF($W11="","",INDEX('Per Line'!$C$2:$C$501,$W11)&"") | C11: =IF($W11="","",INDEX('Per Line'!$A$2:$A$501,$W11)&"") | D11: =IF($W11="","",INDEX('Per Line'!$E$2:$E$501,$W11)&"") | E11: =IF($W11="","",INDEX('Per Line'!$H$2:$H$501,$W11)&"") | F11: =IF($W11="","",INDEX('Per Line'!$K$2:$K$501,$W11)&"") | G11: =IF($W11="","",INDEX('Per Line'!$L$2:$L$501,$W11)&"") | I11: =IF($W11="","",INDEX('Per Line'!$M$2:$M$501,$W11)) | J11: =IF($W11="","",I11*T11/100) | K11: =IF($W11="","",INDEX('Per Line'!$O$2:$O$501,$W11)) | L11: =IF($W11="","",Settings!$C$7) | M11: =IF($W11="","",SUMIFS('Per Line'!$Y$2:$Y$501,'Per Line'!$C$2:$C$501,$B11,'Per Line'!$AD$2:$AD$501,0)) | N11: =IF($W11="","",M11*L11) | O11: =IF($W11="","",Settings!$C$6) | P11: =IF($W11="","",SUMIFS('Per Line'!$Y$2:$Y$501,'Per Line'!$C$2:$C$501,$B11,'Per Line'!$AD$2:$AD$501,1)) | Q11: =IF($W11="","",P11*O11) | R11: =IF($W11="","",Q11+N11) | S11: =IF($W11="","",T11-R11) | T11: =IF($W11="","",M11+P11) | U11: =IF($W11="","",T11-R11-J11) | W11: =IF(ROWS($W$2:$W11)<=MAX('Per Line'!$AC$2:$AC$501),MATCH(ROWS($W$2:$W11),'Per Line'!$AC$2:$AC$501,0),"")
B12: =IF($W12="","",INDEX('Per Line'!$C$2:$C$501,$W12)&"") | C12: =IF($W12="","",INDEX('Per Line'!$A$2:$A$501,$W12)&"") | D12: =IF($W12="","",INDEX('Per Line'!$E$2:$E$501,$W12)&"") | E12: =IF($W12="","",INDEX('Per Line'!$H$2:$H$501,$W12)&"") | F12: =IF($W12="","",INDEX('Per Line'!$K$2:$K$501,$W12)&"") | G12: =IF($W12="","",INDEX('Per Line'!$L$2:$L$501,$W12)&"") | I12: =IF($W12="","",INDEX('Per Line'!$M$2:$M$501,$W12)) | J12: =IF($W12="","",I12*T12/100) | K12: =IF($W12="","",INDEX('Per Line'!$O$2:$O$501,$W12)) | L12: =IF($W12="","",Settings!$C$7) | M12: =IF($W12="","",SUMIFS('Per Line'!$Y$2:$Y$501,'Per Line'!$C$2:$C$501,$B12,'Per Line'!$AD$2:$AD$501,0)) | N12: =IF($W12="","",M12*L12) | O12: =IF($W12="","",Settings!$C$6) | P12: =IF($W12="","",SUMIFS('Per Line'!$Y$2:$Y$501,'Per Line'!$C$2:$C$501,$B12,'Per Line'!$AD$2:$AD$501,1)) | Q12: =IF($W12="","",P12*O12) | R12: =IF($W12="","",Q12+N12) | S12: =IF($W12="","",T12-R12) | T12: =IF($W12="","",M12+P12) | U12: =IF($W12="","",T12-R12-J12) | W12: =IF(ROWS($W$2:$W12)<=MAX('Per Line'!$AC$2:$AC$501),MATCH(ROWS($W$2:$W12),'Per Line'!$AC$2:$AC$501,0),"")
B13: =IF($W13="","",INDEX('Per Line'!$C$2:$C$501,$W13)&"") | C13: =IF($W13="","",INDEX('Per Line'!$A$2:$A$501,$W13)&"") | D13: =IF($W13="","",INDEX('Per Line'!$E$2:$E$501,$W13)&"") | E13: =IF($W13="","",INDEX('Per Line'!$H$2:$H$501,$W13)&"") | F13: =IF($W13="","",INDEX('Per Line'!$K$2:$K$501,$W13)&"") | G13: =IF($W13="","",INDEX('Per Line'!$L$2:$L$501,$W13)&"") | I13: =IF($W13="","",INDEX('Per Line'!$M$2:$M$501,$W13)) | J13: =IF($W13="","",I13*T13/100) | K13: =IF($W13="","",INDEX('Per Line'!$O$2:$O$501,$W13)) | L13: =IF($W13="","",Settings!$C$7) | M13: =IF($W13="","",SUMIFS('Per Line'!$Y$2:$Y$501,'Per Line'!$C$2:$C$501,$B13,'Per Line'!$AD$2:$AD$501,0)) | N13: =IF($W13="","",M13*L13) | O13: =IF($W13="","",Settings!$C$6) | P13: =IF($W13="","",SUMIFS('Per Line'!$Y$2:$Y$501,'Per Line'!$C$2:$C$501,$B13,'Per Line'!$AD$2:$AD$501,1)) | Q13: =IF($W13="","",P13*O13) | R13: =IF($W13="","",Q13+N13) | S13: =IF($W13="","",T13-R13) | T13: =IF($W13="","",M13+P13) | U13: =IF($W13="","",T13-R13-J13) | W13: =IF(ROWS($W$2:$W13)<=MAX('Per Line'!$AC$2:$AC$501),MATCH(ROWS($W$2:$W13),'Per Line'!$AC$2:$AC$501,0),"")
... B201: =IF($W201="","",INDEX('Per Line'!$C$2:$C$501,$W201)&"") | C201: =IF($W201="","",INDEX('Per Line'!$A$2:$A$501,$W201)&"") | D201: =IF($W201="","",INDEX('Per Line'!$E$2:$E$501,$W201)&"") | E201: =IF($W201="","",INDEX('Per Line'!$H$2:$H$501,$W201)&"") | F201: =IF($W201="","",INDEX('Per Line'!$K$2:$K$501,$W201)&"") | G201: =IF($W201="","",INDEX('Per Line'!$L$2:$L$501,$W201)&"") | I201: =IF($W201="","",INDEX('Per Line'!$M$2:$M$501,$W201)) | J201: =IF($W201="","",I201*T201/100) | K201: =IF($W201="","",INDEX('Per Line'!$O$2:$O$501,$W201)) | L201: =IF($W201="","",Settings!$C$7) | M201: =IF($W201="","",SUMIFS('Per Line'!$Y$2:$Y$501,'Per Line'!$C$2:$C$501,$B201,'Per Line'!$AD$2:$AD$501,0)) | N201: =IF($W201="","",M201*L201) | O201: =IF($W201="","",Settings!$C$6) | P201: =IF($W201="","",SUMIFS('Per Line'!$Y$2:$Y$501,'Per Line'!$C$2:$C$501,$B201,'Per Line'!$AD$2:$AD$501,1)) | Q201: =IF($W201="","",P201*O201) | R201: =IF($W201="","",Q201+N201) | S201: =IF($W201="","",T201-R201) | T201: =IF($W201="","",M201+P201) | U201: =IF($W201="","",T201-R201-J201) | W201: =IF(ROWS($W$2:$W201)<=MAX('Per Line'!$AC$2:$AC$501),MATCH(ROWS($W$2:$W201),'Per Line'!$AC$2:$AC$501,0),"")
