Workbook

Sheet How To Use
A1: Claims Template - EL MASHREQ (Chronic)
A3: Monthly steps
A4: 1. Open the 'Per Line' tab. Delete the old data in the BLUE columns only (row 2 down). Never delete the green or grey columns.
A5: 2. Paste the new month's data as VALUES starting at A2, into the blue columns: A-C, E-Q, S-Z, AD-AE, AG-AN (same order as the system export).
A6: 3. Green columns (D, R, AA, AB, AC, AF) and the grey helper columns (AO-AS) calculate automatically - do not paste over them.
A7: 4. 'Per Invoice' fills itself from 'Per Line' (one row per Order #, split into IMP / Local). No pivot table, no refresh.
A8: 5. The ONLY manual column in 'Per Invoice' is column A 'Invoice' (blue): type it yourself. Everything else is formula.
A9: 6. Open 'Settings' and check STATUS says OK (Per Line totals = Per Invoice totals).
A11: Colour legend
A12: Blue header = typed/pasted by you (raw data, and 'Invoice' in Per Invoice). Green header = formula (do not paste over). Grey header = helper formula (do not touch). Yellow cell (Settings) = editable rate.
A14: Calculation rules (taken from the October 2026 sheet)
A15: Co val = Order Co Payment x Total / 100. Discount = Total x Rebates / 100. Subtotal = Total - Discount. Net = Subtotal - Co val. (Total = 'Product Total')
... A20: Capacity: up to 1,000 lines and 300 invoices per month. A line with an empty Order # is ignored.

Sheet Settings
B1: Company settings & checks
B3: Insurance Company | C3: EL MASHREQ | D3: Informational only
B4: Corporate | C4: الوطنية للأسمنت - CLINIC; Resta; المصرية العالمية للتجارة; العربية الدولية للفنادق و السياحة - BULK; Radioshack | D4: Informational only
B5: Sheet type | C5: Chronic | D5: Informational only
B6: Local products rebate % | C6: 0.14 | D6: Source: Oct sheet (Rebates = 14 on Local lines).
B7: Imported (IMP) products rebate % | C7: 0.06 | D7: Source: Oct sheet (Rebates = 6 on non-local lines).
B9: Month totals / reconciliation
B10: Lines loaded | C10: =COUNTA('Per Line'!$E$2:$E$1001)
B11: Invoices (unique Order #) | C11: =MAX('Per Line'!$AP$2:$AP$1001)
B12: Invoices shown in Per Invoice | C12: =SUMPRODUCT(--('Per Invoice'!$B$2:$B$301<>""))
B13: Grand Total - Per Line (Product Total) | C13: =SUM('Per Line'!$Z$2:$Z$1001)
B14: Grand Total - Per Invoice | C14: =SUM('Per Invoice'!$W$2:$W$301)
B15: Discount - Per Line | C15: =SUM('Per Line'!$AA$2:$AA$1001)
B16: Discount - Per Invoice | C16: =SUM('Per Invoice'!$U$2:$U$301)
B17: Co val - Per Line | C17: =SUM('Per Line'!$R$2:$R$1001)
B18: Co val - Per Invoice | C18: =SUM('Per Invoice'!$L$2:$L$301)
B19: Net - Per Line | C19: =SUM('Per Line'!$AC$2:$AC$1001)
B20: Net - Per Invoice | C20: =SUM('Per Invoice'!$X$2:$X$301)
B21: Max Limit adjustment (Co val, Per Invoice only) | C21: 0 | D21: This company's Per Invoice has no Max Limit rule.
B23: STATUS | C23: =IF(C10=0,"No data loaded",IF(COUNTA('Per Line'!$E:$E)-1>1000,"TOO MANY LINES - extend template",IF(C11>300,"TOO MANY INVOICES - extend template",IF(AND(ROUND(C13-C14,2)=0,ROUND(C15-C16,2)=0,ROUND(C17+C21-C18,2)=0,ROUND(C19-C21-C20,2)=0,C11=C12),"OK","CHECK - Per Line and Per Invoice do not match")))) | D23: Must say OK after you paste the month data.

Sheet Per Line
A1: Cycle | B1: Ticket # | C1: Stage | D1: inv | E1: Order # | F1: Approval Ref | G1: Channel | H1: Create At | I1: Insurance Company | J1: Country Portal ID | K1: Corporate | L1: Card | M1: Name | N1: Status | O1: Local Rebates | P1: Imported Rebates | Q1: Order Co Payment | R1: Co val | S1: By Patient | T1: heisenberg id | U1: Product Name | V1: Local | W1: Unit | X1: Quantity | Y1: Unit Price | Z1: Product Total | AA1: Discount | AB1: Subtotal | AC1: Net | AD1: ERX ID | AE1: Special Rebates? | AF1: Rebates | AG1: Approval Type | AH1: Max Limit | AI1: Exceeding Limit | AJ1: Amount collected from customer | AK1: By Patient (Delivered) | AL1: Dispense Number | AM1: Dispense Date | AN1: Has OTP? | AO1: Order 1st Row (helper) | AP1: Invoice # (helper) | AQ1: Is Local (helper) | AR1: Is Special (helper) | AS1: Sort Key (helper)
D2: =IF($E2="","",IFERROR(IF(INDEX('Per Invoice'!$A$2:$A$301,MATCH($E2,'Per Invoice'!$B$2:$B$301,0))=0,"",INDEX('Per Invoice'!$A$2:$A$301,MATCH($E2,'Per Invoice'!$B$2:$B$301,0))),"")) | R2: =IF($E2="","",Q2*Z2/100) | AA2: =IF($E2="","",Z2*AF2/100) | AB2: =IF($E2="","",Z2-AA2) | AC2: =IF($E2="","",AB2-R2) | AF2: =IF($E2="","",IF($AR2=1,0,IF($AQ2=1,Settings!$C$6,Settings!$C$7))*100) | AO2: =IF($E2="","",IF(COUNTIF($E$2:$E2,$E2)=1,1,0)) | AP2: =IF($AO2=1,SUMPRODUCT(--($AS$2:$AS$1001<$AS2))+1,"") | AQ2: =IF($E2="","",IF(OR($V2=TRUE(),$V2="TRUE"),1,0)) | AR2: =IF($E2="","",IF($AE2="Yes",1,0)) | AS2: =IF($AO2=1,IFERROR(IF(VALUE($E2)<100000000,VALUE($E2),1000000000),IFERROR(IF(VALUE(MID($E2,2,20))<100000000,VALUE(MID($E2,2,20)),1000000000),1000000000))+ROW()/100000,"")
D3: =IF($E3="","",IFERROR(IF(INDEX('Per Invoice'!$A$2:$A$301,MATCH($E3,'Per Invoice'!$B$2:$B$301,0))=0,"",INDEX('Per Invoice'!$A$2:$A$301,MATCH($E3,'Per Invoice'!$B$2:$B$301,0))),"")) | R3: =IF($E3="","",Q3*Z3/100) | AA3: =IF($E3="","",Z3*AF3/100) | AB3: =IF($E3="","",Z3-AA3) | AC3: =IF($E3="","",AB3-R3) | AF3: =IF($E3="","",IF($AR3=1,0,IF($AQ3=1,Settings!$C$6,Settings!$C$7))*100) | AO3: =IF($E3="","",IF(COUNTIF($E$2:$E3,$E3)=1,1,0)) | AP3: =IF($AO3=1,SUMPRODUCT(--($AS$2:$AS$1001<$AS3))+1,"") | AQ3: =IF($E3="","",IF(OR($V3=TRUE(),$V3="TRUE"),1,0)) | AR3: =IF($E3="","",IF($AE3="Yes",1,0)) | AS3: =IF($AO3=1,IFERROR(IF(VALUE($E3)<100000000,VALUE($E3),1000000000),IFERROR(IF(VALUE(MID($E3,2,20))<100000000,VALUE(MID($E3,2,20)),1000000000),1000000000))+ROW()/100000,"")
D4: =IF($E4="","",IFERROR(IF(INDEX('Per Invoice'!$A$2:$A$301,MATCH($E4,'Per Invoice'!$B$2:$B$301,0))=0,"",INDEX('Per Invoice'!$A$2:$A$301,MATCH($E4,'Per Invoice'!$B$2:$B$301,0))),"")) | R4: =IF($E4="","",Q4*Z4/100) | AA4: =IF($E4="","",Z4*AF4/100) | AB4: =IF($E4="","",Z4-AA4) | AC4: =IF($E4="","",AB4-R4) | AF4: =IF($E4="","",IF($AR4=1,0,IF($AQ4=1,Settings!$C$6,Settings!$C$7))*100) | AO4: =IF($E4="","",IF(COUNTIF($E$2:$E4,$E4)=1,1,0)) | AP4: =IF($AO4=1,SUMPRODUCT(--($AS$2:$AS$1001<$AS4))+1,"") | AQ4: =IF($E4="","",IF(OR($V4=TRUE(),$V4="TRUE"),1,0)) | AR4: =IF($E4="","",IF($AE4="Yes",1,0)) | AS4: =IF($AO4=1,IFERROR(IF(VALUE($E4)<100000000,VALUE($E4),1000000000),IFERROR(IF(VALUE(MID($E4,2,20))<100000000,VALUE(MID($E4,2,20)),1000000000),1000000000))+ROW()/100000,"")
D5: =IF($E5="","",IFERROR(IF(INDEX('Per Invoice'!$A$2:$A$301,MATCH($E5,'Per Invoice'!$B$2:$B$301,0))=0,"",INDEX('Per Invoice'!$A$2:$A$301,MATCH($E5,'Per Invoice'!$B$2:$B$301,0))),"")) | R5: =IF($E5="","",Q5*Z5/100) | AA5: =IF($E5="","",Z5*AF5/100) | AB5: =IF($E5="","",Z5-AA5) | AC5: =IF($E5="","",AB5-R5) | AF5: =IF($E5="","",IF($AR5=1,0,IF($AQ5=1,Settings!$C$6,Settings!$C$7))*100) | AO5: =IF($E5="","",IF(COUNTIF($E$2:$E5,$E5)=1,1,0)) | AP5: =IF($AO5=1,SUMPRODUCT(--($AS$2:$AS$1001<$AS5))+1,"") | AQ5: =IF($E5="","",IF(OR($V5=TRUE(),$V5="TRUE"),1,0)) | AR5: =IF($E5="","",IF($AE5="Yes",1,0)) | AS5: =IF($AO5=1,IFERROR(IF(VALUE($E5)<100000000,VALUE($E5),1000000000),IFERROR(IF(VALUE(MID($E5,2,20))<100000000,VALUE(MID($E5,2,20)),1000000000),1000000000))+ROW()/100000,"")
D6: =IF($E6="","",IFERROR(IF(INDEX('Per Invoice'!$A$2:$A$301,MATCH($E6,'Per Invoice'!$B$2:$B$301,0))=0,"",INDEX('Per Invoice'!$A$2:$A$301,MATCH($E6,'Per Invoice'!$B$2:$B$301,0))),"")) | R6: =IF($E6="","",Q6*Z6/100) | AA6: =IF($E6="","",Z6*AF6/100) | AB6: =IF($E6="","",Z6-AA6) | AC6: =IF($E6="","",AB6-R6) | AF6: =IF($E6="","",IF($AR6=1,0,IF($AQ6=1,Settings!$C$6,Settings!$C$7))*100) | AO6: =IF($E6="","",IF(COUNTIF($E$2:$E6,$E6)=1,1,0)) | AP6: =IF($AO6=1,SUMPRODUCT(--($AS$2:$AS$1001<$AS6))+1,"") | AQ6: =IF($E6="","",IF(OR($V6=TRUE(),$V6="TRUE"),1,0)) | AR6: =IF($E6="","",IF($AE6="Yes",1,0)) | AS6: =IF($AO6=1,IFERROR(IF(VALUE($E6)<100000000,VALUE($E6),1000000000),IFERROR(IF(VALUE(MID($E6,2,20))<100000000,VALUE(MID($E6,2,20)),1000000000),1000000000))+ROW()/100000,"")
D7: =IF($E7="","",IFERROR(IF(INDEX('Per Invoice'!$A$2:$A$301,MATCH($E7,'Per Invoice'!$B$2:$B$301,0))=0,"",INDEX('Per Invoice'!$A$2:$A$301,MATCH($E7,'Per Invoice'!$B$2:$B$301,0))),"")) | R7: =IF($E7="","",Q7*Z7/100) | AA7: =IF($E7="","",Z7*AF7/100) | AB7: =IF($E7="","",Z7-AA7) | AC7: =IF($E7="","",AB7-R7) | AF7: =IF($E7="","",IF($AR7=1,0,IF($AQ7=1,Settings!$C$6,Settings!$C$7))*100) | AO7: =IF($E7="","",IF(COUNTIF($E$2:$E7,$E7)=1,1,0)) | AP7: =IF($AO7=1,SUMPRODUCT(--($AS$2:$AS$1001<$AS7))+1,"") | AQ7: =IF($E7="","",IF(OR($V7=TRUE(),$V7="TRUE"),1,0)) | AR7: =IF($E7="","",IF($AE7="Yes",1,0)) | AS7: =IF($AO7=1,IFERROR(IF(VALUE($E7)<100000000,VALUE($E7),1000000000),IFERROR(IF(VALUE(MID($E7,2,20))<100000000,VALUE(MID($E7,2,20)),1000000000),1000000000))+ROW()/100000,"")
D8: =IF($E8="","",IFERROR(IF(INDEX('Per Invoice'!$A$2:$A$301,MATCH($E8,'Per Invoice'!$B$2:$B$301,0))=0,"",INDEX('Per Invoice'!$A$2:$A$301,MATCH($E8,'Per Invoice'!$B$2:$B$301,0))),"")) | R8: =IF($E8="","",Q8*Z8/100) | AA8: =IF($E8="","",Z8*AF8/100) | AB8: =IF($E8="","",Z8-AA8) | AC8: =IF($E8="","",AB8-R8) | AF8: =IF($E8="","",IF($AR8=1,0,IF($AQ8=1,Settings!$C$6,Settings!$C$7))*100) | AO8: =IF($E8="","",IF(COUNTIF($E$2:$E8,$E8)=1,1,0)) | AP8: =IF($AO8=1,SUMPRODUCT(--($AS$2:$AS$1001<$AS8))+1,"") | AQ8: =IF($E8="","",IF(OR($V8=TRUE(),$V8="TRUE"),1,0)) | AR8: =IF($E8="","",IF($AE8="Yes",1,0)) | AS8: =IF($AO8=1,IFERROR(IF(VALUE($E8)<100000000,VALUE($E8),1000000000),IFERROR(IF(VALUE(MID($E8,2,20))<100000000,VALUE(MID($E8,2,20)),1000000000),1000000000))+ROW()/100000,"")
D9: =IF($E9="","",IFERROR(IF(INDEX('Per Invoice'!$A$2:$A$301,MATCH($E9,'Per Invoice'!$B$2:$B$301,0))=0,"",INDEX('Per Invoice'!$A$2:$A$301,MATCH($E9,'Per Invoice'!$B$2:$B$301,0))),"")) | R9: =IF($E9="","",Q9*Z9/100) | AA9: =IF($E9="","",Z9*AF9/100) | AB9: =IF($E9="","",Z9-AA9) | AC9: =IF($E9="","",AB9-R9) | AF9: =IF($E9="","",IF($AR9=1,0,IF($AQ9=1,Settings!$C$6,Settings!$C$7))*100) | AO9: =IF($E9="","",IF(COUNTIF($E$2:$E9,$E9)=1,1,0)) | AP9: =IF($AO9=1,SUMPRODUCT(--($AS$2:$AS$1001<$AS9))+1,"") | AQ9: =IF($E9="","",IF(OR($V9=TRUE(),$V9="TRUE"),1,0)) | AR9: =IF($E9="","",IF($AE9="Yes",1,0)) | AS9: =IF($AO9=1,IFERROR(IF(VALUE($E9)<100000000,VALUE($E9),1000000000),IFERROR(IF(VALUE(MID($E9,2,20))<100000000,VALUE(MID($E9,2,20)),1000000000),1000000000))+ROW()/100000,"")
D10: =IF($E10="","",IFERROR(IF(INDEX('Per Invoice'!$A$2:$A$301,MATCH($E10,'Per Invoice'!$B$2:$B$301,0))=0,"",INDEX('Per Invoice'!$A$2:$A$301,MATCH($E10,'Per Invoice'!$B$2:$B$301,0))),"")) | R10: =IF($E10="","",Q10*Z10/100) | AA10: =IF($E10="","",Z10*AF10/100) | AB10: =IF($E10="","",Z10-AA10) | AC10: =IF($E10="","",AB10-R10) | AF10: =IF($E10="","",IF($AR10=1,0,IF($AQ10=1,Settings!$C$6,Settings!$C$7))*100) | AO10: =IF($E10="","",IF(COUNTIF($E$2:$E10,$E10)=1,1,0)) | AP10: =IF($AO10=1,SUMPRODUCT(--($AS$2:$AS$1001<$AS10))+1,"") | AQ10: =IF($E10="","",IF(OR($V10=TRUE(),$V10="TRUE"),1,0)) | AR10: =IF($E10="","",IF($AE10="Yes",1,0)) | AS10: =IF($AO10=1,IFERROR(IF(VALUE($E10)<100000000,VALUE($E10),1000000000),IFERROR(IF(VALUE(MID($E10,2,20))<100000000,VALUE(MID($E10,2,20)),1000000000),1000000000))+ROW()/100000,"")
D11: =IF($E11="","",IFERROR(IF(INDEX('Per Invoice'!$A$2:$A$301,MATCH($E11,'Per Invoice'!$B$2:$B$301,0))=0,"",INDEX('Per Invoice'!$A$2:$A$301,MATCH($E11,'Per Invoice'!$B$2:$B$301,0))),"")) | R11: =IF($E11="","",Q11*Z11/100) | AA11: =IF($E11="","",Z11*AF11/100) | AB11: =IF($E11="","",Z11-AA11) | AC11: =IF($E11="","",AB11-R11) | AF11: =IF($E11="","",IF($AR11=1,0,IF($AQ11=1,Settings!$C$6,Settings!$C$7))*100) | AO11: =IF($E11="","",IF(COUNTIF($E$2:$E11,$E11)=1,1,0)) | AP11: =IF($AO11=1,SUMPRODUCT(--($AS$2:$AS$1001<$AS11))+1,"") | AQ11: =IF($E11="","",IF(OR($V11=TRUE(),$V11="TRUE"),1,0)) | AR11: =IF($E11="","",IF($AE11="Yes",1,0)) | AS11: =IF($AO11=1,IFERROR(IF(VALUE($E11)<100000000,VALUE($E11),1000000000),IFERROR(IF(VALUE(MID($E11,2,20))<100000000,VALUE(MID($E11,2,20)),1000000000),1000000000))+ROW()/100000,"")
D12: =IF($E12="","",IFERROR(IF(INDEX('Per Invoice'!$A$2:$A$301,MATCH($E12,'Per Invoice'!$B$2:$B$301,0))=0,"",INDEX('Per Invoice'!$A$2:$A$301,MATCH($E12,'Per Invoice'!$B$2:$B$301,0))),"")) | R12: =IF($E12="","",Q12*Z12/100) | AA12: =IF($E12="","",Z12*AF12/100) | AB12: =IF($E12="","",Z12-AA12) | AC12: =IF($E12="","",AB12-R12) | AF12: =IF($E12="","",IF($AR12=1,0,IF($AQ12=1,Settings!$C$6,Settings!$C$7))*100) | AO12: =IF($E12="","",IF(COUNTIF($E$2:$E12,$E12)=1,1,0)) | AP12: =IF($AO12=1,SUMPRODUCT(--($AS$2:$AS$1001<$AS12))+1,"") | AQ12: =IF($E12="","",IF(OR($V12=TRUE(),$V12="TRUE"),1,0)) | AR12: =IF($E12="","",IF($AE12="Yes",1,0)) | AS12: =IF($AO12=1,IFERROR(IF(VALUE($E12)<100000000,VALUE($E12),1000000000),IFERROR(IF(VALUE(MID($E12,2,20))<100000000,VALUE(MID($E12,2,20)),1000000000),1000000000))+ROW()/100000,"")
D13: =IF($E13="","",IFERROR(IF(INDEX('Per Invoice'!$A$2:$A$301,MATCH($E13,'Per Invoice'!$B$2:$B$301,0))=0,"",INDEX('Per Invoice'!$A$2:$A$301,MATCH($E13,'Per Invoice'!$B$2:$B$301,0))),"")) | R13: =IF($E13="","",Q13*Z13/100) | AA13: =IF($E13="","",Z13*AF13/100) | AB13: =IF($E13="","",Z13-AA13) | AC13: =IF($E13="","",AB13-R13) | AF13: =IF($E13="","",IF($AR13=1,0,IF($AQ13=1,Settings!$C$6,Settings!$C$7))*100) | AO13: =IF($E13="","",IF(COUNTIF($E$2:$E13,$E13)=1,1,0)) | AP13: =IF($AO13=1,SUMPRODUCT(--($AS$2:$AS$1001<$AS13))+1,"") | AQ13: =IF($E13="","",IF(OR($V13=TRUE(),$V13="TRUE"),1,0)) | AR13: =IF($E13="","",IF($AE13="Yes",1,0)) | AS13: =IF($AO13=1,IFERROR(IF(VALUE($E13)<100000000,VALUE($E13),1000000000),IFERROR(IF(VALUE(MID($E13,2,20))<100000000,VALUE(MID($E13,2,20)),1000000000),1000000000))+ROW()/100000,"")
... D1001: =IF($E1001="","",IFERROR(IF(INDEX('Per Invoice'!$A$2:$A$301,MATCH($E1001,'Per Invoice'!$B$2:$B$301,0))=0,"",INDEX('Per Invoice'!$A$2:$A$301,MATCH($E1001,'Per Invoice'!$B$2:$B$301,0))),"")) | R1001: =IF($E1001="","",Q1001*Z1001/100) | AA1001: =IF($E1001="","",Z1001*AF1001/100) | AB1001: =IF($E1001="","",Z1001-AA1001) | AC1001: =IF($E1001="","",AB1001-R1001) | AF1001: =IF($E1001="","",IF($AR1001=1,0,IF($AQ1001=1,Settings!$C$6,Settings!$C$7))*100) | AO1001: =IF($E1001="","",IF(COUNTIF($E$2:$E1001,$E1001)=1,1,0)) | AP1001: =IF($AO1001=1,SUMPRODUCT(--($AS$2:$AS$1001<$AS1001))+1,"") | AQ1001: =IF($E1001="","",IF(OR($V1001=TRUE(),$V1001="TRUE"),1,0)) | AR1001: =IF($E1001="","",IF($AE1001="Yes",1,0)) | AS1001: =IF($AO1001=1,IFERROR(IF(VALUE($E1001)<100000000,VALUE($E1001),1000000000),IFERROR(IF(VALUE(MID($E1001,2,20))<100000000,VALUE(MID($E1001,2,20)),1000000000),1000000000))+ROW()/100000,"")

Sheet Per Invoice
A1: Invoice | B1: Order # | C1: Approval Ref | D1: Cycle | E1: Ticket # | F1: Channel | G1: Create At | H1: Corporate | I1: Card | J1: Name | K1: Order Co Payment | L1: Co val | M1: ERX ID | N1: Special | O1: imp% | P1: imp | Q1: imp val | R1: local % | S1: local | T1: local val | U1: disc | V1: subtotal | W1: Grand Total | X1: net | Y1: Src Row (helper)
B2: =IF($Y2="","",INDEX('Per Line'!$E$2:$E$1001,$Y2)&"") | C2: =IF($Y2="","",INDEX('Per Line'!$F$2:$F$1001,$Y2)&"") | D2: =IF($Y2="","",INDEX('Per Line'!$A$2:$A$1001,$Y2)&"") | E2: =IF($Y2="","",INDEX('Per Line'!$B$2:$B$1001,$Y2)) | F2: =IF($Y2="","",INDEX('Per Line'!$G$2:$G$1001,$Y2)&"") | G2: =IF($Y2="","",INDEX('Per Line'!$H$2:$H$1001,$Y2)) | H2: =IF($Y2="","",INDEX('Per Line'!$K$2:$K$1001,$Y2)&"") | I2: =IF($Y2="","",INDEX('Per Line'!$L$2:$L$1001,$Y2)&"") | J2: =IF($Y2="","",INDEX('Per Line'!$M$2:$M$1001,$Y2)&"") | K2: =IF($Y2="","",INDEX('Per Line'!$Q$2:$Q$1001,$Y2)) | L2: =IF($Y2="","",K2*W2/100) | M2: =IF($Y2="","",INDEX('Per Line'!$AD$2:$AD$1001,$Y2)&"") | N2: =IF($Y2="","",SUMIFS('Per Line'!$Z$2:$Z$1001,'Per Line'!$E$2:$E$1001,$B2,'Per Line'!$AR$2:$AR$1001,1)) | O2: =IF($Y2="","",Settings!$C$7) | P2: =IF($Y2="","",SUMIFS('Per Line'!$Z$2:$Z$1001,'Per Line'!$E$2:$E$1001,$B2,'Per Line'!$AQ$2:$AQ$1001,0,'Per Line'!$AR$2:$AR$1001,0)) | Q2: =IF($Y2="","",P2*O2) | R2: =IF($Y2="","",Settings!$C$6) | S2: =IF($Y2="","",SUMIFS('Per Line'!$Z$2:$Z$1001,'Per Line'!$E$2:$E$1001,$B2,'Per Line'!$AQ$2:$AQ$1001,1,'Per Line'!$AR$2:$AR$1001,0)) | T2: =IF($Y2="","",S2*R2) | U2: =IF($Y2="","",T2+Q2) | V2: =IF($Y2="","",W2-U2) | W2: =IF($Y2="","",P2+S2+N2) | X2: =IF($Y2="","",W2-U2-L2) | Y2: =IF(ROWS($Y$2:$Y2)<=MAX('Per Line'!$AP$2:$AP$1001),MATCH(ROWS($Y$2:$Y2),'Per Line'!$AP$2:$AP$1001,0),"")
B3: =IF($Y3="","",INDEX('Per Line'!$E$2:$E$1001,$Y3)&"") | C3: =IF($Y3="","",INDEX('Per Line'!$F$2:$F$1001,$Y3)&"") | D3: =IF($Y3="","",INDEX('Per Line'!$A$2:$A$1001,$Y3)&"") | E3: =IF($Y3="","",INDEX('Per Line'!$B$2:$B$1001,$Y3)) | F3: =IF($Y3="","",INDEX('Per Line'!$G$2:$G$1001,$Y3)&"") | G3: =IF($Y3="","",INDEX('Per Line'!$H$2:$H$1001,$Y3)) | H3: =IF($Y3="","",INDEX('Per Line'!$K$2:$K$1001,$Y3)&"") | I3: =IF($Y3="","",INDEX('Per Line'!$L$2:$L$1001,$Y3)&"") | J3: =IF($Y3="","",INDEX('Per Line'!$M$2:$M$1001,$Y3)&"") | K3: =IF($Y3="","",INDEX('Per Line'!$Q$2:$Q$1001,$Y3)) | L3: =IF($Y3="","",K3*W3/100) | M3: =IF($Y3="","",INDEX('Per Line'!$AD$2:$AD$1001,$Y3)&"") | N3: =IF($Y3="","",SUMIFS('Per Line'!$Z$2:$Z$1001,'Per Line'!$E$2:$E$1001,$B3,'Per Line'!$AR$2:$AR$1001,1)) | O3: =IF($Y3="","",Settings!$C$7) | P3: =IF($Y3="","",SUMIFS('Per Line'!$Z$2:$Z$1001,'Per Line'!$E$2:$E$1001,$B3,'Per Line'!$AQ$2:$AQ$1001,0,'Per Line'!$AR$2:$AR$1001,0)) | Q3: =IF($Y3="","",P3*O3) | R3: =IF($Y3="","",Settings!$C$6) | S3: =IF($Y3="","",SUMIFS('Per Line'!$Z$2:$Z$1001,'Per Line'!$E$2:$E$1001,$B3,'Per Line'!$AQ$2:$AQ$1001,1,'Per Line'!$AR$2:$AR$1001,0)) | T3: =IF($Y3="","",S3*R3) | U3: =IF($Y3="","",T3+Q3) | V3: =IF($Y3="","",W3-U3) | W3: =IF($Y3="","",P3+S3+N3) | X3: =IF($Y3="","",W3-U3-L3) | Y3: =IF(ROWS($Y$2:$Y3)<=MAX('Per Line'!$AP$2:$AP$1001),MATCH(ROWS($Y$2:$Y3),'Per Line'!$AP$2:$AP$1001,0),"")
B4: =IF($Y4="","",INDEX('Per Line'!$E$2:$E$1001,$Y4)&"") | C4: =IF($Y4="","",INDEX('Per Line'!$F$2:$F$1001,$Y4)&"") | D4: =IF($Y4="","",INDEX('Per Line'!$A$2:$A$1001,$Y4)&"") | E4: =IF($Y4="","",INDEX('Per Line'!$B$2:$B$1001,$Y4)) | F4: =IF($Y4="","",INDEX('Per Line'!$G$2:$G$1001,$Y4)&"") | G4: =IF($Y4="","",INDEX('Per Line'!$H$2:$H$1001,$Y4)) | H4: =IF($Y4="","",INDEX('Per Line'!$K$2:$K$1001,$Y4)&"") | I4: =IF($Y4="","",INDEX('Per Line'!$L$2:$L$1001,$Y4)&"") | J4: =IF($Y4="","",INDEX('Per Line'!$M$2:$M$1001,$Y4)&"") | K4: =IF($Y4="","",INDEX('Per Line'!$Q$2:$Q$1001,$Y4)) | L4: =IF($Y4="","",K4*W4/100) | M4: =IF($Y4="","",INDEX('Per Line'!$AD$2:$AD$1001,$Y4)&"") | N4: =IF($Y4="","",SUMIFS('Per Line'!$Z$2:$Z$1001,'Per Line'!$E$2:$E$1001,$B4,'Per Line'!$AR$2:$AR$1001,1)) | O4: =IF($Y4="","",Settings!$C$7) | P4: =IF($Y4="","",SUMIFS('Per Line'!$Z$2:$Z$1001,'Per Line'!$E$2:$E$1001,$B4,'Per Line'!$AQ$2:$AQ$1001,0,'Per Line'!$AR$2:$AR$1001,0)) | Q4: =IF($Y4="","",P4*O4) | R4: =IF($Y4="","",Settings!$C$6) | S4: =IF($Y4="","",SUMIFS('Per Line'!$Z$2:$Z$1001,'Per Line'!$E$2:$E$1001,$B4,'Per Line'!$AQ$2:$AQ$1001,1,'Per Line'!$AR$2:$AR$1001,0)) | T4: =IF($Y4="","",S4*R4) | U4: =IF($Y4="","",T4+Q4) | V4: =IF($Y4="","",W4-U4) | W4: =IF($Y4="","",P4+S4+N4) | X4: =IF($Y4="","",W4-U4-L4) | Y4: =IF(ROWS($Y$2:$Y4)<=MAX('Per Line'!$AP$2:$AP$1001),MATCH(ROWS($Y$2:$Y4),'Per Line'!$AP$2:$AP$1001,0),"")
B5: =IF($Y5="","",INDEX('Per Line'!$E$2:$E$1001,$Y5)&"") | C5: =IF($Y5="","",INDEX('Per Line'!$F$2:$F$1001,$Y5)&"") | D5: =IF($Y5="","",INDEX('Per Line'!$A$2:$A$1001,$Y5)&"") | E5: =IF($Y5="","",INDEX('Per Line'!$B$2:$B$1001,$Y5)) | F5: =IF($Y5="","",INDEX('Per Line'!$G$2:$G$1001,$Y5)&"") | G5: =IF($Y5="","",INDEX('Per Line'!$H$2:$H$1001,$Y5)) | H5: =IF($Y5="","",INDEX('Per Line'!$K$2:$K$1001,$Y5)&"") | I5: =IF($Y5="","",INDEX('Per Line'!$L$2:$L$1001,$Y5)&"") | J5: =IF($Y5="","",INDEX('Per Line'!$M$2:$M$1001,$Y5)&"") | K5: =IF($Y5="","",INDEX('Per Line'!$Q$2:$Q$1001,$Y5)) | L5: =IF($Y5="","",K5*W5/100) | M5: =IF($Y5="","",INDEX('Per Line'!$AD$2:$AD$1001,$Y5)&"") | N5: =IF($Y5="","",SUMIFS('Per Line'!$Z$2:$Z$1001,'Per Line'!$E$2:$E$1001,$B5,'Per Line'!$AR$2:$AR$1001,1)) | O5: =IF($Y5="","",Settings!$C$7) | P5: =IF($Y5="","",SUMIFS('Per Line'!$Z$2:$Z$1001,'Per Line'!$E$2:$E$1001,$B5,'Per Line'!$AQ$2:$AQ$1001,0,'Per Line'!$AR$2:$AR$1001,0)) | Q5: =IF($Y5="","",P5*O5) | R5: =IF($Y5="","",Settings!$C$6) | S5: =IF($Y5="","",SUMIFS('Per Line'!$Z$2:$Z$1001,'Per Line'!$E$2:$E$1001,$B5,'Per Line'!$AQ$2:$AQ$1001,1,'Per Line'!$AR$2:$AR$1001,0)) | T5: =IF($Y5="","",S5*R5) | U5: =IF($Y5="","",T5+Q5) | V5: =IF($Y5="","",W5-U5) | W5: =IF($Y5="","",P5+S5+N5) | X5: =IF($Y5="","",W5-U5-L5) | Y5: =IF(ROWS($Y$2:$Y5)<=MAX('Per Line'!$AP$2:$AP$1001),MATCH(ROWS($Y$2:$Y5),'Per Line'!$AP$2:$AP$1001,0),"")
B6: =IF($Y6="","",INDEX('Per Line'!$E$2:$E$1001,$Y6)&"") | C6: =IF($Y6="","",INDEX('Per Line'!$F$2:$F$1001,$Y6)&"") | D6: =IF($Y6="","",INDEX('Per Line'!$A$2:$A$1001,$Y6)&"") | E6: =IF($Y6="","",INDEX('Per Line'!$B$2:$B$1001,$Y6)) | F6: =IF($Y6="","",INDEX('Per Line'!$G$2:$G$1001,$Y6)&"") | G6: =IF($Y6="","",INDEX('Per Line'!$H$2:$H$1001,$Y6)) | H6: =IF($Y6="","",INDEX('Per Line'!$K$2:$K$1001,$Y6)&"") | I6: =IF($Y6="","",INDEX('Per Line'!$L$2:$L$1001,$Y6)&"") | J6: =IF($Y6="","",INDEX('Per Line'!$M$2:$M$1001,$Y6)&"") | K6: =IF($Y6="","",INDEX('Per Line'!$Q$2:$Q$1001,$Y6)) | L6: =IF($Y6="","",K6*W6/100) | M6: =IF($Y6="","",INDEX('Per Line'!$AD$2:$AD$1001,$Y6)&"") | N6: =IF($Y6="","",SUMIFS('Per Line'!$Z$2:$Z$1001,'Per Line'!$E$2:$E$1001,$B6,'Per Line'!$AR$2:$AR$1001,1)) | O6: =IF($Y6="","",Settings!$C$7) | P6: =IF($Y6="","",SUMIFS('Per Line'!$Z$2:$Z$1001,'Per Line'!$E$2:$E$1001,$B6,'Per Line'!$AQ$2:$AQ$1001,0,'Per Line'!$AR$2:$AR$1001,0)) | Q6: =IF($Y6="","",P6*O6) | R6: =IF($Y6="","",Settings!$C$6) | S6: =IF($Y6="","",SUMIFS('Per Line'!$Z$2:$Z$1001,'Per Line'!$E$2:$E$1001,$B6,'Per Line'!$AQ$2:$AQ$1001,1,'Per Line'!$AR$2:$AR$1001,0)) | T6: =IF($Y6="","",S6*R6) | U6: =IF($Y6="","",T6+Q6) | V6: =IF($Y6="","",W6-U6) | W6: =IF($Y6="","",P6+S6+N6) | X6: =IF($Y6="","",W6-U6-L6) | Y6: =IF(ROWS($Y$2:$Y6)<=MAX('Per Line'!$AP$2:$AP$1001),MATCH(ROWS($Y$2:$Y6),'Per Line'!$AP$2:$AP$1001,0),"")
B7: =IF($Y7="","",INDEX('Per Line'!$E$2:$E$1001,$Y7)&"") | C7: =IF($Y7="","",INDEX('Per Line'!$F$2:$F$1001,$Y7)&"") | D7: =IF($Y7="","",INDEX('Per Line'!$A$2:$A$1001,$Y7)&"") | E7: =IF($Y7="","",INDEX('Per Line'!$B$2:$B$1001,$Y7)) | F7: =IF($Y7="","",INDEX('Per Line'!$G$2:$G$1001,$Y7)&"") | G7: =IF($Y7="","",INDEX('Per Line'!$H$2:$H$1001,$Y7)) | H7: =IF($Y7="","",INDEX('Per Line'!$K$2:$K$1001,$Y7)&"") | I7: =IF($Y7="","",INDEX('Per Line'!$L$2:$L$1001,$Y7)&"") | J7: =IF($Y7="","",INDEX('Per Line'!$M$2:$M$1001,$Y7)&"") | K7: =IF($Y7="","",INDEX('Per Line'!$Q$2:$Q$1001,$Y7)) | L7: =IF($Y7="","",K7*W7/100) | M7: =IF($Y7="","",INDEX('Per Line'!$AD$2:$AD$1001,$Y7)&"") | N7: =IF($Y7="","",SUMIFS('Per Line'!$Z$2:$Z$1001,'Per Line'!$E$2:$E$1001,$B7,'Per Line'!$AR$2:$AR$1001,1)) | O7: =IF($Y7="","",Settings!$C$7) | P7: =IF($Y7="","",SUMIFS('Per Line'!$Z$2:$Z$1001,'Per Line'!$E$2:$E$1001,$B7,'Per Line'!$AQ$2:$AQ$1001,0,'Per Line'!$AR$2:$AR$1001,0)) | Q7: =IF($Y7="","",P7*O7) | R7: =IF($Y7="","",Settings!$C$6) | S7: =IF($Y7="","",SUMIFS('Per Line'!$Z$2:$Z$1001,'Per Line'!$E$2:$E$1001,$B7,'Per Line'!$AQ$2:$AQ$1001,1,'Per Line'!$AR$2:$AR$1001,0)) | T7: =IF($Y7="","",S7*R7) | U7: =IF($Y7="","",T7+Q7) | V7: =IF($Y7="","",W7-U7) | W7: =IF($Y7="","",P7+S7+N7) | X7: =IF($Y7="","",W7-U7-L7) | Y7: =IF(ROWS($Y$2:$Y7)<=MAX('Per Line'!$AP$2:$AP$1001),MATCH(ROWS($Y$2:$Y7),'Per Line'!$AP$2:$AP$1001,0),"")
B8: =IF($Y8="","",INDEX('Per Line'!$E$2:$E$1001,$Y8)&"") | C8: =IF($Y8="","",INDEX('Per Line'!$F$2:$F$1001,$Y8)&"") | D8: =IF($Y8="","",INDEX('Per Line'!$A$2:$A$1001,$Y8)&"") | E8: =IF($Y8="","",INDEX('Per Line'!$B$2:$B$1001,$Y8)) | F8: =IF($Y8="","",INDEX('Per Line'!$G$2:$G$1001,$Y8)&"") | G8: =IF($Y8="","",INDEX('Per Line'!$H$2:$H$1001,$Y8)) | H8: =IF($Y8="","",INDEX('Per Line'!$K$2:$K$1001,$Y8)&"") | I8: =IF($Y8="","",INDEX('Per Line'!$L$2:$L$1001,$Y8)&"") | J8: =IF($Y8="","",INDEX('Per Line'!$M$2:$M$1001,$Y8)&"") | K8: =IF($Y8="","",INDEX('Per Line'!$Q$2:$Q$1001,$Y8)) | L8: =IF($Y8="","",K8*W8/100) | M8: =IF($Y8="","",INDEX('Per Line'!$AD$2:$AD$1001,$Y8)&"") | N8: =IF($Y8="","",SUMIFS('Per Line'!$Z$2:$Z$1001,'Per Line'!$E$2:$E$1001,$B8,'Per Line'!$AR$2:$AR$1001,1)) | O8: =IF($Y8="","",Settings!$C$7) | P8: =IF($Y8="","",SUMIFS('Per Line'!$Z$2:$Z$1001,'Per Line'!$E$2:$E$1001,$B8,'Per Line'!$AQ$2:$AQ$1001,0,'Per Line'!$AR$2:$AR$1001,0)) | Q8: =IF($Y8="","",P8*O8) | R8: =IF($Y8="","",Settings!$C$6) | S8: =IF($Y8="","",SUMIFS('Per Line'!$Z$2:$Z$1001,'Per Line'!$E$2:$E$1001,$B8,'Per Line'!$AQ$2:$AQ$1001,1,'Per Line'!$AR$2:$AR$1001,0)) | T8: =IF($Y8="","",S8*R8) | U8: =IF($Y8="","",T8+Q8) | V8: =IF($Y8="","",W8-U8) | W8: =IF($Y8="","",P8+S8+N8) | X8: =IF($Y8="","",W8-U8-L8) | Y8: =IF(ROWS($Y$2:$Y8)<=MAX('Per Line'!$AP$2:$AP$1001),MATCH(ROWS($Y$2:$Y8),'Per Line'!$AP$2:$AP$1001,0),"")
B9: =IF($Y9="","",INDEX('Per Line'!$E$2:$E$1001,$Y9)&"") | C9: =IF($Y9="","",INDEX('Per Line'!$F$2:$F$1001,$Y9)&"") | D9: =IF($Y9="","",INDEX('Per Line'!$A$2:$A$1001,$Y9)&"") | E9: =IF($Y9="","",INDEX('Per Line'!$B$2:$B$1001,$Y9)) | F9: =IF($Y9="","",INDEX('Per Line'!$G$2:$G$1001,$Y9)&"") | G9: =IF($Y9="","",INDEX('Per Line'!$H$2:$H$1001,$Y9)) | H9: =IF($Y9="","",INDEX('Per Line'!$K$2:$K$1001,$Y9)&"") | I9: =IF($Y9="","",INDEX('Per Line'!$L$2:$L$1001,$Y9)&"") | J9: =IF($Y9="","",INDEX('Per Line'!$M$2:$M$1001,$Y9)&"") | K9: =IF($Y9="","",INDEX('Per Line'!$Q$2:$Q$1001,$Y9)) | L9: =IF($Y9="","",K9*W9/100) | M9: =IF($Y9="","",INDEX('Per Line'!$AD$2:$AD$1001,$Y9)&"") | N9: =IF($Y9="","",SUMIFS('Per Line'!$Z$2:$Z$1001,'Per Line'!$E$2:$E$1001,$B9,'Per Line'!$AR$2:$AR$1001,1)) | O9: =IF($Y9="","",Settings!$C$7) | P9: =IF($Y9="","",SUMIFS('Per Line'!$Z$2:$Z$1001,'Per Line'!$E$2:$E$1001,$B9,'Per Line'!$AQ$2:$AQ$1001,0,'Per Line'!$AR$2:$AR$1001,0)) | Q9: =IF($Y9="","",P9*O9) | R9: =IF($Y9="","",Settings!$C$6) | S9: =IF($Y9="","",SUMIFS('Per Line'!$Z$2:$Z$1001,'Per Line'!$E$2:$E$1001,$B9,'Per Line'!$AQ$2:$AQ$1001,1,'Per Line'!$AR$2:$AR$1001,0)) | T9: =IF($Y9="","",S9*R9) | U9: =IF($Y9="","",T9+Q9) | V9: =IF($Y9="","",W9-U9) | W9: =IF($Y9="","",P9+S9+N9) | X9: =IF($Y9="","",W9-U9-L9) | Y9: =IF(ROWS($Y$2:$Y9)<=MAX('Per Line'!$AP$2:$AP$1001),MATCH(ROWS($Y$2:$Y9),'Per Line'!$AP$2:$AP$1001,0),"")
B10: =IF($Y10="","",INDEX('Per Line'!$E$2:$E$1001,$Y10)&"") | C10: =IF($Y10="","",INDEX('Per Line'!$F$2:$F$1001,$Y10)&"") | D10: =IF($Y10="","",INDEX('Per Line'!$A$2:$A$1001,$Y10)&"") | E10: =IF($Y10="","",INDEX('Per Line'!$B$2:$B$1001,$Y10)) | F10: =IF($Y10="","",INDEX('Per Line'!$G$2:$G$1001,$Y10)&"") | G10: =IF($Y10="","",INDEX('Per Line'!$H$2:$H$1001,$Y10)) | H10: =IF($Y10="","",INDEX('Per Line'!$K$2:$K$1001,$Y10)&"") | I10: =IF($Y10="","",INDEX('Per Line'!$L$2:$L$1001,$Y10)&"") | J10: =IF($Y10="","",INDEX('Per Line'!$M$2:$M$1001,$Y10)&"") | K10: =IF($Y10="","",INDEX('Per Line'!$Q$2:$Q$1001,$Y10)) | L10: =IF($Y10="","",K10*W10/100) | M10: =IF($Y10="","",INDEX('Per Line'!$AD$2:$AD$1001,$Y10)&"") | N10: =IF($Y10="","",SUMIFS('Per Line'!$Z$2:$Z$1001,'Per Line'!$E$2:$E$1001,$B10,'Per Line'!$AR$2:$AR$1001,1)) | O10: =IF($Y10="","",Settings!$C$7) | P10: =IF($Y10="","",SUMIFS('Per Line'!$Z$2:$Z$1001,'Per Line'!$E$2:$E$1001,$B10,'Per Line'!$AQ$2:$AQ$1001,0,'Per Line'!$AR$2:$AR$1001,0)) | Q10: =IF($Y10="","",P10*O10) | R10: =IF($Y10="","",Settings!$C$6) | S10: =IF($Y10="","",SUMIFS('Per Line'!$Z$2:$Z$1001,'Per Line'!$E$2:$E$1001,$B10,'Per Line'!$AQ$2:$AQ$1001,1,'Per Line'!$AR$2:$AR$1001,0)) | T10: =IF($Y10="","",S10*R10) | U10: =IF($Y10="","",T10+Q10) | V10: =IF($Y10="","",W10-U10) | W10: =IF($Y10="","",P10+S10+N10) | X10: =IF($Y10="","",W10-U10-L10) | Y10: =IF(ROWS($Y$2:$Y10)<=MAX('Per Line'!$AP$2:$AP$1001),MATCH(ROWS($Y$2:$Y10),'Per Line'!$AP$2:$AP$1001,0),"")
B11: =IF($Y11="","",INDEX('Per Line'!$E$2:$E$1001,$Y11)&"") | C11: =IF($Y11="","",INDEX('Per Line'!$F$2:$F$1001,$Y11)&"") | D11: =IF($Y11="","",INDEX('Per Line'!$A$2:$A$1001,$Y11)&"") | E11: =IF($Y11="","",INDEX('Per Line'!$B$2:$B$1001,$Y11)) | F11: =IF($Y11="","",INDEX('Per Line'!$G$2:$G$1001,$Y11)&"") | G11: =IF($Y11="","",INDEX('Per Line'!$H$2:$H$1001,$Y11)) | H11: =IF($Y11="","",INDEX('Per Line'!$K$2:$K$1001,$Y11)&"") | I11: =IF($Y11="","",INDEX('Per Line'!$L$2:$L$1001,$Y11)&"") | J11: =IF($Y11="","",INDEX('Per Line'!$M$2:$M$1001,$Y11)&"") | K11: =IF($Y11="","",INDEX('Per Line'!$Q$2:$Q$1001,$Y11)) | L11: =IF($Y11="","",K11*W11/100) | M11: =IF($Y11="","",INDEX('Per Line'!$AD$2:$AD$1001,$Y11)&"") | N11: =IF($Y11="","",SUMIFS('Per Line'!$Z$2:$Z$1001,'Per Line'!$E$2:$E$1001,$B11,'Per Line'!$AR$2:$AR$1001,1)) | O11: =IF($Y11="","",Settings!$C$7) | P11: =IF($Y11="","",SUMIFS('Per Line'!$Z$2:$Z$1001,'Per Line'!$E$2:$E$1001,$B11,'Per Line'!$AQ$2:$AQ$1001,0,'Per Line'!$AR$2:$AR$1001,0)) | Q11: =IF($Y11="","",P11*O11) | R11: =IF($Y11="","",Settings!$C$6) | S11: =IF($Y11="","",SUMIFS('Per Line'!$Z$2:$Z$1001,'Per Line'!$E$2:$E$1001,$B11,'Per Line'!$AQ$2:$AQ$1001,1,'Per Line'!$AR$2:$AR$1001,0)) | T11: =IF($Y11="","",S11*R11) | U11: =IF($Y11="","",T11+Q11) | V11: =IF($Y11="","",W11-U11) | W11: =IF($Y11="","",P11+S11+N11) | X11: =IF($Y11="","",W11-U11-L11) | Y11: =IF(ROWS($Y$2:$Y11)<=MAX('Per Line'!$AP$2:$AP$1001),MATCH(ROWS($Y$2:$Y11),'Per Line'!$AP$2:$AP$1001,0),"")
B12: =IF($Y12="","",INDEX('Per Line'!$E$2:$E$1001,$Y12)&"") | C12: =IF($Y12="","",INDEX('Per Line'!$F$2:$F$1001,$Y12)&"") | D12: =IF($Y12="","",INDEX('Per Line'!$A$2:$A$1001,$Y12)&"") | E12: =IF($Y12="","",INDEX('Per Line'!$B$2:$B$1001,$Y12)) | F12: =IF($Y12="","",INDEX('Per Line'!$G$2:$G$1001,$Y12)&"") | G12: =IF($Y12="","",INDEX('Per Line'!$H$2:$H$1001,$Y12)) | H12: =IF($Y12="","",INDEX('Per Line'!$K$2:$K$1001,$Y12)&"") | I12: =IF($Y12="","",INDEX('Per Line'!$L$2:$L$1001,$Y12)&"") | J12: =IF($Y12="","",INDEX('Per Line'!$M$2:$M$1001,$Y12)&"") | K12: =IF($Y12="","",INDEX('Per Line'!$Q$2:$Q$1001,$Y12)) | L12: =IF($Y12="","",K12*W12/100) | M12: =IF($Y12="","",INDEX('Per Line'!$AD$2:$AD$1001,$Y12)&"") | N12: =IF($Y12="","",SUMIFS('Per Line'!$Z$2:$Z$1001,'Per Line'!$E$2:$E$1001,$B12,'Per Line'!$AR$2:$AR$1001,1)) | O12: =IF($Y12="","",Settings!$C$7) | P12: =IF($Y12="","",SUMIFS('Per Line'!$Z$2:$Z$1001,'Per Line'!$E$2:$E$1001,$B12,'Per Line'!$AQ$2:$AQ$1001,0,'Per Line'!$AR$2:$AR$1001,0)) | Q12: =IF($Y12="","",P12*O12) | R12: =IF($Y12="","",Settings!$C$6) | S12: =IF($Y12="","",SUMIFS('Per Line'!$Z$2:$Z$1001,'Per Line'!$E$2:$E$1001,$B12,'Per Line'!$AQ$2:$AQ$1001,1,'Per Line'!$AR$2:$AR$1001,0)) | T12: =IF($Y12="","",S12*R12) | U12: =IF($Y12="","",T12+Q12) | V12: =IF($Y12="","",W12-U12) | W12: =IF($Y12="","",P12+S12+N12) | X12: =IF($Y12="","",W12-U12-L12) | Y12: =IF(ROWS($Y$2:$Y12)<=MAX('Per Line'!$AP$2:$AP$1001),MATCH(ROWS($Y$2:$Y12),'Per Line'!$AP$2:$AP$1001,0),"")
B13: =IF($Y13="","",INDEX('Per Line'!$E$2:$E$1001,$Y13)&"") | C13: =IF($Y13="","",INDEX('Per Line'!$F$2:$F$1001,$Y13)&"") | D13: =IF($Y13="","",INDEX('Per Line'!$A$2:$A$1001,$Y13)&"") | E13: =IF($Y13="","",INDEX('Per Line'!$B$2:$B$1001,$Y13)) | F13: =IF($Y13="","",INDEX('Per Line'!$G$2:$G$1001,$Y13)&"") | G13: =IF($Y13="","",INDEX('Per Line'!$H$2:$H$1001,$Y13)) | H13: =IF($Y13="","",INDEX('Per Line'!$K$2:$K$1001,$Y13)&"") | I13: =IF($Y13="","",INDEX('Per Line'!$L$2:$L$1001,$Y13)&"") | J13: =IF($Y13="","",INDEX('Per Line'!$M$2:$M$1001,$Y13)&"") | K13: =IF($Y13="","",INDEX('Per Line'!$Q$2:$Q$1001,$Y13)) | L13: =IF($Y13="","",K13*W13/100) | M13: =IF($Y13="","",INDEX('Per Line'!$AD$2:$AD$1001,$Y13)&"") | N13: =IF($Y13="","",SUMIFS('Per Line'!$Z$2:$Z$1001,'Per Line'!$E$2:$E$1001,$B13,'Per Line'!$AR$2:$AR$1001,1)) | O13: =IF($Y13="","",Settings!$C$7) | P13: =IF($Y13="","",SUMIFS('Per Line'!$Z$2:$Z$1001,'Per Line'!$E$2:$E$1001,$B13,'Per Line'!$AQ$2:$AQ$1001,0,'Per Line'!$AR$2:$AR$1001,0)) | Q13: =IF($Y13="","",P13*O13) | R13: =IF($Y13="","",Settings!$C$6) | S13: =IF($Y13="","",SUMIFS('Per Line'!$Z$2:$Z$1001,'Per Line'!$E$2:$E$1001,$B13,'Per Line'!$AQ$2:$AQ$1001,1,'Per Line'!$AR$2:$AR$1001,0)) | T13: =IF($Y13="","",S13*R13) | U13: =IF($Y13="","",T13+Q13) | V13: =IF($Y13="","",W13-U13) | W13: =IF($Y13="","",P13+S13+N13) | X13: =IF($Y13="","",W13-U13-L13) | Y13: =IF(ROWS($Y$2:$Y13)<=MAX('Per Line'!$AP$2:$AP$1001),MATCH(ROWS($Y$2:$Y13),'Per Line'!$AP$2:$AP$1001,0),"")
... B301: =IF($Y301="","",INDEX('Per Line'!$E$2:$E$1001,$Y301)&"") | C301: =IF($Y301="","",INDEX('Per Line'!$F$2:$F$1001,$Y301)&"") | D301: =IF($Y301="","",INDEX('Per Line'!$A$2:$A$1001,$Y301)&"") | E301: =IF($Y301="","",INDEX('Per Line'!$B$2:$B$1001,$Y301)) | F301: =IF($Y301="","",INDEX('Per Line'!$G$2:$G$1001,$Y301)&"") | G301: =IF($Y301="","",INDEX('Per Line'!$H$2:$H$1001,$Y301)) | H301: =IF($Y301="","",INDEX('Per Line'!$K$2:$K$1001,$Y301)&"") | I301: =IF($Y301="","",INDEX('Per Line'!$L$2:$L$1001,$Y301)&"") | J301: =IF($Y301="","",INDEX('Per Line'!$M$2:$M$1001,$Y301)&"") | K301: =IF($Y301="","",INDEX('Per Line'!$Q$2:$Q$1001,$Y301)) | L301: =IF($Y301="","",K301*W301/100) | M301: =IF($Y301="","",INDEX('Per Line'!$AD$2:$AD$1001,$Y301)&"") | N301: =IF($Y301="","",SUMIFS('Per Line'!$Z$2:$Z$1001,'Per Line'!$E$2:$E$1001,$B301,'Per Line'!$AR$2:$AR$1001,1)) | O301: =IF($Y301="","",Settings!$C$7) | P301: =IF($Y301="","",SUMIFS('Per Line'!$Z$2:$Z$1001,'Per Line'!$E$2:$E$1001,$B301,'Per Line'!$AQ$2:$AQ$1001,0,'Per Line'!$AR$2:$AR$1001,0)) | Q301: =IF($Y301="","",P301*O301) | R301: =IF($Y301="","",Settings!$C$6) | S301: =IF($Y301="","",SUMIFS('Per Line'!$Z$2:$Z$1001,'Per Line'!$E$2:$E$1001,$B301,'Per Line'!$AQ$2:$AQ$1001,1,'Per Line'!$AR$2:$AR$1001,0)) | T301: =IF($Y301="","",S301*R301) | U301: =IF($Y301="","",T301+Q301) | V301: =IF($Y301="","",W301-U301) | W301: =IF($Y301="","",P301+S301+N301) | X301: =IF($Y301="","",W301-U301-L301) | Y301: =IF(ROWS($Y$2:$Y301)<=MAX('Per Line'!$AP$2:$AP$1001),MATCH(ROWS($Y$2:$Y301),'Per Line'!$AP$2:$AP$1001,0),"")
