Workbook

Sheet How To Use
A1: Claims Template - HYPERONE (Chronic)
A3: Monthly steps
A4: 1. Open the 'Per Line' tab. Delete the old data in the BLUE columns only (row 2 down). Never delete the green or grey columns.
A5: 2. Paste the new month's data as VALUES starting at A2, into the blue columns: A-M, O-V, Z-AA, AC-AJ (same order as the system export).
A6: 3. Green columns (N, W, X, Y, AB) and the grey helper columns (AK-AO) calculate automatically - do not paste over them.
A7: 4. 'Per Invoice' fills itself from 'Per Line' (one row per Order #, split into IMP / Local). No pivot table, no refresh.
A8: 5. The ONLY manual column in 'Per Invoice' is column A 'Invoice' (blue): type it yourself. Everything else is formula.
A9: 6. Open 'Settings' and check STATUS says OK (Per Line totals = Per Invoice totals).
A11: Colour legend
A12: Blue header = typed/pasted by you (raw data, and 'Invoice' in Per Invoice). Green header = formula (do not paste over). Grey header = helper formula (do not touch). Yellow cell (Settings) = editable rate.
A14: Calculation rules (taken from the October 2026 sheet)
A15: Co val = Order Co Payment x Total / 100. Discount = Total x Rebates / 100. Subtotal = Total - Discount. Net = Subtotal - Co val. (Total = 'Product Total')
... A20: Capacity: up to 1,500 lines and 500 invoices per month. A line with an empty Order # is ignored.

Sheet Settings
B1: Company settings & checks
B3: Insurance Company | C3: HYPERONE | D3: Informational only
B4: Corporate | C4: Hyperone -Zayed; HyperOne Sphinx | D4: Informational only
B5: Sheet type | C5: Chronic | D5: Informational only
B6: Local products rebate % | C6: 0.15 | D6: Source: Oct sheet (Rebates = 15 on Local lines).
B7: Imported (IMP) products rebate % | C7: 0.05 | D7: Source: Oct sheet (Rebates = 5 on non-local lines).
B9: Month totals / reconciliation
B10: Lines loaded | C10: =COUNTA('Per Line'!$D$2:$D$1501)
B11: Invoices (unique Order #) | C11: =MAX('Per Line'!$AL$2:$AL$1501)
B12: Invoices shown in Per Invoice | C12: =SUMPRODUCT(--('Per Invoice'!$B$2:$B$501<>""))
B13: Grand Total - Per Line (Product Total) | C13: =SUM('Per Line'!$V$2:$V$1501)
B14: Grand Total - Per Invoice | C14: =SUM('Per Invoice'!$T$2:$T$501)
B15: Discount - Per Line | C15: =SUM('Per Line'!$W$2:$W$1501)
B16: Discount - Per Invoice | C16: =SUM('Per Invoice'!$R$2:$R$501)
B17: Co val - Per Line | C17: =SUM('Per Line'!$N$2:$N$1501)
B18: Co val - Per Invoice | C18: =SUM('Per Invoice'!$J$2:$J$501)
B19: Net - Per Line | C19: =SUM('Per Line'!$Y$2:$Y$1501)
B20: Net - Per Invoice | C20: =SUM('Per Invoice'!$U$2:$U$501)
B21: Max Limit adjustment (Co val, Per Invoice only) | C21: 0 | D21: This company's Per Invoice has no Max Limit rule.
B23: STATUS | C23: =IF(C10=0,"No data loaded",IF(COUNTA('Per Line'!$D:$D)-1>1500,"TOO MANY LINES - extend template",IF(C11>500,"TOO MANY INVOICES - extend template",IF(AND(ROUND(C13-C14,2)=0,ROUND(C15-C16,2)=0,ROUND(C17+C21-C18,2)=0,ROUND(C19-C21-C20,2)=0,C11=C12),"OK","CHECK - Per Line and Per Invoice do not match")))) | D23: Must say OK after you paste the month data.

Sheet Per Line
A1: Ticket # | B1: Stage | C1: Approval Ref | D1: Order # | E1: Channel | F1: Create At | G1: Insurance Company | H1: Country Portal ID | I1: Corporate | J1: Card | K1: Name | L1: Status | M1: Order Co Payment | N1: Co val | O1: By Patient | P1: heisenberg id | Q1: Product Name | R1: Local | S1: Unit | T1: Quantity | U1: Unit Price | V1: Product Total | W1: Discount | X1: Subtotal | Y1: Net | Z1: ERX ID | AA1: Special Rebates? | AB1: Rebates | AC1: Approval Type | AD1: Max Limit | AE1: Exceeding Limit | AF1: Amount collected from customer | AG1: By Patient (Delivered) | AH1: Dispense Number | AI1: Dispense Date | AJ1: Has OTP? | AK1: Order 1st Row (helper) | AL1: Invoice # (helper) | AM1: Is Local (helper) | AN1: Is Special (helper) | AO1: Sort Key (helper)
N2: =IF($D2="","",M2*V2/100) | W2: =IF($D2="","",V2*AB2/100) | X2: =IF($D2="","",V2-W2) | Y2: =IF($D2="","",X2-N2) | AB2: =IF($D2="","",IF($AN2=1,0,IF($AM2=1,Settings!$C$6,Settings!$C$7))*100) | AK2: =IF($D2="","",IF(COUNTIF($D$2:$D2,$D2)=1,1,0)) | AL2: =IF($AK2=1,SUMPRODUCT(--($AO$2:$AO$1501<$AO2))+1,"") | AM2: =IF($D2="","",IF(OR($R2=TRUE(),$R2="TRUE"),1,0)) | AN2: =IF($D2="","",IF($AA2="Yes",1,0)) | AO2: =IF($AK2=1,IFERROR(IF(VALUE($D2)<100000000,VALUE($D2),1000000000),IFERROR(IF(VALUE(MID($D2,2,20))<100000000,VALUE(MID($D2,2,20)),1000000000),1000000000))+ROW()/100000,"")
N3: =IF($D3="","",M3*V3/100) | W3: =IF($D3="","",V3*AB3/100) | X3: =IF($D3="","",V3-W3) | Y3: =IF($D3="","",X3-N3) | AB3: =IF($D3="","",IF($AN3=1,0,IF($AM3=1,Settings!$C$6,Settings!$C$7))*100) | AK3: =IF($D3="","",IF(COUNTIF($D$2:$D3,$D3)=1,1,0)) | AL3: =IF($AK3=1,SUMPRODUCT(--($AO$2:$AO$1501<$AO3))+1,"") | AM3: =IF($D3="","",IF(OR($R3=TRUE(),$R3="TRUE"),1,0)) | AN3: =IF($D3="","",IF($AA3="Yes",1,0)) | AO3: =IF($AK3=1,IFERROR(IF(VALUE($D3)<100000000,VALUE($D3),1000000000),IFERROR(IF(VALUE(MID($D3,2,20))<100000000,VALUE(MID($D3,2,20)),1000000000),1000000000))+ROW()/100000,"")
N4: =IF($D4="","",M4*V4/100) | W4: =IF($D4="","",V4*AB4/100) | X4: =IF($D4="","",V4-W4) | Y4: =IF($D4="","",X4-N4) | AB4: =IF($D4="","",IF($AN4=1,0,IF($AM4=1,Settings!$C$6,Settings!$C$7))*100) | AK4: =IF($D4="","",IF(COUNTIF($D$2:$D4,$D4)=1,1,0)) | AL4: =IF($AK4=1,SUMPRODUCT(--($AO$2:$AO$1501<$AO4))+1,"") | AM4: =IF($D4="","",IF(OR($R4=TRUE(),$R4="TRUE"),1,0)) | AN4: =IF($D4="","",IF($AA4="Yes",1,0)) | AO4: =IF($AK4=1,IFERROR(IF(VALUE($D4)<100000000,VALUE($D4),1000000000),IFERROR(IF(VALUE(MID($D4,2,20))<100000000,VALUE(MID($D4,2,20)),1000000000),1000000000))+ROW()/100000,"")
N5: =IF($D5="","",M5*V5/100) | W5: =IF($D5="","",V5*AB5/100) | X5: =IF($D5="","",V5-W5) | Y5: =IF($D5="","",X5-N5) | AB5: =IF($D5="","",IF($AN5=1,0,IF($AM5=1,Settings!$C$6,Settings!$C$7))*100) | AK5: =IF($D5="","",IF(COUNTIF($D$2:$D5,$D5)=1,1,0)) | AL5: =IF($AK5=1,SUMPRODUCT(--($AO$2:$AO$1501<$AO5))+1,"") | AM5: =IF($D5="","",IF(OR($R5=TRUE(),$R5="TRUE"),1,0)) | AN5: =IF($D5="","",IF($AA5="Yes",1,0)) | AO5: =IF($AK5=1,IFERROR(IF(VALUE($D5)<100000000,VALUE($D5),1000000000),IFERROR(IF(VALUE(MID($D5,2,20))<100000000,VALUE(MID($D5,2,20)),1000000000),1000000000))+ROW()/100000,"")
N6: =IF($D6="","",M6*V6/100) | W6: =IF($D6="","",V6*AB6/100) | X6: =IF($D6="","",V6-W6) | Y6: =IF($D6="","",X6-N6) | AB6: =IF($D6="","",IF($AN6=1,0,IF($AM6=1,Settings!$C$6,Settings!$C$7))*100) | AK6: =IF($D6="","",IF(COUNTIF($D$2:$D6,$D6)=1,1,0)) | AL6: =IF($AK6=1,SUMPRODUCT(--($AO$2:$AO$1501<$AO6))+1,"") | AM6: =IF($D6="","",IF(OR($R6=TRUE(),$R6="TRUE"),1,0)) | AN6: =IF($D6="","",IF($AA6="Yes",1,0)) | AO6: =IF($AK6=1,IFERROR(IF(VALUE($D6)<100000000,VALUE($D6),1000000000),IFERROR(IF(VALUE(MID($D6,2,20))<100000000,VALUE(MID($D6,2,20)),1000000000),1000000000))+ROW()/100000,"")
N7: =IF($D7="","",M7*V7/100) | W7: =IF($D7="","",V7*AB7/100) | X7: =IF($D7="","",V7-W7) | Y7: =IF($D7="","",X7-N7) | AB7: =IF($D7="","",IF($AN7=1,0,IF($AM7=1,Settings!$C$6,Settings!$C$7))*100) | AK7: =IF($D7="","",IF(COUNTIF($D$2:$D7,$D7)=1,1,0)) | AL7: =IF($AK7=1,SUMPRODUCT(--($AO$2:$AO$1501<$AO7))+1,"") | AM7: =IF($D7="","",IF(OR($R7=TRUE(),$R7="TRUE"),1,0)) | AN7: =IF($D7="","",IF($AA7="Yes",1,0)) | AO7: =IF($AK7=1,IFERROR(IF(VALUE($D7)<100000000,VALUE($D7),1000000000),IFERROR(IF(VALUE(MID($D7,2,20))<100000000,VALUE(MID($D7,2,20)),1000000000),1000000000))+ROW()/100000,"")
N8: =IF($D8="","",M8*V8/100) | W8: =IF($D8="","",V8*AB8/100) | X8: =IF($D8="","",V8-W8) | Y8: =IF($D8="","",X8-N8) | AB8: =IF($D8="","",IF($AN8=1,0,IF($AM8=1,Settings!$C$6,Settings!$C$7))*100) | AK8: =IF($D8="","",IF(COUNTIF($D$2:$D8,$D8)=1,1,0)) | AL8: =IF($AK8=1,SUMPRODUCT(--($AO$2:$AO$1501<$AO8))+1,"") | AM8: =IF($D8="","",IF(OR($R8=TRUE(),$R8="TRUE"),1,0)) | AN8: =IF($D8="","",IF($AA8="Yes",1,0)) | AO8: =IF($AK8=1,IFERROR(IF(VALUE($D8)<100000000,VALUE($D8),1000000000),IFERROR(IF(VALUE(MID($D8,2,20))<100000000,VALUE(MID($D8,2,20)),1000000000),1000000000))+ROW()/100000,"")
N9: =IF($D9="","",M9*V9/100) | W9: =IF($D9="","",V9*AB9/100) | X9: =IF($D9="","",V9-W9) | Y9: =IF($D9="","",X9-N9) | AB9: =IF($D9="","",IF($AN9=1,0,IF($AM9=1,Settings!$C$6,Settings!$C$7))*100) | AK9: =IF($D9="","",IF(COUNTIF($D$2:$D9,$D9)=1,1,0)) | AL9: =IF($AK9=1,SUMPRODUCT(--($AO$2:$AO$1501<$AO9))+1,"") | AM9: =IF($D9="","",IF(OR($R9=TRUE(),$R9="TRUE"),1,0)) | AN9: =IF($D9="","",IF($AA9="Yes",1,0)) | AO9: =IF($AK9=1,IFERROR(IF(VALUE($D9)<100000000,VALUE($D9),1000000000),IFERROR(IF(VALUE(MID($D9,2,20))<100000000,VALUE(MID($D9,2,20)),1000000000),1000000000))+ROW()/100000,"")
N10: =IF($D10="","",M10*V10/100) | W10: =IF($D10="","",V10*AB10/100) | X10: =IF($D10="","",V10-W10) | Y10: =IF($D10="","",X10-N10) | AB10: =IF($D10="","",IF($AN10=1,0,IF($AM10=1,Settings!$C$6,Settings!$C$7))*100) | AK10: =IF($D10="","",IF(COUNTIF($D$2:$D10,$D10)=1,1,0)) | AL10: =IF($AK10=1,SUMPRODUCT(--($AO$2:$AO$1501<$AO10))+1,"") | AM10: =IF($D10="","",IF(OR($R10=TRUE(),$R10="TRUE"),1,0)) | AN10: =IF($D10="","",IF($AA10="Yes",1,0)) | AO10: =IF($AK10=1,IFERROR(IF(VALUE($D10)<100000000,VALUE($D10),1000000000),IFERROR(IF(VALUE(MID($D10,2,20))<100000000,VALUE(MID($D10,2,20)),1000000000),1000000000))+ROW()/100000,"")
N11: =IF($D11="","",M11*V11/100) | W11: =IF($D11="","",V11*AB11/100) | X11: =IF($D11="","",V11-W11) | Y11: =IF($D11="","",X11-N11) | AB11: =IF($D11="","",IF($AN11=1,0,IF($AM11=1,Settings!$C$6,Settings!$C$7))*100) | AK11: =IF($D11="","",IF(COUNTIF($D$2:$D11,$D11)=1,1,0)) | AL11: =IF($AK11=1,SUMPRODUCT(--($AO$2:$AO$1501<$AO11))+1,"") | AM11: =IF($D11="","",IF(OR($R11=TRUE(),$R11="TRUE"),1,0)) | AN11: =IF($D11="","",IF($AA11="Yes",1,0)) | AO11: =IF($AK11=1,IFERROR(IF(VALUE($D11)<100000000,VALUE($D11),1000000000),IFERROR(IF(VALUE(MID($D11,2,20))<100000000,VALUE(MID($D11,2,20)),1000000000),1000000000))+ROW()/100000,"")
N12: =IF($D12="","",M12*V12/100) | W12: =IF($D12="","",V12*AB12/100) | X12: =IF($D12="","",V12-W12) | Y12: =IF($D12="","",X12-N12) | AB12: =IF($D12="","",IF($AN12=1,0,IF($AM12=1,Settings!$C$6,Settings!$C$7))*100) | AK12: =IF($D12="","",IF(COUNTIF($D$2:$D12,$D12)=1,1,0)) | AL12: =IF($AK12=1,SUMPRODUCT(--($AO$2:$AO$1501<$AO12))+1,"") | AM12: =IF($D12="","",IF(OR($R12=TRUE(),$R12="TRUE"),1,0)) | AN12: =IF($D12="","",IF($AA12="Yes",1,0)) | AO12: =IF($AK12=1,IFERROR(IF(VALUE($D12)<100000000,VALUE($D12),1000000000),IFERROR(IF(VALUE(MID($D12,2,20))<100000000,VALUE(MID($D12,2,20)),1000000000),1000000000))+ROW()/100000,"")
N13: =IF($D13="","",M13*V13/100) | W13: =IF($D13="","",V13*AB13/100) | X13: =IF($D13="","",V13-W13) | Y13: =IF($D13="","",X13-N13) | AB13: =IF($D13="","",IF($AN13=1,0,IF($AM13=1,Settings!$C$6,Settings!$C$7))*100) | AK13: =IF($D13="","",IF(COUNTIF($D$2:$D13,$D13)=1,1,0)) | AL13: =IF($AK13=1,SUMPRODUCT(--($AO$2:$AO$1501<$AO13))+1,"") | AM13: =IF($D13="","",IF(OR($R13=TRUE(),$R13="TRUE"),1,0)) | AN13: =IF($D13="","",IF($AA13="Yes",1,0)) | AO13: =IF($AK13=1,IFERROR(IF(VALUE($D13)<100000000,VALUE($D13),1000000000),IFERROR(IF(VALUE(MID($D13,2,20))<100000000,VALUE(MID($D13,2,20)),1000000000),1000000000))+ROW()/100000,"")
... N1501: =IF($D1501="","",M1501*V1501/100) | W1501: =IF($D1501="","",V1501*AB1501/100) | X1501: =IF($D1501="","",V1501-W1501) | Y1501: =IF($D1501="","",X1501-N1501) | AB1501: =IF($D1501="","",IF($AN1501=1,0,IF($AM1501=1,Settings!$C$6,Settings!$C$7))*100) | AK1501: =IF($D1501="","",IF(COUNTIF($D$2:$D1501,$D1501)=1,1,0)) | AL1501: =IF($AK1501=1,SUMPRODUCT(--($AO$2:$AO$1501<$AO1501))+1,"") | AM1501: =IF($D1501="","",IF(OR($R1501=TRUE(),$R1501="TRUE"),1,0)) | AN1501: =IF($D1501="","",IF($AA1501="Yes",1,0)) | AO1501: =IF($AK1501=1,IFERROR(IF(VALUE($D1501)<100000000,VALUE($D1501),1000000000),IFERROR(IF(VALUE(MID($D1501,2,20))<100000000,VALUE(MID($D1501,2,20)),1000000000),1000000000))+ROW()/100000,"")

Sheet Per Invoice
A1: Invoice | B1: Order # | C1: Ticket # | D1: ERX ID | E1: Create At | F1: Corporate | G1: Card | H1: Name | I1: Order Co Payment | J1: Co val | K1: Special | L1: imp % | M1: imp | N1: imp val | O1: local val | P1: local | Q1: local val | R1: total val | S1: subtotal | T1: Grand Total | U1: net | V1: Src Row (helper)
B2: =IF($V2="","",INDEX('Per Line'!$D$2:$D$1501,$V2)&"") | C2: =IF($V2="","",INDEX('Per Line'!$A$2:$A$1501,$V2)) | D2: =IF($V2="","",INDEX('Per Line'!$Z$2:$Z$1501,$V2)&"") | E2: =IF($V2="","",INDEX('Per Line'!$F$2:$F$1501,$V2)) | F2: =IF($V2="","",INDEX('Per Line'!$I$2:$I$1501,$V2)&"") | G2: =IF($V2="","",INDEX('Per Line'!$J$2:$J$1501,$V2)&"") | H2: =IF($V2="","",INDEX('Per Line'!$K$2:$K$1501,$V2)&"") | I2: =IF($V2="","",INDEX('Per Line'!$M$2:$M$1501,$V2)) | J2: =IF($V2="","",I2*T2/100) | K2: =IF($V2="","",SUMIFS('Per Line'!$V$2:$V$1501,'Per Line'!$D$2:$D$1501,$B2,'Per Line'!$AN$2:$AN$1501,1)) | L2: =IF($V2="","",Settings!$C$7) | M2: =IF($V2="","",SUMIFS('Per Line'!$V$2:$V$1501,'Per Line'!$D$2:$D$1501,$B2,'Per Line'!$AM$2:$AM$1501,0,'Per Line'!$AN$2:$AN$1501,0)) | N2: =IF($V2="","",M2*L2) | O2: =IF($V2="","",Settings!$C$6) | P2: =IF($V2="","",SUMIFS('Per Line'!$V$2:$V$1501,'Per Line'!$D$2:$D$1501,$B2,'Per Line'!$AM$2:$AM$1501,1,'Per Line'!$AN$2:$AN$1501,0)) | Q2: =IF($V2="","",P2*O2) | R2: =IF($V2="","",Q2+N2) | S2: =IF($V2="","",T2-R2) | T2: =IF($V2="","",M2+P2+K2) | U2: =IF($V2="","",T2-R2-J2) | V2: =IF(ROWS($V$2:$V2)<=MAX('Per Line'!$AL$2:$AL$1501),MATCH(ROWS($V$2:$V2),'Per Line'!$AL$2:$AL$1501,0),"")
B3: =IF($V3="","",INDEX('Per Line'!$D$2:$D$1501,$V3)&"") | C3: =IF($V3="","",INDEX('Per Line'!$A$2:$A$1501,$V3)) | D3: =IF($V3="","",INDEX('Per Line'!$Z$2:$Z$1501,$V3)&"") | E3: =IF($V3="","",INDEX('Per Line'!$F$2:$F$1501,$V3)) | F3: =IF($V3="","",INDEX('Per Line'!$I$2:$I$1501,$V3)&"") | G3: =IF($V3="","",INDEX('Per Line'!$J$2:$J$1501,$V3)&"") | H3: =IF($V3="","",INDEX('Per Line'!$K$2:$K$1501,$V3)&"") | I3: =IF($V3="","",INDEX('Per Line'!$M$2:$M$1501,$V3)) | J3: =IF($V3="","",I3*T3/100) | K3: =IF($V3="","",SUMIFS('Per Line'!$V$2:$V$1501,'Per Line'!$D$2:$D$1501,$B3,'Per Line'!$AN$2:$AN$1501,1)) | L3: =IF($V3="","",Settings!$C$7) | M3: =IF($V3="","",SUMIFS('Per Line'!$V$2:$V$1501,'Per Line'!$D$2:$D$1501,$B3,'Per Line'!$AM$2:$AM$1501,0,'Per Line'!$AN$2:$AN$1501,0)) | N3: =IF($V3="","",M3*L3) | O3: =IF($V3="","",Settings!$C$6) | P3: =IF($V3="","",SUMIFS('Per Line'!$V$2:$V$1501,'Per Line'!$D$2:$D$1501,$B3,'Per Line'!$AM$2:$AM$1501,1,'Per Line'!$AN$2:$AN$1501,0)) | Q3: =IF($V3="","",P3*O3) | R3: =IF($V3="","",Q3+N3) | S3: =IF($V3="","",T3-R3) | T3: =IF($V3="","",M3+P3+K3) | U3: =IF($V3="","",T3-R3-J3) | V3: =IF(ROWS($V$2:$V3)<=MAX('Per Line'!$AL$2:$AL$1501),MATCH(ROWS($V$2:$V3),'Per Line'!$AL$2:$AL$1501,0),"")
B4: =IF($V4="","",INDEX('Per Line'!$D$2:$D$1501,$V4)&"") | C4: =IF($V4="","",INDEX('Per Line'!$A$2:$A$1501,$V4)) | D4: =IF($V4="","",INDEX('Per Line'!$Z$2:$Z$1501,$V4)&"") | E4: =IF($V4="","",INDEX('Per Line'!$F$2:$F$1501,$V4)) | F4: =IF($V4="","",INDEX('Per Line'!$I$2:$I$1501,$V4)&"") | G4: =IF($V4="","",INDEX('Per Line'!$J$2:$J$1501,$V4)&"") | H4: =IF($V4="","",INDEX('Per Line'!$K$2:$K$1501,$V4)&"") | I4: =IF($V4="","",INDEX('Per Line'!$M$2:$M$1501,$V4)) | J4: =IF($V4="","",I4*T4/100) | K4: =IF($V4="","",SUMIFS('Per Line'!$V$2:$V$1501,'Per Line'!$D$2:$D$1501,$B4,'Per Line'!$AN$2:$AN$1501,1)) | L4: =IF($V4="","",Settings!$C$7) | M4: =IF($V4="","",SUMIFS('Per Line'!$V$2:$V$1501,'Per Line'!$D$2:$D$1501,$B4,'Per Line'!$AM$2:$AM$1501,0,'Per Line'!$AN$2:$AN$1501,0)) | N4: =IF($V4="","",M4*L4) | O4: =IF($V4="","",Settings!$C$6) | P4: =IF($V4="","",SUMIFS('Per Line'!$V$2:$V$1501,'Per Line'!$D$2:$D$1501,$B4,'Per Line'!$AM$2:$AM$1501,1,'Per Line'!$AN$2:$AN$1501,0)) | Q4: =IF($V4="","",P4*O4) | R4: =IF($V4="","",Q4+N4) | S4: =IF($V4="","",T4-R4) | T4: =IF($V4="","",M4+P4+K4) | U4: =IF($V4="","",T4-R4-J4) | V4: =IF(ROWS($V$2:$V4)<=MAX('Per Line'!$AL$2:$AL$1501),MATCH(ROWS($V$2:$V4),'Per Line'!$AL$2:$AL$1501,0),"")
B5: =IF($V5="","",INDEX('Per Line'!$D$2:$D$1501,$V5)&"") | C5: =IF($V5="","",INDEX('Per Line'!$A$2:$A$1501,$V5)) | D5: =IF($V5="","",INDEX('Per Line'!$Z$2:$Z$1501,$V5)&"") | E5: =IF($V5="","",INDEX('Per Line'!$F$2:$F$1501,$V5)) | F5: =IF($V5="","",INDEX('Per Line'!$I$2:$I$1501,$V5)&"") | G5: =IF($V5="","",INDEX('Per Line'!$J$2:$J$1501,$V5)&"") | H5: =IF($V5="","",INDEX('Per Line'!$K$2:$K$1501,$V5)&"") | I5: =IF($V5="","",INDEX('Per Line'!$M$2:$M$1501,$V5)) | J5: =IF($V5="","",I5*T5/100) | K5: =IF($V5="","",SUMIFS('Per Line'!$V$2:$V$1501,'Per Line'!$D$2:$D$1501,$B5,'Per Line'!$AN$2:$AN$1501,1)) | L5: =IF($V5="","",Settings!$C$7) | M5: =IF($V5="","",SUMIFS('Per Line'!$V$2:$V$1501,'Per Line'!$D$2:$D$1501,$B5,'Per Line'!$AM$2:$AM$1501,0,'Per Line'!$AN$2:$AN$1501,0)) | N5: =IF($V5="","",M5*L5) | O5: =IF($V5="","",Settings!$C$6) | P5: =IF($V5="","",SUMIFS('Per Line'!$V$2:$V$1501,'Per Line'!$D$2:$D$1501,$B5,'Per Line'!$AM$2:$AM$1501,1,'Per Line'!$AN$2:$AN$1501,0)) | Q5: =IF($V5="","",P5*O5) | R5: =IF($V5="","",Q5+N5) | S5: =IF($V5="","",T5-R5) | T5: =IF($V5="","",M5+P5+K5) | U5: =IF($V5="","",T5-R5-J5) | V5: =IF(ROWS($V$2:$V5)<=MAX('Per Line'!$AL$2:$AL$1501),MATCH(ROWS($V$2:$V5),'Per Line'!$AL$2:$AL$1501,0),"")
B6: =IF($V6="","",INDEX('Per Line'!$D$2:$D$1501,$V6)&"") | C6: =IF($V6="","",INDEX('Per Line'!$A$2:$A$1501,$V6)) | D6: =IF($V6="","",INDEX('Per Line'!$Z$2:$Z$1501,$V6)&"") | E6: =IF($V6="","",INDEX('Per Line'!$F$2:$F$1501,$V6)) | F6: =IF($V6="","",INDEX('Per Line'!$I$2:$I$1501,$V6)&"") | G6: =IF($V6="","",INDEX('Per Line'!$J$2:$J$1501,$V6)&"") | H6: =IF($V6="","",INDEX('Per Line'!$K$2:$K$1501,$V6)&"") | I6: =IF($V6="","",INDEX('Per Line'!$M$2:$M$1501,$V6)) | J6: =IF($V6="","",I6*T6/100) | K6: =IF($V6="","",SUMIFS('Per Line'!$V$2:$V$1501,'Per Line'!$D$2:$D$1501,$B6,'Per Line'!$AN$2:$AN$1501,1)) | L6: =IF($V6="","",Settings!$C$7) | M6: =IF($V6="","",SUMIFS('Per Line'!$V$2:$V$1501,'Per Line'!$D$2:$D$1501,$B6,'Per Line'!$AM$2:$AM$1501,0,'Per Line'!$AN$2:$AN$1501,0)) | N6: =IF($V6="","",M6*L6) | O6: =IF($V6="","",Settings!$C$6) | P6: =IF($V6="","",SUMIFS('Per Line'!$V$2:$V$1501,'Per Line'!$D$2:$D$1501,$B6,'Per Line'!$AM$2:$AM$1501,1,'Per Line'!$AN$2:$AN$1501,0)) | Q6: =IF($V6="","",P6*O6) | R6: =IF($V6="","",Q6+N6) | S6: =IF($V6="","",T6-R6) | T6: =IF($V6="","",M6+P6+K6) | U6: =IF($V6="","",T6-R6-J6) | V6: =IF(ROWS($V$2:$V6)<=MAX('Per Line'!$AL$2:$AL$1501),MATCH(ROWS($V$2:$V6),'Per Line'!$AL$2:$AL$1501,0),"")
B7: =IF($V7="","",INDEX('Per Line'!$D$2:$D$1501,$V7)&"") | C7: =IF($V7="","",INDEX('Per Line'!$A$2:$A$1501,$V7)) | D7: =IF($V7="","",INDEX('Per Line'!$Z$2:$Z$1501,$V7)&"") | E7: =IF($V7="","",INDEX('Per Line'!$F$2:$F$1501,$V7)) | F7: =IF($V7="","",INDEX('Per Line'!$I$2:$I$1501,$V7)&"") | G7: =IF($V7="","",INDEX('Per Line'!$J$2:$J$1501,$V7)&"") | H7: =IF($V7="","",INDEX('Per Line'!$K$2:$K$1501,$V7)&"") | I7: =IF($V7="","",INDEX('Per Line'!$M$2:$M$1501,$V7)) | J7: =IF($V7="","",I7*T7/100) | K7: =IF($V7="","",SUMIFS('Per Line'!$V$2:$V$1501,'Per Line'!$D$2:$D$1501,$B7,'Per Line'!$AN$2:$AN$1501,1)) | L7: =IF($V7="","",Settings!$C$7) | M7: =IF($V7="","",SUMIFS('Per Line'!$V$2:$V$1501,'Per Line'!$D$2:$D$1501,$B7,'Per Line'!$AM$2:$AM$1501,0,'Per Line'!$AN$2:$AN$1501,0)) | N7: =IF($V7="","",M7*L7) | O7: =IF($V7="","",Settings!$C$6) | P7: =IF($V7="","",SUMIFS('Per Line'!$V$2:$V$1501,'Per Line'!$D$2:$D$1501,$B7,'Per Line'!$AM$2:$AM$1501,1,'Per Line'!$AN$2:$AN$1501,0)) | Q7: =IF($V7="","",P7*O7) | R7: =IF($V7="","",Q7+N7) | S7: =IF($V7="","",T7-R7) | T7: =IF($V7="","",M7+P7+K7) | U7: =IF($V7="","",T7-R7-J7) | V7: =IF(ROWS($V$2:$V7)<=MAX('Per Line'!$AL$2:$AL$1501),MATCH(ROWS($V$2:$V7),'Per Line'!$AL$2:$AL$1501,0),"")
B8: =IF($V8="","",INDEX('Per Line'!$D$2:$D$1501,$V8)&"") | C8: =IF($V8="","",INDEX('Per Line'!$A$2:$A$1501,$V8)) | D8: =IF($V8="","",INDEX('Per Line'!$Z$2:$Z$1501,$V8)&"") | E8: =IF($V8="","",INDEX('Per Line'!$F$2:$F$1501,$V8)) | F8: =IF($V8="","",INDEX('Per Line'!$I$2:$I$1501,$V8)&"") | G8: =IF($V8="","",INDEX('Per Line'!$J$2:$J$1501,$V8)&"") | H8: =IF($V8="","",INDEX('Per Line'!$K$2:$K$1501,$V8)&"") | I8: =IF($V8="","",INDEX('Per Line'!$M$2:$M$1501,$V8)) | J8: =IF($V8="","",I8*T8/100) | K8: =IF($V8="","",SUMIFS('Per Line'!$V$2:$V$1501,'Per Line'!$D$2:$D$1501,$B8,'Per Line'!$AN$2:$AN$1501,1)) | L8: =IF($V8="","",Settings!$C$7) | M8: =IF($V8="","",SUMIFS('Per Line'!$V$2:$V$1501,'Per Line'!$D$2:$D$1501,$B8,'Per Line'!$AM$2:$AM$1501,0,'Per Line'!$AN$2:$AN$1501,0)) | N8: =IF($V8="","",M8*L8) | O8: =IF($V8="","",Settings!$C$6) | P8: =IF($V8="","",SUMIFS('Per Line'!$V$2:$V$1501,'Per Line'!$D$2:$D$1501,$B8,'Per Line'!$AM$2:$AM$1501,1,'Per Line'!$AN$2:$AN$1501,0)) | Q8: =IF($V8="","",P8*O8) | R8: =IF($V8="","",Q8+N8) | S8: =IF($V8="","",T8-R8) | T8: =IF($V8="","",M8+P8+K8) | U8: =IF($V8="","",T8-R8-J8) | V8: =IF(ROWS($V$2:$V8)<=MAX('Per Line'!$AL$2:$AL$1501),MATCH(ROWS($V$2:$V8),'Per Line'!$AL$2:$AL$1501,0),"")
B9: =IF($V9="","",INDEX('Per Line'!$D$2:$D$1501,$V9)&"") | C9: =IF($V9="","",INDEX('Per Line'!$A$2:$A$1501,$V9)) | D9: =IF($V9="","",INDEX('Per Line'!$Z$2:$Z$1501,$V9)&"") | E9: =IF($V9="","",INDEX('Per Line'!$F$2:$F$1501,$V9)) | F9: =IF($V9="","",INDEX('Per Line'!$I$2:$I$1501,$V9)&"") | G9: =IF($V9="","",INDEX('Per Line'!$J$2:$J$1501,$V9)&"") | H9: =IF($V9="","",INDEX('Per Line'!$K$2:$K$1501,$V9)&"") | I9: =IF($V9="","",INDEX('Per Line'!$M$2:$M$1501,$V9)) | J9: =IF($V9="","",I9*T9/100) | K9: =IF($V9="","",SUMIFS('Per Line'!$V$2:$V$1501,'Per Line'!$D$2:$D$1501,$B9,'Per Line'!$AN$2:$AN$1501,1)) | L9: =IF($V9="","",Settings!$C$7) | M9: =IF($V9="","",SUMIFS('Per Line'!$V$2:$V$1501,'Per Line'!$D$2:$D$1501,$B9,'Per Line'!$AM$2:$AM$1501,0,'Per Line'!$AN$2:$AN$1501,0)) | N9: =IF($V9="","",M9*L9) | O9: =IF($V9="","",Settings!$C$6) | P9: =IF($V9="","",SUMIFS('Per Line'!$V$2:$V$1501,'Per Line'!$D$2:$D$1501,$B9,'Per Line'!$AM$2:$AM$1501,1,'Per Line'!$AN$2:$AN$1501,0)) | Q9: =IF($V9="","",P9*O9) | R9: =IF($V9="","",Q9+N9) | S9: =IF($V9="","",T9-R9) | T9: =IF($V9="","",M9+P9+K9) | U9: =IF($V9="","",T9-R9-J9) | V9: =IF(ROWS($V$2:$V9)<=MAX('Per Line'!$AL$2:$AL$1501),MATCH(ROWS($V$2:$V9),'Per Line'!$AL$2:$AL$1501,0),"")
B10: =IF($V10="","",INDEX('Per Line'!$D$2:$D$1501,$V10)&"") | C10: =IF($V10="","",INDEX('Per Line'!$A$2:$A$1501,$V10)) | D10: =IF($V10="","",INDEX('Per Line'!$Z$2:$Z$1501,$V10)&"") | E10: =IF($V10="","",INDEX('Per Line'!$F$2:$F$1501,$V10)) | F10: =IF($V10="","",INDEX('Per Line'!$I$2:$I$1501,$V10)&"") | G10: =IF($V10="","",INDEX('Per Line'!$J$2:$J$1501,$V10)&"") | H10: =IF($V10="","",INDEX('Per Line'!$K$2:$K$1501,$V10)&"") | I10: =IF($V10="","",INDEX('Per Line'!$M$2:$M$1501,$V10)) | J10: =IF($V10="","",I10*T10/100) | K10: =IF($V10="","",SUMIFS('Per Line'!$V$2:$V$1501,'Per Line'!$D$2:$D$1501,$B10,'Per Line'!$AN$2:$AN$1501,1)) | L10: =IF($V10="","",Settings!$C$7) | M10: =IF($V10="","",SUMIFS('Per Line'!$V$2:$V$1501,'Per Line'!$D$2:$D$1501,$B10,'Per Line'!$AM$2:$AM$1501,0,'Per Line'!$AN$2:$AN$1501,0)) | N10: =IF($V10="","",M10*L10) | O10: =IF($V10="","",Settings!$C$6) | P10: =IF($V10="","",SUMIFS('Per Line'!$V$2:$V$1501,'Per Line'!$D$2:$D$1501,$B10,'Per Line'!$AM$2:$AM$1501,1,'Per Line'!$AN$2:$AN$1501,0)) | Q10: =IF($V10="","",P10*O10) | R10: =IF($V10="","",Q10+N10) | S10: =IF($V10="","",T10-R10) | T10: =IF($V10="","",M10+P10+K10) | U10: =IF($V10="","",T10-R10-J10) | V10: =IF(ROWS($V$2:$V10)<=MAX('Per Line'!$AL$2:$AL$1501),MATCH(ROWS($V$2:$V10),'Per Line'!$AL$2:$AL$1501,0),"")
B11: =IF($V11="","",INDEX('Per Line'!$D$2:$D$1501,$V11)&"") | C11: =IF($V11="","",INDEX('Per Line'!$A$2:$A$1501,$V11)) | D11: =IF($V11="","",INDEX('Per Line'!$Z$2:$Z$1501,$V11)&"") | E11: =IF($V11="","",INDEX('Per Line'!$F$2:$F$1501,$V11)) | F11: =IF($V11="","",INDEX('Per Line'!$I$2:$I$1501,$V11)&"") | G11: =IF($V11="","",INDEX('Per Line'!$J$2:$J$1501,$V11)&"") | H11: =IF($V11="","",INDEX('Per Line'!$K$2:$K$1501,$V11)&"") | I11: =IF($V11="","",INDEX('Per Line'!$M$2:$M$1501,$V11)) | J11: =IF($V11="","",I11*T11/100) | K11: =IF($V11="","",SUMIFS('Per Line'!$V$2:$V$1501,'Per Line'!$D$2:$D$1501,$B11,'Per Line'!$AN$2:$AN$1501,1)) | L11: =IF($V11="","",Settings!$C$7) | M11: =IF($V11="","",SUMIFS('Per Line'!$V$2:$V$1501,'Per Line'!$D$2:$D$1501,$B11,'Per Line'!$AM$2:$AM$1501,0,'Per Line'!$AN$2:$AN$1501,0)) | N11: =IF($V11="","",M11*L11) | O11: =IF($V11="","",Settings!$C$6) | P11: =IF($V11="","",SUMIFS('Per Line'!$V$2:$V$1501,'Per Line'!$D$2:$D$1501,$B11,'Per Line'!$AM$2:$AM$1501,1,'Per Line'!$AN$2:$AN$1501,0)) | Q11: =IF($V11="","",P11*O11) | R11: =IF($V11="","",Q11+N11) | S11: =IF($V11="","",T11-R11) | T11: =IF($V11="","",M11+P11+K11) | U11: =IF($V11="","",T11-R11-J11) | V11: =IF(ROWS($V$2:$V11)<=MAX('Per Line'!$AL$2:$AL$1501),MATCH(ROWS($V$2:$V11),'Per Line'!$AL$2:$AL$1501,0),"")
B12: =IF($V12="","",INDEX('Per Line'!$D$2:$D$1501,$V12)&"") | C12: =IF($V12="","",INDEX('Per Line'!$A$2:$A$1501,$V12)) | D12: =IF($V12="","",INDEX('Per Line'!$Z$2:$Z$1501,$V12)&"") | E12: =IF($V12="","",INDEX('Per Line'!$F$2:$F$1501,$V12)) | F12: =IF($V12="","",INDEX('Per Line'!$I$2:$I$1501,$V12)&"") | G12: =IF($V12="","",INDEX('Per Line'!$J$2:$J$1501,$V12)&"") | H12: =IF($V12="","",INDEX('Per Line'!$K$2:$K$1501,$V12)&"") | I12: =IF($V12="","",INDEX('Per Line'!$M$2:$M$1501,$V12)) | J12: =IF($V12="","",I12*T12/100) | K12: =IF($V12="","",SUMIFS('Per Line'!$V$2:$V$1501,'Per Line'!$D$2:$D$1501,$B12,'Per Line'!$AN$2:$AN$1501,1)) | L12: =IF($V12="","",Settings!$C$7) | M12: =IF($V12="","",SUMIFS('Per Line'!$V$2:$V$1501,'Per Line'!$D$2:$D$1501,$B12,'Per Line'!$AM$2:$AM$1501,0,'Per Line'!$AN$2:$AN$1501,0)) | N12: =IF($V12="","",M12*L12) | O12: =IF($V12="","",Settings!$C$6) | P12: =IF($V12="","",SUMIFS('Per Line'!$V$2:$V$1501,'Per Line'!$D$2:$D$1501,$B12,'Per Line'!$AM$2:$AM$1501,1,'Per Line'!$AN$2:$AN$1501,0)) | Q12: =IF($V12="","",P12*O12) | R12: =IF($V12="","",Q12+N12) | S12: =IF($V12="","",T12-R12) | T12: =IF($V12="","",M12+P12+K12) | U12: =IF($V12="","",T12-R12-J12) | V12: =IF(ROWS($V$2:$V12)<=MAX('Per Line'!$AL$2:$AL$1501),MATCH(ROWS($V$2:$V12),'Per Line'!$AL$2:$AL$1501,0),"")
B13: =IF($V13="","",INDEX('Per Line'!$D$2:$D$1501,$V13)&"") | C13: =IF($V13="","",INDEX('Per Line'!$A$2:$A$1501,$V13)) | D13: =IF($V13="","",INDEX('Per Line'!$Z$2:$Z$1501,$V13)&"") | E13: =IF($V13="","",INDEX('Per Line'!$F$2:$F$1501,$V13)) | F13: =IF($V13="","",INDEX('Per Line'!$I$2:$I$1501,$V13)&"") | G13: =IF($V13="","",INDEX('Per Line'!$J$2:$J$1501,$V13)&"") | H13: =IF($V13="","",INDEX('Per Line'!$K$2:$K$1501,$V13)&"") | I13: =IF($V13="","",INDEX('Per Line'!$M$2:$M$1501,$V13)) | J13: =IF($V13="","",I13*T13/100) | K13: =IF($V13="","",SUMIFS('Per Line'!$V$2:$V$1501,'Per Line'!$D$2:$D$1501,$B13,'Per Line'!$AN$2:$AN$1501,1)) | L13: =IF($V13="","",Settings!$C$7) | M13: =IF($V13="","",SUMIFS('Per Line'!$V$2:$V$1501,'Per Line'!$D$2:$D$1501,$B13,'Per Line'!$AM$2:$AM$1501,0,'Per Line'!$AN$2:$AN$1501,0)) | N13: =IF($V13="","",M13*L13) | O13: =IF($V13="","",Settings!$C$6) | P13: =IF($V13="","",SUMIFS('Per Line'!$V$2:$V$1501,'Per Line'!$D$2:$D$1501,$B13,'Per Line'!$AM$2:$AM$1501,1,'Per Line'!$AN$2:$AN$1501,0)) | Q13: =IF($V13="","",P13*O13) | R13: =IF($V13="","",Q13+N13) | S13: =IF($V13="","",T13-R13) | T13: =IF($V13="","",M13+P13+K13) | U13: =IF($V13="","",T13-R13-J13) | V13: =IF(ROWS($V$2:$V13)<=MAX('Per Line'!$AL$2:$AL$1501),MATCH(ROWS($V$2:$V13),'Per Line'!$AL$2:$AL$1501,0),"")
... B501: =IF($V501="","",INDEX('Per Line'!$D$2:$D$1501,$V501)&"") | C501: =IF($V501="","",INDEX('Per Line'!$A$2:$A$1501,$V501)) | D501: =IF($V501="","",INDEX('Per Line'!$Z$2:$Z$1501,$V501)&"") | E501: =IF($V501="","",INDEX('Per Line'!$F$2:$F$1501,$V501)) | F501: =IF($V501="","",INDEX('Per Line'!$I$2:$I$1501,$V501)&"") | G501: =IF($V501="","",INDEX('Per Line'!$J$2:$J$1501,$V501)&"") | H501: =IF($V501="","",INDEX('Per Line'!$K$2:$K$1501,$V501)&"") | I501: =IF($V501="","",INDEX('Per Line'!$M$2:$M$1501,$V501)) | J501: =IF($V501="","",I501*T501/100) | K501: =IF($V501="","",SUMIFS('Per Line'!$V$2:$V$1501,'Per Line'!$D$2:$D$1501,$B501,'Per Line'!$AN$2:$AN$1501,1)) | L501: =IF($V501="","",Settings!$C$7) | M501: =IF($V501="","",SUMIFS('Per Line'!$V$2:$V$1501,'Per Line'!$D$2:$D$1501,$B501,'Per Line'!$AM$2:$AM$1501,0,'Per Line'!$AN$2:$AN$1501,0)) | N501: =IF($V501="","",M501*L501) | O501: =IF($V501="","",Settings!$C$6) | P501: =IF($V501="","",SUMIFS('Per Line'!$V$2:$V$1501,'Per Line'!$D$2:$D$1501,$B501,'Per Line'!$AM$2:$AM$1501,1,'Per Line'!$AN$2:$AN$1501,0)) | Q501: =IF($V501="","",P501*O501) | R501: =IF($V501="","",Q501+N501) | S501: =IF($V501="","",T501-R501) | T501: =IF($V501="","",M501+P501+K501) | U501: =IF($V501="","",T501-R501-J501) | V501: =IF(ROWS($V$2:$V501)<=MAX('Per Line'!$AL$2:$AL$1501),MATCH(ROWS($V$2:$V501),'Per Line'!$AL$2:$AL$1501,0),"")

Sheet templet
A1: م | B1: التاريخ | C1: كود الموظف | D1: الاسم | E1: الفرع | F1: محلي | G1: خصم محلي | H1: مستورد | I1: خصم مستورد | J1: بدون خصم | K1: اجمالي الفاتورة | L1: الاجمالي بعد الخصم | M1: ضريبة | N1: القيمه بعد الخصم | O1: القسم | P1: خصم 20% | Q1: بعد خصم 20%
A2: Total | F2: =SUM(F3:F502) | G2: =SUM(G3:G502) | H2: =SUM(H3:H502) | I2: =SUM(I3:I502) | J2: =SUM(J3:J502) | K2: =SUM(K3:K502) | L2: =SUM(L3:L502)
A3: =IF('Per Invoice'!$V2="","",ROWS($A$3:A3)) | B3: =IF('Per Invoice'!$V2="","",'Per Invoice'!E2) | C3: =IF('Per Invoice'!$V2="","",'Per Invoice'!G2) | D3: =IF('Per Invoice'!$V2="","",'Per Invoice'!H2) | E3: =IF('Per Invoice'!$V2="","",'Per Invoice'!F2) | F3: =IF('Per Invoice'!$V2="","",'Per Invoice'!P2) | G3: =IF('Per Invoice'!$V2="","",'Per Invoice'!Q2) | H3: =IF('Per Invoice'!$V2="","",'Per Invoice'!M2) | I3: =IF('Per Invoice'!$V2="","",'Per Invoice'!N2) | J3: =IF('Per Invoice'!$V2="","",'Per Invoice'!K2) | K3: =IF('Per Invoice'!$V2="","",'Per Invoice'!T2) | L3: =IF('Per Invoice'!$V2="","",'Per Invoice'!S2)
A4: =IF('Per Invoice'!$V3="","",ROWS($A$3:A4)) | B4: =IF('Per Invoice'!$V3="","",'Per Invoice'!E3) | C4: =IF('Per Invoice'!$V3="","",'Per Invoice'!G3) | D4: =IF('Per Invoice'!$V3="","",'Per Invoice'!H3) | E4: =IF('Per Invoice'!$V3="","",'Per Invoice'!F3) | F4: =IF('Per Invoice'!$V3="","",'Per Invoice'!P3) | G4: =IF('Per Invoice'!$V3="","",'Per Invoice'!Q3) | H4: =IF('Per Invoice'!$V3="","",'Per Invoice'!M3) | I4: =IF('Per Invoice'!$V3="","",'Per Invoice'!N3) | J4: =IF('Per Invoice'!$V3="","",'Per Invoice'!K3) | K4: =IF('Per Invoice'!$V3="","",'Per Invoice'!T3) | L4: =IF('Per Invoice'!$V3="","",'Per Invoice'!S3)
A5: =IF('Per Invoice'!$V4="","",ROWS($A$3:A5)) | B5: =IF('Per Invoice'!$V4="","",'Per Invoice'!E4) | C5: =IF('Per Invoice'!$V4="","",'Per Invoice'!G4) | D5: =IF('Per Invoice'!$V4="","",'Per Invoice'!H4) | E5: =IF('Per Invoice'!$V4="","",'Per Invoice'!F4) | F5: =IF('Per Invoice'!$V4="","",'Per Invoice'!P4) | G5: =IF('Per Invoice'!$V4="","",'Per Invoice'!Q4) | H5: =IF('Per Invoice'!$V4="","",'Per Invoice'!M4) | I5: =IF('Per Invoice'!$V4="","",'Per Invoice'!N4) | J5: =IF('Per Invoice'!$V4="","",'Per Invoice'!K4) | K5: =IF('Per Invoice'!$V4="","",'Per Invoice'!T4) | L5: =IF('Per Invoice'!$V4="","",'Per Invoice'!S4)
A6: =IF('Per Invoice'!$V5="","",ROWS($A$3:A6)) | B6: =IF('Per Invoice'!$V5="","",'Per Invoice'!E5) | C6: =IF('Per Invoice'!$V5="","",'Per Invoice'!G5) | D6: =IF('Per Invoice'!$V5="","",'Per Invoice'!H5) | E6: =IF('Per Invoice'!$V5="","",'Per Invoice'!F5) | F6: =IF('Per Invoice'!$V5="","",'Per Invoice'!P5) | G6: =IF('Per Invoice'!$V5="","",'Per Invoice'!Q5) | H6: =IF('Per Invoice'!$V5="","",'Per Invoice'!M5) | I6: =IF('Per Invoice'!$V5="","",'Per Invoice'!N5) | J6: =IF('Per Invoice'!$V5="","",'Per Invoice'!K5) | K6: =IF('Per Invoice'!$V5="","",'Per Invoice'!T5) | L6: =IF('Per Invoice'!$V5="","",'Per Invoice'!S5)
A7: =IF('Per Invoice'!$V6="","",ROWS($A$3:A7)) | B7: =IF('Per Invoice'!$V6="","",'Per Invoice'!E6) | C7: =IF('Per Invoice'!$V6="","",'Per Invoice'!G6) | D7: =IF('Per Invoice'!$V6="","",'Per Invoice'!H6) | E7: =IF('Per Invoice'!$V6="","",'Per Invoice'!F6) | F7: =IF('Per Invoice'!$V6="","",'Per Invoice'!P6) | G7: =IF('Per Invoice'!$V6="","",'Per Invoice'!Q6) | H7: =IF('Per Invoice'!$V6="","",'Per Invoice'!M6) | I7: =IF('Per Invoice'!$V6="","",'Per Invoice'!N6) | J7: =IF('Per Invoice'!$V6="","",'Per Invoice'!K6) | K7: =IF('Per Invoice'!$V6="","",'Per Invoice'!T6) | L7: =IF('Per Invoice'!$V6="","",'Per Invoice'!S6)
A8: =IF('Per Invoice'!$V7="","",ROWS($A$3:A8)) | B8: =IF('Per Invoice'!$V7="","",'Per Invoice'!E7) | C8: =IF('Per Invoice'!$V7="","",'Per Invoice'!G7) | D8: =IF('Per Invoice'!$V7="","",'Per Invoice'!H7) | E8: =IF('Per Invoice'!$V7="","",'Per Invoice'!F7) | F8: =IF('Per Invoice'!$V7="","",'Per Invoice'!P7) | G8: =IF('Per Invoice'!$V7="","",'Per Invoice'!Q7) | H8: =IF('Per Invoice'!$V7="","",'Per Invoice'!M7) | I8: =IF('Per Invoice'!$V7="","",'Per Invoice'!N7) | J8: =IF('Per Invoice'!$V7="","",'Per Invoice'!K7) | K8: =IF('Per Invoice'!$V7="","",'Per Invoice'!T7) | L8: =IF('Per Invoice'!$V7="","",'Per Invoice'!S7)
A9: =IF('Per Invoice'!$V8="","",ROWS($A$3:A9)) | B9: =IF('Per Invoice'!$V8="","",'Per Invoice'!E8) | C9: =IF('Per Invoice'!$V8="","",'Per Invoice'!G8) | D9: =IF('Per Invoice'!$V8="","",'Per Invoice'!H8) | E9: =IF('Per Invoice'!$V8="","",'Per Invoice'!F8) | F9: =IF('Per Invoice'!$V8="","",'Per Invoice'!P8) | G9: =IF('Per Invoice'!$V8="","",'Per Invoice'!Q8) | H9: =IF('Per Invoice'!$V8="","",'Per Invoice'!M8) | I9: =IF('Per Invoice'!$V8="","",'Per Invoice'!N8) | J9: =IF('Per Invoice'!$V8="","",'Per Invoice'!K8) | K9: =IF('Per Invoice'!$V8="","",'Per Invoice'!T8) | L9: =IF('Per Invoice'!$V8="","",'Per Invoice'!S8)
A10: =IF('Per Invoice'!$V9="","",ROWS($A$3:A10)) | B10: =IF('Per Invoice'!$V9="","",'Per Invoice'!E9) | C10: =IF('Per Invoice'!$V9="","",'Per Invoice'!G9) | D10: =IF('Per Invoice'!$V9="","",'Per Invoice'!H9) | E10: =IF('Per Invoice'!$V9="","",'Per Invoice'!F9) | F10: =IF('Per Invoice'!$V9="","",'Per Invoice'!P9) | G10: =IF('Per Invoice'!$V9="","",'Per Invoice'!Q9) | H10: =IF('Per Invoice'!$V9="","",'Per Invoice'!M9) | I10: =IF('Per Invoice'!$V9="","",'Per Invoice'!N9) | J10: =IF('Per Invoice'!$V9="","",'Per Invoice'!K9) | K10: =IF('Per Invoice'!$V9="","",'Per Invoice'!T9) | L10: =IF('Per Invoice'!$V9="","",'Per Invoice'!S9)
A11: =IF('Per Invoice'!$V10="","",ROWS($A$3:A11)) | B11: =IF('Per Invoice'!$V10="","",'Per Invoice'!E10) | C11: =IF('Per Invoice'!$V10="","",'Per Invoice'!G10) | D11: =IF('Per Invoice'!$V10="","",'Per Invoice'!H10) | E11: =IF('Per Invoice'!$V10="","",'Per Invoice'!F10) | F11: =IF('Per Invoice'!$V10="","",'Per Invoice'!P10) | G11: =IF('Per Invoice'!$V10="","",'Per Invoice'!Q10) | H11: =IF('Per Invoice'!$V10="","",'Per Invoice'!M10) | I11: =IF('Per Invoice'!$V10="","",'Per Invoice'!N10) | J11: =IF('Per Invoice'!$V10="","",'Per Invoice'!K10) | K11: =IF('Per Invoice'!$V10="","",'Per Invoice'!T10) | L11: =IF('Per Invoice'!$V10="","",'Per Invoice'!S10)
A12: =IF('Per Invoice'!$V11="","",ROWS($A$3:A12)) | B12: =IF('Per Invoice'!$V11="","",'Per Invoice'!E11) | C12: =IF('Per Invoice'!$V11="","",'Per Invoice'!G11) | D12: =IF('Per Invoice'!$V11="","",'Per Invoice'!H11) | E12: =IF('Per Invoice'!$V11="","",'Per Invoice'!F11) | F12: =IF('Per Invoice'!$V11="","",'Per Invoice'!P11) | G12: =IF('Per Invoice'!$V11="","",'Per Invoice'!Q11) | H12: =IF('Per Invoice'!$V11="","",'Per Invoice'!M11) | I12: =IF('Per Invoice'!$V11="","",'Per Invoice'!N11) | J12: =IF('Per Invoice'!$V11="","",'Per Invoice'!K11) | K12: =IF('Per Invoice'!$V11="","",'Per Invoice'!T11) | L12: =IF('Per Invoice'!$V11="","",'Per Invoice'!S11)
A13: =IF('Per Invoice'!$V12="","",ROWS($A$3:A13)) | B13: =IF('Per Invoice'!$V12="","",'Per Invoice'!E12) | C13: =IF('Per Invoice'!$V12="","",'Per Invoice'!G12) | D13: =IF('Per Invoice'!$V12="","",'Per Invoice'!H12) | E13: =IF('Per Invoice'!$V12="","",'Per Invoice'!F12) | F13: =IF('Per Invoice'!$V12="","",'Per Invoice'!P12) | G13: =IF('Per Invoice'!$V12="","",'Per Invoice'!Q12) | H13: =IF('Per Invoice'!$V12="","",'Per Invoice'!M12) | I13: =IF('Per Invoice'!$V12="","",'Per Invoice'!N12) | J13: =IF('Per Invoice'!$V12="","",'Per Invoice'!K12) | K13: =IF('Per Invoice'!$V12="","",'Per Invoice'!T12) | L13: =IF('Per Invoice'!$V12="","",'Per Invoice'!S12)
A14: =IF('Per Invoice'!$V13="","",ROWS($A$3:A14)) | B14: =IF('Per Invoice'!$V13="","",'Per Invoice'!E13) | C14: =IF('Per Invoice'!$V13="","",'Per Invoice'!G13) | D14: =IF('Per Invoice'!$V13="","",'Per Invoice'!H13) | E14: =IF('Per Invoice'!$V13="","",'Per Invoice'!F13) | F14: =IF('Per Invoice'!$V13="","",'Per Invoice'!P13) | G14: =IF('Per Invoice'!$V13="","",'Per Invoice'!Q13) | H14: =IF('Per Invoice'!$V13="","",'Per Invoice'!M13) | I14: =IF('Per Invoice'!$V13="","",'Per Invoice'!N13) | J14: =IF('Per Invoice'!$V13="","",'Per Invoice'!K13) | K14: =IF('Per Invoice'!$V13="","",'Per Invoice'!T13) | L14: =IF('Per Invoice'!$V13="","",'Per Invoice'!S13)
... A502: =IF('Per Invoice'!$V501="","",ROWS($A$3:A502)) | B502: =IF('Per Invoice'!$V501="","",'Per Invoice'!E501) | C502: =IF('Per Invoice'!$V501="","",'Per Invoice'!G501) | D502: =IF('Per Invoice'!$V501="","",'Per Invoice'!H501) | E502: =IF('Per Invoice'!$V501="","",'Per Invoice'!F501) | F502: =IF('Per Invoice'!$V501="","",'Per Invoice'!P501) | G502: =IF('Per Invoice'!$V501="","",'Per Invoice'!Q501) | H502: =IF('Per Invoice'!$V501="","",'Per Invoice'!M501) | I502: =IF('Per Invoice'!$V501="","",'Per Invoice'!N501) | J502: =IF('Per Invoice'!$V501="","",'Per Invoice'!K501) | K502: =IF('Per Invoice'!$V501="","",'Per Invoice'!T501) | L502: =IF('Per Invoice'!$V501="","",'Per Invoice'!S501)
