Workbook

Sheet How To Use
A1: Claims Template - MEDICARE (Chronic)
A3: Monthly steps
A4: 1. Open the 'Per Line' tab. Delete the old data in the BLUE columns only (row 2 down). Never delete the green or grey columns.
A5: 2. Paste the new month's data as VALUES starting at A2, into the blue columns: A-L, N-T, V-W, Y-AF (same order as the system export).
A6: 3. Green columns (M, U, X, AG, AH, AI) and the grey helper columns (AJ-AN) calculate automatically - do not paste over them.
A7: 4. 'Per Invoice' fills itself from 'Per Line' (one row per Order #, split into IMP / Local). No pivot table, no refresh.
A8: 5. The ONLY manual column in 'Per Invoice' is column A 'Invoice' (blue): type it yourself. Everything else is formula.
A9: 6. Open 'Settings' and check STATUS says OK (Per Line totals = Per Invoice totals).
A11: Colour legend
A12: Blue header = typed/pasted by you (raw data, and 'Invoice' in Per Invoice). Green header = formula (do not paste over). Grey header = helper formula (do not touch). Yellow cell (Settings) = editable rate.
A14: Calculation rules (taken from the September 2026 sheet)
A15: Co val = Order Co Payment x Total / 100. Discount = Total x Rebates / 100. Subtotal = Total - Discount. Net = Subtotal - Co val. (Total = 'Product Total')
... A21: Max Limit rule (as in the old sheet): if an invoice's Grand Total is above its Max Limit, Co val = Co Payment x Max Limit / 100 + (Grand Total - Max Limit). Per Line keeps the plain Co val, so 'Settings' shows the difference as 'Max Limit adjustment'.

Sheet Settings
B1: Company settings & checks
B3: Insurance Company | C3: MEDICARE | D3: Informational only
B4: Corporate | C4: Sanipure; Orascom Construction; الإدارة الطبية لميدي كير; Purex Health Care | D4: Informational only
B5: Sheet type | C5: Chronic | D5: Informational only
B6: Local products rebate % | C6: 0.14 | D6: Source: Sep sheet (Rebates = 14 on Local lines).
B7: Imported (IMP) products rebate % | C7: 0.06 | D7: Source: Sep sheet (Rebates = 6 on non-local lines; 0 on Special Rebates = Yes).
B9: Month totals / reconciliation
B10: Lines loaded | C10: =COUNTA('Per Line'!$C$2:$C$4001)
B11: Invoices (unique Order #) | C11: =MAX('Per Line'!$AK$2:$AK$4001)
B12: Invoices shown in Per Invoice | C12: =SUMPRODUCT(--('Per Invoice'!$B$2:$B$1001<>""))
B13: Grand Total - Per Line (Product Total) | C13: =SUM('Per Line'!$U$2:$U$4001)
B14: Grand Total - Per Invoice | C14: =SUM('Per Invoice'!$Z$2:$Z$1001)
B15: Discount - Per Line | C15: =SUM('Per Line'!$AG$2:$AG$4001)
B16: Discount - Per Invoice | C16: =SUM('Per Invoice'!$X$2:$X$1001)
B17: Co val - Per Line | C17: =SUM('Per Line'!$M$2:$M$4001)
B18: Co val - Per Invoice | C18: =SUM('Per Invoice'!$M$2:$M$1001)
B19: Net - Per Line | C19: =SUM('Per Line'!$AI$2:$AI$4001)
B20: Net - Per Invoice | C20: =SUM('Per Invoice'!$AA$2:$AA$1001)
B21: Max Limit adjustment (Co val, Per Invoice only) | C21: =SUM('Per Invoice'!$AC$2:$AC$1001) | D21: Invoices whose Grand Total is above the Max Limit: Co val = Co% x Max Limit / 100 + (Grand Total - Max Limit). This difference exists only in Per Invoice, as in the old sheet.
B23: STATUS | C23: =IF(C10=0,"No data loaded",IF(COUNTA('Per Line'!$C:$C)-1>4000,"TOO MANY LINES - extend template",IF(C11>1000,"TOO MANY INVOICES - extend template",IF(AND(ROUND(C13-C14,2)=0,ROUND(C15-C16,2)=0,ROUND(C17+C21-C18,2)=0,ROUND(C19-C21-C20,2)=0,C11=C12),"OK","CHECK - Per Line and Per Invoice do not match")))) | D23: Must say OK after you paste the month data.

Sheet Per Line
A1: Ticket # | B1: Stage | C1: Order # | D1: Channel | E1: Create At | F1: Insurance Company | G1: Country Portal ID | H1: Corporate | I1: Card | J1: Name | K1: Status | L1: Order Co Payment | M1: Co val | N1: By Patient | O1: heisenberg id | P1: Product Name | Q1: Local | R1: Unit | S1: Quantity | T1: Unit Price | U1: Product Total | V1: ERX ID | W1: Special Rebates? | X1: Rebates | Y1: Approval Type | Z1: Max Limit | AA1: Exceeding Limit | AB1: Amount collected from customer | AC1: By Patient (Delivered) | AD1: Dispense Number | AE1: Dispense Date | AF1: Has OTP? | AG1: Discount | AH1: Subtotal | AI1: Net | AJ1: Order 1st Row (helper) | AK1: Invoice # (helper) | AL1: Is Local (helper) | AM1: Is Special (helper) | AN1: Sort Key (helper)
M2: =IF($C2="","",L2*U2/100) | U2: =IF($C2="","",S2*T2) | X2: =IF($C2="","",IF($AM2=1,0,IF($AL2=1,Settings!$C$6,Settings!$C$7))*100) | AG2: =IF($C2="","",U2*X2/100) | AH2: =IF($C2="","",U2-AG2) | AI2: =IF($C2="","",AH2-M2) | AJ2: =IF($C2="","",IF(COUNTIF($C$2:$C2,$C2)=1,1,0)) | AK2: =IF($AJ2=1,SUMPRODUCT(--($AN$2:$AN$4001<$AN2))+1,"") | AL2: =IF($C2="","",IF(OR($Q2=TRUE(),$Q2="TRUE"),1,0)) | AM2: =IF($C2="","",IF($W2="Yes",1,0)) | AN2: =IF($AJ2=1,IFERROR(IF(VALUE($C2)<100000000,VALUE($C2),1000000000),IFERROR(IF(VALUE(MID($C2,2,20))<100000000,VALUE(MID($C2,2,20)),1000000000),1000000000))+ROW()/100000,"")
M3: =IF($C3="","",L3*U3/100) | U3: =IF($C3="","",S3*T3) | X3: =IF($C3="","",IF($AM3=1,0,IF($AL3=1,Settings!$C$6,Settings!$C$7))*100) | AG3: =IF($C3="","",U3*X3/100) | AH3: =IF($C3="","",U3-AG3) | AI3: =IF($C3="","",AH3-M3) | AJ3: =IF($C3="","",IF(COUNTIF($C$2:$C3,$C3)=1,1,0)) | AK3: =IF($AJ3=1,SUMPRODUCT(--($AN$2:$AN$4001<$AN3))+1,"") | AL3: =IF($C3="","",IF(OR($Q3=TRUE(),$Q3="TRUE"),1,0)) | AM3: =IF($C3="","",IF($W3="Yes",1,0)) | AN3: =IF($AJ3=1,IFERROR(IF(VALUE($C3)<100000000,VALUE($C3),1000000000),IFERROR(IF(VALUE(MID($C3,2,20))<100000000,VALUE(MID($C3,2,20)),1000000000),1000000000))+ROW()/100000,"")
M4: =IF($C4="","",L4*U4/100) | U4: =IF($C4="","",S4*T4) | X4: =IF($C4="","",IF($AM4=1,0,IF($AL4=1,Settings!$C$6,Settings!$C$7))*100) | AG4: =IF($C4="","",U4*X4/100) | AH4: =IF($C4="","",U4-AG4) | AI4: =IF($C4="","",AH4-M4) | AJ4: =IF($C4="","",IF(COUNTIF($C$2:$C4,$C4)=1,1,0)) | AK4: =IF($AJ4=1,SUMPRODUCT(--($AN$2:$AN$4001<$AN4))+1,"") | AL4: =IF($C4="","",IF(OR($Q4=TRUE(),$Q4="TRUE"),1,0)) | AM4: =IF($C4="","",IF($W4="Yes",1,0)) | AN4: =IF($AJ4=1,IFERROR(IF(VALUE($C4)<100000000,VALUE($C4),1000000000),IFERROR(IF(VALUE(MID($C4,2,20))<100000000,VALUE(MID($C4,2,20)),1000000000),1000000000))+ROW()/100000,"")
M5: =IF($C5="","",L5*U5/100) | U5: =IF($C5="","",S5*T5) | X5: =IF($C5="","",IF($AM5=1,0,IF($AL5=1,Settings!$C$6,Settings!$C$7))*100) | AG5: =IF($C5="","",U5*X5/100) | AH5: =IF($C5="","",U5-AG5) | AI5: =IF($C5="","",AH5-M5) | AJ5: =IF($C5="","",IF(COUNTIF($C$2:$C5,$C5)=1,1,0)) | AK5: =IF($AJ5=1,SUMPRODUCT(--($AN$2:$AN$4001<$AN5))+1,"") | AL5: =IF($C5="","",IF(OR($Q5=TRUE(),$Q5="TRUE"),1,0)) | AM5: =IF($C5="","",IF($W5="Yes",1,0)) | AN5: =IF($AJ5=1,IFERROR(IF(VALUE($C5)<100000000,VALUE($C5),1000000000),IFERROR(IF(VALUE(MID($C5,2,20))<100000000,VALUE(MID($C5,2,20)),1000000000),1000000000))+ROW()/100000,"")
M6: =IF($C6="","",L6*U6/100) | U6: =IF($C6="","",S6*T6) | X6: =IF($C6="","",IF($AM6=1,0,IF($AL6=1,Settings!$C$6,Settings!$C$7))*100) | AG6: =IF($C6="","",U6*X6/100) | AH6: =IF($C6="","",U6-AG6) | AI6: =IF($C6="","",AH6-M6) | AJ6: =IF($C6="","",IF(COUNTIF($C$2:$C6,$C6)=1,1,0)) | AK6: =IF($AJ6=1,SUMPRODUCT(--($AN$2:$AN$4001<$AN6))+1,"") | AL6: =IF($C6="","",IF(OR($Q6=TRUE(),$Q6="TRUE"),1,0)) | AM6: =IF($C6="","",IF($W6="Yes",1,0)) | AN6: =IF($AJ6=1,IFERROR(IF(VALUE($C6)<100000000,VALUE($C6),1000000000),IFERROR(IF(VALUE(MID($C6,2,20))<100000000,VALUE(MID($C6,2,20)),1000000000),1000000000))+ROW()/100000,"")
M7: =IF($C7="","",L7*U7/100) | U7: =IF($C7="","",S7*T7) | X7: =IF($C7="","",IF($AM7=1,0,IF($AL7=1,Settings!$C$6,Settings!$C$7))*100) | AG7: =IF($C7="","",U7*X7/100) | AH7: =IF($C7="","",U7-AG7) | AI7: =IF($C7="","",AH7-M7) | AJ7: =IF($C7="","",IF(COUNTIF($C$2:$C7,$C7)=1,1,0)) | AK7: =IF($AJ7=1,SUMPRODUCT(--($AN$2:$AN$4001<$AN7))+1,"") | AL7: =IF($C7="","",IF(OR($Q7=TRUE(),$Q7="TRUE"),1,0)) | AM7: =IF($C7="","",IF($W7="Yes",1,0)) | AN7: =IF($AJ7=1,IFERROR(IF(VALUE($C7)<100000000,VALUE($C7),1000000000),IFERROR(IF(VALUE(MID($C7,2,20))<100000000,VALUE(MID($C7,2,20)),1000000000),1000000000))+ROW()/100000,"")
M8: =IF($C8="","",L8*U8/100) | U8: =IF($C8="","",S8*T8) | X8: =IF($C8="","",IF($AM8=1,0,IF($AL8=1,Settings!$C$6,Settings!$C$7))*100) | AG8: =IF($C8="","",U8*X8/100) | AH8: =IF($C8="","",U8-AG8) | AI8: =IF($C8="","",AH8-M8) | AJ8: =IF($C8="","",IF(COUNTIF($C$2:$C8,$C8)=1,1,0)) | AK8: =IF($AJ8=1,SUMPRODUCT(--($AN$2:$AN$4001<$AN8))+1,"") | AL8: =IF($C8="","",IF(OR($Q8=TRUE(),$Q8="TRUE"),1,0)) | AM8: =IF($C8="","",IF($W8="Yes",1,0)) | AN8: =IF($AJ8=1,IFERROR(IF(VALUE($C8)<100000000,VALUE($C8),1000000000),IFERROR(IF(VALUE(MID($C8,2,20))<100000000,VALUE(MID($C8,2,20)),1000000000),1000000000))+ROW()/100000,"")
M9: =IF($C9="","",L9*U9/100) | U9: =IF($C9="","",S9*T9) | X9: =IF($C9="","",IF($AM9=1,0,IF($AL9=1,Settings!$C$6,Settings!$C$7))*100) | AG9: =IF($C9="","",U9*X9/100) | AH9: =IF($C9="","",U9-AG9) | AI9: =IF($C9="","",AH9-M9) | AJ9: =IF($C9="","",IF(COUNTIF($C$2:$C9,$C9)=1,1,0)) | AK9: =IF($AJ9=1,SUMPRODUCT(--($AN$2:$AN$4001<$AN9))+1,"") | AL9: =IF($C9="","",IF(OR($Q9=TRUE(),$Q9="TRUE"),1,0)) | AM9: =IF($C9="","",IF($W9="Yes",1,0)) | AN9: =IF($AJ9=1,IFERROR(IF(VALUE($C9)<100000000,VALUE($C9),1000000000),IFERROR(IF(VALUE(MID($C9,2,20))<100000000,VALUE(MID($C9,2,20)),1000000000),1000000000))+ROW()/100000,"")
M10: =IF($C10="","",L10*U10/100) | U10: =IF($C10="","",S10*T10) | X10: =IF($C10="","",IF($AM10=1,0,IF($AL10=1,Settings!$C$6,Settings!$C$7))*100) | AG10: =IF($C10="","",U10*X10/100) | AH10: =IF($C10="","",U10-AG10) | AI10: =IF($C10="","",AH10-M10) | AJ10: =IF($C10="","",IF(COUNTIF($C$2:$C10,$C10)=1,1,0)) | AK10: =IF($AJ10=1,SUMPRODUCT(--($AN$2:$AN$4001<$AN10))+1,"") | AL10: =IF($C10="","",IF(OR($Q10=TRUE(),$Q10="TRUE"),1,0)) | AM10: =IF($C10="","",IF($W10="Yes",1,0)) | AN10: =IF($AJ10=1,IFERROR(IF(VALUE($C10)<100000000,VALUE($C10),1000000000),IFERROR(IF(VALUE(MID($C10,2,20))<100000000,VALUE(MID($C10,2,20)),1000000000),1000000000))+ROW()/100000,"")
M11: =IF($C11="","",L11*U11/100) | U11: =IF($C11="","",S11*T11) | X11: =IF($C11="","",IF($AM11=1,0,IF($AL11=1,Settings!$C$6,Settings!$C$7))*100) | AG11: =IF($C11="","",U11*X11/100) | AH11: =IF($C11="","",U11-AG11) | AI11: =IF($C11="","",AH11-M11) | AJ11: =IF($C11="","",IF(COUNTIF($C$2:$C11,$C11)=1,1,0)) | AK11: =IF($AJ11=1,SUMPRODUCT(--($AN$2:$AN$4001<$AN11))+1,"") | AL11: =IF($C11="","",IF(OR($Q11=TRUE(),$Q11="TRUE"),1,0)) | AM11: =IF($C11="","",IF($W11="Yes",1,0)) | AN11: =IF($AJ11=1,IFERROR(IF(VALUE($C11)<100000000,VALUE($C11),1000000000),IFERROR(IF(VALUE(MID($C11,2,20))<100000000,VALUE(MID($C11,2,20)),1000000000),1000000000))+ROW()/100000,"")
M12: =IF($C12="","",L12*U12/100) | U12: =IF($C12="","",S12*T12) | X12: =IF($C12="","",IF($AM12=1,0,IF($AL12=1,Settings!$C$6,Settings!$C$7))*100) | AG12: =IF($C12="","",U12*X12/100) | AH12: =IF($C12="","",U12-AG12) | AI12: =IF($C12="","",AH12-M12) | AJ12: =IF($C12="","",IF(COUNTIF($C$2:$C12,$C12)=1,1,0)) | AK12: =IF($AJ12=1,SUMPRODUCT(--($AN$2:$AN$4001<$AN12))+1,"") | AL12: =IF($C12="","",IF(OR($Q12=TRUE(),$Q12="TRUE"),1,0)) | AM12: =IF($C12="","",IF($W12="Yes",1,0)) | AN12: =IF($AJ12=1,IFERROR(IF(VALUE($C12)<100000000,VALUE($C12),1000000000),IFERROR(IF(VALUE(MID($C12,2,20))<100000000,VALUE(MID($C12,2,20)),1000000000),1000000000))+ROW()/100000,"")
M13: =IF($C13="","",L13*U13/100) | U13: =IF($C13="","",S13*T13) | X13: =IF($C13="","",IF($AM13=1,0,IF($AL13=1,Settings!$C$6,Settings!$C$7))*100) | AG13: =IF($C13="","",U13*X13/100) | AH13: =IF($C13="","",U13-AG13) | AI13: =IF($C13="","",AH13-M13) | AJ13: =IF($C13="","",IF(COUNTIF($C$2:$C13,$C13)=1,1,0)) | AK13: =IF($AJ13=1,SUMPRODUCT(--($AN$2:$AN$4001<$AN13))+1,"") | AL13: =IF($C13="","",IF(OR($Q13=TRUE(),$Q13="TRUE"),1,0)) | AM13: =IF($C13="","",IF($W13="Yes",1,0)) | AN13: =IF($AJ13=1,IFERROR(IF(VALUE($C13)<100000000,VALUE($C13),1000000000),IFERROR(IF(VALUE(MID($C13,2,20))<100000000,VALUE(MID($C13,2,20)),1000000000),1000000000))+ROW()/100000,"")
... M4001: =IF($C4001="","",L4001*U4001/100) | U4001: =IF($C4001="","",S4001*T4001) | X4001: =IF($C4001="","",IF($AM4001=1,0,IF($AL4001=1,Settings!$C$6,Settings!$C$7))*100) | AG4001: =IF($C4001="","",U4001*X4001/100) | AH4001: =IF($C4001="","",U4001-AG4001) | AI4001: =IF($C4001="","",AH4001-M4001) | AJ4001: =IF($C4001="","",IF(COUNTIF($C$2:$C4001,$C4001)=1,1,0)) | AK4001: =IF($AJ4001=1,SUMPRODUCT(--($AN$2:$AN$4001<$AN4001))+1,"") | AL4001: =IF($C4001="","",IF(OR($Q4001=TRUE(),$Q4001="TRUE"),1,0)) | AM4001: =IF($C4001="","",IF($W4001="Yes",1,0)) | AN4001: =IF($AJ4001=1,IFERROR(IF(VALUE($C4001)<100000000,VALUE($C4001),1000000000),IFERROR(IF(VALUE(MID($C4001,2,20))<100000000,VALUE(MID($C4001,2,20)),1000000000),1000000000))+ROW()/100000,"")

Sheet Per Invoice
A1: Invoice | B1: Order # | C1: Channel | D1: Stage | E1: Ticket # | F1: Create At | G1: Insurance Company | H1: Corporate | I1: Card | J1: Name | K1: Status | L1: Order Co Payment | M1: Co val | N1: ERX ID | O1: Max Limit | P1: Exceeding Limit | Q1: SP | R1: IMP% | S1: IMP | T1: IMP VAL | U1: LOCAL% | V1: LOCAL | W1: LOCAL VAL | X1: TOTAL VAL | Y1: SUBTOTAL | Z1: Grand Total | AA1: NET | AB1: Src Row (helper) | AC1: Limit Adj (helper)
B2: =IF($AB2="","",INDEX('Per Line'!$C$2:$C$4001,$AB2)&"") | C2: =IF($AB2="","",INDEX('Per Line'!$D$2:$D$4001,$AB2)&"") | D2: =IF($AB2="","",INDEX('Per Line'!$B$2:$B$4001,$AB2)&"") | E2: =IF($AB2="","",INDEX('Per Line'!$A$2:$A$4001,$AB2)) | F2: =IF($AB2="","",INDEX('Per Line'!$E$2:$E$4001,$AB2)) | G2: =IF($AB2="","",INDEX('Per Line'!$F$2:$F$4001,$AB2)&"") | H2: =IF($AB2="","",INDEX('Per Line'!$H$2:$H$4001,$AB2)&"") | I2: =IF($AB2="","",INDEX('Per Line'!$I$2:$I$4001,$AB2)&"") | J2: =IF($AB2="","",INDEX('Per Line'!$J$2:$J$4001,$AB2)&"") | K2: =IF($AB2="","",INDEX('Per Line'!$K$2:$K$4001,$AB2)&"") | L2: =IF($AB2="","",INDEX('Per Line'!$L$2:$L$4001,$AB2)) | M2: =IF($AB2="","",IF(AND(ISNUMBER(O2),O2>0,Z2>O2),L2*O2/100+(Z2-O2),L2*Z2/100)) | N2: =IF($AB2="","",INDEX('Per Line'!$V$2:$V$4001,$AB2)&"") | O2: =IF($AB2="","",INDEX('Per Line'!$Z$2:$Z$4001,$AB2)) | P2: =IF($AB2="","",IF(AND(ISNUMBER(O2),O2>0),Z2>O2,FALSE)) | Q2: =IF($AB2="","",SUMIFS('Per Line'!$U$2:$U$4001,'Per Line'!$C$2:$C$4001,$B2,'Per Line'!$AM$2:$AM$4001,1)) | R2: =IF($AB2="","",Settings!$C$7) | S2: =IF($AB2="","",SUMIFS('Per Line'!$U$2:$U$4001,'Per Line'!$C$2:$C$4001,$B2,'Per Line'!$AL$2:$AL$4001,0,'Per Line'!$AM$2:$AM$4001,0)) | T2: =IF($AB2="","",S2*R2) | U2: =IF($AB2="","",Settings!$C$6) | V2: =IF($AB2="","",SUMIFS('Per Line'!$U$2:$U$4001,'Per Line'!$C$2:$C$4001,$B2,'Per Line'!$AL$2:$AL$4001,1,'Per Line'!$AM$2:$AM$4001,0)) | W2: =IF($AB2="","",V2*U2) | X2: =IF($AB2="","",W2+T2) | Y2: =IF($AB2="","",Z2-X2) | Z2: =IF($AB2="","",S2+V2+Q2) | AA2: =IF($AB2="","",Z2-X2-M2) | AB2: =IF(ROWS($AB$2:$AB2)<=MAX('Per Line'!$AK$2:$AK$4001),MATCH(ROWS($AB$2:$AB2),'Per Line'!$AK$2:$AK$4001,0),"") | AC2: =IF($AB2="","",M2-L2*Z2/100)
B3: =IF($AB3="","",INDEX('Per Line'!$C$2:$C$4001,$AB3)&"") | C3: =IF($AB3="","",INDEX('Per Line'!$D$2:$D$4001,$AB3)&"") | D3: =IF($AB3="","",INDEX('Per Line'!$B$2:$B$4001,$AB3)&"") | E3: =IF($AB3="","",INDEX('Per Line'!$A$2:$A$4001,$AB3)) | F3: =IF($AB3="","",INDEX('Per Line'!$E$2:$E$4001,$AB3)) | G3: =IF($AB3="","",INDEX('Per Line'!$F$2:$F$4001,$AB3)&"") | H3: =IF($AB3="","",INDEX('Per Line'!$H$2:$H$4001,$AB3)&"") | I3: =IF($AB3="","",INDEX('Per Line'!$I$2:$I$4001,$AB3)&"") | J3: =IF($AB3="","",INDEX('Per Line'!$J$2:$J$4001,$AB3)&"") | K3: =IF($AB3="","",INDEX('Per Line'!$K$2:$K$4001,$AB3)&"") | L3: =IF($AB3="","",INDEX('Per Line'!$L$2:$L$4001,$AB3)) | M3: =IF($AB3="","",IF(AND(ISNUMBER(O3),O3>0,Z3>O3),L3*O3/100+(Z3-O3),L3*Z3/100)) | N3: =IF($AB3="","",INDEX('Per Line'!$V$2:$V$4001,$AB3)&"") | O3: =IF($AB3="","",INDEX('Per Line'!$Z$2:$Z$4001,$AB3)) | P3: =IF($AB3="","",IF(AND(ISNUMBER(O3),O3>0),Z3>O3,FALSE)) | Q3: =IF($AB3="","",SUMIFS('Per Line'!$U$2:$U$4001,'Per Line'!$C$2:$C$4001,$B3,'Per Line'!$AM$2:$AM$4001,1)) | R3: =IF($AB3="","",Settings!$C$7) | S3: =IF($AB3="","",SUMIFS('Per Line'!$U$2:$U$4001,'Per Line'!$C$2:$C$4001,$B3,'Per Line'!$AL$2:$AL$4001,0,'Per Line'!$AM$2:$AM$4001,0)) | T3: =IF($AB3="","",S3*R3) | U3: =IF($AB3="","",Settings!$C$6) | V3: =IF($AB3="","",SUMIFS('Per Line'!$U$2:$U$4001,'Per Line'!$C$2:$C$4001,$B3,'Per Line'!$AL$2:$AL$4001,1,'Per Line'!$AM$2:$AM$4001,0)) | W3: =IF($AB3="","",V3*U3) | X3: =IF($AB3="","",W3+T3) | Y3: =IF($AB3="","",Z3-X3) | Z3: =IF($AB3="","",S3+V3+Q3) | AA3: =IF($AB3="","",Z3-X3-M3) | AB3: =IF(ROWS($AB$2:$AB3)<=MAX('Per Line'!$AK$2:$AK$4001),MATCH(ROWS($AB$2:$AB3),'Per Line'!$AK$2:$AK$4001,0),"") | AC3: =IF($AB3="","",M3-L3*Z3/100)
B4: =IF($AB4="","",INDEX('Per Line'!$C$2:$C$4001,$AB4)&"") | C4: =IF($AB4="","",INDEX('Per Line'!$D$2:$D$4001,$AB4)&"") | D4: =IF($AB4="","",INDEX('Per Line'!$B$2:$B$4001,$AB4)&"") | E4: =IF($AB4="","",INDEX('Per Line'!$A$2:$A$4001,$AB4)) | F4: =IF($AB4="","",INDEX('Per Line'!$E$2:$E$4001,$AB4)) | G4: =IF($AB4="","",INDEX('Per Line'!$F$2:$F$4001,$AB4)&"") | H4: =IF($AB4="","",INDEX('Per Line'!$H$2:$H$4001,$AB4)&"") | I4: =IF($AB4="","",INDEX('Per Line'!$I$2:$I$4001,$AB4)&"") | J4: =IF($AB4="","",INDEX('Per Line'!$J$2:$J$4001,$AB4)&"") | K4: =IF($AB4="","",INDEX('Per Line'!$K$2:$K$4001,$AB4)&"") | L4: =IF($AB4="","",INDEX('Per Line'!$L$2:$L$4001,$AB4)) | M4: =IF($AB4="","",IF(AND(ISNUMBER(O4),O4>0,Z4>O4),L4*O4/100+(Z4-O4),L4*Z4/100)) | N4: =IF($AB4="","",INDEX('Per Line'!$V$2:$V$4001,$AB4)&"") | O4: =IF($AB4="","",INDEX('Per Line'!$Z$2:$Z$4001,$AB4)) | P4: =IF($AB4="","",IF(AND(ISNUMBER(O4),O4>0),Z4>O4,FALSE)) | Q4: =IF($AB4="","",SUMIFS('Per Line'!$U$2:$U$4001,'Per Line'!$C$2:$C$4001,$B4,'Per Line'!$AM$2:$AM$4001,1)) | R4: =IF($AB4="","",Settings!$C$7) | S4: =IF($AB4="","",SUMIFS('Per Line'!$U$2:$U$4001,'Per Line'!$C$2:$C$4001,$B4,'Per Line'!$AL$2:$AL$4001,0,'Per Line'!$AM$2:$AM$4001,0)) | T4: =IF($AB4="","",S4*R4) | U4: =IF($AB4="","",Settings!$C$6) | V4: =IF($AB4="","",SUMIFS('Per Line'!$U$2:$U$4001,'Per Line'!$C$2:$C$4001,$B4,'Per Line'!$AL$2:$AL$4001,1,'Per Line'!$AM$2:$AM$4001,0)) | W4: =IF($AB4="","",V4*U4) | X4: =IF($AB4="","",W4+T4) | Y4: =IF($AB4="","",Z4-X4) | Z4: =IF($AB4="","",S4+V4+Q4) | AA4: =IF($AB4="","",Z4-X4-M4) | AB4: =IF(ROWS($AB$2:$AB4)<=MAX('Per Line'!$AK$2:$AK$4001),MATCH(ROWS($AB$2:$AB4),'Per Line'!$AK$2:$AK$4001,0),"") | AC4: =IF($AB4="","",M4-L4*Z4/100)
B5: =IF($AB5="","",INDEX('Per Line'!$C$2:$C$4001,$AB5)&"") | C5: =IF($AB5="","",INDEX('Per Line'!$D$2:$D$4001,$AB5)&"") | D5: =IF($AB5="","",INDEX('Per Line'!$B$2:$B$4001,$AB5)&"") | E5: =IF($AB5="","",INDEX('Per Line'!$A$2:$A$4001,$AB5)) | F5: =IF($AB5="","",INDEX('Per Line'!$E$2:$E$4001,$AB5)) | G5: =IF($AB5="","",INDEX('Per Line'!$F$2:$F$4001,$AB5)&"") | H5: =IF($AB5="","",INDEX('Per Line'!$H$2:$H$4001,$AB5)&"") | I5: =IF($AB5="","",INDEX('Per Line'!$I$2:$I$4001,$AB5)&"") | J5: =IF($AB5="","",INDEX('Per Line'!$J$2:$J$4001,$AB5)&"") | K5: =IF($AB5="","",INDEX('Per Line'!$K$2:$K$4001,$AB5)&"") | L5: =IF($AB5="","",INDEX('Per Line'!$L$2:$L$4001,$AB5)) | M5: =IF($AB5="","",IF(AND(ISNUMBER(O5),O5>0,Z5>O5),L5*O5/100+(Z5-O5),L5*Z5/100)) | N5: =IF($AB5="","",INDEX('Per Line'!$V$2:$V$4001,$AB5)&"") | O5: =IF($AB5="","",INDEX('Per Line'!$Z$2:$Z$4001,$AB5)) | P5: =IF($AB5="","",IF(AND(ISNUMBER(O5),O5>0),Z5>O5,FALSE)) | Q5: =IF($AB5="","",SUMIFS('Per Line'!$U$2:$U$4001,'Per Line'!$C$2:$C$4001,$B5,'Per Line'!$AM$2:$AM$4001,1)) | R5: =IF($AB5="","",Settings!$C$7) | S5: =IF($AB5="","",SUMIFS('Per Line'!$U$2:$U$4001,'Per Line'!$C$2:$C$4001,$B5,'Per Line'!$AL$2:$AL$4001,0,'Per Line'!$AM$2:$AM$4001,0)) | T5: =IF($AB5="","",S5*R5) | U5: =IF($AB5="","",Settings!$C$6) | V5: =IF($AB5="","",SUMIFS('Per Line'!$U$2:$U$4001,'Per Line'!$C$2:$C$4001,$B5,'Per Line'!$AL$2:$AL$4001,1,'Per Line'!$AM$2:$AM$4001,0)) | W5: =IF($AB5="","",V5*U5) | X5: =IF($AB5="","",W5+T5) | Y5: =IF($AB5="","",Z5-X5) | Z5: =IF($AB5="","",S5+V5+Q5) | AA5: =IF($AB5="","",Z5-X5-M5) | AB5: =IF(ROWS($AB$2:$AB5)<=MAX('Per Line'!$AK$2:$AK$4001),MATCH(ROWS($AB$2:$AB5),'Per Line'!$AK$2:$AK$4001,0),"") | AC5: =IF($AB5="","",M5-L5*Z5/100)
B6: =IF($AB6="","",INDEX('Per Line'!$C$2:$C$4001,$AB6)&"") | C6: =IF($AB6="","",INDEX('Per Line'!$D$2:$D$4001,$AB6)&"") | D6: =IF($AB6="","",INDEX('Per Line'!$B$2:$B$4001,$AB6)&"") | E6: =IF($AB6="","",INDEX('Per Line'!$A$2:$A$4001,$AB6)) | F6: =IF($AB6="","",INDEX('Per Line'!$E$2:$E$4001,$AB6)) | G6: =IF($AB6="","",INDEX('Per Line'!$F$2:$F$4001,$AB6)&"") | H6: =IF($AB6="","",INDEX('Per Line'!$H$2:$H$4001,$AB6)&"") | I6: =IF($AB6="","",INDEX('Per Line'!$I$2:$I$4001,$AB6)&"") | J6: =IF($AB6="","",INDEX('Per Line'!$J$2:$J$4001,$AB6)&"") | K6: =IF($AB6="","",INDEX('Per Line'!$K$2:$K$4001,$AB6)&"") | L6: =IF($AB6="","",INDEX('Per Line'!$L$2:$L$4001,$AB6)) | M6: =IF($AB6="","",IF(AND(ISNUMBER(O6),O6>0,Z6>O6),L6*O6/100+(Z6-O6),L6*Z6/100)) | N6: =IF($AB6="","",INDEX('Per Line'!$V$2:$V$4001,$AB6)&"") | O6: =IF($AB6="","",INDEX('Per Line'!$Z$2:$Z$4001,$AB6)) | P6: =IF($AB6="","",IF(AND(ISNUMBER(O6),O6>0),Z6>O6,FALSE)) | Q6: =IF($AB6="","",SUMIFS('Per Line'!$U$2:$U$4001,'Per Line'!$C$2:$C$4001,$B6,'Per Line'!$AM$2:$AM$4001,1)) | R6: =IF($AB6="","",Settings!$C$7) | S6: =IF($AB6="","",SUMIFS('Per Line'!$U$2:$U$4001,'Per Line'!$C$2:$C$4001,$B6,'Per Line'!$AL$2:$AL$4001,0,'Per Line'!$AM$2:$AM$4001,0)) | T6: =IF($AB6="","",S6*R6) | U6: =IF($AB6="","",Settings!$C$6) | V6: =IF($AB6="","",SUMIFS('Per Line'!$U$2:$U$4001,'Per Line'!$C$2:$C$4001,$B6,'Per Line'!$AL$2:$AL$4001,1,'Per Line'!$AM$2:$AM$4001,0)) | W6: =IF($AB6="","",V6*U6) | X6: =IF($AB6="","",W6+T6) | Y6: =IF($AB6="","",Z6-X6) | Z6: =IF($AB6="","",S6+V6+Q6) | AA6: =IF($AB6="","",Z6-X6-M6) | AB6: =IF(ROWS($AB$2:$AB6)<=MAX('Per Line'!$AK$2:$AK$4001),MATCH(ROWS($AB$2:$AB6),'Per Line'!$AK$2:$AK$4001,0),"") | AC6: =IF($AB6="","",M6-L6*Z6/100)
B7: =IF($AB7="","",INDEX('Per Line'!$C$2:$C$4001,$AB7)&"") | C7: =IF($AB7="","",INDEX('Per Line'!$D$2:$D$4001,$AB7)&"") | D7: =IF($AB7="","",INDEX('Per Line'!$B$2:$B$4001,$AB7)&"") | E7: =IF($AB7="","",INDEX('Per Line'!$A$2:$A$4001,$AB7)) | F7: =IF($AB7="","",INDEX('Per Line'!$E$2:$E$4001,$AB7)) | G7: =IF($AB7="","",INDEX('Per Line'!$F$2:$F$4001,$AB7)&"") | H7: =IF($AB7="","",INDEX('Per Line'!$H$2:$H$4001,$AB7)&"") | I7: =IF($AB7="","",INDEX('Per Line'!$I$2:$I$4001,$AB7)&"") | J7: =IF($AB7="","",INDEX('Per Line'!$J$2:$J$4001,$AB7)&"") | K7: =IF($AB7="","",INDEX('Per Line'!$K$2:$K$4001,$AB7)&"") | L7: =IF($AB7="","",INDEX('Per Line'!$L$2:$L$4001,$AB7)) | M7: =IF($AB7="","",IF(AND(ISNUMBER(O7),O7>0,Z7>O7),L7*O7/100+(Z7-O7),L7*Z7/100)) | N7: =IF($AB7="","",INDEX('Per Line'!$V$2:$V$4001,$AB7)&"") | O7: =IF($AB7="","",INDEX('Per Line'!$Z$2:$Z$4001,$AB7)) | P7: =IF($AB7="","",IF(AND(ISNUMBER(O7),O7>0),Z7>O7,FALSE)) | Q7: =IF($AB7="","",SUMIFS('Per Line'!$U$2:$U$4001,'Per Line'!$C$2:$C$4001,$B7,'Per Line'!$AM$2:$AM$4001,1)) | R7: =IF($AB7="","",Settings!$C$7) | S7: =IF($AB7="","",SUMIFS('Per Line'!$U$2:$U$4001,'Per Line'!$C$2:$C$4001,$B7,'Per Line'!$AL$2:$AL$4001,0,'Per Line'!$AM$2:$AM$4001,0)) | T7: =IF($AB7="","",S7*R7) | U7: =IF($AB7="","",Settings!$C$6) | V7: =IF($AB7="","",SUMIFS('Per Line'!$U$2:$U$4001,'Per Line'!$C$2:$C$4001,$B7,'Per Line'!$AL$2:$AL$4001,1,'Per Line'!$AM$2:$AM$4001,0)) | W7: =IF($AB7="","",V7*U7) | X7: =IF($AB7="","",W7+T7) | Y7: =IF($AB7="","",Z7-X7) | Z7: =IF($AB7="","",S7+V7+Q7) | AA7: =IF($AB7="","",Z7-X7-M7) | AB7: =IF(ROWS($AB$2:$AB7)<=MAX('Per Line'!$AK$2:$AK$4001),MATCH(ROWS($AB$2:$AB7),'Per Line'!$AK$2:$AK$4001,0),"") | AC7: =IF($AB7="","",M7-L7*Z7/100)
B8: =IF($AB8="","",INDEX('Per Line'!$C$2:$C$4001,$AB8)&"") | C8: =IF($AB8="","",INDEX('Per Line'!$D$2:$D$4001,$AB8)&"") | D8: =IF($AB8="","",INDEX('Per Line'!$B$2:$B$4001,$AB8)&"") | E8: =IF($AB8="","",INDEX('Per Line'!$A$2:$A$4001,$AB8)) | F8: =IF($AB8="","",INDEX('Per Line'!$E$2:$E$4001,$AB8)) | G8: =IF($AB8="","",INDEX('Per Line'!$F$2:$F$4001,$AB8)&"") | H8: =IF($AB8="","",INDEX('Per Line'!$H$2:$H$4001,$AB8)&"") | I8: =IF($AB8="","",INDEX('Per Line'!$I$2:$I$4001,$AB8)&"") | J8: =IF($AB8="","",INDEX('Per Line'!$J$2:$J$4001,$AB8)&"") | K8: =IF($AB8="","",INDEX('Per Line'!$K$2:$K$4001,$AB8)&"") | L8: =IF($AB8="","",INDEX('Per Line'!$L$2:$L$4001,$AB8)) | M8: =IF($AB8="","",IF(AND(ISNUMBER(O8),O8>0,Z8>O8),L8*O8/100+(Z8-O8),L8*Z8/100)) | N8: =IF($AB8="","",INDEX('Per Line'!$V$2:$V$4001,$AB8)&"") | O8: =IF($AB8="","",INDEX('Per Line'!$Z$2:$Z$4001,$AB8)) | P8: =IF($AB8="","",IF(AND(ISNUMBER(O8),O8>0),Z8>O8,FALSE)) | Q8: =IF($AB8="","",SUMIFS('Per Line'!$U$2:$U$4001,'Per Line'!$C$2:$C$4001,$B8,'Per Line'!$AM$2:$AM$4001,1)) | R8: =IF($AB8="","",Settings!$C$7) | S8: =IF($AB8="","",SUMIFS('Per Line'!$U$2:$U$4001,'Per Line'!$C$2:$C$4001,$B8,'Per Line'!$AL$2:$AL$4001,0,'Per Line'!$AM$2:$AM$4001,0)) | T8: =IF($AB8="","",S8*R8) | U8: =IF($AB8="","",Settings!$C$6) | V8: =IF($AB8="","",SUMIFS('Per Line'!$U$2:$U$4001,'Per Line'!$C$2:$C$4001,$B8,'Per Line'!$AL$2:$AL$4001,1,'Per Line'!$AM$2:$AM$4001,0)) | W8: =IF($AB8="","",V8*U8) | X8: =IF($AB8="","",W8+T8) | Y8: =IF($AB8="","",Z8-X8) | Z8: =IF($AB8="","",S8+V8+Q8) | AA8: =IF($AB8="","",Z8-X8-M8) | AB8: =IF(ROWS($AB$2:$AB8)<=MAX('Per Line'!$AK$2:$AK$4001),MATCH(ROWS($AB$2:$AB8),'Per Line'!$AK$2:$AK$4001,0),"") | AC8: =IF($AB8="","",M8-L8*Z8/100)
B9: =IF($AB9="","",INDEX('Per Line'!$C$2:$C$4001,$AB9)&"") | C9: =IF($AB9="","",INDEX('Per Line'!$D$2:$D$4001,$AB9)&"") | D9: =IF($AB9="","",INDEX('Per Line'!$B$2:$B$4001,$AB9)&"") | E9: =IF($AB9="","",INDEX('Per Line'!$A$2:$A$4001,$AB9)) | F9: =IF($AB9="","",INDEX('Per Line'!$E$2:$E$4001,$AB9)) | G9: =IF($AB9="","",INDEX('Per Line'!$F$2:$F$4001,$AB9)&"") | H9: =IF($AB9="","",INDEX('Per Line'!$H$2:$H$4001,$AB9)&"") | I9: =IF($AB9="","",INDEX('Per Line'!$I$2:$I$4001,$AB9)&"") | J9: =IF($AB9="","",INDEX('Per Line'!$J$2:$J$4001,$AB9)&"") | K9: =IF($AB9="","",INDEX('Per Line'!$K$2:$K$4001,$AB9)&"") | L9: =IF($AB9="","",INDEX('Per Line'!$L$2:$L$4001,$AB9)) | M9: =IF($AB9="","",IF(AND(ISNUMBER(O9),O9>0,Z9>O9),L9*O9/100+(Z9-O9),L9*Z9/100)) | N9: =IF($AB9="","",INDEX('Per Line'!$V$2:$V$4001,$AB9)&"") | O9: =IF($AB9="","",INDEX('Per Line'!$Z$2:$Z$4001,$AB9)) | P9: =IF($AB9="","",IF(AND(ISNUMBER(O9),O9>0),Z9>O9,FALSE)) | Q9: =IF($AB9="","",SUMIFS('Per Line'!$U$2:$U$4001,'Per Line'!$C$2:$C$4001,$B9,'Per Line'!$AM$2:$AM$4001,1)) | R9: =IF($AB9="","",Settings!$C$7) | S9: =IF($AB9="","",SUMIFS('Per Line'!$U$2:$U$4001,'Per Line'!$C$2:$C$4001,$B9,'Per Line'!$AL$2:$AL$4001,0,'Per Line'!$AM$2:$AM$4001,0)) | T9: =IF($AB9="","",S9*R9) | U9: =IF($AB9="","",Settings!$C$6) | V9: =IF($AB9="","",SUMIFS('Per Line'!$U$2:$U$4001,'Per Line'!$C$2:$C$4001,$B9,'Per Line'!$AL$2:$AL$4001,1,'Per Line'!$AM$2:$AM$4001,0)) | W9: =IF($AB9="","",V9*U9) | X9: =IF($AB9="","",W9+T9) | Y9: =IF($AB9="","",Z9-X9) | Z9: =IF($AB9="","",S9+V9+Q9) | AA9: =IF($AB9="","",Z9-X9-M9) | AB9: =IF(ROWS($AB$2:$AB9)<=MAX('Per Line'!$AK$2:$AK$4001),MATCH(ROWS($AB$2:$AB9),'Per Line'!$AK$2:$AK$4001,0),"") | AC9: =IF($AB9="","",M9-L9*Z9/100)
B10: =IF($AB10="","",INDEX('Per Line'!$C$2:$C$4001,$AB10)&"") | C10: =IF($AB10="","",INDEX('Per Line'!$D$2:$D$4001,$AB10)&"") | D10: =IF($AB10="","",INDEX('Per Line'!$B$2:$B$4001,$AB10)&"") | E10: =IF($AB10="","",INDEX('Per Line'!$A$2:$A$4001,$AB10)) | F10: =IF($AB10="","",INDEX('Per Line'!$E$2:$E$4001,$AB10)) | G10: =IF($AB10="","",INDEX('Per Line'!$F$2:$F$4001,$AB10)&"") | H10: =IF($AB10="","",INDEX('Per Line'!$H$2:$H$4001,$AB10)&"") | I10: =IF($AB10="","",INDEX('Per Line'!$I$2:$I$4001,$AB10)&"") | J10: =IF($AB10="","",INDEX('Per Line'!$J$2:$J$4001,$AB10)&"") | K10: =IF($AB10="","",INDEX('Per Line'!$K$2:$K$4001,$AB10)&"") | L10: =IF($AB10="","",INDEX('Per Line'!$L$2:$L$4001,$AB10)) | M10: =IF($AB10="","",IF(AND(ISNUMBER(O10),O10>0,Z10>O10),L10*O10/100+(Z10-O10),L10*Z10/100)) | N10: =IF($AB10="","",INDEX('Per Line'!$V$2:$V$4001,$AB10)&"") | O10: =IF($AB10="","",INDEX('Per Line'!$Z$2:$Z$4001,$AB10)) | P10: =IF($AB10="","",IF(AND(ISNUMBER(O10),O10>0),Z10>O10,FALSE)) | Q10: =IF($AB10="","",SUMIFS('Per Line'!$U$2:$U$4001,'Per Line'!$C$2:$C$4001,$B10,'Per Line'!$AM$2:$AM$4001,1)) | R10: =IF($AB10="","",Settings!$C$7) | S10: =IF($AB10="","",SUMIFS('Per Line'!$U$2:$U$4001,'Per Line'!$C$2:$C$4001,$B10,'Per Line'!$AL$2:$AL$4001,0,'Per Line'!$AM$2:$AM$4001,0)) | T10: =IF($AB10="","",S10*R10) | U10: =IF($AB10="","",Settings!$C$6) | V10: =IF($AB10="","",SUMIFS('Per Line'!$U$2:$U$4001,'Per Line'!$C$2:$C$4001,$B10,'Per Line'!$AL$2:$AL$4001,1,'Per Line'!$AM$2:$AM$4001,0)) | W10: =IF($AB10="","",V10*U10) | X10: =IF($AB10="","",W10+T10) | Y10: =IF($AB10="","",Z10-X10) | Z10: =IF($AB10="","",S10+V10+Q10) | AA10: =IF($AB10="","",Z10-X10-M10) | AB10: =IF(ROWS($AB$2:$AB10)<=MAX('Per Line'!$AK$2:$AK$4001),MATCH(ROWS($AB$2:$AB10),'Per Line'!$AK$2:$AK$4001,0),"") | AC10: =IF($AB10="","",M10-L10*Z10/100)
B11: =IF($AB11="","",INDEX('Per Line'!$C$2:$C$4001,$AB11)&"") | C11: =IF($AB11="","",INDEX('Per Line'!$D$2:$D$4001,$AB11)&"") | D11: =IF($AB11="","",INDEX('Per Line'!$B$2:$B$4001,$AB11)&"") | E11: =IF($AB11="","",INDEX('Per Line'!$A$2:$A$4001,$AB11)) | F11: =IF($AB11="","",INDEX('Per Line'!$E$2:$E$4001,$AB11)) | G11: =IF($AB11="","",INDEX('Per Line'!$F$2:$F$4001,$AB11)&"") | H11: =IF($AB11="","",INDEX('Per Line'!$H$2:$H$4001,$AB11)&"") | I11: =IF($AB11="","",INDEX('Per Line'!$I$2:$I$4001,$AB11)&"") | J11: =IF($AB11="","",INDEX('Per Line'!$J$2:$J$4001,$AB11)&"") | K11: =IF($AB11="","",INDEX('Per Line'!$K$2:$K$4001,$AB11)&"") | L11: =IF($AB11="","",INDEX('Per Line'!$L$2:$L$4001,$AB11)) | M11: =IF($AB11="","",IF(AND(ISNUMBER(O11),O11>0,Z11>O11),L11*O11/100+(Z11-O11),L11*Z11/100)) | N11: =IF($AB11="","",INDEX('Per Line'!$V$2:$V$4001,$AB11)&"") | O11: =IF($AB11="","",INDEX('Per Line'!$Z$2:$Z$4001,$AB11)) | P11: =IF($AB11="","",IF(AND(ISNUMBER(O11),O11>0),Z11>O11,FALSE)) | Q11: =IF($AB11="","",SUMIFS('Per Line'!$U$2:$U$4001,'Per Line'!$C$2:$C$4001,$B11,'Per Line'!$AM$2:$AM$4001,1)) | R11: =IF($AB11="","",Settings!$C$7) | S11: =IF($AB11="","",SUMIFS('Per Line'!$U$2:$U$4001,'Per Line'!$C$2:$C$4001,$B11,'Per Line'!$AL$2:$AL$4001,0,'Per Line'!$AM$2:$AM$4001,0)) | T11: =IF($AB11="","",S11*R11) | U11: =IF($AB11="","",Settings!$C$6) | V11: =IF($AB11="","",SUMIFS('Per Line'!$U$2:$U$4001,'Per Line'!$C$2:$C$4001,$B11,'Per Line'!$AL$2:$AL$4001,1,'Per Line'!$AM$2:$AM$4001,0)) | W11: =IF($AB11="","",V11*U11) | X11: =IF($AB11="","",W11+T11) | Y11: =IF($AB11="","",Z11-X11) | Z11: =IF($AB11="","",S11+V11+Q11) | AA11: =IF($AB11="","",Z11-X11-M11) | AB11: =IF(ROWS($AB$2:$AB11)<=MAX('Per Line'!$AK$2:$AK$4001),MATCH(ROWS($AB$2:$AB11),'Per Line'!$AK$2:$AK$4001,0),"") | AC11: =IF($AB11="","",M11-L11*Z11/100)
B12: =IF($AB12="","",INDEX('Per Line'!$C$2:$C$4001,$AB12)&"") | C12: =IF($AB12="","",INDEX('Per Line'!$D$2:$D$4001,$AB12)&"") | D12: =IF($AB12="","",INDEX('Per Line'!$B$2:$B$4001,$AB12)&"") | E12: =IF($AB12="","",INDEX('Per Line'!$A$2:$A$4001,$AB12)) | F12: =IF($AB12="","",INDEX('Per Line'!$E$2:$E$4001,$AB12)) | G12: =IF($AB12="","",INDEX('Per Line'!$F$2:$F$4001,$AB12)&"") | H12: =IF($AB12="","",INDEX('Per Line'!$H$2:$H$4001,$AB12)&"") | I12: =IF($AB12="","",INDEX('Per Line'!$I$2:$I$4001,$AB12)&"") | J12: =IF($AB12="","",INDEX('Per Line'!$J$2:$J$4001,$AB12)&"") | K12: =IF($AB12="","",INDEX('Per Line'!$K$2:$K$4001,$AB12)&"") | L12: =IF($AB12="","",INDEX('Per Line'!$L$2:$L$4001,$AB12)) | M12: =IF($AB12="","",IF(AND(ISNUMBER(O12),O12>0,Z12>O12),L12*O12/100+(Z12-O12),L12*Z12/100)) | N12: =IF($AB12="","",INDEX('Per Line'!$V$2:$V$4001,$AB12)&"") | O12: =IF($AB12="","",INDEX('Per Line'!$Z$2:$Z$4001,$AB12)) | P12: =IF($AB12="","",IF(AND(ISNUMBER(O12),O12>0),Z12>O12,FALSE)) | Q12: =IF($AB12="","",SUMIFS('Per Line'!$U$2:$U$4001,'Per Line'!$C$2:$C$4001,$B12,'Per Line'!$AM$2:$AM$4001,1)) | R12: =IF($AB12="","",Settings!$C$7) | S12: =IF($AB12="","",SUMIFS('Per Line'!$U$2:$U$4001,'Per Line'!$C$2:$C$4001,$B12,'Per Line'!$AL$2:$AL$4001,0,'Per Line'!$AM$2:$AM$4001,0)) | T12: =IF($AB12="","",S12*R12) | U12: =IF($AB12="","",Settings!$C$6) | V12: =IF($AB12="","",SUMIFS('Per Line'!$U$2:$U$4001,'Per Line'!$C$2:$C$4001,$B12,'Per Line'!$AL$2:$AL$4001,1,'Per Line'!$AM$2:$AM$4001,0)) | W12: =IF($AB12="","",V12*U12) | X12: =IF($AB12="","",W12+T12) | Y12: =IF($AB12="","",Z12-X12) | Z12: =IF($AB12="","",S12+V12+Q12) | AA12: =IF($AB12="","",Z12-X12-M12) | AB12: =IF(ROWS($AB$2:$AB12)<=MAX('Per Line'!$AK$2:$AK$4001),MATCH(ROWS($AB$2:$AB12),'Per Line'!$AK$2:$AK$4001,0),"") | AC12: =IF($AB12="","",M12-L12*Z12/100)
B13: =IF($AB13="","",INDEX('Per Line'!$C$2:$C$4001,$AB13)&"") | C13: =IF($AB13="","",INDEX('Per Line'!$D$2:$D$4001,$AB13)&"") | D13: =IF($AB13="","",INDEX('Per Line'!$B$2:$B$4001,$AB13)&"") | E13: =IF($AB13="","",INDEX('Per Line'!$A$2:$A$4001,$AB13)) | F13: =IF($AB13="","",INDEX('Per Line'!$E$2:$E$4001,$AB13)) | G13: =IF($AB13="","",INDEX('Per Line'!$F$2:$F$4001,$AB13)&"") | H13: =IF($AB13="","",INDEX('Per Line'!$H$2:$H$4001,$AB13)&"") | I13: =IF($AB13="","",INDEX('Per Line'!$I$2:$I$4001,$AB13)&"") | J13: =IF($AB13="","",INDEX('Per Line'!$J$2:$J$4001,$AB13)&"") | K13: =IF($AB13="","",INDEX('Per Line'!$K$2:$K$4001,$AB13)&"") | L13: =IF($AB13="","",INDEX('Per Line'!$L$2:$L$4001,$AB13)) | M13: =IF($AB13="","",IF(AND(ISNUMBER(O13),O13>0,Z13>O13),L13*O13/100+(Z13-O13),L13*Z13/100)) | N13: =IF($AB13="","",INDEX('Per Line'!$V$2:$V$4001,$AB13)&"") | O13: =IF($AB13="","",INDEX('Per Line'!$Z$2:$Z$4001,$AB13)) | P13: =IF($AB13="","",IF(AND(ISNUMBER(O13),O13>0),Z13>O13,FALSE)) | Q13: =IF($AB13="","",SUMIFS('Per Line'!$U$2:$U$4001,'Per Line'!$C$2:$C$4001,$B13,'Per Line'!$AM$2:$AM$4001,1)) | R13: =IF($AB13="","",Settings!$C$7) | S13: =IF($AB13="","",SUMIFS('Per Line'!$U$2:$U$4001,'Per Line'!$C$2:$C$4001,$B13,'Per Line'!$AL$2:$AL$4001,0,'Per Line'!$AM$2:$AM$4001,0)) | T13: =IF($AB13="","",S13*R13) | U13: =IF($AB13="","",Settings!$C$6) | V13: =IF($AB13="","",SUMIFS('Per Line'!$U$2:$U$4001,'Per Line'!$C$2:$C$4001,$B13,'Per Line'!$AL$2:$AL$4001,1,'Per Line'!$AM$2:$AM$4001,0)) | W13: =IF($AB13="","",V13*U13) | X13: =IF($AB13="","",W13+T13) | Y13: =IF($AB13="","",Z13-X13) | Z13: =IF($AB13="","",S13+V13+Q13) | AA13: =IF($AB13="","",Z13-X13-M13) | AB13: =IF(ROWS($AB$2:$AB13)<=MAX('Per Line'!$AK$2:$AK$4001),MATCH(ROWS($AB$2:$AB13),'Per Line'!$AK$2:$AK$4001,0),"") | AC13: =IF($AB13="","",M13-L13*Z13/100)
... B1001: =IF($AB1001="","",INDEX('Per Line'!$C$2:$C$4001,$AB1001)&"") | C1001: =IF($AB1001="","",INDEX('Per Line'!$D$2:$D$4001,$AB1001)&"") | D1001: =IF($AB1001="","",INDEX('Per Line'!$B$2:$B$4001,$AB1001)&"") | E1001: =IF($AB1001="","",INDEX('Per Line'!$A$2:$A$4001,$AB1001)) | F1001: =IF($AB1001="","",INDEX('Per Line'!$E$2:$E$4001,$AB1001)) | G1001: =IF($AB1001="","",INDEX('Per Line'!$F$2:$F$4001,$AB1001)&"") | H1001: =IF($AB1001="","",INDEX('Per Line'!$H$2:$H$4001,$AB1001)&"") | I1001: =IF($AB1001="","",INDEX('Per Line'!$I$2:$I$4001,$AB1001)&"") | J1001: =IF($AB1001="","",INDEX('Per Line'!$J$2:$J$4001,$AB1001)&"") | K1001: =IF($AB1001="","",INDEX('Per Line'!$K$2:$K$4001,$AB1001)&"") | L1001: =IF($AB1001="","",INDEX('Per Line'!$L$2:$L$4001,$AB1001)) | M1001: =IF($AB1001="","",IF(AND(ISNUMBER(O1001),O1001>0,Z1001>O1001),L1001*O1001/100+(Z1001-O1001),L1001*Z1001/100)) | N1001: =IF($AB1001="","",INDEX('Per Line'!$V$2:$V$4001,$AB1001)&"") | O1001: =IF($AB1001="","",INDEX('Per Line'!$Z$2:$Z$4001,$AB1001)) | P1001: =IF($AB1001="","",IF(AND(ISNUMBER(O1001),O1001>0),Z1001>O1001,FALSE)) | Q1001: =IF($AB1001="","",SUMIFS('Per Line'!$U$2:$U$4001,'Per Line'!$C$2:$C$4001,$B1001,'Per Line'!$AM$2:$AM$4001,1)) | R1001: =IF($AB1001="","",Settings!$C$7) | S1001: =IF($AB1001="","",SUMIFS('Per Line'!$U$2:$U$4001,'Per Line'!$C$2:$C$4001,$B1001,'Per Line'!$AL$2:$AL$4001,0,'Per Line'!$AM$2:$AM$4001,0)) | T1001: =IF($AB1001="","",S1001*R1001) | U1001: =IF($AB1001="","",Settings!$C$6) | V1001: =IF($AB1001="","",SUMIFS('Per Line'!$U$2:$U$4001,'Per Line'!$C$2:$C$4001,$B1001,'Per Line'!$AL$2:$AL$4001,1,'Per Line'!$AM$2:$AM$4001,0)) | W1001: =IF($AB1001="","",V1001*U1001) | X1001: =IF($AB1001="","",W1001+T1001) | Y1001: =IF($AB1001="","",Z1001-X1001) | Z1001: =IF($AB1001="","",S1001+V1001+Q1001) | AA1001: =IF($AB1001="","",Z1001-X1001-M1001) | AB1001: =IF(ROWS($AB$2:$AB1001)<=MAX('Per Line'!$AK$2:$AK$4001),MATCH(ROWS($AB$2:$AB1001),'Per Line'!$AK$2:$AK$4001,0),"") | AC1001: =IF($AB1001="","",M1001-L1001*Z1001/100)
