Workbook

Sheet How To Use
A1: Claims Template - MEDNET (Walk In)
A3: Monthly steps
A4: 1. Open the 'Per Line' tab. Delete the old data in the BLUE columns only (row 2 down). Never delete the green or grey columns.
A5: 2. Paste the new month's data as VALUES starting at A2, into the blue columns: A-E, G-J, N-T, V (same order as the system export).
A6: 3. Green columns (F, K, L, M, U) and the grey helper columns (W-Z) calculate automatically - do not paste over them.
A7: 4. 'Per Invoice' fills itself from 'Per Line' (one row per POS Reference, split into IMP / Local). No pivot table, no refresh.
A8: 5. The ONLY manual column in 'Per Invoice' is column B 'Invoice' (blue): type it yourself. Everything else is formula.
A9: 6. Open 'Settings' and check STATUS says OK (Per Line totals = Per Invoice totals).
A11: Colour legend
A12: Blue header = typed/pasted by you (raw data, and 'Invoice' in Per Invoice). Green header = formula (do not paste over). Grey header = helper formula (do not touch). Yellow cell (Settings) = editable rate.
A14: Calculation rules (taken from the September 2026 sheet)
A15: Co val = Co Payment % x Total / 100. Discount = Total x Rebates (Rebates is a fraction here, e.g. 0.14). Subtotal = Total - Discount. Net = Subtotal - Co val. (Total = 'Total Delivered')
... A20: Capacity: up to 500 lines and 200 invoices per month. A line with an empty POS Reference is ignored.

Sheet Settings
B1: Company settings & checks
B3: Insurance Company | C3: MEDNET | D3: Informational only
B4: Corporate | C4: - | D4: Informational only
B5: Sheet type | C5: Walk In | D5: Informational only
B6: Local products rebate % | C6: 0.14 | D6: Source: Sep sheet (Rebates = 0.14 on Local lines).
B7: Imported (IMP) products rebate % | C7: 0.05 | D7: NOT in the Walk In sheet (only Local lines that month). 5% is the Mednet Chronic/VPN imported rate - confirm it for Walk In.
B9: Month totals / reconciliation
B10: Lines loaded | C10: =COUNTA('Per Line'!$A$2:$A$501)
B11: Invoices (unique Order #) | C11: =MAX('Per Line'!$X$2:$X$501)
B12: Invoices shown in Per Invoice | C12: =SUMPRODUCT(--('Per Invoice'!$A$2:$A$201<>""))
B13: Grand Total - Per Line (Product Total) | C13: =SUM('Per Line'!$N$2:$N$501)
B14: Grand Total - Per Invoice | C14: =SUM('Per Invoice'!$T$2:$T$201)
B15: Discount - Per Line | C15: =SUM('Per Line'!$K$2:$K$501)
B16: Discount - Per Invoice | C16: =SUM('Per Invoice'!$R$2:$R$201)
B17: Co val - Per Line | C17: =SUM('Per Line'!$F$2:$F$501)
B18: Co val - Per Invoice | C18: =SUM('Per Invoice'!$G$2:$G$201)
B19: Net - Per Line | C19: =SUM('Per Line'!$M$2:$M$501)
B20: Net - Per Invoice | C20: =SUM('Per Invoice'!$U$2:$U$201)
B21: Max Limit adjustment (Co val, Per Invoice only) | C21: 0 | D21: This company's Per Invoice has no Max Limit rule.
B23: STATUS | C23: =IF(C10=0,"No data loaded",IF(COUNTA('Per Line'!$A:$A)-1>500,"TOO MANY LINES - extend template",IF(C11>200,"TOO MANY INVOICES - extend template",IF(AND(ROUND(C13-C14,2)=0,ROUND(C15-C16,2)=0,ROUND(C17+C21-C18,2)=0,ROUND(C19-C21-C20,2)=0,C11=C12),"OK","CHECK - Per Line and Per Invoice do not match")))) | D23: Must say OK after you paste the month data.

Sheet Per Line
A1: Pos Reference | B1: Insurance Company | C1: Name | D1: Card Number | E1: Co Payment % | F1: Co val | G1: Heisenberg id | H1: Product | I1: Delivered Qty | J1: Delivered Price | K1: Discount | L1: Subtotal | M1: Net | N1: Total Delivered | O1: Order Amount Total | P1: Payment Amount | Q1: Payment Type | R1: Session | S1: Create Date | T1: Order Reference | U1: Rebates | V1: Product Template - Product Tmpl → Is Local | W1: Order 1st Row (helper) | X1: Invoice # (helper) | Y1: Is Local (helper) | Z1: Sort Key (helper)
F2: =IF($A2="","",E2*N2/100) | K2: =IF($A2="","",U2*N2) | L2: =IF($A2="","",N2-K2) | M2: =IF($A2="","",L2-F2) | U2: =IF($A2="","",IF($Y2=1,Settings!$C$6,Settings!$C$7)*1) | W2: =IF($A2="","",IF(COUNTIF($A$2:$A2,$A2)=1,1,0)) | X2: =IF($W2=1,SUMPRODUCT(--($Z$2:$Z$501<$Z2))+1,"") | Y2: =IF($A2="","",IF(OR($V2=TRUE(),$V2="TRUE"),1,0)) | Z2: =IF($W2=1,IFERROR(IF(VALUE($A2)<100000000,VALUE($A2),1000000000),IFERROR(IF(VALUE(MID($A2,2,20))<100000000,VALUE(MID($A2,2,20)),1000000000),1000000000))+ROW()/100000,"")
F3: =IF($A3="","",E3*N3/100) | K3: =IF($A3="","",U3*N3) | L3: =IF($A3="","",N3-K3) | M3: =IF($A3="","",L3-F3) | U3: =IF($A3="","",IF($Y3=1,Settings!$C$6,Settings!$C$7)*1) | W3: =IF($A3="","",IF(COUNTIF($A$2:$A3,$A3)=1,1,0)) | X3: =IF($W3=1,SUMPRODUCT(--($Z$2:$Z$501<$Z3))+1,"") | Y3: =IF($A3="","",IF(OR($V3=TRUE(),$V3="TRUE"),1,0)) | Z3: =IF($W3=1,IFERROR(IF(VALUE($A3)<100000000,VALUE($A3),1000000000),IFERROR(IF(VALUE(MID($A3,2,20))<100000000,VALUE(MID($A3,2,20)),1000000000),1000000000))+ROW()/100000,"")
F4: =IF($A4="","",E4*N4/100) | K4: =IF($A4="","",U4*N4) | L4: =IF($A4="","",N4-K4) | M4: =IF($A4="","",L4-F4) | U4: =IF($A4="","",IF($Y4=1,Settings!$C$6,Settings!$C$7)*1) | W4: =IF($A4="","",IF(COUNTIF($A$2:$A4,$A4)=1,1,0)) | X4: =IF($W4=1,SUMPRODUCT(--($Z$2:$Z$501<$Z4))+1,"") | Y4: =IF($A4="","",IF(OR($V4=TRUE(),$V4="TRUE"),1,0)) | Z4: =IF($W4=1,IFERROR(IF(VALUE($A4)<100000000,VALUE($A4),1000000000),IFERROR(IF(VALUE(MID($A4,2,20))<100000000,VALUE(MID($A4,2,20)),1000000000),1000000000))+ROW()/100000,"")
F5: =IF($A5="","",E5*N5/100) | K5: =IF($A5="","",U5*N5) | L5: =IF($A5="","",N5-K5) | M5: =IF($A5="","",L5-F5) | U5: =IF($A5="","",IF($Y5=1,Settings!$C$6,Settings!$C$7)*1) | W5: =IF($A5="","",IF(COUNTIF($A$2:$A5,$A5)=1,1,0)) | X5: =IF($W5=1,SUMPRODUCT(--($Z$2:$Z$501<$Z5))+1,"") | Y5: =IF($A5="","",IF(OR($V5=TRUE(),$V5="TRUE"),1,0)) | Z5: =IF($W5=1,IFERROR(IF(VALUE($A5)<100000000,VALUE($A5),1000000000),IFERROR(IF(VALUE(MID($A5,2,20))<100000000,VALUE(MID($A5,2,20)),1000000000),1000000000))+ROW()/100000,"")
F6: =IF($A6="","",E6*N6/100) | K6: =IF($A6="","",U6*N6) | L6: =IF($A6="","",N6-K6) | M6: =IF($A6="","",L6-F6) | U6: =IF($A6="","",IF($Y6=1,Settings!$C$6,Settings!$C$7)*1) | W6: =IF($A6="","",IF(COUNTIF($A$2:$A6,$A6)=1,1,0)) | X6: =IF($W6=1,SUMPRODUCT(--($Z$2:$Z$501<$Z6))+1,"") | Y6: =IF($A6="","",IF(OR($V6=TRUE(),$V6="TRUE"),1,0)) | Z6: =IF($W6=1,IFERROR(IF(VALUE($A6)<100000000,VALUE($A6),1000000000),IFERROR(IF(VALUE(MID($A6,2,20))<100000000,VALUE(MID($A6,2,20)),1000000000),1000000000))+ROW()/100000,"")
F7: =IF($A7="","",E7*N7/100) | K7: =IF($A7="","",U7*N7) | L7: =IF($A7="","",N7-K7) | M7: =IF($A7="","",L7-F7) | U7: =IF($A7="","",IF($Y7=1,Settings!$C$6,Settings!$C$7)*1) | W7: =IF($A7="","",IF(COUNTIF($A$2:$A7,$A7)=1,1,0)) | X7: =IF($W7=1,SUMPRODUCT(--($Z$2:$Z$501<$Z7))+1,"") | Y7: =IF($A7="","",IF(OR($V7=TRUE(),$V7="TRUE"),1,0)) | Z7: =IF($W7=1,IFERROR(IF(VALUE($A7)<100000000,VALUE($A7),1000000000),IFERROR(IF(VALUE(MID($A7,2,20))<100000000,VALUE(MID($A7,2,20)),1000000000),1000000000))+ROW()/100000,"")
F8: =IF($A8="","",E8*N8/100) | K8: =IF($A8="","",U8*N8) | L8: =IF($A8="","",N8-K8) | M8: =IF($A8="","",L8-F8) | U8: =IF($A8="","",IF($Y8=1,Settings!$C$6,Settings!$C$7)*1) | W8: =IF($A8="","",IF(COUNTIF($A$2:$A8,$A8)=1,1,0)) | X8: =IF($W8=1,SUMPRODUCT(--($Z$2:$Z$501<$Z8))+1,"") | Y8: =IF($A8="","",IF(OR($V8=TRUE(),$V8="TRUE"),1,0)) | Z8: =IF($W8=1,IFERROR(IF(VALUE($A8)<100000000,VALUE($A8),1000000000),IFERROR(IF(VALUE(MID($A8,2,20))<100000000,VALUE(MID($A8,2,20)),1000000000),1000000000))+ROW()/100000,"")
F9: =IF($A9="","",E9*N9/100) | K9: =IF($A9="","",U9*N9) | L9: =IF($A9="","",N9-K9) | M9: =IF($A9="","",L9-F9) | U9: =IF($A9="","",IF($Y9=1,Settings!$C$6,Settings!$C$7)*1) | W9: =IF($A9="","",IF(COUNTIF($A$2:$A9,$A9)=1,1,0)) | X9: =IF($W9=1,SUMPRODUCT(--($Z$2:$Z$501<$Z9))+1,"") | Y9: =IF($A9="","",IF(OR($V9=TRUE(),$V9="TRUE"),1,0)) | Z9: =IF($W9=1,IFERROR(IF(VALUE($A9)<100000000,VALUE($A9),1000000000),IFERROR(IF(VALUE(MID($A9,2,20))<100000000,VALUE(MID($A9,2,20)),1000000000),1000000000))+ROW()/100000,"")
F10: =IF($A10="","",E10*N10/100) | K10: =IF($A10="","",U10*N10) | L10: =IF($A10="","",N10-K10) | M10: =IF($A10="","",L10-F10) | U10: =IF($A10="","",IF($Y10=1,Settings!$C$6,Settings!$C$7)*1) | W10: =IF($A10="","",IF(COUNTIF($A$2:$A10,$A10)=1,1,0)) | X10: =IF($W10=1,SUMPRODUCT(--($Z$2:$Z$501<$Z10))+1,"") | Y10: =IF($A10="","",IF(OR($V10=TRUE(),$V10="TRUE"),1,0)) | Z10: =IF($W10=1,IFERROR(IF(VALUE($A10)<100000000,VALUE($A10),1000000000),IFERROR(IF(VALUE(MID($A10,2,20))<100000000,VALUE(MID($A10,2,20)),1000000000),1000000000))+ROW()/100000,"")
F11: =IF($A11="","",E11*N11/100) | K11: =IF($A11="","",U11*N11) | L11: =IF($A11="","",N11-K11) | M11: =IF($A11="","",L11-F11) | U11: =IF($A11="","",IF($Y11=1,Settings!$C$6,Settings!$C$7)*1) | W11: =IF($A11="","",IF(COUNTIF($A$2:$A11,$A11)=1,1,0)) | X11: =IF($W11=1,SUMPRODUCT(--($Z$2:$Z$501<$Z11))+1,"") | Y11: =IF($A11="","",IF(OR($V11=TRUE(),$V11="TRUE"),1,0)) | Z11: =IF($W11=1,IFERROR(IF(VALUE($A11)<100000000,VALUE($A11),1000000000),IFERROR(IF(VALUE(MID($A11,2,20))<100000000,VALUE(MID($A11,2,20)),1000000000),1000000000))+ROW()/100000,"")
F12: =IF($A12="","",E12*N12/100) | K12: =IF($A12="","",U12*N12) | L12: =IF($A12="","",N12-K12) | M12: =IF($A12="","",L12-F12) | U12: =IF($A12="","",IF($Y12=1,Settings!$C$6,Settings!$C$7)*1) | W12: =IF($A12="","",IF(COUNTIF($A$2:$A12,$A12)=1,1,0)) | X12: =IF($W12=1,SUMPRODUCT(--($Z$2:$Z$501<$Z12))+1,"") | Y12: =IF($A12="","",IF(OR($V12=TRUE(),$V12="TRUE"),1,0)) | Z12: =IF($W12=1,IFERROR(IF(VALUE($A12)<100000000,VALUE($A12),1000000000),IFERROR(IF(VALUE(MID($A12,2,20))<100000000,VALUE(MID($A12,2,20)),1000000000),1000000000))+ROW()/100000,"")
F13: =IF($A13="","",E13*N13/100) | K13: =IF($A13="","",U13*N13) | L13: =IF($A13="","",N13-K13) | M13: =IF($A13="","",L13-F13) | U13: =IF($A13="","",IF($Y13=1,Settings!$C$6,Settings!$C$7)*1) | W13: =IF($A13="","",IF(COUNTIF($A$2:$A13,$A13)=1,1,0)) | X13: =IF($W13=1,SUMPRODUCT(--($Z$2:$Z$501<$Z13))+1,"") | Y13: =IF($A13="","",IF(OR($V13=TRUE(),$V13="TRUE"),1,0)) | Z13: =IF($W13=1,IFERROR(IF(VALUE($A13)<100000000,VALUE($A13),1000000000),IFERROR(IF(VALUE(MID($A13,2,20))<100000000,VALUE(MID($A13,2,20)),1000000000),1000000000))+ROW()/100000,"")
... F501: =IF($A501="","",E501*N501/100) | K501: =IF($A501="","",U501*N501) | L501: =IF($A501="","",N501-K501) | M501: =IF($A501="","",L501-F501) | U501: =IF($A501="","",IF($Y501=1,Settings!$C$6,Settings!$C$7)*1) | W501: =IF($A501="","",IF(COUNTIF($A$2:$A501,$A501)=1,1,0)) | X501: =IF($W501=1,SUMPRODUCT(--($Z$2:$Z$501<$Z501))+1,"") | Y501: =IF($A501="","",IF(OR($V501=TRUE(),$V501="TRUE"),1,0)) | Z501: =IF($W501=1,IFERROR(IF(VALUE($A501)<100000000,VALUE($A501),1000000000),IFERROR(IF(VALUE(MID($A501,2,20))<100000000,VALUE(MID($A501,2,20)),1000000000),1000000000))+ROW()/100000,"")

Sheet Per Invoice
A1: Pos Reference | B1: Invoice | C1: Insurance Company | D1: Name | E1: Card Number | F1: Co Payment % | G1: Co val | H1: Payment Type | I1: Session | J1: Create Date | K1: Order Reference | L1: Imp % | M1: Imp | N1: Imp Val | O1: LOC % | P1: LOC | Q1: LOC VAL | R1: TOTAL VAL | S1: SUBTOTAL | T1: Grand Total | U1: NET | V1: Src Row (helper)
A2: =IF($V2="","",INDEX('Per Line'!$A$2:$A$501,$V2)&"") | C2: =IF($V2="","",INDEX('Per Line'!$B$2:$B$501,$V2)&"") | D2: =IF($V2="","",INDEX('Per Line'!$C$2:$C$501,$V2)&"") | E2: =IF($V2="","",INDEX('Per Line'!$D$2:$D$501,$V2)&"") | F2: =IF($V2="","",INDEX('Per Line'!$E$2:$E$501,$V2)) | G2: =IF($V2="","",F2*T2/100) | H2: =IF($V2="","",INDEX('Per Line'!$Q$2:$Q$501,$V2)&"") | I2: =IF($V2="","",INDEX('Per Line'!$R$2:$R$501,$V2)&"") | J2: =IF($V2="","",INDEX('Per Line'!$S$2:$S$501,$V2)) | K2: =IF($V2="","",INDEX('Per Line'!$T$2:$T$501,$V2)&"") | L2: =IF($V2="","",Settings!$C$7) | M2: =IF($V2="","",SUMIFS('Per Line'!$N$2:$N$501,'Per Line'!$A$2:$A$501,$A2,'Per Line'!$Y$2:$Y$501,0)) | N2: =IF($V2="","",M2*L2) | O2: =IF($V2="","",Settings!$C$6) | P2: =IF($V2="","",SUMIFS('Per Line'!$N$2:$N$501,'Per Line'!$A$2:$A$501,$A2,'Per Line'!$Y$2:$Y$501,1)) | Q2: =IF($V2="","",P2*O2) | R2: =IF($V2="","",Q2+N2) | S2: =IF($V2="","",T2-R2) | T2: =IF($V2="","",M2+P2) | U2: =IF($V2="","",T2-R2-G2) | V2: =IF(ROWS($V$2:$V2)<=MAX('Per Line'!$X$2:$X$501),MATCH(ROWS($V$2:$V2),'Per Line'!$X$2:$X$501,0),"")
A3: =IF($V3="","",INDEX('Per Line'!$A$2:$A$501,$V3)&"") | C3: =IF($V3="","",INDEX('Per Line'!$B$2:$B$501,$V3)&"") | D3: =IF($V3="","",INDEX('Per Line'!$C$2:$C$501,$V3)&"") | E3: =IF($V3="","",INDEX('Per Line'!$D$2:$D$501,$V3)&"") | F3: =IF($V3="","",INDEX('Per Line'!$E$2:$E$501,$V3)) | G3: =IF($V3="","",F3*T3/100) | H3: =IF($V3="","",INDEX('Per Line'!$Q$2:$Q$501,$V3)&"") | I3: =IF($V3="","",INDEX('Per Line'!$R$2:$R$501,$V3)&"") | J3: =IF($V3="","",INDEX('Per Line'!$S$2:$S$501,$V3)) | K3: =IF($V3="","",INDEX('Per Line'!$T$2:$T$501,$V3)&"") | L3: =IF($V3="","",Settings!$C$7) | M3: =IF($V3="","",SUMIFS('Per Line'!$N$2:$N$501,'Per Line'!$A$2:$A$501,$A3,'Per Line'!$Y$2:$Y$501,0)) | N3: =IF($V3="","",M3*L3) | O3: =IF($V3="","",Settings!$C$6) | P3: =IF($V3="","",SUMIFS('Per Line'!$N$2:$N$501,'Per Line'!$A$2:$A$501,$A3,'Per Line'!$Y$2:$Y$501,1)) | Q3: =IF($V3="","",P3*O3) | R3: =IF($V3="","",Q3+N3) | S3: =IF($V3="","",T3-R3) | T3: =IF($V3="","",M3+P3) | U3: =IF($V3="","",T3-R3-G3) | V3: =IF(ROWS($V$2:$V3)<=MAX('Per Line'!$X$2:$X$501),MATCH(ROWS($V$2:$V3),'Per Line'!$X$2:$X$501,0),"")
A4: =IF($V4="","",INDEX('Per Line'!$A$2:$A$501,$V4)&"") | C4: =IF($V4="","",INDEX('Per Line'!$B$2:$B$501,$V4)&"") | D4: =IF($V4="","",INDEX('Per Line'!$C$2:$C$501,$V4)&"") | E4: =IF($V4="","",INDEX('Per Line'!$D$2:$D$501,$V4)&"") | F4: =IF($V4="","",INDEX('Per Line'!$E$2:$E$501,$V4)) | G4: =IF($V4="","",F4*T4/100) | H4: =IF($V4="","",INDEX('Per Line'!$Q$2:$Q$501,$V4)&"") | I4: =IF($V4="","",INDEX('Per Line'!$R$2:$R$501,$V4)&"") | J4: =IF($V4="","",INDEX('Per Line'!$S$2:$S$501,$V4)) | K4: =IF($V4="","",INDEX('Per Line'!$T$2:$T$501,$V4)&"") | L4: =IF($V4="","",Settings!$C$7) | M4: =IF($V4="","",SUMIFS('Per Line'!$N$2:$N$501,'Per Line'!$A$2:$A$501,$A4,'Per Line'!$Y$2:$Y$501,0)) | N4: =IF($V4="","",M4*L4) | O4: =IF($V4="","",Settings!$C$6) | P4: =IF($V4="","",SUMIFS('Per Line'!$N$2:$N$501,'Per Line'!$A$2:$A$501,$A4,'Per Line'!$Y$2:$Y$501,1)) | Q4: =IF($V4="","",P4*O4) | R4: =IF($V4="","",Q4+N4) | S4: =IF($V4="","",T4-R4) | T4: =IF($V4="","",M4+P4) | U4: =IF($V4="","",T4-R4-G4) | V4: =IF(ROWS($V$2:$V4)<=MAX('Per Line'!$X$2:$X$501),MATCH(ROWS($V$2:$V4),'Per Line'!$X$2:$X$501,0),"")
A5: =IF($V5="","",INDEX('Per Line'!$A$2:$A$501,$V5)&"") | C5: =IF($V5="","",INDEX('Per Line'!$B$2:$B$501,$V5)&"") | D5: =IF($V5="","",INDEX('Per Line'!$C$2:$C$501,$V5)&"") | E5: =IF($V5="","",INDEX('Per Line'!$D$2:$D$501,$V5)&"") | F5: =IF($V5="","",INDEX('Per Line'!$E$2:$E$501,$V5)) | G5: =IF($V5="","",F5*T5/100) | H5: =IF($V5="","",INDEX('Per Line'!$Q$2:$Q$501,$V5)&"") | I5: =IF($V5="","",INDEX('Per Line'!$R$2:$R$501,$V5)&"") | J5: =IF($V5="","",INDEX('Per Line'!$S$2:$S$501,$V5)) | K5: =IF($V5="","",INDEX('Per Line'!$T$2:$T$501,$V5)&"") | L5: =IF($V5="","",Settings!$C$7) | M5: =IF($V5="","",SUMIFS('Per Line'!$N$2:$N$501,'Per Line'!$A$2:$A$501,$A5,'Per Line'!$Y$2:$Y$501,0)) | N5: =IF($V5="","",M5*L5) | O5: =IF($V5="","",Settings!$C$6) | P5: =IF($V5="","",SUMIFS('Per Line'!$N$2:$N$501,'Per Line'!$A$2:$A$501,$A5,'Per Line'!$Y$2:$Y$501,1)) | Q5: =IF($V5="","",P5*O5) | R5: =IF($V5="","",Q5+N5) | S5: =IF($V5="","",T5-R5) | T5: =IF($V5="","",M5+P5) | U5: =IF($V5="","",T5-R5-G5) | V5: =IF(ROWS($V$2:$V5)<=MAX('Per Line'!$X$2:$X$501),MATCH(ROWS($V$2:$V5),'Per Line'!$X$2:$X$501,0),"")
A6: =IF($V6="","",INDEX('Per Line'!$A$2:$A$501,$V6)&"") | C6: =IF($V6="","",INDEX('Per Line'!$B$2:$B$501,$V6)&"") | D6: =IF($V6="","",INDEX('Per Line'!$C$2:$C$501,$V6)&"") | E6: =IF($V6="","",INDEX('Per Line'!$D$2:$D$501,$V6)&"") | F6: =IF($V6="","",INDEX('Per Line'!$E$2:$E$501,$V6)) | G6: =IF($V6="","",F6*T6/100) | H6: =IF($V6="","",INDEX('Per Line'!$Q$2:$Q$501,$V6)&"") | I6: =IF($V6="","",INDEX('Per Line'!$R$2:$R$501,$V6)&"") | J6: =IF($V6="","",INDEX('Per Line'!$S$2:$S$501,$V6)) | K6: =IF($V6="","",INDEX('Per Line'!$T$2:$T$501,$V6)&"") | L6: =IF($V6="","",Settings!$C$7) | M6: =IF($V6="","",SUMIFS('Per Line'!$N$2:$N$501,'Per Line'!$A$2:$A$501,$A6,'Per Line'!$Y$2:$Y$501,0)) | N6: =IF($V6="","",M6*L6) | O6: =IF($V6="","",Settings!$C$6) | P6: =IF($V6="","",SUMIFS('Per Line'!$N$2:$N$501,'Per Line'!$A$2:$A$501,$A6,'Per Line'!$Y$2:$Y$501,1)) | Q6: =IF($V6="","",P6*O6) | R6: =IF($V6="","",Q6+N6) | S6: =IF($V6="","",T6-R6) | T6: =IF($V6="","",M6+P6) | U6: =IF($V6="","",T6-R6-G6) | V6: =IF(ROWS($V$2:$V6)<=MAX('Per Line'!$X$2:$X$501),MATCH(ROWS($V$2:$V6),'Per Line'!$X$2:$X$501,0),"")
A7: =IF($V7="","",INDEX('Per Line'!$A$2:$A$501,$V7)&"") | C7: =IF($V7="","",INDEX('Per Line'!$B$2:$B$501,$V7)&"") | D7: =IF($V7="","",INDEX('Per Line'!$C$2:$C$501,$V7)&"") | E7: =IF($V7="","",INDEX('Per Line'!$D$2:$D$501,$V7)&"") | F7: =IF($V7="","",INDEX('Per Line'!$E$2:$E$501,$V7)) | G7: =IF($V7="","",F7*T7/100) | H7: =IF($V7="","",INDEX('Per Line'!$Q$2:$Q$501,$V7)&"") | I7: =IF($V7="","",INDEX('Per Line'!$R$2:$R$501,$V7)&"") | J7: =IF($V7="","",INDEX('Per Line'!$S$2:$S$501,$V7)) | K7: =IF($V7="","",INDEX('Per Line'!$T$2:$T$501,$V7)&"") | L7: =IF($V7="","",Settings!$C$7) | M7: =IF($V7="","",SUMIFS('Per Line'!$N$2:$N$501,'Per Line'!$A$2:$A$501,$A7,'Per Line'!$Y$2:$Y$501,0)) | N7: =IF($V7="","",M7*L7) | O7: =IF($V7="","",Settings!$C$6) | P7: =IF($V7="","",SUMIFS('Per Line'!$N$2:$N$501,'Per Line'!$A$2:$A$501,$A7,'Per Line'!$Y$2:$Y$501,1)) | Q7: =IF($V7="","",P7*O7) | R7: =IF($V7="","",Q7+N7) | S7: =IF($V7="","",T7-R7) | T7: =IF($V7="","",M7+P7) | U7: =IF($V7="","",T7-R7-G7) | V7: =IF(ROWS($V$2:$V7)<=MAX('Per Line'!$X$2:$X$501),MATCH(ROWS($V$2:$V7),'Per Line'!$X$2:$X$501,0),"")
A8: =IF($V8="","",INDEX('Per Line'!$A$2:$A$501,$V8)&"") | C8: =IF($V8="","",INDEX('Per Line'!$B$2:$B$501,$V8)&"") | D8: =IF($V8="","",INDEX('Per Line'!$C$2:$C$501,$V8)&"") | E8: =IF($V8="","",INDEX('Per Line'!$D$2:$D$501,$V8)&"") | F8: =IF($V8="","",INDEX('Per Line'!$E$2:$E$501,$V8)) | G8: =IF($V8="","",F8*T8/100) | H8: =IF($V8="","",INDEX('Per Line'!$Q$2:$Q$501,$V8)&"") | I8: =IF($V8="","",INDEX('Per Line'!$R$2:$R$501,$V8)&"") | J8: =IF($V8="","",INDEX('Per Line'!$S$2:$S$501,$V8)) | K8: =IF($V8="","",INDEX('Per Line'!$T$2:$T$501,$V8)&"") | L8: =IF($V8="","",Settings!$C$7) | M8: =IF($V8="","",SUMIFS('Per Line'!$N$2:$N$501,'Per Line'!$A$2:$A$501,$A8,'Per Line'!$Y$2:$Y$501,0)) | N8: =IF($V8="","",M8*L8) | O8: =IF($V8="","",Settings!$C$6) | P8: =IF($V8="","",SUMIFS('Per Line'!$N$2:$N$501,'Per Line'!$A$2:$A$501,$A8,'Per Line'!$Y$2:$Y$501,1)) | Q8: =IF($V8="","",P8*O8) | R8: =IF($V8="","",Q8+N8) | S8: =IF($V8="","",T8-R8) | T8: =IF($V8="","",M8+P8) | U8: =IF($V8="","",T8-R8-G8) | V8: =IF(ROWS($V$2:$V8)<=MAX('Per Line'!$X$2:$X$501),MATCH(ROWS($V$2:$V8),'Per Line'!$X$2:$X$501,0),"")
A9: =IF($V9="","",INDEX('Per Line'!$A$2:$A$501,$V9)&"") | C9: =IF($V9="","",INDEX('Per Line'!$B$2:$B$501,$V9)&"") | D9: =IF($V9="","",INDEX('Per Line'!$C$2:$C$501,$V9)&"") | E9: =IF($V9="","",INDEX('Per Line'!$D$2:$D$501,$V9)&"") | F9: =IF($V9="","",INDEX('Per Line'!$E$2:$E$501,$V9)) | G9: =IF($V9="","",F9*T9/100) | H9: =IF($V9="","",INDEX('Per Line'!$Q$2:$Q$501,$V9)&"") | I9: =IF($V9="","",INDEX('Per Line'!$R$2:$R$501,$V9)&"") | J9: =IF($V9="","",INDEX('Per Line'!$S$2:$S$501,$V9)) | K9: =IF($V9="","",INDEX('Per Line'!$T$2:$T$501,$V9)&"") | L9: =IF($V9="","",Settings!$C$7) | M9: =IF($V9="","",SUMIFS('Per Line'!$N$2:$N$501,'Per Line'!$A$2:$A$501,$A9,'Per Line'!$Y$2:$Y$501,0)) | N9: =IF($V9="","",M9*L9) | O9: =IF($V9="","",Settings!$C$6) | P9: =IF($V9="","",SUMIFS('Per Line'!$N$2:$N$501,'Per Line'!$A$2:$A$501,$A9,'Per Line'!$Y$2:$Y$501,1)) | Q9: =IF($V9="","",P9*O9) | R9: =IF($V9="","",Q9+N9) | S9: =IF($V9="","",T9-R9) | T9: =IF($V9="","",M9+P9) | U9: =IF($V9="","",T9-R9-G9) | V9: =IF(ROWS($V$2:$V9)<=MAX('Per Line'!$X$2:$X$501),MATCH(ROWS($V$2:$V9),'Per Line'!$X$2:$X$501,0),"")
A10: =IF($V10="","",INDEX('Per Line'!$A$2:$A$501,$V10)&"") | C10: =IF($V10="","",INDEX('Per Line'!$B$2:$B$501,$V10)&"") | D10: =IF($V10="","",INDEX('Per Line'!$C$2:$C$501,$V10)&"") | E10: =IF($V10="","",INDEX('Per Line'!$D$2:$D$501,$V10)&"") | F10: =IF($V10="","",INDEX('Per Line'!$E$2:$E$501,$V10)) | G10: =IF($V10="","",F10*T10/100) | H10: =IF($V10="","",INDEX('Per Line'!$Q$2:$Q$501,$V10)&"") | I10: =IF($V10="","",INDEX('Per Line'!$R$2:$R$501,$V10)&"") | J10: =IF($V10="","",INDEX('Per Line'!$S$2:$S$501,$V10)) | K10: =IF($V10="","",INDEX('Per Line'!$T$2:$T$501,$V10)&"") | L10: =IF($V10="","",Settings!$C$7) | M10: =IF($V10="","",SUMIFS('Per Line'!$N$2:$N$501,'Per Line'!$A$2:$A$501,$A10,'Per Line'!$Y$2:$Y$501,0)) | N10: =IF($V10="","",M10*L10) | O10: =IF($V10="","",Settings!$C$6) | P10: =IF($V10="","",SUMIFS('Per Line'!$N$2:$N$501,'Per Line'!$A$2:$A$501,$A10,'Per Line'!$Y$2:$Y$501,1)) | Q10: =IF($V10="","",P10*O10) | R10: =IF($V10="","",Q10+N10) | S10: =IF($V10="","",T10-R10) | T10: =IF($V10="","",M10+P10) | U10: =IF($V10="","",T10-R10-G10) | V10: =IF(ROWS($V$2:$V10)<=MAX('Per Line'!$X$2:$X$501),MATCH(ROWS($V$2:$V10),'Per Line'!$X$2:$X$501,0),"")
A11: =IF($V11="","",INDEX('Per Line'!$A$2:$A$501,$V11)&"") | C11: =IF($V11="","",INDEX('Per Line'!$B$2:$B$501,$V11)&"") | D11: =IF($V11="","",INDEX('Per Line'!$C$2:$C$501,$V11)&"") | E11: =IF($V11="","",INDEX('Per Line'!$D$2:$D$501,$V11)&"") | F11: =IF($V11="","",INDEX('Per Line'!$E$2:$E$501,$V11)) | G11: =IF($V11="","",F11*T11/100) | H11: =IF($V11="","",INDEX('Per Line'!$Q$2:$Q$501,$V11)&"") | I11: =IF($V11="","",INDEX('Per Line'!$R$2:$R$501,$V11)&"") | J11: =IF($V11="","",INDEX('Per Line'!$S$2:$S$501,$V11)) | K11: =IF($V11="","",INDEX('Per Line'!$T$2:$T$501,$V11)&"") | L11: =IF($V11="","",Settings!$C$7) | M11: =IF($V11="","",SUMIFS('Per Line'!$N$2:$N$501,'Per Line'!$A$2:$A$501,$A11,'Per Line'!$Y$2:$Y$501,0)) | N11: =IF($V11="","",M11*L11) | O11: =IF($V11="","",Settings!$C$6) | P11: =IF($V11="","",SUMIFS('Per Line'!$N$2:$N$501,'Per Line'!$A$2:$A$501,$A11,'Per Line'!$Y$2:$Y$501,1)) | Q11: =IF($V11="","",P11*O11) | R11: =IF($V11="","",Q11+N11) | S11: =IF($V11="","",T11-R11) | T11: =IF($V11="","",M11+P11) | U11: =IF($V11="","",T11-R11-G11) | V11: =IF(ROWS($V$2:$V11)<=MAX('Per Line'!$X$2:$X$501),MATCH(ROWS($V$2:$V11),'Per Line'!$X$2:$X$501,0),"")
A12: =IF($V12="","",INDEX('Per Line'!$A$2:$A$501,$V12)&"") | C12: =IF($V12="","",INDEX('Per Line'!$B$2:$B$501,$V12)&"") | D12: =IF($V12="","",INDEX('Per Line'!$C$2:$C$501,$V12)&"") | E12: =IF($V12="","",INDEX('Per Line'!$D$2:$D$501,$V12)&"") | F12: =IF($V12="","",INDEX('Per Line'!$E$2:$E$501,$V12)) | G12: =IF($V12="","",F12*T12/100) | H12: =IF($V12="","",INDEX('Per Line'!$Q$2:$Q$501,$V12)&"") | I12: =IF($V12="","",INDEX('Per Line'!$R$2:$R$501,$V12)&"") | J12: =IF($V12="","",INDEX('Per Line'!$S$2:$S$501,$V12)) | K12: =IF($V12="","",INDEX('Per Line'!$T$2:$T$501,$V12)&"") | L12: =IF($V12="","",Settings!$C$7) | M12: =IF($V12="","",SUMIFS('Per Line'!$N$2:$N$501,'Per Line'!$A$2:$A$501,$A12,'Per Line'!$Y$2:$Y$501,0)) | N12: =IF($V12="","",M12*L12) | O12: =IF($V12="","",Settings!$C$6) | P12: =IF($V12="","",SUMIFS('Per Line'!$N$2:$N$501,'Per Line'!$A$2:$A$501,$A12,'Per Line'!$Y$2:$Y$501,1)) | Q12: =IF($V12="","",P12*O12) | R12: =IF($V12="","",Q12+N12) | S12: =IF($V12="","",T12-R12) | T12: =IF($V12="","",M12+P12) | U12: =IF($V12="","",T12-R12-G12) | V12: =IF(ROWS($V$2:$V12)<=MAX('Per Line'!$X$2:$X$501),MATCH(ROWS($V$2:$V12),'Per Line'!$X$2:$X$501,0),"")
A13: =IF($V13="","",INDEX('Per Line'!$A$2:$A$501,$V13)&"") | C13: =IF($V13="","",INDEX('Per Line'!$B$2:$B$501,$V13)&"") | D13: =IF($V13="","",INDEX('Per Line'!$C$2:$C$501,$V13)&"") | E13: =IF($V13="","",INDEX('Per Line'!$D$2:$D$501,$V13)&"") | F13: =IF($V13="","",INDEX('Per Line'!$E$2:$E$501,$V13)) | G13: =IF($V13="","",F13*T13/100) | H13: =IF($V13="","",INDEX('Per Line'!$Q$2:$Q$501,$V13)&"") | I13: =IF($V13="","",INDEX('Per Line'!$R$2:$R$501,$V13)&"") | J13: =IF($V13="","",INDEX('Per Line'!$S$2:$S$501,$V13)) | K13: =IF($V13="","",INDEX('Per Line'!$T$2:$T$501,$V13)&"") | L13: =IF($V13="","",Settings!$C$7) | M13: =IF($V13="","",SUMIFS('Per Line'!$N$2:$N$501,'Per Line'!$A$2:$A$501,$A13,'Per Line'!$Y$2:$Y$501,0)) | N13: =IF($V13="","",M13*L13) | O13: =IF($V13="","",Settings!$C$6) | P13: =IF($V13="","",SUMIFS('Per Line'!$N$2:$N$501,'Per Line'!$A$2:$A$501,$A13,'Per Line'!$Y$2:$Y$501,1)) | Q13: =IF($V13="","",P13*O13) | R13: =IF($V13="","",Q13+N13) | S13: =IF($V13="","",T13-R13) | T13: =IF($V13="","",M13+P13) | U13: =IF($V13="","",T13-R13-G13) | V13: =IF(ROWS($V$2:$V13)<=MAX('Per Line'!$X$2:$X$501),MATCH(ROWS($V$2:$V13),'Per Line'!$X$2:$X$501,0),"")
... A201: =IF($V201="","",INDEX('Per Line'!$A$2:$A$501,$V201)&"") | C201: =IF($V201="","",INDEX('Per Line'!$B$2:$B$501,$V201)&"") | D201: =IF($V201="","",INDEX('Per Line'!$C$2:$C$501,$V201)&"") | E201: =IF($V201="","",INDEX('Per Line'!$D$2:$D$501,$V201)&"") | F201: =IF($V201="","",INDEX('Per Line'!$E$2:$E$501,$V201)) | G201: =IF($V201="","",F201*T201/100) | H201: =IF($V201="","",INDEX('Per Line'!$Q$2:$Q$501,$V201)&"") | I201: =IF($V201="","",INDEX('Per Line'!$R$2:$R$501,$V201)&"") | J201: =IF($V201="","",INDEX('Per Line'!$S$2:$S$501,$V201)) | K201: =IF($V201="","",INDEX('Per Line'!$T$2:$T$501,$V201)&"") | L201: =IF($V201="","",Settings!$C$7) | M201: =IF($V201="","",SUMIFS('Per Line'!$N$2:$N$501,'Per Line'!$A$2:$A$501,$A201,'Per Line'!$Y$2:$Y$501,0)) | N201: =IF($V201="","",M201*L201) | O201: =IF($V201="","",Settings!$C$6) | P201: =IF($V201="","",SUMIFS('Per Line'!$N$2:$N$501,'Per Line'!$A$2:$A$501,$A201,'Per Line'!$Y$2:$Y$501,1)) | Q201: =IF($V201="","",P201*O201) | R201: =IF($V201="","",Q201+N201) | S201: =IF($V201="","",T201-R201) | T201: =IF($V201="","",M201+P201) | U201: =IF($V201="","",T201-R201-G201) | V201: =IF(ROWS($V$2:$V201)<=MAX('Per Line'!$X$2:$X$501),MATCH(ROWS($V$2:$V201),'Per Line'!$X$2:$X$501,0),"")
