Workbook

Sheet How To Use
A1: Claims Template - MISR HEALTH CARE (Walk In)
A3: Monthly steps
A4: 1. Open the 'Per Line' tab. Delete the old data in the BLUE columns only (row 2 down). Never delete the green or grey columns.
A5: 2. Paste the new month's data as VALUES starting at A2, into the blue columns: A-E, G-K, O-R (same order as the system export).
A6: 3. Green columns (F, L, M, N, S) and the grey helper columns (T-W) calculate automatically - do not paste over them.
A7: 4. 'Per Invoice' fills itself from 'Per Line' (one row per POS Reference, split into IMP / Local). No pivot table, no refresh.
A8: 5. The columns you type yourself in 'Per Invoice' (blue headers): A 'Invoice', C 'approval Refrence'. Everything else is formula. Type them AFTER pasting the month data (they follow the row, not the order).
A9: 6. Open 'Settings' and check STATUS says OK (Per Line totals = Per Invoice totals).
A11: Colour legend
A12: Blue header = typed/pasted by you (raw data, and 'Invoice' in Per Invoice). Green header = formula (do not paste over). Grey header = helper formula (do not touch). Yellow cell (Settings) = editable rate.
A14: Calculation rules (taken from the September 2026 sheet)
A15: Co val = Co Payment % x Total / 100. Discount = Total x Rebates (Rebates is a fraction here, e.g. 0.14). Subtotal = Total - Discount. Net = Subtotal - Co val. (Total = 'Total Delivered')
... A20: Capacity: up to 1,000 lines and 300 invoices per month. A line with an empty POS Reference is ignored.

Sheet Settings
B1: Company settings & checks
B3: Insurance Company | C3: MISR HEALTH CARE | D3: Informational only
B4: Corporate | C4: - | D4: Informational only
B5: Sheet type | C5: Walk In | D5: Informational only
B6: Local products rebate % | C6: 0.12 | D6: Source: Sep sheet (Rebates = 0.12 on Local lines).
B7: Imported (IMP) products rebate % | C7: 0.04 | D7: Source: Sep sheet (Rebates = 0.04 on non-local lines).
B9: Month totals / reconciliation
B10: Lines loaded | C10: =COUNTA('Per Line'!$A$2:$A$1001)
B11: Invoices (unique Order #) | C11: =MAX('Per Line'!$U$2:$U$1001)
B12: Invoices shown in Per Invoice | C12: =SUMPRODUCT(--('Per Invoice'!$B$2:$B$301<>""))
B13: Grand Total - Per Line (Product Total) | C13: =SUM('Per Line'!$K$2:$K$1001)
B14: Grand Total - Per Invoice | C14: =SUM('Per Invoice'!$R$2:$R$301)
B15: Discount - Per Line | C15: =SUM('Per Line'!$L$2:$L$1001)
B16: Discount - Per Invoice | C16: =SUM('Per Invoice'!$P$2:$P$301)
B17: Co val - Per Line | C17: =SUM('Per Line'!$F$2:$F$1001)
B18: Co val - Per Invoice | C18: =SUM('Per Invoice'!$H$2:$H$301)
B19: Net - Per Line | C19: =SUM('Per Line'!$N$2:$N$1001)
B20: Net - Per Invoice | C20: =SUM('Per Invoice'!$S$2:$S$301)
B21: Max Limit adjustment (Co val, Per Invoice only) | C21: 0 | D21: This company's Per Invoice has no Max Limit rule.
B23: STATUS | C23: =IF(C10=0,"No data loaded",IF(COUNTA('Per Line'!$A:$A)-1>1000,"TOO MANY LINES - extend template",IF(C11>300,"TOO MANY INVOICES - extend template",IF(AND(ROUND(C13-C14,2)=0,ROUND(C15-C16,2)=0,ROUND(C17+C21-C18,2)=0,ROUND(C19-C21-C20,2)=0,C11=C12),"OK","CHECK - Per Line and Per Invoice do not match")))) | D23: Must say OK after you paste the month data.

Sheet Per Line
A1: Pos Reference | B1: Insurance Company | C1: Name | D1: Card Number | E1: Co Payment % | F1: Co val | G1: Heisenberg id | H1: Product | I1: Delivered Qty | J1: Delivered Price | K1: Total Delivered | L1: Discount | M1: Subtotal | N1: Net | O1: Payment Type | P1: Session | Q1: Create Date | R1: Product Template - Product Tmpl → Is Local | S1: Rebates | T1: Order 1st Row (helper) | U1: Invoice # (helper) | V1: Is Local (helper) | W1: Sort Key (helper)
F2: =IF($A2="","",E2*K2/100) | L2: =IF($A2="","",S2*K2) | M2: =IF($A2="","",K2-L2) | N2: =IF($A2="","",M2-F2) | S2: =IF($A2="","",IF(AND(ISNUMBER($R2),NOT(ISLOGICAL($R2)),N($R2)>1),$R2/100*1,IF($V2=1,Settings!$C$6,Settings!$C$7)*1)) | T2: =IF($A2="","",IF(COUNTIF($A$2:$A2,$A2)=1,1,0)) | U2: =IF($T2=1,SUMPRODUCT(--($W$2:$W$1001<$W2))+1,"") | V2: =IF($A2="","",IF(AND(ISNUMBER($R2),NOT(ISLOGICAL($R2)),N($R2)>1),IF(ABS($R2/100-Settings!$C$6)<=ABS($R2/100-Settings!$C$7),1,0),IF(OR($R2=TRUE(),$R2="TRUE"),1,0))) | W2: =IF($T2=1,IFERROR(IF(VALUE($A2)<100000000,VALUE($A2),1000000000),IFERROR(IF(VALUE(MID($A2,2,20))<100000000,VALUE(MID($A2,2,20)),1000000000),1000000000))+ROW()/100000,"")
F3: =IF($A3="","",E3*K3/100) | L3: =IF($A3="","",S3*K3) | M3: =IF($A3="","",K3-L3) | N3: =IF($A3="","",M3-F3) | S3: =IF($A3="","",IF(AND(ISNUMBER($R3),NOT(ISLOGICAL($R3)),N($R3)>1),$R3/100*1,IF($V3=1,Settings!$C$6,Settings!$C$7)*1)) | T3: =IF($A3="","",IF(COUNTIF($A$2:$A3,$A3)=1,1,0)) | U3: =IF($T3=1,SUMPRODUCT(--($W$2:$W$1001<$W3))+1,"") | V3: =IF($A3="","",IF(AND(ISNUMBER($R3),NOT(ISLOGICAL($R3)),N($R3)>1),IF(ABS($R3/100-Settings!$C$6)<=ABS($R3/100-Settings!$C$7),1,0),IF(OR($R3=TRUE(),$R3="TRUE"),1,0))) | W3: =IF($T3=1,IFERROR(IF(VALUE($A3)<100000000,VALUE($A3),1000000000),IFERROR(IF(VALUE(MID($A3,2,20))<100000000,VALUE(MID($A3,2,20)),1000000000),1000000000))+ROW()/100000,"")
F4: =IF($A4="","",E4*K4/100) | L4: =IF($A4="","",S4*K4) | M4: =IF($A4="","",K4-L4) | N4: =IF($A4="","",M4-F4) | S4: =IF($A4="","",IF(AND(ISNUMBER($R4),NOT(ISLOGICAL($R4)),N($R4)>1),$R4/100*1,IF($V4=1,Settings!$C$6,Settings!$C$7)*1)) | T4: =IF($A4="","",IF(COUNTIF($A$2:$A4,$A4)=1,1,0)) | U4: =IF($T4=1,SUMPRODUCT(--($W$2:$W$1001<$W4))+1,"") | V4: =IF($A4="","",IF(AND(ISNUMBER($R4),NOT(ISLOGICAL($R4)),N($R4)>1),IF(ABS($R4/100-Settings!$C$6)<=ABS($R4/100-Settings!$C$7),1,0),IF(OR($R4=TRUE(),$R4="TRUE"),1,0))) | W4: =IF($T4=1,IFERROR(IF(VALUE($A4)<100000000,VALUE($A4),1000000000),IFERROR(IF(VALUE(MID($A4,2,20))<100000000,VALUE(MID($A4,2,20)),1000000000),1000000000))+ROW()/100000,"")
F5: =IF($A5="","",E5*K5/100) | L5: =IF($A5="","",S5*K5) | M5: =IF($A5="","",K5-L5) | N5: =IF($A5="","",M5-F5) | S5: =IF($A5="","",IF(AND(ISNUMBER($R5),NOT(ISLOGICAL($R5)),N($R5)>1),$R5/100*1,IF($V5=1,Settings!$C$6,Settings!$C$7)*1)) | T5: =IF($A5="","",IF(COUNTIF($A$2:$A5,$A5)=1,1,0)) | U5: =IF($T5=1,SUMPRODUCT(--($W$2:$W$1001<$W5))+1,"") | V5: =IF($A5="","",IF(AND(ISNUMBER($R5),NOT(ISLOGICAL($R5)),N($R5)>1),IF(ABS($R5/100-Settings!$C$6)<=ABS($R5/100-Settings!$C$7),1,0),IF(OR($R5=TRUE(),$R5="TRUE"),1,0))) | W5: =IF($T5=1,IFERROR(IF(VALUE($A5)<100000000,VALUE($A5),1000000000),IFERROR(IF(VALUE(MID($A5,2,20))<100000000,VALUE(MID($A5,2,20)),1000000000),1000000000))+ROW()/100000,"")
F6: =IF($A6="","",E6*K6/100) | L6: =IF($A6="","",S6*K6) | M6: =IF($A6="","",K6-L6) | N6: =IF($A6="","",M6-F6) | S6: =IF($A6="","",IF(AND(ISNUMBER($R6),NOT(ISLOGICAL($R6)),N($R6)>1),$R6/100*1,IF($V6=1,Settings!$C$6,Settings!$C$7)*1)) | T6: =IF($A6="","",IF(COUNTIF($A$2:$A6,$A6)=1,1,0)) | U6: =IF($T6=1,SUMPRODUCT(--($W$2:$W$1001<$W6))+1,"") | V6: =IF($A6="","",IF(AND(ISNUMBER($R6),NOT(ISLOGICAL($R6)),N($R6)>1),IF(ABS($R6/100-Settings!$C$6)<=ABS($R6/100-Settings!$C$7),1,0),IF(OR($R6=TRUE(),$R6="TRUE"),1,0))) | W6: =IF($T6=1,IFERROR(IF(VALUE($A6)<100000000,VALUE($A6),1000000000),IFERROR(IF(VALUE(MID($A6,2,20))<100000000,VALUE(MID($A6,2,20)),1000000000),1000000000))+ROW()/100000,"")
F7: =IF($A7="","",E7*K7/100) | L7: =IF($A7="","",S7*K7) | M7: =IF($A7="","",K7-L7) | N7: =IF($A7="","",M7-F7) | S7: =IF($A7="","",IF(AND(ISNUMBER($R7),NOT(ISLOGICAL($R7)),N($R7)>1),$R7/100*1,IF($V7=1,Settings!$C$6,Settings!$C$7)*1)) | T7: =IF($A7="","",IF(COUNTIF($A$2:$A7,$A7)=1,1,0)) | U7: =IF($T7=1,SUMPRODUCT(--($W$2:$W$1001<$W7))+1,"") | V7: =IF($A7="","",IF(AND(ISNUMBER($R7),NOT(ISLOGICAL($R7)),N($R7)>1),IF(ABS($R7/100-Settings!$C$6)<=ABS($R7/100-Settings!$C$7),1,0),IF(OR($R7=TRUE(),$R7="TRUE"),1,0))) | W7: =IF($T7=1,IFERROR(IF(VALUE($A7)<100000000,VALUE($A7),1000000000),IFERROR(IF(VALUE(MID($A7,2,20))<100000000,VALUE(MID($A7,2,20)),1000000000),1000000000))+ROW()/100000,"")
F8: =IF($A8="","",E8*K8/100) | L8: =IF($A8="","",S8*K8) | M8: =IF($A8="","",K8-L8) | N8: =IF($A8="","",M8-F8) | S8: =IF($A8="","",IF(AND(ISNUMBER($R8),NOT(ISLOGICAL($R8)),N($R8)>1),$R8/100*1,IF($V8=1,Settings!$C$6,Settings!$C$7)*1)) | T8: =IF($A8="","",IF(COUNTIF($A$2:$A8,$A8)=1,1,0)) | U8: =IF($T8=1,SUMPRODUCT(--($W$2:$W$1001<$W8))+1,"") | V8: =IF($A8="","",IF(AND(ISNUMBER($R8),NOT(ISLOGICAL($R8)),N($R8)>1),IF(ABS($R8/100-Settings!$C$6)<=ABS($R8/100-Settings!$C$7),1,0),IF(OR($R8=TRUE(),$R8="TRUE"),1,0))) | W8: =IF($T8=1,IFERROR(IF(VALUE($A8)<100000000,VALUE($A8),1000000000),IFERROR(IF(VALUE(MID($A8,2,20))<100000000,VALUE(MID($A8,2,20)),1000000000),1000000000))+ROW()/100000,"")
F9: =IF($A9="","",E9*K9/100) | L9: =IF($A9="","",S9*K9) | M9: =IF($A9="","",K9-L9) | N9: =IF($A9="","",M9-F9) | S9: =IF($A9="","",IF(AND(ISNUMBER($R9),NOT(ISLOGICAL($R9)),N($R9)>1),$R9/100*1,IF($V9=1,Settings!$C$6,Settings!$C$7)*1)) | T9: =IF($A9="","",IF(COUNTIF($A$2:$A9,$A9)=1,1,0)) | U9: =IF($T9=1,SUMPRODUCT(--($W$2:$W$1001<$W9))+1,"") | V9: =IF($A9="","",IF(AND(ISNUMBER($R9),NOT(ISLOGICAL($R9)),N($R9)>1),IF(ABS($R9/100-Settings!$C$6)<=ABS($R9/100-Settings!$C$7),1,0),IF(OR($R9=TRUE(),$R9="TRUE"),1,0))) | W9: =IF($T9=1,IFERROR(IF(VALUE($A9)<100000000,VALUE($A9),1000000000),IFERROR(IF(VALUE(MID($A9,2,20))<100000000,VALUE(MID($A9,2,20)),1000000000),1000000000))+ROW()/100000,"")
F10: =IF($A10="","",E10*K10/100) | L10: =IF($A10="","",S10*K10) | M10: =IF($A10="","",K10-L10) | N10: =IF($A10="","",M10-F10) | S10: =IF($A10="","",IF(AND(ISNUMBER($R10),NOT(ISLOGICAL($R10)),N($R10)>1),$R10/100*1,IF($V10=1,Settings!$C$6,Settings!$C$7)*1)) | T10: =IF($A10="","",IF(COUNTIF($A$2:$A10,$A10)=1,1,0)) | U10: =IF($T10=1,SUMPRODUCT(--($W$2:$W$1001<$W10))+1,"") | V10: =IF($A10="","",IF(AND(ISNUMBER($R10),NOT(ISLOGICAL($R10)),N($R10)>1),IF(ABS($R10/100-Settings!$C$6)<=ABS($R10/100-Settings!$C$7),1,0),IF(OR($R10=TRUE(),$R10="TRUE"),1,0))) | W10: =IF($T10=1,IFERROR(IF(VALUE($A10)<100000000,VALUE($A10),1000000000),IFERROR(IF(VALUE(MID($A10,2,20))<100000000,VALUE(MID($A10,2,20)),1000000000),1000000000))+ROW()/100000,"")
F11: =IF($A11="","",E11*K11/100) | L11: =IF($A11="","",S11*K11) | M11: =IF($A11="","",K11-L11) | N11: =IF($A11="","",M11-F11) | S11: =IF($A11="","",IF(AND(ISNUMBER($R11),NOT(ISLOGICAL($R11)),N($R11)>1),$R11/100*1,IF($V11=1,Settings!$C$6,Settings!$C$7)*1)) | T11: =IF($A11="","",IF(COUNTIF($A$2:$A11,$A11)=1,1,0)) | U11: =IF($T11=1,SUMPRODUCT(--($W$2:$W$1001<$W11))+1,"") | V11: =IF($A11="","",IF(AND(ISNUMBER($R11),NOT(ISLOGICAL($R11)),N($R11)>1),IF(ABS($R11/100-Settings!$C$6)<=ABS($R11/100-Settings!$C$7),1,0),IF(OR($R11=TRUE(),$R11="TRUE"),1,0))) | W11: =IF($T11=1,IFERROR(IF(VALUE($A11)<100000000,VALUE($A11),1000000000),IFERROR(IF(VALUE(MID($A11,2,20))<100000000,VALUE(MID($A11,2,20)),1000000000),1000000000))+ROW()/100000,"")
F12: =IF($A12="","",E12*K12/100) | L12: =IF($A12="","",S12*K12) | M12: =IF($A12="","",K12-L12) | N12: =IF($A12="","",M12-F12) | S12: =IF($A12="","",IF(AND(ISNUMBER($R12),NOT(ISLOGICAL($R12)),N($R12)>1),$R12/100*1,IF($V12=1,Settings!$C$6,Settings!$C$7)*1)) | T12: =IF($A12="","",IF(COUNTIF($A$2:$A12,$A12)=1,1,0)) | U12: =IF($T12=1,SUMPRODUCT(--($W$2:$W$1001<$W12))+1,"") | V12: =IF($A12="","",IF(AND(ISNUMBER($R12),NOT(ISLOGICAL($R12)),N($R12)>1),IF(ABS($R12/100-Settings!$C$6)<=ABS($R12/100-Settings!$C$7),1,0),IF(OR($R12=TRUE(),$R12="TRUE"),1,0))) | W12: =IF($T12=1,IFERROR(IF(VALUE($A12)<100000000,VALUE($A12),1000000000),IFERROR(IF(VALUE(MID($A12,2,20))<100000000,VALUE(MID($A12,2,20)),1000000000),1000000000))+ROW()/100000,"")
F13: =IF($A13="","",E13*K13/100) | L13: =IF($A13="","",S13*K13) | M13: =IF($A13="","",K13-L13) | N13: =IF($A13="","",M13-F13) | S13: =IF($A13="","",IF(AND(ISNUMBER($R13),NOT(ISLOGICAL($R13)),N($R13)>1),$R13/100*1,IF($V13=1,Settings!$C$6,Settings!$C$7)*1)) | T13: =IF($A13="","",IF(COUNTIF($A$2:$A13,$A13)=1,1,0)) | U13: =IF($T13=1,SUMPRODUCT(--($W$2:$W$1001<$W13))+1,"") | V13: =IF($A13="","",IF(AND(ISNUMBER($R13),NOT(ISLOGICAL($R13)),N($R13)>1),IF(ABS($R13/100-Settings!$C$6)<=ABS($R13/100-Settings!$C$7),1,0),IF(OR($R13=TRUE(),$R13="TRUE"),1,0))) | W13: =IF($T13=1,IFERROR(IF(VALUE($A13)<100000000,VALUE($A13),1000000000),IFERROR(IF(VALUE(MID($A13,2,20))<100000000,VALUE(MID($A13,2,20)),1000000000),1000000000))+ROW()/100000,"")
... F1001: =IF($A1001="","",E1001*K1001/100) | L1001: =IF($A1001="","",S1001*K1001) | M1001: =IF($A1001="","",K1001-L1001) | N1001: =IF($A1001="","",M1001-F1001) | S1001: =IF($A1001="","",IF(AND(ISNUMBER($R1001),NOT(ISLOGICAL($R1001)),N($R1001)>1),$R1001/100*1,IF($V1001=1,Settings!$C$6,Settings!$C$7)*1)) | T1001: =IF($A1001="","",IF(COUNTIF($A$2:$A1001,$A1001)=1,1,0)) | U1001: =IF($T1001=1,SUMPRODUCT(--($W$2:$W$1001<$W1001))+1,"") | V1001: =IF($A1001="","",IF(AND(ISNUMBER($R1001),NOT(ISLOGICAL($R1001)),N($R1001)>1),IF(ABS($R1001/100-Settings!$C$6)<=ABS($R1001/100-Settings!$C$7),1,0),IF(OR($R1001=TRUE(),$R1001="TRUE"),1,0))) | W1001: =IF($T1001=1,IFERROR(IF(VALUE($A1001)<100000000,VALUE($A1001),1000000000),IFERROR(IF(VALUE(MID($A1001,2,20))<100000000,VALUE(MID($A1001,2,20)),1000000000),1000000000))+ROW()/100000,"")

Sheet Per Invoice
A1: Invoice | B1: Pos Reference | C1: approval Refrence | D1: Insurance Company | E1: Name | F1: Card Number | G1: Co Payment % | H1: Co val | I1: Create Date | J1: IMP% | K1: IMP | L1: IMP VAL | M1: LOCAL% | N1: LOCAL | O1: LOCAL VAL | P1: TOTAL VAL | Q1: SUBTOTAL | R1: Grand Total | S1: NET | T1: Src Row (helper)
B2: =IF($T2="","",INDEX('Per Line'!$A$2:$A$1001,$T2)&"") | D2: =IF($T2="","",INDEX('Per Line'!$B$2:$B$1001,$T2)&"") | E2: =IF($T2="","",INDEX('Per Line'!$C$2:$C$1001,$T2)&"") | F2: =IF($T2="","",INDEX('Per Line'!$D$2:$D$1001,$T2)&"") | G2: =IF($T2="","",INDEX('Per Line'!$E$2:$E$1001,$T2)) | H2: =IF($T2="","",G2*R2/100) | I2: =IF($T2="","",INDEX('Per Line'!$Q$2:$Q$1001,$T2)) | J2: =IF($T2="","",Settings!$C$7) | K2: =IF($T2="","",SUMIFS('Per Line'!$K$2:$K$1001,'Per Line'!$A$2:$A$1001,$B2,'Per Line'!$V$2:$V$1001,0)) | L2: =IF($T2="","",K2*J2) | M2: =IF($T2="","",Settings!$C$6) | N2: =IF($T2="","",SUMIFS('Per Line'!$K$2:$K$1001,'Per Line'!$A$2:$A$1001,$B2,'Per Line'!$V$2:$V$1001,1)) | O2: =IF($T2="","",N2*M2) | P2: =IF($T2="","",O2+L2) | Q2: =IF($T2="","",R2-P2) | R2: =IF($T2="","",K2+N2) | S2: =IF($T2="","",R2-P2-H2) | T2: =IF(ROWS($T$2:$T2)<=MAX('Per Line'!$U$2:$U$1001),MATCH(ROWS($T$2:$T2),'Per Line'!$U$2:$U$1001,0),"")
B3: =IF($T3="","",INDEX('Per Line'!$A$2:$A$1001,$T3)&"") | D3: =IF($T3="","",INDEX('Per Line'!$B$2:$B$1001,$T3)&"") | E3: =IF($T3="","",INDEX('Per Line'!$C$2:$C$1001,$T3)&"") | F3: =IF($T3="","",INDEX('Per Line'!$D$2:$D$1001,$T3)&"") | G3: =IF($T3="","",INDEX('Per Line'!$E$2:$E$1001,$T3)) | H3: =IF($T3="","",G3*R3/100) | I3: =IF($T3="","",INDEX('Per Line'!$Q$2:$Q$1001,$T3)) | J3: =IF($T3="","",Settings!$C$7) | K3: =IF($T3="","",SUMIFS('Per Line'!$K$2:$K$1001,'Per Line'!$A$2:$A$1001,$B3,'Per Line'!$V$2:$V$1001,0)) | L3: =IF($T3="","",K3*J3) | M3: =IF($T3="","",Settings!$C$6) | N3: =IF($T3="","",SUMIFS('Per Line'!$K$2:$K$1001,'Per Line'!$A$2:$A$1001,$B3,'Per Line'!$V$2:$V$1001,1)) | O3: =IF($T3="","",N3*M3) | P3: =IF($T3="","",O3+L3) | Q3: =IF($T3="","",R3-P3) | R3: =IF($T3="","",K3+N3) | S3: =IF($T3="","",R3-P3-H3) | T3: =IF(ROWS($T$2:$T3)<=MAX('Per Line'!$U$2:$U$1001),MATCH(ROWS($T$2:$T3),'Per Line'!$U$2:$U$1001,0),"")
B4: =IF($T4="","",INDEX('Per Line'!$A$2:$A$1001,$T4)&"") | D4: =IF($T4="","",INDEX('Per Line'!$B$2:$B$1001,$T4)&"") | E4: =IF($T4="","",INDEX('Per Line'!$C$2:$C$1001,$T4)&"") | F4: =IF($T4="","",INDEX('Per Line'!$D$2:$D$1001,$T4)&"") | G4: =IF($T4="","",INDEX('Per Line'!$E$2:$E$1001,$T4)) | H4: =IF($T4="","",G4*R4/100) | I4: =IF($T4="","",INDEX('Per Line'!$Q$2:$Q$1001,$T4)) | J4: =IF($T4="","",Settings!$C$7) | K4: =IF($T4="","",SUMIFS('Per Line'!$K$2:$K$1001,'Per Line'!$A$2:$A$1001,$B4,'Per Line'!$V$2:$V$1001,0)) | L4: =IF($T4="","",K4*J4) | M4: =IF($T4="","",Settings!$C$6) | N4: =IF($T4="","",SUMIFS('Per Line'!$K$2:$K$1001,'Per Line'!$A$2:$A$1001,$B4,'Per Line'!$V$2:$V$1001,1)) | O4: =IF($T4="","",N4*M4) | P4: =IF($T4="","",O4+L4) | Q4: =IF($T4="","",R4-P4) | R4: =IF($T4="","",K4+N4) | S4: =IF($T4="","",R4-P4-H4) | T4: =IF(ROWS($T$2:$T4)<=MAX('Per Line'!$U$2:$U$1001),MATCH(ROWS($T$2:$T4),'Per Line'!$U$2:$U$1001,0),"")
B5: =IF($T5="","",INDEX('Per Line'!$A$2:$A$1001,$T5)&"") | D5: =IF($T5="","",INDEX('Per Line'!$B$2:$B$1001,$T5)&"") | E5: =IF($T5="","",INDEX('Per Line'!$C$2:$C$1001,$T5)&"") | F5: =IF($T5="","",INDEX('Per Line'!$D$2:$D$1001,$T5)&"") | G5: =IF($T5="","",INDEX('Per Line'!$E$2:$E$1001,$T5)) | H5: =IF($T5="","",G5*R5/100) | I5: =IF($T5="","",INDEX('Per Line'!$Q$2:$Q$1001,$T5)) | J5: =IF($T5="","",Settings!$C$7) | K5: =IF($T5="","",SUMIFS('Per Line'!$K$2:$K$1001,'Per Line'!$A$2:$A$1001,$B5,'Per Line'!$V$2:$V$1001,0)) | L5: =IF($T5="","",K5*J5) | M5: =IF($T5="","",Settings!$C$6) | N5: =IF($T5="","",SUMIFS('Per Line'!$K$2:$K$1001,'Per Line'!$A$2:$A$1001,$B5,'Per Line'!$V$2:$V$1001,1)) | O5: =IF($T5="","",N5*M5) | P5: =IF($T5="","",O5+L5) | Q5: =IF($T5="","",R5-P5) | R5: =IF($T5="","",K5+N5) | S5: =IF($T5="","",R5-P5-H5) | T5: =IF(ROWS($T$2:$T5)<=MAX('Per Line'!$U$2:$U$1001),MATCH(ROWS($T$2:$T5),'Per Line'!$U$2:$U$1001,0),"")
B6: =IF($T6="","",INDEX('Per Line'!$A$2:$A$1001,$T6)&"") | D6: =IF($T6="","",INDEX('Per Line'!$B$2:$B$1001,$T6)&"") | E6: =IF($T6="","",INDEX('Per Line'!$C$2:$C$1001,$T6)&"") | F6: =IF($T6="","",INDEX('Per Line'!$D$2:$D$1001,$T6)&"") | G6: =IF($T6="","",INDEX('Per Line'!$E$2:$E$1001,$T6)) | H6: =IF($T6="","",G6*R6/100) | I6: =IF($T6="","",INDEX('Per Line'!$Q$2:$Q$1001,$T6)) | J6: =IF($T6="","",Settings!$C$7) | K6: =IF($T6="","",SUMIFS('Per Line'!$K$2:$K$1001,'Per Line'!$A$2:$A$1001,$B6,'Per Line'!$V$2:$V$1001,0)) | L6: =IF($T6="","",K6*J6) | M6: =IF($T6="","",Settings!$C$6) | N6: =IF($T6="","",SUMIFS('Per Line'!$K$2:$K$1001,'Per Line'!$A$2:$A$1001,$B6,'Per Line'!$V$2:$V$1001,1)) | O6: =IF($T6="","",N6*M6) | P6: =IF($T6="","",O6+L6) | Q6: =IF($T6="","",R6-P6) | R6: =IF($T6="","",K6+N6) | S6: =IF($T6="","",R6-P6-H6) | T6: =IF(ROWS($T$2:$T6)<=MAX('Per Line'!$U$2:$U$1001),MATCH(ROWS($T$2:$T6),'Per Line'!$U$2:$U$1001,0),"")
B7: =IF($T7="","",INDEX('Per Line'!$A$2:$A$1001,$T7)&"") | D7: =IF($T7="","",INDEX('Per Line'!$B$2:$B$1001,$T7)&"") | E7: =IF($T7="","",INDEX('Per Line'!$C$2:$C$1001,$T7)&"") | F7: =IF($T7="","",INDEX('Per Line'!$D$2:$D$1001,$T7)&"") | G7: =IF($T7="","",INDEX('Per Line'!$E$2:$E$1001,$T7)) | H7: =IF($T7="","",G7*R7/100) | I7: =IF($T7="","",INDEX('Per Line'!$Q$2:$Q$1001,$T7)) | J7: =IF($T7="","",Settings!$C$7) | K7: =IF($T7="","",SUMIFS('Per Line'!$K$2:$K$1001,'Per Line'!$A$2:$A$1001,$B7,'Per Line'!$V$2:$V$1001,0)) | L7: =IF($T7="","",K7*J7) | M7: =IF($T7="","",Settings!$C$6) | N7: =IF($T7="","",SUMIFS('Per Line'!$K$2:$K$1001,'Per Line'!$A$2:$A$1001,$B7,'Per Line'!$V$2:$V$1001,1)) | O7: =IF($T7="","",N7*M7) | P7: =IF($T7="","",O7+L7) | Q7: =IF($T7="","",R7-P7) | R7: =IF($T7="","",K7+N7) | S7: =IF($T7="","",R7-P7-H7) | T7: =IF(ROWS($T$2:$T7)<=MAX('Per Line'!$U$2:$U$1001),MATCH(ROWS($T$2:$T7),'Per Line'!$U$2:$U$1001,0),"")
B8: =IF($T8="","",INDEX('Per Line'!$A$2:$A$1001,$T8)&"") | D8: =IF($T8="","",INDEX('Per Line'!$B$2:$B$1001,$T8)&"") | E8: =IF($T8="","",INDEX('Per Line'!$C$2:$C$1001,$T8)&"") | F8: =IF($T8="","",INDEX('Per Line'!$D$2:$D$1001,$T8)&"") | G8: =IF($T8="","",INDEX('Per Line'!$E$2:$E$1001,$T8)) | H8: =IF($T8="","",G8*R8/100) | I8: =IF($T8="","",INDEX('Per Line'!$Q$2:$Q$1001,$T8)) | J8: =IF($T8="","",Settings!$C$7) | K8: =IF($T8="","",SUMIFS('Per Line'!$K$2:$K$1001,'Per Line'!$A$2:$A$1001,$B8,'Per Line'!$V$2:$V$1001,0)) | L8: =IF($T8="","",K8*J8) | M8: =IF($T8="","",Settings!$C$6) | N8: =IF($T8="","",SUMIFS('Per Line'!$K$2:$K$1001,'Per Line'!$A$2:$A$1001,$B8,'Per Line'!$V$2:$V$1001,1)) | O8: =IF($T8="","",N8*M8) | P8: =IF($T8="","",O8+L8) | Q8: =IF($T8="","",R8-P8) | R8: =IF($T8="","",K8+N8) | S8: =IF($T8="","",R8-P8-H8) | T8: =IF(ROWS($T$2:$T8)<=MAX('Per Line'!$U$2:$U$1001),MATCH(ROWS($T$2:$T8),'Per Line'!$U$2:$U$1001,0),"")
B9: =IF($T9="","",INDEX('Per Line'!$A$2:$A$1001,$T9)&"") | D9: =IF($T9="","",INDEX('Per Line'!$B$2:$B$1001,$T9)&"") | E9: =IF($T9="","",INDEX('Per Line'!$C$2:$C$1001,$T9)&"") | F9: =IF($T9="","",INDEX('Per Line'!$D$2:$D$1001,$T9)&"") | G9: =IF($T9="","",INDEX('Per Line'!$E$2:$E$1001,$T9)) | H9: =IF($T9="","",G9*R9/100) | I9: =IF($T9="","",INDEX('Per Line'!$Q$2:$Q$1001,$T9)) | J9: =IF($T9="","",Settings!$C$7) | K9: =IF($T9="","",SUMIFS('Per Line'!$K$2:$K$1001,'Per Line'!$A$2:$A$1001,$B9,'Per Line'!$V$2:$V$1001,0)) | L9: =IF($T9="","",K9*J9) | M9: =IF($T9="","",Settings!$C$6) | N9: =IF($T9="","",SUMIFS('Per Line'!$K$2:$K$1001,'Per Line'!$A$2:$A$1001,$B9,'Per Line'!$V$2:$V$1001,1)) | O9: =IF($T9="","",N9*M9) | P9: =IF($T9="","",O9+L9) | Q9: =IF($T9="","",R9-P9) | R9: =IF($T9="","",K9+N9) | S9: =IF($T9="","",R9-P9-H9) | T9: =IF(ROWS($T$2:$T9)<=MAX('Per Line'!$U$2:$U$1001),MATCH(ROWS($T$2:$T9),'Per Line'!$U$2:$U$1001,0),"")
B10: =IF($T10="","",INDEX('Per Line'!$A$2:$A$1001,$T10)&"") | D10: =IF($T10="","",INDEX('Per Line'!$B$2:$B$1001,$T10)&"") | E10: =IF($T10="","",INDEX('Per Line'!$C$2:$C$1001,$T10)&"") | F10: =IF($T10="","",INDEX('Per Line'!$D$2:$D$1001,$T10)&"") | G10: =IF($T10="","",INDEX('Per Line'!$E$2:$E$1001,$T10)) | H10: =IF($T10="","",G10*R10/100) | I10: =IF($T10="","",INDEX('Per Line'!$Q$2:$Q$1001,$T10)) | J10: =IF($T10="","",Settings!$C$7) | K10: =IF($T10="","",SUMIFS('Per Line'!$K$2:$K$1001,'Per Line'!$A$2:$A$1001,$B10,'Per Line'!$V$2:$V$1001,0)) | L10: =IF($T10="","",K10*J10) | M10: =IF($T10="","",Settings!$C$6) | N10: =IF($T10="","",SUMIFS('Per Line'!$K$2:$K$1001,'Per Line'!$A$2:$A$1001,$B10,'Per Line'!$V$2:$V$1001,1)) | O10: =IF($T10="","",N10*M10) | P10: =IF($T10="","",O10+L10) | Q10: =IF($T10="","",R10-P10) | R10: =IF($T10="","",K10+N10) | S10: =IF($T10="","",R10-P10-H10) | T10: =IF(ROWS($T$2:$T10)<=MAX('Per Line'!$U$2:$U$1001),MATCH(ROWS($T$2:$T10),'Per Line'!$U$2:$U$1001,0),"")
B11: =IF($T11="","",INDEX('Per Line'!$A$2:$A$1001,$T11)&"") | D11: =IF($T11="","",INDEX('Per Line'!$B$2:$B$1001,$T11)&"") | E11: =IF($T11="","",INDEX('Per Line'!$C$2:$C$1001,$T11)&"") | F11: =IF($T11="","",INDEX('Per Line'!$D$2:$D$1001,$T11)&"") | G11: =IF($T11="","",INDEX('Per Line'!$E$2:$E$1001,$T11)) | H11: =IF($T11="","",G11*R11/100) | I11: =IF($T11="","",INDEX('Per Line'!$Q$2:$Q$1001,$T11)) | J11: =IF($T11="","",Settings!$C$7) | K11: =IF($T11="","",SUMIFS('Per Line'!$K$2:$K$1001,'Per Line'!$A$2:$A$1001,$B11,'Per Line'!$V$2:$V$1001,0)) | L11: =IF($T11="","",K11*J11) | M11: =IF($T11="","",Settings!$C$6) | N11: =IF($T11="","",SUMIFS('Per Line'!$K$2:$K$1001,'Per Line'!$A$2:$A$1001,$B11,'Per Line'!$V$2:$V$1001,1)) | O11: =IF($T11="","",N11*M11) | P11: =IF($T11="","",O11+L11) | Q11: =IF($T11="","",R11-P11) | R11: =IF($T11="","",K11+N11) | S11: =IF($T11="","",R11-P11-H11) | T11: =IF(ROWS($T$2:$T11)<=MAX('Per Line'!$U$2:$U$1001),MATCH(ROWS($T$2:$T11),'Per Line'!$U$2:$U$1001,0),"")
B12: =IF($T12="","",INDEX('Per Line'!$A$2:$A$1001,$T12)&"") | D12: =IF($T12="","",INDEX('Per Line'!$B$2:$B$1001,$T12)&"") | E12: =IF($T12="","",INDEX('Per Line'!$C$2:$C$1001,$T12)&"") | F12: =IF($T12="","",INDEX('Per Line'!$D$2:$D$1001,$T12)&"") | G12: =IF($T12="","",INDEX('Per Line'!$E$2:$E$1001,$T12)) | H12: =IF($T12="","",G12*R12/100) | I12: =IF($T12="","",INDEX('Per Line'!$Q$2:$Q$1001,$T12)) | J12: =IF($T12="","",Settings!$C$7) | K12: =IF($T12="","",SUMIFS('Per Line'!$K$2:$K$1001,'Per Line'!$A$2:$A$1001,$B12,'Per Line'!$V$2:$V$1001,0)) | L12: =IF($T12="","",K12*J12) | M12: =IF($T12="","",Settings!$C$6) | N12: =IF($T12="","",SUMIFS('Per Line'!$K$2:$K$1001,'Per Line'!$A$2:$A$1001,$B12,'Per Line'!$V$2:$V$1001,1)) | O12: =IF($T12="","",N12*M12) | P12: =IF($T12="","",O12+L12) | Q12: =IF($T12="","",R12-P12) | R12: =IF($T12="","",K12+N12) | S12: =IF($T12="","",R12-P12-H12) | T12: =IF(ROWS($T$2:$T12)<=MAX('Per Line'!$U$2:$U$1001),MATCH(ROWS($T$2:$T12),'Per Line'!$U$2:$U$1001,0),"")
B13: =IF($T13="","",INDEX('Per Line'!$A$2:$A$1001,$T13)&"") | D13: =IF($T13="","",INDEX('Per Line'!$B$2:$B$1001,$T13)&"") | E13: =IF($T13="","",INDEX('Per Line'!$C$2:$C$1001,$T13)&"") | F13: =IF($T13="","",INDEX('Per Line'!$D$2:$D$1001,$T13)&"") | G13: =IF($T13="","",INDEX('Per Line'!$E$2:$E$1001,$T13)) | H13: =IF($T13="","",G13*R13/100) | I13: =IF($T13="","",INDEX('Per Line'!$Q$2:$Q$1001,$T13)) | J13: =IF($T13="","",Settings!$C$7) | K13: =IF($T13="","",SUMIFS('Per Line'!$K$2:$K$1001,'Per Line'!$A$2:$A$1001,$B13,'Per Line'!$V$2:$V$1001,0)) | L13: =IF($T13="","",K13*J13) | M13: =IF($T13="","",Settings!$C$6) | N13: =IF($T13="","",SUMIFS('Per Line'!$K$2:$K$1001,'Per Line'!$A$2:$A$1001,$B13,'Per Line'!$V$2:$V$1001,1)) | O13: =IF($T13="","",N13*M13) | P13: =IF($T13="","",O13+L13) | Q13: =IF($T13="","",R13-P13) | R13: =IF($T13="","",K13+N13) | S13: =IF($T13="","",R13-P13-H13) | T13: =IF(ROWS($T$2:$T13)<=MAX('Per Line'!$U$2:$U$1001),MATCH(ROWS($T$2:$T13),'Per Line'!$U$2:$U$1001,0),"")
... B301: =IF($T301="","",INDEX('Per Line'!$A$2:$A$1001,$T301)&"") | D301: =IF($T301="","",INDEX('Per Line'!$B$2:$B$1001,$T301)&"") | E301: =IF($T301="","",INDEX('Per Line'!$C$2:$C$1001,$T301)&"") | F301: =IF($T301="","",INDEX('Per Line'!$D$2:$D$1001,$T301)&"") | G301: =IF($T301="","",INDEX('Per Line'!$E$2:$E$1001,$T301)) | H301: =IF($T301="","",G301*R301/100) | I301: =IF($T301="","",INDEX('Per Line'!$Q$2:$Q$1001,$T301)) | J301: =IF($T301="","",Settings!$C$7) | K301: =IF($T301="","",SUMIFS('Per Line'!$K$2:$K$1001,'Per Line'!$A$2:$A$1001,$B301,'Per Line'!$V$2:$V$1001,0)) | L301: =IF($T301="","",K301*J301) | M301: =IF($T301="","",Settings!$C$6) | N301: =IF($T301="","",SUMIFS('Per Line'!$K$2:$K$1001,'Per Line'!$A$2:$A$1001,$B301,'Per Line'!$V$2:$V$1001,1)) | O301: =IF($T301="","",N301*M301) | P301: =IF($T301="","",O301+L301) | Q301: =IF($T301="","",R301-P301) | R301: =IF($T301="","",K301+N301) | S301: =IF($T301="","",R301-P301-H301) | T301: =IF(ROWS($T$2:$T301)<=MAX('Per Line'!$U$2:$U$1001),MATCH(ROWS($T$2:$T301),'Per Line'!$U$2:$U$1001,0),"")
