Workbook

Sheet How To Use
A1: Claims Template - MISR HEALTH CARE (VPN)
A3: Monthly steps
A4: 1. Open the 'Per Line' tab. Delete the old data in the BLUE columns only (row 2 down). Never delete the green or grey columns.
A5: 2. Paste the new month's data as VALUES starting at A2, into the blue columns: A-Q, S-AD (same order as the system export).
A6: 3. Green columns (R, AE, AF, AG, AH) and the grey helper columns (AI-AL) calculate automatically - do not paste over them.
A7: 4. 'Per Invoice' fills itself from 'Per Line' (one row per Order #, split into IMP / Local). No pivot table, no refresh.
A8: 5. The ONLY manual column in 'Per Invoice' is column A 'Invoice' (blue): type it yourself. Everything else is formula.
A9: 6. Open 'Settings' and check STATUS says OK (Per Line totals = Per Invoice totals).
A11: Colour legend
A12: Blue header = typed/pasted by you (raw data, and 'Invoice' in Per Invoice). Green header = formula (do not paste over). Grey header = helper formula (do not touch). Yellow cell (Settings) = editable rate.
A14: Calculation rules (taken from the August 2026 sheet)
A15: Co val = Co Payment % x Total / 100. Discount = Total x Rebates (Rebates is a fraction here, e.g. 0.14). Subtotal = Total - Discount. Net = Subtotal - Co val. (Total = 'Item Total Price (EGP)')
... A20: Capacity: up to 1,500 lines and 500 invoices per month. A line with an empty Order # is ignored.

Sheet Settings
B1: Company settings & checks
B3: Insurance Company | C3: MISR HEALTH CARE | D3: Informational only
B4: Corporate | C4: - | D4: Informational only
B5: Sheet type | C5: VPN | D5: Informational only
B6: Local products rebate % | C6: 0.12 | D6: Source: Aug sheet (Rebates = 0.12 when Imported = FALSE).
B7: Imported (IMP) products rebate % | C7: 0.04 | D7: Source: Aug sheet (Rebates = 0.04 when Imported = TRUE).
B9: Month totals / reconciliation
B10: Lines loaded | C10: =COUNTA('Per Line'!$C$2:$C$1501)
B11: Invoices (unique Order #) | C11: =MAX('Per Line'!$AJ$2:$AJ$1501)
B12: Invoices shown in Per Invoice | C12: =SUMPRODUCT(--('Per Invoice'!$C$2:$C$501<>""))
B13: Grand Total - Per Line (Product Total) | C13: =SUM('Per Line'!$AC$2:$AC$1501)
B14: Grand Total - Per Invoice | C14: =SUM('Per Invoice'!$T$2:$T$501)
B15: Discount - Per Line | C15: =SUM('Per Line'!$AF$2:$AF$1501)
B16: Discount - Per Invoice | C16: =SUM('Per Invoice'!$R$2:$R$501)
B17: Co val - Per Line | C17: =SUM('Per Line'!$R$2:$R$1501)
B18: Co val - Per Invoice | C18: =SUM('Per Invoice'!$K$2:$K$501)
B19: Net - Per Line | C19: =SUM('Per Line'!$AH$2:$AH$1501)
B20: Net - Per Invoice | C20: =SUM('Per Invoice'!$U$2:$U$501)
B21: Max Limit adjustment (Co val, Per Invoice only) | C21: 0 | D21: This company's Per Invoice has no Max Limit rule.
B23: STATUS | C23: =IF(C10=0,"No data loaded",IF(COUNTA('Per Line'!$C:$C)-1>1500,"TOO MANY LINES - extend template",IF(C11>500,"TOO MANY INVOICES - extend template",IF(AND(ROUND(C13-C14,2)=0,ROUND(C15-C16,2)=0,ROUND(C17+C21-C18,2)=0,ROUND(C19-C21-C20,2)=0,C11=C12),"OK","CHECK - Per Line and Per Invoice do not match")))) | D23: Must say OK after you paste the month data.

Sheet Per Line
A1: ERX ID | B1: Mongo Order ID | C1: Order Number | D1: Pool ID | E1: Approval Number | F1: Approval Reference | G1: Group ID | H1: Branch ID | I1: Order Status | J1: Total (EGP) | K1: By Patient (EGP) | L1: Order Type | M1: Original Order Type | N1: Payer | O1: Card Holder Name | P1: Card Number | Q1: Co Payment (%) | R1: Co val | S1: Creation Date | T1: Creation Time | U1: Dispatch Date | V1: Dispatch Time | W1: Heisenberg ID | X1: Item | Y1: Item Unit | Z1: Item Form | AA1: Item Price (EGP) | AB1: Item Quantity | AC1: Item Total Price (EGP) | AD1: Imported | AE1: Rebates | AF1: Discount | AG1: Subtotal | AH1: Net | AI1: Order 1st Row (helper) | AJ1: Invoice # (helper) | AK1: Is Local (helper) | AL1: Sort Key (helper)
R2: =IF($C2="","",Q2*AC2/100) | AE2: =IF($C2="","",IF($AK2=1,Settings!$C$6,Settings!$C$7)*1) | AF2: =IF($C2="","",AE2*AC2) | AG2: =IF($C2="","",AC2-AF2) | AH2: =IF($C2="","",AG2-R2) | AI2: =IF($C2="","",IF(COUNTIF($C$2:$C2,$C2)=1,1,0)) | AJ2: =IF($AI2=1,SUMPRODUCT(--($AL$2:$AL$1501<$AL2))+1,"") | AK2: =IF($C2="","",IF(OR($AD2=TRUE(),$AD2="TRUE"),0,1)) | AL2: =IF($AI2=1,IFERROR(IF(VALUE($C2)<100000000,VALUE($C2),1000000000),IFERROR(IF(VALUE(MID($C2,2,20))<100000000,VALUE(MID($C2,2,20)),1000000000),1000000000))+ROW()/100000,"")
R3: =IF($C3="","",Q3*AC3/100) | AE3: =IF($C3="","",IF($AK3=1,Settings!$C$6,Settings!$C$7)*1) | AF3: =IF($C3="","",AE3*AC3) | AG3: =IF($C3="","",AC3-AF3) | AH3: =IF($C3="","",AG3-R3) | AI3: =IF($C3="","",IF(COUNTIF($C$2:$C3,$C3)=1,1,0)) | AJ3: =IF($AI3=1,SUMPRODUCT(--($AL$2:$AL$1501<$AL3))+1,"") | AK3: =IF($C3="","",IF(OR($AD3=TRUE(),$AD3="TRUE"),0,1)) | AL3: =IF($AI3=1,IFERROR(IF(VALUE($C3)<100000000,VALUE($C3),1000000000),IFERROR(IF(VALUE(MID($C3,2,20))<100000000,VALUE(MID($C3,2,20)),1000000000),1000000000))+ROW()/100000,"")
R4: =IF($C4="","",Q4*AC4/100) | AE4: =IF($C4="","",IF($AK4=1,Settings!$C$6,Settings!$C$7)*1) | AF4: =IF($C4="","",AE4*AC4) | AG4: =IF($C4="","",AC4-AF4) | AH4: =IF($C4="","",AG4-R4) | AI4: =IF($C4="","",IF(COUNTIF($C$2:$C4,$C4)=1,1,0)) | AJ4: =IF($AI4=1,SUMPRODUCT(--($AL$2:$AL$1501<$AL4))+1,"") | AK4: =IF($C4="","",IF(OR($AD4=TRUE(),$AD4="TRUE"),0,1)) | AL4: =IF($AI4=1,IFERROR(IF(VALUE($C4)<100000000,VALUE($C4),1000000000),IFERROR(IF(VALUE(MID($C4,2,20))<100000000,VALUE(MID($C4,2,20)),1000000000),1000000000))+ROW()/100000,"")
R5: =IF($C5="","",Q5*AC5/100) | AE5: =IF($C5="","",IF($AK5=1,Settings!$C$6,Settings!$C$7)*1) | AF5: =IF($C5="","",AE5*AC5) | AG5: =IF($C5="","",AC5-AF5) | AH5: =IF($C5="","",AG5-R5) | AI5: =IF($C5="","",IF(COUNTIF($C$2:$C5,$C5)=1,1,0)) | AJ5: =IF($AI5=1,SUMPRODUCT(--($AL$2:$AL$1501<$AL5))+1,"") | AK5: =IF($C5="","",IF(OR($AD5=TRUE(),$AD5="TRUE"),0,1)) | AL5: =IF($AI5=1,IFERROR(IF(VALUE($C5)<100000000,VALUE($C5),1000000000),IFERROR(IF(VALUE(MID($C5,2,20))<100000000,VALUE(MID($C5,2,20)),1000000000),1000000000))+ROW()/100000,"")
R6: =IF($C6="","",Q6*AC6/100) | AE6: =IF($C6="","",IF($AK6=1,Settings!$C$6,Settings!$C$7)*1) | AF6: =IF($C6="","",AE6*AC6) | AG6: =IF($C6="","",AC6-AF6) | AH6: =IF($C6="","",AG6-R6) | AI6: =IF($C6="","",IF(COUNTIF($C$2:$C6,$C6)=1,1,0)) | AJ6: =IF($AI6=1,SUMPRODUCT(--($AL$2:$AL$1501<$AL6))+1,"") | AK6: =IF($C6="","",IF(OR($AD6=TRUE(),$AD6="TRUE"),0,1)) | AL6: =IF($AI6=1,IFERROR(IF(VALUE($C6)<100000000,VALUE($C6),1000000000),IFERROR(IF(VALUE(MID($C6,2,20))<100000000,VALUE(MID($C6,2,20)),1000000000),1000000000))+ROW()/100000,"")
R7: =IF($C7="","",Q7*AC7/100) | AE7: =IF($C7="","",IF($AK7=1,Settings!$C$6,Settings!$C$7)*1) | AF7: =IF($C7="","",AE7*AC7) | AG7: =IF($C7="","",AC7-AF7) | AH7: =IF($C7="","",AG7-R7) | AI7: =IF($C7="","",IF(COUNTIF($C$2:$C7,$C7)=1,1,0)) | AJ7: =IF($AI7=1,SUMPRODUCT(--($AL$2:$AL$1501<$AL7))+1,"") | AK7: =IF($C7="","",IF(OR($AD7=TRUE(),$AD7="TRUE"),0,1)) | AL7: =IF($AI7=1,IFERROR(IF(VALUE($C7)<100000000,VALUE($C7),1000000000),IFERROR(IF(VALUE(MID($C7,2,20))<100000000,VALUE(MID($C7,2,20)),1000000000),1000000000))+ROW()/100000,"")
R8: =IF($C8="","",Q8*AC8/100) | AE8: =IF($C8="","",IF($AK8=1,Settings!$C$6,Settings!$C$7)*1) | AF8: =IF($C8="","",AE8*AC8) | AG8: =IF($C8="","",AC8-AF8) | AH8: =IF($C8="","",AG8-R8) | AI8: =IF($C8="","",IF(COUNTIF($C$2:$C8,$C8)=1,1,0)) | AJ8: =IF($AI8=1,SUMPRODUCT(--($AL$2:$AL$1501<$AL8))+1,"") | AK8: =IF($C8="","",IF(OR($AD8=TRUE(),$AD8="TRUE"),0,1)) | AL8: =IF($AI8=1,IFERROR(IF(VALUE($C8)<100000000,VALUE($C8),1000000000),IFERROR(IF(VALUE(MID($C8,2,20))<100000000,VALUE(MID($C8,2,20)),1000000000),1000000000))+ROW()/100000,"")
R9: =IF($C9="","",Q9*AC9/100) | AE9: =IF($C9="","",IF($AK9=1,Settings!$C$6,Settings!$C$7)*1) | AF9: =IF($C9="","",AE9*AC9) | AG9: =IF($C9="","",AC9-AF9) | AH9: =IF($C9="","",AG9-R9) | AI9: =IF($C9="","",IF(COUNTIF($C$2:$C9,$C9)=1,1,0)) | AJ9: =IF($AI9=1,SUMPRODUCT(--($AL$2:$AL$1501<$AL9))+1,"") | AK9: =IF($C9="","",IF(OR($AD9=TRUE(),$AD9="TRUE"),0,1)) | AL9: =IF($AI9=1,IFERROR(IF(VALUE($C9)<100000000,VALUE($C9),1000000000),IFERROR(IF(VALUE(MID($C9,2,20))<100000000,VALUE(MID($C9,2,20)),1000000000),1000000000))+ROW()/100000,"")
R10: =IF($C10="","",Q10*AC10/100) | AE10: =IF($C10="","",IF($AK10=1,Settings!$C$6,Settings!$C$7)*1) | AF10: =IF($C10="","",AE10*AC10) | AG10: =IF($C10="","",AC10-AF10) | AH10: =IF($C10="","",AG10-R10) | AI10: =IF($C10="","",IF(COUNTIF($C$2:$C10,$C10)=1,1,0)) | AJ10: =IF($AI10=1,SUMPRODUCT(--($AL$2:$AL$1501<$AL10))+1,"") | AK10: =IF($C10="","",IF(OR($AD10=TRUE(),$AD10="TRUE"),0,1)) | AL10: =IF($AI10=1,IFERROR(IF(VALUE($C10)<100000000,VALUE($C10),1000000000),IFERROR(IF(VALUE(MID($C10,2,20))<100000000,VALUE(MID($C10,2,20)),1000000000),1000000000))+ROW()/100000,"")
R11: =IF($C11="","",Q11*AC11/100) | AE11: =IF($C11="","",IF($AK11=1,Settings!$C$6,Settings!$C$7)*1) | AF11: =IF($C11="","",AE11*AC11) | AG11: =IF($C11="","",AC11-AF11) | AH11: =IF($C11="","",AG11-R11) | AI11: =IF($C11="","",IF(COUNTIF($C$2:$C11,$C11)=1,1,0)) | AJ11: =IF($AI11=1,SUMPRODUCT(--($AL$2:$AL$1501<$AL11))+1,"") | AK11: =IF($C11="","",IF(OR($AD11=TRUE(),$AD11="TRUE"),0,1)) | AL11: =IF($AI11=1,IFERROR(IF(VALUE($C11)<100000000,VALUE($C11),1000000000),IFERROR(IF(VALUE(MID($C11,2,20))<100000000,VALUE(MID($C11,2,20)),1000000000),1000000000))+ROW()/100000,"")
R12: =IF($C12="","",Q12*AC12/100) | AE12: =IF($C12="","",IF($AK12=1,Settings!$C$6,Settings!$C$7)*1) | AF12: =IF($C12="","",AE12*AC12) | AG12: =IF($C12="","",AC12-AF12) | AH12: =IF($C12="","",AG12-R12) | AI12: =IF($C12="","",IF(COUNTIF($C$2:$C12,$C12)=1,1,0)) | AJ12: =IF($AI12=1,SUMPRODUCT(--($AL$2:$AL$1501<$AL12))+1,"") | AK12: =IF($C12="","",IF(OR($AD12=TRUE(),$AD12="TRUE"),0,1)) | AL12: =IF($AI12=1,IFERROR(IF(VALUE($C12)<100000000,VALUE($C12),1000000000),IFERROR(IF(VALUE(MID($C12,2,20))<100000000,VALUE(MID($C12,2,20)),1000000000),1000000000))+ROW()/100000,"")
R13: =IF($C13="","",Q13*AC13/100) | AE13: =IF($C13="","",IF($AK13=1,Settings!$C$6,Settings!$C$7)*1) | AF13: =IF($C13="","",AE13*AC13) | AG13: =IF($C13="","",AC13-AF13) | AH13: =IF($C13="","",AG13-R13) | AI13: =IF($C13="","",IF(COUNTIF($C$2:$C13,$C13)=1,1,0)) | AJ13: =IF($AI13=1,SUMPRODUCT(--($AL$2:$AL$1501<$AL13))+1,"") | AK13: =IF($C13="","",IF(OR($AD13=TRUE(),$AD13="TRUE"),0,1)) | AL13: =IF($AI13=1,IFERROR(IF(VALUE($C13)<100000000,VALUE($C13),1000000000),IFERROR(IF(VALUE(MID($C13,2,20))<100000000,VALUE(MID($C13,2,20)),1000000000),1000000000))+ROW()/100000,"")
... R1501: =IF($C1501="","",Q1501*AC1501/100) | AE1501: =IF($C1501="","",IF($AK1501=1,Settings!$C$6,Settings!$C$7)*1) | AF1501: =IF($C1501="","",AE1501*AC1501) | AG1501: =IF($C1501="","",AC1501-AF1501) | AH1501: =IF($C1501="","",AG1501-R1501) | AI1501: =IF($C1501="","",IF(COUNTIF($C$2:$C1501,$C1501)=1,1,0)) | AJ1501: =IF($AI1501=1,SUMPRODUCT(--($AL$2:$AL$1501<$AL1501))+1,"") | AK1501: =IF($C1501="","",IF(OR($AD1501=TRUE(),$AD1501="TRUE"),0,1)) | AL1501: =IF($AI1501=1,IFERROR(IF(VALUE($C1501)<100000000,VALUE($C1501),1000000000),IFERROR(IF(VALUE(MID($C1501,2,20))<100000000,VALUE(MID($C1501,2,20)),1000000000),1000000000))+ROW()/100000,"")

Sheet Per Invoice
A1: Invoice | B1: ERX ID | C1: Order Number | D1: creation date | E1: Approval Reference | F1: Order Type | G1: Card Holder Name | H1: Card Number | I1: Payer | J1: Co Payment (%) | K1: Co val | L1: IMP% | M1: IMP | N1: IMP VAL | O1: LOCAL % | P1: LOCAL | Q1: LOCAL VAL | R1: TOTAL VAL | S1: SUBTOTAL | T1: Grand Total | U1: NET | V1: Src Row (helper)
B2: =IF($V2="","",INDEX('Per Line'!$A$2:$A$1501,$V2)&"") | C2: =IF($V2="","",INDEX('Per Line'!$C$2:$C$1501,$V2)&"") | D2: =IF($V2="","",INDEX('Per Line'!$S$2:$S$1501,$V2)) | E2: =IF($V2="","",INDEX('Per Line'!$F$2:$F$1501,$V2)&"") | F2: =IF($V2="","",INDEX('Per Line'!$L$2:$L$1501,$V2)&"") | G2: =IF($V2="","",INDEX('Per Line'!$O$2:$O$1501,$V2)&"") | H2: =IF($V2="","",INDEX('Per Line'!$P$2:$P$1501,$V2)&"") | I2: =IF($V2="","",INDEX('Per Line'!$N$2:$N$1501,$V2)&"") | J2: =IF($V2="","",INDEX('Per Line'!$Q$2:$Q$1501,$V2)) | K2: =IF($V2="","",J2*T2/100) | L2: =IF($V2="","",Settings!$C$7) | M2: =IF($V2="","",SUMIFS('Per Line'!$AC$2:$AC$1501,'Per Line'!$C$2:$C$1501,$C2,'Per Line'!$AK$2:$AK$1501,0)) | N2: =IF($V2="","",M2*L2) | O2: =IF($V2="","",Settings!$C$6) | P2: =IF($V2="","",SUMIFS('Per Line'!$AC$2:$AC$1501,'Per Line'!$C$2:$C$1501,$C2,'Per Line'!$AK$2:$AK$1501,1)) | Q2: =IF($V2="","",P2*O2) | R2: =IF($V2="","",Q2+N2) | S2: =IF($V2="","",T2-R2) | T2: =IF($V2="","",M2+P2) | U2: =IF($V2="","",T2-R2-K2) | V2: =IF(ROWS($V$2:$V2)<=MAX('Per Line'!$AJ$2:$AJ$1501),MATCH(ROWS($V$2:$V2),'Per Line'!$AJ$2:$AJ$1501,0),"")
B3: =IF($V3="","",INDEX('Per Line'!$A$2:$A$1501,$V3)&"") | C3: =IF($V3="","",INDEX('Per Line'!$C$2:$C$1501,$V3)&"") | D3: =IF($V3="","",INDEX('Per Line'!$S$2:$S$1501,$V3)) | E3: =IF($V3="","",INDEX('Per Line'!$F$2:$F$1501,$V3)&"") | F3: =IF($V3="","",INDEX('Per Line'!$L$2:$L$1501,$V3)&"") | G3: =IF($V3="","",INDEX('Per Line'!$O$2:$O$1501,$V3)&"") | H3: =IF($V3="","",INDEX('Per Line'!$P$2:$P$1501,$V3)&"") | I3: =IF($V3="","",INDEX('Per Line'!$N$2:$N$1501,$V3)&"") | J3: =IF($V3="","",INDEX('Per Line'!$Q$2:$Q$1501,$V3)) | K3: =IF($V3="","",J3*T3/100) | L3: =IF($V3="","",Settings!$C$7) | M3: =IF($V3="","",SUMIFS('Per Line'!$AC$2:$AC$1501,'Per Line'!$C$2:$C$1501,$C3,'Per Line'!$AK$2:$AK$1501,0)) | N3: =IF($V3="","",M3*L3) | O3: =IF($V3="","",Settings!$C$6) | P3: =IF($V3="","",SUMIFS('Per Line'!$AC$2:$AC$1501,'Per Line'!$C$2:$C$1501,$C3,'Per Line'!$AK$2:$AK$1501,1)) | Q3: =IF($V3="","",P3*O3) | R3: =IF($V3="","",Q3+N3) | S3: =IF($V3="","",T3-R3) | T3: =IF($V3="","",M3+P3) | U3: =IF($V3="","",T3-R3-K3) | V3: =IF(ROWS($V$2:$V3)<=MAX('Per Line'!$AJ$2:$AJ$1501),MATCH(ROWS($V$2:$V3),'Per Line'!$AJ$2:$AJ$1501,0),"")
B4: =IF($V4="","",INDEX('Per Line'!$A$2:$A$1501,$V4)&"") | C4: =IF($V4="","",INDEX('Per Line'!$C$2:$C$1501,$V4)&"") | D4: =IF($V4="","",INDEX('Per Line'!$S$2:$S$1501,$V4)) | E4: =IF($V4="","",INDEX('Per Line'!$F$2:$F$1501,$V4)&"") | F4: =IF($V4="","",INDEX('Per Line'!$L$2:$L$1501,$V4)&"") | G4: =IF($V4="","",INDEX('Per Line'!$O$2:$O$1501,$V4)&"") | H4: =IF($V4="","",INDEX('Per Line'!$P$2:$P$1501,$V4)&"") | I4: =IF($V4="","",INDEX('Per Line'!$N$2:$N$1501,$V4)&"") | J4: =IF($V4="","",INDEX('Per Line'!$Q$2:$Q$1501,$V4)) | K4: =IF($V4="","",J4*T4/100) | L4: =IF($V4="","",Settings!$C$7) | M4: =IF($V4="","",SUMIFS('Per Line'!$AC$2:$AC$1501,'Per Line'!$C$2:$C$1501,$C4,'Per Line'!$AK$2:$AK$1501,0)) | N4: =IF($V4="","",M4*L4) | O4: =IF($V4="","",Settings!$C$6) | P4: =IF($V4="","",SUMIFS('Per Line'!$AC$2:$AC$1501,'Per Line'!$C$2:$C$1501,$C4,'Per Line'!$AK$2:$AK$1501,1)) | Q4: =IF($V4="","",P4*O4) | R4: =IF($V4="","",Q4+N4) | S4: =IF($V4="","",T4-R4) | T4: =IF($V4="","",M4+P4) | U4: =IF($V4="","",T4-R4-K4) | V4: =IF(ROWS($V$2:$V4)<=MAX('Per Line'!$AJ$2:$AJ$1501),MATCH(ROWS($V$2:$V4),'Per Line'!$AJ$2:$AJ$1501,0),"")
B5: =IF($V5="","",INDEX('Per Line'!$A$2:$A$1501,$V5)&"") | C5: =IF($V5="","",INDEX('Per Line'!$C$2:$C$1501,$V5)&"") | D5: =IF($V5="","",INDEX('Per Line'!$S$2:$S$1501,$V5)) | E5: =IF($V5="","",INDEX('Per Line'!$F$2:$F$1501,$V5)&"") | F5: =IF($V5="","",INDEX('Per Line'!$L$2:$L$1501,$V5)&"") | G5: =IF($V5="","",INDEX('Per Line'!$O$2:$O$1501,$V5)&"") | H5: =IF($V5="","",INDEX('Per Line'!$P$2:$P$1501,$V5)&"") | I5: =IF($V5="","",INDEX('Per Line'!$N$2:$N$1501,$V5)&"") | J5: =IF($V5="","",INDEX('Per Line'!$Q$2:$Q$1501,$V5)) | K5: =IF($V5="","",J5*T5/100) | L5: =IF($V5="","",Settings!$C$7) | M5: =IF($V5="","",SUMIFS('Per Line'!$AC$2:$AC$1501,'Per Line'!$C$2:$C$1501,$C5,'Per Line'!$AK$2:$AK$1501,0)) | N5: =IF($V5="","",M5*L5) | O5: =IF($V5="","",Settings!$C$6) | P5: =IF($V5="","",SUMIFS('Per Line'!$AC$2:$AC$1501,'Per Line'!$C$2:$C$1501,$C5,'Per Line'!$AK$2:$AK$1501,1)) | Q5: =IF($V5="","",P5*O5) | R5: =IF($V5="","",Q5+N5) | S5: =IF($V5="","",T5-R5) | T5: =IF($V5="","",M5+P5) | U5: =IF($V5="","",T5-R5-K5) | V5: =IF(ROWS($V$2:$V5)<=MAX('Per Line'!$AJ$2:$AJ$1501),MATCH(ROWS($V$2:$V5),'Per Line'!$AJ$2:$AJ$1501,0),"")
B6: =IF($V6="","",INDEX('Per Line'!$A$2:$A$1501,$V6)&"") | C6: =IF($V6="","",INDEX('Per Line'!$C$2:$C$1501,$V6)&"") | D6: =IF($V6="","",INDEX('Per Line'!$S$2:$S$1501,$V6)) | E6: =IF($V6="","",INDEX('Per Line'!$F$2:$F$1501,$V6)&"") | F6: =IF($V6="","",INDEX('Per Line'!$L$2:$L$1501,$V6)&"") | G6: =IF($V6="","",INDEX('Per Line'!$O$2:$O$1501,$V6)&"") | H6: =IF($V6="","",INDEX('Per Line'!$P$2:$P$1501,$V6)&"") | I6: =IF($V6="","",INDEX('Per Line'!$N$2:$N$1501,$V6)&"") | J6: =IF($V6="","",INDEX('Per Line'!$Q$2:$Q$1501,$V6)) | K6: =IF($V6="","",J6*T6/100) | L6: =IF($V6="","",Settings!$C$7) | M6: =IF($V6="","",SUMIFS('Per Line'!$AC$2:$AC$1501,'Per Line'!$C$2:$C$1501,$C6,'Per Line'!$AK$2:$AK$1501,0)) | N6: =IF($V6="","",M6*L6) | O6: =IF($V6="","",Settings!$C$6) | P6: =IF($V6="","",SUMIFS('Per Line'!$AC$2:$AC$1501,'Per Line'!$C$2:$C$1501,$C6,'Per Line'!$AK$2:$AK$1501,1)) | Q6: =IF($V6="","",P6*O6) | R6: =IF($V6="","",Q6+N6) | S6: =IF($V6="","",T6-R6) | T6: =IF($V6="","",M6+P6) | U6: =IF($V6="","",T6-R6-K6) | V6: =IF(ROWS($V$2:$V6)<=MAX('Per Line'!$AJ$2:$AJ$1501),MATCH(ROWS($V$2:$V6),'Per Line'!$AJ$2:$AJ$1501,0),"")
B7: =IF($V7="","",INDEX('Per Line'!$A$2:$A$1501,$V7)&"") | C7: =IF($V7="","",INDEX('Per Line'!$C$2:$C$1501,$V7)&"") | D7: =IF($V7="","",INDEX('Per Line'!$S$2:$S$1501,$V7)) | E7: =IF($V7="","",INDEX('Per Line'!$F$2:$F$1501,$V7)&"") | F7: =IF($V7="","",INDEX('Per Line'!$L$2:$L$1501,$V7)&"") | G7: =IF($V7="","",INDEX('Per Line'!$O$2:$O$1501,$V7)&"") | H7: =IF($V7="","",INDEX('Per Line'!$P$2:$P$1501,$V7)&"") | I7: =IF($V7="","",INDEX('Per Line'!$N$2:$N$1501,$V7)&"") | J7: =IF($V7="","",INDEX('Per Line'!$Q$2:$Q$1501,$V7)) | K7: =IF($V7="","",J7*T7/100) | L7: =IF($V7="","",Settings!$C$7) | M7: =IF($V7="","",SUMIFS('Per Line'!$AC$2:$AC$1501,'Per Line'!$C$2:$C$1501,$C7,'Per Line'!$AK$2:$AK$1501,0)) | N7: =IF($V7="","",M7*L7) | O7: =IF($V7="","",Settings!$C$6) | P7: =IF($V7="","",SUMIFS('Per Line'!$AC$2:$AC$1501,'Per Line'!$C$2:$C$1501,$C7,'Per Line'!$AK$2:$AK$1501,1)) | Q7: =IF($V7="","",P7*O7) | R7: =IF($V7="","",Q7+N7) | S7: =IF($V7="","",T7-R7) | T7: =IF($V7="","",M7+P7) | U7: =IF($V7="","",T7-R7-K7) | V7: =IF(ROWS($V$2:$V7)<=MAX('Per Line'!$AJ$2:$AJ$1501),MATCH(ROWS($V$2:$V7),'Per Line'!$AJ$2:$AJ$1501,0),"")
B8: =IF($V8="","",INDEX('Per Line'!$A$2:$A$1501,$V8)&"") | C8: =IF($V8="","",INDEX('Per Line'!$C$2:$C$1501,$V8)&"") | D8: =IF($V8="","",INDEX('Per Line'!$S$2:$S$1501,$V8)) | E8: =IF($V8="","",INDEX('Per Line'!$F$2:$F$1501,$V8)&"") | F8: =IF($V8="","",INDEX('Per Line'!$L$2:$L$1501,$V8)&"") | G8: =IF($V8="","",INDEX('Per Line'!$O$2:$O$1501,$V8)&"") | H8: =IF($V8="","",INDEX('Per Line'!$P$2:$P$1501,$V8)&"") | I8: =IF($V8="","",INDEX('Per Line'!$N$2:$N$1501,$V8)&"") | J8: =IF($V8="","",INDEX('Per Line'!$Q$2:$Q$1501,$V8)) | K8: =IF($V8="","",J8*T8/100) | L8: =IF($V8="","",Settings!$C$7) | M8: =IF($V8="","",SUMIFS('Per Line'!$AC$2:$AC$1501,'Per Line'!$C$2:$C$1501,$C8,'Per Line'!$AK$2:$AK$1501,0)) | N8: =IF($V8="","",M8*L8) | O8: =IF($V8="","",Settings!$C$6) | P8: =IF($V8="","",SUMIFS('Per Line'!$AC$2:$AC$1501,'Per Line'!$C$2:$C$1501,$C8,'Per Line'!$AK$2:$AK$1501,1)) | Q8: =IF($V8="","",P8*O8) | R8: =IF($V8="","",Q8+N8) | S8: =IF($V8="","",T8-R8) | T8: =IF($V8="","",M8+P8) | U8: =IF($V8="","",T8-R8-K8) | V8: =IF(ROWS($V$2:$V8)<=MAX('Per Line'!$AJ$2:$AJ$1501),MATCH(ROWS($V$2:$V8),'Per Line'!$AJ$2:$AJ$1501,0),"")
B9: =IF($V9="","",INDEX('Per Line'!$A$2:$A$1501,$V9)&"") | C9: =IF($V9="","",INDEX('Per Line'!$C$2:$C$1501,$V9)&"") | D9: =IF($V9="","",INDEX('Per Line'!$S$2:$S$1501,$V9)) | E9: =IF($V9="","",INDEX('Per Line'!$F$2:$F$1501,$V9)&"") | F9: =IF($V9="","",INDEX('Per Line'!$L$2:$L$1501,$V9)&"") | G9: =IF($V9="","",INDEX('Per Line'!$O$2:$O$1501,$V9)&"") | H9: =IF($V9="","",INDEX('Per Line'!$P$2:$P$1501,$V9)&"") | I9: =IF($V9="","",INDEX('Per Line'!$N$2:$N$1501,$V9)&"") | J9: =IF($V9="","",INDEX('Per Line'!$Q$2:$Q$1501,$V9)) | K9: =IF($V9="","",J9*T9/100) | L9: =IF($V9="","",Settings!$C$7) | M9: =IF($V9="","",SUMIFS('Per Line'!$AC$2:$AC$1501,'Per Line'!$C$2:$C$1501,$C9,'Per Line'!$AK$2:$AK$1501,0)) | N9: =IF($V9="","",M9*L9) | O9: =IF($V9="","",Settings!$C$6) | P9: =IF($V9="","",SUMIFS('Per Line'!$AC$2:$AC$1501,'Per Line'!$C$2:$C$1501,$C9,'Per Line'!$AK$2:$AK$1501,1)) | Q9: =IF($V9="","",P9*O9) | R9: =IF($V9="","",Q9+N9) | S9: =IF($V9="","",T9-R9) | T9: =IF($V9="","",M9+P9) | U9: =IF($V9="","",T9-R9-K9) | V9: =IF(ROWS($V$2:$V9)<=MAX('Per Line'!$AJ$2:$AJ$1501),MATCH(ROWS($V$2:$V9),'Per Line'!$AJ$2:$AJ$1501,0),"")
B10: =IF($V10="","",INDEX('Per Line'!$A$2:$A$1501,$V10)&"") | C10: =IF($V10="","",INDEX('Per Line'!$C$2:$C$1501,$V10)&"") | D10: =IF($V10="","",INDEX('Per Line'!$S$2:$S$1501,$V10)) | E10: =IF($V10="","",INDEX('Per Line'!$F$2:$F$1501,$V10)&"") | F10: =IF($V10="","",INDEX('Per Line'!$L$2:$L$1501,$V10)&"") | G10: =IF($V10="","",INDEX('Per Line'!$O$2:$O$1501,$V10)&"") | H10: =IF($V10="","",INDEX('Per Line'!$P$2:$P$1501,$V10)&"") | I10: =IF($V10="","",INDEX('Per Line'!$N$2:$N$1501,$V10)&"") | J10: =IF($V10="","",INDEX('Per Line'!$Q$2:$Q$1501,$V10)) | K10: =IF($V10="","",J10*T10/100) | L10: =IF($V10="","",Settings!$C$7) | M10: =IF($V10="","",SUMIFS('Per Line'!$AC$2:$AC$1501,'Per Line'!$C$2:$C$1501,$C10,'Per Line'!$AK$2:$AK$1501,0)) | N10: =IF($V10="","",M10*L10) | O10: =IF($V10="","",Settings!$C$6) | P10: =IF($V10="","",SUMIFS('Per Line'!$AC$2:$AC$1501,'Per Line'!$C$2:$C$1501,$C10,'Per Line'!$AK$2:$AK$1501,1)) | Q10: =IF($V10="","",P10*O10) | R10: =IF($V10="","",Q10+N10) | S10: =IF($V10="","",T10-R10) | T10: =IF($V10="","",M10+P10) | U10: =IF($V10="","",T10-R10-K10) | V10: =IF(ROWS($V$2:$V10)<=MAX('Per Line'!$AJ$2:$AJ$1501),MATCH(ROWS($V$2:$V10),'Per Line'!$AJ$2:$AJ$1501,0),"")
B11: =IF($V11="","",INDEX('Per Line'!$A$2:$A$1501,$V11)&"") | C11: =IF($V11="","",INDEX('Per Line'!$C$2:$C$1501,$V11)&"") | D11: =IF($V11="","",INDEX('Per Line'!$S$2:$S$1501,$V11)) | E11: =IF($V11="","",INDEX('Per Line'!$F$2:$F$1501,$V11)&"") | F11: =IF($V11="","",INDEX('Per Line'!$L$2:$L$1501,$V11)&"") | G11: =IF($V11="","",INDEX('Per Line'!$O$2:$O$1501,$V11)&"") | H11: =IF($V11="","",INDEX('Per Line'!$P$2:$P$1501,$V11)&"") | I11: =IF($V11="","",INDEX('Per Line'!$N$2:$N$1501,$V11)&"") | J11: =IF($V11="","",INDEX('Per Line'!$Q$2:$Q$1501,$V11)) | K11: =IF($V11="","",J11*T11/100) | L11: =IF($V11="","",Settings!$C$7) | M11: =IF($V11="","",SUMIFS('Per Line'!$AC$2:$AC$1501,'Per Line'!$C$2:$C$1501,$C11,'Per Line'!$AK$2:$AK$1501,0)) | N11: =IF($V11="","",M11*L11) | O11: =IF($V11="","",Settings!$C$6) | P11: =IF($V11="","",SUMIFS('Per Line'!$AC$2:$AC$1501,'Per Line'!$C$2:$C$1501,$C11,'Per Line'!$AK$2:$AK$1501,1)) | Q11: =IF($V11="","",P11*O11) | R11: =IF($V11="","",Q11+N11) | S11: =IF($V11="","",T11-R11) | T11: =IF($V11="","",M11+P11) | U11: =IF($V11="","",T11-R11-K11) | V11: =IF(ROWS($V$2:$V11)<=MAX('Per Line'!$AJ$2:$AJ$1501),MATCH(ROWS($V$2:$V11),'Per Line'!$AJ$2:$AJ$1501,0),"")
B12: =IF($V12="","",INDEX('Per Line'!$A$2:$A$1501,$V12)&"") | C12: =IF($V12="","",INDEX('Per Line'!$C$2:$C$1501,$V12)&"") | D12: =IF($V12="","",INDEX('Per Line'!$S$2:$S$1501,$V12)) | E12: =IF($V12="","",INDEX('Per Line'!$F$2:$F$1501,$V12)&"") | F12: =IF($V12="","",INDEX('Per Line'!$L$2:$L$1501,$V12)&"") | G12: =IF($V12="","",INDEX('Per Line'!$O$2:$O$1501,$V12)&"") | H12: =IF($V12="","",INDEX('Per Line'!$P$2:$P$1501,$V12)&"") | I12: =IF($V12="","",INDEX('Per Line'!$N$2:$N$1501,$V12)&"") | J12: =IF($V12="","",INDEX('Per Line'!$Q$2:$Q$1501,$V12)) | K12: =IF($V12="","",J12*T12/100) | L12: =IF($V12="","",Settings!$C$7) | M12: =IF($V12="","",SUMIFS('Per Line'!$AC$2:$AC$1501,'Per Line'!$C$2:$C$1501,$C12,'Per Line'!$AK$2:$AK$1501,0)) | N12: =IF($V12="","",M12*L12) | O12: =IF($V12="","",Settings!$C$6) | P12: =IF($V12="","",SUMIFS('Per Line'!$AC$2:$AC$1501,'Per Line'!$C$2:$C$1501,$C12,'Per Line'!$AK$2:$AK$1501,1)) | Q12: =IF($V12="","",P12*O12) | R12: =IF($V12="","",Q12+N12) | S12: =IF($V12="","",T12-R12) | T12: =IF($V12="","",M12+P12) | U12: =IF($V12="","",T12-R12-K12) | V12: =IF(ROWS($V$2:$V12)<=MAX('Per Line'!$AJ$2:$AJ$1501),MATCH(ROWS($V$2:$V12),'Per Line'!$AJ$2:$AJ$1501,0),"")
B13: =IF($V13="","",INDEX('Per Line'!$A$2:$A$1501,$V13)&"") | C13: =IF($V13="","",INDEX('Per Line'!$C$2:$C$1501,$V13)&"") | D13: =IF($V13="","",INDEX('Per Line'!$S$2:$S$1501,$V13)) | E13: =IF($V13="","",INDEX('Per Line'!$F$2:$F$1501,$V13)&"") | F13: =IF($V13="","",INDEX('Per Line'!$L$2:$L$1501,$V13)&"") | G13: =IF($V13="","",INDEX('Per Line'!$O$2:$O$1501,$V13)&"") | H13: =IF($V13="","",INDEX('Per Line'!$P$2:$P$1501,$V13)&"") | I13: =IF($V13="","",INDEX('Per Line'!$N$2:$N$1501,$V13)&"") | J13: =IF($V13="","",INDEX('Per Line'!$Q$2:$Q$1501,$V13)) | K13: =IF($V13="","",J13*T13/100) | L13: =IF($V13="","",Settings!$C$7) | M13: =IF($V13="","",SUMIFS('Per Line'!$AC$2:$AC$1501,'Per Line'!$C$2:$C$1501,$C13,'Per Line'!$AK$2:$AK$1501,0)) | N13: =IF($V13="","",M13*L13) | O13: =IF($V13="","",Settings!$C$6) | P13: =IF($V13="","",SUMIFS('Per Line'!$AC$2:$AC$1501,'Per Line'!$C$2:$C$1501,$C13,'Per Line'!$AK$2:$AK$1501,1)) | Q13: =IF($V13="","",P13*O13) | R13: =IF($V13="","",Q13+N13) | S13: =IF($V13="","",T13-R13) | T13: =IF($V13="","",M13+P13) | U13: =IF($V13="","",T13-R13-K13) | V13: =IF(ROWS($V$2:$V13)<=MAX('Per Line'!$AJ$2:$AJ$1501),MATCH(ROWS($V$2:$V13),'Per Line'!$AJ$2:$AJ$1501,0),"")
... B501: =IF($V501="","",INDEX('Per Line'!$A$2:$A$1501,$V501)&"") | C501: =IF($V501="","",INDEX('Per Line'!$C$2:$C$1501,$V501)&"") | D501: =IF($V501="","",INDEX('Per Line'!$S$2:$S$1501,$V501)) | E501: =IF($V501="","",INDEX('Per Line'!$F$2:$F$1501,$V501)&"") | F501: =IF($V501="","",INDEX('Per Line'!$L$2:$L$1501,$V501)&"") | G501: =IF($V501="","",INDEX('Per Line'!$O$2:$O$1501,$V501)&"") | H501: =IF($V501="","",INDEX('Per Line'!$P$2:$P$1501,$V501)&"") | I501: =IF($V501="","",INDEX('Per Line'!$N$2:$N$1501,$V501)&"") | J501: =IF($V501="","",INDEX('Per Line'!$Q$2:$Q$1501,$V501)) | K501: =IF($V501="","",J501*T501/100) | L501: =IF($V501="","",Settings!$C$7) | M501: =IF($V501="","",SUMIFS('Per Line'!$AC$2:$AC$1501,'Per Line'!$C$2:$C$1501,$C501,'Per Line'!$AK$2:$AK$1501,0)) | N501: =IF($V501="","",M501*L501) | O501: =IF($V501="","",Settings!$C$6) | P501: =IF($V501="","",SUMIFS('Per Line'!$AC$2:$AC$1501,'Per Line'!$C$2:$C$1501,$C501,'Per Line'!$AK$2:$AK$1501,1)) | Q501: =IF($V501="","",P501*O501) | R501: =IF($V501="","",Q501+N501) | S501: =IF($V501="","",T501-R501) | T501: =IF($V501="","",M501+P501) | U501: =IF($V501="","",T501-R501-K501) | V501: =IF(ROWS($V$2:$V501)<=MAX('Per Line'!$AJ$2:$AJ$1501),MATCH(ROWS($V$2:$V501),'Per Line'!$AJ$2:$AJ$1501,0),"")
