Workbook

Sheet How To Use
A1: Claims Template - NASR MINING (El Nasr Mining - Edfu)
A3: Monthly steps
A4: 1. Open the 'Per Line' tab. Delete the old data in the BLUE columns only (row 2 down). Never delete the green columns.
A5: 2. Paste the new month's data as VALUES starting at A2, into the blue columns: A-M, O-U, Y-AA, AC-AG (same order as the system export).
A6: 3. Green columns (N, V, W, X, AB) and the grey helper columns (AH-AK) calculate automatically - do not paste over them.
A7: 4. 'Per Invoice' fills itself from 'Per Line' (one row per Order #, split into IMP / Local). No pivot table, no refresh.
A8: 5. The ONLY manual column in 'Per Invoice' is column A 'Invoice' (blue): type the invoice number yourself. Everything else is formula.
A9: 6. Open 'Settings' and check STATUS says OK (Per Line totals = Per Invoice totals).
A11: Colour legend
A12: Blue header = typed/pasted by you (raw data, and 'Invoice' in Per Invoice). Green header = formula (do not paste over). Grey header = helper formula (do not touch). Yellow cell (Settings) = editable rate.
A14: Calculation rules (taken from the September sheet)
A15: Co val = Order Co Payment x Product Total / 100. Discount = Product Total x Rebates / 100. Subtotal = Product Total - Discount. Net = Subtotal - Co val.
... A20: Capacity: up to 4,000 lines and 1,500 invoices per month. A line with an empty Order # is ignored.

Sheet Settings
B1: Company settings & checks
B3: Insurance Company | C3: NASR MINING | D3: Informational only
B4: Corporate | C4: El Nasr Mining - Edfu | D4: Informational only
B6: Local products rebate % | C6: 0.15 | D6: Source: September sheet (Rebates = 15 on Local lines, 8 on non-local lines; Per Invoice used 0.15 / 0.08).
B7: Imported (IMP) products rebate % | C7: 0.08 | D7: Change here if the contract rates change - Per Line and Per Invoice both follow.
B9: Month totals / reconciliation
B10: Lines loaded | C10: =COUNTA('Per Line'!$D$2:$D$4001) -> 0
B11: Invoices (unique Order #) | C11: =MAX('Per Line'!$AI$2:$AI$4001) -> 0
B12: Invoices shown in Per Invoice | C12: =SUMPRODUCT(--('Per Invoice'!$B$2:$B$1501<>"")) -> 0
B13: Grand Total - Per Line (Product Total) | C13: =SUM('Per Line'!$Y$2:$Y$4001) -> 0
B14: Grand Total - Per Invoice | C14: =SUM('Per Invoice'!$V$2:$V$1501) -> 0
B15: Discount - Per Line | C15: =SUM('Per Line'!$V$2:$V$4001) -> 0
B16: Discount - Per Invoice | C16: =SUM('Per Invoice'!$T$2:$T$1501) -> 0
B17: Co val - Per Invoice | C17: =SUM('Per Invoice'!$L$2:$L$1501) -> 0
B18: Net - Per Line | C18: =SUM('Per Line'!$X$2:$X$4001) -> 0
B19: Net - Per Invoice | C19: =SUM('Per Invoice'!$W$2:$W$1501) -> 0
B21: STATUS | C21: =IF(C10=0,"No data loaded",IF(COUNTA('Per Line'!$D:$D)-1>4000,"TOO MANY LINES - extend template",IF(C11>1500,"TOO MANY INVOICES - extend template",IF(AND(ROUND(C13-C14,2)=0,ROUND(C15-C16,2)=0,ROUND(C18-C19,2)=0,C11=C12),"OK","CHECK - Per Line and Per Invoice do not match")))) -> No data loaded

Sheet Per Line
A1: Cycle | B1: Ticket # | C1: Stage | D1: Order # | E1: Channel | F1: Create At | G1: Insurance Company | H1: Country Portal ID | I1: Corporate | J1: Card | K1: Name | L1: Status | M1: Order Co Payment | N1: Co val | O1: By Patient | P1: heisenberg id | Q1: Product Name | R1: Local | S1: Unit | T1: Quantity | U1: Unit Price | V1: Discount | W1: Subtotal | X1: Net | Y1: Product Total | Z1: ERX ID | AA1: Special Rebates? | AB1: Rebates | AC1: Approval Type | AD1: Max Limit | AE1: Exceeding Limit | AF1: By Patient (Delivered) | AG1: Has OTP? | AH1: Order 1st Row (helper) | AI1: Invoice # (helper) | AJ1: Is Local (helper) | AK1: Sort Key (helper)
N2: =IF($D2="","",M2*Y2/100) | V2: =IF($D2="","",Y2*AB2/100) | W2: =IF($D2="","",Y2-V2) | X2: =IF($D2="","",W2-N2) | AB2: =IF($D2="","",IF(OR($R2=TRUE(),$R2="TRUE"),Settings!$C$6,Settings!$C$7)*100) | AH2: =IF($D2="","",IF(COUNTIF($D$2:$D2,$D2)=1,1,0)) | AI2: =IF($AH2=1,SUMPRODUCT(--($AK$2:$AK$4001<$AK2))+1,"") | AJ2: =IF($D2="","",IF(OR($R2=TRUE(),$R2="TRUE"),1,0)) | AK2: =IF($AH2=1,IFERROR(VALUE(MID($D2,2,20)),1000000000)+ROW()/10000000,"")
N3: =IF($D3="","",M3*Y3/100) | V3: =IF($D3="","",Y3*AB3/100) | W3: =IF($D3="","",Y3-V3) | X3: =IF($D3="","",W3-N3) | AB3: =IF($D3="","",IF(OR($R3=TRUE(),$R3="TRUE"),Settings!$C$6,Settings!$C$7)*100) | AH3: =IF($D3="","",IF(COUNTIF($D$2:$D3,$D3)=1,1,0)) | AI3: =IF($AH3=1,SUMPRODUCT(--($AK$2:$AK$4001<$AK3))+1,"") | AJ3: =IF($D3="","",IF(OR($R3=TRUE(),$R3="TRUE"),1,0)) | AK3: =IF($AH3=1,IFERROR(VALUE(MID($D3,2,20)),1000000000)+ROW()/10000000,"")
N4: =IF($D4="","",M4*Y4/100) | V4: =IF($D4="","",Y4*AB4/100) | W4: =IF($D4="","",Y4-V4) | X4: =IF($D4="","",W4-N4) | AB4: =IF($D4="","",IF(OR($R4=TRUE(),$R4="TRUE"),Settings!$C$6,Settings!$C$7)*100) | AH4: =IF($D4="","",IF(COUNTIF($D$2:$D4,$D4)=1,1,0)) | AI4: =IF($AH4=1,SUMPRODUCT(--($AK$2:$AK$4001<$AK4))+1,"") | AJ4: =IF($D4="","",IF(OR($R4=TRUE(),$R4="TRUE"),1,0)) | AK4: =IF($AH4=1,IFERROR(VALUE(MID($D4,2,20)),1000000000)+ROW()/10000000,"")
N5: =IF($D5="","",M5*Y5/100) | V5: =IF($D5="","",Y5*AB5/100) | W5: =IF($D5="","",Y5-V5) | X5: =IF($D5="","",W5-N5) | AB5: =IF($D5="","",IF(OR($R5=TRUE(),$R5="TRUE"),Settings!$C$6,Settings!$C$7)*100) | AH5: =IF($D5="","",IF(COUNTIF($D$2:$D5,$D5)=1,1,0)) | AI5: =IF($AH5=1,SUMPRODUCT(--($AK$2:$AK$4001<$AK5))+1,"") | AJ5: =IF($D5="","",IF(OR($R5=TRUE(),$R5="TRUE"),1,0)) | AK5: =IF($AH5=1,IFERROR(VALUE(MID($D5,2,20)),1000000000)+ROW()/10000000,"")
N6: =IF($D6="","",M6*Y6/100) | V6: =IF($D6="","",Y6*AB6/100) | W6: =IF($D6="","",Y6-V6) | X6: =IF($D6="","",W6-N6) | AB6: =IF($D6="","",IF(OR($R6=TRUE(),$R6="TRUE"),Settings!$C$6,Settings!$C$7)*100) | AH6: =IF($D6="","",IF(COUNTIF($D$2:$D6,$D6)=1,1,0)) | AI6: =IF($AH6=1,SUMPRODUCT(--($AK$2:$AK$4001<$AK6))+1,"") | AJ6: =IF($D6="","",IF(OR($R6=TRUE(),$R6="TRUE"),1,0)) | AK6: =IF($AH6=1,IFERROR(VALUE(MID($D6,2,20)),1000000000)+ROW()/10000000,"")
N7: =IF($D7="","",M7*Y7/100) | V7: =IF($D7="","",Y7*AB7/100) | W7: =IF($D7="","",Y7-V7) | X7: =IF($D7="","",W7-N7) | AB7: =IF($D7="","",IF(OR($R7=TRUE(),$R7="TRUE"),Settings!$C$6,Settings!$C$7)*100) | AH7: =IF($D7="","",IF(COUNTIF($D$2:$D7,$D7)=1,1,0)) | AI7: =IF($AH7=1,SUMPRODUCT(--($AK$2:$AK$4001<$AK7))+1,"") | AJ7: =IF($D7="","",IF(OR($R7=TRUE(),$R7="TRUE"),1,0)) | AK7: =IF($AH7=1,IFERROR(VALUE(MID($D7,2,20)),1000000000)+ROW()/10000000,"")
N8: =IF($D8="","",M8*Y8/100) | V8: =IF($D8="","",Y8*AB8/100) | W8: =IF($D8="","",Y8-V8) | X8: =IF($D8="","",W8-N8) | AB8: =IF($D8="","",IF(OR($R8=TRUE(),$R8="TRUE"),Settings!$C$6,Settings!$C$7)*100) | AH8: =IF($D8="","",IF(COUNTIF($D$2:$D8,$D8)=1,1,0)) | AI8: =IF($AH8=1,SUMPRODUCT(--($AK$2:$AK$4001<$AK8))+1,"") | AJ8: =IF($D8="","",IF(OR($R8=TRUE(),$R8="TRUE"),1,0)) | AK8: =IF($AH8=1,IFERROR(VALUE(MID($D8,2,20)),1000000000)+ROW()/10000000,"")
N9: =IF($D9="","",M9*Y9/100) | V9: =IF($D9="","",Y9*AB9/100) | W9: =IF($D9="","",Y9-V9) | X9: =IF($D9="","",W9-N9) | AB9: =IF($D9="","",IF(OR($R9=TRUE(),$R9="TRUE"),Settings!$C$6,Settings!$C$7)*100) | AH9: =IF($D9="","",IF(COUNTIF($D$2:$D9,$D9)=1,1,0)) | AI9: =IF($AH9=1,SUMPRODUCT(--($AK$2:$AK$4001<$AK9))+1,"") | AJ9: =IF($D9="","",IF(OR($R9=TRUE(),$R9="TRUE"),1,0)) | AK9: =IF($AH9=1,IFERROR(VALUE(MID($D9,2,20)),1000000000)+ROW()/10000000,"")
N10: =IF($D10="","",M10*Y10/100) | V10: =IF($D10="","",Y10*AB10/100) | W10: =IF($D10="","",Y10-V10) | X10: =IF($D10="","",W10-N10) | AB10: =IF($D10="","",IF(OR($R10=TRUE(),$R10="TRUE"),Settings!$C$6,Settings!$C$7)*100) | AH10: =IF($D10="","",IF(COUNTIF($D$2:$D10,$D10)=1,1,0)) | AI10: =IF($AH10=1,SUMPRODUCT(--($AK$2:$AK$4001<$AK10))+1,"") | AJ10: =IF($D10="","",IF(OR($R10=TRUE(),$R10="TRUE"),1,0)) | AK10: =IF($AH10=1,IFERROR(VALUE(MID($D10,2,20)),1000000000)+ROW()/10000000,"")
N11: =IF($D11="","",M11*Y11/100) | V11: =IF($D11="","",Y11*AB11/100) | W11: =IF($D11="","",Y11-V11) | X11: =IF($D11="","",W11-N11) | AB11: =IF($D11="","",IF(OR($R11=TRUE(),$R11="TRUE"),Settings!$C$6,Settings!$C$7)*100) | AH11: =IF($D11="","",IF(COUNTIF($D$2:$D11,$D11)=1,1,0)) | AI11: =IF($AH11=1,SUMPRODUCT(--($AK$2:$AK$4001<$AK11))+1,"") | AJ11: =IF($D11="","",IF(OR($R11=TRUE(),$R11="TRUE"),1,0)) | AK11: =IF($AH11=1,IFERROR(VALUE(MID($D11,2,20)),1000000000)+ROW()/10000000,"")
N12: =IF($D12="","",M12*Y12/100) | V12: =IF($D12="","",Y12*AB12/100) | W12: =IF($D12="","",Y12-V12) | X12: =IF($D12="","",W12-N12) | AB12: =IF($D12="","",IF(OR($R12=TRUE(),$R12="TRUE"),Settings!$C$6,Settings!$C$7)*100) | AH12: =IF($D12="","",IF(COUNTIF($D$2:$D12,$D12)=1,1,0)) | AI12: =IF($AH12=1,SUMPRODUCT(--($AK$2:$AK$4001<$AK12))+1,"") | AJ12: =IF($D12="","",IF(OR($R12=TRUE(),$R12="TRUE"),1,0)) | AK12: =IF($AH12=1,IFERROR(VALUE(MID($D12,2,20)),1000000000)+ROW()/10000000,"")
N13: =IF($D13="","",M13*Y13/100) | V13: =IF($D13="","",Y13*AB13/100) | W13: =IF($D13="","",Y13-V13) | X13: =IF($D13="","",W13-N13) | AB13: =IF($D13="","",IF(OR($R13=TRUE(),$R13="TRUE"),Settings!$C$6,Settings!$C$7)*100) | AH13: =IF($D13="","",IF(COUNTIF($D$2:$D13,$D13)=1,1,0)) | AI13: =IF($AH13=1,SUMPRODUCT(--($AK$2:$AK$4001<$AK13))+1,"") | AJ13: =IF($D13="","",IF(OR($R13=TRUE(),$R13="TRUE"),1,0)) | AK13: =IF($AH13=1,IFERROR(VALUE(MID($D13,2,20)),1000000000)+ROW()/10000000,"")
... N4001: =IF($D4001="","",M4001*Y4001/100) | V4001: =IF($D4001="","",Y4001*AB4001/100) | W4001: =IF($D4001="","",Y4001-V4001) | X4001: =IF($D4001="","",W4001-N4001) | AB4001: =IF($D4001="","",IF(OR($R4001=TRUE(),$R4001="TRUE"),Settings!$C$6,Settings!$C$7)*100) | AH4001: =IF($D4001="","",IF(COUNTIF($D$2:$D4001,$D4001)=1,1,0)) | AI4001: =IF($AH4001=1,SUMPRODUCT(--($AK$2:$AK$4001<$AK4001))+1,"") | AJ4001: =IF($D4001="","",IF(OR($R4001=TRUE(),$R4001="TRUE"),1,0)) | AK4001: =IF($AH4001=1,IFERROR(VALUE(MID($D4001,2,20)),1000000000)+ROW()/10000000,"")

Sheet Per Invoice
A1: Invoice | B1: Order # | C1: Stage | D1: Cycle | E1: Create At | F1: Insurance Company | G1: Corporate | H1: Card | I1: Name | J1: Status | K1: Order Co Payment | L1: Co val | M1: ERX ID | N1: % | O1: IMP | P1: IMP val | Q1: % | R1: Local | S1: Local val | T1: Discount | U1: Subtotal | V1: Grand Total | W1: Net | X1: Src Row (helper)
B2: =IF($X2="","",INDEX('Per Line'!$D$2:$D$4001,$X2)) | C2: =IF($X2="","",INDEX('Per Line'!$C$2:$C$4001,$X2)) | D2: =IF($X2="","",INDEX('Per Line'!$A$2:$A$4001,$X2)) | E2: =IF($X2="","",INDEX('Per Line'!$F$2:$F$4001,$X2)) | F2: =IF($X2="","",INDEX('Per Line'!$G$2:$G$4001,$X2)) | G2: =IF($X2="","",INDEX('Per Line'!$I$2:$I$4001,$X2)) | H2: =IF($X2="","",INDEX('Per Line'!$J$2:$J$4001,$X2)) | I2: =IF($X2="","",INDEX('Per Line'!$K$2:$K$4001,$X2)) | J2: =IF($X2="","",INDEX('Per Line'!$L$2:$L$4001,$X2)) | K2: =IF($X2="","",INDEX('Per Line'!$M$2:$M$4001,$X2)) | L2: =IF($X2="","",K2*V2/100) | M2: =IF($X2="","",INDEX('Per Line'!$Z$2:$Z$4001,$X2)) | N2: =IF($X2="","",Settings!$C$7) | O2: =IF($X2="","",SUMIFS('Per Line'!$Y$2:$Y$4001,'Per Line'!$D$2:$D$4001,$B2,'Per Line'!$AJ$2:$AJ$4001,0)) | P2: =IF($X2="","",O2*N2) | Q2: =IF($X2="","",Settings!$C$6) | R2: =IF($X2="","",SUMIFS('Per Line'!$Y$2:$Y$4001,'Per Line'!$D$2:$D$4001,$B2,'Per Line'!$AJ$2:$AJ$4001,1)) | S2: =IF($X2="","",R2*Q2) | T2: =IF($X2="","",S2+P2) | U2: =IF($X2="","",V2-T2) | V2: =IF($X2="","",O2+R2) | W2: =IF($X2="","",U2-L2) | X2: =IF(ROWS($X$2:$X2)<=MAX('Per Line'!$AI$2:$AI$4001),MATCH(ROWS($X$2:$X2),'Per Line'!$AI$2:$AI$4001,0),"")
B3: =IF($X3="","",INDEX('Per Line'!$D$2:$D$4001,$X3)) | C3: =IF($X3="","",INDEX('Per Line'!$C$2:$C$4001,$X3)) | D3: =IF($X3="","",INDEX('Per Line'!$A$2:$A$4001,$X3)) | E3: =IF($X3="","",INDEX('Per Line'!$F$2:$F$4001,$X3)) | F3: =IF($X3="","",INDEX('Per Line'!$G$2:$G$4001,$X3)) | G3: =IF($X3="","",INDEX('Per Line'!$I$2:$I$4001,$X3)) | H3: =IF($X3="","",INDEX('Per Line'!$J$2:$J$4001,$X3)) | I3: =IF($X3="","",INDEX('Per Line'!$K$2:$K$4001,$X3)) | J3: =IF($X3="","",INDEX('Per Line'!$L$2:$L$4001,$X3)) | K3: =IF($X3="","",INDEX('Per Line'!$M$2:$M$4001,$X3)) | L3: =IF($X3="","",K3*V3/100) | M3: =IF($X3="","",INDEX('Per Line'!$Z$2:$Z$4001,$X3)) | N3: =IF($X3="","",Settings!$C$7) | O3: =IF($X3="","",SUMIFS('Per Line'!$Y$2:$Y$4001,'Per Line'!$D$2:$D$4001,$B3,'Per Line'!$AJ$2:$AJ$4001,0)) | P3: =IF($X3="","",O3*N3) | Q3: =IF($X3="","",Settings!$C$6) | R3: =IF($X3="","",SUMIFS('Per Line'!$Y$2:$Y$4001,'Per Line'!$D$2:$D$4001,$B3,'Per Line'!$AJ$2:$AJ$4001,1)) | S3: =IF($X3="","",R3*Q3) | T3: =IF($X3="","",S3+P3) | U3: =IF($X3="","",V3-T3) | V3: =IF($X3="","",O3+R3) | W3: =IF($X3="","",U3-L3) | X3: =IF(ROWS($X$2:$X3)<=MAX('Per Line'!$AI$2:$AI$4001),MATCH(ROWS($X$2:$X3),'Per Line'!$AI$2:$AI$4001,0),"")
B4: =IF($X4="","",INDEX('Per Line'!$D$2:$D$4001,$X4)) | C4: =IF($X4="","",INDEX('Per Line'!$C$2:$C$4001,$X4)) | D4: =IF($X4="","",INDEX('Per Line'!$A$2:$A$4001,$X4)) | E4: =IF($X4="","",INDEX('Per Line'!$F$2:$F$4001,$X4)) | F4: =IF($X4="","",INDEX('Per Line'!$G$2:$G$4001,$X4)) | G4: =IF($X4="","",INDEX('Per Line'!$I$2:$I$4001,$X4)) | H4: =IF($X4="","",INDEX('Per Line'!$J$2:$J$4001,$X4)) | I4: =IF($X4="","",INDEX('Per Line'!$K$2:$K$4001,$X4)) | J4: =IF($X4="","",INDEX('Per Line'!$L$2:$L$4001,$X4)) | K4: =IF($X4="","",INDEX('Per Line'!$M$2:$M$4001,$X4)) | L4: =IF($X4="","",K4*V4/100) | M4: =IF($X4="","",INDEX('Per Line'!$Z$2:$Z$4001,$X4)) | N4: =IF($X4="","",Settings!$C$7) | O4: =IF($X4="","",SUMIFS('Per Line'!$Y$2:$Y$4001,'Per Line'!$D$2:$D$4001,$B4,'Per Line'!$AJ$2:$AJ$4001,0)) | P4: =IF($X4="","",O4*N4) | Q4: =IF($X4="","",Settings!$C$6) | R4: =IF($X4="","",SUMIFS('Per Line'!$Y$2:$Y$4001,'Per Line'!$D$2:$D$4001,$B4,'Per Line'!$AJ$2:$AJ$4001,1)) | S4: =IF($X4="","",R4*Q4) | T4: =IF($X4="","",S4+P4) | U4: =IF($X4="","",V4-T4) | V4: =IF($X4="","",O4+R4) | W4: =IF($X4="","",U4-L4) | X4: =IF(ROWS($X$2:$X4)<=MAX('Per Line'!$AI$2:$AI$4001),MATCH(ROWS($X$2:$X4),'Per Line'!$AI$2:$AI$4001,0),"")
B5: =IF($X5="","",INDEX('Per Line'!$D$2:$D$4001,$X5)) | C5: =IF($X5="","",INDEX('Per Line'!$C$2:$C$4001,$X5)) | D5: =IF($X5="","",INDEX('Per Line'!$A$2:$A$4001,$X5)) | E5: =IF($X5="","",INDEX('Per Line'!$F$2:$F$4001,$X5)) | F5: =IF($X5="","",INDEX('Per Line'!$G$2:$G$4001,$X5)) | G5: =IF($X5="","",INDEX('Per Line'!$I$2:$I$4001,$X5)) | H5: =IF($X5="","",INDEX('Per Line'!$J$2:$J$4001,$X5)) | I5: =IF($X5="","",INDEX('Per Line'!$K$2:$K$4001,$X5)) | J5: =IF($X5="","",INDEX('Per Line'!$L$2:$L$4001,$X5)) | K5: =IF($X5="","",INDEX('Per Line'!$M$2:$M$4001,$X5)) | L5: =IF($X5="","",K5*V5/100) | M5: =IF($X5="","",INDEX('Per Line'!$Z$2:$Z$4001,$X5)) | N5: =IF($X5="","",Settings!$C$7) | O5: =IF($X5="","",SUMIFS('Per Line'!$Y$2:$Y$4001,'Per Line'!$D$2:$D$4001,$B5,'Per Line'!$AJ$2:$AJ$4001,0)) | P5: =IF($X5="","",O5*N5) | Q5: =IF($X5="","",Settings!$C$6) | R5: =IF($X5="","",SUMIFS('Per Line'!$Y$2:$Y$4001,'Per Line'!$D$2:$D$4001,$B5,'Per Line'!$AJ$2:$AJ$4001,1)) | S5: =IF($X5="","",R5*Q5) | T5: =IF($X5="","",S5+P5) | U5: =IF($X5="","",V5-T5) | V5: =IF($X5="","",O5+R5) | W5: =IF($X5="","",U5-L5) | X5: =IF(ROWS($X$2:$X5)<=MAX('Per Line'!$AI$2:$AI$4001),MATCH(ROWS($X$2:$X5),'Per Line'!$AI$2:$AI$4001,0),"")
B6: =IF($X6="","",INDEX('Per Line'!$D$2:$D$4001,$X6)) | C6: =IF($X6="","",INDEX('Per Line'!$C$2:$C$4001,$X6)) | D6: =IF($X6="","",INDEX('Per Line'!$A$2:$A$4001,$X6)) | E6: =IF($X6="","",INDEX('Per Line'!$F$2:$F$4001,$X6)) | F6: =IF($X6="","",INDEX('Per Line'!$G$2:$G$4001,$X6)) | G6: =IF($X6="","",INDEX('Per Line'!$I$2:$I$4001,$X6)) | H6: =IF($X6="","",INDEX('Per Line'!$J$2:$J$4001,$X6)) | I6: =IF($X6="","",INDEX('Per Line'!$K$2:$K$4001,$X6)) | J6: =IF($X6="","",INDEX('Per Line'!$L$2:$L$4001,$X6)) | K6: =IF($X6="","",INDEX('Per Line'!$M$2:$M$4001,$X6)) | L6: =IF($X6="","",K6*V6/100) | M6: =IF($X6="","",INDEX('Per Line'!$Z$2:$Z$4001,$X6)) | N6: =IF($X6="","",Settings!$C$7) | O6: =IF($X6="","",SUMIFS('Per Line'!$Y$2:$Y$4001,'Per Line'!$D$2:$D$4001,$B6,'Per Line'!$AJ$2:$AJ$4001,0)) | P6: =IF($X6="","",O6*N6) | Q6: =IF($X6="","",Settings!$C$6) | R6: =IF($X6="","",SUMIFS('Per Line'!$Y$2:$Y$4001,'Per Line'!$D$2:$D$4001,$B6,'Per Line'!$AJ$2:$AJ$4001,1)) | S6: =IF($X6="","",R6*Q6) | T6: =IF($X6="","",S6+P6) | U6: =IF($X6="","",V6-T6) | V6: =IF($X6="","",O6+R6) | W6: =IF($X6="","",U6-L6) | X6: =IF(ROWS($X$2:$X6)<=MAX('Per Line'!$AI$2:$AI$4001),MATCH(ROWS($X$2:$X6),'Per Line'!$AI$2:$AI$4001,0),"")
B7: =IF($X7="","",INDEX('Per Line'!$D$2:$D$4001,$X7)) | C7: =IF($X7="","",INDEX('Per Line'!$C$2:$C$4001,$X7)) | D7: =IF($X7="","",INDEX('Per Line'!$A$2:$A$4001,$X7)) | E7: =IF($X7="","",INDEX('Per Line'!$F$2:$F$4001,$X7)) | F7: =IF($X7="","",INDEX('Per Line'!$G$2:$G$4001,$X7)) | G7: =IF($X7="","",INDEX('Per Line'!$I$2:$I$4001,$X7)) | H7: =IF($X7="","",INDEX('Per Line'!$J$2:$J$4001,$X7)) | I7: =IF($X7="","",INDEX('Per Line'!$K$2:$K$4001,$X7)) | J7: =IF($X7="","",INDEX('Per Line'!$L$2:$L$4001,$X7)) | K7: =IF($X7="","",INDEX('Per Line'!$M$2:$M$4001,$X7)) | L7: =IF($X7="","",K7*V7/100) | M7: =IF($X7="","",INDEX('Per Line'!$Z$2:$Z$4001,$X7)) | N7: =IF($X7="","",Settings!$C$7) | O7: =IF($X7="","",SUMIFS('Per Line'!$Y$2:$Y$4001,'Per Line'!$D$2:$D$4001,$B7,'Per Line'!$AJ$2:$AJ$4001,0)) | P7: =IF($X7="","",O7*N7) | Q7: =IF($X7="","",Settings!$C$6) | R7: =IF($X7="","",SUMIFS('Per Line'!$Y$2:$Y$4001,'Per Line'!$D$2:$D$4001,$B7,'Per Line'!$AJ$2:$AJ$4001,1)) | S7: =IF($X7="","",R7*Q7) | T7: =IF($X7="","",S7+P7) | U7: =IF($X7="","",V7-T7) | V7: =IF($X7="","",O7+R7) | W7: =IF($X7="","",U7-L7) | X7: =IF(ROWS($X$2:$X7)<=MAX('Per Line'!$AI$2:$AI$4001),MATCH(ROWS($X$2:$X7),'Per Line'!$AI$2:$AI$4001,0),"")
B8: =IF($X8="","",INDEX('Per Line'!$D$2:$D$4001,$X8)) | C8: =IF($X8="","",INDEX('Per Line'!$C$2:$C$4001,$X8)) | D8: =IF($X8="","",INDEX('Per Line'!$A$2:$A$4001,$X8)) | E8: =IF($X8="","",INDEX('Per Line'!$F$2:$F$4001,$X8)) | F8: =IF($X8="","",INDEX('Per Line'!$G$2:$G$4001,$X8)) | G8: =IF($X8="","",INDEX('Per Line'!$I$2:$I$4001,$X8)) | H8: =IF($X8="","",INDEX('Per Line'!$J$2:$J$4001,$X8)) | I8: =IF($X8="","",INDEX('Per Line'!$K$2:$K$4001,$X8)) | J8: =IF($X8="","",INDEX('Per Line'!$L$2:$L$4001,$X8)) | K8: =IF($X8="","",INDEX('Per Line'!$M$2:$M$4001,$X8)) | L8: =IF($X8="","",K8*V8/100) | M8: =IF($X8="","",INDEX('Per Line'!$Z$2:$Z$4001,$X8)) | N8: =IF($X8="","",Settings!$C$7) | O8: =IF($X8="","",SUMIFS('Per Line'!$Y$2:$Y$4001,'Per Line'!$D$2:$D$4001,$B8,'Per Line'!$AJ$2:$AJ$4001,0)) | P8: =IF($X8="","",O8*N8) | Q8: =IF($X8="","",Settings!$C$6) | R8: =IF($X8="","",SUMIFS('Per Line'!$Y$2:$Y$4001,'Per Line'!$D$2:$D$4001,$B8,'Per Line'!$AJ$2:$AJ$4001,1)) | S8: =IF($X8="","",R8*Q8) | T8: =IF($X8="","",S8+P8) | U8: =IF($X8="","",V8-T8) | V8: =IF($X8="","",O8+R8) | W8: =IF($X8="","",U8-L8) | X8: =IF(ROWS($X$2:$X8)<=MAX('Per Line'!$AI$2:$AI$4001),MATCH(ROWS($X$2:$X8),'Per Line'!$AI$2:$AI$4001,0),"")
B9: =IF($X9="","",INDEX('Per Line'!$D$2:$D$4001,$X9)) | C9: =IF($X9="","",INDEX('Per Line'!$C$2:$C$4001,$X9)) | D9: =IF($X9="","",INDEX('Per Line'!$A$2:$A$4001,$X9)) | E9: =IF($X9="","",INDEX('Per Line'!$F$2:$F$4001,$X9)) | F9: =IF($X9="","",INDEX('Per Line'!$G$2:$G$4001,$X9)) | G9: =IF($X9="","",INDEX('Per Line'!$I$2:$I$4001,$X9)) | H9: =IF($X9="","",INDEX('Per Line'!$J$2:$J$4001,$X9)) | I9: =IF($X9="","",INDEX('Per Line'!$K$2:$K$4001,$X9)) | J9: =IF($X9="","",INDEX('Per Line'!$L$2:$L$4001,$X9)) | K9: =IF($X9="","",INDEX('Per Line'!$M$2:$M$4001,$X9)) | L9: =IF($X9="","",K9*V9/100) | M9: =IF($X9="","",INDEX('Per Line'!$Z$2:$Z$4001,$X9)) | N9: =IF($X9="","",Settings!$C$7) | O9: =IF($X9="","",SUMIFS('Per Line'!$Y$2:$Y$4001,'Per Line'!$D$2:$D$4001,$B9,'Per Line'!$AJ$2:$AJ$4001,0)) | P9: =IF($X9="","",O9*N9) | Q9: =IF($X9="","",Settings!$C$6) | R9: =IF($X9="","",SUMIFS('Per Line'!$Y$2:$Y$4001,'Per Line'!$D$2:$D$4001,$B9,'Per Line'!$AJ$2:$AJ$4001,1)) | S9: =IF($X9="","",R9*Q9) | T9: =IF($X9="","",S9+P9) | U9: =IF($X9="","",V9-T9) | V9: =IF($X9="","",O9+R9) | W9: =IF($X9="","",U9-L9) | X9: =IF(ROWS($X$2:$X9)<=MAX('Per Line'!$AI$2:$AI$4001),MATCH(ROWS($X$2:$X9),'Per Line'!$AI$2:$AI$4001,0),"")
B10: =IF($X10="","",INDEX('Per Line'!$D$2:$D$4001,$X10)) | C10: =IF($X10="","",INDEX('Per Line'!$C$2:$C$4001,$X10)) | D10: =IF($X10="","",INDEX('Per Line'!$A$2:$A$4001,$X10)) | E10: =IF($X10="","",INDEX('Per Line'!$F$2:$F$4001,$X10)) | F10: =IF($X10="","",INDEX('Per Line'!$G$2:$G$4001,$X10)) | G10: =IF($X10="","",INDEX('Per Line'!$I$2:$I$4001,$X10)) | H10: =IF($X10="","",INDEX('Per Line'!$J$2:$J$4001,$X10)) | I10: =IF($X10="","",INDEX('Per Line'!$K$2:$K$4001,$X10)) | J10: =IF($X10="","",INDEX('Per Line'!$L$2:$L$4001,$X10)) | K10: =IF($X10="","",INDEX('Per Line'!$M$2:$M$4001,$X10)) | L10: =IF($X10="","",K10*V10/100) | M10: =IF($X10="","",INDEX('Per Line'!$Z$2:$Z$4001,$X10)) | N10: =IF($X10="","",Settings!$C$7) | O10: =IF($X10="","",SUMIFS('Per Line'!$Y$2:$Y$4001,'Per Line'!$D$2:$D$4001,$B10,'Per Line'!$AJ$2:$AJ$4001,0)) | P10: =IF($X10="","",O10*N10) | Q10: =IF($X10="","",Settings!$C$6) | R10: =IF($X10="","",SUMIFS('Per Line'!$Y$2:$Y$4001,'Per Line'!$D$2:$D$4001,$B10,'Per Line'!$AJ$2:$AJ$4001,1)) | S10: =IF($X10="","",R10*Q10) | T10: =IF($X10="","",S10+P10) | U10: =IF($X10="","",V10-T10) | V10: =IF($X10="","",O10+R10) | W10: =IF($X10="","",U10-L10) | X10: =IF(ROWS($X$2:$X10)<=MAX('Per Line'!$AI$2:$AI$4001),MATCH(ROWS($X$2:$X10),'Per Line'!$AI$2:$AI$4001,0),"")
B11: =IF($X11="","",INDEX('Per Line'!$D$2:$D$4001,$X11)) | C11: =IF($X11="","",INDEX('Per Line'!$C$2:$C$4001,$X11)) | D11: =IF($X11="","",INDEX('Per Line'!$A$2:$A$4001,$X11)) | E11: =IF($X11="","",INDEX('Per Line'!$F$2:$F$4001,$X11)) | F11: =IF($X11="","",INDEX('Per Line'!$G$2:$G$4001,$X11)) | G11: =IF($X11="","",INDEX('Per Line'!$I$2:$I$4001,$X11)) | H11: =IF($X11="","",INDEX('Per Line'!$J$2:$J$4001,$X11)) | I11: =IF($X11="","",INDEX('Per Line'!$K$2:$K$4001,$X11)) | J11: =IF($X11="","",INDEX('Per Line'!$L$2:$L$4001,$X11)) | K11: =IF($X11="","",INDEX('Per Line'!$M$2:$M$4001,$X11)) | L11: =IF($X11="","",K11*V11/100) | M11: =IF($X11="","",INDEX('Per Line'!$Z$2:$Z$4001,$X11)) | N11: =IF($X11="","",Settings!$C$7) | O11: =IF($X11="","",SUMIFS('Per Line'!$Y$2:$Y$4001,'Per Line'!$D$2:$D$4001,$B11,'Per Line'!$AJ$2:$AJ$4001,0)) | P11: =IF($X11="","",O11*N11) | Q11: =IF($X11="","",Settings!$C$6) | R11: =IF($X11="","",SUMIFS('Per Line'!$Y$2:$Y$4001,'Per Line'!$D$2:$D$4001,$B11,'Per Line'!$AJ$2:$AJ$4001,1)) | S11: =IF($X11="","",R11*Q11) | T11: =IF($X11="","",S11+P11) | U11: =IF($X11="","",V11-T11) | V11: =IF($X11="","",O11+R11) | W11: =IF($X11="","",U11-L11) | X11: =IF(ROWS($X$2:$X11)<=MAX('Per Line'!$AI$2:$AI$4001),MATCH(ROWS($X$2:$X11),'Per Line'!$AI$2:$AI$4001,0),"")
B12: =IF($X12="","",INDEX('Per Line'!$D$2:$D$4001,$X12)) | C12: =IF($X12="","",INDEX('Per Line'!$C$2:$C$4001,$X12)) | D12: =IF($X12="","",INDEX('Per Line'!$A$2:$A$4001,$X12)) | E12: =IF($X12="","",INDEX('Per Line'!$F$2:$F$4001,$X12)) | F12: =IF($X12="","",INDEX('Per Line'!$G$2:$G$4001,$X12)) | G12: =IF($X12="","",INDEX('Per Line'!$I$2:$I$4001,$X12)) | H12: =IF($X12="","",INDEX('Per Line'!$J$2:$J$4001,$X12)) | I12: =IF($X12="","",INDEX('Per Line'!$K$2:$K$4001,$X12)) | J12: =IF($X12="","",INDEX('Per Line'!$L$2:$L$4001,$X12)) | K12: =IF($X12="","",INDEX('Per Line'!$M$2:$M$4001,$X12)) | L12: =IF($X12="","",K12*V12/100) | M12: =IF($X12="","",INDEX('Per Line'!$Z$2:$Z$4001,$X12)) | N12: =IF($X12="","",Settings!$C$7) | O12: =IF($X12="","",SUMIFS('Per Line'!$Y$2:$Y$4001,'Per Line'!$D$2:$D$4001,$B12,'Per Line'!$AJ$2:$AJ$4001,0)) | P12: =IF($X12="","",O12*N12) | Q12: =IF($X12="","",Settings!$C$6) | R12: =IF($X12="","",SUMIFS('Per Line'!$Y$2:$Y$4001,'Per Line'!$D$2:$D$4001,$B12,'Per Line'!$AJ$2:$AJ$4001,1)) | S12: =IF($X12="","",R12*Q12) | T12: =IF($X12="","",S12+P12) | U12: =IF($X12="","",V12-T12) | V12: =IF($X12="","",O12+R12) | W12: =IF($X12="","",U12-L12) | X12: =IF(ROWS($X$2:$X12)<=MAX('Per Line'!$AI$2:$AI$4001),MATCH(ROWS($X$2:$X12),'Per Line'!$AI$2:$AI$4001,0),"")
B13: =IF($X13="","",INDEX('Per Line'!$D$2:$D$4001,$X13)) | C13: =IF($X13="","",INDEX('Per Line'!$C$2:$C$4001,$X13)) | D13: =IF($X13="","",INDEX('Per Line'!$A$2:$A$4001,$X13)) | E13: =IF($X13="","",INDEX('Per Line'!$F$2:$F$4001,$X13)) | F13: =IF($X13="","",INDEX('Per Line'!$G$2:$G$4001,$X13)) | G13: =IF($X13="","",INDEX('Per Line'!$I$2:$I$4001,$X13)) | H13: =IF($X13="","",INDEX('Per Line'!$J$2:$J$4001,$X13)) | I13: =IF($X13="","",INDEX('Per Line'!$K$2:$K$4001,$X13)) | J13: =IF($X13="","",INDEX('Per Line'!$L$2:$L$4001,$X13)) | K13: =IF($X13="","",INDEX('Per Line'!$M$2:$M$4001,$X13)) | L13: =IF($X13="","",K13*V13/100) | M13: =IF($X13="","",INDEX('Per Line'!$Z$2:$Z$4001,$X13)) | N13: =IF($X13="","",Settings!$C$7) | O13: =IF($X13="","",SUMIFS('Per Line'!$Y$2:$Y$4001,'Per Line'!$D$2:$D$4001,$B13,'Per Line'!$AJ$2:$AJ$4001,0)) | P13: =IF($X13="","",O13*N13) | Q13: =IF($X13="","",Settings!$C$6) | R13: =IF($X13="","",SUMIFS('Per Line'!$Y$2:$Y$4001,'Per Line'!$D$2:$D$4001,$B13,'Per Line'!$AJ$2:$AJ$4001,1)) | S13: =IF($X13="","",R13*Q13) | T13: =IF($X13="","",S13+P13) | U13: =IF($X13="","",V13-T13) | V13: =IF($X13="","",O13+R13) | W13: =IF($X13="","",U13-L13) | X13: =IF(ROWS($X$2:$X13)<=MAX('Per Line'!$AI$2:$AI$4001),MATCH(ROWS($X$2:$X13),'Per Line'!$AI$2:$AI$4001,0),"")
... B1501: =IF($X1501="","",INDEX('Per Line'!$D$2:$D$4001,$X1501)) | C1501: =IF($X1501="","",INDEX('Per Line'!$C$2:$C$4001,$X1501)) | D1501: =IF($X1501="","",INDEX('Per Line'!$A$2:$A$4001,$X1501)) | E1501: =IF($X1501="","",INDEX('Per Line'!$F$2:$F$4001,$X1501)) | F1501: =IF($X1501="","",INDEX('Per Line'!$G$2:$G$4001,$X1501)) | G1501: =IF($X1501="","",INDEX('Per Line'!$I$2:$I$4001,$X1501)) | H1501: =IF($X1501="","",INDEX('Per Line'!$J$2:$J$4001,$X1501)) | I1501: =IF($X1501="","",INDEX('Per Line'!$K$2:$K$4001,$X1501)) | J1501: =IF($X1501="","",INDEX('Per Line'!$L$2:$L$4001,$X1501)) | K1501: =IF($X1501="","",INDEX('Per Line'!$M$2:$M$4001,$X1501)) | L1501: =IF($X1501="","",K1501*V1501/100) | M1501: =IF($X1501="","",INDEX('Per Line'!$Z$2:$Z$4001,$X1501)) | N1501: =IF($X1501="","",Settings!$C$7) | O1501: =IF($X1501="","",SUMIFS('Per Line'!$Y$2:$Y$4001,'Per Line'!$D$2:$D$4001,$B1501,'Per Line'!$AJ$2:$AJ$4001,0)) | P1501: =IF($X1501="","",O1501*N1501) | Q1501: =IF($X1501="","",Settings!$C$6) | R1501: =IF($X1501="","",SUMIFS('Per Line'!$Y$2:$Y$4001,'Per Line'!$D$2:$D$4001,$B1501,'Per Line'!$AJ$2:$AJ$4001,1)) | S1501: =IF($X1501="","",R1501*Q1501) | T1501: =IF($X1501="","",S1501+P1501) | U1501: =IF($X1501="","",V1501-T1501) | V1501: =IF($X1501="","",O1501+R1501) | W1501: =IF($X1501="","",U1501-L1501) | X1501: =IF(ROWS($X$2:$X1501)<=MAX('Per Line'!$AI$2:$AI$4001),MATCH(ROWS($X$2:$X1501),'Per Line'!$AI$2:$AI$4001,0),"")
