Workbook

Sheet How To Use
A1: Claims Template - NILESAT (Chronic)
A3: Monthly steps
A4: 1. Open the 'Per Line' tab. Delete the old data in the BLUE columns only (row 2 down). Never delete the green or grey columns.
A5: 2. Paste the new month's data as VALUES starting at A2, into the blue columns: A-P, R-Y, AC, AE-AL (same order as the system export).
A6: 3. Green columns (Q, Z, AA, AB, AD) and the grey helper columns (AM-AQ) calculate automatically - do not paste over them.
A7: 4. 'Per Invoice' fills itself from 'Per Line' (one row per Order #, split into IMP / Local). No pivot table, no refresh.
A8: 5. The ONLY manual column in 'Per Invoice' is column A 'Invoice' (blue): type the invoice number yourself. Everything else is formula.
A9: 6. Open 'Settings' and check STATUS says OK (Per Line totals = Per Invoice totals).
A11: Colour legend
A12: Blue header = typed/pasted by you (raw data, and 'Invoice' in Per Invoice). Green header = formula (do not paste over). Grey header = helper formula (do not touch). Yellow cell (Settings) = editable rate.
A14: Calculation rules (taken from the October 2026 sheet)
A15: Co val = Order Co Payment x Total / 100. Discount = Total x Rebates / 100. Subtotal = Total - Discount. Net = Subtotal - Co val. (Total = 'Product Total')
... A20: Capacity: up to 1,000 lines and 300 invoices per month. A line with an empty Order # is ignored.

Sheet Settings
B1: Company settings & checks
B3: Insurance Company | C3: NILESAT | D3: Informational only
B4: Corporate | C4: NileSat individual | D4: Informational only
B5: Sheet type | C5: Chronic | D5: Informational only
B6: Local products rebate % | C6: 0.15 | D6: Source: Oct sheet (Rebates = 15 on Local lines).
B7: Imported (IMP) products rebate % | C7: 0.06 | D7: Source: Oct sheet (Rebates = 6 on non-local lines).
B9: Month totals / reconciliation
B10: Lines loaded | C10: =COUNTA('Per Line'!$D$2:$D$1001)
B11: Invoices (unique Order #) | C11: =MAX('Per Line'!$AN$2:$AN$1001)
B12: Invoices shown in Per Invoice | C12: =SUMPRODUCT(--('Per Invoice'!$B$2:$B$301<>""))
B13: Grand Total - Per Line (Product Total) | C13: =SUM('Per Line'!$Y$2:$Y$1001)
B14: Grand Total - Per Invoice | C14: =SUM('Per Invoice'!$X$2:$X$301)
B15: Discount - Per Line | C15: =SUM('Per Line'!$Z$2:$Z$1001)
B16: Discount - Per Invoice | C16: =SUM('Per Invoice'!$V$2:$V$301)
B17: Co val - Per Line | C17: =SUM('Per Line'!$Q$2:$Q$1001)
B18: Co val - Per Invoice | C18: =SUM('Per Invoice'!$N$2:$N$301)
B19: Net - Per Line | C19: =SUM('Per Line'!$AB$2:$AB$1001)
B20: Net - Per Invoice | C20: =SUM('Per Invoice'!$Y$2:$Y$301)
B21: Max Limit adjustment (Co val, Per Invoice only) | C21: 0 | D21: This company's Per Invoice has no Max Limit rule.
B23: STATUS | C23: =IF(C10=0,"No data loaded",IF(COUNTA('Per Line'!$D:$D)-1>1000,"TOO MANY LINES - extend template",IF(C11>300,"TOO MANY INVOICES - extend template",IF(AND(ROUND(C13-C14,2)=0,ROUND(C15-C16,2)=0,ROUND(C17+C21-C18,2)=0,ROUND(C19-C21-C20,2)=0,C11=C12),"OK","CHECK - Per Line and Per Invoice do not match")))) | D23: Must say OK after you paste the month data.

Sheet Per Line
A1: Ticket # | B1: Stage | C1: Approval Ref | D1: Order # | E1: Channel | F1: ERX ID | G1: Create At | H1: Insurance Company | I1: Country Portal ID | J1: Corporate | K1: Card | L1: Name | M1: Status | N1: Local Rebates | O1: Imported Rebates | P1: Order Co Payment | Q1: Co val | R1: By Patient | S1: heisenberg id | T1: Product Name | U1: Local | V1: Unit | W1: Quantity | X1: Unit Price | Y1: Product Total | Z1: Discount | AA1: Subtotal | AB1: Net | AC1: Special Rebates? | AD1: Rebates | AE1: Approval Type | AF1: Max Limit | AG1: Exceeding Limit | AH1: Amount collected from customer | AI1: By Patient (Delivered) | AJ1: Dispense Number | AK1: Dispense Date | AL1: Has OTP? | AM1: Order 1st Row (helper) | AN1: Invoice # (helper) | AO1: Is Local (helper) | AP1: Is Special (helper) | AQ1: Sort Key (helper)
Q2: =IF($D2="","",P2*Y2/100) | Z2: =IF($D2="","",Y2*AD2/100) | AA2: =IF($D2="","",Y2-Z2) | AB2: =IF($D2="","",AA2-Q2) | AD2: =IF($D2="","",IF($AP2=1,0,IF($AO2=1,Settings!$C$6,Settings!$C$7))*100) | AM2: =IF($D2="","",IF(COUNTIF($D$2:$D2,$D2)=1,1,0)) | AN2: =IF($AM2=1,SUMPRODUCT(--($AQ$2:$AQ$1001<$AQ2))+1,"") | AO2: =IF($D2="","",IF(OR($U2=TRUE(),$U2="TRUE"),1,0)) | AP2: =IF($D2="","",IF($AC2="Yes",1,0)) | AQ2: =IF($AM2=1,IFERROR(VALUE(MID($D2,2,20)),1000000000)+ROW()/100000,"")
Q3: =IF($D3="","",P3*Y3/100) | Z3: =IF($D3="","",Y3*AD3/100) | AA3: =IF($D3="","",Y3-Z3) | AB3: =IF($D3="","",AA3-Q3) | AD3: =IF($D3="","",IF($AP3=1,0,IF($AO3=1,Settings!$C$6,Settings!$C$7))*100) | AM3: =IF($D3="","",IF(COUNTIF($D$2:$D3,$D3)=1,1,0)) | AN3: =IF($AM3=1,SUMPRODUCT(--($AQ$2:$AQ$1001<$AQ3))+1,"") | AO3: =IF($D3="","",IF(OR($U3=TRUE(),$U3="TRUE"),1,0)) | AP3: =IF($D3="","",IF($AC3="Yes",1,0)) | AQ3: =IF($AM3=1,IFERROR(VALUE(MID($D3,2,20)),1000000000)+ROW()/100000,"")
Q4: =IF($D4="","",P4*Y4/100) | Z4: =IF($D4="","",Y4*AD4/100) | AA4: =IF($D4="","",Y4-Z4) | AB4: =IF($D4="","",AA4-Q4) | AD4: =IF($D4="","",IF($AP4=1,0,IF($AO4=1,Settings!$C$6,Settings!$C$7))*100) | AM4: =IF($D4="","",IF(COUNTIF($D$2:$D4,$D4)=1,1,0)) | AN4: =IF($AM4=1,SUMPRODUCT(--($AQ$2:$AQ$1001<$AQ4))+1,"") | AO4: =IF($D4="","",IF(OR($U4=TRUE(),$U4="TRUE"),1,0)) | AP4: =IF($D4="","",IF($AC4="Yes",1,0)) | AQ4: =IF($AM4=1,IFERROR(VALUE(MID($D4,2,20)),1000000000)+ROW()/100000,"")
Q5: =IF($D5="","",P5*Y5/100) | Z5: =IF($D5="","",Y5*AD5/100) | AA5: =IF($D5="","",Y5-Z5) | AB5: =IF($D5="","",AA5-Q5) | AD5: =IF($D5="","",IF($AP5=1,0,IF($AO5=1,Settings!$C$6,Settings!$C$7))*100) | AM5: =IF($D5="","",IF(COUNTIF($D$2:$D5,$D5)=1,1,0)) | AN5: =IF($AM5=1,SUMPRODUCT(--($AQ$2:$AQ$1001<$AQ5))+1,"") | AO5: =IF($D5="","",IF(OR($U5=TRUE(),$U5="TRUE"),1,0)) | AP5: =IF($D5="","",IF($AC5="Yes",1,0)) | AQ5: =IF($AM5=1,IFERROR(VALUE(MID($D5,2,20)),1000000000)+ROW()/100000,"")
Q6: =IF($D6="","",P6*Y6/100) | Z6: =IF($D6="","",Y6*AD6/100) | AA6: =IF($D6="","",Y6-Z6) | AB6: =IF($D6="","",AA6-Q6) | AD6: =IF($D6="","",IF($AP6=1,0,IF($AO6=1,Settings!$C$6,Settings!$C$7))*100) | AM6: =IF($D6="","",IF(COUNTIF($D$2:$D6,$D6)=1,1,0)) | AN6: =IF($AM6=1,SUMPRODUCT(--($AQ$2:$AQ$1001<$AQ6))+1,"") | AO6: =IF($D6="","",IF(OR($U6=TRUE(),$U6="TRUE"),1,0)) | AP6: =IF($D6="","",IF($AC6="Yes",1,0)) | AQ6: =IF($AM6=1,IFERROR(VALUE(MID($D6,2,20)),1000000000)+ROW()/100000,"")
Q7: =IF($D7="","",P7*Y7/100) | Z7: =IF($D7="","",Y7*AD7/100) | AA7: =IF($D7="","",Y7-Z7) | AB7: =IF($D7="","",AA7-Q7) | AD7: =IF($D7="","",IF($AP7=1,0,IF($AO7=1,Settings!$C$6,Settings!$C$7))*100) | AM7: =IF($D7="","",IF(COUNTIF($D$2:$D7,$D7)=1,1,0)) | AN7: =IF($AM7=1,SUMPRODUCT(--($AQ$2:$AQ$1001<$AQ7))+1,"") | AO7: =IF($D7="","",IF(OR($U7=TRUE(),$U7="TRUE"),1,0)) | AP7: =IF($D7="","",IF($AC7="Yes",1,0)) | AQ7: =IF($AM7=1,IFERROR(VALUE(MID($D7,2,20)),1000000000)+ROW()/100000,"")
Q8: =IF($D8="","",P8*Y8/100) | Z8: =IF($D8="","",Y8*AD8/100) | AA8: =IF($D8="","",Y8-Z8) | AB8: =IF($D8="","",AA8-Q8) | AD8: =IF($D8="","",IF($AP8=1,0,IF($AO8=1,Settings!$C$6,Settings!$C$7))*100) | AM8: =IF($D8="","",IF(COUNTIF($D$2:$D8,$D8)=1,1,0)) | AN8: =IF($AM8=1,SUMPRODUCT(--($AQ$2:$AQ$1001<$AQ8))+1,"") | AO8: =IF($D8="","",IF(OR($U8=TRUE(),$U8="TRUE"),1,0)) | AP8: =IF($D8="","",IF($AC8="Yes",1,0)) | AQ8: =IF($AM8=1,IFERROR(VALUE(MID($D8,2,20)),1000000000)+ROW()/100000,"")
Q9: =IF($D9="","",P9*Y9/100) | Z9: =IF($D9="","",Y9*AD9/100) | AA9: =IF($D9="","",Y9-Z9) | AB9: =IF($D9="","",AA9-Q9) | AD9: =IF($D9="","",IF($AP9=1,0,IF($AO9=1,Settings!$C$6,Settings!$C$7))*100) | AM9: =IF($D9="","",IF(COUNTIF($D$2:$D9,$D9)=1,1,0)) | AN9: =IF($AM9=1,SUMPRODUCT(--($AQ$2:$AQ$1001<$AQ9))+1,"") | AO9: =IF($D9="","",IF(OR($U9=TRUE(),$U9="TRUE"),1,0)) | AP9: =IF($D9="","",IF($AC9="Yes",1,0)) | AQ9: =IF($AM9=1,IFERROR(VALUE(MID($D9,2,20)),1000000000)+ROW()/100000,"")
Q10: =IF($D10="","",P10*Y10/100) | Z10: =IF($D10="","",Y10*AD10/100) | AA10: =IF($D10="","",Y10-Z10) | AB10: =IF($D10="","",AA10-Q10) | AD10: =IF($D10="","",IF($AP10=1,0,IF($AO10=1,Settings!$C$6,Settings!$C$7))*100) | AM10: =IF($D10="","",IF(COUNTIF($D$2:$D10,$D10)=1,1,0)) | AN10: =IF($AM10=1,SUMPRODUCT(--($AQ$2:$AQ$1001<$AQ10))+1,"") | AO10: =IF($D10="","",IF(OR($U10=TRUE(),$U10="TRUE"),1,0)) | AP10: =IF($D10="","",IF($AC10="Yes",1,0)) | AQ10: =IF($AM10=1,IFERROR(VALUE(MID($D10,2,20)),1000000000)+ROW()/100000,"")
Q11: =IF($D11="","",P11*Y11/100) | Z11: =IF($D11="","",Y11*AD11/100) | AA11: =IF($D11="","",Y11-Z11) | AB11: =IF($D11="","",AA11-Q11) | AD11: =IF($D11="","",IF($AP11=1,0,IF($AO11=1,Settings!$C$6,Settings!$C$7))*100) | AM11: =IF($D11="","",IF(COUNTIF($D$2:$D11,$D11)=1,1,0)) | AN11: =IF($AM11=1,SUMPRODUCT(--($AQ$2:$AQ$1001<$AQ11))+1,"") | AO11: =IF($D11="","",IF(OR($U11=TRUE(),$U11="TRUE"),1,0)) | AP11: =IF($D11="","",IF($AC11="Yes",1,0)) | AQ11: =IF($AM11=1,IFERROR(VALUE(MID($D11,2,20)),1000000000)+ROW()/100000,"")
Q12: =IF($D12="","",P12*Y12/100) | Z12: =IF($D12="","",Y12*AD12/100) | AA12: =IF($D12="","",Y12-Z12) | AB12: =IF($D12="","",AA12-Q12) | AD12: =IF($D12="","",IF($AP12=1,0,IF($AO12=1,Settings!$C$6,Settings!$C$7))*100) | AM12: =IF($D12="","",IF(COUNTIF($D$2:$D12,$D12)=1,1,0)) | AN12: =IF($AM12=1,SUMPRODUCT(--($AQ$2:$AQ$1001<$AQ12))+1,"") | AO12: =IF($D12="","",IF(OR($U12=TRUE(),$U12="TRUE"),1,0)) | AP12: =IF($D12="","",IF($AC12="Yes",1,0)) | AQ12: =IF($AM12=1,IFERROR(VALUE(MID($D12,2,20)),1000000000)+ROW()/100000,"")
Q13: =IF($D13="","",P13*Y13/100) | Z13: =IF($D13="","",Y13*AD13/100) | AA13: =IF($D13="","",Y13-Z13) | AB13: =IF($D13="","",AA13-Q13) | AD13: =IF($D13="","",IF($AP13=1,0,IF($AO13=1,Settings!$C$6,Settings!$C$7))*100) | AM13: =IF($D13="","",IF(COUNTIF($D$2:$D13,$D13)=1,1,0)) | AN13: =IF($AM13=1,SUMPRODUCT(--($AQ$2:$AQ$1001<$AQ13))+1,"") | AO13: =IF($D13="","",IF(OR($U13=TRUE(),$U13="TRUE"),1,0)) | AP13: =IF($D13="","",IF($AC13="Yes",1,0)) | AQ13: =IF($AM13=1,IFERROR(VALUE(MID($D13,2,20)),1000000000)+ROW()/100000,"")
... Q1001: =IF($D1001="","",P1001*Y1001/100) | Z1001: =IF($D1001="","",Y1001*AD1001/100) | AA1001: =IF($D1001="","",Y1001-Z1001) | AB1001: =IF($D1001="","",AA1001-Q1001) | AD1001: =IF($D1001="","",IF($AP1001=1,0,IF($AO1001=1,Settings!$C$6,Settings!$C$7))*100) | AM1001: =IF($D1001="","",IF(COUNTIF($D$2:$D1001,$D1001)=1,1,0)) | AN1001: =IF($AM1001=1,SUMPRODUCT(--($AQ$2:$AQ$1001<$AQ1001))+1,"") | AO1001: =IF($D1001="","",IF(OR($U1001=TRUE(),$U1001="TRUE"),1,0)) | AP1001: =IF($D1001="","",IF($AC1001="Yes",1,0)) | AQ1001: =IF($AM1001=1,IFERROR(VALUE(MID($D1001,2,20)),1000000000)+ROW()/100000,"")

Sheet Per Invoice
A1: Invoice | B1: Order # | C1: Stage | D1: Ticket # | E1: Channel | F1: ERX ID | G1: Create At | H1: Country Portal ID | I1: Corporate | J1: Card | K1: Name | L1: Status | M1: Order Co Payment | N1: Co val | O1: Special | P1: imp % | Q1: imp | R1: imp val | S1: local% | T1: local | U1: local val | V1: disc | W1: sub | X1: Grand Total | Y1: net | Z1: Src Row (helper)
B2: =IF($Z2="","",INDEX('Per Line'!$D$2:$D$1001,$Z2)&"") | C2: =IF($Z2="","",INDEX('Per Line'!$B$2:$B$1001,$Z2)&"") | D2: =IF($Z2="","",INDEX('Per Line'!$A$2:$A$1001,$Z2)) | E2: =IF($Z2="","",INDEX('Per Line'!$E$2:$E$1001,$Z2)&"") | F2: =IF($Z2="","",INDEX('Per Line'!$F$2:$F$1001,$Z2)&"") | G2: =IF($Z2="","",INDEX('Per Line'!$G$2:$G$1001,$Z2)) | H2: =IF($Z2="","",INDEX('Per Line'!$I$2:$I$1001,$Z2)&"") | I2: =IF($Z2="","",INDEX('Per Line'!$J$2:$J$1001,$Z2)&"") | J2: =IF($Z2="","",INDEX('Per Line'!$K$2:$K$1001,$Z2)&"") | K2: =IF($Z2="","",INDEX('Per Line'!$L$2:$L$1001,$Z2)&"") | L2: =IF($Z2="","",INDEX('Per Line'!$M$2:$M$1001,$Z2)&"") | M2: =IF($Z2="","",INDEX('Per Line'!$P$2:$P$1001,$Z2)) | N2: =IF($Z2="","",M2*X2/100) | O2: =IF($Z2="","",SUMIFS('Per Line'!$Y$2:$Y$1001,'Per Line'!$D$2:$D$1001,$B2,'Per Line'!$AP$2:$AP$1001,1)) | P2: =IF($Z2="","",Settings!$C$7) | Q2: =IF($Z2="","",SUMIFS('Per Line'!$Y$2:$Y$1001,'Per Line'!$D$2:$D$1001,$B2,'Per Line'!$AO$2:$AO$1001,0,'Per Line'!$AP$2:$AP$1001,0)) | R2: =IF($Z2="","",Q2*P2) | S2: =IF($Z2="","",Settings!$C$6) | T2: =IF($Z2="","",SUMIFS('Per Line'!$Y$2:$Y$1001,'Per Line'!$D$2:$D$1001,$B2,'Per Line'!$AO$2:$AO$1001,1,'Per Line'!$AP$2:$AP$1001,0)) | U2: =IF($Z2="","",T2*S2) | V2: =IF($Z2="","",U2+R2) | W2: =IF($Z2="","",X2-V2) | X2: =IF($Z2="","",Q2+T2+O2) | Y2: =IF($Z2="","",X2-V2-N2) | Z2: =IF(ROWS($Z$2:$Z2)<=MAX('Per Line'!$AN$2:$AN$1001),MATCH(ROWS($Z$2:$Z2),'Per Line'!$AN$2:$AN$1001,0),"")
B3: =IF($Z3="","",INDEX('Per Line'!$D$2:$D$1001,$Z3)&"") | C3: =IF($Z3="","",INDEX('Per Line'!$B$2:$B$1001,$Z3)&"") | D3: =IF($Z3="","",INDEX('Per Line'!$A$2:$A$1001,$Z3)) | E3: =IF($Z3="","",INDEX('Per Line'!$E$2:$E$1001,$Z3)&"") | F3: =IF($Z3="","",INDEX('Per Line'!$F$2:$F$1001,$Z3)&"") | G3: =IF($Z3="","",INDEX('Per Line'!$G$2:$G$1001,$Z3)) | H3: =IF($Z3="","",INDEX('Per Line'!$I$2:$I$1001,$Z3)&"") | I3: =IF($Z3="","",INDEX('Per Line'!$J$2:$J$1001,$Z3)&"") | J3: =IF($Z3="","",INDEX('Per Line'!$K$2:$K$1001,$Z3)&"") | K3: =IF($Z3="","",INDEX('Per Line'!$L$2:$L$1001,$Z3)&"") | L3: =IF($Z3="","",INDEX('Per Line'!$M$2:$M$1001,$Z3)&"") | M3: =IF($Z3="","",INDEX('Per Line'!$P$2:$P$1001,$Z3)) | N3: =IF($Z3="","",M3*X3/100) | O3: =IF($Z3="","",SUMIFS('Per Line'!$Y$2:$Y$1001,'Per Line'!$D$2:$D$1001,$B3,'Per Line'!$AP$2:$AP$1001,1)) | P3: =IF($Z3="","",Settings!$C$7) | Q3: =IF($Z3="","",SUMIFS('Per Line'!$Y$2:$Y$1001,'Per Line'!$D$2:$D$1001,$B3,'Per Line'!$AO$2:$AO$1001,0,'Per Line'!$AP$2:$AP$1001,0)) | R3: =IF($Z3="","",Q3*P3) | S3: =IF($Z3="","",Settings!$C$6) | T3: =IF($Z3="","",SUMIFS('Per Line'!$Y$2:$Y$1001,'Per Line'!$D$2:$D$1001,$B3,'Per Line'!$AO$2:$AO$1001,1,'Per Line'!$AP$2:$AP$1001,0)) | U3: =IF($Z3="","",T3*S3) | V3: =IF($Z3="","",U3+R3) | W3: =IF($Z3="","",X3-V3) | X3: =IF($Z3="","",Q3+T3+O3) | Y3: =IF($Z3="","",X3-V3-N3) | Z3: =IF(ROWS($Z$2:$Z3)<=MAX('Per Line'!$AN$2:$AN$1001),MATCH(ROWS($Z$2:$Z3),'Per Line'!$AN$2:$AN$1001,0),"")
B4: =IF($Z4="","",INDEX('Per Line'!$D$2:$D$1001,$Z4)&"") | C4: =IF($Z4="","",INDEX('Per Line'!$B$2:$B$1001,$Z4)&"") | D4: =IF($Z4="","",INDEX('Per Line'!$A$2:$A$1001,$Z4)) | E4: =IF($Z4="","",INDEX('Per Line'!$E$2:$E$1001,$Z4)&"") | F4: =IF($Z4="","",INDEX('Per Line'!$F$2:$F$1001,$Z4)&"") | G4: =IF($Z4="","",INDEX('Per Line'!$G$2:$G$1001,$Z4)) | H4: =IF($Z4="","",INDEX('Per Line'!$I$2:$I$1001,$Z4)&"") | I4: =IF($Z4="","",INDEX('Per Line'!$J$2:$J$1001,$Z4)&"") | J4: =IF($Z4="","",INDEX('Per Line'!$K$2:$K$1001,$Z4)&"") | K4: =IF($Z4="","",INDEX('Per Line'!$L$2:$L$1001,$Z4)&"") | L4: =IF($Z4="","",INDEX('Per Line'!$M$2:$M$1001,$Z4)&"") | M4: =IF($Z4="","",INDEX('Per Line'!$P$2:$P$1001,$Z4)) | N4: =IF($Z4="","",M4*X4/100) | O4: =IF($Z4="","",SUMIFS('Per Line'!$Y$2:$Y$1001,'Per Line'!$D$2:$D$1001,$B4,'Per Line'!$AP$2:$AP$1001,1)) | P4: =IF($Z4="","",Settings!$C$7) | Q4: =IF($Z4="","",SUMIFS('Per Line'!$Y$2:$Y$1001,'Per Line'!$D$2:$D$1001,$B4,'Per Line'!$AO$2:$AO$1001,0,'Per Line'!$AP$2:$AP$1001,0)) | R4: =IF($Z4="","",Q4*P4) | S4: =IF($Z4="","",Settings!$C$6) | T4: =IF($Z4="","",SUMIFS('Per Line'!$Y$2:$Y$1001,'Per Line'!$D$2:$D$1001,$B4,'Per Line'!$AO$2:$AO$1001,1,'Per Line'!$AP$2:$AP$1001,0)) | U4: =IF($Z4="","",T4*S4) | V4: =IF($Z4="","",U4+R4) | W4: =IF($Z4="","",X4-V4) | X4: =IF($Z4="","",Q4+T4+O4) | Y4: =IF($Z4="","",X4-V4-N4) | Z4: =IF(ROWS($Z$2:$Z4)<=MAX('Per Line'!$AN$2:$AN$1001),MATCH(ROWS($Z$2:$Z4),'Per Line'!$AN$2:$AN$1001,0),"")
B5: =IF($Z5="","",INDEX('Per Line'!$D$2:$D$1001,$Z5)&"") | C5: =IF($Z5="","",INDEX('Per Line'!$B$2:$B$1001,$Z5)&"") | D5: =IF($Z5="","",INDEX('Per Line'!$A$2:$A$1001,$Z5)) | E5: =IF($Z5="","",INDEX('Per Line'!$E$2:$E$1001,$Z5)&"") | F5: =IF($Z5="","",INDEX('Per Line'!$F$2:$F$1001,$Z5)&"") | G5: =IF($Z5="","",INDEX('Per Line'!$G$2:$G$1001,$Z5)) | H5: =IF($Z5="","",INDEX('Per Line'!$I$2:$I$1001,$Z5)&"") | I5: =IF($Z5="","",INDEX('Per Line'!$J$2:$J$1001,$Z5)&"") | J5: =IF($Z5="","",INDEX('Per Line'!$K$2:$K$1001,$Z5)&"") | K5: =IF($Z5="","",INDEX('Per Line'!$L$2:$L$1001,$Z5)&"") | L5: =IF($Z5="","",INDEX('Per Line'!$M$2:$M$1001,$Z5)&"") | M5: =IF($Z5="","",INDEX('Per Line'!$P$2:$P$1001,$Z5)) | N5: =IF($Z5="","",M5*X5/100) | O5: =IF($Z5="","",SUMIFS('Per Line'!$Y$2:$Y$1001,'Per Line'!$D$2:$D$1001,$B5,'Per Line'!$AP$2:$AP$1001,1)) | P5: =IF($Z5="","",Settings!$C$7) | Q5: =IF($Z5="","",SUMIFS('Per Line'!$Y$2:$Y$1001,'Per Line'!$D$2:$D$1001,$B5,'Per Line'!$AO$2:$AO$1001,0,'Per Line'!$AP$2:$AP$1001,0)) | R5: =IF($Z5="","",Q5*P5) | S5: =IF($Z5="","",Settings!$C$6) | T5: =IF($Z5="","",SUMIFS('Per Line'!$Y$2:$Y$1001,'Per Line'!$D$2:$D$1001,$B5,'Per Line'!$AO$2:$AO$1001,1,'Per Line'!$AP$2:$AP$1001,0)) | U5: =IF($Z5="","",T5*S5) | V5: =IF($Z5="","",U5+R5) | W5: =IF($Z5="","",X5-V5) | X5: =IF($Z5="","",Q5+T5+O5) | Y5: =IF($Z5="","",X5-V5-N5) | Z5: =IF(ROWS($Z$2:$Z5)<=MAX('Per Line'!$AN$2:$AN$1001),MATCH(ROWS($Z$2:$Z5),'Per Line'!$AN$2:$AN$1001,0),"")
B6: =IF($Z6="","",INDEX('Per Line'!$D$2:$D$1001,$Z6)&"") | C6: =IF($Z6="","",INDEX('Per Line'!$B$2:$B$1001,$Z6)&"") | D6: =IF($Z6="","",INDEX('Per Line'!$A$2:$A$1001,$Z6)) | E6: =IF($Z6="","",INDEX('Per Line'!$E$2:$E$1001,$Z6)&"") | F6: =IF($Z6="","",INDEX('Per Line'!$F$2:$F$1001,$Z6)&"") | G6: =IF($Z6="","",INDEX('Per Line'!$G$2:$G$1001,$Z6)) | H6: =IF($Z6="","",INDEX('Per Line'!$I$2:$I$1001,$Z6)&"") | I6: =IF($Z6="","",INDEX('Per Line'!$J$2:$J$1001,$Z6)&"") | J6: =IF($Z6="","",INDEX('Per Line'!$K$2:$K$1001,$Z6)&"") | K6: =IF($Z6="","",INDEX('Per Line'!$L$2:$L$1001,$Z6)&"") | L6: =IF($Z6="","",INDEX('Per Line'!$M$2:$M$1001,$Z6)&"") | M6: =IF($Z6="","",INDEX('Per Line'!$P$2:$P$1001,$Z6)) | N6: =IF($Z6="","",M6*X6/100) | O6: =IF($Z6="","",SUMIFS('Per Line'!$Y$2:$Y$1001,'Per Line'!$D$2:$D$1001,$B6,'Per Line'!$AP$2:$AP$1001,1)) | P6: =IF($Z6="","",Settings!$C$7) | Q6: =IF($Z6="","",SUMIFS('Per Line'!$Y$2:$Y$1001,'Per Line'!$D$2:$D$1001,$B6,'Per Line'!$AO$2:$AO$1001,0,'Per Line'!$AP$2:$AP$1001,0)) | R6: =IF($Z6="","",Q6*P6) | S6: =IF($Z6="","",Settings!$C$6) | T6: =IF($Z6="","",SUMIFS('Per Line'!$Y$2:$Y$1001,'Per Line'!$D$2:$D$1001,$B6,'Per Line'!$AO$2:$AO$1001,1,'Per Line'!$AP$2:$AP$1001,0)) | U6: =IF($Z6="","",T6*S6) | V6: =IF($Z6="","",U6+R6) | W6: =IF($Z6="","",X6-V6) | X6: =IF($Z6="","",Q6+T6+O6) | Y6: =IF($Z6="","",X6-V6-N6) | Z6: =IF(ROWS($Z$2:$Z6)<=MAX('Per Line'!$AN$2:$AN$1001),MATCH(ROWS($Z$2:$Z6),'Per Line'!$AN$2:$AN$1001,0),"")
B7: =IF($Z7="","",INDEX('Per Line'!$D$2:$D$1001,$Z7)&"") | C7: =IF($Z7="","",INDEX('Per Line'!$B$2:$B$1001,$Z7)&"") | D7: =IF($Z7="","",INDEX('Per Line'!$A$2:$A$1001,$Z7)) | E7: =IF($Z7="","",INDEX('Per Line'!$E$2:$E$1001,$Z7)&"") | F7: =IF($Z7="","",INDEX('Per Line'!$F$2:$F$1001,$Z7)&"") | G7: =IF($Z7="","",INDEX('Per Line'!$G$2:$G$1001,$Z7)) | H7: =IF($Z7="","",INDEX('Per Line'!$I$2:$I$1001,$Z7)&"") | I7: =IF($Z7="","",INDEX('Per Line'!$J$2:$J$1001,$Z7)&"") | J7: =IF($Z7="","",INDEX('Per Line'!$K$2:$K$1001,$Z7)&"") | K7: =IF($Z7="","",INDEX('Per Line'!$L$2:$L$1001,$Z7)&"") | L7: =IF($Z7="","",INDEX('Per Line'!$M$2:$M$1001,$Z7)&"") | M7: =IF($Z7="","",INDEX('Per Line'!$P$2:$P$1001,$Z7)) | N7: =IF($Z7="","",M7*X7/100) | O7: =IF($Z7="","",SUMIFS('Per Line'!$Y$2:$Y$1001,'Per Line'!$D$2:$D$1001,$B7,'Per Line'!$AP$2:$AP$1001,1)) | P7: =IF($Z7="","",Settings!$C$7) | Q7: =IF($Z7="","",SUMIFS('Per Line'!$Y$2:$Y$1001,'Per Line'!$D$2:$D$1001,$B7,'Per Line'!$AO$2:$AO$1001,0,'Per Line'!$AP$2:$AP$1001,0)) | R7: =IF($Z7="","",Q7*P7) | S7: =IF($Z7="","",Settings!$C$6) | T7: =IF($Z7="","",SUMIFS('Per Line'!$Y$2:$Y$1001,'Per Line'!$D$2:$D$1001,$B7,'Per Line'!$AO$2:$AO$1001,1,'Per Line'!$AP$2:$AP$1001,0)) | U7: =IF($Z7="","",T7*S7) | V7: =IF($Z7="","",U7+R7) | W7: =IF($Z7="","",X7-V7) | X7: =IF($Z7="","",Q7+T7+O7) | Y7: =IF($Z7="","",X7-V7-N7) | Z7: =IF(ROWS($Z$2:$Z7)<=MAX('Per Line'!$AN$2:$AN$1001),MATCH(ROWS($Z$2:$Z7),'Per Line'!$AN$2:$AN$1001,0),"")
B8: =IF($Z8="","",INDEX('Per Line'!$D$2:$D$1001,$Z8)&"") | C8: =IF($Z8="","",INDEX('Per Line'!$B$2:$B$1001,$Z8)&"") | D8: =IF($Z8="","",INDEX('Per Line'!$A$2:$A$1001,$Z8)) | E8: =IF($Z8="","",INDEX('Per Line'!$E$2:$E$1001,$Z8)&"") | F8: =IF($Z8="","",INDEX('Per Line'!$F$2:$F$1001,$Z8)&"") | G8: =IF($Z8="","",INDEX('Per Line'!$G$2:$G$1001,$Z8)) | H8: =IF($Z8="","",INDEX('Per Line'!$I$2:$I$1001,$Z8)&"") | I8: =IF($Z8="","",INDEX('Per Line'!$J$2:$J$1001,$Z8)&"") | J8: =IF($Z8="","",INDEX('Per Line'!$K$2:$K$1001,$Z8)&"") | K8: =IF($Z8="","",INDEX('Per Line'!$L$2:$L$1001,$Z8)&"") | L8: =IF($Z8="","",INDEX('Per Line'!$M$2:$M$1001,$Z8)&"") | M8: =IF($Z8="","",INDEX('Per Line'!$P$2:$P$1001,$Z8)) | N8: =IF($Z8="","",M8*X8/100) | O8: =IF($Z8="","",SUMIFS('Per Line'!$Y$2:$Y$1001,'Per Line'!$D$2:$D$1001,$B8,'Per Line'!$AP$2:$AP$1001,1)) | P8: =IF($Z8="","",Settings!$C$7) | Q8: =IF($Z8="","",SUMIFS('Per Line'!$Y$2:$Y$1001,'Per Line'!$D$2:$D$1001,$B8,'Per Line'!$AO$2:$AO$1001,0,'Per Line'!$AP$2:$AP$1001,0)) | R8: =IF($Z8="","",Q8*P8) | S8: =IF($Z8="","",Settings!$C$6) | T8: =IF($Z8="","",SUMIFS('Per Line'!$Y$2:$Y$1001,'Per Line'!$D$2:$D$1001,$B8,'Per Line'!$AO$2:$AO$1001,1,'Per Line'!$AP$2:$AP$1001,0)) | U8: =IF($Z8="","",T8*S8) | V8: =IF($Z8="","",U8+R8) | W8: =IF($Z8="","",X8-V8) | X8: =IF($Z8="","",Q8+T8+O8) | Y8: =IF($Z8="","",X8-V8-N8) | Z8: =IF(ROWS($Z$2:$Z8)<=MAX('Per Line'!$AN$2:$AN$1001),MATCH(ROWS($Z$2:$Z8),'Per Line'!$AN$2:$AN$1001,0),"")
B9: =IF($Z9="","",INDEX('Per Line'!$D$2:$D$1001,$Z9)&"") | C9: =IF($Z9="","",INDEX('Per Line'!$B$2:$B$1001,$Z9)&"") | D9: =IF($Z9="","",INDEX('Per Line'!$A$2:$A$1001,$Z9)) | E9: =IF($Z9="","",INDEX('Per Line'!$E$2:$E$1001,$Z9)&"") | F9: =IF($Z9="","",INDEX('Per Line'!$F$2:$F$1001,$Z9)&"") | G9: =IF($Z9="","",INDEX('Per Line'!$G$2:$G$1001,$Z9)) | H9: =IF($Z9="","",INDEX('Per Line'!$I$2:$I$1001,$Z9)&"") | I9: =IF($Z9="","",INDEX('Per Line'!$J$2:$J$1001,$Z9)&"") | J9: =IF($Z9="","",INDEX('Per Line'!$K$2:$K$1001,$Z9)&"") | K9: =IF($Z9="","",INDEX('Per Line'!$L$2:$L$1001,$Z9)&"") | L9: =IF($Z9="","",INDEX('Per Line'!$M$2:$M$1001,$Z9)&"") | M9: =IF($Z9="","",INDEX('Per Line'!$P$2:$P$1001,$Z9)) | N9: =IF($Z9="","",M9*X9/100) | O9: =IF($Z9="","",SUMIFS('Per Line'!$Y$2:$Y$1001,'Per Line'!$D$2:$D$1001,$B9,'Per Line'!$AP$2:$AP$1001,1)) | P9: =IF($Z9="","",Settings!$C$7) | Q9: =IF($Z9="","",SUMIFS('Per Line'!$Y$2:$Y$1001,'Per Line'!$D$2:$D$1001,$B9,'Per Line'!$AO$2:$AO$1001,0,'Per Line'!$AP$2:$AP$1001,0)) | R9: =IF($Z9="","",Q9*P9) | S9: =IF($Z9="","",Settings!$C$6) | T9: =IF($Z9="","",SUMIFS('Per Line'!$Y$2:$Y$1001,'Per Line'!$D$2:$D$1001,$B9,'Per Line'!$AO$2:$AO$1001,1,'Per Line'!$AP$2:$AP$1001,0)) | U9: =IF($Z9="","",T9*S9) | V9: =IF($Z9="","",U9+R9) | W9: =IF($Z9="","",X9-V9) | X9: =IF($Z9="","",Q9+T9+O9) | Y9: =IF($Z9="","",X9-V9-N9) | Z9: =IF(ROWS($Z$2:$Z9)<=MAX('Per Line'!$AN$2:$AN$1001),MATCH(ROWS($Z$2:$Z9),'Per Line'!$AN$2:$AN$1001,0),"")
B10: =IF($Z10="","",INDEX('Per Line'!$D$2:$D$1001,$Z10)&"") | C10: =IF($Z10="","",INDEX('Per Line'!$B$2:$B$1001,$Z10)&"") | D10: =IF($Z10="","",INDEX('Per Line'!$A$2:$A$1001,$Z10)) | E10: =IF($Z10="","",INDEX('Per Line'!$E$2:$E$1001,$Z10)&"") | F10: =IF($Z10="","",INDEX('Per Line'!$F$2:$F$1001,$Z10)&"") | G10: =IF($Z10="","",INDEX('Per Line'!$G$2:$G$1001,$Z10)) | H10: =IF($Z10="","",INDEX('Per Line'!$I$2:$I$1001,$Z10)&"") | I10: =IF($Z10="","",INDEX('Per Line'!$J$2:$J$1001,$Z10)&"") | J10: =IF($Z10="","",INDEX('Per Line'!$K$2:$K$1001,$Z10)&"") | K10: =IF($Z10="","",INDEX('Per Line'!$L$2:$L$1001,$Z10)&"") | L10: =IF($Z10="","",INDEX('Per Line'!$M$2:$M$1001,$Z10)&"") | M10: =IF($Z10="","",INDEX('Per Line'!$P$2:$P$1001,$Z10)) | N10: =IF($Z10="","",M10*X10/100) | O10: =IF($Z10="","",SUMIFS('Per Line'!$Y$2:$Y$1001,'Per Line'!$D$2:$D$1001,$B10,'Per Line'!$AP$2:$AP$1001,1)) | P10: =IF($Z10="","",Settings!$C$7) | Q10: =IF($Z10="","",SUMIFS('Per Line'!$Y$2:$Y$1001,'Per Line'!$D$2:$D$1001,$B10,'Per Line'!$AO$2:$AO$1001,0,'Per Line'!$AP$2:$AP$1001,0)) | R10: =IF($Z10="","",Q10*P10) | S10: =IF($Z10="","",Settings!$C$6) | T10: =IF($Z10="","",SUMIFS('Per Line'!$Y$2:$Y$1001,'Per Line'!$D$2:$D$1001,$B10,'Per Line'!$AO$2:$AO$1001,1,'Per Line'!$AP$2:$AP$1001,0)) | U10: =IF($Z10="","",T10*S10) | V10: =IF($Z10="","",U10+R10) | W10: =IF($Z10="","",X10-V10) | X10: =IF($Z10="","",Q10+T10+O10) | Y10: =IF($Z10="","",X10-V10-N10) | Z10: =IF(ROWS($Z$2:$Z10)<=MAX('Per Line'!$AN$2:$AN$1001),MATCH(ROWS($Z$2:$Z10),'Per Line'!$AN$2:$AN$1001,0),"")
B11: =IF($Z11="","",INDEX('Per Line'!$D$2:$D$1001,$Z11)&"") | C11: =IF($Z11="","",INDEX('Per Line'!$B$2:$B$1001,$Z11)&"") | D11: =IF($Z11="","",INDEX('Per Line'!$A$2:$A$1001,$Z11)) | E11: =IF($Z11="","",INDEX('Per Line'!$E$2:$E$1001,$Z11)&"") | F11: =IF($Z11="","",INDEX('Per Line'!$F$2:$F$1001,$Z11)&"") | G11: =IF($Z11="","",INDEX('Per Line'!$G$2:$G$1001,$Z11)) | H11: =IF($Z11="","",INDEX('Per Line'!$I$2:$I$1001,$Z11)&"") | I11: =IF($Z11="","",INDEX('Per Line'!$J$2:$J$1001,$Z11)&"") | J11: =IF($Z11="","",INDEX('Per Line'!$K$2:$K$1001,$Z11)&"") | K11: =IF($Z11="","",INDEX('Per Line'!$L$2:$L$1001,$Z11)&"") | L11: =IF($Z11="","",INDEX('Per Line'!$M$2:$M$1001,$Z11)&"") | M11: =IF($Z11="","",INDEX('Per Line'!$P$2:$P$1001,$Z11)) | N11: =IF($Z11="","",M11*X11/100) | O11: =IF($Z11="","",SUMIFS('Per Line'!$Y$2:$Y$1001,'Per Line'!$D$2:$D$1001,$B11,'Per Line'!$AP$2:$AP$1001,1)) | P11: =IF($Z11="","",Settings!$C$7) | Q11: =IF($Z11="","",SUMIFS('Per Line'!$Y$2:$Y$1001,'Per Line'!$D$2:$D$1001,$B11,'Per Line'!$AO$2:$AO$1001,0,'Per Line'!$AP$2:$AP$1001,0)) | R11: =IF($Z11="","",Q11*P11) | S11: =IF($Z11="","",Settings!$C$6) | T11: =IF($Z11="","",SUMIFS('Per Line'!$Y$2:$Y$1001,'Per Line'!$D$2:$D$1001,$B11,'Per Line'!$AO$2:$AO$1001,1,'Per Line'!$AP$2:$AP$1001,0)) | U11: =IF($Z11="","",T11*S11) | V11: =IF($Z11="","",U11+R11) | W11: =IF($Z11="","",X11-V11) | X11: =IF($Z11="","",Q11+T11+O11) | Y11: =IF($Z11="","",X11-V11-N11) | Z11: =IF(ROWS($Z$2:$Z11)<=MAX('Per Line'!$AN$2:$AN$1001),MATCH(ROWS($Z$2:$Z11),'Per Line'!$AN$2:$AN$1001,0),"")
B12: =IF($Z12="","",INDEX('Per Line'!$D$2:$D$1001,$Z12)&"") | C12: =IF($Z12="","",INDEX('Per Line'!$B$2:$B$1001,$Z12)&"") | D12: =IF($Z12="","",INDEX('Per Line'!$A$2:$A$1001,$Z12)) | E12: =IF($Z12="","",INDEX('Per Line'!$E$2:$E$1001,$Z12)&"") | F12: =IF($Z12="","",INDEX('Per Line'!$F$2:$F$1001,$Z12)&"") | G12: =IF($Z12="","",INDEX('Per Line'!$G$2:$G$1001,$Z12)) | H12: =IF($Z12="","",INDEX('Per Line'!$I$2:$I$1001,$Z12)&"") | I12: =IF($Z12="","",INDEX('Per Line'!$J$2:$J$1001,$Z12)&"") | J12: =IF($Z12="","",INDEX('Per Line'!$K$2:$K$1001,$Z12)&"") | K12: =IF($Z12="","",INDEX('Per Line'!$L$2:$L$1001,$Z12)&"") | L12: =IF($Z12="","",INDEX('Per Line'!$M$2:$M$1001,$Z12)&"") | M12: =IF($Z12="","",INDEX('Per Line'!$P$2:$P$1001,$Z12)) | N12: =IF($Z12="","",M12*X12/100) | O12: =IF($Z12="","",SUMIFS('Per Line'!$Y$2:$Y$1001,'Per Line'!$D$2:$D$1001,$B12,'Per Line'!$AP$2:$AP$1001,1)) | P12: =IF($Z12="","",Settings!$C$7) | Q12: =IF($Z12="","",SUMIFS('Per Line'!$Y$2:$Y$1001,'Per Line'!$D$2:$D$1001,$B12,'Per Line'!$AO$2:$AO$1001,0,'Per Line'!$AP$2:$AP$1001,0)) | R12: =IF($Z12="","",Q12*P12) | S12: =IF($Z12="","",Settings!$C$6) | T12: =IF($Z12="","",SUMIFS('Per Line'!$Y$2:$Y$1001,'Per Line'!$D$2:$D$1001,$B12,'Per Line'!$AO$2:$AO$1001,1,'Per Line'!$AP$2:$AP$1001,0)) | U12: =IF($Z12="","",T12*S12) | V12: =IF($Z12="","",U12+R12) | W12: =IF($Z12="","",X12-V12) | X12: =IF($Z12="","",Q12+T12+O12) | Y12: =IF($Z12="","",X12-V12-N12) | Z12: =IF(ROWS($Z$2:$Z12)<=MAX('Per Line'!$AN$2:$AN$1001),MATCH(ROWS($Z$2:$Z12),'Per Line'!$AN$2:$AN$1001,0),"")
B13: =IF($Z13="","",INDEX('Per Line'!$D$2:$D$1001,$Z13)&"") | C13: =IF($Z13="","",INDEX('Per Line'!$B$2:$B$1001,$Z13)&"") | D13: =IF($Z13="","",INDEX('Per Line'!$A$2:$A$1001,$Z13)) | E13: =IF($Z13="","",INDEX('Per Line'!$E$2:$E$1001,$Z13)&"") | F13: =IF($Z13="","",INDEX('Per Line'!$F$2:$F$1001,$Z13)&"") | G13: =IF($Z13="","",INDEX('Per Line'!$G$2:$G$1001,$Z13)) | H13: =IF($Z13="","",INDEX('Per Line'!$I$2:$I$1001,$Z13)&"") | I13: =IF($Z13="","",INDEX('Per Line'!$J$2:$J$1001,$Z13)&"") | J13: =IF($Z13="","",INDEX('Per Line'!$K$2:$K$1001,$Z13)&"") | K13: =IF($Z13="","",INDEX('Per Line'!$L$2:$L$1001,$Z13)&"") | L13: =IF($Z13="","",INDEX('Per Line'!$M$2:$M$1001,$Z13)&"") | M13: =IF($Z13="","",INDEX('Per Line'!$P$2:$P$1001,$Z13)) | N13: =IF($Z13="","",M13*X13/100) | O13: =IF($Z13="","",SUMIFS('Per Line'!$Y$2:$Y$1001,'Per Line'!$D$2:$D$1001,$B13,'Per Line'!$AP$2:$AP$1001,1)) | P13: =IF($Z13="","",Settings!$C$7) | Q13: =IF($Z13="","",SUMIFS('Per Line'!$Y$2:$Y$1001,'Per Line'!$D$2:$D$1001,$B13,'Per Line'!$AO$2:$AO$1001,0,'Per Line'!$AP$2:$AP$1001,0)) | R13: =IF($Z13="","",Q13*P13) | S13: =IF($Z13="","",Settings!$C$6) | T13: =IF($Z13="","",SUMIFS('Per Line'!$Y$2:$Y$1001,'Per Line'!$D$2:$D$1001,$B13,'Per Line'!$AO$2:$AO$1001,1,'Per Line'!$AP$2:$AP$1001,0)) | U13: =IF($Z13="","",T13*S13) | V13: =IF($Z13="","",U13+R13) | W13: =IF($Z13="","",X13-V13) | X13: =IF($Z13="","",Q13+T13+O13) | Y13: =IF($Z13="","",X13-V13-N13) | Z13: =IF(ROWS($Z$2:$Z13)<=MAX('Per Line'!$AN$2:$AN$1001),MATCH(ROWS($Z$2:$Z13),'Per Line'!$AN$2:$AN$1001,0),"")
... B301: =IF($Z301="","",INDEX('Per Line'!$D$2:$D$1001,$Z301)&"") | C301: =IF($Z301="","",INDEX('Per Line'!$B$2:$B$1001,$Z301)&"") | D301: =IF($Z301="","",INDEX('Per Line'!$A$2:$A$1001,$Z301)) | E301: =IF($Z301="","",INDEX('Per Line'!$E$2:$E$1001,$Z301)&"") | F301: =IF($Z301="","",INDEX('Per Line'!$F$2:$F$1001,$Z301)&"") | G301: =IF($Z301="","",INDEX('Per Line'!$G$2:$G$1001,$Z301)) | H301: =IF($Z301="","",INDEX('Per Line'!$I$2:$I$1001,$Z301)&"") | I301: =IF($Z301="","",INDEX('Per Line'!$J$2:$J$1001,$Z301)&"") | J301: =IF($Z301="","",INDEX('Per Line'!$K$2:$K$1001,$Z301)&"") | K301: =IF($Z301="","",INDEX('Per Line'!$L$2:$L$1001,$Z301)&"") | L301: =IF($Z301="","",INDEX('Per Line'!$M$2:$M$1001,$Z301)&"") | M301: =IF($Z301="","",INDEX('Per Line'!$P$2:$P$1001,$Z301)) | N301: =IF($Z301="","",M301*X301/100) | O301: =IF($Z301="","",SUMIFS('Per Line'!$Y$2:$Y$1001,'Per Line'!$D$2:$D$1001,$B301,'Per Line'!$AP$2:$AP$1001,1)) | P301: =IF($Z301="","",Settings!$C$7) | Q301: =IF($Z301="","",SUMIFS('Per Line'!$Y$2:$Y$1001,'Per Line'!$D$2:$D$1001,$B301,'Per Line'!$AO$2:$AO$1001,0,'Per Line'!$AP$2:$AP$1001,0)) | R301: =IF($Z301="","",Q301*P301) | S301: =IF($Z301="","",Settings!$C$6) | T301: =IF($Z301="","",SUMIFS('Per Line'!$Y$2:$Y$1001,'Per Line'!$D$2:$D$1001,$B301,'Per Line'!$AO$2:$AO$1001,1,'Per Line'!$AP$2:$AP$1001,0)) | U301: =IF($Z301="","",T301*S301) | V301: =IF($Z301="","",U301+R301) | W301: =IF($Z301="","",X301-V301) | X301: =IF($Z301="","",Q301+T301+O301) | Y301: =IF($Z301="","",X301-V301-N301) | Z301: =IF(ROWS($Z$2:$Z301)<=MAX('Per Line'!$AN$2:$AN$1001),MATCH(ROWS($Z$2:$Z301),'Per Line'!$AN$2:$AN$1001,0),"")
