Workbook

Sheet How To Use
A1: Claims Template - OMEGA CARE (Walk In)
A3: Monthly steps
A4: 1. Open the 'Per Line' tab. Delete the old data in the BLUE columns only (row 2 down). Never delete the green or grey columns.
A5: 2. Paste the new month's data as VALUES starting at A2, into the blue columns: A-E, G-O (same order as the system export).
A6: 3. Green columns (F, P, Q, R, S) and the grey helper columns (T-W) calculate automatically - do not paste over them.
A7: 4. 'Per Invoice' fills itself from 'Per Line' (one row per POS Reference, split into IMP / Local). No pivot table, no refresh.
A8: 5. The ONLY manual column in 'Per Invoice' is column A 'Invoice' (blue): type the invoice number yourself. Everything else is formula.
A9: 6. Open 'Settings' and check STATUS says OK (Per Line totals = Per Invoice totals).
A11: Colour legend
A12: Blue header = typed/pasted by you (raw data, and 'Invoice' in Per Invoice). Green header = formula (do not paste over). Grey header = helper formula (do not touch). Yellow cell (Settings) = editable rate.
A14: Calculation rules (taken from the July 2026 sheet)
A15: Co val = Co Payment % x Total / 100. Discount = Total x Rebates (Rebates is a fraction here, e.g. 0.14). Subtotal = Total - Discount. Net = Subtotal - Co val. (Total = 'Total Delivered')
... A20: Capacity: up to 500 lines and 200 invoices per month. A line with an empty POS Reference is ignored.

Sheet Settings
B1: Company settings & checks
B3: Insurance Company | C3: OMEGA CARE | D3: Informational only
B4: Corporate | C4: - | D4: Informational only
B5: Sheet type | C5: Walk In | D5: Informational only
B6: Local products rebate % | C6: 0.14 | D6: Source: July sheet (Rebates = 0.14 on every line).
B7: Imported (IMP) products rebate % | C7: 0.06 | D7: Source: July Per Inv used 6% for IMP (no imported lines that month; the export has no Is Local column, so all lines use the Local rate).
B9: Month totals / reconciliation
B10: Lines loaded | C10: =COUNTA('Per Line'!$A$2:$A$501)
B11: Invoices (unique Order #) | C11: =MAX('Per Line'!$U$2:$U$501)
B12: Invoices shown in Per Invoice | C12: =SUMPRODUCT(--('Per Invoice'!$B$2:$B$201<>""))
B13: Grand Total - Per Line (Product Total) | C13: =SUM('Per Line'!$K$2:$K$501)
B14: Grand Total - Per Invoice | C14: =SUM('Per Invoice'!$Q$2:$Q$201)
B15: Discount - Per Line | C15: =SUM('Per Line'!$Q$2:$Q$501)
B16: Discount - Per Invoice | C16: =SUM('Per Invoice'!$O$2:$O$201)
B17: Co val - Per Line | C17: =SUM('Per Line'!$F$2:$F$501)
B18: Co val - Per Invoice | C18: =SUM('Per Invoice'!$G$2:$G$201)
B19: Net - Per Line | C19: =SUM('Per Line'!$S$2:$S$501)
B20: Net - Per Invoice | C20: =SUM('Per Invoice'!$R$2:$R$201)
B21: Max Limit adjustment (Co val, Per Invoice only) | C21: 0 | D21: This company's Per Invoice has no Max Limit rule.
B23: STATUS | C23: =IF(C10=0,"No data loaded",IF(COUNTA('Per Line'!$A:$A)-1>500,"TOO MANY LINES - extend template",IF(C11>200,"TOO MANY INVOICES - extend template",IF(AND(ROUND(C13-C14,2)=0,ROUND(C15-C16,2)=0,ROUND(C17+C21-C18,2)=0,ROUND(C19-C21-C20,2)=0,C11=C12),"OK","CHECK - Per Line and Per Invoice do not match")))) | D23: Must say OK after you paste the month data.

Sheet Per Line
A1: Pos Reference | B1: Insurance Company | C1: Name | D1: Card Number | E1: Co Payment % | F1: Co val | G1: Heisenberg id | H1: Product | I1: Delivered Qty | J1: Delivered Price | K1: Total Delivered | L1: Payment Amount | M1: Payment Type | N1: Session | O1: Create Date | P1: Rebates | Q1: Discount | R1: Subtotal | S1: Net | T1: Order 1st Row (helper) | U1: Invoice # (helper) | V1: Is Local (helper) | W1: Sort Key (helper)
F2: =IF($A2="","",E2*K2/100) | P2: =IF($A2="","",IF($V2=1,Settings!$C$6,Settings!$C$7)*1) | Q2: =IF($A2="","",P2*K2) | R2: =IF($A2="","",K2-Q2) | S2: =IF($A2="","",R2-F2) | T2: =IF($A2="","",IF(COUNTIF($A$2:$A2,$A2)=1,1,0)) | U2: =IF($T2=1,SUMPRODUCT(--($W$2:$W$501<$W2))+1,"") | V2: =IF($A2="","",1) | W2: =IF($T2=1,IFERROR(VALUE(MID($A2,2,20)),1000000000)+ROW()/100000,"")
F3: =IF($A3="","",E3*K3/100) | P3: =IF($A3="","",IF($V3=1,Settings!$C$6,Settings!$C$7)*1) | Q3: =IF($A3="","",P3*K3) | R3: =IF($A3="","",K3-Q3) | S3: =IF($A3="","",R3-F3) | T3: =IF($A3="","",IF(COUNTIF($A$2:$A3,$A3)=1,1,0)) | U3: =IF($T3=1,SUMPRODUCT(--($W$2:$W$501<$W3))+1,"") | V3: =IF($A3="","",1) | W3: =IF($T3=1,IFERROR(VALUE(MID($A3,2,20)),1000000000)+ROW()/100000,"")
F4: =IF($A4="","",E4*K4/100) | P4: =IF($A4="","",IF($V4=1,Settings!$C$6,Settings!$C$7)*1) | Q4: =IF($A4="","",P4*K4) | R4: =IF($A4="","",K4-Q4) | S4: =IF($A4="","",R4-F4) | T4: =IF($A4="","",IF(COUNTIF($A$2:$A4,$A4)=1,1,0)) | U4: =IF($T4=1,SUMPRODUCT(--($W$2:$W$501<$W4))+1,"") | V4: =IF($A4="","",1) | W4: =IF($T4=1,IFERROR(VALUE(MID($A4,2,20)),1000000000)+ROW()/100000,"")
F5: =IF($A5="","",E5*K5/100) | P5: =IF($A5="","",IF($V5=1,Settings!$C$6,Settings!$C$7)*1) | Q5: =IF($A5="","",P5*K5) | R5: =IF($A5="","",K5-Q5) | S5: =IF($A5="","",R5-F5) | T5: =IF($A5="","",IF(COUNTIF($A$2:$A5,$A5)=1,1,0)) | U5: =IF($T5=1,SUMPRODUCT(--($W$2:$W$501<$W5))+1,"") | V5: =IF($A5="","",1) | W5: =IF($T5=1,IFERROR(VALUE(MID($A5,2,20)),1000000000)+ROW()/100000,"")
F6: =IF($A6="","",E6*K6/100) | P6: =IF($A6="","",IF($V6=1,Settings!$C$6,Settings!$C$7)*1) | Q6: =IF($A6="","",P6*K6) | R6: =IF($A6="","",K6-Q6) | S6: =IF($A6="","",R6-F6) | T6: =IF($A6="","",IF(COUNTIF($A$2:$A6,$A6)=1,1,0)) | U6: =IF($T6=1,SUMPRODUCT(--($W$2:$W$501<$W6))+1,"") | V6: =IF($A6="","",1) | W6: =IF($T6=1,IFERROR(VALUE(MID($A6,2,20)),1000000000)+ROW()/100000,"")
F7: =IF($A7="","",E7*K7/100) | P7: =IF($A7="","",IF($V7=1,Settings!$C$6,Settings!$C$7)*1) | Q7: =IF($A7="","",P7*K7) | R7: =IF($A7="","",K7-Q7) | S7: =IF($A7="","",R7-F7) | T7: =IF($A7="","",IF(COUNTIF($A$2:$A7,$A7)=1,1,0)) | U7: =IF($T7=1,SUMPRODUCT(--($W$2:$W$501<$W7))+1,"") | V7: =IF($A7="","",1) | W7: =IF($T7=1,IFERROR(VALUE(MID($A7,2,20)),1000000000)+ROW()/100000,"")
F8: =IF($A8="","",E8*K8/100) | P8: =IF($A8="","",IF($V8=1,Settings!$C$6,Settings!$C$7)*1) | Q8: =IF($A8="","",P8*K8) | R8: =IF($A8="","",K8-Q8) | S8: =IF($A8="","",R8-F8) | T8: =IF($A8="","",IF(COUNTIF($A$2:$A8,$A8)=1,1,0)) | U8: =IF($T8=1,SUMPRODUCT(--($W$2:$W$501<$W8))+1,"") | V8: =IF($A8="","",1) | W8: =IF($T8=1,IFERROR(VALUE(MID($A8,2,20)),1000000000)+ROW()/100000,"")
F9: =IF($A9="","",E9*K9/100) | P9: =IF($A9="","",IF($V9=1,Settings!$C$6,Settings!$C$7)*1) | Q9: =IF($A9="","",P9*K9) | R9: =IF($A9="","",K9-Q9) | S9: =IF($A9="","",R9-F9) | T9: =IF($A9="","",IF(COUNTIF($A$2:$A9,$A9)=1,1,0)) | U9: =IF($T9=1,SUMPRODUCT(--($W$2:$W$501<$W9))+1,"") | V9: =IF($A9="","",1) | W9: =IF($T9=1,IFERROR(VALUE(MID($A9,2,20)),1000000000)+ROW()/100000,"")
F10: =IF($A10="","",E10*K10/100) | P10: =IF($A10="","",IF($V10=1,Settings!$C$6,Settings!$C$7)*1) | Q10: =IF($A10="","",P10*K10) | R10: =IF($A10="","",K10-Q10) | S10: =IF($A10="","",R10-F10) | T10: =IF($A10="","",IF(COUNTIF($A$2:$A10,$A10)=1,1,0)) | U10: =IF($T10=1,SUMPRODUCT(--($W$2:$W$501<$W10))+1,"") | V10: =IF($A10="","",1) | W10: =IF($T10=1,IFERROR(VALUE(MID($A10,2,20)),1000000000)+ROW()/100000,"")
F11: =IF($A11="","",E11*K11/100) | P11: =IF($A11="","",IF($V11=1,Settings!$C$6,Settings!$C$7)*1) | Q11: =IF($A11="","",P11*K11) | R11: =IF($A11="","",K11-Q11) | S11: =IF($A11="","",R11-F11) | T11: =IF($A11="","",IF(COUNTIF($A$2:$A11,$A11)=1,1,0)) | U11: =IF($T11=1,SUMPRODUCT(--($W$2:$W$501<$W11))+1,"") | V11: =IF($A11="","",1) | W11: =IF($T11=1,IFERROR(VALUE(MID($A11,2,20)),1000000000)+ROW()/100000,"")
F12: =IF($A12="","",E12*K12/100) | P12: =IF($A12="","",IF($V12=1,Settings!$C$6,Settings!$C$7)*1) | Q12: =IF($A12="","",P12*K12) | R12: =IF($A12="","",K12-Q12) | S12: =IF($A12="","",R12-F12) | T12: =IF($A12="","",IF(COUNTIF($A$2:$A12,$A12)=1,1,0)) | U12: =IF($T12=1,SUMPRODUCT(--($W$2:$W$501<$W12))+1,"") | V12: =IF($A12="","",1) | W12: =IF($T12=1,IFERROR(VALUE(MID($A12,2,20)),1000000000)+ROW()/100000,"")
F13: =IF($A13="","",E13*K13/100) | P13: =IF($A13="","",IF($V13=1,Settings!$C$6,Settings!$C$7)*1) | Q13: =IF($A13="","",P13*K13) | R13: =IF($A13="","",K13-Q13) | S13: =IF($A13="","",R13-F13) | T13: =IF($A13="","",IF(COUNTIF($A$2:$A13,$A13)=1,1,0)) | U13: =IF($T13=1,SUMPRODUCT(--($W$2:$W$501<$W13))+1,"") | V13: =IF($A13="","",1) | W13: =IF($T13=1,IFERROR(VALUE(MID($A13,2,20)),1000000000)+ROW()/100000,"")
... F501: =IF($A501="","",E501*K501/100) | P501: =IF($A501="","",IF($V501=1,Settings!$C$6,Settings!$C$7)*1) | Q501: =IF($A501="","",P501*K501) | R501: =IF($A501="","",K501-Q501) | S501: =IF($A501="","",R501-F501) | T501: =IF($A501="","",IF(COUNTIF($A$2:$A501,$A501)=1,1,0)) | U501: =IF($T501=1,SUMPRODUCT(--($W$2:$W$501<$W501))+1,"") | V501: =IF($A501="","",1) | W501: =IF($T501=1,IFERROR(VALUE(MID($A501,2,20)),1000000000)+ROW()/100000,"")

Sheet Per Invoice
A1: Invoice | B1: Pos Reference | C1: Insurance Company | D1: Name | E1: Card Number | F1: Co Payment % | G1: Co val | H1: Create Date | I1: Imp % | J1: Imp | K1: Imp Val | L1: Local % | M1: Local | N1: Local val | O1: Total val | P1: Subtotal | Q1: Grand Total | R1: Net | S1: Src Row (helper)
B2: =IF($S2="","",INDEX('Per Line'!$A$2:$A$501,$S2)&"") | C2: =IF($S2="","",INDEX('Per Line'!$B$2:$B$501,$S2)&"") | D2: =IF($S2="","",INDEX('Per Line'!$C$2:$C$501,$S2)&"") | E2: =IF($S2="","",INDEX('Per Line'!$D$2:$D$501,$S2)&"") | F2: =IF($S2="","",INDEX('Per Line'!$E$2:$E$501,$S2)) | G2: =IF($S2="","",F2*Q2/100) | H2: =IF($S2="","",INDEX('Per Line'!$O$2:$O$501,$S2)) | I2: =IF($S2="","",Settings!$C$7) | J2: =IF($S2="","",SUMIFS('Per Line'!$K$2:$K$501,'Per Line'!$A$2:$A$501,$B2,'Per Line'!$V$2:$V$501,0)) | K2: =IF($S2="","",J2*I2) | L2: =IF($S2="","",Settings!$C$6) | M2: =IF($S2="","",SUMIFS('Per Line'!$K$2:$K$501,'Per Line'!$A$2:$A$501,$B2,'Per Line'!$V$2:$V$501,1)) | N2: =IF($S2="","",M2*L2) | O2: =IF($S2="","",N2+K2) | P2: =IF($S2="","",Q2-O2) | Q2: =IF($S2="","",J2+M2) | R2: =IF($S2="","",Q2-O2-G2) | S2: =IF(ROWS($S$2:$S2)<=MAX('Per Line'!$U$2:$U$501),MATCH(ROWS($S$2:$S2),'Per Line'!$U$2:$U$501,0),"")
B3: =IF($S3="","",INDEX('Per Line'!$A$2:$A$501,$S3)&"") | C3: =IF($S3="","",INDEX('Per Line'!$B$2:$B$501,$S3)&"") | D3: =IF($S3="","",INDEX('Per Line'!$C$2:$C$501,$S3)&"") | E3: =IF($S3="","",INDEX('Per Line'!$D$2:$D$501,$S3)&"") | F3: =IF($S3="","",INDEX('Per Line'!$E$2:$E$501,$S3)) | G3: =IF($S3="","",F3*Q3/100) | H3: =IF($S3="","",INDEX('Per Line'!$O$2:$O$501,$S3)) | I3: =IF($S3="","",Settings!$C$7) | J3: =IF($S3="","",SUMIFS('Per Line'!$K$2:$K$501,'Per Line'!$A$2:$A$501,$B3,'Per Line'!$V$2:$V$501,0)) | K3: =IF($S3="","",J3*I3) | L3: =IF($S3="","",Settings!$C$6) | M3: =IF($S3="","",SUMIFS('Per Line'!$K$2:$K$501,'Per Line'!$A$2:$A$501,$B3,'Per Line'!$V$2:$V$501,1)) | N3: =IF($S3="","",M3*L3) | O3: =IF($S3="","",N3+K3) | P3: =IF($S3="","",Q3-O3) | Q3: =IF($S3="","",J3+M3) | R3: =IF($S3="","",Q3-O3-G3) | S3: =IF(ROWS($S$2:$S3)<=MAX('Per Line'!$U$2:$U$501),MATCH(ROWS($S$2:$S3),'Per Line'!$U$2:$U$501,0),"")
B4: =IF($S4="","",INDEX('Per Line'!$A$2:$A$501,$S4)&"") | C4: =IF($S4="","",INDEX('Per Line'!$B$2:$B$501,$S4)&"") | D4: =IF($S4="","",INDEX('Per Line'!$C$2:$C$501,$S4)&"") | E4: =IF($S4="","",INDEX('Per Line'!$D$2:$D$501,$S4)&"") | F4: =IF($S4="","",INDEX('Per Line'!$E$2:$E$501,$S4)) | G4: =IF($S4="","",F4*Q4/100) | H4: =IF($S4="","",INDEX('Per Line'!$O$2:$O$501,$S4)) | I4: =IF($S4="","",Settings!$C$7) | J4: =IF($S4="","",SUMIFS('Per Line'!$K$2:$K$501,'Per Line'!$A$2:$A$501,$B4,'Per Line'!$V$2:$V$501,0)) | K4: =IF($S4="","",J4*I4) | L4: =IF($S4="","",Settings!$C$6) | M4: =IF($S4="","",SUMIFS('Per Line'!$K$2:$K$501,'Per Line'!$A$2:$A$501,$B4,'Per Line'!$V$2:$V$501,1)) | N4: =IF($S4="","",M4*L4) | O4: =IF($S4="","",N4+K4) | P4: =IF($S4="","",Q4-O4) | Q4: =IF($S4="","",J4+M4) | R4: =IF($S4="","",Q4-O4-G4) | S4: =IF(ROWS($S$2:$S4)<=MAX('Per Line'!$U$2:$U$501),MATCH(ROWS($S$2:$S4),'Per Line'!$U$2:$U$501,0),"")
B5: =IF($S5="","",INDEX('Per Line'!$A$2:$A$501,$S5)&"") | C5: =IF($S5="","",INDEX('Per Line'!$B$2:$B$501,$S5)&"") | D5: =IF($S5="","",INDEX('Per Line'!$C$2:$C$501,$S5)&"") | E5: =IF($S5="","",INDEX('Per Line'!$D$2:$D$501,$S5)&"") | F5: =IF($S5="","",INDEX('Per Line'!$E$2:$E$501,$S5)) | G5: =IF($S5="","",F5*Q5/100) | H5: =IF($S5="","",INDEX('Per Line'!$O$2:$O$501,$S5)) | I5: =IF($S5="","",Settings!$C$7) | J5: =IF($S5="","",SUMIFS('Per Line'!$K$2:$K$501,'Per Line'!$A$2:$A$501,$B5,'Per Line'!$V$2:$V$501,0)) | K5: =IF($S5="","",J5*I5) | L5: =IF($S5="","",Settings!$C$6) | M5: =IF($S5="","",SUMIFS('Per Line'!$K$2:$K$501,'Per Line'!$A$2:$A$501,$B5,'Per Line'!$V$2:$V$501,1)) | N5: =IF($S5="","",M5*L5) | O5: =IF($S5="","",N5+K5) | P5: =IF($S5="","",Q5-O5) | Q5: =IF($S5="","",J5+M5) | R5: =IF($S5="","",Q5-O5-G5) | S5: =IF(ROWS($S$2:$S5)<=MAX('Per Line'!$U$2:$U$501),MATCH(ROWS($S$2:$S5),'Per Line'!$U$2:$U$501,0),"")
B6: =IF($S6="","",INDEX('Per Line'!$A$2:$A$501,$S6)&"") | C6: =IF($S6="","",INDEX('Per Line'!$B$2:$B$501,$S6)&"") | D6: =IF($S6="","",INDEX('Per Line'!$C$2:$C$501,$S6)&"") | E6: =IF($S6="","",INDEX('Per Line'!$D$2:$D$501,$S6)&"") | F6: =IF($S6="","",INDEX('Per Line'!$E$2:$E$501,$S6)) | G6: =IF($S6="","",F6*Q6/100) | H6: =IF($S6="","",INDEX('Per Line'!$O$2:$O$501,$S6)) | I6: =IF($S6="","",Settings!$C$7) | J6: =IF($S6="","",SUMIFS('Per Line'!$K$2:$K$501,'Per Line'!$A$2:$A$501,$B6,'Per Line'!$V$2:$V$501,0)) | K6: =IF($S6="","",J6*I6) | L6: =IF($S6="","",Settings!$C$6) | M6: =IF($S6="","",SUMIFS('Per Line'!$K$2:$K$501,'Per Line'!$A$2:$A$501,$B6,'Per Line'!$V$2:$V$501,1)) | N6: =IF($S6="","",M6*L6) | O6: =IF($S6="","",N6+K6) | P6: =IF($S6="","",Q6-O6) | Q6: =IF($S6="","",J6+M6) | R6: =IF($S6="","",Q6-O6-G6) | S6: =IF(ROWS($S$2:$S6)<=MAX('Per Line'!$U$2:$U$501),MATCH(ROWS($S$2:$S6),'Per Line'!$U$2:$U$501,0),"")
B7: =IF($S7="","",INDEX('Per Line'!$A$2:$A$501,$S7)&"") | C7: =IF($S7="","",INDEX('Per Line'!$B$2:$B$501,$S7)&"") | D7: =IF($S7="","",INDEX('Per Line'!$C$2:$C$501,$S7)&"") | E7: =IF($S7="","",INDEX('Per Line'!$D$2:$D$501,$S7)&"") | F7: =IF($S7="","",INDEX('Per Line'!$E$2:$E$501,$S7)) | G7: =IF($S7="","",F7*Q7/100) | H7: =IF($S7="","",INDEX('Per Line'!$O$2:$O$501,$S7)) | I7: =IF($S7="","",Settings!$C$7) | J7: =IF($S7="","",SUMIFS('Per Line'!$K$2:$K$501,'Per Line'!$A$2:$A$501,$B7,'Per Line'!$V$2:$V$501,0)) | K7: =IF($S7="","",J7*I7) | L7: =IF($S7="","",Settings!$C$6) | M7: =IF($S7="","",SUMIFS('Per Line'!$K$2:$K$501,'Per Line'!$A$2:$A$501,$B7,'Per Line'!$V$2:$V$501,1)) | N7: =IF($S7="","",M7*L7) | O7: =IF($S7="","",N7+K7) | P7: =IF($S7="","",Q7-O7) | Q7: =IF($S7="","",J7+M7) | R7: =IF($S7="","",Q7-O7-G7) | S7: =IF(ROWS($S$2:$S7)<=MAX('Per Line'!$U$2:$U$501),MATCH(ROWS($S$2:$S7),'Per Line'!$U$2:$U$501,0),"")
B8: =IF($S8="","",INDEX('Per Line'!$A$2:$A$501,$S8)&"") | C8: =IF($S8="","",INDEX('Per Line'!$B$2:$B$501,$S8)&"") | D8: =IF($S8="","",INDEX('Per Line'!$C$2:$C$501,$S8)&"") | E8: =IF($S8="","",INDEX('Per Line'!$D$2:$D$501,$S8)&"") | F8: =IF($S8="","",INDEX('Per Line'!$E$2:$E$501,$S8)) | G8: =IF($S8="","",F8*Q8/100) | H8: =IF($S8="","",INDEX('Per Line'!$O$2:$O$501,$S8)) | I8: =IF($S8="","",Settings!$C$7) | J8: =IF($S8="","",SUMIFS('Per Line'!$K$2:$K$501,'Per Line'!$A$2:$A$501,$B8,'Per Line'!$V$2:$V$501,0)) | K8: =IF($S8="","",J8*I8) | L8: =IF($S8="","",Settings!$C$6) | M8: =IF($S8="","",SUMIFS('Per Line'!$K$2:$K$501,'Per Line'!$A$2:$A$501,$B8,'Per Line'!$V$2:$V$501,1)) | N8: =IF($S8="","",M8*L8) | O8: =IF($S8="","",N8+K8) | P8: =IF($S8="","",Q8-O8) | Q8: =IF($S8="","",J8+M8) | R8: =IF($S8="","",Q8-O8-G8) | S8: =IF(ROWS($S$2:$S8)<=MAX('Per Line'!$U$2:$U$501),MATCH(ROWS($S$2:$S8),'Per Line'!$U$2:$U$501,0),"")
B9: =IF($S9="","",INDEX('Per Line'!$A$2:$A$501,$S9)&"") | C9: =IF($S9="","",INDEX('Per Line'!$B$2:$B$501,$S9)&"") | D9: =IF($S9="","",INDEX('Per Line'!$C$2:$C$501,$S9)&"") | E9: =IF($S9="","",INDEX('Per Line'!$D$2:$D$501,$S9)&"") | F9: =IF($S9="","",INDEX('Per Line'!$E$2:$E$501,$S9)) | G9: =IF($S9="","",F9*Q9/100) | H9: =IF($S9="","",INDEX('Per Line'!$O$2:$O$501,$S9)) | I9: =IF($S9="","",Settings!$C$7) | J9: =IF($S9="","",SUMIFS('Per Line'!$K$2:$K$501,'Per Line'!$A$2:$A$501,$B9,'Per Line'!$V$2:$V$501,0)) | K9: =IF($S9="","",J9*I9) | L9: =IF($S9="","",Settings!$C$6) | M9: =IF($S9="","",SUMIFS('Per Line'!$K$2:$K$501,'Per Line'!$A$2:$A$501,$B9,'Per Line'!$V$2:$V$501,1)) | N9: =IF($S9="","",M9*L9) | O9: =IF($S9="","",N9+K9) | P9: =IF($S9="","",Q9-O9) | Q9: =IF($S9="","",J9+M9) | R9: =IF($S9="","",Q9-O9-G9) | S9: =IF(ROWS($S$2:$S9)<=MAX('Per Line'!$U$2:$U$501),MATCH(ROWS($S$2:$S9),'Per Line'!$U$2:$U$501,0),"")
B10: =IF($S10="","",INDEX('Per Line'!$A$2:$A$501,$S10)&"") | C10: =IF($S10="","",INDEX('Per Line'!$B$2:$B$501,$S10)&"") | D10: =IF($S10="","",INDEX('Per Line'!$C$2:$C$501,$S10)&"") | E10: =IF($S10="","",INDEX('Per Line'!$D$2:$D$501,$S10)&"") | F10: =IF($S10="","",INDEX('Per Line'!$E$2:$E$501,$S10)) | G10: =IF($S10="","",F10*Q10/100) | H10: =IF($S10="","",INDEX('Per Line'!$O$2:$O$501,$S10)) | I10: =IF($S10="","",Settings!$C$7) | J10: =IF($S10="","",SUMIFS('Per Line'!$K$2:$K$501,'Per Line'!$A$2:$A$501,$B10,'Per Line'!$V$2:$V$501,0)) | K10: =IF($S10="","",J10*I10) | L10: =IF($S10="","",Settings!$C$6) | M10: =IF($S10="","",SUMIFS('Per Line'!$K$2:$K$501,'Per Line'!$A$2:$A$501,$B10,'Per Line'!$V$2:$V$501,1)) | N10: =IF($S10="","",M10*L10) | O10: =IF($S10="","",N10+K10) | P10: =IF($S10="","",Q10-O10) | Q10: =IF($S10="","",J10+M10) | R10: =IF($S10="","",Q10-O10-G10) | S10: =IF(ROWS($S$2:$S10)<=MAX('Per Line'!$U$2:$U$501),MATCH(ROWS($S$2:$S10),'Per Line'!$U$2:$U$501,0),"")
B11: =IF($S11="","",INDEX('Per Line'!$A$2:$A$501,$S11)&"") | C11: =IF($S11="","",INDEX('Per Line'!$B$2:$B$501,$S11)&"") | D11: =IF($S11="","",INDEX('Per Line'!$C$2:$C$501,$S11)&"") | E11: =IF($S11="","",INDEX('Per Line'!$D$2:$D$501,$S11)&"") | F11: =IF($S11="","",INDEX('Per Line'!$E$2:$E$501,$S11)) | G11: =IF($S11="","",F11*Q11/100) | H11: =IF($S11="","",INDEX('Per Line'!$O$2:$O$501,$S11)) | I11: =IF($S11="","",Settings!$C$7) | J11: =IF($S11="","",SUMIFS('Per Line'!$K$2:$K$501,'Per Line'!$A$2:$A$501,$B11,'Per Line'!$V$2:$V$501,0)) | K11: =IF($S11="","",J11*I11) | L11: =IF($S11="","",Settings!$C$6) | M11: =IF($S11="","",SUMIFS('Per Line'!$K$2:$K$501,'Per Line'!$A$2:$A$501,$B11,'Per Line'!$V$2:$V$501,1)) | N11: =IF($S11="","",M11*L11) | O11: =IF($S11="","",N11+K11) | P11: =IF($S11="","",Q11-O11) | Q11: =IF($S11="","",J11+M11) | R11: =IF($S11="","",Q11-O11-G11) | S11: =IF(ROWS($S$2:$S11)<=MAX('Per Line'!$U$2:$U$501),MATCH(ROWS($S$2:$S11),'Per Line'!$U$2:$U$501,0),"")
B12: =IF($S12="","",INDEX('Per Line'!$A$2:$A$501,$S12)&"") | C12: =IF($S12="","",INDEX('Per Line'!$B$2:$B$501,$S12)&"") | D12: =IF($S12="","",INDEX('Per Line'!$C$2:$C$501,$S12)&"") | E12: =IF($S12="","",INDEX('Per Line'!$D$2:$D$501,$S12)&"") | F12: =IF($S12="","",INDEX('Per Line'!$E$2:$E$501,$S12)) | G12: =IF($S12="","",F12*Q12/100) | H12: =IF($S12="","",INDEX('Per Line'!$O$2:$O$501,$S12)) | I12: =IF($S12="","",Settings!$C$7) | J12: =IF($S12="","",SUMIFS('Per Line'!$K$2:$K$501,'Per Line'!$A$2:$A$501,$B12,'Per Line'!$V$2:$V$501,0)) | K12: =IF($S12="","",J12*I12) | L12: =IF($S12="","",Settings!$C$6) | M12: =IF($S12="","",SUMIFS('Per Line'!$K$2:$K$501,'Per Line'!$A$2:$A$501,$B12,'Per Line'!$V$2:$V$501,1)) | N12: =IF($S12="","",M12*L12) | O12: =IF($S12="","",N12+K12) | P12: =IF($S12="","",Q12-O12) | Q12: =IF($S12="","",J12+M12) | R12: =IF($S12="","",Q12-O12-G12) | S12: =IF(ROWS($S$2:$S12)<=MAX('Per Line'!$U$2:$U$501),MATCH(ROWS($S$2:$S12),'Per Line'!$U$2:$U$501,0),"")
B13: =IF($S13="","",INDEX('Per Line'!$A$2:$A$501,$S13)&"") | C13: =IF($S13="","",INDEX('Per Line'!$B$2:$B$501,$S13)&"") | D13: =IF($S13="","",INDEX('Per Line'!$C$2:$C$501,$S13)&"") | E13: =IF($S13="","",INDEX('Per Line'!$D$2:$D$501,$S13)&"") | F13: =IF($S13="","",INDEX('Per Line'!$E$2:$E$501,$S13)) | G13: =IF($S13="","",F13*Q13/100) | H13: =IF($S13="","",INDEX('Per Line'!$O$2:$O$501,$S13)) | I13: =IF($S13="","",Settings!$C$7) | J13: =IF($S13="","",SUMIFS('Per Line'!$K$2:$K$501,'Per Line'!$A$2:$A$501,$B13,'Per Line'!$V$2:$V$501,0)) | K13: =IF($S13="","",J13*I13) | L13: =IF($S13="","",Settings!$C$6) | M13: =IF($S13="","",SUMIFS('Per Line'!$K$2:$K$501,'Per Line'!$A$2:$A$501,$B13,'Per Line'!$V$2:$V$501,1)) | N13: =IF($S13="","",M13*L13) | O13: =IF($S13="","",N13+K13) | P13: =IF($S13="","",Q13-O13) | Q13: =IF($S13="","",J13+M13) | R13: =IF($S13="","",Q13-O13-G13) | S13: =IF(ROWS($S$2:$S13)<=MAX('Per Line'!$U$2:$U$501),MATCH(ROWS($S$2:$S13),'Per Line'!$U$2:$U$501,0),"")
... B201: =IF($S201="","",INDEX('Per Line'!$A$2:$A$501,$S201)&"") | C201: =IF($S201="","",INDEX('Per Line'!$B$2:$B$501,$S201)&"") | D201: =IF($S201="","",INDEX('Per Line'!$C$2:$C$501,$S201)&"") | E201: =IF($S201="","",INDEX('Per Line'!$D$2:$D$501,$S201)&"") | F201: =IF($S201="","",INDEX('Per Line'!$E$2:$E$501,$S201)) | G201: =IF($S201="","",F201*Q201/100) | H201: =IF($S201="","",INDEX('Per Line'!$O$2:$O$501,$S201)) | I201: =IF($S201="","",Settings!$C$7) | J201: =IF($S201="","",SUMIFS('Per Line'!$K$2:$K$501,'Per Line'!$A$2:$A$501,$B201,'Per Line'!$V$2:$V$501,0)) | K201: =IF($S201="","",J201*I201) | L201: =IF($S201="","",Settings!$C$6) | M201: =IF($S201="","",SUMIFS('Per Line'!$K$2:$K$501,'Per Line'!$A$2:$A$501,$B201,'Per Line'!$V$2:$V$501,1)) | N201: =IF($S201="","",M201*L201) | O201: =IF($S201="","",N201+K201) | P201: =IF($S201="","",Q201-O201) | Q201: =IF($S201="","",J201+M201) | R201: =IF($S201="","",Q201-O201-G201) | S201: =IF(ROWS($S$2:$S201)<=MAX('Per Line'!$U$2:$U$501),MATCH(ROWS($S$2:$S201),'Per Line'!$U$2:$U$501,0),"")
