Workbook

Sheet How To Use
A1: Claims Template - CHEIRON - PICO PETROLEUM (Chronic)
A3: Monthly steps
A4: 1. Open the 'Per Line' tab. Delete the old data in the BLUE columns only (row 2 down). Never delete the green or grey columns.
A5: 2. Paste the new month's data as VALUES starting at A2, into the blue columns: A-I, K-Q, U-V, X-AE (same order as the system export).
A6: 3. Green columns (J, R, S, T, W) and the grey helper columns (AF-AJ) calculate automatically - do not paste over them.
A7: 4. 'Per Invoice' fills itself from 'Per Line' (one row per Order #, split into IMP / Local). No pivot table, no refresh.
A8: 5. The ONLY manual column in 'Per Invoice' is column A 'Invoice' (blue): type it yourself. Everything else is formula.
A9: 6. Open 'Settings' and check STATUS says OK (Per Line totals = Per Invoice totals).
A11: Colour legend
A12: Blue header = typed/pasted by you (raw data, and 'Invoice' in Per Invoice). Green header = formula (do not paste over). Grey header = helper formula (do not touch). Yellow cell (Settings) = editable rate.
A14: Calculation rules (taken from the September 2026 sheet)
A15: Co val = Order Co Payment x Total / 100. Discount = Total x Rebates / 100. Subtotal = Total - Discount. Net = Subtotal - Co val. (Total = 'Product Total')
... A20: Capacity: up to 1,500 lines and 300 invoices per month. A line with an empty Order # is ignored.

Sheet Settings
B1: Company settings & checks
B3: Insurance Company | C3: CHEIRON - PICO PETROLEUM | D3: Informational only
B4: Corporate | C4: Pico Indvidual; Pico الشركات المشتركة; Pico 1st floor; Pico 2nd floor; Pico 3rd floor; Pico 4th floor; Pico G floor | D4: Informational only
B5: Sheet type | C5: Chronic | D5: Informational only
B6: Local products rebate % | C6: 0.15 | D6: Source: Sep sheet (Rebates = 15 on Local lines, 0 on Special Rebates = Yes).
B7: Imported (IMP) products rebate % | C7: 0.05 | D7: Source: Sep sheet (Rebates = 5 on non-local lines).
B9: Month totals / reconciliation
B10: Lines loaded | C10: =COUNTA('Per Line'!$B$2:$B$1501)
B11: Invoices (unique Order #) | C11: =MAX('Per Line'!$AG$2:$AG$1501)
B12: Invoices shown in Per Invoice | C12: =SUMPRODUCT(--('Per Invoice'!$B$2:$B$301<>""))
B13: Grand Total - Per Line (Product Total) | C13: =SUM('Per Line'!$Q$2:$Q$1501)
B14: Grand Total - Per Invoice | C14: =SUM('Per Invoice'!$U$2:$U$301)
B15: Discount - Per Line | C15: =SUM('Per Line'!$R$2:$R$1501)
B16: Discount - Per Invoice | C16: =SUM('Per Invoice'!$S$2:$S$301)
B17: Co val - Per Line | C17: =SUM('Per Line'!$J$2:$J$1501)
B18: Co val - Per Invoice | C18: =SUM('Per Invoice'!$J$2:$J$301)
B19: Net - Per Line | C19: =SUM('Per Line'!$T$2:$T$1501)
B20: Net - Per Invoice | C20: =SUM('Per Invoice'!$V$2:$V$301)
B21: Max Limit adjustment (Co val, Per Invoice only) | C21: 0 | D21: This company's Per Invoice has no Max Limit rule.
B23: STATUS | C23: =IF(C10=0,"No data loaded",IF(COUNTA('Per Line'!$B:$B)-1>1500,"TOO MANY LINES - extend template",IF(C11>300,"TOO MANY INVOICES - extend template",IF(AND(ROUND(C13-C14,2)=0,ROUND(C15-C16,2)=0,ROUND(C17+C21-C18,2)=0,ROUND(C19-C21-C20,2)=0,C11=C12),"OK","CHECK - Per Line and Per Invoice do not match")))) | D23: Must say OK after you paste the month data.

Sheet Per Line
A1: Ticket # | B1: Order # | C1: Create At | D1: Insurance Company | E1: Country Portal ID | F1: Corporate | G1: Card | H1: Name | I1: Order Co Payment | J1: Co val | K1: heisenberg id | L1: Product Name | M1: Local | N1: Unit | O1: Quantity | P1: Unit Price | Q1: Product Total | R1: Discount | S1: Subtotal | T1: Net | U1: ERX ID | V1: Special Rebates? | W1: Rebates | X1: Approval Type | Y1: Max Limit | Z1: Exceeding Limit | AA1: Amount collected from customer | AB1: By Patient (Delivered) | AC1: Dispense Number | AD1: Dispense Date | AE1: Has OTP? | AF1: Order 1st Row (helper) | AG1: Invoice # (helper) | AH1: Is Local (helper) | AI1: Is Special (helper) | AJ1: Sort Key (helper)
J2: =IF($B2="","",I2*Q2/100) | R2: =IF($B2="","",Q2*W2/100) | S2: =IF($B2="","",Q2-R2) | T2: =IF($B2="","",S2-J2) | W2: =IF($B2="","",IF($AI2=1,0,IF($AH2=1,Settings!$C$6,Settings!$C$7))*100) | AF2: =IF($B2="","",IF(COUNTIF($B$2:$B2,$B2)=1,1,0)) | AG2: =IF($AF2=1,SUMPRODUCT(--($AJ$2:$AJ$1501<$AJ2))+1,"") | AH2: =IF($B2="","",IF(OR($M2=TRUE(),$M2="TRUE"),1,0)) | AI2: =IF($B2="","",IF($V2="Yes",1,0)) | AJ2: =IF($AF2=1,IFERROR(IF(VALUE($B2)<100000000,VALUE($B2),1000000000),IFERROR(IF(VALUE(MID($B2,2,20))<100000000,VALUE(MID($B2,2,20)),1000000000),1000000000))+ROW()/100000,"")
J3: =IF($B3="","",I3*Q3/100) | R3: =IF($B3="","",Q3*W3/100) | S3: =IF($B3="","",Q3-R3) | T3: =IF($B3="","",S3-J3) | W3: =IF($B3="","",IF($AI3=1,0,IF($AH3=1,Settings!$C$6,Settings!$C$7))*100) | AF3: =IF($B3="","",IF(COUNTIF($B$2:$B3,$B3)=1,1,0)) | AG3: =IF($AF3=1,SUMPRODUCT(--($AJ$2:$AJ$1501<$AJ3))+1,"") | AH3: =IF($B3="","",IF(OR($M3=TRUE(),$M3="TRUE"),1,0)) | AI3: =IF($B3="","",IF($V3="Yes",1,0)) | AJ3: =IF($AF3=1,IFERROR(IF(VALUE($B3)<100000000,VALUE($B3),1000000000),IFERROR(IF(VALUE(MID($B3,2,20))<100000000,VALUE(MID($B3,2,20)),1000000000),1000000000))+ROW()/100000,"")
J4: =IF($B4="","",I4*Q4/100) | R4: =IF($B4="","",Q4*W4/100) | S4: =IF($B4="","",Q4-R4) | T4: =IF($B4="","",S4-J4) | W4: =IF($B4="","",IF($AI4=1,0,IF($AH4=1,Settings!$C$6,Settings!$C$7))*100) | AF4: =IF($B4="","",IF(COUNTIF($B$2:$B4,$B4)=1,1,0)) | AG4: =IF($AF4=1,SUMPRODUCT(--($AJ$2:$AJ$1501<$AJ4))+1,"") | AH4: =IF($B4="","",IF(OR($M4=TRUE(),$M4="TRUE"),1,0)) | AI4: =IF($B4="","",IF($V4="Yes",1,0)) | AJ4: =IF($AF4=1,IFERROR(IF(VALUE($B4)<100000000,VALUE($B4),1000000000),IFERROR(IF(VALUE(MID($B4,2,20))<100000000,VALUE(MID($B4,2,20)),1000000000),1000000000))+ROW()/100000,"")
J5: =IF($B5="","",I5*Q5/100) | R5: =IF($B5="","",Q5*W5/100) | S5: =IF($B5="","",Q5-R5) | T5: =IF($B5="","",S5-J5) | W5: =IF($B5="","",IF($AI5=1,0,IF($AH5=1,Settings!$C$6,Settings!$C$7))*100) | AF5: =IF($B5="","",IF(COUNTIF($B$2:$B5,$B5)=1,1,0)) | AG5: =IF($AF5=1,SUMPRODUCT(--($AJ$2:$AJ$1501<$AJ5))+1,"") | AH5: =IF($B5="","",IF(OR($M5=TRUE(),$M5="TRUE"),1,0)) | AI5: =IF($B5="","",IF($V5="Yes",1,0)) | AJ5: =IF($AF5=1,IFERROR(IF(VALUE($B5)<100000000,VALUE($B5),1000000000),IFERROR(IF(VALUE(MID($B5,2,20))<100000000,VALUE(MID($B5,2,20)),1000000000),1000000000))+ROW()/100000,"")
J6: =IF($B6="","",I6*Q6/100) | R6: =IF($B6="","",Q6*W6/100) | S6: =IF($B6="","",Q6-R6) | T6: =IF($B6="","",S6-J6) | W6: =IF($B6="","",IF($AI6=1,0,IF($AH6=1,Settings!$C$6,Settings!$C$7))*100) | AF6: =IF($B6="","",IF(COUNTIF($B$2:$B6,$B6)=1,1,0)) | AG6: =IF($AF6=1,SUMPRODUCT(--($AJ$2:$AJ$1501<$AJ6))+1,"") | AH6: =IF($B6="","",IF(OR($M6=TRUE(),$M6="TRUE"),1,0)) | AI6: =IF($B6="","",IF($V6="Yes",1,0)) | AJ6: =IF($AF6=1,IFERROR(IF(VALUE($B6)<100000000,VALUE($B6),1000000000),IFERROR(IF(VALUE(MID($B6,2,20))<100000000,VALUE(MID($B6,2,20)),1000000000),1000000000))+ROW()/100000,"")
J7: =IF($B7="","",I7*Q7/100) | R7: =IF($B7="","",Q7*W7/100) | S7: =IF($B7="","",Q7-R7) | T7: =IF($B7="","",S7-J7) | W7: =IF($B7="","",IF($AI7=1,0,IF($AH7=1,Settings!$C$6,Settings!$C$7))*100) | AF7: =IF($B7="","",IF(COUNTIF($B$2:$B7,$B7)=1,1,0)) | AG7: =IF($AF7=1,SUMPRODUCT(--($AJ$2:$AJ$1501<$AJ7))+1,"") | AH7: =IF($B7="","",IF(OR($M7=TRUE(),$M7="TRUE"),1,0)) | AI7: =IF($B7="","",IF($V7="Yes",1,0)) | AJ7: =IF($AF7=1,IFERROR(IF(VALUE($B7)<100000000,VALUE($B7),1000000000),IFERROR(IF(VALUE(MID($B7,2,20))<100000000,VALUE(MID($B7,2,20)),1000000000),1000000000))+ROW()/100000,"")
J8: =IF($B8="","",I8*Q8/100) | R8: =IF($B8="","",Q8*W8/100) | S8: =IF($B8="","",Q8-R8) | T8: =IF($B8="","",S8-J8) | W8: =IF($B8="","",IF($AI8=1,0,IF($AH8=1,Settings!$C$6,Settings!$C$7))*100) | AF8: =IF($B8="","",IF(COUNTIF($B$2:$B8,$B8)=1,1,0)) | AG8: =IF($AF8=1,SUMPRODUCT(--($AJ$2:$AJ$1501<$AJ8))+1,"") | AH8: =IF($B8="","",IF(OR($M8=TRUE(),$M8="TRUE"),1,0)) | AI8: =IF($B8="","",IF($V8="Yes",1,0)) | AJ8: =IF($AF8=1,IFERROR(IF(VALUE($B8)<100000000,VALUE($B8),1000000000),IFERROR(IF(VALUE(MID($B8,2,20))<100000000,VALUE(MID($B8,2,20)),1000000000),1000000000))+ROW()/100000,"")
J9: =IF($B9="","",I9*Q9/100) | R9: =IF($B9="","",Q9*W9/100) | S9: =IF($B9="","",Q9-R9) | T9: =IF($B9="","",S9-J9) | W9: =IF($B9="","",IF($AI9=1,0,IF($AH9=1,Settings!$C$6,Settings!$C$7))*100) | AF9: =IF($B9="","",IF(COUNTIF($B$2:$B9,$B9)=1,1,0)) | AG9: =IF($AF9=1,SUMPRODUCT(--($AJ$2:$AJ$1501<$AJ9))+1,"") | AH9: =IF($B9="","",IF(OR($M9=TRUE(),$M9="TRUE"),1,0)) | AI9: =IF($B9="","",IF($V9="Yes",1,0)) | AJ9: =IF($AF9=1,IFERROR(IF(VALUE($B9)<100000000,VALUE($B9),1000000000),IFERROR(IF(VALUE(MID($B9,2,20))<100000000,VALUE(MID($B9,2,20)),1000000000),1000000000))+ROW()/100000,"")
J10: =IF($B10="","",I10*Q10/100) | R10: =IF($B10="","",Q10*W10/100) | S10: =IF($B10="","",Q10-R10) | T10: =IF($B10="","",S10-J10) | W10: =IF($B10="","",IF($AI10=1,0,IF($AH10=1,Settings!$C$6,Settings!$C$7))*100) | AF10: =IF($B10="","",IF(COUNTIF($B$2:$B10,$B10)=1,1,0)) | AG10: =IF($AF10=1,SUMPRODUCT(--($AJ$2:$AJ$1501<$AJ10))+1,"") | AH10: =IF($B10="","",IF(OR($M10=TRUE(),$M10="TRUE"),1,0)) | AI10: =IF($B10="","",IF($V10="Yes",1,0)) | AJ10: =IF($AF10=1,IFERROR(IF(VALUE($B10)<100000000,VALUE($B10),1000000000),IFERROR(IF(VALUE(MID($B10,2,20))<100000000,VALUE(MID($B10,2,20)),1000000000),1000000000))+ROW()/100000,"")
J11: =IF($B11="","",I11*Q11/100) | R11: =IF($B11="","",Q11*W11/100) | S11: =IF($B11="","",Q11-R11) | T11: =IF($B11="","",S11-J11) | W11: =IF($B11="","",IF($AI11=1,0,IF($AH11=1,Settings!$C$6,Settings!$C$7))*100) | AF11: =IF($B11="","",IF(COUNTIF($B$2:$B11,$B11)=1,1,0)) | AG11: =IF($AF11=1,SUMPRODUCT(--($AJ$2:$AJ$1501<$AJ11))+1,"") | AH11: =IF($B11="","",IF(OR($M11=TRUE(),$M11="TRUE"),1,0)) | AI11: =IF($B11="","",IF($V11="Yes",1,0)) | AJ11: =IF($AF11=1,IFERROR(IF(VALUE($B11)<100000000,VALUE($B11),1000000000),IFERROR(IF(VALUE(MID($B11,2,20))<100000000,VALUE(MID($B11,2,20)),1000000000),1000000000))+ROW()/100000,"")
J12: =IF($B12="","",I12*Q12/100) | R12: =IF($B12="","",Q12*W12/100) | S12: =IF($B12="","",Q12-R12) | T12: =IF($B12="","",S12-J12) | W12: =IF($B12="","",IF($AI12=1,0,IF($AH12=1,Settings!$C$6,Settings!$C$7))*100) | AF12: =IF($B12="","",IF(COUNTIF($B$2:$B12,$B12)=1,1,0)) | AG12: =IF($AF12=1,SUMPRODUCT(--($AJ$2:$AJ$1501<$AJ12))+1,"") | AH12: =IF($B12="","",IF(OR($M12=TRUE(),$M12="TRUE"),1,0)) | AI12: =IF($B12="","",IF($V12="Yes",1,0)) | AJ12: =IF($AF12=1,IFERROR(IF(VALUE($B12)<100000000,VALUE($B12),1000000000),IFERROR(IF(VALUE(MID($B12,2,20))<100000000,VALUE(MID($B12,2,20)),1000000000),1000000000))+ROW()/100000,"")
J13: =IF($B13="","",I13*Q13/100) | R13: =IF($B13="","",Q13*W13/100) | S13: =IF($B13="","",Q13-R13) | T13: =IF($B13="","",S13-J13) | W13: =IF($B13="","",IF($AI13=1,0,IF($AH13=1,Settings!$C$6,Settings!$C$7))*100) | AF13: =IF($B13="","",IF(COUNTIF($B$2:$B13,$B13)=1,1,0)) | AG13: =IF($AF13=1,SUMPRODUCT(--($AJ$2:$AJ$1501<$AJ13))+1,"") | AH13: =IF($B13="","",IF(OR($M13=TRUE(),$M13="TRUE"),1,0)) | AI13: =IF($B13="","",IF($V13="Yes",1,0)) | AJ13: =IF($AF13=1,IFERROR(IF(VALUE($B13)<100000000,VALUE($B13),1000000000),IFERROR(IF(VALUE(MID($B13,2,20))<100000000,VALUE(MID($B13,2,20)),1000000000),1000000000))+ROW()/100000,"")
... J1501: =IF($B1501="","",I1501*Q1501/100) | R1501: =IF($B1501="","",Q1501*W1501/100) | S1501: =IF($B1501="","",Q1501-R1501) | T1501: =IF($B1501="","",S1501-J1501) | W1501: =IF($B1501="","",IF($AI1501=1,0,IF($AH1501=1,Settings!$C$6,Settings!$C$7))*100) | AF1501: =IF($B1501="","",IF(COUNTIF($B$2:$B1501,$B1501)=1,1,0)) | AG1501: =IF($AF1501=1,SUMPRODUCT(--($AJ$2:$AJ$1501<$AJ1501))+1,"") | AH1501: =IF($B1501="","",IF(OR($M1501=TRUE(),$M1501="TRUE"),1,0)) | AI1501: =IF($B1501="","",IF($V1501="Yes",1,0)) | AJ1501: =IF($AF1501=1,IFERROR(IF(VALUE($B1501)<100000000,VALUE($B1501),1000000000),IFERROR(IF(VALUE(MID($B1501,2,20))<100000000,VALUE(MID($B1501,2,20)),1000000000),1000000000))+ROW()/100000,"")

Sheet Per Invoice
A1: Invoice | B1: Order # | C1: Ticket # | D1: Create At | E1: Insurance Company | F1: Corporate | G1: Card | H1: Name | I1: Order Co Payment | J1: Co val | K1: ERX ID | L1: SP | M1: IMP% | N1: IMP | O1: IM VAL | P1: LOCAL% | Q1: LOCAL | R1: LOCAL VAL | S1: TOTAL VAL | T1: SUBTOTAL | U1: Grand Total | V1: NET | W1: Src Row (helper)
B2: =IF($W2="","",INDEX('Per Line'!$B$2:$B$1501,$W2)&"") | C2: =IF($W2="","",INDEX('Per Line'!$A$2:$A$1501,$W2)) | D2: =IF($W2="","",INDEX('Per Line'!$C$2:$C$1501,$W2)) | E2: =IF($W2="","",INDEX('Per Line'!$D$2:$D$1501,$W2)&"") | F2: =IF($W2="","",INDEX('Per Line'!$F$2:$F$1501,$W2)&"") | G2: =IF($W2="","",INDEX('Per Line'!$G$2:$G$1501,$W2)&"") | H2: =IF($W2="","",INDEX('Per Line'!$H$2:$H$1501,$W2)&"") | I2: =IF($W2="","",INDEX('Per Line'!$I$2:$I$1501,$W2)) | J2: =IF($W2="","",I2*U2/100) | K2: =IF($W2="","",INDEX('Per Line'!$U$2:$U$1501,$W2)&"") | L2: =IF($W2="","",SUMIFS('Per Line'!$Q$2:$Q$1501,'Per Line'!$B$2:$B$1501,$B2,'Per Line'!$AI$2:$AI$1501,1)) | M2: =IF($W2="","",Settings!$C$7) | N2: =IF($W2="","",SUMIFS('Per Line'!$Q$2:$Q$1501,'Per Line'!$B$2:$B$1501,$B2,'Per Line'!$AH$2:$AH$1501,0,'Per Line'!$AI$2:$AI$1501,0)) | O2: =IF($W2="","",N2*M2) | P2: =IF($W2="","",Settings!$C$6) | Q2: =IF($W2="","",SUMIFS('Per Line'!$Q$2:$Q$1501,'Per Line'!$B$2:$B$1501,$B2,'Per Line'!$AH$2:$AH$1501,1,'Per Line'!$AI$2:$AI$1501,0)) | R2: =IF($W2="","",Q2*P2) | S2: =IF($W2="","",R2+O2) | T2: =IF($W2="","",U2-S2) | U2: =IF($W2="","",N2+Q2+L2) | V2: =IF($W2="","",U2-S2-J2) | W2: =IF(ROWS($W$2:$W2)<=MAX('Per Line'!$AG$2:$AG$1501),MATCH(ROWS($W$2:$W2),'Per Line'!$AG$2:$AG$1501,0),"")
B3: =IF($W3="","",INDEX('Per Line'!$B$2:$B$1501,$W3)&"") | C3: =IF($W3="","",INDEX('Per Line'!$A$2:$A$1501,$W3)) | D3: =IF($W3="","",INDEX('Per Line'!$C$2:$C$1501,$W3)) | E3: =IF($W3="","",INDEX('Per Line'!$D$2:$D$1501,$W3)&"") | F3: =IF($W3="","",INDEX('Per Line'!$F$2:$F$1501,$W3)&"") | G3: =IF($W3="","",INDEX('Per Line'!$G$2:$G$1501,$W3)&"") | H3: =IF($W3="","",INDEX('Per Line'!$H$2:$H$1501,$W3)&"") | I3: =IF($W3="","",INDEX('Per Line'!$I$2:$I$1501,$W3)) | J3: =IF($W3="","",I3*U3/100) | K3: =IF($W3="","",INDEX('Per Line'!$U$2:$U$1501,$W3)&"") | L3: =IF($W3="","",SUMIFS('Per Line'!$Q$2:$Q$1501,'Per Line'!$B$2:$B$1501,$B3,'Per Line'!$AI$2:$AI$1501,1)) | M3: =IF($W3="","",Settings!$C$7) | N3: =IF($W3="","",SUMIFS('Per Line'!$Q$2:$Q$1501,'Per Line'!$B$2:$B$1501,$B3,'Per Line'!$AH$2:$AH$1501,0,'Per Line'!$AI$2:$AI$1501,0)) | O3: =IF($W3="","",N3*M3) | P3: =IF($W3="","",Settings!$C$6) | Q3: =IF($W3="","",SUMIFS('Per Line'!$Q$2:$Q$1501,'Per Line'!$B$2:$B$1501,$B3,'Per Line'!$AH$2:$AH$1501,1,'Per Line'!$AI$2:$AI$1501,0)) | R3: =IF($W3="","",Q3*P3) | S3: =IF($W3="","",R3+O3) | T3: =IF($W3="","",U3-S3) | U3: =IF($W3="","",N3+Q3+L3) | V3: =IF($W3="","",U3-S3-J3) | W3: =IF(ROWS($W$2:$W3)<=MAX('Per Line'!$AG$2:$AG$1501),MATCH(ROWS($W$2:$W3),'Per Line'!$AG$2:$AG$1501,0),"")
B4: =IF($W4="","",INDEX('Per Line'!$B$2:$B$1501,$W4)&"") | C4: =IF($W4="","",INDEX('Per Line'!$A$2:$A$1501,$W4)) | D4: =IF($W4="","",INDEX('Per Line'!$C$2:$C$1501,$W4)) | E4: =IF($W4="","",INDEX('Per Line'!$D$2:$D$1501,$W4)&"") | F4: =IF($W4="","",INDEX('Per Line'!$F$2:$F$1501,$W4)&"") | G4: =IF($W4="","",INDEX('Per Line'!$G$2:$G$1501,$W4)&"") | H4: =IF($W4="","",INDEX('Per Line'!$H$2:$H$1501,$W4)&"") | I4: =IF($W4="","",INDEX('Per Line'!$I$2:$I$1501,$W4)) | J4: =IF($W4="","",I4*U4/100) | K4: =IF($W4="","",INDEX('Per Line'!$U$2:$U$1501,$W4)&"") | L4: =IF($W4="","",SUMIFS('Per Line'!$Q$2:$Q$1501,'Per Line'!$B$2:$B$1501,$B4,'Per Line'!$AI$2:$AI$1501,1)) | M4: =IF($W4="","",Settings!$C$7) | N4: =IF($W4="","",SUMIFS('Per Line'!$Q$2:$Q$1501,'Per Line'!$B$2:$B$1501,$B4,'Per Line'!$AH$2:$AH$1501,0,'Per Line'!$AI$2:$AI$1501,0)) | O4: =IF($W4="","",N4*M4) | P4: =IF($W4="","",Settings!$C$6) | Q4: =IF($W4="","",SUMIFS('Per Line'!$Q$2:$Q$1501,'Per Line'!$B$2:$B$1501,$B4,'Per Line'!$AH$2:$AH$1501,1,'Per Line'!$AI$2:$AI$1501,0)) | R4: =IF($W4="","",Q4*P4) | S4: =IF($W4="","",R4+O4) | T4: =IF($W4="","",U4-S4) | U4: =IF($W4="","",N4+Q4+L4) | V4: =IF($W4="","",U4-S4-J4) | W4: =IF(ROWS($W$2:$W4)<=MAX('Per Line'!$AG$2:$AG$1501),MATCH(ROWS($W$2:$W4),'Per Line'!$AG$2:$AG$1501,0),"")
B5: =IF($W5="","",INDEX('Per Line'!$B$2:$B$1501,$W5)&"") | C5: =IF($W5="","",INDEX('Per Line'!$A$2:$A$1501,$W5)) | D5: =IF($W5="","",INDEX('Per Line'!$C$2:$C$1501,$W5)) | E5: =IF($W5="","",INDEX('Per Line'!$D$2:$D$1501,$W5)&"") | F5: =IF($W5="","",INDEX('Per Line'!$F$2:$F$1501,$W5)&"") | G5: =IF($W5="","",INDEX('Per Line'!$G$2:$G$1501,$W5)&"") | H5: =IF($W5="","",INDEX('Per Line'!$H$2:$H$1501,$W5)&"") | I5: =IF($W5="","",INDEX('Per Line'!$I$2:$I$1501,$W5)) | J5: =IF($W5="","",I5*U5/100) | K5: =IF($W5="","",INDEX('Per Line'!$U$2:$U$1501,$W5)&"") | L5: =IF($W5="","",SUMIFS('Per Line'!$Q$2:$Q$1501,'Per Line'!$B$2:$B$1501,$B5,'Per Line'!$AI$2:$AI$1501,1)) | M5: =IF($W5="","",Settings!$C$7) | N5: =IF($W5="","",SUMIFS('Per Line'!$Q$2:$Q$1501,'Per Line'!$B$2:$B$1501,$B5,'Per Line'!$AH$2:$AH$1501,0,'Per Line'!$AI$2:$AI$1501,0)) | O5: =IF($W5="","",N5*M5) | P5: =IF($W5="","",Settings!$C$6) | Q5: =IF($W5="","",SUMIFS('Per Line'!$Q$2:$Q$1501,'Per Line'!$B$2:$B$1501,$B5,'Per Line'!$AH$2:$AH$1501,1,'Per Line'!$AI$2:$AI$1501,0)) | R5: =IF($W5="","",Q5*P5) | S5: =IF($W5="","",R5+O5) | T5: =IF($W5="","",U5-S5) | U5: =IF($W5="","",N5+Q5+L5) | V5: =IF($W5="","",U5-S5-J5) | W5: =IF(ROWS($W$2:$W5)<=MAX('Per Line'!$AG$2:$AG$1501),MATCH(ROWS($W$2:$W5),'Per Line'!$AG$2:$AG$1501,0),"")
B6: =IF($W6="","",INDEX('Per Line'!$B$2:$B$1501,$W6)&"") | C6: =IF($W6="","",INDEX('Per Line'!$A$2:$A$1501,$W6)) | D6: =IF($W6="","",INDEX('Per Line'!$C$2:$C$1501,$W6)) | E6: =IF($W6="","",INDEX('Per Line'!$D$2:$D$1501,$W6)&"") | F6: =IF($W6="","",INDEX('Per Line'!$F$2:$F$1501,$W6)&"") | G6: =IF($W6="","",INDEX('Per Line'!$G$2:$G$1501,$W6)&"") | H6: =IF($W6="","",INDEX('Per Line'!$H$2:$H$1501,$W6)&"") | I6: =IF($W6="","",INDEX('Per Line'!$I$2:$I$1501,$W6)) | J6: =IF($W6="","",I6*U6/100) | K6: =IF($W6="","",INDEX('Per Line'!$U$2:$U$1501,$W6)&"") | L6: =IF($W6="","",SUMIFS('Per Line'!$Q$2:$Q$1501,'Per Line'!$B$2:$B$1501,$B6,'Per Line'!$AI$2:$AI$1501,1)) | M6: =IF($W6="","",Settings!$C$7) | N6: =IF($W6="","",SUMIFS('Per Line'!$Q$2:$Q$1501,'Per Line'!$B$2:$B$1501,$B6,'Per Line'!$AH$2:$AH$1501,0,'Per Line'!$AI$2:$AI$1501,0)) | O6: =IF($W6="","",N6*M6) | P6: =IF($W6="","",Settings!$C$6) | Q6: =IF($W6="","",SUMIFS('Per Line'!$Q$2:$Q$1501,'Per Line'!$B$2:$B$1501,$B6,'Per Line'!$AH$2:$AH$1501,1,'Per Line'!$AI$2:$AI$1501,0)) | R6: =IF($W6="","",Q6*P6) | S6: =IF($W6="","",R6+O6) | T6: =IF($W6="","",U6-S6) | U6: =IF($W6="","",N6+Q6+L6) | V6: =IF($W6="","",U6-S6-J6) | W6: =IF(ROWS($W$2:$W6)<=MAX('Per Line'!$AG$2:$AG$1501),MATCH(ROWS($W$2:$W6),'Per Line'!$AG$2:$AG$1501,0),"")
B7: =IF($W7="","",INDEX('Per Line'!$B$2:$B$1501,$W7)&"") | C7: =IF($W7="","",INDEX('Per Line'!$A$2:$A$1501,$W7)) | D7: =IF($W7="","",INDEX('Per Line'!$C$2:$C$1501,$W7)) | E7: =IF($W7="","",INDEX('Per Line'!$D$2:$D$1501,$W7)&"") | F7: =IF($W7="","",INDEX('Per Line'!$F$2:$F$1501,$W7)&"") | G7: =IF($W7="","",INDEX('Per Line'!$G$2:$G$1501,$W7)&"") | H7: =IF($W7="","",INDEX('Per Line'!$H$2:$H$1501,$W7)&"") | I7: =IF($W7="","",INDEX('Per Line'!$I$2:$I$1501,$W7)) | J7: =IF($W7="","",I7*U7/100) | K7: =IF($W7="","",INDEX('Per Line'!$U$2:$U$1501,$W7)&"") | L7: =IF($W7="","",SUMIFS('Per Line'!$Q$2:$Q$1501,'Per Line'!$B$2:$B$1501,$B7,'Per Line'!$AI$2:$AI$1501,1)) | M7: =IF($W7="","",Settings!$C$7) | N7: =IF($W7="","",SUMIFS('Per Line'!$Q$2:$Q$1501,'Per Line'!$B$2:$B$1501,$B7,'Per Line'!$AH$2:$AH$1501,0,'Per Line'!$AI$2:$AI$1501,0)) | O7: =IF($W7="","",N7*M7) | P7: =IF($W7="","",Settings!$C$6) | Q7: =IF($W7="","",SUMIFS('Per Line'!$Q$2:$Q$1501,'Per Line'!$B$2:$B$1501,$B7,'Per Line'!$AH$2:$AH$1501,1,'Per Line'!$AI$2:$AI$1501,0)) | R7: =IF($W7="","",Q7*P7) | S7: =IF($W7="","",R7+O7) | T7: =IF($W7="","",U7-S7) | U7: =IF($W7="","",N7+Q7+L7) | V7: =IF($W7="","",U7-S7-J7) | W7: =IF(ROWS($W$2:$W7)<=MAX('Per Line'!$AG$2:$AG$1501),MATCH(ROWS($W$2:$W7),'Per Line'!$AG$2:$AG$1501,0),"")
B8: =IF($W8="","",INDEX('Per Line'!$B$2:$B$1501,$W8)&"") | C8: =IF($W8="","",INDEX('Per Line'!$A$2:$A$1501,$W8)) | D8: =IF($W8="","",INDEX('Per Line'!$C$2:$C$1501,$W8)) | E8: =IF($W8="","",INDEX('Per Line'!$D$2:$D$1501,$W8)&"") | F8: =IF($W8="","",INDEX('Per Line'!$F$2:$F$1501,$W8)&"") | G8: =IF($W8="","",INDEX('Per Line'!$G$2:$G$1501,$W8)&"") | H8: =IF($W8="","",INDEX('Per Line'!$H$2:$H$1501,$W8)&"") | I8: =IF($W8="","",INDEX('Per Line'!$I$2:$I$1501,$W8)) | J8: =IF($W8="","",I8*U8/100) | K8: =IF($W8="","",INDEX('Per Line'!$U$2:$U$1501,$W8)&"") | L8: =IF($W8="","",SUMIFS('Per Line'!$Q$2:$Q$1501,'Per Line'!$B$2:$B$1501,$B8,'Per Line'!$AI$2:$AI$1501,1)) | M8: =IF($W8="","",Settings!$C$7) | N8: =IF($W8="","",SUMIFS('Per Line'!$Q$2:$Q$1501,'Per Line'!$B$2:$B$1501,$B8,'Per Line'!$AH$2:$AH$1501,0,'Per Line'!$AI$2:$AI$1501,0)) | O8: =IF($W8="","",N8*M8) | P8: =IF($W8="","",Settings!$C$6) | Q8: =IF($W8="","",SUMIFS('Per Line'!$Q$2:$Q$1501,'Per Line'!$B$2:$B$1501,$B8,'Per Line'!$AH$2:$AH$1501,1,'Per Line'!$AI$2:$AI$1501,0)) | R8: =IF($W8="","",Q8*P8) | S8: =IF($W8="","",R8+O8) | T8: =IF($W8="","",U8-S8) | U8: =IF($W8="","",N8+Q8+L8) | V8: =IF($W8="","",U8-S8-J8) | W8: =IF(ROWS($W$2:$W8)<=MAX('Per Line'!$AG$2:$AG$1501),MATCH(ROWS($W$2:$W8),'Per Line'!$AG$2:$AG$1501,0),"")
B9: =IF($W9="","",INDEX('Per Line'!$B$2:$B$1501,$W9)&"") | C9: =IF($W9="","",INDEX('Per Line'!$A$2:$A$1501,$W9)) | D9: =IF($W9="","",INDEX('Per Line'!$C$2:$C$1501,$W9)) | E9: =IF($W9="","",INDEX('Per Line'!$D$2:$D$1501,$W9)&"") | F9: =IF($W9="","",INDEX('Per Line'!$F$2:$F$1501,$W9)&"") | G9: =IF($W9="","",INDEX('Per Line'!$G$2:$G$1501,$W9)&"") | H9: =IF($W9="","",INDEX('Per Line'!$H$2:$H$1501,$W9)&"") | I9: =IF($W9="","",INDEX('Per Line'!$I$2:$I$1501,$W9)) | J9: =IF($W9="","",I9*U9/100) | K9: =IF($W9="","",INDEX('Per Line'!$U$2:$U$1501,$W9)&"") | L9: =IF($W9="","",SUMIFS('Per Line'!$Q$2:$Q$1501,'Per Line'!$B$2:$B$1501,$B9,'Per Line'!$AI$2:$AI$1501,1)) | M9: =IF($W9="","",Settings!$C$7) | N9: =IF($W9="","",SUMIFS('Per Line'!$Q$2:$Q$1501,'Per Line'!$B$2:$B$1501,$B9,'Per Line'!$AH$2:$AH$1501,0,'Per Line'!$AI$2:$AI$1501,0)) | O9: =IF($W9="","",N9*M9) | P9: =IF($W9="","",Settings!$C$6) | Q9: =IF($W9="","",SUMIFS('Per Line'!$Q$2:$Q$1501,'Per Line'!$B$2:$B$1501,$B9,'Per Line'!$AH$2:$AH$1501,1,'Per Line'!$AI$2:$AI$1501,0)) | R9: =IF($W9="","",Q9*P9) | S9: =IF($W9="","",R9+O9) | T9: =IF($W9="","",U9-S9) | U9: =IF($W9="","",N9+Q9+L9) | V9: =IF($W9="","",U9-S9-J9) | W9: =IF(ROWS($W$2:$W9)<=MAX('Per Line'!$AG$2:$AG$1501),MATCH(ROWS($W$2:$W9),'Per Line'!$AG$2:$AG$1501,0),"")
B10: =IF($W10="","",INDEX('Per Line'!$B$2:$B$1501,$W10)&"") | C10: =IF($W10="","",INDEX('Per Line'!$A$2:$A$1501,$W10)) | D10: =IF($W10="","",INDEX('Per Line'!$C$2:$C$1501,$W10)) | E10: =IF($W10="","",INDEX('Per Line'!$D$2:$D$1501,$W10)&"") | F10: =IF($W10="","",INDEX('Per Line'!$F$2:$F$1501,$W10)&"") | G10: =IF($W10="","",INDEX('Per Line'!$G$2:$G$1501,$W10)&"") | H10: =IF($W10="","",INDEX('Per Line'!$H$2:$H$1501,$W10)&"") | I10: =IF($W10="","",INDEX('Per Line'!$I$2:$I$1501,$W10)) | J10: =IF($W10="","",I10*U10/100) | K10: =IF($W10="","",INDEX('Per Line'!$U$2:$U$1501,$W10)&"") | L10: =IF($W10="","",SUMIFS('Per Line'!$Q$2:$Q$1501,'Per Line'!$B$2:$B$1501,$B10,'Per Line'!$AI$2:$AI$1501,1)) | M10: =IF($W10="","",Settings!$C$7) | N10: =IF($W10="","",SUMIFS('Per Line'!$Q$2:$Q$1501,'Per Line'!$B$2:$B$1501,$B10,'Per Line'!$AH$2:$AH$1501,0,'Per Line'!$AI$2:$AI$1501,0)) | O10: =IF($W10="","",N10*M10) | P10: =IF($W10="","",Settings!$C$6) | Q10: =IF($W10="","",SUMIFS('Per Line'!$Q$2:$Q$1501,'Per Line'!$B$2:$B$1501,$B10,'Per Line'!$AH$2:$AH$1501,1,'Per Line'!$AI$2:$AI$1501,0)) | R10: =IF($W10="","",Q10*P10) | S10: =IF($W10="","",R10+O10) | T10: =IF($W10="","",U10-S10) | U10: =IF($W10="","",N10+Q10+L10) | V10: =IF($W10="","",U10-S10-J10) | W10: =IF(ROWS($W$2:$W10)<=MAX('Per Line'!$AG$2:$AG$1501),MATCH(ROWS($W$2:$W10),'Per Line'!$AG$2:$AG$1501,0),"")
B11: =IF($W11="","",INDEX('Per Line'!$B$2:$B$1501,$W11)&"") | C11: =IF($W11="","",INDEX('Per Line'!$A$2:$A$1501,$W11)) | D11: =IF($W11="","",INDEX('Per Line'!$C$2:$C$1501,$W11)) | E11: =IF($W11="","",INDEX('Per Line'!$D$2:$D$1501,$W11)&"") | F11: =IF($W11="","",INDEX('Per Line'!$F$2:$F$1501,$W11)&"") | G11: =IF($W11="","",INDEX('Per Line'!$G$2:$G$1501,$W11)&"") | H11: =IF($W11="","",INDEX('Per Line'!$H$2:$H$1501,$W11)&"") | I11: =IF($W11="","",INDEX('Per Line'!$I$2:$I$1501,$W11)) | J11: =IF($W11="","",I11*U11/100) | K11: =IF($W11="","",INDEX('Per Line'!$U$2:$U$1501,$W11)&"") | L11: =IF($W11="","",SUMIFS('Per Line'!$Q$2:$Q$1501,'Per Line'!$B$2:$B$1501,$B11,'Per Line'!$AI$2:$AI$1501,1)) | M11: =IF($W11="","",Settings!$C$7) | N11: =IF($W11="","",SUMIFS('Per Line'!$Q$2:$Q$1501,'Per Line'!$B$2:$B$1501,$B11,'Per Line'!$AH$2:$AH$1501,0,'Per Line'!$AI$2:$AI$1501,0)) | O11: =IF($W11="","",N11*M11) | P11: =IF($W11="","",Settings!$C$6) | Q11: =IF($W11="","",SUMIFS('Per Line'!$Q$2:$Q$1501,'Per Line'!$B$2:$B$1501,$B11,'Per Line'!$AH$2:$AH$1501,1,'Per Line'!$AI$2:$AI$1501,0)) | R11: =IF($W11="","",Q11*P11) | S11: =IF($W11="","",R11+O11) | T11: =IF($W11="","",U11-S11) | U11: =IF($W11="","",N11+Q11+L11) | V11: =IF($W11="","",U11-S11-J11) | W11: =IF(ROWS($W$2:$W11)<=MAX('Per Line'!$AG$2:$AG$1501),MATCH(ROWS($W$2:$W11),'Per Line'!$AG$2:$AG$1501,0),"")
B12: =IF($W12="","",INDEX('Per Line'!$B$2:$B$1501,$W12)&"") | C12: =IF($W12="","",INDEX('Per Line'!$A$2:$A$1501,$W12)) | D12: =IF($W12="","",INDEX('Per Line'!$C$2:$C$1501,$W12)) | E12: =IF($W12="","",INDEX('Per Line'!$D$2:$D$1501,$W12)&"") | F12: =IF($W12="","",INDEX('Per Line'!$F$2:$F$1501,$W12)&"") | G12: =IF($W12="","",INDEX('Per Line'!$G$2:$G$1501,$W12)&"") | H12: =IF($W12="","",INDEX('Per Line'!$H$2:$H$1501,$W12)&"") | I12: =IF($W12="","",INDEX('Per Line'!$I$2:$I$1501,$W12)) | J12: =IF($W12="","",I12*U12/100) | K12: =IF($W12="","",INDEX('Per Line'!$U$2:$U$1501,$W12)&"") | L12: =IF($W12="","",SUMIFS('Per Line'!$Q$2:$Q$1501,'Per Line'!$B$2:$B$1501,$B12,'Per Line'!$AI$2:$AI$1501,1)) | M12: =IF($W12="","",Settings!$C$7) | N12: =IF($W12="","",SUMIFS('Per Line'!$Q$2:$Q$1501,'Per Line'!$B$2:$B$1501,$B12,'Per Line'!$AH$2:$AH$1501,0,'Per Line'!$AI$2:$AI$1501,0)) | O12: =IF($W12="","",N12*M12) | P12: =IF($W12="","",Settings!$C$6) | Q12: =IF($W12="","",SUMIFS('Per Line'!$Q$2:$Q$1501,'Per Line'!$B$2:$B$1501,$B12,'Per Line'!$AH$2:$AH$1501,1,'Per Line'!$AI$2:$AI$1501,0)) | R12: =IF($W12="","",Q12*P12) | S12: =IF($W12="","",R12+O12) | T12: =IF($W12="","",U12-S12) | U12: =IF($W12="","",N12+Q12+L12) | V12: =IF($W12="","",U12-S12-J12) | W12: =IF(ROWS($W$2:$W12)<=MAX('Per Line'!$AG$2:$AG$1501),MATCH(ROWS($W$2:$W12),'Per Line'!$AG$2:$AG$1501,0),"")
B13: =IF($W13="","",INDEX('Per Line'!$B$2:$B$1501,$W13)&"") | C13: =IF($W13="","",INDEX('Per Line'!$A$2:$A$1501,$W13)) | D13: =IF($W13="","",INDEX('Per Line'!$C$2:$C$1501,$W13)) | E13: =IF($W13="","",INDEX('Per Line'!$D$2:$D$1501,$W13)&"") | F13: =IF($W13="","",INDEX('Per Line'!$F$2:$F$1501,$W13)&"") | G13: =IF($W13="","",INDEX('Per Line'!$G$2:$G$1501,$W13)&"") | H13: =IF($W13="","",INDEX('Per Line'!$H$2:$H$1501,$W13)&"") | I13: =IF($W13="","",INDEX('Per Line'!$I$2:$I$1501,$W13)) | J13: =IF($W13="","",I13*U13/100) | K13: =IF($W13="","",INDEX('Per Line'!$U$2:$U$1501,$W13)&"") | L13: =IF($W13="","",SUMIFS('Per Line'!$Q$2:$Q$1501,'Per Line'!$B$2:$B$1501,$B13,'Per Line'!$AI$2:$AI$1501,1)) | M13: =IF($W13="","",Settings!$C$7) | N13: =IF($W13="","",SUMIFS('Per Line'!$Q$2:$Q$1501,'Per Line'!$B$2:$B$1501,$B13,'Per Line'!$AH$2:$AH$1501,0,'Per Line'!$AI$2:$AI$1501,0)) | O13: =IF($W13="","",N13*M13) | P13: =IF($W13="","",Settings!$C$6) | Q13: =IF($W13="","",SUMIFS('Per Line'!$Q$2:$Q$1501,'Per Line'!$B$2:$B$1501,$B13,'Per Line'!$AH$2:$AH$1501,1,'Per Line'!$AI$2:$AI$1501,0)) | R13: =IF($W13="","",Q13*P13) | S13: =IF($W13="","",R13+O13) | T13: =IF($W13="","",U13-S13) | U13: =IF($W13="","",N13+Q13+L13) | V13: =IF($W13="","",U13-S13-J13) | W13: =IF(ROWS($W$2:$W13)<=MAX('Per Line'!$AG$2:$AG$1501),MATCH(ROWS($W$2:$W13),'Per Line'!$AG$2:$AG$1501,0),"")
... B301: =IF($W301="","",INDEX('Per Line'!$B$2:$B$1501,$W301)&"") | C301: =IF($W301="","",INDEX('Per Line'!$A$2:$A$1501,$W301)) | D301: =IF($W301="","",INDEX('Per Line'!$C$2:$C$1501,$W301)) | E301: =IF($W301="","",INDEX('Per Line'!$D$2:$D$1501,$W301)&"") | F301: =IF($W301="","",INDEX('Per Line'!$F$2:$F$1501,$W301)&"") | G301: =IF($W301="","",INDEX('Per Line'!$G$2:$G$1501,$W301)&"") | H301: =IF($W301="","",INDEX('Per Line'!$H$2:$H$1501,$W301)&"") | I301: =IF($W301="","",INDEX('Per Line'!$I$2:$I$1501,$W301)) | J301: =IF($W301="","",I301*U301/100) | K301: =IF($W301="","",INDEX('Per Line'!$U$2:$U$1501,$W301)&"") | L301: =IF($W301="","",SUMIFS('Per Line'!$Q$2:$Q$1501,'Per Line'!$B$2:$B$1501,$B301,'Per Line'!$AI$2:$AI$1501,1)) | M301: =IF($W301="","",Settings!$C$7) | N301: =IF($W301="","",SUMIFS('Per Line'!$Q$2:$Q$1501,'Per Line'!$B$2:$B$1501,$B301,'Per Line'!$AH$2:$AH$1501,0,'Per Line'!$AI$2:$AI$1501,0)) | O301: =IF($W301="","",N301*M301) | P301: =IF($W301="","",Settings!$C$6) | Q301: =IF($W301="","",SUMIFS('Per Line'!$Q$2:$Q$1501,'Per Line'!$B$2:$B$1501,$B301,'Per Line'!$AH$2:$AH$1501,1,'Per Line'!$AI$2:$AI$1501,0)) | R301: =IF($W301="","",Q301*P301) | S301: =IF($W301="","",R301+O301) | T301: =IF($W301="","",U301-S301) | U301: =IF($W301="","",N301+Q301+L301) | V301: =IF($W301="","",U301-S301-J301) | W301: =IF(ROWS($W$2:$W301)<=MAX('Per Line'!$AG$2:$AG$1501),MATCH(ROWS($W$2:$W301),'Per Line'!$AG$2:$AG$1501,0),"")
