Workbook

Sheet How To Use
A1: Claims Template - SEHA ONE (Walk In)
A3: Monthly steps
A4: 1. Open the 'Per Line' tab. Delete the old data in the BLUE columns only (row 2 down). Never delete the green or grey columns.
A5: 2. Paste the new month's data as VALUES starting at A2, into the blue columns: A, C-F, H-Q (same order as the system export).
A6: 3. Green columns (B, G, R, S, T, U) and the grey helper columns (V-Y) calculate automatically - do not paste over them.
A7: 4. 'Per Invoice' fills itself from 'Per Line' (one row per POS Reference, split into IMP / Local). No pivot table, no refresh.
A8: 5. The ONLY manual column in 'Per Invoice' is column A 'Invoice' (blue): type the invoice number yourself. Everything else is formula.
A9: 6. Open 'Settings' and check STATUS says OK (Per Line totals = Per Invoice totals).
A11: Colour legend
A12: Blue header = typed/pasted by you (raw data, and 'Invoice' in Per Invoice). Green header = formula (do not paste over). Grey header = helper formula (do not touch). Yellow cell (Settings) = editable rate.
A14: Calculation rules (taken from the July 2026 sheet)
A15: Co val = Co Payment % x Subtotal / 100. Discount = Total x Rebates (Rebates is a fraction here, e.g. 0.14). Subtotal = Total - Discount. Net = Subtotal - Co val. (Total = 'Total Delivered')
... A20: Capacity: up to 500 lines and 200 invoices per month. A line with an empty POS Reference is ignored.

Sheet Settings
B1: Company settings & checks
B3: Insurance Company | C3: SEHA ONE | D3: Informational only
B4: Corporate | C4: - | D4: Informational only
B5: Sheet type | C5: Walk In | D5: Informational only
B6: Local products rebate % | C6: 0.11 | D6: Source: July sheet (Rebates = 0.11 on Local lines).
B7: Imported (IMP) products rebate % | C7: 0.05 | D7: Source: July sheet (Rebates = 0.05 on non-local lines).
B9: Month totals / reconciliation
B10: Lines loaded | C10: =COUNTA('Per Line'!$A$2:$A$501)
B11: Invoices (unique Order #) | C11: =MAX('Per Line'!$W$2:$W$501)
B12: Invoices shown in Per Invoice | C12: =SUMPRODUCT(--('Per Invoice'!$B$2:$B$201<>""))
B13: Grand Total - Per Line (Product Total) | C13: =SUM('Per Line'!$L$2:$L$501)
B14: Grand Total - Per Invoice | C14: =SUM('Per Invoice'!$O$2:$O$201)
B15: Discount - Per Line | C15: =SUM('Per Line'!$S$2:$S$501)
B16: Discount - Per Invoice | C16: =SUM('Per Invoice'!$M$2:$M$201)
B17: Co val - Per Line | C17: =SUM('Per Line'!$G$2:$G$501)
B18: Co val - Per Invoice | C18: =SUM('Per Invoice'!$F$2:$F$201)
B19: Net - Per Line | C19: =SUM('Per Line'!$U$2:$U$501)
B20: Net - Per Invoice | C20: =SUM('Per Invoice'!$P$2:$P$201)
B21: Max Limit adjustment (Co val, Per Invoice only) | C21: 0 | D21: This company's Per Invoice has no Max Limit rule.
B23: STATUS | C23: =IF(C10=0,"No data loaded",IF(COUNTA('Per Line'!$A:$A)-1>500,"TOO MANY LINES - extend template",IF(C11>200,"TOO MANY INVOICES - extend template",IF(AND(ROUND(C13-C14,2)=0,ROUND(C15-C16,2)=0,ROUND(C17+C21-C18,2)=0,ROUND(C19-C21-C20,2)=0,C11=C12),"OK","CHECK - Per Line and Per Invoice do not match")))) | D23: Must say OK after you paste the month data.

Sheet Per Line
A1: Pos Reference | B1: Inv | C1: Insurance Company | D1: Name | E1: Card Number | F1: Co Payment % | G1: Co val | H1: Heisenberg id | I1: Product | J1: Original Quantity | K1: Original Price | L1: Total Delivered | M1: Payment Type | N1: Session | O1: Create Date | P1: Order Reference | Q1: Product Template - Product Tmpl → Is Local | R1: Rebates | S1: Discount | T1: Subtotal | U1: Net | V1: Order 1st Row (helper) | W1: Invoice # (helper) | X1: Is Local (helper) | Y1: Sort Key (helper)
B2: =IF($A2="","",IFERROR(IF(INDEX('Per Invoice'!$A$2:$A$201,MATCH($A2,'Per Invoice'!$B$2:$B$201,0))=0,"",INDEX('Per Invoice'!$A$2:$A$201,MATCH($A2,'Per Invoice'!$B$2:$B$201,0))),"")) | G2: =IF($A2="","",F2*T2/100) | R2: =IF($A2="","",IF($X2=1,Settings!$C$6,Settings!$C$7)*1) | S2: =IF($A2="","",R2*L2) | T2: =IF($A2="","",L2-S2) | U2: =IF($A2="","",T2-G2) | V2: =IF($A2="","",IF(COUNTIF($A$2:$A2,$A2)=1,1,0)) | W2: =IF($V2=1,SUMPRODUCT(--($Y$2:$Y$501<$Y2))+1,"") | X2: =IF($A2="","",IF(OR($Q2=TRUE(),$Q2="TRUE"),1,0)) | Y2: =IF($V2=1,IFERROR(VALUE(MID($A2,2,20)),1000000000)+ROW()/100000,"")
B3: =IF($A3="","",IFERROR(IF(INDEX('Per Invoice'!$A$2:$A$201,MATCH($A3,'Per Invoice'!$B$2:$B$201,0))=0,"",INDEX('Per Invoice'!$A$2:$A$201,MATCH($A3,'Per Invoice'!$B$2:$B$201,0))),"")) | G3: =IF($A3="","",F3*T3/100) | R3: =IF($A3="","",IF($X3=1,Settings!$C$6,Settings!$C$7)*1) | S3: =IF($A3="","",R3*L3) | T3: =IF($A3="","",L3-S3) | U3: =IF($A3="","",T3-G3) | V3: =IF($A3="","",IF(COUNTIF($A$2:$A3,$A3)=1,1,0)) | W3: =IF($V3=1,SUMPRODUCT(--($Y$2:$Y$501<$Y3))+1,"") | X3: =IF($A3="","",IF(OR($Q3=TRUE(),$Q3="TRUE"),1,0)) | Y3: =IF($V3=1,IFERROR(VALUE(MID($A3,2,20)),1000000000)+ROW()/100000,"")
B4: =IF($A4="","",IFERROR(IF(INDEX('Per Invoice'!$A$2:$A$201,MATCH($A4,'Per Invoice'!$B$2:$B$201,0))=0,"",INDEX('Per Invoice'!$A$2:$A$201,MATCH($A4,'Per Invoice'!$B$2:$B$201,0))),"")) | G4: =IF($A4="","",F4*T4/100) | R4: =IF($A4="","",IF($X4=1,Settings!$C$6,Settings!$C$7)*1) | S4: =IF($A4="","",R4*L4) | T4: =IF($A4="","",L4-S4) | U4: =IF($A4="","",T4-G4) | V4: =IF($A4="","",IF(COUNTIF($A$2:$A4,$A4)=1,1,0)) | W4: =IF($V4=1,SUMPRODUCT(--($Y$2:$Y$501<$Y4))+1,"") | X4: =IF($A4="","",IF(OR($Q4=TRUE(),$Q4="TRUE"),1,0)) | Y4: =IF($V4=1,IFERROR(VALUE(MID($A4,2,20)),1000000000)+ROW()/100000,"")
B5: =IF($A5="","",IFERROR(IF(INDEX('Per Invoice'!$A$2:$A$201,MATCH($A5,'Per Invoice'!$B$2:$B$201,0))=0,"",INDEX('Per Invoice'!$A$2:$A$201,MATCH($A5,'Per Invoice'!$B$2:$B$201,0))),"")) | G5: =IF($A5="","",F5*T5/100) | R5: =IF($A5="","",IF($X5=1,Settings!$C$6,Settings!$C$7)*1) | S5: =IF($A5="","",R5*L5) | T5: =IF($A5="","",L5-S5) | U5: =IF($A5="","",T5-G5) | V5: =IF($A5="","",IF(COUNTIF($A$2:$A5,$A5)=1,1,0)) | W5: =IF($V5=1,SUMPRODUCT(--($Y$2:$Y$501<$Y5))+1,"") | X5: =IF($A5="","",IF(OR($Q5=TRUE(),$Q5="TRUE"),1,0)) | Y5: =IF($V5=1,IFERROR(VALUE(MID($A5,2,20)),1000000000)+ROW()/100000,"")
B6: =IF($A6="","",IFERROR(IF(INDEX('Per Invoice'!$A$2:$A$201,MATCH($A6,'Per Invoice'!$B$2:$B$201,0))=0,"",INDEX('Per Invoice'!$A$2:$A$201,MATCH($A6,'Per Invoice'!$B$2:$B$201,0))),"")) | G6: =IF($A6="","",F6*T6/100) | R6: =IF($A6="","",IF($X6=1,Settings!$C$6,Settings!$C$7)*1) | S6: =IF($A6="","",R6*L6) | T6: =IF($A6="","",L6-S6) | U6: =IF($A6="","",T6-G6) | V6: =IF($A6="","",IF(COUNTIF($A$2:$A6,$A6)=1,1,0)) | W6: =IF($V6=1,SUMPRODUCT(--($Y$2:$Y$501<$Y6))+1,"") | X6: =IF($A6="","",IF(OR($Q6=TRUE(),$Q6="TRUE"),1,0)) | Y6: =IF($V6=1,IFERROR(VALUE(MID($A6,2,20)),1000000000)+ROW()/100000,"")
B7: =IF($A7="","",IFERROR(IF(INDEX('Per Invoice'!$A$2:$A$201,MATCH($A7,'Per Invoice'!$B$2:$B$201,0))=0,"",INDEX('Per Invoice'!$A$2:$A$201,MATCH($A7,'Per Invoice'!$B$2:$B$201,0))),"")) | G7: =IF($A7="","",F7*T7/100) | R7: =IF($A7="","",IF($X7=1,Settings!$C$6,Settings!$C$7)*1) | S7: =IF($A7="","",R7*L7) | T7: =IF($A7="","",L7-S7) | U7: =IF($A7="","",T7-G7) | V7: =IF($A7="","",IF(COUNTIF($A$2:$A7,$A7)=1,1,0)) | W7: =IF($V7=1,SUMPRODUCT(--($Y$2:$Y$501<$Y7))+1,"") | X7: =IF($A7="","",IF(OR($Q7=TRUE(),$Q7="TRUE"),1,0)) | Y7: =IF($V7=1,IFERROR(VALUE(MID($A7,2,20)),1000000000)+ROW()/100000,"")
B8: =IF($A8="","",IFERROR(IF(INDEX('Per Invoice'!$A$2:$A$201,MATCH($A8,'Per Invoice'!$B$2:$B$201,0))=0,"",INDEX('Per Invoice'!$A$2:$A$201,MATCH($A8,'Per Invoice'!$B$2:$B$201,0))),"")) | G8: =IF($A8="","",F8*T8/100) | R8: =IF($A8="","",IF($X8=1,Settings!$C$6,Settings!$C$7)*1) | S8: =IF($A8="","",R8*L8) | T8: =IF($A8="","",L8-S8) | U8: =IF($A8="","",T8-G8) | V8: =IF($A8="","",IF(COUNTIF($A$2:$A8,$A8)=1,1,0)) | W8: =IF($V8=1,SUMPRODUCT(--($Y$2:$Y$501<$Y8))+1,"") | X8: =IF($A8="","",IF(OR($Q8=TRUE(),$Q8="TRUE"),1,0)) | Y8: =IF($V8=1,IFERROR(VALUE(MID($A8,2,20)),1000000000)+ROW()/100000,"")
B9: =IF($A9="","",IFERROR(IF(INDEX('Per Invoice'!$A$2:$A$201,MATCH($A9,'Per Invoice'!$B$2:$B$201,0))=0,"",INDEX('Per Invoice'!$A$2:$A$201,MATCH($A9,'Per Invoice'!$B$2:$B$201,0))),"")) | G9: =IF($A9="","",F9*T9/100) | R9: =IF($A9="","",IF($X9=1,Settings!$C$6,Settings!$C$7)*1) | S9: =IF($A9="","",R9*L9) | T9: =IF($A9="","",L9-S9) | U9: =IF($A9="","",T9-G9) | V9: =IF($A9="","",IF(COUNTIF($A$2:$A9,$A9)=1,1,0)) | W9: =IF($V9=1,SUMPRODUCT(--($Y$2:$Y$501<$Y9))+1,"") | X9: =IF($A9="","",IF(OR($Q9=TRUE(),$Q9="TRUE"),1,0)) | Y9: =IF($V9=1,IFERROR(VALUE(MID($A9,2,20)),1000000000)+ROW()/100000,"")
B10: =IF($A10="","",IFERROR(IF(INDEX('Per Invoice'!$A$2:$A$201,MATCH($A10,'Per Invoice'!$B$2:$B$201,0))=0,"",INDEX('Per Invoice'!$A$2:$A$201,MATCH($A10,'Per Invoice'!$B$2:$B$201,0))),"")) | G10: =IF($A10="","",F10*T10/100) | R10: =IF($A10="","",IF($X10=1,Settings!$C$6,Settings!$C$7)*1) | S10: =IF($A10="","",R10*L10) | T10: =IF($A10="","",L10-S10) | U10: =IF($A10="","",T10-G10) | V10: =IF($A10="","",IF(COUNTIF($A$2:$A10,$A10)=1,1,0)) | W10: =IF($V10=1,SUMPRODUCT(--($Y$2:$Y$501<$Y10))+1,"") | X10: =IF($A10="","",IF(OR($Q10=TRUE(),$Q10="TRUE"),1,0)) | Y10: =IF($V10=1,IFERROR(VALUE(MID($A10,2,20)),1000000000)+ROW()/100000,"")
B11: =IF($A11="","",IFERROR(IF(INDEX('Per Invoice'!$A$2:$A$201,MATCH($A11,'Per Invoice'!$B$2:$B$201,0))=0,"",INDEX('Per Invoice'!$A$2:$A$201,MATCH($A11,'Per Invoice'!$B$2:$B$201,0))),"")) | G11: =IF($A11="","",F11*T11/100) | R11: =IF($A11="","",IF($X11=1,Settings!$C$6,Settings!$C$7)*1) | S11: =IF($A11="","",R11*L11) | T11: =IF($A11="","",L11-S11) | U11: =IF($A11="","",T11-G11) | V11: =IF($A11="","",IF(COUNTIF($A$2:$A11,$A11)=1,1,0)) | W11: =IF($V11=1,SUMPRODUCT(--($Y$2:$Y$501<$Y11))+1,"") | X11: =IF($A11="","",IF(OR($Q11=TRUE(),$Q11="TRUE"),1,0)) | Y11: =IF($V11=1,IFERROR(VALUE(MID($A11,2,20)),1000000000)+ROW()/100000,"")
B12: =IF($A12="","",IFERROR(IF(INDEX('Per Invoice'!$A$2:$A$201,MATCH($A12,'Per Invoice'!$B$2:$B$201,0))=0,"",INDEX('Per Invoice'!$A$2:$A$201,MATCH($A12,'Per Invoice'!$B$2:$B$201,0))),"")) | G12: =IF($A12="","",F12*T12/100) | R12: =IF($A12="","",IF($X12=1,Settings!$C$6,Settings!$C$7)*1) | S12: =IF($A12="","",R12*L12) | T12: =IF($A12="","",L12-S12) | U12: =IF($A12="","",T12-G12) | V12: =IF($A12="","",IF(COUNTIF($A$2:$A12,$A12)=1,1,0)) | W12: =IF($V12=1,SUMPRODUCT(--($Y$2:$Y$501<$Y12))+1,"") | X12: =IF($A12="","",IF(OR($Q12=TRUE(),$Q12="TRUE"),1,0)) | Y12: =IF($V12=1,IFERROR(VALUE(MID($A12,2,20)),1000000000)+ROW()/100000,"")
B13: =IF($A13="","",IFERROR(IF(INDEX('Per Invoice'!$A$2:$A$201,MATCH($A13,'Per Invoice'!$B$2:$B$201,0))=0,"",INDEX('Per Invoice'!$A$2:$A$201,MATCH($A13,'Per Invoice'!$B$2:$B$201,0))),"")) | G13: =IF($A13="","",F13*T13/100) | R13: =IF($A13="","",IF($X13=1,Settings!$C$6,Settings!$C$7)*1) | S13: =IF($A13="","",R13*L13) | T13: =IF($A13="","",L13-S13) | U13: =IF($A13="","",T13-G13) | V13: =IF($A13="","",IF(COUNTIF($A$2:$A13,$A13)=1,1,0)) | W13: =IF($V13=1,SUMPRODUCT(--($Y$2:$Y$501<$Y13))+1,"") | X13: =IF($A13="","",IF(OR($Q13=TRUE(),$Q13="TRUE"),1,0)) | Y13: =IF($V13=1,IFERROR(VALUE(MID($A13,2,20)),1000000000)+ROW()/100000,"")
... B501: =IF($A501="","",IFERROR(IF(INDEX('Per Invoice'!$A$2:$A$201,MATCH($A501,'Per Invoice'!$B$2:$B$201,0))=0,"",INDEX('Per Invoice'!$A$2:$A$201,MATCH($A501,'Per Invoice'!$B$2:$B$201,0))),"")) | G501: =IF($A501="","",F501*T501/100) | R501: =IF($A501="","",IF($X501=1,Settings!$C$6,Settings!$C$7)*1) | S501: =IF($A501="","",R501*L501) | T501: =IF($A501="","",L501-S501) | U501: =IF($A501="","",T501-G501) | V501: =IF($A501="","",IF(COUNTIF($A$2:$A501,$A501)=1,1,0)) | W501: =IF($V501=1,SUMPRODUCT(--($Y$2:$Y$501<$Y501))+1,"") | X501: =IF($A501="","",IF(OR($Q501=TRUE(),$Q501="TRUE"),1,0)) | Y501: =IF($V501=1,IFERROR(VALUE(MID($A501,2,20)),1000000000)+ROW()/100000,"")

Sheet Per Invoice
A1: Invoice | B1: Pos Reference | C1: Name | D1: Card Number | E1: Co Payment % | F1: Co val | G1: Imp % | H1: Imp | I1: Imp Val | J1: Local % | K1: Local | L1: local val | M1: Total val | N1: Subtotal | O1: Grand Total | P1: Net | Q1: Src Row (helper)
B2: =IF($Q2="","",INDEX('Per Line'!$A$2:$A$501,$Q2)&"") | C2: =IF($Q2="","",INDEX('Per Line'!$D$2:$D$501,$Q2)&"") | D2: =IF($Q2="","",INDEX('Per Line'!$E$2:$E$501,$Q2)&"") | E2: =IF($Q2="","",INDEX('Per Line'!$F$2:$F$501,$Q2)) | F2: =IF($Q2="","",E2*N2/100) | G2: =IF($Q2="","",Settings!$C$7) | H2: =IF($Q2="","",SUMIFS('Per Line'!$L$2:$L$501,'Per Line'!$A$2:$A$501,$B2,'Per Line'!$X$2:$X$501,0)) | I2: =IF($Q2="","",H2*G2) | J2: =IF($Q2="","",Settings!$C$6) | K2: =IF($Q2="","",SUMIFS('Per Line'!$L$2:$L$501,'Per Line'!$A$2:$A$501,$B2,'Per Line'!$X$2:$X$501,1)) | L2: =IF($Q2="","",K2*J2) | M2: =IF($Q2="","",L2+I2) | N2: =IF($Q2="","",O2-M2) | O2: =IF($Q2="","",H2+K2) | P2: =IF($Q2="","",O2-M2-F2) | Q2: =IF(ROWS($Q$2:$Q2)<=MAX('Per Line'!$W$2:$W$501),MATCH(ROWS($Q$2:$Q2),'Per Line'!$W$2:$W$501,0),"")
B3: =IF($Q3="","",INDEX('Per Line'!$A$2:$A$501,$Q3)&"") | C3: =IF($Q3="","",INDEX('Per Line'!$D$2:$D$501,$Q3)&"") | D3: =IF($Q3="","",INDEX('Per Line'!$E$2:$E$501,$Q3)&"") | E3: =IF($Q3="","",INDEX('Per Line'!$F$2:$F$501,$Q3)) | F3: =IF($Q3="","",E3*N3/100) | G3: =IF($Q3="","",Settings!$C$7) | H3: =IF($Q3="","",SUMIFS('Per Line'!$L$2:$L$501,'Per Line'!$A$2:$A$501,$B3,'Per Line'!$X$2:$X$501,0)) | I3: =IF($Q3="","",H3*G3) | J3: =IF($Q3="","",Settings!$C$6) | K3: =IF($Q3="","",SUMIFS('Per Line'!$L$2:$L$501,'Per Line'!$A$2:$A$501,$B3,'Per Line'!$X$2:$X$501,1)) | L3: =IF($Q3="","",K3*J3) | M3: =IF($Q3="","",L3+I3) | N3: =IF($Q3="","",O3-M3) | O3: =IF($Q3="","",H3+K3) | P3: =IF($Q3="","",O3-M3-F3) | Q3: =IF(ROWS($Q$2:$Q3)<=MAX('Per Line'!$W$2:$W$501),MATCH(ROWS($Q$2:$Q3),'Per Line'!$W$2:$W$501,0),"")
B4: =IF($Q4="","",INDEX('Per Line'!$A$2:$A$501,$Q4)&"") | C4: =IF($Q4="","",INDEX('Per Line'!$D$2:$D$501,$Q4)&"") | D4: =IF($Q4="","",INDEX('Per Line'!$E$2:$E$501,$Q4)&"") | E4: =IF($Q4="","",INDEX('Per Line'!$F$2:$F$501,$Q4)) | F4: =IF($Q4="","",E4*N4/100) | G4: =IF($Q4="","",Settings!$C$7) | H4: =IF($Q4="","",SUMIFS('Per Line'!$L$2:$L$501,'Per Line'!$A$2:$A$501,$B4,'Per Line'!$X$2:$X$501,0)) | I4: =IF($Q4="","",H4*G4) | J4: =IF($Q4="","",Settings!$C$6) | K4: =IF($Q4="","",SUMIFS('Per Line'!$L$2:$L$501,'Per Line'!$A$2:$A$501,$B4,'Per Line'!$X$2:$X$501,1)) | L4: =IF($Q4="","",K4*J4) | M4: =IF($Q4="","",L4+I4) | N4: =IF($Q4="","",O4-M4) | O4: =IF($Q4="","",H4+K4) | P4: =IF($Q4="","",O4-M4-F4) | Q4: =IF(ROWS($Q$2:$Q4)<=MAX('Per Line'!$W$2:$W$501),MATCH(ROWS($Q$2:$Q4),'Per Line'!$W$2:$W$501,0),"")
B5: =IF($Q5="","",INDEX('Per Line'!$A$2:$A$501,$Q5)&"") | C5: =IF($Q5="","",INDEX('Per Line'!$D$2:$D$501,$Q5)&"") | D5: =IF($Q5="","",INDEX('Per Line'!$E$2:$E$501,$Q5)&"") | E5: =IF($Q5="","",INDEX('Per Line'!$F$2:$F$501,$Q5)) | F5: =IF($Q5="","",E5*N5/100) | G5: =IF($Q5="","",Settings!$C$7) | H5: =IF($Q5="","",SUMIFS('Per Line'!$L$2:$L$501,'Per Line'!$A$2:$A$501,$B5,'Per Line'!$X$2:$X$501,0)) | I5: =IF($Q5="","",H5*G5) | J5: =IF($Q5="","",Settings!$C$6) | K5: =IF($Q5="","",SUMIFS('Per Line'!$L$2:$L$501,'Per Line'!$A$2:$A$501,$B5,'Per Line'!$X$2:$X$501,1)) | L5: =IF($Q5="","",K5*J5) | M5: =IF($Q5="","",L5+I5) | N5: =IF($Q5="","",O5-M5) | O5: =IF($Q5="","",H5+K5) | P5: =IF($Q5="","",O5-M5-F5) | Q5: =IF(ROWS($Q$2:$Q5)<=MAX('Per Line'!$W$2:$W$501),MATCH(ROWS($Q$2:$Q5),'Per Line'!$W$2:$W$501,0),"")
B6: =IF($Q6="","",INDEX('Per Line'!$A$2:$A$501,$Q6)&"") | C6: =IF($Q6="","",INDEX('Per Line'!$D$2:$D$501,$Q6)&"") | D6: =IF($Q6="","",INDEX('Per Line'!$E$2:$E$501,$Q6)&"") | E6: =IF($Q6="","",INDEX('Per Line'!$F$2:$F$501,$Q6)) | F6: =IF($Q6="","",E6*N6/100) | G6: =IF($Q6="","",Settings!$C$7) | H6: =IF($Q6="","",SUMIFS('Per Line'!$L$2:$L$501,'Per Line'!$A$2:$A$501,$B6,'Per Line'!$X$2:$X$501,0)) | I6: =IF($Q6="","",H6*G6) | J6: =IF($Q6="","",Settings!$C$6) | K6: =IF($Q6="","",SUMIFS('Per Line'!$L$2:$L$501,'Per Line'!$A$2:$A$501,$B6,'Per Line'!$X$2:$X$501,1)) | L6: =IF($Q6="","",K6*J6) | M6: =IF($Q6="","",L6+I6) | N6: =IF($Q6="","",O6-M6) | O6: =IF($Q6="","",H6+K6) | P6: =IF($Q6="","",O6-M6-F6) | Q6: =IF(ROWS($Q$2:$Q6)<=MAX('Per Line'!$W$2:$W$501),MATCH(ROWS($Q$2:$Q6),'Per Line'!$W$2:$W$501,0),"")
B7: =IF($Q7="","",INDEX('Per Line'!$A$2:$A$501,$Q7)&"") | C7: =IF($Q7="","",INDEX('Per Line'!$D$2:$D$501,$Q7)&"") | D7: =IF($Q7="","",INDEX('Per Line'!$E$2:$E$501,$Q7)&"") | E7: =IF($Q7="","",INDEX('Per Line'!$F$2:$F$501,$Q7)) | F7: =IF($Q7="","",E7*N7/100) | G7: =IF($Q7="","",Settings!$C$7) | H7: =IF($Q7="","",SUMIFS('Per Line'!$L$2:$L$501,'Per Line'!$A$2:$A$501,$B7,'Per Line'!$X$2:$X$501,0)) | I7: =IF($Q7="","",H7*G7) | J7: =IF($Q7="","",Settings!$C$6) | K7: =IF($Q7="","",SUMIFS('Per Line'!$L$2:$L$501,'Per Line'!$A$2:$A$501,$B7,'Per Line'!$X$2:$X$501,1)) | L7: =IF($Q7="","",K7*J7) | M7: =IF($Q7="","",L7+I7) | N7: =IF($Q7="","",O7-M7) | O7: =IF($Q7="","",H7+K7) | P7: =IF($Q7="","",O7-M7-F7) | Q7: =IF(ROWS($Q$2:$Q7)<=MAX('Per Line'!$W$2:$W$501),MATCH(ROWS($Q$2:$Q7),'Per Line'!$W$2:$W$501,0),"")
B8: =IF($Q8="","",INDEX('Per Line'!$A$2:$A$501,$Q8)&"") | C8: =IF($Q8="","",INDEX('Per Line'!$D$2:$D$501,$Q8)&"") | D8: =IF($Q8="","",INDEX('Per Line'!$E$2:$E$501,$Q8)&"") | E8: =IF($Q8="","",INDEX('Per Line'!$F$2:$F$501,$Q8)) | F8: =IF($Q8="","",E8*N8/100) | G8: =IF($Q8="","",Settings!$C$7) | H8: =IF($Q8="","",SUMIFS('Per Line'!$L$2:$L$501,'Per Line'!$A$2:$A$501,$B8,'Per Line'!$X$2:$X$501,0)) | I8: =IF($Q8="","",H8*G8) | J8: =IF($Q8="","",Settings!$C$6) | K8: =IF($Q8="","",SUMIFS('Per Line'!$L$2:$L$501,'Per Line'!$A$2:$A$501,$B8,'Per Line'!$X$2:$X$501,1)) | L8: =IF($Q8="","",K8*J8) | M8: =IF($Q8="","",L8+I8) | N8: =IF($Q8="","",O8-M8) | O8: =IF($Q8="","",H8+K8) | P8: =IF($Q8="","",O8-M8-F8) | Q8: =IF(ROWS($Q$2:$Q8)<=MAX('Per Line'!$W$2:$W$501),MATCH(ROWS($Q$2:$Q8),'Per Line'!$W$2:$W$501,0),"")
B9: =IF($Q9="","",INDEX('Per Line'!$A$2:$A$501,$Q9)&"") | C9: =IF($Q9="","",INDEX('Per Line'!$D$2:$D$501,$Q9)&"") | D9: =IF($Q9="","",INDEX('Per Line'!$E$2:$E$501,$Q9)&"") | E9: =IF($Q9="","",INDEX('Per Line'!$F$2:$F$501,$Q9)) | F9: =IF($Q9="","",E9*N9/100) | G9: =IF($Q9="","",Settings!$C$7) | H9: =IF($Q9="","",SUMIFS('Per Line'!$L$2:$L$501,'Per Line'!$A$2:$A$501,$B9,'Per Line'!$X$2:$X$501,0)) | I9: =IF($Q9="","",H9*G9) | J9: =IF($Q9="","",Settings!$C$6) | K9: =IF($Q9="","",SUMIFS('Per Line'!$L$2:$L$501,'Per Line'!$A$2:$A$501,$B9,'Per Line'!$X$2:$X$501,1)) | L9: =IF($Q9="","",K9*J9) | M9: =IF($Q9="","",L9+I9) | N9: =IF($Q9="","",O9-M9) | O9: =IF($Q9="","",H9+K9) | P9: =IF($Q9="","",O9-M9-F9) | Q9: =IF(ROWS($Q$2:$Q9)<=MAX('Per Line'!$W$2:$W$501),MATCH(ROWS($Q$2:$Q9),'Per Line'!$W$2:$W$501,0),"")
B10: =IF($Q10="","",INDEX('Per Line'!$A$2:$A$501,$Q10)&"") | C10: =IF($Q10="","",INDEX('Per Line'!$D$2:$D$501,$Q10)&"") | D10: =IF($Q10="","",INDEX('Per Line'!$E$2:$E$501,$Q10)&"") | E10: =IF($Q10="","",INDEX('Per Line'!$F$2:$F$501,$Q10)) | F10: =IF($Q10="","",E10*N10/100) | G10: =IF($Q10="","",Settings!$C$7) | H10: =IF($Q10="","",SUMIFS('Per Line'!$L$2:$L$501,'Per Line'!$A$2:$A$501,$B10,'Per Line'!$X$2:$X$501,0)) | I10: =IF($Q10="","",H10*G10) | J10: =IF($Q10="","",Settings!$C$6) | K10: =IF($Q10="","",SUMIFS('Per Line'!$L$2:$L$501,'Per Line'!$A$2:$A$501,$B10,'Per Line'!$X$2:$X$501,1)) | L10: =IF($Q10="","",K10*J10) | M10: =IF($Q10="","",L10+I10) | N10: =IF($Q10="","",O10-M10) | O10: =IF($Q10="","",H10+K10) | P10: =IF($Q10="","",O10-M10-F10) | Q10: =IF(ROWS($Q$2:$Q10)<=MAX('Per Line'!$W$2:$W$501),MATCH(ROWS($Q$2:$Q10),'Per Line'!$W$2:$W$501,0),"")
B11: =IF($Q11="","",INDEX('Per Line'!$A$2:$A$501,$Q11)&"") | C11: =IF($Q11="","",INDEX('Per Line'!$D$2:$D$501,$Q11)&"") | D11: =IF($Q11="","",INDEX('Per Line'!$E$2:$E$501,$Q11)&"") | E11: =IF($Q11="","",INDEX('Per Line'!$F$2:$F$501,$Q11)) | F11: =IF($Q11="","",E11*N11/100) | G11: =IF($Q11="","",Settings!$C$7) | H11: =IF($Q11="","",SUMIFS('Per Line'!$L$2:$L$501,'Per Line'!$A$2:$A$501,$B11,'Per Line'!$X$2:$X$501,0)) | I11: =IF($Q11="","",H11*G11) | J11: =IF($Q11="","",Settings!$C$6) | K11: =IF($Q11="","",SUMIFS('Per Line'!$L$2:$L$501,'Per Line'!$A$2:$A$501,$B11,'Per Line'!$X$2:$X$501,1)) | L11: =IF($Q11="","",K11*J11) | M11: =IF($Q11="","",L11+I11) | N11: =IF($Q11="","",O11-M11) | O11: =IF($Q11="","",H11+K11) | P11: =IF($Q11="","",O11-M11-F11) | Q11: =IF(ROWS($Q$2:$Q11)<=MAX('Per Line'!$W$2:$W$501),MATCH(ROWS($Q$2:$Q11),'Per Line'!$W$2:$W$501,0),"")
B12: =IF($Q12="","",INDEX('Per Line'!$A$2:$A$501,$Q12)&"") | C12: =IF($Q12="","",INDEX('Per Line'!$D$2:$D$501,$Q12)&"") | D12: =IF($Q12="","",INDEX('Per Line'!$E$2:$E$501,$Q12)&"") | E12: =IF($Q12="","",INDEX('Per Line'!$F$2:$F$501,$Q12)) | F12: =IF($Q12="","",E12*N12/100) | G12: =IF($Q12="","",Settings!$C$7) | H12: =IF($Q12="","",SUMIFS('Per Line'!$L$2:$L$501,'Per Line'!$A$2:$A$501,$B12,'Per Line'!$X$2:$X$501,0)) | I12: =IF($Q12="","",H12*G12) | J12: =IF($Q12="","",Settings!$C$6) | K12: =IF($Q12="","",SUMIFS('Per Line'!$L$2:$L$501,'Per Line'!$A$2:$A$501,$B12,'Per Line'!$X$2:$X$501,1)) | L12: =IF($Q12="","",K12*J12) | M12: =IF($Q12="","",L12+I12) | N12: =IF($Q12="","",O12-M12) | O12: =IF($Q12="","",H12+K12) | P12: =IF($Q12="","",O12-M12-F12) | Q12: =IF(ROWS($Q$2:$Q12)<=MAX('Per Line'!$W$2:$W$501),MATCH(ROWS($Q$2:$Q12),'Per Line'!$W$2:$W$501,0),"")
B13: =IF($Q13="","",INDEX('Per Line'!$A$2:$A$501,$Q13)&"") | C13: =IF($Q13="","",INDEX('Per Line'!$D$2:$D$501,$Q13)&"") | D13: =IF($Q13="","",INDEX('Per Line'!$E$2:$E$501,$Q13)&"") | E13: =IF($Q13="","",INDEX('Per Line'!$F$2:$F$501,$Q13)) | F13: =IF($Q13="","",E13*N13/100) | G13: =IF($Q13="","",Settings!$C$7) | H13: =IF($Q13="","",SUMIFS('Per Line'!$L$2:$L$501,'Per Line'!$A$2:$A$501,$B13,'Per Line'!$X$2:$X$501,0)) | I13: =IF($Q13="","",H13*G13) | J13: =IF($Q13="","",Settings!$C$6) | K13: =IF($Q13="","",SUMIFS('Per Line'!$L$2:$L$501,'Per Line'!$A$2:$A$501,$B13,'Per Line'!$X$2:$X$501,1)) | L13: =IF($Q13="","",K13*J13) | M13: =IF($Q13="","",L13+I13) | N13: =IF($Q13="","",O13-M13) | O13: =IF($Q13="","",H13+K13) | P13: =IF($Q13="","",O13-M13-F13) | Q13: =IF(ROWS($Q$2:$Q13)<=MAX('Per Line'!$W$2:$W$501),MATCH(ROWS($Q$2:$Q13),'Per Line'!$W$2:$W$501,0),"")
... B201: =IF($Q201="","",INDEX('Per Line'!$A$2:$A$501,$Q201)&"") | C201: =IF($Q201="","",INDEX('Per Line'!$D$2:$D$501,$Q201)&"") | D201: =IF($Q201="","",INDEX('Per Line'!$E$2:$E$501,$Q201)&"") | E201: =IF($Q201="","",INDEX('Per Line'!$F$2:$F$501,$Q201)) | F201: =IF($Q201="","",E201*N201/100) | G201: =IF($Q201="","",Settings!$C$7) | H201: =IF($Q201="","",SUMIFS('Per Line'!$L$2:$L$501,'Per Line'!$A$2:$A$501,$B201,'Per Line'!$X$2:$X$501,0)) | I201: =IF($Q201="","",H201*G201) | J201: =IF($Q201="","",Settings!$C$6) | K201: =IF($Q201="","",SUMIFS('Per Line'!$L$2:$L$501,'Per Line'!$A$2:$A$501,$B201,'Per Line'!$X$2:$X$501,1)) | L201: =IF($Q201="","",K201*J201) | M201: =IF($Q201="","",L201+I201) | N201: =IF($Q201="","",O201-M201) | O201: =IF($Q201="","",H201+K201) | P201: =IF($Q201="","",O201-M201-F201) | Q201: =IF(ROWS($Q$2:$Q201)<=MAX('Per Line'!$W$2:$W$501),MATCH(ROWS($Q$2:$Q201),'Per Line'!$W$2:$W$501,0),"")
