Workbook

Sheet How To Use
A1: Claims Template - SMART MEDICAL SERVICES (Chronic)
A3: Monthly steps
A4: 1. Open the 'Per Line' tab. Delete the old data in the BLUE columns only (row 2 down). Never delete the green or grey columns.
A5: 2. Paste the new month's data as VALUES starting at A2, into the blue columns: A-P, R-X, AB-AD, AF-AM (same order as the system export).
A6: 3. Green columns (Q, Y, Z, AA, AE) and the grey helper columns (AN-AR) calculate automatically - do not paste over them.
A7: 4. 'Per Invoice' fills itself from 'Per Line' (one row per Order #, split into IMP / Local). No pivot table, no refresh.
A8: 5. The ONLY manual column in 'Per Invoice' is column A 'Invoice' (blue): type the invoice number yourself. Everything else is formula.
A9: 6. Open 'Settings' and check STATUS says OK (Per Line totals = Per Invoice totals).
A11: Colour legend
A12: Blue header = typed/pasted by you (raw data, and 'Invoice' in Per Invoice). Green header = formula (do not paste over). Grey header = helper formula (do not touch). Yellow cell (Settings) = editable rate.
A14: Calculation rules (taken from the September 2026 sheet)
A15: Co val = Order Co Payment x Total / 100. Discount = Total x Rebates / 100. Subtotal = Total - Discount. Net = Subtotal - Co val. (Total = 'Product Total')
... A21: Max Limit rule (as in the old sheet): if an invoice's Grand Total is above its Max Limit, Co val = Co Payment x Max Limit / 100 + (Grand Total - Max Limit). Per Line keeps the plain Co val, so 'Settings' shows the difference as 'Max Limit adjustment'.

Sheet Settings
B1: Company settings & checks
B3: Insurance Company | C3: SMART MEDICAL SERVICES | D3: Informational only
B4: Corporate | C4: SHOURA; ITDA Nasr City; Hesni; ITDA-New Capital; ITDA Fostat; ITDA IND | D4: Informational only
B5: Sheet type | C5: Chronic | D5: Informational only
B6: Local products rebate % | C6: 0.13 | D6: Source: Sep sheet (Rebates = 13 on Local lines).
B7: Imported (IMP) products rebate % | C7: 0.03 | D7: Source: Sep sheet (Rebates = 3 on non-local lines; 0 on Special Rebates = Yes).
B9: Month totals / reconciliation
B10: Lines loaded | C10: =COUNTA('Per Line'!$E$2:$E$3001)
B11: Invoices (unique Order #) | C11: =MAX('Per Line'!$AO$2:$AO$3001)
B12: Invoices shown in Per Invoice | C12: =SUMPRODUCT(--('Per Invoice'!$B$2:$B$1001<>""))
B13: Grand Total - Per Line (Product Total) | C13: =SUM('Per Line'!$AB$2:$AB$3001)
B14: Grand Total - Per Invoice | C14: =SUM('Per Invoice'!$AB$2:$AB$1001)
B15: Discount - Per Line | C15: =SUM('Per Line'!$Y$2:$Y$3001)
B16: Discount - Per Invoice | C16: =SUM('Per Invoice'!$Z$2:$Z$1001)
B17: Co val - Per Line | C17: =SUM('Per Line'!$Q$2:$Q$3001)
B18: Co val - Per Invoice | C18: =SUM('Per Invoice'!$P$2:$P$1001)
B19: Net - Per Line | C19: =SUM('Per Line'!$AA$2:$AA$3001)
B20: Net - Per Invoice | C20: =SUM('Per Invoice'!$AC$2:$AC$1001)
B21: Max Limit adjustment (Co val, Per Invoice only) | C21: =SUM('Per Invoice'!$AE$2:$AE$1001) | D21: Invoices whose Grand Total is above the Max Limit: Co val = Co% x Max Limit / 100 + (Grand Total - Max Limit). This difference exists only in Per Invoice, as in the old sheet.
B23: STATUS | C23: =IF(C10=0,"No data loaded",IF(COUNTA('Per Line'!$E:$E)-1>3000,"TOO MANY LINES - extend template",IF(C11>1000,"TOO MANY INVOICES - extend template",IF(AND(ROUND(C13-C14,2)=0,ROUND(C15-C16,2)=0,ROUND(C17+C21-C18,2)=0,ROUND(C19-C21-C20,2)=0,C11=C12),"OK","CHECK - Per Line and Per Invoice do not match")))) | D23: Must say OK after you paste the month data.

Sheet Per Line
A1: Cycle | B1: Ticket # | C1: Stage | D1: Approval Ref | E1: Order # | F1: Channel | G1: Create At | H1: Insurance Company | I1: Country Portal ID | J1: Corporate | K1: Card | L1: Name | M1: Status | N1: Local Rebates | O1: Imported Rebates | P1: Order Co Payment | Q1: Co val | R1: By Patient | S1: heisenberg id | T1: Product Name | U1: Local | V1: Unit | W1: Quantity | X1: Unit Price | Y1: Discount | Z1: Subtotal | AA1: Net | AB1: Product Total | AC1: ERX ID | AD1: Special Rebates? | AE1: Rebates | AF1: Approval Type | AG1: Max Limit | AH1: Exceeding Limit | AI1: Amount collected from customer | AJ1: By Patient (Delivered) | AK1: Dispense Number | AL1: Dispense Date | AM1: Has OTP? | AN1: Order 1st Row (helper) | AO1: Invoice # (helper) | AP1: Is Local (helper) | AQ1: Is Special (helper) | AR1: Sort Key (helper)
Q2: =IF($E2="","",P2*AB2/100) | Y2: =IF($E2="","",AB2*AE2/100) | Z2: =IF($E2="","",AB2-Y2) | AA2: =IF($E2="","",Z2-Q2) | AE2: =IF($E2="","",IF($AQ2=1,0,IF($AP2=1,Settings!$C$6,Settings!$C$7))*100) | AN2: =IF($E2="","",IF(COUNTIF($E$2:$E2,$E2)=1,1,0)) | AO2: =IF($AN2=1,SUMPRODUCT(--($AR$2:$AR$3001<$AR2))+1,"") | AP2: =IF($E2="","",IF(OR($U2=TRUE(),$U2="TRUE"),1,0)) | AQ2: =IF($E2="","",IF($AD2="Yes",1,0)) | AR2: =IF($AN2=1,IFERROR(VALUE(MID($E2,2,20)),1000000000)+ROW()/100000,"")
Q3: =IF($E3="","",P3*AB3/100) | Y3: =IF($E3="","",AB3*AE3/100) | Z3: =IF($E3="","",AB3-Y3) | AA3: =IF($E3="","",Z3-Q3) | AE3: =IF($E3="","",IF($AQ3=1,0,IF($AP3=1,Settings!$C$6,Settings!$C$7))*100) | AN3: =IF($E3="","",IF(COUNTIF($E$2:$E3,$E3)=1,1,0)) | AO3: =IF($AN3=1,SUMPRODUCT(--($AR$2:$AR$3001<$AR3))+1,"") | AP3: =IF($E3="","",IF(OR($U3=TRUE(),$U3="TRUE"),1,0)) | AQ3: =IF($E3="","",IF($AD3="Yes",1,0)) | AR3: =IF($AN3=1,IFERROR(VALUE(MID($E3,2,20)),1000000000)+ROW()/100000,"")
Q4: =IF($E4="","",P4*AB4/100) | Y4: =IF($E4="","",AB4*AE4/100) | Z4: =IF($E4="","",AB4-Y4) | AA4: =IF($E4="","",Z4-Q4) | AE4: =IF($E4="","",IF($AQ4=1,0,IF($AP4=1,Settings!$C$6,Settings!$C$7))*100) | AN4: =IF($E4="","",IF(COUNTIF($E$2:$E4,$E4)=1,1,0)) | AO4: =IF($AN4=1,SUMPRODUCT(--($AR$2:$AR$3001<$AR4))+1,"") | AP4: =IF($E4="","",IF(OR($U4=TRUE(),$U4="TRUE"),1,0)) | AQ4: =IF($E4="","",IF($AD4="Yes",1,0)) | AR4: =IF($AN4=1,IFERROR(VALUE(MID($E4,2,20)),1000000000)+ROW()/100000,"")
Q5: =IF($E5="","",P5*AB5/100) | Y5: =IF($E5="","",AB5*AE5/100) | Z5: =IF($E5="","",AB5-Y5) | AA5: =IF($E5="","",Z5-Q5) | AE5: =IF($E5="","",IF($AQ5=1,0,IF($AP5=1,Settings!$C$6,Settings!$C$7))*100) | AN5: =IF($E5="","",IF(COUNTIF($E$2:$E5,$E5)=1,1,0)) | AO5: =IF($AN5=1,SUMPRODUCT(--($AR$2:$AR$3001<$AR5))+1,"") | AP5: =IF($E5="","",IF(OR($U5=TRUE(),$U5="TRUE"),1,0)) | AQ5: =IF($E5="","",IF($AD5="Yes",1,0)) | AR5: =IF($AN5=1,IFERROR(VALUE(MID($E5,2,20)),1000000000)+ROW()/100000,"")
Q6: =IF($E6="","",P6*AB6/100) | Y6: =IF($E6="","",AB6*AE6/100) | Z6: =IF($E6="","",AB6-Y6) | AA6: =IF($E6="","",Z6-Q6) | AE6: =IF($E6="","",IF($AQ6=1,0,IF($AP6=1,Settings!$C$6,Settings!$C$7))*100) | AN6: =IF($E6="","",IF(COUNTIF($E$2:$E6,$E6)=1,1,0)) | AO6: =IF($AN6=1,SUMPRODUCT(--($AR$2:$AR$3001<$AR6))+1,"") | AP6: =IF($E6="","",IF(OR($U6=TRUE(),$U6="TRUE"),1,0)) | AQ6: =IF($E6="","",IF($AD6="Yes",1,0)) | AR6: =IF($AN6=1,IFERROR(VALUE(MID($E6,2,20)),1000000000)+ROW()/100000,"")
Q7: =IF($E7="","",P7*AB7/100) | Y7: =IF($E7="","",AB7*AE7/100) | Z7: =IF($E7="","",AB7-Y7) | AA7: =IF($E7="","",Z7-Q7) | AE7: =IF($E7="","",IF($AQ7=1,0,IF($AP7=1,Settings!$C$6,Settings!$C$7))*100) | AN7: =IF($E7="","",IF(COUNTIF($E$2:$E7,$E7)=1,1,0)) | AO7: =IF($AN7=1,SUMPRODUCT(--($AR$2:$AR$3001<$AR7))+1,"") | AP7: =IF($E7="","",IF(OR($U7=TRUE(),$U7="TRUE"),1,0)) | AQ7: =IF($E7="","",IF($AD7="Yes",1,0)) | AR7: =IF($AN7=1,IFERROR(VALUE(MID($E7,2,20)),1000000000)+ROW()/100000,"")
Q8: =IF($E8="","",P8*AB8/100) | Y8: =IF($E8="","",AB8*AE8/100) | Z8: =IF($E8="","",AB8-Y8) | AA8: =IF($E8="","",Z8-Q8) | AE8: =IF($E8="","",IF($AQ8=1,0,IF($AP8=1,Settings!$C$6,Settings!$C$7))*100) | AN8: =IF($E8="","",IF(COUNTIF($E$2:$E8,$E8)=1,1,0)) | AO8: =IF($AN8=1,SUMPRODUCT(--($AR$2:$AR$3001<$AR8))+1,"") | AP8: =IF($E8="","",IF(OR($U8=TRUE(),$U8="TRUE"),1,0)) | AQ8: =IF($E8="","",IF($AD8="Yes",1,0)) | AR8: =IF($AN8=1,IFERROR(VALUE(MID($E8,2,20)),1000000000)+ROW()/100000,"")
Q9: =IF($E9="","",P9*AB9/100) | Y9: =IF($E9="","",AB9*AE9/100) | Z9: =IF($E9="","",AB9-Y9) | AA9: =IF($E9="","",Z9-Q9) | AE9: =IF($E9="","",IF($AQ9=1,0,IF($AP9=1,Settings!$C$6,Settings!$C$7))*100) | AN9: =IF($E9="","",IF(COUNTIF($E$2:$E9,$E9)=1,1,0)) | AO9: =IF($AN9=1,SUMPRODUCT(--($AR$2:$AR$3001<$AR9))+1,"") | AP9: =IF($E9="","",IF(OR($U9=TRUE(),$U9="TRUE"),1,0)) | AQ9: =IF($E9="","",IF($AD9="Yes",1,0)) | AR9: =IF($AN9=1,IFERROR(VALUE(MID($E9,2,20)),1000000000)+ROW()/100000,"")
Q10: =IF($E10="","",P10*AB10/100) | Y10: =IF($E10="","",AB10*AE10/100) | Z10: =IF($E10="","",AB10-Y10) | AA10: =IF($E10="","",Z10-Q10) | AE10: =IF($E10="","",IF($AQ10=1,0,IF($AP10=1,Settings!$C$6,Settings!$C$7))*100) | AN10: =IF($E10="","",IF(COUNTIF($E$2:$E10,$E10)=1,1,0)) | AO10: =IF($AN10=1,SUMPRODUCT(--($AR$2:$AR$3001<$AR10))+1,"") | AP10: =IF($E10="","",IF(OR($U10=TRUE(),$U10="TRUE"),1,0)) | AQ10: =IF($E10="","",IF($AD10="Yes",1,0)) | AR10: =IF($AN10=1,IFERROR(VALUE(MID($E10,2,20)),1000000000)+ROW()/100000,"")
Q11: =IF($E11="","",P11*AB11/100) | Y11: =IF($E11="","",AB11*AE11/100) | Z11: =IF($E11="","",AB11-Y11) | AA11: =IF($E11="","",Z11-Q11) | AE11: =IF($E11="","",IF($AQ11=1,0,IF($AP11=1,Settings!$C$6,Settings!$C$7))*100) | AN11: =IF($E11="","",IF(COUNTIF($E$2:$E11,$E11)=1,1,0)) | AO11: =IF($AN11=1,SUMPRODUCT(--($AR$2:$AR$3001<$AR11))+1,"") | AP11: =IF($E11="","",IF(OR($U11=TRUE(),$U11="TRUE"),1,0)) | AQ11: =IF($E11="","",IF($AD11="Yes",1,0)) | AR11: =IF($AN11=1,IFERROR(VALUE(MID($E11,2,20)),1000000000)+ROW()/100000,"")
Q12: =IF($E12="","",P12*AB12/100) | Y12: =IF($E12="","",AB12*AE12/100) | Z12: =IF($E12="","",AB12-Y12) | AA12: =IF($E12="","",Z12-Q12) | AE12: =IF($E12="","",IF($AQ12=1,0,IF($AP12=1,Settings!$C$6,Settings!$C$7))*100) | AN12: =IF($E12="","",IF(COUNTIF($E$2:$E12,$E12)=1,1,0)) | AO12: =IF($AN12=1,SUMPRODUCT(--($AR$2:$AR$3001<$AR12))+1,"") | AP12: =IF($E12="","",IF(OR($U12=TRUE(),$U12="TRUE"),1,0)) | AQ12: =IF($E12="","",IF($AD12="Yes",1,0)) | AR12: =IF($AN12=1,IFERROR(VALUE(MID($E12,2,20)),1000000000)+ROW()/100000,"")
Q13: =IF($E13="","",P13*AB13/100) | Y13: =IF($E13="","",AB13*AE13/100) | Z13: =IF($E13="","",AB13-Y13) | AA13: =IF($E13="","",Z13-Q13) | AE13: =IF($E13="","",IF($AQ13=1,0,IF($AP13=1,Settings!$C$6,Settings!$C$7))*100) | AN13: =IF($E13="","",IF(COUNTIF($E$2:$E13,$E13)=1,1,0)) | AO13: =IF($AN13=1,SUMPRODUCT(--($AR$2:$AR$3001<$AR13))+1,"") | AP13: =IF($E13="","",IF(OR($U13=TRUE(),$U13="TRUE"),1,0)) | AQ13: =IF($E13="","",IF($AD13="Yes",1,0)) | AR13: =IF($AN13=1,IFERROR(VALUE(MID($E13,2,20)),1000000000)+ROW()/100000,"")
... Q3001: =IF($E3001="","",P3001*AB3001/100) | Y3001: =IF($E3001="","",AB3001*AE3001/100) | Z3001: =IF($E3001="","",AB3001-Y3001) | AA3001: =IF($E3001="","",Z3001-Q3001) | AE3001: =IF($E3001="","",IF($AQ3001=1,0,IF($AP3001=1,Settings!$C$6,Settings!$C$7))*100) | AN3001: =IF($E3001="","",IF(COUNTIF($E$2:$E3001,$E3001)=1,1,0)) | AO3001: =IF($AN3001=1,SUMPRODUCT(--($AR$2:$AR$3001<$AR3001))+1,"") | AP3001: =IF($E3001="","",IF(OR($U3001=TRUE(),$U3001="TRUE"),1,0)) | AQ3001: =IF($E3001="","",IF($AD3001="Yes",1,0)) | AR3001: =IF($AN3001=1,IFERROR(VALUE(MID($E3001,2,20)),1000000000)+ROW()/100000,"")

Sheet Per Invoice
A1: Invoice | B1: Order # | C1: Cycle | D1: Stage | E1: Ticket # | F1: Approval Ref | G1: Create At | H1: Corporate | I1: Insurance Company | J1: Channel | K1: Card | L1: Name | M1: Status | N1: ERX ID | O1: CO | P1: Co val | Q1: Max Limit | R1: Exceeding Limit | S1: Special | T1: IMP % | U1: IMP | V1: IMP VAL | W1: LOC % | X1: LOC | Y1: LOC VAL | Z1: TOTAL VAL | AA1: SUBTOTAL | AB1: Grand Total | AC1: NET | AD1: Src Row (helper) | AE1: Limit Adj (helper)
B2: =IF($AD2="","",INDEX('Per Line'!$E$2:$E$3001,$AD2)&"") | C2: =IF($AD2="","",INDEX('Per Line'!$A$2:$A$3001,$AD2)&"") | D2: =IF($AD2="","",INDEX('Per Line'!$C$2:$C$3001,$AD2)&"") | E2: =IF($AD2="","",INDEX('Per Line'!$B$2:$B$3001,$AD2)) | F2: =IF($AD2="","",INDEX('Per Line'!$D$2:$D$3001,$AD2)&"") | G2: =IF($AD2="","",INDEX('Per Line'!$G$2:$G$3001,$AD2)) | H2: =IF($AD2="","",INDEX('Per Line'!$J$2:$J$3001,$AD2)&"") | I2: =IF($AD2="","",INDEX('Per Line'!$H$2:$H$3001,$AD2)&"") | J2: =IF($AD2="","",INDEX('Per Line'!$F$2:$F$3001,$AD2)&"") | K2: =IF($AD2="","",INDEX('Per Line'!$K$2:$K$3001,$AD2)&"") | L2: =IF($AD2="","",INDEX('Per Line'!$L$2:$L$3001,$AD2)&"") | M2: =IF($AD2="","",INDEX('Per Line'!$M$2:$M$3001,$AD2)&"") | N2: =IF($AD2="","",INDEX('Per Line'!$AC$2:$AC$3001,$AD2)&"") | O2: =IF($AD2="","",INDEX('Per Line'!$P$2:$P$3001,$AD2)) | P2: =IF($AD2="","",IF(AND(ISNUMBER(Q2),Q2>0,AB2>Q2),O2*Q2/100+(AB2-Q2),O2*AB2/100)) | Q2: =IF($AD2="","",INDEX('Per Line'!$AG$2:$AG$3001,$AD2)) | R2: =IF($AD2="","",IF(AND(ISNUMBER(Q2),Q2>0),AB2>Q2,FALSE)) | S2: =IF($AD2="","",SUMIFS('Per Line'!$AB$2:$AB$3001,'Per Line'!$E$2:$E$3001,$B2,'Per Line'!$AQ$2:$AQ$3001,1)) | T2: =IF($AD2="","",Settings!$C$7) | U2: =IF($AD2="","",SUMIFS('Per Line'!$AB$2:$AB$3001,'Per Line'!$E$2:$E$3001,$B2,'Per Line'!$AP$2:$AP$3001,0,'Per Line'!$AQ$2:$AQ$3001,0)) | V2: =IF($AD2="","",U2*T2) | W2: =IF($AD2="","",Settings!$C$6) | X2: =IF($AD2="","",SUMIFS('Per Line'!$AB$2:$AB$3001,'Per Line'!$E$2:$E$3001,$B2,'Per Line'!$AP$2:$AP$3001,1,'Per Line'!$AQ$2:$AQ$3001,0)) | Y2: =IF($AD2="","",X2*W2) | Z2: =IF($AD2="","",Y2+V2) | AA2: =IF($AD2="","",AB2-Z2) | AB2: =IF($AD2="","",U2+X2+S2) | AC2: =IF($AD2="","",AB2-Z2-P2) | AD2: =IF(ROWS($AD$2:$AD2)<=MAX('Per Line'!$AO$2:$AO$3001),MATCH(ROWS($AD$2:$AD2),'Per Line'!$AO$2:$AO$3001,0),"") | AE2: =IF($AD2="","",P2-O2*AB2/100)
B3: =IF($AD3="","",INDEX('Per Line'!$E$2:$E$3001,$AD3)&"") | C3: =IF($AD3="","",INDEX('Per Line'!$A$2:$A$3001,$AD3)&"") | D3: =IF($AD3="","",INDEX('Per Line'!$C$2:$C$3001,$AD3)&"") | E3: =IF($AD3="","",INDEX('Per Line'!$B$2:$B$3001,$AD3)) | F3: =IF($AD3="","",INDEX('Per Line'!$D$2:$D$3001,$AD3)&"") | G3: =IF($AD3="","",INDEX('Per Line'!$G$2:$G$3001,$AD3)) | H3: =IF($AD3="","",INDEX('Per Line'!$J$2:$J$3001,$AD3)&"") | I3: =IF($AD3="","",INDEX('Per Line'!$H$2:$H$3001,$AD3)&"") | J3: =IF($AD3="","",INDEX('Per Line'!$F$2:$F$3001,$AD3)&"") | K3: =IF($AD3="","",INDEX('Per Line'!$K$2:$K$3001,$AD3)&"") | L3: =IF($AD3="","",INDEX('Per Line'!$L$2:$L$3001,$AD3)&"") | M3: =IF($AD3="","",INDEX('Per Line'!$M$2:$M$3001,$AD3)&"") | N3: =IF($AD3="","",INDEX('Per Line'!$AC$2:$AC$3001,$AD3)&"") | O3: =IF($AD3="","",INDEX('Per Line'!$P$2:$P$3001,$AD3)) | P3: =IF($AD3="","",IF(AND(ISNUMBER(Q3),Q3>0,AB3>Q3),O3*Q3/100+(AB3-Q3),O3*AB3/100)) | Q3: =IF($AD3="","",INDEX('Per Line'!$AG$2:$AG$3001,$AD3)) | R3: =IF($AD3="","",IF(AND(ISNUMBER(Q3),Q3>0),AB3>Q3,FALSE)) | S3: =IF($AD3="","",SUMIFS('Per Line'!$AB$2:$AB$3001,'Per Line'!$E$2:$E$3001,$B3,'Per Line'!$AQ$2:$AQ$3001,1)) | T3: =IF($AD3="","",Settings!$C$7) | U3: =IF($AD3="","",SUMIFS('Per Line'!$AB$2:$AB$3001,'Per Line'!$E$2:$E$3001,$B3,'Per Line'!$AP$2:$AP$3001,0,'Per Line'!$AQ$2:$AQ$3001,0)) | V3: =IF($AD3="","",U3*T3) | W3: =IF($AD3="","",Settings!$C$6) | X3: =IF($AD3="","",SUMIFS('Per Line'!$AB$2:$AB$3001,'Per Line'!$E$2:$E$3001,$B3,'Per Line'!$AP$2:$AP$3001,1,'Per Line'!$AQ$2:$AQ$3001,0)) | Y3: =IF($AD3="","",X3*W3) | Z3: =IF($AD3="","",Y3+V3) | AA3: =IF($AD3="","",AB3-Z3) | AB3: =IF($AD3="","",U3+X3+S3) | AC3: =IF($AD3="","",AB3-Z3-P3) | AD3: =IF(ROWS($AD$2:$AD3)<=MAX('Per Line'!$AO$2:$AO$3001),MATCH(ROWS($AD$2:$AD3),'Per Line'!$AO$2:$AO$3001,0),"") | AE3: =IF($AD3="","",P3-O3*AB3/100)
B4: =IF($AD4="","",INDEX('Per Line'!$E$2:$E$3001,$AD4)&"") | C4: =IF($AD4="","",INDEX('Per Line'!$A$2:$A$3001,$AD4)&"") | D4: =IF($AD4="","",INDEX('Per Line'!$C$2:$C$3001,$AD4)&"") | E4: =IF($AD4="","",INDEX('Per Line'!$B$2:$B$3001,$AD4)) | F4: =IF($AD4="","",INDEX('Per Line'!$D$2:$D$3001,$AD4)&"") | G4: =IF($AD4="","",INDEX('Per Line'!$G$2:$G$3001,$AD4)) | H4: =IF($AD4="","",INDEX('Per Line'!$J$2:$J$3001,$AD4)&"") | I4: =IF($AD4="","",INDEX('Per Line'!$H$2:$H$3001,$AD4)&"") | J4: =IF($AD4="","",INDEX('Per Line'!$F$2:$F$3001,$AD4)&"") | K4: =IF($AD4="","",INDEX('Per Line'!$K$2:$K$3001,$AD4)&"") | L4: =IF($AD4="","",INDEX('Per Line'!$L$2:$L$3001,$AD4)&"") | M4: =IF($AD4="","",INDEX('Per Line'!$M$2:$M$3001,$AD4)&"") | N4: =IF($AD4="","",INDEX('Per Line'!$AC$2:$AC$3001,$AD4)&"") | O4: =IF($AD4="","",INDEX('Per Line'!$P$2:$P$3001,$AD4)) | P4: =IF($AD4="","",IF(AND(ISNUMBER(Q4),Q4>0,AB4>Q4),O4*Q4/100+(AB4-Q4),O4*AB4/100)) | Q4: =IF($AD4="","",INDEX('Per Line'!$AG$2:$AG$3001,$AD4)) | R4: =IF($AD4="","",IF(AND(ISNUMBER(Q4),Q4>0),AB4>Q4,FALSE)) | S4: =IF($AD4="","",SUMIFS('Per Line'!$AB$2:$AB$3001,'Per Line'!$E$2:$E$3001,$B4,'Per Line'!$AQ$2:$AQ$3001,1)) | T4: =IF($AD4="","",Settings!$C$7) | U4: =IF($AD4="","",SUMIFS('Per Line'!$AB$2:$AB$3001,'Per Line'!$E$2:$E$3001,$B4,'Per Line'!$AP$2:$AP$3001,0,'Per Line'!$AQ$2:$AQ$3001,0)) | V4: =IF($AD4="","",U4*T4) | W4: =IF($AD4="","",Settings!$C$6) | X4: =IF($AD4="","",SUMIFS('Per Line'!$AB$2:$AB$3001,'Per Line'!$E$2:$E$3001,$B4,'Per Line'!$AP$2:$AP$3001,1,'Per Line'!$AQ$2:$AQ$3001,0)) | Y4: =IF($AD4="","",X4*W4) | Z4: =IF($AD4="","",Y4+V4) | AA4: =IF($AD4="","",AB4-Z4) | AB4: =IF($AD4="","",U4+X4+S4) | AC4: =IF($AD4="","",AB4-Z4-P4) | AD4: =IF(ROWS($AD$2:$AD4)<=MAX('Per Line'!$AO$2:$AO$3001),MATCH(ROWS($AD$2:$AD4),'Per Line'!$AO$2:$AO$3001,0),"") | AE4: =IF($AD4="","",P4-O4*AB4/100)
B5: =IF($AD5="","",INDEX('Per Line'!$E$2:$E$3001,$AD5)&"") | C5: =IF($AD5="","",INDEX('Per Line'!$A$2:$A$3001,$AD5)&"") | D5: =IF($AD5="","",INDEX('Per Line'!$C$2:$C$3001,$AD5)&"") | E5: =IF($AD5="","",INDEX('Per Line'!$B$2:$B$3001,$AD5)) | F5: =IF($AD5="","",INDEX('Per Line'!$D$2:$D$3001,$AD5)&"") | G5: =IF($AD5="","",INDEX('Per Line'!$G$2:$G$3001,$AD5)) | H5: =IF($AD5="","",INDEX('Per Line'!$J$2:$J$3001,$AD5)&"") | I5: =IF($AD5="","",INDEX('Per Line'!$H$2:$H$3001,$AD5)&"") | J5: =IF($AD5="","",INDEX('Per Line'!$F$2:$F$3001,$AD5)&"") | K5: =IF($AD5="","",INDEX('Per Line'!$K$2:$K$3001,$AD5)&"") | L5: =IF($AD5="","",INDEX('Per Line'!$L$2:$L$3001,$AD5)&"") | M5: =IF($AD5="","",INDEX('Per Line'!$M$2:$M$3001,$AD5)&"") | N5: =IF($AD5="","",INDEX('Per Line'!$AC$2:$AC$3001,$AD5)&"") | O5: =IF($AD5="","",INDEX('Per Line'!$P$2:$P$3001,$AD5)) | P5: =IF($AD5="","",IF(AND(ISNUMBER(Q5),Q5>0,AB5>Q5),O5*Q5/100+(AB5-Q5),O5*AB5/100)) | Q5: =IF($AD5="","",INDEX('Per Line'!$AG$2:$AG$3001,$AD5)) | R5: =IF($AD5="","",IF(AND(ISNUMBER(Q5),Q5>0),AB5>Q5,FALSE)) | S5: =IF($AD5="","",SUMIFS('Per Line'!$AB$2:$AB$3001,'Per Line'!$E$2:$E$3001,$B5,'Per Line'!$AQ$2:$AQ$3001,1)) | T5: =IF($AD5="","",Settings!$C$7) | U5: =IF($AD5="","",SUMIFS('Per Line'!$AB$2:$AB$3001,'Per Line'!$E$2:$E$3001,$B5,'Per Line'!$AP$2:$AP$3001,0,'Per Line'!$AQ$2:$AQ$3001,0)) | V5: =IF($AD5="","",U5*T5) | W5: =IF($AD5="","",Settings!$C$6) | X5: =IF($AD5="","",SUMIFS('Per Line'!$AB$2:$AB$3001,'Per Line'!$E$2:$E$3001,$B5,'Per Line'!$AP$2:$AP$3001,1,'Per Line'!$AQ$2:$AQ$3001,0)) | Y5: =IF($AD5="","",X5*W5) | Z5: =IF($AD5="","",Y5+V5) | AA5: =IF($AD5="","",AB5-Z5) | AB5: =IF($AD5="","",U5+X5+S5) | AC5: =IF($AD5="","",AB5-Z5-P5) | AD5: =IF(ROWS($AD$2:$AD5)<=MAX('Per Line'!$AO$2:$AO$3001),MATCH(ROWS($AD$2:$AD5),'Per Line'!$AO$2:$AO$3001,0),"") | AE5: =IF($AD5="","",P5-O5*AB5/100)
B6: =IF($AD6="","",INDEX('Per Line'!$E$2:$E$3001,$AD6)&"") | C6: =IF($AD6="","",INDEX('Per Line'!$A$2:$A$3001,$AD6)&"") | D6: =IF($AD6="","",INDEX('Per Line'!$C$2:$C$3001,$AD6)&"") | E6: =IF($AD6="","",INDEX('Per Line'!$B$2:$B$3001,$AD6)) | F6: =IF($AD6="","",INDEX('Per Line'!$D$2:$D$3001,$AD6)&"") | G6: =IF($AD6="","",INDEX('Per Line'!$G$2:$G$3001,$AD6)) | H6: =IF($AD6="","",INDEX('Per Line'!$J$2:$J$3001,$AD6)&"") | I6: =IF($AD6="","",INDEX('Per Line'!$H$2:$H$3001,$AD6)&"") | J6: =IF($AD6="","",INDEX('Per Line'!$F$2:$F$3001,$AD6)&"") | K6: =IF($AD6="","",INDEX('Per Line'!$K$2:$K$3001,$AD6)&"") | L6: =IF($AD6="","",INDEX('Per Line'!$L$2:$L$3001,$AD6)&"") | M6: =IF($AD6="","",INDEX('Per Line'!$M$2:$M$3001,$AD6)&"") | N6: =IF($AD6="","",INDEX('Per Line'!$AC$2:$AC$3001,$AD6)&"") | O6: =IF($AD6="","",INDEX('Per Line'!$P$2:$P$3001,$AD6)) | P6: =IF($AD6="","",IF(AND(ISNUMBER(Q6),Q6>0,AB6>Q6),O6*Q6/100+(AB6-Q6),O6*AB6/100)) | Q6: =IF($AD6="","",INDEX('Per Line'!$AG$2:$AG$3001,$AD6)) | R6: =IF($AD6="","",IF(AND(ISNUMBER(Q6),Q6>0),AB6>Q6,FALSE)) | S6: =IF($AD6="","",SUMIFS('Per Line'!$AB$2:$AB$3001,'Per Line'!$E$2:$E$3001,$B6,'Per Line'!$AQ$2:$AQ$3001,1)) | T6: =IF($AD6="","",Settings!$C$7) | U6: =IF($AD6="","",SUMIFS('Per Line'!$AB$2:$AB$3001,'Per Line'!$E$2:$E$3001,$B6,'Per Line'!$AP$2:$AP$3001,0,'Per Line'!$AQ$2:$AQ$3001,0)) | V6: =IF($AD6="","",U6*T6) | W6: =IF($AD6="","",Settings!$C$6) | X6: =IF($AD6="","",SUMIFS('Per Line'!$AB$2:$AB$3001,'Per Line'!$E$2:$E$3001,$B6,'Per Line'!$AP$2:$AP$3001,1,'Per Line'!$AQ$2:$AQ$3001,0)) | Y6: =IF($AD6="","",X6*W6) | Z6: =IF($AD6="","",Y6+V6) | AA6: =IF($AD6="","",AB6-Z6) | AB6: =IF($AD6="","",U6+X6+S6) | AC6: =IF($AD6="","",AB6-Z6-P6) | AD6: =IF(ROWS($AD$2:$AD6)<=MAX('Per Line'!$AO$2:$AO$3001),MATCH(ROWS($AD$2:$AD6),'Per Line'!$AO$2:$AO$3001,0),"") | AE6: =IF($AD6="","",P6-O6*AB6/100)
B7: =IF($AD7="","",INDEX('Per Line'!$E$2:$E$3001,$AD7)&"") | C7: =IF($AD7="","",INDEX('Per Line'!$A$2:$A$3001,$AD7)&"") | D7: =IF($AD7="","",INDEX('Per Line'!$C$2:$C$3001,$AD7)&"") | E7: =IF($AD7="","",INDEX('Per Line'!$B$2:$B$3001,$AD7)) | F7: =IF($AD7="","",INDEX('Per Line'!$D$2:$D$3001,$AD7)&"") | G7: =IF($AD7="","",INDEX('Per Line'!$G$2:$G$3001,$AD7)) | H7: =IF($AD7="","",INDEX('Per Line'!$J$2:$J$3001,$AD7)&"") | I7: =IF($AD7="","",INDEX('Per Line'!$H$2:$H$3001,$AD7)&"") | J7: =IF($AD7="","",INDEX('Per Line'!$F$2:$F$3001,$AD7)&"") | K7: =IF($AD7="","",INDEX('Per Line'!$K$2:$K$3001,$AD7)&"") | L7: =IF($AD7="","",INDEX('Per Line'!$L$2:$L$3001,$AD7)&"") | M7: =IF($AD7="","",INDEX('Per Line'!$M$2:$M$3001,$AD7)&"") | N7: =IF($AD7="","",INDEX('Per Line'!$AC$2:$AC$3001,$AD7)&"") | O7: =IF($AD7="","",INDEX('Per Line'!$P$2:$P$3001,$AD7)) | P7: =IF($AD7="","",IF(AND(ISNUMBER(Q7),Q7>0,AB7>Q7),O7*Q7/100+(AB7-Q7),O7*AB7/100)) | Q7: =IF($AD7="","",INDEX('Per Line'!$AG$2:$AG$3001,$AD7)) | R7: =IF($AD7="","",IF(AND(ISNUMBER(Q7),Q7>0),AB7>Q7,FALSE)) | S7: =IF($AD7="","",SUMIFS('Per Line'!$AB$2:$AB$3001,'Per Line'!$E$2:$E$3001,$B7,'Per Line'!$AQ$2:$AQ$3001,1)) | T7: =IF($AD7="","",Settings!$C$7) | U7: =IF($AD7="","",SUMIFS('Per Line'!$AB$2:$AB$3001,'Per Line'!$E$2:$E$3001,$B7,'Per Line'!$AP$2:$AP$3001,0,'Per Line'!$AQ$2:$AQ$3001,0)) | V7: =IF($AD7="","",U7*T7) | W7: =IF($AD7="","",Settings!$C$6) | X7: =IF($AD7="","",SUMIFS('Per Line'!$AB$2:$AB$3001,'Per Line'!$E$2:$E$3001,$B7,'Per Line'!$AP$2:$AP$3001,1,'Per Line'!$AQ$2:$AQ$3001,0)) | Y7: =IF($AD7="","",X7*W7) | Z7: =IF($AD7="","",Y7+V7) | AA7: =IF($AD7="","",AB7-Z7) | AB7: =IF($AD7="","",U7+X7+S7) | AC7: =IF($AD7="","",AB7-Z7-P7) | AD7: =IF(ROWS($AD$2:$AD7)<=MAX('Per Line'!$AO$2:$AO$3001),MATCH(ROWS($AD$2:$AD7),'Per Line'!$AO$2:$AO$3001,0),"") | AE7: =IF($AD7="","",P7-O7*AB7/100)
B8: =IF($AD8="","",INDEX('Per Line'!$E$2:$E$3001,$AD8)&"") | C8: =IF($AD8="","",INDEX('Per Line'!$A$2:$A$3001,$AD8)&"") | D8: =IF($AD8="","",INDEX('Per Line'!$C$2:$C$3001,$AD8)&"") | E8: =IF($AD8="","",INDEX('Per Line'!$B$2:$B$3001,$AD8)) | F8: =IF($AD8="","",INDEX('Per Line'!$D$2:$D$3001,$AD8)&"") | G8: =IF($AD8="","",INDEX('Per Line'!$G$2:$G$3001,$AD8)) | H8: =IF($AD8="","",INDEX('Per Line'!$J$2:$J$3001,$AD8)&"") | I8: =IF($AD8="","",INDEX('Per Line'!$H$2:$H$3001,$AD8)&"") | J8: =IF($AD8="","",INDEX('Per Line'!$F$2:$F$3001,$AD8)&"") | K8: =IF($AD8="","",INDEX('Per Line'!$K$2:$K$3001,$AD8)&"") | L8: =IF($AD8="","",INDEX('Per Line'!$L$2:$L$3001,$AD8)&"") | M8: =IF($AD8="","",INDEX('Per Line'!$M$2:$M$3001,$AD8)&"") | N8: =IF($AD8="","",INDEX('Per Line'!$AC$2:$AC$3001,$AD8)&"") | O8: =IF($AD8="","",INDEX('Per Line'!$P$2:$P$3001,$AD8)) | P8: =IF($AD8="","",IF(AND(ISNUMBER(Q8),Q8>0,AB8>Q8),O8*Q8/100+(AB8-Q8),O8*AB8/100)) | Q8: =IF($AD8="","",INDEX('Per Line'!$AG$2:$AG$3001,$AD8)) | R8: =IF($AD8="","",IF(AND(ISNUMBER(Q8),Q8>0),AB8>Q8,FALSE)) | S8: =IF($AD8="","",SUMIFS('Per Line'!$AB$2:$AB$3001,'Per Line'!$E$2:$E$3001,$B8,'Per Line'!$AQ$2:$AQ$3001,1)) | T8: =IF($AD8="","",Settings!$C$7) | U8: =IF($AD8="","",SUMIFS('Per Line'!$AB$2:$AB$3001,'Per Line'!$E$2:$E$3001,$B8,'Per Line'!$AP$2:$AP$3001,0,'Per Line'!$AQ$2:$AQ$3001,0)) | V8: =IF($AD8="","",U8*T8) | W8: =IF($AD8="","",Settings!$C$6) | X8: =IF($AD8="","",SUMIFS('Per Line'!$AB$2:$AB$3001,'Per Line'!$E$2:$E$3001,$B8,'Per Line'!$AP$2:$AP$3001,1,'Per Line'!$AQ$2:$AQ$3001,0)) | Y8: =IF($AD8="","",X8*W8) | Z8: =IF($AD8="","",Y8+V8) | AA8: =IF($AD8="","",AB8-Z8) | AB8: =IF($AD8="","",U8+X8+S8) | AC8: =IF($AD8="","",AB8-Z8-P8) | AD8: =IF(ROWS($AD$2:$AD8)<=MAX('Per Line'!$AO$2:$AO$3001),MATCH(ROWS($AD$2:$AD8),'Per Line'!$AO$2:$AO$3001,0),"") | AE8: =IF($AD8="","",P8-O8*AB8/100)
B9: =IF($AD9="","",INDEX('Per Line'!$E$2:$E$3001,$AD9)&"") | C9: =IF($AD9="","",INDEX('Per Line'!$A$2:$A$3001,$AD9)&"") | D9: =IF($AD9="","",INDEX('Per Line'!$C$2:$C$3001,$AD9)&"") | E9: =IF($AD9="","",INDEX('Per Line'!$B$2:$B$3001,$AD9)) | F9: =IF($AD9="","",INDEX('Per Line'!$D$2:$D$3001,$AD9)&"") | G9: =IF($AD9="","",INDEX('Per Line'!$G$2:$G$3001,$AD9)) | H9: =IF($AD9="","",INDEX('Per Line'!$J$2:$J$3001,$AD9)&"") | I9: =IF($AD9="","",INDEX('Per Line'!$H$2:$H$3001,$AD9)&"") | J9: =IF($AD9="","",INDEX('Per Line'!$F$2:$F$3001,$AD9)&"") | K9: =IF($AD9="","",INDEX('Per Line'!$K$2:$K$3001,$AD9)&"") | L9: =IF($AD9="","",INDEX('Per Line'!$L$2:$L$3001,$AD9)&"") | M9: =IF($AD9="","",INDEX('Per Line'!$M$2:$M$3001,$AD9)&"") | N9: =IF($AD9="","",INDEX('Per Line'!$AC$2:$AC$3001,$AD9)&"") | O9: =IF($AD9="","",INDEX('Per Line'!$P$2:$P$3001,$AD9)) | P9: =IF($AD9="","",IF(AND(ISNUMBER(Q9),Q9>0,AB9>Q9),O9*Q9/100+(AB9-Q9),O9*AB9/100)) | Q9: =IF($AD9="","",INDEX('Per Line'!$AG$2:$AG$3001,$AD9)) | R9: =IF($AD9="","",IF(AND(ISNUMBER(Q9),Q9>0),AB9>Q9,FALSE)) | S9: =IF($AD9="","",SUMIFS('Per Line'!$AB$2:$AB$3001,'Per Line'!$E$2:$E$3001,$B9,'Per Line'!$AQ$2:$AQ$3001,1)) | T9: =IF($AD9="","",Settings!$C$7) | U9: =IF($AD9="","",SUMIFS('Per Line'!$AB$2:$AB$3001,'Per Line'!$E$2:$E$3001,$B9,'Per Line'!$AP$2:$AP$3001,0,'Per Line'!$AQ$2:$AQ$3001,0)) | V9: =IF($AD9="","",U9*T9) | W9: =IF($AD9="","",Settings!$C$6) | X9: =IF($AD9="","",SUMIFS('Per Line'!$AB$2:$AB$3001,'Per Line'!$E$2:$E$3001,$B9,'Per Line'!$AP$2:$AP$3001,1,'Per Line'!$AQ$2:$AQ$3001,0)) | Y9: =IF($AD9="","",X9*W9) | Z9: =IF($AD9="","",Y9+V9) | AA9: =IF($AD9="","",AB9-Z9) | AB9: =IF($AD9="","",U9+X9+S9) | AC9: =IF($AD9="","",AB9-Z9-P9) | AD9: =IF(ROWS($AD$2:$AD9)<=MAX('Per Line'!$AO$2:$AO$3001),MATCH(ROWS($AD$2:$AD9),'Per Line'!$AO$2:$AO$3001,0),"") | AE9: =IF($AD9="","",P9-O9*AB9/100)
B10: =IF($AD10="","",INDEX('Per Line'!$E$2:$E$3001,$AD10)&"") | C10: =IF($AD10="","",INDEX('Per Line'!$A$2:$A$3001,$AD10)&"") | D10: =IF($AD10="","",INDEX('Per Line'!$C$2:$C$3001,$AD10)&"") | E10: =IF($AD10="","",INDEX('Per Line'!$B$2:$B$3001,$AD10)) | F10: =IF($AD10="","",INDEX('Per Line'!$D$2:$D$3001,$AD10)&"") | G10: =IF($AD10="","",INDEX('Per Line'!$G$2:$G$3001,$AD10)) | H10: =IF($AD10="","",INDEX('Per Line'!$J$2:$J$3001,$AD10)&"") | I10: =IF($AD10="","",INDEX('Per Line'!$H$2:$H$3001,$AD10)&"") | J10: =IF($AD10="","",INDEX('Per Line'!$F$2:$F$3001,$AD10)&"") | K10: =IF($AD10="","",INDEX('Per Line'!$K$2:$K$3001,$AD10)&"") | L10: =IF($AD10="","",INDEX('Per Line'!$L$2:$L$3001,$AD10)&"") | M10: =IF($AD10="","",INDEX('Per Line'!$M$2:$M$3001,$AD10)&"") | N10: =IF($AD10="","",INDEX('Per Line'!$AC$2:$AC$3001,$AD10)&"") | O10: =IF($AD10="","",INDEX('Per Line'!$P$2:$P$3001,$AD10)) | P10: =IF($AD10="","",IF(AND(ISNUMBER(Q10),Q10>0,AB10>Q10),O10*Q10/100+(AB10-Q10),O10*AB10/100)) | Q10: =IF($AD10="","",INDEX('Per Line'!$AG$2:$AG$3001,$AD10)) | R10: =IF($AD10="","",IF(AND(ISNUMBER(Q10),Q10>0),AB10>Q10,FALSE)) | S10: =IF($AD10="","",SUMIFS('Per Line'!$AB$2:$AB$3001,'Per Line'!$E$2:$E$3001,$B10,'Per Line'!$AQ$2:$AQ$3001,1)) | T10: =IF($AD10="","",Settings!$C$7) | U10: =IF($AD10="","",SUMIFS('Per Line'!$AB$2:$AB$3001,'Per Line'!$E$2:$E$3001,$B10,'Per Line'!$AP$2:$AP$3001,0,'Per Line'!$AQ$2:$AQ$3001,0)) | V10: =IF($AD10="","",U10*T10) | W10: =IF($AD10="","",Settings!$C$6) | X10: =IF($AD10="","",SUMIFS('Per Line'!$AB$2:$AB$3001,'Per Line'!$E$2:$E$3001,$B10,'Per Line'!$AP$2:$AP$3001,1,'Per Line'!$AQ$2:$AQ$3001,0)) | Y10: =IF($AD10="","",X10*W10) | Z10: =IF($AD10="","",Y10+V10) | AA10: =IF($AD10="","",AB10-Z10) | AB10: =IF($AD10="","",U10+X10+S10) | AC10: =IF($AD10="","",AB10-Z10-P10) | AD10: =IF(ROWS($AD$2:$AD10)<=MAX('Per Line'!$AO$2:$AO$3001),MATCH(ROWS($AD$2:$AD10),'Per Line'!$AO$2:$AO$3001,0),"") | AE10: =IF($AD10="","",P10-O10*AB10/100)
B11: =IF($AD11="","",INDEX('Per Line'!$E$2:$E$3001,$AD11)&"") | C11: =IF($AD11="","",INDEX('Per Line'!$A$2:$A$3001,$AD11)&"") | D11: =IF($AD11="","",INDEX('Per Line'!$C$2:$C$3001,$AD11)&"") | E11: =IF($AD11="","",INDEX('Per Line'!$B$2:$B$3001,$AD11)) | F11: =IF($AD11="","",INDEX('Per Line'!$D$2:$D$3001,$AD11)&"") | G11: =IF($AD11="","",INDEX('Per Line'!$G$2:$G$3001,$AD11)) | H11: =IF($AD11="","",INDEX('Per Line'!$J$2:$J$3001,$AD11)&"") | I11: =IF($AD11="","",INDEX('Per Line'!$H$2:$H$3001,$AD11)&"") | J11: =IF($AD11="","",INDEX('Per Line'!$F$2:$F$3001,$AD11)&"") | K11: =IF($AD11="","",INDEX('Per Line'!$K$2:$K$3001,$AD11)&"") | L11: =IF($AD11="","",INDEX('Per Line'!$L$2:$L$3001,$AD11)&"") | M11: =IF($AD11="","",INDEX('Per Line'!$M$2:$M$3001,$AD11)&"") | N11: =IF($AD11="","",INDEX('Per Line'!$AC$2:$AC$3001,$AD11)&"") | O11: =IF($AD11="","",INDEX('Per Line'!$P$2:$P$3001,$AD11)) | P11: =IF($AD11="","",IF(AND(ISNUMBER(Q11),Q11>0,AB11>Q11),O11*Q11/100+(AB11-Q11),O11*AB11/100)) | Q11: =IF($AD11="","",INDEX('Per Line'!$AG$2:$AG$3001,$AD11)) | R11: =IF($AD11="","",IF(AND(ISNUMBER(Q11),Q11>0),AB11>Q11,FALSE)) | S11: =IF($AD11="","",SUMIFS('Per Line'!$AB$2:$AB$3001,'Per Line'!$E$2:$E$3001,$B11,'Per Line'!$AQ$2:$AQ$3001,1)) | T11: =IF($AD11="","",Settings!$C$7) | U11: =IF($AD11="","",SUMIFS('Per Line'!$AB$2:$AB$3001,'Per Line'!$E$2:$E$3001,$B11,'Per Line'!$AP$2:$AP$3001,0,'Per Line'!$AQ$2:$AQ$3001,0)) | V11: =IF($AD11="","",U11*T11) | W11: =IF($AD11="","",Settings!$C$6) | X11: =IF($AD11="","",SUMIFS('Per Line'!$AB$2:$AB$3001,'Per Line'!$E$2:$E$3001,$B11,'Per Line'!$AP$2:$AP$3001,1,'Per Line'!$AQ$2:$AQ$3001,0)) | Y11: =IF($AD11="","",X11*W11) | Z11: =IF($AD11="","",Y11+V11) | AA11: =IF($AD11="","",AB11-Z11) | AB11: =IF($AD11="","",U11+X11+S11) | AC11: =IF($AD11="","",AB11-Z11-P11) | AD11: =IF(ROWS($AD$2:$AD11)<=MAX('Per Line'!$AO$2:$AO$3001),MATCH(ROWS($AD$2:$AD11),'Per Line'!$AO$2:$AO$3001,0),"") | AE11: =IF($AD11="","",P11-O11*AB11/100)
B12: =IF($AD12="","",INDEX('Per Line'!$E$2:$E$3001,$AD12)&"") | C12: =IF($AD12="","",INDEX('Per Line'!$A$2:$A$3001,$AD12)&"") | D12: =IF($AD12="","",INDEX('Per Line'!$C$2:$C$3001,$AD12)&"") | E12: =IF($AD12="","",INDEX('Per Line'!$B$2:$B$3001,$AD12)) | F12: =IF($AD12="","",INDEX('Per Line'!$D$2:$D$3001,$AD12)&"") | G12: =IF($AD12="","",INDEX('Per Line'!$G$2:$G$3001,$AD12)) | H12: =IF($AD12="","",INDEX('Per Line'!$J$2:$J$3001,$AD12)&"") | I12: =IF($AD12="","",INDEX('Per Line'!$H$2:$H$3001,$AD12)&"") | J12: =IF($AD12="","",INDEX('Per Line'!$F$2:$F$3001,$AD12)&"") | K12: =IF($AD12="","",INDEX('Per Line'!$K$2:$K$3001,$AD12)&"") | L12: =IF($AD12="","",INDEX('Per Line'!$L$2:$L$3001,$AD12)&"") | M12: =IF($AD12="","",INDEX('Per Line'!$M$2:$M$3001,$AD12)&"") | N12: =IF($AD12="","",INDEX('Per Line'!$AC$2:$AC$3001,$AD12)&"") | O12: =IF($AD12="","",INDEX('Per Line'!$P$2:$P$3001,$AD12)) | P12: =IF($AD12="","",IF(AND(ISNUMBER(Q12),Q12>0,AB12>Q12),O12*Q12/100+(AB12-Q12),O12*AB12/100)) | Q12: =IF($AD12="","",INDEX('Per Line'!$AG$2:$AG$3001,$AD12)) | R12: =IF($AD12="","",IF(AND(ISNUMBER(Q12),Q12>0),AB12>Q12,FALSE)) | S12: =IF($AD12="","",SUMIFS('Per Line'!$AB$2:$AB$3001,'Per Line'!$E$2:$E$3001,$B12,'Per Line'!$AQ$2:$AQ$3001,1)) | T12: =IF($AD12="","",Settings!$C$7) | U12: =IF($AD12="","",SUMIFS('Per Line'!$AB$2:$AB$3001,'Per Line'!$E$2:$E$3001,$B12,'Per Line'!$AP$2:$AP$3001,0,'Per Line'!$AQ$2:$AQ$3001,0)) | V12: =IF($AD12="","",U12*T12) | W12: =IF($AD12="","",Settings!$C$6) | X12: =IF($AD12="","",SUMIFS('Per Line'!$AB$2:$AB$3001,'Per Line'!$E$2:$E$3001,$B12,'Per Line'!$AP$2:$AP$3001,1,'Per Line'!$AQ$2:$AQ$3001,0)) | Y12: =IF($AD12="","",X12*W12) | Z12: =IF($AD12="","",Y12+V12) | AA12: =IF($AD12="","",AB12-Z12) | AB12: =IF($AD12="","",U12+X12+S12) | AC12: =IF($AD12="","",AB12-Z12-P12) | AD12: =IF(ROWS($AD$2:$AD12)<=MAX('Per Line'!$AO$2:$AO$3001),MATCH(ROWS($AD$2:$AD12),'Per Line'!$AO$2:$AO$3001,0),"") | AE12: =IF($AD12="","",P12-O12*AB12/100)
B13: =IF($AD13="","",INDEX('Per Line'!$E$2:$E$3001,$AD13)&"") | C13: =IF($AD13="","",INDEX('Per Line'!$A$2:$A$3001,$AD13)&"") | D13: =IF($AD13="","",INDEX('Per Line'!$C$2:$C$3001,$AD13)&"") | E13: =IF($AD13="","",INDEX('Per Line'!$B$2:$B$3001,$AD13)) | F13: =IF($AD13="","",INDEX('Per Line'!$D$2:$D$3001,$AD13)&"") | G13: =IF($AD13="","",INDEX('Per Line'!$G$2:$G$3001,$AD13)) | H13: =IF($AD13="","",INDEX('Per Line'!$J$2:$J$3001,$AD13)&"") | I13: =IF($AD13="","",INDEX('Per Line'!$H$2:$H$3001,$AD13)&"") | J13: =IF($AD13="","",INDEX('Per Line'!$F$2:$F$3001,$AD13)&"") | K13: =IF($AD13="","",INDEX('Per Line'!$K$2:$K$3001,$AD13)&"") | L13: =IF($AD13="","",INDEX('Per Line'!$L$2:$L$3001,$AD13)&"") | M13: =IF($AD13="","",INDEX('Per Line'!$M$2:$M$3001,$AD13)&"") | N13: =IF($AD13="","",INDEX('Per Line'!$AC$2:$AC$3001,$AD13)&"") | O13: =IF($AD13="","",INDEX('Per Line'!$P$2:$P$3001,$AD13)) | P13: =IF($AD13="","",IF(AND(ISNUMBER(Q13),Q13>0,AB13>Q13),O13*Q13/100+(AB13-Q13),O13*AB13/100)) | Q13: =IF($AD13="","",INDEX('Per Line'!$AG$2:$AG$3001,$AD13)) | R13: =IF($AD13="","",IF(AND(ISNUMBER(Q13),Q13>0),AB13>Q13,FALSE)) | S13: =IF($AD13="","",SUMIFS('Per Line'!$AB$2:$AB$3001,'Per Line'!$E$2:$E$3001,$B13,'Per Line'!$AQ$2:$AQ$3001,1)) | T13: =IF($AD13="","",Settings!$C$7) | U13: =IF($AD13="","",SUMIFS('Per Line'!$AB$2:$AB$3001,'Per Line'!$E$2:$E$3001,$B13,'Per Line'!$AP$2:$AP$3001,0,'Per Line'!$AQ$2:$AQ$3001,0)) | V13: =IF($AD13="","",U13*T13) | W13: =IF($AD13="","",Settings!$C$6) | X13: =IF($AD13="","",SUMIFS('Per Line'!$AB$2:$AB$3001,'Per Line'!$E$2:$E$3001,$B13,'Per Line'!$AP$2:$AP$3001,1,'Per Line'!$AQ$2:$AQ$3001,0)) | Y13: =IF($AD13="","",X13*W13) | Z13: =IF($AD13="","",Y13+V13) | AA13: =IF($AD13="","",AB13-Z13) | AB13: =IF($AD13="","",U13+X13+S13) | AC13: =IF($AD13="","",AB13-Z13-P13) | AD13: =IF(ROWS($AD$2:$AD13)<=MAX('Per Line'!$AO$2:$AO$3001),MATCH(ROWS($AD$2:$AD13),'Per Line'!$AO$2:$AO$3001,0),"") | AE13: =IF($AD13="","",P13-O13*AB13/100)
... B1001: =IF($AD1001="","",INDEX('Per Line'!$E$2:$E$3001,$AD1001)&"") | C1001: =IF($AD1001="","",INDEX('Per Line'!$A$2:$A$3001,$AD1001)&"") | D1001: =IF($AD1001="","",INDEX('Per Line'!$C$2:$C$3001,$AD1001)&"") | E1001: =IF($AD1001="","",INDEX('Per Line'!$B$2:$B$3001,$AD1001)) | F1001: =IF($AD1001="","",INDEX('Per Line'!$D$2:$D$3001,$AD1001)&"") | G1001: =IF($AD1001="","",INDEX('Per Line'!$G$2:$G$3001,$AD1001)) | H1001: =IF($AD1001="","",INDEX('Per Line'!$J$2:$J$3001,$AD1001)&"") | I1001: =IF($AD1001="","",INDEX('Per Line'!$H$2:$H$3001,$AD1001)&"") | J1001: =IF($AD1001="","",INDEX('Per Line'!$F$2:$F$3001,$AD1001)&"") | K1001: =IF($AD1001="","",INDEX('Per Line'!$K$2:$K$3001,$AD1001)&"") | L1001: =IF($AD1001="","",INDEX('Per Line'!$L$2:$L$3001,$AD1001)&"") | M1001: =IF($AD1001="","",INDEX('Per Line'!$M$2:$M$3001,$AD1001)&"") | N1001: =IF($AD1001="","",INDEX('Per Line'!$AC$2:$AC$3001,$AD1001)&"") | O1001: =IF($AD1001="","",INDEX('Per Line'!$P$2:$P$3001,$AD1001)) | P1001: =IF($AD1001="","",IF(AND(ISNUMBER(Q1001),Q1001>0,AB1001>Q1001),O1001*Q1001/100+(AB1001-Q1001),O1001*AB1001/100)) | Q1001: =IF($AD1001="","",INDEX('Per Line'!$AG$2:$AG$3001,$AD1001)) | R1001: =IF($AD1001="","",IF(AND(ISNUMBER(Q1001),Q1001>0),AB1001>Q1001,FALSE)) | S1001: =IF($AD1001="","",SUMIFS('Per Line'!$AB$2:$AB$3001,'Per Line'!$E$2:$E$3001,$B1001,'Per Line'!$AQ$2:$AQ$3001,1)) | T1001: =IF($AD1001="","",Settings!$C$7) | U1001: =IF($AD1001="","",SUMIFS('Per Line'!$AB$2:$AB$3001,'Per Line'!$E$2:$E$3001,$B1001,'Per Line'!$AP$2:$AP$3001,0,'Per Line'!$AQ$2:$AQ$3001,0)) | V1001: =IF($AD1001="","",U1001*T1001) | W1001: =IF($AD1001="","",Settings!$C$6) | X1001: =IF($AD1001="","",SUMIFS('Per Line'!$AB$2:$AB$3001,'Per Line'!$E$2:$E$3001,$B1001,'Per Line'!$AP$2:$AP$3001,1,'Per Line'!$AQ$2:$AQ$3001,0)) | Y1001: =IF($AD1001="","",X1001*W1001) | Z1001: =IF($AD1001="","",Y1001+V1001) | AA1001: =IF($AD1001="","",AB1001-Z1001) | AB1001: =IF($AD1001="","",U1001+X1001+S1001) | AC1001: =IF($AD1001="","",AB1001-Z1001-P1001) | AD1001: =IF(ROWS($AD$2:$AD1001)<=MAX('Per Line'!$AO$2:$AO$3001),MATCH(ROWS($AD$2:$AD1001),'Per Line'!$AO$2:$AO$3001,0),"") | AE1001: =IF($AD1001="","",P1001-O1001*AB1001/100)
